Workbook

Sheet 使用说明
A1: 需求与范围管理-20260918-V7 使用说明
A2: 管理需求入口、范围基线、追踪关系、WBS字典和范围变更。
A4: 项目 | B4: 能源行业合同全生命周期管理系统
A5: 适用对象 | B5: 产品经理、业务负责人、项目经理、测试负责人
A6: 更新频率 | B6: 需求评审后更新；变更评审和基线发布时同步维护。
A7: 版本日期 | B7: 2026-09-18
A8: 颜色约定 | B8: 浅蓝表头；黄色为人工输入区；白色/灰色通常为公式、说明或系统数据。
A10: 推荐使用流程
A11: 1 | B11: 登记需求并完成澄清
A12: 2 | B12: 确认优先级和验收标准
A13: 3 | B13: 纳入范围基线并建立追踪
A14: 4 | B14: 编制并评审94条P0接口规格，批准后再进入详细设计基线
A15: 5 | B15: 通过范围变更评审处理新增或删减
A18: 工作表导航
A19: 顺序 | B19: 工作表 | C19: 用途
A20: 1 | B20: 范围总览 | C20: 查看需求与范围关键指标和门禁。
A21: 2 | B21: 需求池 | C21: 登记、澄清、评审和排序需求。
A22: 3 | B22: 范围基线 | C22: 记录批准纳入和排除的范围。
A23: 4 | B23: 需求追踪矩阵 | C23: 连接需求、设计、开发、测试和验收证据。
A24: 5 | B24: WBS字典 | C24: 定义工作包边界、交付物和验收条件。
A25: 6 | B25: 范围变更评审 | C25: 评估范围变更影响及批准结论。
A26: 7 | B26: _数据接口 | C26: 供Python脚本和AI PMO读取，人工一般不直接修改。
A28: 接口管理补充说明
A29: 1 | B29: 接口清单：131条接口范围、优先级和责任人的权威录入点；范围变更须先审批。
A30: 2 | B30: 接口评审清单：维护跨系统联合评审结论及责任，按系统ID核对接口数量。
A31: 3 | B31: P0接口规格台账：保存待批准的规格基线；系统集成文件维护执行明细。
A33: 数据入口与联动规则
A34: 1 | B34: 接口范围和优先级在本文件唯一录入；04系统集成为执行快照。批准变更后按IF/SPEC ID核对并同步，不将静态复制视为实时联动。
A35: 范围总览 | B35: 顶部六项统计为公式联动：需求总数/P0/待确认来自需求池，范围项与包含、排除来自范围基线，追踪覆盖率来自追踪矩阵；灰色计算字段随台账自动更新

Sheet 范围总览
A1: 需求与范围管理总览
A2: 数据日期：2026-09-18。当前内容为需求基线评审前的初始草案，黄色字段需项目团队确认。
A4: 需求总数 | C4: P0需求 | E4: 待确认/待验证 | G4: 范围项 | I4: 包含/条件包含 | K4: 排除项 | M4: 追踪覆盖率
A5: =COUNTIF(需求池!$A$5:$A$100,"REQ-*") -> 24 | C5: =COUNTIF(需求池!$F$5:$F$100,"P0") -> 19 | E5: =COUNTIF(需求池!$I$5:$I$100,"待*") -> 24 | G5: =COUNTIF(范围基线!$A$5:$A$100,"SCP-*") -> 12 | I5: =COUNTIF(范围基线!$D$5:$D$100,"包含")+COUNTIF(范围基线!$D$5:$D$100,"条件包含") -> 8 | K5: =COUNTIF(范围基线!$D$5:$D$100,"不包含") -> 4 | M5: =IF(COUNTIF(需求追踪矩阵!$C$5:$C$100,"P0")=0,0,COUNTIFS(需求追踪矩阵!$C$5:$C$100,"P0",需求追踪矩阵!$N$5:$N$100,"完整")/COUNTIF(需求追踪矩阵!$C$5:$C$100,"P0")) -> 0
A8: 需求基线门禁
A9: 门禁项 | B9: 当前状态 | C9: 责任人 | D9: 最迟日期 | E9: 通过标准 | F9: 证据位置
A10: P0/P1/P2分级完成 | B10: 未通过 | C10: 产品经理 | D10: 46346 | E10: 每项需求完成优先级、范围决策和验收标准 | F10: 需求池
A11: 业务需求评审完成 | B11: 未通过 | C11: 产品经理 | D11: 46351 | E11: 业务负责人确认核心场景、规则和边界 | F11: 评审纪要
A12: 技术可行性评审完成 | B12: 未通过 | C12: 技术经理 | D12: 46351 | E12: 接口、数据、安全、性能和外部依赖可实现 | F12: 技术评审记录
A13: 需求追踪矩阵完整 | B13: 未通过 | C13: 项目经理 | D13: 46353 | E13: P0需求均关联WBS、设计、测试和验收证据 | F13: 需求追踪矩阵
A14: 范围基线批准 | B14: 未通过 | C14: 项目集经理 | D14: 46356 | E14: 包含、排除、假设和约束均得到批准 | F14: 范围基线批准记录
A15: 接口范围与责任矩阵确认 | B15: 未通过 | C15: 技术经理 | D15: 46311 | E15: 37个系统完成责任确认；P0接口范围、责任人和联调窗口获得批准 | F15: 接口评审清单
A17: 使用规则
A18: 1 | B18: 需求先进入需求池，完成来源、优先级、验收标准和范围决策后才能进入基线。
A19: 2 | B19: P0需求必须关联WBS、设计/接口、测试用例、UAT场景和验收证据。
A20: 3 | B20: 范围基线批准后，新增、删除或调整需求必须通过“范围变更评审”。
A21: 4 | B21: 黄色字段为人工确认项；灰色字段为计算或关联结果；红色表示门禁未通过。
A22: 5 | B22: 外部产品需求以POC结论为准，未通过验证的能力不得直接承诺进入P0。

Sheet 需求池
A1: 需求池
A2: 用于收集、分级和确认需求；“范围决策”为需求基线入口。
A4: 需求ID | B4: 业务域 | C4: 功能模块 | D4: 需求描述 | E4: 来源 | F4: 优先级 | G4: 需求类型 | H4: 责任人 | I4: 确认状态 | J4: 验收标准 | K4: 关联里程碑 | L4: 关联工作包 | M4: 范围决策
A5: REQ-001 | B5: 合同准备 | C5: 合同模板 | D5: 支持按合同类型维护标准模板和必填条款 | E5: 业务梳理初稿 | F5: P0 | G5: 业务 | H5: 产品经理 | I5: 待确认 | J5: 模板版本可追溯，必填条款缺失时不能提交 | K5: MS008 | L5: SCP-WP-001 | M5: 拟纳入
A6: REQ-002 | B6: 合同准备 | C6: 相对方管理 | D6: 统一维护合同相对方、资质、联系人和风险标识 | E6: 业务梳理初稿 | F6: P0 | G6: 业务 | H6: 产品经理 | I6: 待确认 | J6: 可查询有效资质并提示过期或黑名单状态 | K6: MS008 | L6: SCP-WP-002 | M6: 拟纳入
A7: REQ-003 | B7: 合同起草 | C7: 在线起草 | D7: 基于模板生成合同并支持条款编辑、版本比较 | E7: 业务梳理初稿 | F7: P0 | G7: 业务 | H7: 产品经理 | I7: 待确认 | J7: 保留每次版本及差异，可回退到历史版本 | K7: MS008 | L7: SCP-WP-003 | M7: 拟纳入
A8: REQ-004 | B8: 合同起草 | C8: 附件管理 | D8: 支持附件上传、分类、版本和在线预览 | E8: 业务梳理初稿 | F8: P0 | G8: 业务 | H8: 产品经理 | I8: 待确认 | J8: 附件版本、上传人和时间完整记录 | K8: MS008 | L8: SCP-WP-003 | M8: 拟纳入
A9: REQ-005 | B9: 合同审查 | C9: 规则审查 | D9: 按合同类型执行必备条款和风险条款检查 | E9: 业务梳理初稿 | F9: P0 | G9: 业务 | H9: 产品经理 | I9: 待确认 | J9: 命中规则时给出风险等级、依据和处理建议 | K9: MS008 | L9: SCP-WP-004 | M9: 拟纳入
A10: REQ-006 | B10: 合同审查 | C10: 会签审批 | D10: 支持业务、法务、财务等多角色并行或串行审批 | E10: 业务梳理初稿 | F10: P0 | G10: 业务 | H10: 产品经理 | I10: 待确认 | J10: 审批路径可配置，意见与操作全程留痕 | K10: MS008 | L10: SCP-WP-005 | M10: 拟纳入
A11: REQ-007 | B11: 合同签署 | C11: 电子签署 | D11: 对接CA和电子签章完成签署、验签和时间戳 | E11: POC范围 | F11: P0 | G11: 接口 | H11: 技术经理 | I11: 待验证 | J11: 签署结果可验真，失败可重试并记录原因 | K11: MS012 | L11: SCP-WP-006 | M11: POC后确认
A12: REQ-008 | B12: 合同签署 | C12: 纸质签署 | D12: 支持线下签署登记、扫描件上传和原件位置记录 | E12: 业务梳理初稿 | F12: P1 | G12: 业务 | H12: 产品经理 | I12: 待确认 | J12: 纸质签署状态与电子归档一致 | K12: MS008 | L12: SCP-WP-006 | M12: 拟纳入
A13: REQ-009 | B13: 合同履约 | C13: 履约计划 | D13: 按合同约定生成交付、收付款和关键义务计划 | E13: 业务梳理初稿 | F13: P0 | G13: 业务 | H13: 产品经理 | I13: 待确认 | J13: 计划包含责任人、日期、金额和完成证据 | K13: MS008 | L13: SCP-WP-007 | M13: 拟纳入
A14: REQ-010 | B14: 合同履约 | C14: 履约预警 | D14: 对到期、逾期、金额偏差和证照到期进行预警 | E14: 业务梳理初稿 | F14: P0 | G14: 业务 | H14: 产品经理 | I14: 待确认 | J14: 预警规则可配置并形成闭环记录 | K14: MS008 | L14: SCP-WP-007 | M14: 拟纳入
A15: REQ-011 | B15: 合同履约 | C15: 付款申请 | D15: 关联合同、履约节点和发票发起付款申请 | E15: 业务梳理初稿 | F15: P0 | G15: 业务 | H15: 产品经理 | I15: 待确认 | J15: 付款金额不超过合同可支付余额且依据完整 | K15: MS008 | L15: SCP-WP-008 | M15: 拟纳入
... A28: REQ-024 | B28: 非功能 | C28: 可用性容灾 | D28: 明确可用性、备份、恢复和容灾目标 | E28: 架构基线 | F28: P0 | G28: 非功能 | H28: 技术经理 | I28: 待量化 | J28: 明确SLA、RPO、RTO并完成演练验证 | K28: MS009 | L28: SCP-WP-015 | M28: 待量化

Sheet 范围基线
A1: 范围基线
A2: 明确项目包含、不包含和条件包含的边界。基线批准后，调整必须走范围变更评审。
A4: 范围ID | B4: 范围主题 | C4: 范围说明 | D4: 范围类型 | E4: 边界/前提条件 | F4: 负责人 | G4: 关联里程碑 | H4: 确认状态
A5: SCP-001 | B5: 合同全生命周期业务 | C5: 合同准备、起草、审查、审批、签署、履约、变更、终止和归档 | D5: 包含 | E5: P0需求基线批准 | F5: 产品经理 | G5: MS008 | H5: 待确认
A6: SCP-002 | B6: 外部产品集成 | C6: CA、电子文档和BI报表产品能力集成 | D6: 条件包含 | E6: POC通过并形成选型结论 | F6: 技术经理 | G6: MS017 | H6: 待验证
A7: SCP-003 | B7: 内部系统集成 | C7: 统一身份、组织人员、消息及内部主数据接口 | D7: 包含 | E7: 接口清单和责任边界确认 | F7: 技术经理 | G7: MS011 | H7: 待确认
A8: SCP-004 | B8: 外部系统集成 | C8: ERP、财务、OA、电子签章和外部主数据接口 | D8: 包含 | E8: 对方接口计划和测试环境落实 | F8: 技术经理 | G8: MS012 | H8: 待确认
A9: SCP-005 | B9: 数据迁移 | C9: 存量合同、附件、相对方和履约关键数据迁移 | D9: 包含 | E9: 范围、质量标准和切换方案确认 | F9: 产品经理 | G9: MS014 | H9: 待确认
A10: SCP-006 | B10: 安全与审计 | C10: 身份、权限、数据范围、日志和敏感数据保护 | D10: 包含 | E10: 安全方案与测试标准批准 | F10: 技术经理 | G10: MS009 | H10: 待确认
A11: SCP-007 | B11: 测试与验收 | C11: 单元、集成、系统、性能、安全和UAT | D11: 包含 | E11: 测试策略及验收样例批准 | F11: 高级测试人员、中级测试人员 | G11: MS014 | H11: 待确认
A12: SCP-008 | B12: 上线与移交 | C12: 生产部署、数据切换、培训、支持和运维移交 | D12: 包含 | E12: 上线门禁全部通过 | F12: 项目经理 | G12: MS016 | H12: 待确认
A13: SCP-009 | B13: 硬件采购 | C13: 业务终端、网络和基础硬件采购 | D13: 不包含 | E13: 由基础设施专项另行管理 | F13: 项目经理 | G13: MS006 | H13: 已排除
A14: SCP-010 | B14: 历史纸质档案数字化 | C14: 全部存量纸质合同扫描和人工著录 | D14: 不包含 | E14: 仅迁移已数字化且质量合格的数据 | F14: 产品经理 | G14: MS008 | H14: 已排除
A15: SCP-011 | B15: 第三方产品改造 | C15: CA、电子文档、BI产品内核定制开发 | D15: 不包含 | E15: 采用标准产品能力与公开接口 | F15: 技术经理 | G15: MS017 | H15: 已排除
A16: SCP-012 | B16: 上线后长期运营 | C16: 试运行结束后的常态化运营服务 | D16: 不包含 | E16: 另行签订运维服务与SLA | F16: 项目集经理 | G16: MS016 | H16: 已排除

Sheet 需求追踪矩阵
A1: 需求追踪矩阵
A2: P0需求应形成“需求—范围—工作包—设计—测试—UAT—验收证据”闭环。
A4: 需求ID | B4: 需求描述 | C4: 优先级 | D4: 范围决策 | E4: 范围ID | F4: 工作包ID | G4: 设计/接口文档 | H4: 测试用例ID | I4: UAT场景ID | J4: 验收证据 | K4: 责任人 | L4: 目标里程碑 | M4: 确认状态 | N4: 追踪完整性
A5: REQ-001 | B5: 支持按合同类型维护标准模板和必填条款 | C5: P0 | D5: 拟纳入 | E5: SCP-001 | F5: SCP-WP-001 | G5: 待补充 | H5: 待补充 | I5: 待补充 | J5: 待补充 | K5: 产品经理 | L5: MS008 | M5: 待确认 | N5: =IF($C5<>"P0","按需",IF(COUNTBLANK($E5:$J5)+COUNTIF($E5:$J5,"待补充")=0,"完整","不完整")) -> 不完整
A6: REQ-002 | B6: 统一维护合同相对方、资质、联系人和风险标识 | C6: P0 | D6: 拟纳入 | E6: SCP-001 | F6: SCP-WP-002 | G6: 待补充 | H6: 待补充 | I6: 待补充 | J6: 待补充 | K6: 产品经理 | L6: MS008 | M6: 待确认 | N6: =IF($C6<>"P0","按需",IF(COUNTBLANK($E6:$J6)+COUNTIF($E6:$J6,"待补充")=0,"完整","不完整")) -> 不完整
A7: REQ-003 | B7: 基于模板生成合同并支持条款编辑、版本比较 | C7: P0 | D7: 拟纳入 | E7: SCP-001 | F7: SCP-WP-003 | G7: 待补充 | H7: 待补充 | I7: 待补充 | J7: 待补充 | K7: 产品经理 | L7: MS008 | M7: 待确认 | N7: =IF($C7<>"P0","按需",IF(COUNTBLANK($E7:$J7)+COUNTIF($E7:$J7,"待补充")=0,"完整","不完整")) -> 不完整
A8: REQ-004 | B8: 支持附件上传、分类、版本和在线预览 | C8: P0 | D8: 拟纳入 | E8: SCP-002 | F8: SCP-WP-003 | G8: 待补充 | H8: 待补充 | I8: 待补充 | J8: 待补充 | K8: 产品经理 | L8: MS008 | M8: 待确认 | N8: =IF($C8<>"P0","按需",IF(COUNTBLANK($E8:$J8)+COUNTIF($E8:$J8,"待补充")=0,"完整","不完整")) -> 不完整
A9: REQ-005 | B9: 按合同类型执行必备条款和风险条款检查 | C9: P0 | D9: 拟纳入 | E9: SCP-002 | F9: SCP-WP-004 | G9: 待补充 | H9: 待补充 | I9: 待补充 | J9: 待补充 | K9: 产品经理 | L9: MS008 | M9: 待确认 | N9: =IF($C9<>"P0","按需",IF(COUNTBLANK($E9:$J9)+COUNTIF($E9:$J9,"待补充")=0,"完整","不完整")) -> 不完整
A10: REQ-006 | B10: 支持业务、法务、财务等多角色并行或串行审批 | C10: P0 | D10: 拟纳入 | E10: SCP-002 | F10: SCP-WP-005 | G10: 待补充 | H10: 待补充 | I10: 待补充 | J10: 待补充 | K10: 产品经理 | L10: MS008 | M10: 待确认 | N10: =IF($C10<>"P0","按需",IF(COUNTBLANK($E10:$J10)+COUNTIF($E10:$J10,"待补充")=0,"完整","不完整")) -> 不完整
A11: REQ-007 | B11: 对接CA和电子签章完成签署、验签和时间戳 | C11: P0 | D11: POC后确认 | E11: SCP-003 | F11: SCP-WP-006 | G11: 待补充 | H11: 待补充 | I11: 待补充 | J11: 待补充 | K11: 技术经理 | L11: MS012 | M11: 待验证 | N11: =IF($C11<>"P0","按需",IF(COUNTBLANK($E11:$J11)+COUNTIF($E11:$J11,"待补充")=0,"完整","不完整")) -> 不完整
A12: REQ-008 | B12: 支持线下签署登记、扫描件上传和原件位置记录 | C12: P1 | D12: 拟纳入 | E12: SCP-003 | F12: SCP-WP-006 | G12: 待补充 | H12: 待补充 | I12: 待补充 | J12: 待补充 | K12: 产品经理 | L12: MS008 | M12: 待确认 | N12: =IF($C12<>"P0","按需",IF(COUNTBLANK($E12:$J12)+COUNTIF($E12:$J12,"待补充")=0,"完整","不完整")) -> 按需
A13: REQ-009 | B13: 按合同约定生成交付、收付款和关键义务计划 | C13: P0 | D13: 拟纳入 | E13: SCP-003 | F13: SCP-WP-007 | G13: 待补充 | H13: 待补充 | I13: 待补充 | J13: 待补充 | K13: 产品经理 | L13: MS008 | M13: 待确认 | N13: =IF($C13<>"P0","按需",IF(COUNTBLANK($E13:$J13)+COUNTIF($E13:$J13,"待补充")=0,"完整","不完整")) -> 不完整
A14: REQ-010 | B14: 对到期、逾期、金额偏差和证照到期进行预警 | C14: P0 | D14: 拟纳入 | E14: SCP-004 | F14: SCP-WP-007 | G14: 待补充 | H14: 待补充 | I14: 待补充 | J14: 待补充 | K14: 产品经理 | L14: MS008 | M14: 待确认 | N14: =IF($C14<>"P0","按需",IF(COUNTBLANK($E14:$J14)+COUNTIF($E14:$J14,"待补充")=0,"完整","不完整")) -> 不完整
A15: REQ-011 | B15: 关联合同、履约节点和发票发起付款申请 | C15: P0 | D15: 拟纳入 | E15: SCP-004 | F15: SCP-WP-008 | G15: 待补充 | H15: 待补充 | I15: 待补充 | J15: 待补充 | K15: 产品经理 | L15: MS008 | M15: 待确认 | N15: =IF($C15<>"P0","按需",IF(COUNTBLANK($E15:$J15)+COUNTIF($E15:$J15,"待补充")=0,"完整","不完整")) -> 不完整
A16: REQ-012 | B16: 登记应收计划、实收结果及逾期原因 | C16: P1 | D16: 拟纳入 | E16: SCP-004 | F16: SCP-WP-008 | G16: 待补充 | H16: 待补充 | I16: 待补充 | J16: 待补充 | K16: 产品经理 | L16: MS008 | M16: 待确认 | N16: =IF($C16<>"P0","按需",IF(COUNTBLANK($E16:$J16)+COUNTIF($E16:$J16,"待补充")=0,"完整","不完整")) -> 按需
... A28: REQ-024 | B28: 明确可用性、备份、恢复和容灾目标 | C28: P0 | D28: 待量化 | E28: SCP-008 | F28: SCP-WP-015 | G28: 待补充 | H28: 待补充 | I28: 待补充 | J28: 待补充 | K28: 技术经理 | L28: MS009 | M28: 待量化 | N28: =IF($C28<>"P0","按需",IF(COUNTBLANK($E28:$J28)+COUNTIF($E28:$J28,"待补充")=0,"完整","不完整")) -> 不完整

Sheet WBS字典
A1: 范围WBS字典
A2: 定义范围工作包、交付物和完成标准；计划日期和资源安排在计划与进度管理模块维护。
A4: 工作包ID | B4: WBS编码 | C4: 工作包名称 | D4: 工作内容 | E4: 主要交付物 | F4: 负责人 | G4: 关联需求 | H4: 目标里程碑 | I4: 完成标准
A5: SCP-WP-001 | B5: 1.1 | C5: 模板与条款库 | D5: 完成合同类型、模板、条款和必填规则配置 | E5: 需求说明、原型、配置清单 | F5: 产品经理 | G5: REQ-001 | H5: MS010 | I5: 验收样例通过
A6: SCP-WP-002 | B6: 1.2 | C6: 相对方管理 | D6: 建设相对方主档、资质、联系人和风险标识 | E6: 需求说明、数据模型、接口说明 | F6: 产品经理 | G6: REQ-002 | H6: MS010 | I6: 主数据验证通过
A7: SCP-WP-003 | B7: 2.1 | C7: 合同起草与附件 | D7: 实现在线起草、版本比较和附件管理 | E7: 可测试功能、单元测试证据 | F7: 高级开发人员 | G7: REQ-003,REQ-004 | H7: MS010 | I7: P0功能及单测通过
A8: SCP-WP-004 | B8: 2.2 | C8: 合同规则审查 | D8: 建设必备条款和风险条款检查能力 | E8: 规则清单、审查报告样例 | F8: 高级开发人员 | G8: REQ-005 | H8: MS010 | I8: 规则命中结果准确
A9: SCP-WP-005 | B9: 2.3 | C9: 会签审批 | D9: 实现多角色审批路径、意见和留痕 | E9: 流程配置、审批记录 | F9: 高级开发人员 | G9: REQ-006 | H9: MS010 | I9: 端到端审批通过
A10: SCP-WP-006 | B10: 3.1 | C10: 合同签署 | D10: 集成电子签署并支持纸质签署登记 | E10: 接口、签署回执、验签证据 | F10: 技术经理 | G10: REQ-007,REQ-008 | H10: MS012 | I10: 签署及异常场景通过
A11: SCP-WP-007 | B11: 4.1 | C11: 履约计划与预警 | D11: 实现履约计划、责任分配和预警闭环 | E11: 履约计划、预警记录 | F11: 产品经理 | G11: REQ-009,REQ-010 | H11: MS010 | I11: 核心履约场景通过
A12: SCP-WP-008 | B12: 4.2 | C12: 收付款管理 | D12: 实现付款申请、收款跟踪和差异核对 | E12: 交易记录、对账报告 | F12: 产品经理 | G12: REQ-011,REQ-012 | H12: MS012 | I12: 财务对账通过
A13: SCP-WP-009 | B13: 5.1 | C13: 合同变更 | D13: 实现变更申请、评审、补充协议和基线更新 | E13: 变更单、批准记录、版本 | F13: 项目经理 | G13: REQ-013,REQ-014 | H13: MS010 | I13: 未批准变更无法生效
A14: SCP-WP-010 | B14: 5.2 | C14: 终止与关闭 | D14: 实现终止、解除、结算和关闭校验 | E14: 关闭清单、终止记录 | F14: 产品经理 | G14: REQ-015 | H14: MS010 | I14: 未结事项得到处置
A15: SCP-WP-011 | B15: 6.1 | C15: 电子归档 | D15: 形成完整归档包及检索授权能力 | E15: 归档包、检索验证记录 | F15: 高级开发人员 | G15: REQ-016 | H15: MS012 | I15: 完整性和权限验证通过
... A19: SCP-WP-015 | B19: 8.3 | C19: 非功能能力 | D19: 实现性能、容量、可用性、备份和容灾要求 | E19: 非功能方案、测试与演练报告 | F19: 技术经理 | G19: REQ-023,REQ-024 | H19: MS013 | I19: 量化指标验证通过

Sheet 范围变更评审
A1: 范围变更评审
A2: 需求基线批准后使用。填写变更内容和影响分析，由变更控制委员会决定是否更新基线。
A4: 变更ID | B4: 提出日期 | C4: 提出人 | D4: 变更类型 | E4: 关联需求/范围 | F4: 变更说明 | G4: 业务价值 | H4: 范围影响 | I4: 进度影响(天) | J4: 成本影响(元) | K4: 质量/风险影响 | L4: 评估负责人 | M4: 决策 | N4: 决策人 | O4: 决策日期 | P4: 基线更新状态

Sheet _数据接口
A1: 字段 | B1: 值
A2: Project_ID | B2: ECM-2026
A3: 项目名称 | B3: 能源行业合同全生命周期管理系统
A4: 模块编码 | B4: 03
A5: 数据日期 | B5: 46282
A6: 数据模式 | B6: 需求与范围基线草案
A7: 需求总数 | B7: =范围总览!A5 -> 24
A8: P0需求数 | B8: =范围总览!C5 -> 19
A9: 范围项数 | B9: =范围总览!G5 -> 12
A10: 工作包数 | B10: =COUNTIF(WBS字典!$A$5:$A$100,"SCP-WP-*") -> 15
A11: 需求基线里程碑 | B11: MS008
A12: 基线计划完成 | B12: 2026-11-30
A13: 中央数据库 | B13: ../90_项目数据中心/ai_pmo.db

Sheet 接口清单
A1: 外部系统接口清单
A2: 来源：02合同系统2.0集成接口.xlsx。131条已有明细接口分级建议：P0 94条、P1 27条、P2 10条、暂不建设 0条；结论需联合评审批准。
A4: 清单ID | B4: 集成系统 | C4: 接口名称 | D4: 接口描述 | E4: 接口方向 | F4: 范围决策 | G4: 优先级 | H4: 接口责任人 | I4: 规格状态 | J4: 测试状态 | K4: 备注
A5: IF-001 | B5: 大集中ERP | C5: CI11-合同信息传输接口 | D5: 合同签订完成后，将合同签订相关信息（含合同标的明细）推送到ERP系统，在ERP系统进行保存，ERP系统维护采购订单时，引用或校验合同信息（当需要由合同信息建立采购订单是引用合同信息，当手动维护采购订单时，校验合同信息） [20231018ADD]对项目服务采购的合同信息，在ERP接受后，根据WBS的组织信息，自动匹配上对应的采购组织信息，并完成采购订单的自动创建。 已补充合同相对人银行信息相关字段 | E5: 合同系统推送大集中erp | F5: 拟纳入一期 | G5: P0 | H5: 技术经理 | I5: 规格台账已建立 | J5: 未开始 | K5: AI评审建议：直接支撑合同、采购、预算、履约、结算、收付款或主数据核心链路；需业务、技术及外部系统责任人确认。
A6: IF-002 | B6: 大集中ERP | C6: CI12-采购订单创建信息同步接口 | D6: ERP系统依据采购合同创建采购订单后，将采购订单相关信息传输给合同系统，合同管理系统保存合同与采购订单的关系和采购订单状态值，传采购订单号（先签框架协议合同，依据框架协议创建采购订单，采购订单记录框架协议号，传输合同系统，建立框架协议子合同，返回ERP更新采购订单中的合同号） | E6: 大集中erp推送合同系统 | F6: 拟纳入一期 | G6: P0 | H6: 技术经理 | I6: 规格台账已建立 | J6: 未开始 | K6: AI评审建议：直接支撑合同、采购、预算、履约、结算、收付款或主数据核心链路；需业务、技术及外部系统责任人确认。
A7: IF-003 | B7: 大集中ERP | C7: CI13-采购申请传输合同系统接口 | D7: 项目服务采购申请审批完成后，通过接口传输到合同系统，作为合同签约的依据，采购申请上传后采购申请状态被锁定，不能删除，合同系统成功接收采购申请后，回传信息，更新采购申请状态为已传输 | E7: 大集中erp推送合同系统 | F7: 拟纳入一期 | G7: P0 | H7: 技术经理 | I7: 规格台账已建立 | J7: 未开始 | K7: AI评审建议：直接支撑合同、采购、预算、履约、结算、收付款或主数据核心链路；需业务、技术及外部系统责任人确认。
A8: IF-004 | B8: 大集中ERP | C8: CI14-采购申请退回接口 | D8: 采购申请上传后，如需要进行修改使用采购申请退回接口，由合同系统退回采购申请到ERP系统，采购申请退回后，更新采购申请状态为：“已退回”ERP系统中采购申请解锁，并可以在修改后重新上传 | E8: 合同系统推送大集中erp | F8: 拟纳入一期 | G8: P0 | H8: 技术经理 | I8: 规格台账已建立 | J8: 未开始 | K8: AI评审建议：直接支撑合同、采购、预算、履约、结算、收付款或主数据核心链路；需业务、技术及外部系统责任人确认。
A9: IF-005 | B9: 大集中ERP | C9: CI15-服务确认传输合同系统接口 | D9: 项目服务进度确认后，服务进度信息从ERP系统推送到合同系统，合同管理系统记录服务进度信息作为履约申请单的依据 | E9: 大集中erp推送合同系统 | F9: 拟纳入一期 | G9: P0 | H9: 技术经理 | I9: 规格台账已建立 | J9: 未开始 | K9: AI评审建议：直接支撑合同、采购、预算、履约、结算、收付款或主数据核心链路；需业务、技术及外部系统责任人确认。
A10: IF-006 | B10: 大集中ERP | C10: CI16-采购订单状态查询接口 | D10: 当采购订单进行变更时，合同系统通过此接口查询采购订单信息并进行校验，如果存在未结采购订单不能进行合同标的明细变更 | E10: 大集中erp推送合同系统 | F10: 拟纳入一期 | G10: P0 | H10: 技术经理 | I10: 规格台账已建立 | J10: 未开始 | K10: AI评审建议：直接支撑合同、采购、预算、履约、结算、收付款或主数据核心链路；需业务、技术及外部系统责任人确认。
A11: IF-007 | B11: 大集中ERP | C11: CI17-合同系统变更审批结果推送ERP系统（项目预算释放） | D11: 带wbs号的变更申请，在合同系统变更审批完成后，通过此接口将信息传递到ERP系统，ERP系统接到接口信息进行采购订单变更 | E11: 合同系统推送大集中erp | F11: 拟纳入一期 | G11: P0 | H11: 技术经理 | I11: 规格台账已建立 | J11: 未开始 | K11: AI评审建议：直接支撑合同、采购、预算、履约、结算、收付款或主数据核心链路；需业务、技术及外部系统责任人确认。
A12: IF-008 | B12: 大集中ERP | C12: CI18-采购订单退回ERP | D12: 采购订单信息通过CI12接口传输合同系统后，如子合同审核未批准，删除子合同时传输信息到ERP系统 | E12: 合同系统推送大集中erp | F12: 拟纳入一期 | G12: P0 | H12: 技术经理 | I12: 规格台账已建立 | J12: 未开始 | K12: AI评审建议：直接支撑合同、采购、预算、履约、结算、收付款或主数据核心链路；需业务、技术及外部系统责任人确认。
A13: IF-009 | B13: 大集中ERP | C13: CI19-合同变更申请信息推送ERP系统（项目预算占用） | D13: 此接口为同步接口，带wbs号的变更申请，在合同系统提交变更审批时，调用ERP系统预算管控查询，如果变更申请不超过预算金额则可以提交，如果变更申请超过预算金额返回错误信息，错误信息包含超预算的行项目信息和金额，同时将变更信息更新到PR以占用预算 | E13: 合同系统推送大集中erp | F13: 拟纳入一期 | G13: P0 | H13: 技术经理 | I13: 规格台账已建立 | J13: 未开始 | K13: AI评审建议：直接支撑合同、采购、预算、履约、结算、收付款或主数据核心链路；需业务、技术及外部系统责任人确认。
A14: IF-010 | B14: 大集中ERP | C14: CI22-合同解除接口 | D14: 合同解除状态推送大集中erp | E14: 合同系统推送大集中erp | F14: 拟纳入一期 | G14: P0 | H14: 技术经理 | I14: 规格台账已建立 | J14: 未开始 | K14: AI评审建议：直接支撑合同、采购、预算、履约、结算、收付款或主数据核心链路；需业务、技术及外部系统责任人确认。
A15: IF-011 | B15: 大集中ERP | C15: CI23-合同终止接口 | D15: 合同终止后结果发送到ERP系统，ERP系统不可以引用带有终止标记的合同 | E15: 合同系统推送大集中erp | F15: 拟纳入一期 | G15: P0 | H15: 技术经理 | I15: 规格台账已建立 | J15: 未开始 | K15: AI评审建议：直接支撑合同、采购、预算、履约、结算、收付款或主数据核心链路；需业务、技术及外部系统责任人确认。
... A135: IF-131 | B135: MDG | C135: CI99-01-MDG员工模型 | D135: MDG综合编码 | E135: MDG推送合同系统 | F135: 拟纳入一期 | G135: P0 | H135: 技术经理 | I135: 规格台账已建立 | J135: 未开始 | K135: AI评审建议：组织、人员、往来单位、物料、服务、项目及财务主数据是核心前置；需业务、技术及外部系统责任人确认。

Sheet 接口评审清单
A1: 接口联合评审与责任矩阵
A2: 覆盖37个集成系统。黄色字段需由合同系统、外部系统和业务共同确认；评审结论未批准前不得视为正式范围基线。
A4: 系统ID | B4: 集成系统 | C4: 明细状态 | D4: 接口总数 | E4: P0 | F4: P1 | G4: P2 | H4: 建议范围 | I4: 合同系统负责人 | J4: 外部系统负责人 | K4: 业务确认人 | L4: 最迟确认日期 | M4: 评审状态 | N4: 评审结论 | O4: 未决问题 | P4: 证据/备注
A5: SYS-001 | B5: 大集中ERP | C5: 已有接口明细 | D5: 36 | E5: 23 | F5: 9 | G5: 4 | H5: 一期+后续批次 | I5: 技术经理 | J5: 待外部系统指定 | K5: 财务/采购业务负责人 | L5: 46304 | M5: 待评审 | O5: 确认P0边界、责任人、规格和联调窗口 | P5: 来源：02合同系统2.0集成接口.xlsx；联合评审后形成批准结论
A6: SYS-002 | B6: 昆仑ERP | C6: 已有接口明细 | D6: 36 | E6: 23 | F6: 9 | G6: 4 | H6: 一期+后续批次 | I6: 技术经理 | J6: 待外部系统指定 | K6: 财务/采购业务负责人 | L6: 46304 | M6: 待评审 | O6: 确认P0边界、责任人、规格和联调窗口 | P6: 来源：02合同系统2.0集成接口.xlsx；联合评审后形成批准结论
A7: SYS-003 | B7: 云梦泽 | C7: 已有接口明细 | D7: 17 | E7: 13 | F7: 4 | G7: 0 | H7: 一期+后续批次 | I7: 技术经理 | J7: 待外部系统指定 | K7: 采购业务负责人 | L7: 46304 | M7: 待评审 | O7: 确认P0边界、责任人、规格和联调窗口 | P7: 来源：02合同系统2.0集成接口.xlsx；联合评审后形成批准结论
A8: SYS-004 | B8: 税务系统 | C8: 接口明细待补充 | D8: 0 | E8: 0 | F8: 0 | G8: 0 | H8: 待评审 | I8: 技术经理 | J8: 待外部系统指定 | K8: 财务/采购业务负责人 | L8: 46311 | M8: 待评审 | O8: 补充接口清单、业务场景、方向和责任人 | P8: 来源：02合同系统2.0集成接口.xlsx；联合评审后形成批准结论
A9: SYS-005 | B9: 档案系统 | C9: 已有接口明细 | D9: 7 | E9: 7 | F9: 0 | G9: 0 | H9: 一期+后续批次 | I9: 技术经理 | J9: 待外部系统指定 | K9: 档案业务负责人 | L9: 46304 | M9: 待评审 | O9: 确认P0边界、责任人、规格和联调窗口 | P9: 来源：02合同系统2.0集成接口.xlsx；联合评审后形成批准结论
A10: SYS-006 | B10: 财务共享 | C10: 已有接口明细 | D10: 10 | E10: 9 | F10: 0 | G10: 1 | H10: 一期+后续批次 | I10: 技术经理 | J10: 待外部系统指定 | K10: 财务/采购业务负责人 | L10: 46304 | M10: 待评审 | O10: 确认P0边界、责任人、规格和联调窗口 | P10: 来源：02合同系统2.0集成接口.xlsx；联合评审后形成批准结论
A11: SYS-007 | B11: 国资监管平台 | C11: 接口明细待补充 | D11: 0 | E11: 0 | F11: 0 | G11: 0 | H11: 待评审 | I11: 技术经理 | J11: 待外部系统指定 | K11: 对应业务系统负责人 | L11: 46311 | M11: 待评审 | O11: 补充接口清单、业务场景、方向和责任人 | P11: 来源：02合同系统2.0集成接口.xlsx；联合评审后形成批准结论
A12: SYS-008 | B12: IAM | C12: 已有接口明细 | D12: 1 | E12: 1 | F12: 0 | G12: 0 | H12: 一期+后续批次 | I12: 技术经理 | J12: 待外部系统指定 | K12: 数据/信息化负责人 | L12: 46304 | M12: 待评审 | O12: 确认P0边界、责任人、规格和联调窗口 | P12: 来源：02合同系统2.0集成接口.xlsx；联合评审后形成批准结论
A13: SYS-009 | B13: 工程建设EPM | C13: 已有接口明细 | D13: 4 | E13: 2 | F13: 1 | G13: 1 | H13: 一期+后续批次 | I13: 技术经理 | J13: 待外部系统指定 | K13: 工程业务负责人 | L13: 46304 | M13: 待评审 | O13: 确认P0边界、责任人、规格和联调窗口 | P13: 来源：02合同系统2.0集成接口.xlsx；联合评审后形成批准结论
A14: SYS-010 | B14: 采油与地面工程运行管理系统（A5) | C14: 接口明细待补充 | D14: 0 | E14: 0 | F14: 0 | G14: 0 | H14: 待评审 | I14: 技术经理 | J14: 待外部系统指定 | K14: 工程业务负责人 | L14: 46311 | M14: 待评审 | O14: 补充接口清单、业务场景、方向和责任人 | P14: 来源：02合同系统2.0集成接口.xlsx；联合评审后形成批准结论
A15: SYS-011 | B15: 客户关系CRM | C15: 接口明细待补充 | D15: 0 | E15: 0 | F15: 0 | G15: 0 | H15: 待评审 | I15: 技术经理 | J15: 待外部系统指定 | K15: 对应业务系统负责人 | L15: 46311 | M15: 待评审 | O15: 补充接口清单、业务场景、方向和责任人 | P15: 来源：02合同系统2.0集成接口.xlsx；联合评审后形成批准结论
A16: SYS-012 | B16: 资金管理(中间库) | C16: 接口明细待补充 | D16: 0 | E16: 0 | F16: 0 | G16: 0 | H16: 待评审 | I16: 技术经理 | J16: 待外部系统指定 | K16: 财务/采购业务负责人 | L16: 46311 | M16: 待评审 | O16: 补充接口清单、业务场景、方向和责任人 | P16: 来源：02合同系统2.0集成接口.xlsx；联合评审后形成批准结论
... A41: SYS-037 | B41: 加管3.0 | C41: 接口明细待补充 | D41: 0 | E41: 0 | F41: 0 | G41: 0 | H41: 待评审 | I41: 技术经理 | J41: 待外部系统指定 | K41: 对应业务系统负责人 | L41: 46311 | M41: 待评审 | O41: 补充接口清单、业务场景、方向和责任人 | P41: 来源：02合同系统2.0集成接口.xlsx；联合评审后形成批准结论

Sheet P0接口规格台账
A1: P0接口规格准备台账
A2: 共94条P0接口。参考资料仅提供接口名称、描述和方向；黄色字段必须由相关责任人补充并通过评审，禁止将“待确认”直接作为设计基线。
A4: 规格ID | B4: 清单ID | C4: 集成系统 | D4: 接口名称 | E4: 业务描述 | F4: 优先级 | G4: 接口方向 | H4: 源系统 | I4: 目标系统 | J4: 交互模式 | K4: 调用频率 | L4: 关键字段 | M4: 鉴权方式 | N4: 幂等键 | O4: 超时/重试 | P4: 异常补偿 | Q4: 对账规则 | R4: 数据敏感级别 | S4: 接口责任人 | T4: 计划评审日期 | U4: 规格状态 | V4: 备注
A5: SPEC-001 | B5: IF-001 | C5: 大集中ERP | D5: CI11-合同信息传输接口 | E5: 合同签订完成后，将合同签订相关信息（含合同标的明细）推送到ERP系统，在ERP系统进行保存，ERP系统维护采购订单时，引用或校验合同信息（当需要由合同信息建立采购订单是引用合同信息，当手动维护采购订单时，校验合同信息） [20231018ADD]对项目服务采购的合同信息，在ERP接受后，根据WBS的组织信息，自动匹配上对应的采购组织信息，并完成采购订单的自动创建。 已补充合同相对人银行信息相关字段 | F5: P0 | G5: 合同系统推送大集中erp | H5: 合同系统 | I5: 大集中ERP | J5: 待确认 | K5: 待业务确认 | L5: 待补充字段清单 | M5: 待确认 | N5: 待确认 | O5: 待确认 | P5: 待确认 | Q5: 待确认 | R5: 重要业务数据 | S5: 技术经理 | T5: 46367 | U5: 待编制 | V5: 由合同系统、外部系统、业务和测试联合评审
A6: SPEC-002 | B6: IF-002 | C6: 大集中ERP | D6: CI12-采购订单创建信息同步接口 | E6: ERP系统依据采购合同创建采购订单后，将采购订单相关信息传输给合同系统，合同管理系统保存合同与采购订单的关系和采购订单状态值，传采购订单号（先签框架协议合同，依据框架协议创建采购订单，采购订单记录框架协议号，传输合同系统，建立框架协议子合同，返回ERP更新采购订单中的合同号） | F6: P0 | G6: 大集中erp推送合同系统 | H6: 大集中ERP | I6: 合同系统 | J6: 待确认 | K6: 待业务确认 | L6: 待补充字段清单 | M6: 待确认 | N6: 待确认 | O6: 待确认 | P6: 待确认 | Q6: 待确认 | R6: 重要业务数据 | S6: 技术经理 | T6: 46367 | U6: 待编制 | V6: 由合同系统、外部系统、业务和测试联合评审
A7: SPEC-003 | B7: IF-003 | C7: 大集中ERP | D7: CI13-采购申请传输合同系统接口 | E7: 项目服务采购申请审批完成后，通过接口传输到合同系统，作为合同签约的依据，采购申请上传后采购申请状态被锁定，不能删除，合同系统成功接收采购申请后，回传信息，更新采购申请状态为已传输 | F7: P0 | G7: 大集中erp推送合同系统 | H7: 大集中ERP | I7: 合同系统 | J7: 待确认 | K7: 待业务确认 | L7: 待补充字段清单 | M7: 待确认 | N7: 待确认 | O7: 待确认 | P7: 待确认 | Q7: 待确认 | R7: 重要业务数据 | S7: 技术经理 | T7: 46367 | U7: 待编制 | V7: 由合同系统、外部系统、业务和测试联合评审
A8: SPEC-004 | B8: IF-004 | C8: 大集中ERP | D8: CI14-采购申请退回接口 | E8: 采购申请上传后，如需要进行修改使用采购申请退回接口，由合同系统退回采购申请到ERP系统，采购申请退回后，更新采购申请状态为：“已退回”ERP系统中采购申请解锁，并可以在修改后重新上传 | F8: P0 | G8: 合同系统推送大集中erp | H8: 合同系统 | I8: 大集中ERP | J8: 待确认 | K8: 待业务确认 | L8: 待补充字段清单 | M8: 待确认 | N8: 待确认 | O8: 待确认 | P8: 待确认 | Q8: 待确认 | R8: 重要业务数据 | S8: 技术经理 | T8: 46367 | U8: 待编制 | V8: 由合同系统、外部系统、业务和测试联合评审
A9: SPEC-005 | B9: IF-005 | C9: 大集中ERP | D9: CI15-服务确认传输合同系统接口 | E9: 项目服务进度确认后，服务进度信息从ERP系统推送到合同系统，合同管理系统记录服务进度信息作为履约申请单的依据 | F9: P0 | G9: 大集中erp推送合同系统 | H9: 大集中ERP | I9: 合同系统 | J9: 待确认 | K9: 待业务确认 | L9: 待补充字段清单 | M9: 待确认 | N9: 待确认 | O9: 待确认 | P9: 待确认 | Q9: 待确认 | R9: 重要业务数据 | S9: 技术经理 | T9: 46367 | U9: 待编制 | V9: 由合同系统、外部系统、业务和测试联合评审
A10: SPEC-006 | B10: IF-006 | C10: 大集中ERP | D10: CI16-采购订单状态查询接口 | E10: 当采购订单进行变更时，合同系统通过此接口查询采购订单信息并进行校验，如果存在未结采购订单不能进行合同标的明细变更 | F10: P0 | G10: 大集中erp推送合同系统 | H10: 大集中ERP | I10: 合同系统 | J10: 同步（待确认） | K10: 待业务确认 | L10: 待补充字段清单 | M10: 待确认 | N10: 待确认 | O10: 待确认 | P10: 待确认 | Q10: 待确认 | R10: 重要业务数据 | S10: 技术经理 | T10: 46367 | U10: 待编制 | V10: 由合同系统、外部系统、业务和测试联合评审
A11: SPEC-007 | B11: IF-007 | C11: 大集中ERP | D11: CI17-合同系统变更审批结果推送ERP系统（项目预算释放） | E11: 带wbs号的变更申请，在合同系统变更审批完成后，通过此接口将信息传递到ERP系统，ERP系统接到接口信息进行采购订单变更 | F11: P0 | G11: 合同系统推送大集中erp | H11: 合同系统 | I11: 大集中ERP | J11: 待确认 | K11: 待业务确认 | L11: 待补充字段清单 | M11: 待确认 | N11: 待确认 | O11: 待确认 | P11: 待确认 | Q11: 待确认 | R11: 重要业务数据 | S11: 技术经理 | T11: 46367 | U11: 待编制 | V11: 由合同系统、外部系统、业务和测试联合评审
A12: SPEC-008 | B12: IF-008 | C12: 大集中ERP | D12: CI18-采购订单退回ERP | E12: 采购订单信息通过CI12接口传输合同系统后，如子合同审核未批准，删除子合同时传输信息到ERP系统 | F12: P0 | G12: 合同系统推送大集中erp | H12: 合同系统 | I12: 大集中ERP | J12: 待确认 | K12: 待业务确认 | L12: 待补充字段清单 | M12: 待确认 | N12: 待确认 | O12: 待确认 | P12: 待确认 | Q12: 待确认 | R12: 重要业务数据 | S12: 技术经理 | T12: 46367 | U12: 待编制 | V12: 由合同系统、外部系统、业务和测试联合评审
A13: SPEC-009 | B13: IF-009 | C13: 大集中ERP | D13: CI19-合同变更申请信息推送ERP系统（项目预算占用） | E13: 此接口为同步接口，带wbs号的变更申请，在合同系统提交变更审批时，调用ERP系统预算管控查询，如果变更申请不超过预算金额则可以提交，如果变更申请超过预算金额返回错误信息，错误信息包含超预算的行项目信息和金额，同时将变更信息更新到PR以占用预算 | F13: P0 | G13: 合同系统推送大集中erp | H13: 合同系统 | I13: 大集中ERP | J13: 同步（待确认） | K13: 待业务确认 | L13: 待补充字段清单 | M13: 待确认 | N13: 待确认 | O13: 待确认 | P13: 待确认 | Q13: 待确认 | R13: 重要业务数据 | S13: 技术经理 | T13: 46367 | U13: 待编制 | V13: 由合同系统、外部系统、业务和测试联合评审
A14: SPEC-010 | B14: IF-010 | C14: 大集中ERP | D14: CI22-合同解除接口 | E14: 合同解除状态推送大集中erp | F14: P0 | G14: 合同系统推送大集中erp | H14: 合同系统 | I14: 大集中ERP | J14: 待确认 | K14: 待业务确认 | L14: 待补充字段清单 | M14: 待确认 | N14: 待确认 | O14: 待确认 | P14: 待确认 | Q14: 待确认 | R14: 重要业务数据 | S14: 技术经理 | T14: 46367 | U14: 待编制 | V14: 由合同系统、外部系统、业务和测试联合评审
A15: SPEC-011 | B15: IF-011 | C15: 大集中ERP | D15: CI23-合同终止接口 | E15: 合同终止后结果发送到ERP系统，ERP系统不可以引用带有终止标记的合同 | F15: P0 | G15: 合同系统推送大集中erp | H15: 合同系统 | I15: 大集中ERP | J15: 待确认 | K15: 待业务确认 | L15: 待补充字段清单 | M15: 待确认 | N15: 待确认 | O15: 待确认 | P15: 待确认 | Q15: 待确认 | R15: 重要业务数据 | S15: 技术经理 | T15: 46367 | U15: 待编制 | V15: 由合同系统、外部系统、业务和测试联合评审
A16: SPEC-012 | B16: IF-012 | C16: 大集中ERP | D16: CI25-销售订单状态查询接口 | E16: 在发起收入类合同变更前，查询ERP系统中销售订单的情况，入参：合同号，出参：合同号，订单号，订单状态描述等信息 | F16: P0 | G16: 大集中erp推送合同系统 | H16: 大集中ERP | I16: 合同系统 | J16: 同步（待确认） | K16: 待业务确认 | L16: 待补充字段清单 | M16: 待确认 | N16: 待确认 | O16: 待确认 | P16: 待确认 | Q16: 待确认 | R16: 重要业务数据 | S16: 技术经理 | T16: 46367 | U16: 待编制 | V16: 由合同系统、外部系统、业务和测试联合评审
... A98: SPEC-094 | B98: IF-131 | C98: MDG | D98: CI99-01-MDG员工模型 | E98: MDG综合编码 | F98: P0 | G98: MDG推送合同系统 | H98: MDG | I98: 合同系统 | J98: 待确认 | K98: 待业务确认 | L98: 待补充字段清单 | M98: 待确认 | N98: 待确认 | O98: 待确认 | P98: 待确认 | Q98: 待确认 | R98: 重要业务数据 | S98: 技术经理 | T98: 46353 | U98: 待编制 | V98: 由合同系统、外部系统、业务和测试联合评审
