Workbook

Sheet 使用说明
A1: 上线移交与运营-20260918-V5 使用说明
A2: 管理上线策略、准备、迁移、切换、回退、移交、试运行和SLA。
A4: 项目 | B4: 能源行业合同全生命周期管理系统
A5: 适用对象 | B5: 项目经理、技术经理、运维负责人、业务负责人
A6: 更新频率 | B6: 上线准备期每周更新；上线窗口和试运行期每日更新。
A7: 版本日期 | B7: 2026-10-19
A8: 颜色约定 | B8: 浅蓝表头；黄色为人工输入区；白色/灰色通常为公式、说明或系统数据。
A10: 推荐使用流程
A11: 1 | B11: 确认上线策略和门禁
A12: 2 | B12: 完成准备项及数据迁移核验
A13: 3 | B13: 按切换计划执行并保留证据
A14: 4 | B14: 必要时按回退方案决策
A15: 5 | B15: 完成运维移交并跟踪试运行和SLA
A18: 工作表导航
A19: 顺序 | B19: 工作表 | C19: 用途
A20: 1 | B20: 上线总览 | C20: 查看上线准备、迁移、移交和事件状态。
A21: 2 | B21: 上线策略 | C21: 定义上线方式、窗口、门禁和组织。
A22: 3 | B22: 上线准备清单 | C22: 核对上线前置条件。
A23: 4 | B23: 数据迁移与核验 | C23: 记录迁移批次和核验结果。
A24: 5 | B24: 切换执行计划 | C24: 编排上线窗口任务。
A25: 6 | B25: 上线部署 | C25: 按部署批次跟踪部署人员、上线状态与计划/实际上线时间；G列状态公式自动联动。
A26: 7 | B26: 回退方案 | C26: 定义触发条件和回退步骤。
A27: 8 | B27: 移交清单 | C27: 跟踪向运维和业务移交。
A28: 9 | B28: 试运行台账 | C28: 记录试运行问题和观察结果。
A29: 10 | B29: 运维SLA | C29: 定义服务级别和责任。
A30: 11 | B30: 上线事件日志 | C30: 记录上线事件及处置。
A31: 12 | B31: _数据接口 | C31: 供Python脚本和AI PMO读取，人工一般不直接修改。
A32: 维护与检查规则
A33: 1 | B33: 先维护唯一编号、责任人、计划日期和状态，再补充说明与证据。
A34: 2 | B34: 状态变化时同步更新实际日期、完成比例、阻塞原因或验证结果。
A35: 3 | B35: 涉及基线、预算、范围、合同或上线门禁的变化，须先履行评审或审批。
A36: 4 | B36: 不要覆盖公式、汇总区、图表数据区和“_数据接口”中的系统字段。
A37: 5 | B37: 每周检查空责任人、逾期未完成、状态与日期矛盾、缺少证据和公式错误。
A38: 6 | B38: 文件升级后，将被替换版本移入本模块_archive目录，不在正式目录保留多个现行版本。
A39: 7 | B39: 上线部署G列"状态"为公式联动列：上线状态改"已完成"后自动变为"已完成"；实际上线日期与上线状态须同步维护，勿改G列公式。

Sheet 上线总览
A1: 上线移交与运营总览
A2: 数据日期：2026-09-17。计划2027-05-31完成系统上线，2027-06-30完成试运行退出。
A4: 上线检查项 | C4: 已就绪 | E4: 阻塞项 | G4: 待完成移交 | I4: 未关闭事件 | K4: 综合状态
A5: =COUNTA(上线准备清单!A5:A34) -> 20 | C5: =COUNTIF(上线准备清单!K5:K34,"已就绪") -> 0 | E5: =COUNTIF(上线准备清单!K5:K34,"阻塞") -> 0 | G5: =COUNTIF(移交清单!J5:J34,"<>已完成")-COUNTBLANK(移交清单!A5:A34) -> 12 | I5: =COUNTIF(上线事件日志!I5:I104,"<>已关闭")-COUNTBLANK(上线事件日志!A5:A104) -> 0 | K5: =IF(E5>0,"红",IF(C5<A5,"黄","绿")) -> 黄
A8: 关键门禁
A9: 门禁 | B9: 计划日期 | C9: 负责人 | D9: 通过标准 | E9: 当前状态 | F9: 批准人 | G9: 证据
A10: UAT验收门禁 | B10: 46517 | C10: 产品经理 | D10: P0场景100%通过，遗留风险获得批准 | E10: 未通过 | F10: 业务负责人 | G10: UAT报告/业务确认
A11: 数据迁移门禁 | B11: 46527 | C11: 产品经理 | D11: 完整性、准确性、金额和状态对账通过 | E11: 未通过 | F11: 业务负责人 | G11: 迁移和对账报告
A12: 技术上线门禁 | B12: 46531 | C12: 技术经理 | D12: 环境、接口、安全、性能、监控和回退可用 | E12: 未通过 | F12: 项目经理 | G12: 技术验证和演练证据
A13: 业务上线门禁 | B13: 46531 | C13: 产品经理 | D13: 流程、权限、用户、培训、手册和支持就绪 | E13: 未通过 | F13: 业务负责人 | G13: 培训和业务确认
A14: Go/No-Go决策 | B14: 46535 | C14: 项目集经理 | D14: 所有必须项通过，遗留风险有批准和责任人 | E14: 未通过 | F14: 项目赞助人/治理委员会 | G14: Go/No-Go决策记录
A15: 生产上线验证 | B15: 46538 | C15: 项目经理 | D15: 核心链路、数据、接口、权限和监控验证通过 | E15: 未通过 | F15: 项目集经理 | G15: 生产验证报告
A16: 试运行退出门禁 | B16: 46568 | C16: 项目经理 | D16: 事件、缺陷、性能、用户反馈和SLA达到批准标准 | E16: 未通过 | F16: 项目赞助人 | G16: 试运行报告/移交确认

Sheet 上线策略
A1: 上线策略
A2: 本项目默认采用分阶段准备、统一窗口切换和一个月试运行。
A4: 策略项 | B4: 当前方案 | C4: 责任人 | D4: 批准人 | E4: 计划日期 | F4: 准入条件 | G4: 输出/证据 | H4: 状态
A5: 上线方式 | B5: 集中生产切换，关键流程分批开通 | C5: 项目集经理 | D5: 项目赞助人 | E5: 46535 | F5: UAT、数据、接口和回退门禁通过 | G5: Go/No-Go决策 | H5: 待批准
A6: 上线窗口 | B6: 2027-05-28冻结，2027-05-29至05-31切换和验证 | C6: 项目经理 | D6: 项目集经理 | E6: 46535 | F6: 生产环境、人员、授权和沟通到位 | G6: 切换计划 | H6: 待批准
A7: 数据策略 | B7: 全量初始化+增量补数+业务对账 | C7: 产品经理 | D7: 业务负责人 | E7: 46527 | F7: 数据规则、源数据、脱敏和验证脚本就绪 | G7: 迁移与对账报告 | H7: 待批准
A8: 变更冻结 | B8: 上线前3天冻结代码、配置、接口和数据规则 | C8: 技术经理 | D8: 项目经理 | E8: 46535 | F8: 生产版本、基线和紧急变更流程明确 | G8: 冻结清单/发布版本 | H8: 待批准
A9: 回退策略 | B9: 在规定判定窗口内回退至上一稳定版本 | C9: 技术经理 | D9: 项目集经理 | E9: 46531 | F9: 备份、回退脚本、数据处置和演练通过 | G9: 回退方案/演练报告 | H9: 待批准
A10: 支持策略 | B10: 试运行期间业务、产品、开发、测试和运维联合值守 | C10: 项目经理 | D10: 项目集经理 | E10: 46531 | F10: 联系人、排班、SLA、升级和工单渠道明确 | G10: 支持手册/值班表 | H10: 待批准
A11: 试运行 | B11: 2027-06-01至2027-06-30，按日监控、按周评审 | C11: 项目经理 | D11: 项目赞助人 | E11: 46538 | F11: 生产验证通过，支持和监控就绪 | G11: 试运行计划 | H11: 待批准
A12: 试运行退出 | B12: 达到SLA、缺陷、事件、性能和用户反馈标准后移交运营 | C12: 项目集经理 | D12: 项目赞助人 | E12: 46568 | F12: 试运行退出门禁通过 | G12: 试运行报告/移交确认 | H12: 未开始
A13: 沟通策略 | B13: 上线前每日准备会，窗口期间按节点通报，事件触发升级 | C13: 项目经理 | D13: 项目集经理 | E13: 46518 | F13: 通讯录、模板、群组和升级路径就绪 | G13: 沟通计划/上线通知 | H13: 未开始
A14: 业务连续性 | B14: 明确切换期业务暂停、手工处理、补录和对账机制 | C14: 产品经理 | D14: 业务负责人 | E14: 46531 | F14: 临时业务方案和恢复后补录规则明确 | G14: 业务连续性方案 | H14: 未开始

Sheet 上线准备清单
A1: 上线准备清单
A2: 必须项未就绪或阻塞时，Go/No-Go必须明确处置决定。
A4: 检查项ID | B4: 领域 | C4: 检查项 | D4: 责任人 | E4: 通过标准 | F4: 计划完成 | G4: 是否必须 | H4: 实际完成 | I4: 验证人 | J4: 证据 | K4: 状态 | L4: 备注
A5: RDY-001 | B5: 范围 | C5: P0范围和上线版本冻结 | D5: 项目经理 | E5: 上线版本与批准范围一致 | F5: 46535 | G5: 必须 | K5: 未就绪
A6: RDY-002 | B6: 需求 | C6: P0需求和验收标准完成 | D6: 产品经理 | E6: P0覆盖率100% | F6: 46517 | G6: 必须 | K6: 未就绪
A7: RDY-003 | B7: 缺陷 | C7: Blocker/Critical缺陷清零 | D7: 测试负责人 | E7: 未关闭数为0或获得书面批准 | F7: 46531 | G7: 必须 | K7: 未就绪
A8: RDY-004 | B8: UAT | C8: 关键用户完成UAT确认 | D8: 产品经理 | E8: P0场景100%通过 | F8: 46517 | G8: 必须 | K8: 未就绪
A9: RDY-005 | B9: 数据 | C9: 迁移、增量补数和业务对账通过 | D9: 产品经理 | E9: 关键对账差异为0或获批准 | F9: 46527 | G9: 必须 | K9: 未就绪
A10: RDY-006 | B10: 接口 | C10: P0接口完成联调、异常补偿、对账和生产参数核验 | D10: 技术经理 | E10: 37个系统完成范围决策；P0接口联调通过率100%，未关闭对账差异为0或获批准 | F10: 46527 | G10: 必须 | J10: 接口范围基线、联调报告、对账报告、生产参数清单 | K10: 未就绪
A11: RDY-007 | B11: 权限 | C11: 角色、组织、数据权限和审计校验 | D11: 技术经理 | E11: 越权被阻止，审计日志完整 | F11: 46527 | G11: 必须 | K11: 未就绪
A12: RDY-008 | B12: 性能 | C12: 核心页面和接口性能达标 | D12: 技术经理 | E12: 达到批准的并发、响应和容量指标 | F12: 46527 | G12: 必须 | K12: 未就绪
A13: RDY-009 | B13: 安全 | C13: 安全测试和高风险整改完成 | D13: 技术经理 | E13: 高风险问题为0 | F13: 46527 | G13: 必须 | K13: 未就绪
A14: RDY-010 | B14: 环境 | C14: 生产环境、网络、证书、域名和时间同步就绪 | D14: 配置人员 | E14: 环境验证清单通过 | F14: 46527 | G14: 必须 | K14: 未就绪
A15: RDY-011 | B15: 发布 | C15: 发布包、脚本、配置和版本可追溯 | D15: 技术经理 | E15: 版本、校验值和审批完整 | F15: 46531 | G15: 必须 | K15: 未就绪
A16: RDY-012 | B16: 监控 | C16: 应用、接口、数据库、中间件和业务监控就绪 | D16: 技术经理 | E16: 监控、告警、通知和值班验证通过 | F16: 46531 | G16: 必须 | K16: 未就绪
A17: RDY-013 | B17: 备份 | C17: 数据库、文件、配置和密钥备份完成 | D17: 配置人员 | E17: 备份可恢复并完成抽样验证 | F17: 46531 | G17: 必须 | K17: 未就绪
A18: RDY-014 | B18: 回退 | C18: 回退方案、脚本和演练通过 | D18: 技术经理 | E18: RTO/RPO和业务验证达标 | F18: 46531 | G18: 必须 | K18: 未就绪
A19: RDY-015 | B19: 用户 | C19: 生产用户、角色和初始化数据准备完成 | D19: 产品经理 | E19: 用户清单和授权审批完整 | F19: 46531 | G19: 必须 | K19: 未就绪
A20: RDY-016 | B20: 培训 | C20: 管理员、关键用户和支持人员培训完成 | D20: 产品经理 | E20: 出席、课件、考核和问题记录完整 | F20: 46531 | G20: 必须 | K20: 未就绪
A21: RDY-017 | B21: 文档 | C21: 用户手册、运维手册、应急手册和配置清单完成 | D21: 项目经理 | E21: 文档通过评审并存入指定位置 | F21: 46531 | G21: 必须 | K21: 未就绪
A22: RDY-018 | B22: 支持 | C22: 试运行值守、工单、SLA和升级路径就绪 | D22: 项目经理 | E22: 轮值和升级演练通过 | F22: 46531 | G22: 必须 | K22: 未就绪
... A24: RDY-020 | B24: 商务 | C24: 外部产品授权、证书、SLA和支持权益生效 | D24: 项目经理 | E24: CA/电子文档/BI合同权益可用 | F24: 46531 | G24: 必须 | K24: 未就绪

Sheet 数据迁移与核验
A1: 数据迁移与核验
A2: 迁移必须同时验证完整性、准确性、一致性、附件可用性和业务可操作性。
A4: 迁移ID | B4: 数据对象 | C4: 来源系统 | D4: 迁移范围 | E4: 迁移方式 | F4: 负责人 | G4: 计划执行 | H4: 源数量 | I4: 目标数量 | J4: 差异数量 | K4: 差异率 | L4: 核验规则 | M4: 核验结果 | N4: 差异处置 | O4: 批准人 | P4: 证据
A5: MIG-001 | B5: 合同主数据 | C5: 现有合同系统/档案 | D5: 有效及需追溯合同 | E5: 全量+增量 | F5: 产品经理 | G5: 46524 | K5: =IF(OR(H5="",I5=""),"",IF(H5=0,"n.a.",J5/H5)) | L5: 记录数、金额、状态、关键字段和抽样业务校验 | M5: 未执行 | O5: 业务负责人
A6: MIG-002 | B6: 合同相对方 | C6: 主数据平台 | D6: 有效客户、供应商和资质 | E6: 全量+增量 | F6: 产品经理 | G6: 46524 | K6: =IF(OR(H6="",I6=""),"",IF(H6=0,"n.a.",J6/H6)) | L6: 编码、名称、统一社会信用代码、状态和资质 | M6: 未执行 | O6: 业务负责人
A7: MIG-003 | B7: 履约与收付款 | C7: 现有业务/财务系统 | D7: 未完成履约、应收应付和关键历史 | E7: 全量+增量 | F7: 产品经理 | G7: 46525 | K7: =IF(OR(H7="",I7=""),"",IF(H7=0,"n.a.",J7/H7)) | L7: 节点、金额、余额、状态和业财对账 | M7: 未执行 | O7: 业务/财务负责人
A8: MIG-004 | B8: 合同附件与归档文件 | C8: 档案/文件系统 | D8: 正文、附件、审批和签署证据 | E8: 全量+增量 | F8: 产品经理 | G8: 46526 | K8: =IF(OR(H8="",I8=""),"",IF(H8=0,"n.a.",J8/H8)) | L8: 文件数、大小、哈希、关联、打开和权限 | M8: 未执行 | O8: 档案负责人
A9: MIG-005 | B9: 组织、用户与权限 | C9: 组织/身份平台 | D9: 组织、人员、岗位、角色和数据范围 | E9: 全量+增量 | F9: 技术经理 | G9: 46526 | K9: =IF(OR(H9="",I9=""),"",IF(H9=0,"n.a.",J9/H9)) | L9: 账号状态、角色、最小权限、离职失效和越权验证 | M9: 未执行 | O9: 安全/业务负责人
A10: MIG-006 | B10: 经营指标初始数据 | C10: 合同系统/BI | D10: 合同金额、履约、收付款和风险指标 | E10: 全量汇总 | F10: 产品经理 | G10: 46527 | K10: =IF(OR(H10="",I10=""),"",IF(H10=0,"n.a.",J10/H10)) | L10: 明细与报表汇总、指标口径和数据权限 | M10: 未执行 | O10: 业务负责人

Sheet 切换执行计划
A1: 切换执行计划
A2: 以实际时间、执行人、验证结果和证据记录整个上线窗口。
A4: 任务ID | B4: 阶段 | C4: 切换任务 | D4: 前置任务 | E4: 负责人 | F4: 复核人 | G4: 计划开始 | H4: 计划结束 | I4: 实际开始 | J4: 实际结束 | K4: 执行命令/步骤 | L4: 验证方法 | M4: 状态 | N4: 执行结果 | O4: 证据 | P4: 异常/事件ID
A5: CUT-001 | B5: 准备 | C5: 确认Go/No-Go批准 | E5: 项目集经理 | F5: 项目赞助人 | G5: 46535 | H5: 46535 | K5: 核对门禁、风险批准和责任人 | L5: 决策记录完整 | M5: 未开始
A6: CUT-002 | B6: 准备 | C6: 冻结代码、配置、数据规则和接口 | D6: CUT-001 | E6: 技术经理 | F6: 项目经理 | G6: 46535 | H6: 46535 | K6: 标记生产基线，关闭普通变更入口 | L6: 基线编号、校验值可追溯 | M6: 未开始
A7: CUT-003 | B7: 备份 | C7: 执行生产前数据、文件、配置和密钥备份 | D7: CUT-002 | E7: 配置人员 | F7: 技术经理 | G7: 46536 | H7: 46536 | K7: 按备份清单执行并记录校验值 | L7: 恢复抽样成功 | M7: 未开始
A8: CUT-004 | B8: 部署 | C8: 部署应用、配置、中间件和数据库变更 | D8: CUT-003 | E8: 技术经理 | F8: 配置人员 | G8: 46536 | H8: 46536 | K8: 按发布手册和自动化脚本执行 | L8: 版本、配置、进程和日志正常 | M8: 未开始
A9: CUT-005 | B9: 数据 | C9: 执行全量/增量数据迁移 | D9: CUT-003 | E9: 产品经理 | F9: 技术经理 | G9: 46536 | H9: 46537 | K9: 执行迁移脚本、增量补数和对账 | L9: 迁移对象逐项核验 | M9: 未开始
A10: CUT-006 | B10: 集成 | C10: 启用大集中ERP、昆仑ERP、云梦泽、财务共享、档案、IAM、EPM、MDG及外部产品生产接口 | D10: CUT-004,CUT-005 | E10: 技术经理 | F10: 接口负责人 | G10: 46537 | H10: 46537 | K10: 按批准的P0接口清单配置生产端点、证书、账号、白名单和调度 | L10: 逐系统健康检查、核心交易验证、重试补偿和对账 | M10: 未开始
A11: CUT-007 | B11: 权限 | C11: 初始化生产用户、角色和数据权限 | D11: CUT-004,CUT-005 | E11: 产品经理 | F11: 安全负责人 | G11: 46537 | H11: 46537 | K11: 导入批准用户和权限清单 | L11: 允许、拒绝、数据范围和审计验证 | M11: 未开始
A12: CUT-008 | B12: 验证 | C12: 执行核心合同生命周期烟测 | D12: CUT-004,CUT-005,CUT-006,CUT-007 | E12: 测试负责人 | F12: 产品经理 | G12: 46537 | H12: 46538 | K12: 创建、审查、审批、签署、履约、变更、归档 | L12: 业务结果、数据、接口和审计日志正确 | M12: 未开始
A13: CUT-009 | B13: 监控 | C13: 启用监控、告警、日志聚合和值班通知 | D13: CUT-004 | E13: 技术经理 | F13: 运维负责人 | G13: 46537 | H13: 46537 | K13: 开启监控项、告警规则和通知链路 | L13: 模拟告警可送达并处理 | M13: 未开始
A14: CUT-010 | B14: 业务 | C14: 发布上线通知并开放生产访问 | D14: CUT-008,CUT-009 | E14: 项目经理 | F14: 业务负责人 | G14: 46538 | H14: 46538 | K14: 按通知模板发送用户范围、入口和支持方式 | L14: 关键用户确认可访问 | M14: 未开始
A15: CUT-011 | B15: 试运行 | C15: 启动试运行值守和每日跟踪 | D15: CUT-010 | E15: 项目经理 | F15: 项目集经理 | G15: 46539 | H15: 46539 | K15: 启动值班表、工单渠道、SLA和日报 | L15: 首日状态和联络链路正常 | M15: 未开始
A16: CUT-012 | B16: 收尾 | C16: 完成生产验证报告和窗口复盘 | D16: CUT-010 | E16: 项目经理 | F16: 项目集经理 | G16: 46539 | H16: 46540 | K16: 汇总任务、异常、用时、结果和遗留项 | L16: 报告和行动项获得确认 | M16: 未开始

Sheet 上线部署
A1: 上线部署
A2: 按部署批次跟踪上线部署的人员、上线状态与计划/实际上线时间。G列"状态"为公式联动：上线状态=已完成→已完成、已回退→已回退、进行中→进行中；其余按计划上线时间与数据日期（_数据接口!B6）判定未排期/已延期/未开始。参考样式：港口交易平台开发计划上线字段。
A4: 部署ID | B4: 部署对象 | C4: 人员 | D4: 上线状态 | E4: 计划上线时间 | F4: 实际上线日期 | G4: 状态 | H4: 备注
A5: DPL-001 | B5: 生产环境部署与冒烟验证 | C5: 技术经理 | E5: 46531 | G5: =IF($A5="","",IF($D5="已完成","已完成",IF($D5="已回退","已回退",IF($D5="进行中","进行中",IF($E5="","未排期",IF($E5<_数据接口!$B$6,"已延期","未开始")))))) -> 未开始
A6: DPL-002 | B6: 数据迁移切换执行 | C6: 产品经理 | E6: 46535 | G6: =IF($A6="","",IF($D6="已完成","已完成",IF($D6="已回退","已回退",IF($D6="进行中","进行中",IF($E6="","未排期",IF($E6<_数据接口!$B$6,"已延期","未开始")))))) -> 未开始
A7: DPL-003 | B7: 系统正式上线切换 | C7: 项目集经理 | E7: 46538 | G7: =IF($A7="","",IF($D7="已完成","已完成",IF($D7="已回退","已回退",IF($D7="进行中","进行中",IF($E7="","未排期",IF($E7<_数据接口!$B$6,"已延期","未开始")))))) -> 未开始
A8: DPL-004 | B8: 试运行保障与退出门禁 | C8: 项目经理 | E8: 46568 | G8: =IF($A8="","",IF($D8="已完成","已完成",IF($D8="已回退","已回退",IF($D8="进行中","进行中",IF($E8="","未排期",IF($E8<_数据接口!$B$6,"已延期","未开始")))))) -> 未开始
G9: =IF($A9="","",IF($D9="已完成","已完成",IF($D9="已回退","已回退",IF($D9="进行中","进行中",IF($E9="","未排期",IF($E9<_数据接口!$B$6,"已延期","未开始"))))))
G10: =IF($A10="","",IF($D10="已完成","已完成",IF($D10="已回退","已回退",IF($D10="进行中","进行中",IF($E10="","未排期",IF($E10<_数据接口!$B$6,"已延期","未开始"))))))
G11: =IF($A11="","",IF($D11="已完成","已完成",IF($D11="已回退","已回退",IF($D11="进行中","进行中",IF($E11="","未排期",IF($E11<_数据接口!$B$6,"已延期","未开始"))))))
G12: =IF($A12="","",IF($D12="已完成","已完成",IF($D12="已回退","已回退",IF($D12="进行中","进行中",IF($E12="","未排期",IF($E12<_数据接口!$B$6,"已延期","未开始"))))))
G13: =IF($A13="","",IF($D13="已完成","已完成",IF($D13="已回退","已回退",IF($D13="进行中","进行中",IF($E13="","未排期",IF($E13<_数据接口!$B$6,"已延期","未开始"))))))
G14: =IF($A14="","",IF($D14="已完成","已完成",IF($D14="已回退","已回退",IF($D14="进行中","进行中",IF($E14="","未排期",IF($E14<_数据接口!$B$6,"已延期","未开始"))))))
G15: =IF($A15="","",IF($D15="已完成","已完成",IF($D15="已回退","已回退",IF($D15="进行中","进行中",IF($E15="","未排期",IF($E15<_数据接口!$B$6,"已延期","未开始"))))))
G16: =IF($A16="","",IF($D16="已完成","已完成",IF($D16="已回退","已回退",IF($D16="进行中","进行中",IF($E16="","未排期",IF($E16<_数据接口!$B$6,"已延期","未开始"))))))
G17: =IF($A17="","",IF($D17="已完成","已完成",IF($D17="已回退","已回退",IF($D17="进行中","进行中",IF($E17="","未排期",IF($E17<_数据接口!$B$6,"已延期","未开始"))))))
G18: =IF($A18="","",IF($D18="已完成","已完成",IF($D18="已回退","已回退",IF($D18="进行中","进行中",IF($E18="","未排期",IF($E18<_数据接口!$B$6,"已延期","未开始"))))))
G19: =IF($A19="","",IF($D19="已完成","已完成",IF($D19="已回退","已回退",IF($D19="进行中","进行中",IF($E19="","未排期",IF($E19<_数据接口!$B$6,"已延期","未开始"))))))
G20: =IF($A20="","",IF($D20="已完成","已完成",IF($D20="已回退","已回退",IF($D20="进行中","进行中",IF($E20="","未排期",IF($E20<_数据接口!$B$6,"已延期","未开始"))))))
... G24: =IF($A24="","",IF($D24="已完成","已完成",IF($D24="已回退","已回退",IF($D24="进行中","进行中",IF($E24="","未排期",IF($E24<_数据接口!$B$6,"已延期","未开始"))))))

Sheet 回退方案
A1: 回退方案
A2: 回退的核心是明确触发条件、决策时限、数据边界、恢复验证和沟通责任。
A4: 回退ID | B4: 场景 | C4: 触发条件 | D4: 决策人 | E4: 决策截止 | F4: 回退步骤 | G4: 数据处理 | H4: 验证方法 | I4: RTO目标 | J4: RPO目标 | K4: 执行负责人 | L4: 沟通对象 | M4: 演练结果 | N4: 证据
A5: RBK-001 | B5: 应用版本无法启动/核心链路不可用 | C5: 两次修复失败或超过切换窗口 | D5: 项目集经理 | E5: 问题确认后30分钟 | F5: 停止流量、卸载/停用新版本、恢复旧版、验证 | G5: 新版交易统计并按方案补偿 | H5: 登录、核心流程、接口、日志 | I5: 2小时 | J5: 15分钟 | K5: 技术经理 | L5: 业务、管理层、项目组 | M5: 未演练
A6: RBK-002 | B6: 数据迁移差异不可接受 | C6: 关键数据不完整、金额或状态差异无法在窗口内解决 | D6: 项目集经理 | E6: 对账结果出具后30分钟 | F6: 停止开放、保留旧系统、恢复备份、重新对账 | G6: 禁止双写，保留迁移批次和差异明细 | H6: 数量、金额、状态、附件和抽样 | I6: 4小时 | J6: 0 | K6: 产品经理/技术经理 | L6: 业务、财务、管理层 | M6: 未演练
A7: RBK-003 | B7: P0外部接口核心交易不可用 | C7: 任一大集中ERP、昆仑ERP、云梦泽、财务共享、档案、MDG等P0链路无法在批准时限内恢复 | D7: 项目集经理 | E7: 问题确认后60分钟 | F7: 停止新交易、切换旧链路/手工方案、重新对账 | G7: 记录待补偿交易和幂等键 | H7: 按接口清单执行健康检查、核心交易、重试、补偿和对账 | I7: 2小时 | J7: 15分钟 | K7: 技术经理 | L7: 业务、外部系统、项目组 | M7: 未演练
A8: RBK-004 | B8: 权限或安全问题 | C8: 发生严重越权、数据泄露或高风险漏洞 | D8: 项目赞助人/安全负责人 | E8: 立即 | F8: 关闭入口、停止服务、保全日志、回退、启动应急响应 | G8: 保留现场，禁止未授权修改 | H8: 安全扫描、权限验证、日志审计 | I8: 2小时 | J8: 0 | K8: 技术经理 | L8: 安全、管理层、业务、法务 | M8: 未演练
A9: RBK-005 | B9: 性能或容量严重不足 | C9: 核心业务超时/错误率超阈值且扩容无效 | D9: 项目集经理 | E9: 超阈值后60分钟 | F9: 限流、降级、扩容，仍无效时回退 | G9: 确保交易不丢失不重复 | H9: 压力、交易量、错误率、资源和业务体验 | I9: 2小时 | J9: 15分钟 | K9: 技术经理 | L9: 业务、运维、管理层 | M9: 未演练
A10: RBK-006 | B10: 回退后验证 | C10: 任一回退场景触发 | D10: 项目集经理 | E10: 回退后30分钟内启动验证 | F10: 检查系统、数据、接口、权限、监控，发布恢复通知 | G10: 对账回退前后交易并形成补偿清单 | H10: 核心合同生命周期业务烟测 | I10: 1小时 | J10: 15分钟 | K10: 测试负责人 | L10: 全体相关方 | M10: 未演练

Sheet 移交清单
A1: 移交清单
A2: 移交以接收人可独立运营和可检索证据为完成标准。
A4: 移交ID | B4: 类别 | C4: 移交项 | D4: 交付标准 | E4: 移交人 | F4: 接收人 | G4: 计划日期 | H4: 实际日期 | I4: 存放位置/链接 | J4: 状态 | K4: 确认人 | L4: 备注
A5: HOV-001 | B5: 管理 | C5: 项目章程、基线、决策、风险、变更和会议记录 | D5: 索引完整、版本可追溯 | E5: 项目经理 | F5: 运营负责人 | G5: 46558 | J5: 未开始
A6: HOV-002 | B6: 业务 | C6: 业务流程、规则、配置、权限和指标口径 | D6: 与生产配置一致并通过业务确认 | E6: 产品经理 | F6: 业务运营负责人 | G6: 46558 | J6: 未开始
A7: HOV-003 | B7: 用户 | C7: 用户手册、常见问题和培训材料 | D7: 文档可用，关键用户完成培训 | E7: 产品经理 | F7: 业务运营负责人 | G7: 46558 | J7: 未开始
A8: HOV-004 | B8: 技术 | C8: 架构、部署、接口、数据、安全和性能文档 | D8: 与生产一致，关键决策和已知限制明确 | E8: 技术经理 | F8: 运维负责人 | G8: 46558 | J8: 未开始
A9: HOV-005 | B9: 运维 | C9: 运维手册、监控、告警、备份、恢复和日常巡检 | D9: 运维人员可独立执行标准操作 | E9: 技术经理 | F9: 运维负责人 | G9: 46558 | J9: 未开始
A10: HOV-006 | B10: 账号 | C10: 系统账号、服务账号、证书、密钥和到期日 | D10: 权属、保管、轮换和审批流程明确 | E10: 配置人员 | F10: 运维/安全负责人 | G10: 46558 | J10: 未开始
A11: HOV-007 | B11: 配置 | C11: 应用、数据库、中间件、调度和接口配置清单 | D11: 生产基线可追溯，敏感项脱敏 | E11: 配置人员 | F11: 运维负责人 | G11: 46558 | J11: 未开始
A12: HOV-008 | B12: 供应商 | C12: CA/电子文档/BI产品授权、SLA、联系人和支持流程 | D12: 权益生效，联系人和升级路径有效 | E12: 项目经理 | F12: 运维/采购负责人 | G12: 46558 | J12: 未开始
A13: HOV-009 | B13: 未结事项 | C13: 已知缺陷、风险、技术债和后续优化 | D13: 影响、应对、责任人和日期明确并获批准 | E13: 项目经理 | F13: 运营负责人 | G13: 46563 | J13: 未开始
A14: HOV-010 | B14: 验收 | C14: 交付物、验收证据、发票付款和合同义务 | D14: 交付物与合同清单匹配，未结义务明确 | E14: 项目经理 | F14: 合同/采购负责人 | G14: 46563 | J14: 未开始
A15: HOV-011 | B15: 数据 | C15: 数据字典、迁移映射、对账规则和数据质量问题 | D15: 口径和数据责任明确 | E15: 产品经理 | F15: 数据/运营负责人 | G15: 46558 | J15: 未开始
A16: HOV-012 | B16: 应急 | C16: 应急预案、回退方案、演练报告和通讯录 | D16: 运维可按预案独立组织响应 | E16: 技术经理 | F16: 运维负责人 | G16: 46558 | J16: 未开始

Sheet 试运行台账
A1: 试运行台账
A2: 按日/周记录系统、业务、数据、接口、性能、支持和用户反馈。
A4: 周期ID | B4: 开始日期 | C4: 结束日期 | D4: 生产交易量 | E4: 核心链路成功率 | F4: P1/P2事件数 | G4: 未关闭严重缺陷 | H4: SLA达成率 | I4: 用户反馈 | J4: 主要问题 | K4: 本期行动 | L4: 负责人 | M4: 状态 | N4: 证据/报告
A5: OPS-001 | B5: 46539 | C5: 46544 | L5: 项目经理 | M5: 未开始
A6: OPS-002 | B6: 46545 | C6: 46551 | L6: 项目经理 | M6: 未开始
A7: OPS-003 | B7: 46552 | C7: 46558 | L7: 项目经理 | M7: 未开始
A8: OPS-004 | B8: 46559 | C8: 46565 | L8: 项目经理 | M8: 未开始
A9: OPS-005 | B9: 46566 | C9: 46568 | L9: 项目经理 | M9: 未开始

Sheet 运维SLA
A1: 运维SLA与支持模型
A2: SLA阈值为项目建议初值，正式生效前应由业务、运维和供应商确认。
A4: 服务项 | B4: 级别/场景 | C4: 服务时间 | D4: 响应时限 | E4: 恢复/解决目标 | F4: 升级时限 | G4: 一线负责 | H4: 二线负责 | I4: 三线/供应商 | J4: 监控/证据 | K4: 报告频率 | L4: 状态
A5: 事件处理 | B5: P1-系统不可用/严重数据或安全影响 | C5: 7×24 | D5: 15分钟 | E5: 2小时恢复，根因按批准时限 | F5: 15分钟 | G5: 服务台 | H5: 运维/技术经理 | I5: 项目集经理/供应商 | J5: 工单、监控、时间线和复盘 | K5: 每30分钟通报 | L5: 待确认
A6: 事件处理 | B6: P2-核心功能严重受影响 | C6: 7×24 | D6: 30分钟 | E6: 4小时恢复 | F6: 1小时 | G6: 服务台 | H6: 运维/开发 | I6: 技术经理/供应商 | J6: 工单、日志和处理证据 | K6: 每2小时通报 | L6: 待确认
A7: 事件处理 | B7: P3-一般功能受影响 | C7: 5×8 | D7: 4小时 | E7: 2个工作日 | F7: 1个工作日 | G7: 服务台 | H7: 运维/开发 | I7: 供应商 | J7: 工单和解决记录 | K7: 日报 | L7: 待确认
A8: 事件处理 | B8: P4-咨询/轻微影响 | C8: 5×8 | D8: 1个工作日 | E8: 5个工作日 | F8: 3个工作日 | G8: 服务台 | H8: 运维/产品 | I8: 供应商 | J8: 工单和知识库 | K8: 周报 | L8: 待确认
A9: 系统可用性 | B9: 核心服务 | C9: 7×24 | D9: 监控实时 | E9: 月度可用性≥99.9% | F9: 超阈值立即 | G9: 运维 | H9: 技术经理 | I9: 供应商 | J9: 可用性、停机时间和排除项 | K9: 月报 | L9: 待确认
A10: 接口可用性 | B10: 核心ERP/财务/CA/文档接口 | C10: 7×24 | D10: 监控实时 | E10: 成功率≥99.9%，失败可重试补偿 | F10: 连续失败超阈值 | G10: 运维 | H10: 技术经理 | I10: 外部系统/供应商 | J10: 成功率、延迟、重试、补偿和对账 | K10: 日报/月报 | L10: 待确认
A11: 备份与恢复 | B11: 数据库、文件和配置 | C11: 7×24 | D11: 备份失败立即 | E11: RPO≤15分钟，RTO≤4小时 | F11: 备份失败后30分钟 | G11: 运维 | H11: 技术经理 | I11: 基础设施供应商 | J11: 备份作业、恢复演练和校验记录 | K11: 日报/季度演练 | L11: 待确认
A12: 支持与报告 | B12: 试运行联合支持 | C12: 7×24 | D12: 按事件级别 | E12: 问题当日分类并持续跟踪 | F12: 阻塞或逾期立即 | G12: 服务台 | H12: 项目组 | I12: 供应商 | J12: 工单、日报、趋势和复盘 | K12: 每日/每周 | L12: 待确认

Sheet 上线事件日志
A1: 上线事件日志
A2: 记录上线窗口和试运行事件。P1/P2事件需复盘和根因分析。
A4: 事件ID | B4: 发生时间 | C4: 级别 | D4: 类别 | E4: 现象/影响 | F4: 发现方式 | G4: 负责人 | H4: 首次响应 | I4: 状态 | J4: 恢复时间 | K4: 解决时间 | L4: 根因 | M4: 处置措施 | N4: 问题/缺陷ID | O4: 证据/复盘

Sheet _数据接口
A1: 字段 | B1: 值
A2: Project_ID | B2: ECM-2026
A3: 项目名称 | B3: 能源行业合同全生命周期管理系统
A4: 模块编码 | B4: 09
A5: 版本日期 | B5: 46282
A6: 数据日期 | B6: 46282
A7: 计划上线日期 | B7: 46538
A8: 试运行开始 | B8: 46539
A9: 试运行退出 | B9: 46568
A10: 上线门禁数 | B10: 7
A11: 上线准备项数 | B11: 20
A12: 迁移对象数 | B12: 6
A13: 切换任务数 | B13: 12
A14: 移交项数 | B14: 12
A15: 使用说明Sheet | B15: 已包含
A16: 使用说明版本 | B16: 20260917-V1
A17: 上游模块 | B17: 02_计划与进度/06_风险问题与变更/07_质量测试与验收/08_沟通会议与报告
A18: 下游模块 | B18: 10_复盘与经验沉淀/11_AI_PMO中心
A19: 中央数据库 | B19: ../90_项目数据中心/ai_pmo.db
