Workbook

Sheet 项目驾驶舱
A1: 华能交易中心港口交易平台｜项目管理驾驶舱
A3: 统计日期 | B3: 46276
A5: 总任务数 | B5: 已完成 | C5: 进行中 | D5: 未开始 | E5: 暂停 | F5: 平均进度 | G5: 已延期 | H5: 临近到期 | I5: 高风险 | J5: 未关闭问题 | K5: 待决变更 | L5: 里程碑达成 | M5: 集成完成 | N5: 交付物完成
A6: =COUNTA(项目总控台账!$A$4:$A$203) -> 145 | B6: =COUNTIF(项目总控台账!$G$4:$G$203,"已完成") -> 73 | C6: =COUNTIF(项目总控台账!$G$4:$G$203,"进行中") -> 23 | D6: =COUNTIF(项目总控台账!$G$4:$G$203,"未开始") -> 43 | E6: =COUNTIF(项目总控台账!$G$4:$G$203,"暂停") -> 6 | F6: =AVERAGE(项目总控台账!$AB$4:$AB$203) -> 0.6062069 | G6: =COUNTIF(项目总控台账!$AC$4:$AC$203,"已延期") -> 24 | H6: =COUNTIF(项目总控台账!$AC$4:$AC$203,"临近到期") -> 0 | I6: =COUNTIFS(风险问题台账!$D$4:$D$103,"高",风险问题台账!$K$4:$K$103,"<>已关闭") -> 5 | J6: =COUNTIF(风险问题台账!$K$4:$K$103,"处理中")+COUNTIF(风险问题台账!$K$4:$K$103,"待处理") -> 6 | K6: =COUNTIF(变更台账!$G$4:$G$53,"评估中")+COUNTIF(变更台账!$G$4:$G$53,"待审批") -> 0 | L6: =IFERROR(COUNTIF(里程碑计划!$G$4:$G$23,"已完成")/COUNTA(里程碑计划!$A$4:$A$23),0) -> 0 | M6: =IFERROR(COUNTIF(集成管理!$G$4:$G$53,"已完成")/COUNTA(集成管理!$A$4:$A$53),0) -> 0.33333333 | N6: =IFERROR(COUNTIF(交付物台账!$G$4:$G$53,"已完成")/COUNTA(交付物台账!$A$4:$A$53),0) -> 0
A7: 综合进度 | D7: 任务完成率 | G7: 计划投入人天 | J7: 计划人工成本 | M7: 人日单价
A8: =AVERAGE(项目总控台账!$AB$4:$AB$148) -> 0.6062069 | D8: =COUNTIF(项目总控台账!$G$4:$G$148,"已完成")/COUNTIF(项目总控台账!$A$4:$A$148,"<>") -> 0.50344828 | G8: =SUM(资源计划!$H$5:$H$10)/8 -> 500 | J8: =G8*M8 -> 600000 | M8: 1200
A9: 状态 | B9: 任务数 | D9: 批次 | E9: 任务数 | F9: 已完成 | G9: 完成率
A10: 已完成 | B10: =B6 -> 73 | D10: 第一批次 | E10: =COUNTIF(项目总控台账!$F$4:$F$203,D10) -> 61 | F10: =COUNTIFS(项目总控台账!$F$4:$F$203,D10,项目总控台账!$G$4:$G$203,"已完成") -> 57 | G10: =IFERROR(F10/E10,0) -> 0.93442623
A11: 进行中 | B11: =C6 -> 23 | D11: 第二批次 | E11: =COUNTIF(项目总控台账!$F$4:$F$203,D11) -> 78 | F11: =COUNTIFS(项目总控台账!$F$4:$F$203,D11,项目总控台账!$G$4:$G$203,"已完成") -> 16 | G11: =IFERROR(F11/E11,0) -> 0.20512821
A12: 未开始 | B12: =D6 -> 43 | D12: 其他 | E12: =$A$6-E10-E11 -> 6 | F12: =$B$6-F10-F11 -> 0 | G12: =IFERROR(F12/E12,0) -> 0
A13: 暂停 | B13: =E6 -> 6
A16: 管理关注点
A17: ="截至 "&TEXT($B$3,"yyyy-mm-dd")&"：延期任务 "&G6&" 项，临近到期 "&H6&" 项，高风险 "&I6&" 项。建议优先处理外部系统集成依赖、第二批次未启动任务及无明确上线日期的功能。" -> 截至 2026-09-11：延期任务 24 项，临近到期 0 项，高风险 5 项。建议优先处理外部系统集成依赖、第二批次未启动任务及无明确上线日期的功能。
A22: 相关方管理
A23: 重点管理： | D23: 当前不支持： | G23: 沟通逾期： | J23: 待升级事项：
A24: =COUNTIFS(相关方管理!$B$9:$B$108,"<>",相关方管理!$N$9:$N$108,"重点管理") -> 0 | D24: =COUNTIFS(相关方管理!$B$9:$B$108,"<>",相关方管理!$J$9:$J$108,"抵触")+COUNTIFS(相关方管理!$B$9:$B$108,"<>",相关方管理!$J$9:$J$108,"不支持") -> 0 | G24: =COUNTIFS(相关方管理!$B$9:$B$108,"<>",相关方管理!$T$9:$T$108,"<"&$B$3,相关方管理!$T$9:$T$108,"<>") -> 0 | J24: =COUNTIFS(相关方管理!$B$9:$B$108,"<>",相关方管理!$Z$9:$Z$108,"是") -> 0
A26: 风险管理
A27: 重大剩余风险 | D27: 高剩余风险 | G27: 应对逾期 | J27: 趋势上升
A28: =COUNTIFS(风险登记册!$B$9:$B$108,"<>",风险登记册!$AH$9:$AH$108,"重大") -> 0 | D28: =COUNTIFS(风险登记册!$B$9:$B$108,"<>",风险登记册!$AH$9:$AH$108,"高") -> 0 | G28: =COUNTIFS(风险应对计划!$B$5:$B$104,"<>",风险应对计划!$Q$5:$Q$104,"是") -> 0 | J28: =COUNTIFS(风险登记册!$B$9:$B$108,"<>",风险登记册!$AI$9:$AI$108,"上升") -> 0

Sheet 项目总控台账
A1: 华能交易中心港口交易平台｜项目总控台账
A2: 蓝色字段来自原开发计划；黄色字段为管理补充项；进度与延期由公式自动计算。
A3: 任务ID | B3: 一级功能 | C3: 二级功能 | D3: 三级功能 | E3: 四级功能 | F3: 批次 | G3: 总体状态 | H3: 主责人 | I3: 计划开始 | J3: 计划完成 | K3: 计划上线 | L3: 业务负责人 | M3: 业务状态 | N3: 业务开始 | O3: 业务结束 | P3: 后端负责人 | Q3: 后端状态 | R3: 后端开始 | S3: 后端结束 | T3: 前端负责人 | U3: 前端状态 | V3: 前端开始 | W3: 前端结束 | X3: 测试负责人 | Y3: 测试状态 | Z3: 测试开始 | AA3: 测试结束 | AB3: 综合进度 | AC3: 延期状态 | AD3: 当前问题/阻塞 | AE3: 备注
A4: T001 | B4: 基础数据 | C4: 车辆信息维护 | D4: 新增车辆信息 | E4: / | F4: 第一批次 | G4: =IF(OR(M4="挂起",M4="暂停",Q4="挂起",Q4="暂停",U4="挂起",U4="暂停",Y4="挂起",Y4="暂停"),"暂停","已完成") -> 已完成 | H4: =IF(L4<>"",L4,IF(P4<>"",P4,IF(T4<>"",T4,X4))) -> 郑士旺 | I4: =IF(COUNT(N4,R4,V4,Z4)=0,"",MIN(N4,R4,V4,Z4)) -> 46202 | J4: =IF(ISNUMBER(K4),K4,IF(COUNT(O4,S4,W4,AA4)=0,"",MAX(O4,S4,W4,AA4))) -> 46234 | K4: / | L4: 郑士旺 | M4: 已完成 | N4: 46202 | O4: 46206 | P4: 石军磊、刘凯 | Q4: 已完成 | R4: 46209 | S4: 46225 | T4: 贺航 | U4: 已完成 | V4: 46209 | W4: 46225 | X4: 袁丽荣 | Y4: 已完成 | Z4: 46216 | AA4: 46234 | AB4: =(IF(M4="已完成",1,IF(M4="进行中",0.5,0))*15%+IF(Q4="已完成",1,IF(Q4="进行中",0.5,0))*35%+IF(U4="已完成",1,IF(U4="进行中",0.5,0))*30%+IF(Y4="已完成",1,IF(Y4="进行中",0.5,0))*20%) -> 1 | AC4: =IF(G4="已完成","正常",IF(OR(G4="暂停",G4="挂起"),"暂停",IF(J4="","日期缺失",IF(J4<项目驾驶舱!$B$3,"已延期",IF(J4<=项目驾驶舱!$B$3+7,"临近到期","正常"))))) -> 正常 | AD4: 69 | AE4: 69
A5: T002 | B5: 基础数据 | C5: 车辆信息维护 | D5: 修改车辆信息 | E5: / | F5: 第一批次 | G5: =IF(OR(M5="挂起",M5="暂停",Q5="挂起",Q5="暂停",U5="挂起",U5="暂停",Y5="挂起",Y5="暂停"),"暂停","已完成") -> 已完成 | H5: =IF(L5<>"",L5,IF(P5<>"",P5,IF(T5<>"",T5,X5))) -> 郑士旺 | I5: =IF(COUNT(N5,R5,V5,Z5)=0,"",MIN(N5,R5,V5,Z5)) -> 46202 | J5: =IF(ISNUMBER(K5),K5,IF(COUNT(O5,S5,W5,AA5)=0,"",MAX(O5,S5,W5,AA5))) -> 46234 | K5: / | L5: 郑士旺 | M5: 已完成 | N5: 46202 | O5: 46206 | P5: 石军磊、刘凯 | Q5: 已完成 | R5: 46209 | S5: 46225 | T5: 贺航 | U5: 已完成 | V5: 46209 | W5: 46225 | X5: 袁丽荣 | Y5: 已完成 | Z5: 46216 | AA5: 46234 | AB5: =(IF(M5="已完成",1,IF(M5="进行中",0.5,0))*15%+IF(Q5="已完成",1,IF(Q5="进行中",0.5,0))*35%+IF(U5="已完成",1,IF(U5="进行中",0.5,0))*30%+IF(Y5="已完成",1,IF(Y5="进行中",0.5,0))*20%) -> 1 | AC5: =IF(G5="已完成","正常",IF(OR(G5="暂停",G5="挂起"),"暂停",IF(J5="","日期缺失",IF(J5<项目驾驶舱!$B$3,"已延期",IF(J5<=项目驾驶舱!$B$3+7,"临近到期","正常"))))) -> 正常 | AD5: 69 | AE5: 69
A6: T003 | B6: 基础数据 | C6: 车辆信息维护 | D6: 删除车辆信息 | E6: / | F6: 第一批次 | G6: =IF(OR(M6="挂起",M6="暂停",Q6="挂起",Q6="暂停",U6="挂起",U6="暂停",Y6="挂起",Y6="暂停"),"暂停","已完成") -> 已完成 | H6: =IF(L6<>"",L6,IF(P6<>"",P6,IF(T6<>"",T6,X6))) -> 郑士旺 | I6: =IF(COUNT(N6,R6,V6,Z6)=0,"",MIN(N6,R6,V6,Z6)) -> 46202 | J6: =IF(ISNUMBER(K6),K6,IF(COUNT(O6,S6,W6,AA6)=0,"",MAX(O6,S6,W6,AA6))) -> 46234 | K6: / | L6: 郑士旺 | M6: 已完成 | N6: 46202 | O6: 46206 | P6: 石军磊、刘凯 | Q6: 已完成 | R6: 46209 | S6: 46225 | T6: 贺航 | U6: 已完成 | V6: 46209 | W6: 46225 | X6: 袁丽荣 | Y6: 已完成 | Z6: 46216 | AA6: 46234 | AB6: =(IF(M6="已完成",1,IF(M6="进行中",0.5,0))*15%+IF(Q6="已完成",1,IF(Q6="进行中",0.5,0))*35%+IF(U6="已完成",1,IF(U6="进行中",0.5,0))*30%+IF(Y6="已完成",1,IF(Y6="进行中",0.5,0))*20%) -> 1 | AC6: =IF(G6="已完成","正常",IF(OR(G6="暂停",G6="挂起"),"暂停",IF(J6="","日期缺失",IF(J6<项目驾驶舱!$B$3,"已延期",IF(J6<=项目驾驶舱!$B$3+7,"临近到期","正常"))))) -> 正常 | AD6: 69 | AE6: 69
A7: T004 | B7: 基础数据 | C7: 车辆信息维护 | D7: 查询展示车辆信息 | E7: / | F7: 第一批次 | G7: =IF(OR(M7="挂起",M7="暂停",Q7="挂起",Q7="暂停",U7="挂起",U7="暂停",Y7="挂起",Y7="暂停"),"暂停","已完成") -> 已完成 | H7: =IF(L7<>"",L7,IF(P7<>"",P7,IF(T7<>"",T7,X7))) -> 郑士旺 | I7: =IF(COUNT(N7,R7,V7,Z7)=0,"",MIN(N7,R7,V7,Z7)) -> 46202 | J7: =IF(ISNUMBER(K7),K7,IF(COUNT(O7,S7,W7,AA7)=0,"",MAX(O7,S7,W7,AA7))) -> 46234 | K7: / | L7: 郑士旺 | M7: 已完成 | N7: 46202 | O7: 46206 | P7: 石军磊、刘凯 | Q7: 已完成 | R7: 46209 | S7: 46225 | T7: 贺航 | U7: 已完成 | V7: 46209 | W7: 46225 | X7: 袁丽荣 | Y7: 已完成 | Z7: 46216 | AA7: 46234 | AB7: =(IF(M7="已完成",1,IF(M7="进行中",0.5,0))*15%+IF(Q7="已完成",1,IF(Q7="进行中",0.5,0))*35%+IF(U7="已完成",1,IF(U7="进行中",0.5,0))*30%+IF(Y7="已完成",1,IF(Y7="进行中",0.5,0))*20%) -> 1 | AC7: =IF(G7="已完成","正常",IF(OR(G7="暂停",G7="挂起"),"暂停",IF(J7="","日期缺失",IF(J7<项目驾驶舱!$B$3,"已延期",IF(J7<=项目驾驶舱!$B$3+7,"临近到期","正常"))))) -> 正常 | AD7: 69 | AE7: 69
A8: T005 | B8: 基础数据 | C8: 船舶信息维护 | D8: 船舶唯一性校验 | E8: / | F8: 第二批次 | G8: =IF(OR(M8="挂起",M8="暂停",Q8="挂起",Q8="暂停",U8="挂起",U8="暂停",Y8="挂起",Y8="暂停"),"暂停","已完成") -> 已完成 | H8: =IF(L8<>"",L8,IF(P8<>"",P8,IF(T8<>"",T8,X8))) -> 郑士旺 | I8: =IF(COUNT(N8,R8,V8,Z8)=0,"",MIN(N8,R8,V8,Z8)) -> 46230 | J8: =IF(ISNUMBER(K8),K8,IF(COUNT(O8,S8,W8,AA8)=0,"",MAX(O8,S8,W8,AA8))) -> 46353 | K8: / | L8: 郑士旺 | M8: 已完成 | N8: 46230 | O8: 46241 | P8: 石军磊、刘凯 | Q8: 已完成 | R8: 46307 | S8: 46339 | T8: 贺航 | U8: 已完成 | V8: 46307 | W8: 46339 | X8: 袁丽荣 | Y8: 已完成 | Z8: 46342 | AA8: 46353 | AB8: =(IF(M8="已完成",1,IF(M8="进行中",0.5,0))*15%+IF(Q8="已完成",1,IF(Q8="进行中",0.5,0))*35%+IF(U8="已完成",1,IF(U8="进行中",0.5,0))*30%+IF(Y8="已完成",1,IF(Y8="进行中",0.5,0))*20%) -> 1 | AC8: =IF(G8="已完成","正常",IF(OR(G8="暂停",G8="挂起"),"暂停",IF(J8="","日期缺失",IF(J8<项目驾驶舱!$B$3,"已延期",IF(J8<=项目驾驶舱!$B$3+7,"临近到期","正常"))))) -> 正常 | AD8: 69 | AE8: 69
A9: T006 | B9: 基础数据 | C9: 收费标准信息维护 | D9: 优化收费标准（装卸费）新增 | E9: / | F9: 第一批次 | G9: =IF(OR(M9="挂起",M9="暂停",Q9="挂起",Q9="暂停",U9="挂起",U9="暂停",Y9="挂起",Y9="暂停"),"暂停","已完成") -> 已完成 | H9: =IF(L9<>"",L9,IF(P9<>"",P9,IF(T9<>"",T9,X9))) -> 郑士旺 | I9: =IF(COUNT(N9,R9,V9,Z9)=0,"",MIN(N9,R9,V9,Z9)) -> 46202 | J9: =IF(ISNUMBER(K9),K9,IF(COUNT(O9,S9,W9,AA9)=0,"",MAX(O9,S9,W9,AA9))) -> 46224 | K9: 46224 | L9: 郑士旺 | M9: 已完成 | N9: 46202 | O9: 46206 | P9: 石军磊、刘凯 | Q9: 已完成 | R9: 46209 | S9: 46227 | T9: 贺航 | U9: 已完成 | V9: 46209 | W9: 46227 | X9: 袁丽荣 | Y9: 已完成 | Z9: 46216 | AA9: 46234 | AB9: =(IF(M9="已完成",1,IF(M9="进行中",0.5,0))*15%+IF(Q9="已完成",1,IF(Q9="进行中",0.5,0))*35%+IF(U9="已完成",1,IF(U9="进行中",0.5,0))*30%+IF(Y9="已完成",1,IF(Y9="进行中",0.5,0))*20%) -> 1 | AC9: =IF(G9="已完成","正常",IF(OR(G9="暂停",G9="挂起"),"暂停",IF(J9="","日期缺失",IF(J9<项目驾驶舱!$B$3,"已延期",IF(J9<=项目驾驶舱!$B$3+7,"临近到期","正常"))))) -> 正常 | AD9: 69 | AE9: 69
A10: T007 | B10: 基础数据 | C10: 收费标准信息维护 | D10: 优化收费标准（装卸费）编辑 | E10: / | F10: 第一批次 | G10: =IF(OR(M10="挂起",M10="暂停",Q10="挂起",Q10="暂停",U10="挂起",U10="暂停",Y10="挂起",Y10="暂停"),"暂停","已完成") -> 已完成 | H10: =IF(L10<>"",L10,IF(P10<>"",P10,IF(T10<>"",T10,X10))) -> 郑士旺 | I10: =IF(COUNT(N10,R10,V10,Z10)=0,"",MIN(N10,R10,V10,Z10)) -> 46202 | J10: =IF(ISNUMBER(K10),K10,IF(COUNT(O10,S10,W10,AA10)=0,"",MAX(O10,S10,W10,AA10))) -> 46224 | K10: 46224 | L10: 郑士旺 | M10: 已完成 | N10: 46202 | O10: 46206 | P10: 石军磊、刘凯 | Q10: 已完成 | R10: 46209 | S10: 46227 | T10: 贺航 | U10: 已完成 | V10: 46209 | W10: 46227 | X10: 袁丽荣 | Y10: 已完成 | Z10: 46216 | AA10: 46234 | AB10: =(IF(M10="已完成",1,IF(M10="进行中",0.5,0))*15%+IF(Q10="已完成",1,IF(Q10="进行中",0.5,0))*35%+IF(U10="已完成",1,IF(U10="进行中",0.5,0))*30%+IF(Y10="已完成",1,IF(Y10="进行中",0.5,0))*20%) -> 1 | AC10: =IF(G10="已完成","正常",IF(OR(G10="暂停",G10="挂起"),"暂停",IF(J10="","日期缺失",IF(J10<项目驾驶舱!$B$3,"已延期",IF(J10<=项目驾驶舱!$B$3+7,"临近到期","正常"))))) -> 正常 | AD10: 69 | AE10: 69
A11: T008 | B11: 基础数据 | C11: 收费标准信息维护 | D11: 优化收费标准（装卸费）详情 | E11: / | F11: 第一批次 | G11: =IF(OR(M11="挂起",M11="暂停",Q11="挂起",Q11="暂停",U11="挂起",U11="暂停",Y11="挂起",Y11="暂停"),"暂停","已完成") -> 已完成 | H11: =IF(L11<>"",L11,IF(P11<>"",P11,IF(T11<>"",T11,X11))) -> 郑士旺 | I11: =IF(COUNT(N11,R11,V11,Z11)=0,"",MIN(N11,R11,V11,Z11)) -> 46202 | J11: =IF(ISNUMBER(K11),K11,IF(COUNT(O11,S11,W11,AA11)=0,"",MAX(O11,S11,W11,AA11))) -> 46224 | K11: 46224 | L11: 郑士旺 | M11: 已完成 | N11: 46202 | O11: 46206 | P11: 石军磊、刘凯 | Q11: 已完成 | R11: 46209 | S11: 46227 | T11: 贺航 | U11: 已完成 | V11: 46209 | W11: 46227 | X11: 袁丽荣 | Y11: 已完成 | Z11: 46216 | AA11: 46234 | AB11: =(IF(M11="已完成",1,IF(M11="进行中",0.5,0))*15%+IF(Q11="已完成",1,IF(Q11="进行中",0.5,0))*35%+IF(U11="已完成",1,IF(U11="进行中",0.5,0))*30%+IF(Y11="已完成",1,IF(Y11="进行中",0.5,0))*20%) -> 1 | AC11: =IF(G11="已完成","正常",IF(OR(G11="暂停",G11="挂起"),"暂停",IF(J11="","日期缺失",IF(J11<项目驾驶舱!$B$3,"已延期",IF(J11<=项目驾驶舱!$B$3+7,"临近到期","正常"))))) -> 正常 | AD11: 69 | AE11: 69
A12: T009 | B12: 基础数据 | C12: 采样方式信息维护 | D12: 优化采样方式新增 | E12: / | F12: 第一批次 | G12: =IF(OR(M12="挂起",M12="暂停",Q12="挂起",Q12="暂停",U12="挂起",U12="暂停",Y12="挂起",Y12="暂停"),"暂停","已完成") -> 已完成 | H12: =IF(L12<>"",L12,IF(P12<>"",P12,IF(T12<>"",T12,X12))) -> 郑士旺 | I12: =IF(COUNT(N12,R12,V12,Z12)=0,"",MIN(N12,R12,V12,Z12)) -> 46202 | J12: =IF(ISNUMBER(K12),K12,IF(COUNT(O12,S12,W12,AA12)=0,"",MAX(O12,S12,W12,AA12))) -> 46224 | K12: 46224 | L12: 郑士旺 | M12: 已完成 | N12: 46202 | O12: 46206 | P12: 石军磊、刘凯 | Q12: 已完成 | R12: 46209 | S12: 46227 | T12: 贺航 | U12: 已完成 | V12: 46209 | W12: 46227 | X12: 袁丽荣 | Y12: 已完成 | Z12: 46216 | AA12: 46234 | AB12: =(IF(M12="已完成",1,IF(M12="进行中",0.5,0))*15%+IF(Q12="已完成",1,IF(Q12="进行中",0.5,0))*35%+IF(U12="已完成",1,IF(U12="进行中",0.5,0))*30%+IF(Y12="已完成",1,IF(Y12="进行中",0.5,0))*20%) -> 1 | AC12: =IF(G12="已完成","正常",IF(OR(G12="暂停",G12="挂起"),"暂停",IF(J12="","日期缺失",IF(J12<项目驾驶舱!$B$3,"已延期",IF(J12<=项目驾驶舱!$B$3+7,"临近到期","正常"))))) -> 正常 | AD12: 69 | AE12: 69
A13: T010 | B13: 基础数据 | C13: 采样方式信息维护 | D13: 优化采样方式编辑 | E13: / | F13: 第一批次 | G13: =IF(OR(M13="挂起",M13="暂停",Q13="挂起",Q13="暂停",U13="挂起",U13="暂停",Y13="挂起",Y13="暂停"),"暂停","已完成") -> 已完成 | H13: =IF(L13<>"",L13,IF(P13<>"",P13,IF(T13<>"",T13,X13))) -> 郑士旺 | I13: =IF(COUNT(N13,R13,V13,Z13)=0,"",MIN(N13,R13,V13,Z13)) -> 46202 | J13: =IF(ISNUMBER(K13),K13,IF(COUNT(O13,S13,W13,AA13)=0,"",MAX(O13,S13,W13,AA13))) -> 46224 | K13: 46224 | L13: 郑士旺 | M13: 已完成 | N13: 46202 | O13: 46206 | P13: 石军磊、刘凯 | Q13: 已完成 | R13: 46209 | S13: 46227 | T13: 贺航 | U13: 已完成 | V13: 46209 | W13: 46227 | X13: 袁丽荣 | Y13: 已完成 | Z13: 46216 | AA13: 46234 | AB13: =(IF(M13="已完成",1,IF(M13="进行中",0.5,0))*15%+IF(Q13="已完成",1,IF(Q13="进行中",0.5,0))*35%+IF(U13="已完成",1,IF(U13="进行中",0.5,0))*30%+IF(Y13="已完成",1,IF(Y13="进行中",0.5,0))*20%) -> 1 | AC13: =IF(G13="已完成","正常",IF(OR(G13="暂停",G13="挂起"),"暂停",IF(J13="","日期缺失",IF(J13<项目驾驶舱!$B$3,"已延期",IF(J13<=项目驾驶舱!$B$3+7,"临近到期","正常"))))) -> 正常 | AD13: 69 | AE13: 69
A14: T011 | B14: 网上营业厅 | C14: 交易中心报单信息展示及应单入口 | D14: 获取报单数据及展示 | E14: / | F14: 第一批次 | G14: =IF(OR(M14="挂起",M14="暂停",Q14="挂起",Q14="暂停",U14="挂起",U14="暂停",Y14="挂起",Y14="暂停"),"暂停","已完成") -> 已完成 | H14: =IF(L14<>"",L14,IF(P14<>"",P14,IF(T14<>"",T14,X14))) -> 郑士旺 | I14: =IF(COUNT(N14,R14,V14,Z14)=0,"",MIN(N14,R14,V14,Z14)) -> 46202 | J14: =IF(ISNUMBER(K14),K14,IF(COUNT(O14,S14,W14,AA14)=0,"",MAX(O14,S14,W14,AA14))) -> 46224 | K14: 46224 | L14: 郑士旺 | M14: 已完成 | N14: 46202 | O14: 46206 | P14: 石军磊、刘凯 | Q14: 已完成 | R14: 46209 | S14: 46227 | T14: 贺航 | U14: 已完成 | V14: 46209 | W14: 46225 | X14: 袁丽荣 | Y14: 已完成 | Z14: 46216 | AA14: 46234 | AB14: =(IF(M14="已完成",1,IF(M14="进行中",0.5,0))*15%+IF(Q14="已完成",1,IF(Q14="进行中",0.5,0))*35%+IF(U14="已完成",1,IF(U14="进行中",0.5,0))*30%+IF(Y14="已完成",1,IF(Y14="进行中",0.5,0))*20%) -> 1 | AC14: =IF(G14="已完成","正常",IF(OR(G14="暂停",G14="挂起"),"暂停",IF(J14="","日期缺失",IF(J14<项目驾驶舱!$B$3,"已延期",IF(J14<=项目驾驶舱!$B$3+7,"临近到期","正常"))))) -> 正常 | AD14: 69 | AE14: 69
A15: T012 | B15: 网上营业厅 | C15: 交易中心报单信息展示及应单入口 | D15: 应单入口 | E15: / | F15: 第一批次 | G15: =IF(OR(M15="挂起",M15="暂停",Q15="挂起",Q15="暂停",U15="挂起",U15="暂停",Y15="挂起",Y15="暂停"),"暂停","已完成") -> 已完成 | H15: =IF(L15<>"",L15,IF(P15<>"",P15,IF(T15<>"",T15,X15))) -> 郑士旺 | I15: =IF(COUNT(N15,R15,V15,Z15)=0,"",MIN(N15,R15,V15,Z15)) -> 46202 | J15: =IF(ISNUMBER(K15),K15,IF(COUNT(O15,S15,W15,AA15)=0,"",MAX(O15,S15,W15,AA15))) -> 46224 | K15: 46224 | L15: 郑士旺 | M15: 已完成 | N15: 46202 | O15: 46206 | P15: 石军磊、刘凯 | Q15: 已完成 | R15: 46209 | S15: 46227 | T15: 贺航 | U15: 已完成 | V15: 46209 | W15: 46225 | X15: 袁丽荣 | Y15: 已完成 | Z15: 46216 | AA15: 46234 | AB15: =(IF(M15="已完成",1,IF(M15="进行中",0.5,0))*15%+IF(Q15="已完成",1,IF(Q15="进行中",0.5,0))*35%+IF(U15="已完成",1,IF(U15="进行中",0.5,0))*30%+IF(Y15="已完成",1,IF(Y15="进行中",0.5,0))*20%) -> 1 | AC15: =IF(G15="已完成","正常",IF(OR(G15="暂停",G15="挂起"),"暂停",IF(J15="","日期缺失",IF(J15<项目驾驶舱!$B$3,"已延期",IF(J15<=项目驾驶舱!$B$3+7,"临近到期","正常"))))) -> 正常 | AD15: 69 | AE15: 69
A16: T013 | B16: 网上营业厅 | C16: 结算条款管理 | D16: 新增结算条款 | E16: / | F16: 第二批次 | G16: =IF(OR(M16="挂起",M16="暂停",Q16="挂起",Q16="暂停",U16="挂起",U16="暂停",Y16="挂起",Y16="暂停"),"暂停","进行中") -> 进行中 | H16: =IF(L16<>"",L16,IF(P16<>"",P16,IF(T16<>"",T16,X16))) -> 郑士旺 | I16: =IF(COUNT(N16,R16,V16,Z16)=0,"",MIN(N16,R16,V16,Z16)) -> 46223 | J16: =IF(ISNUMBER(K16),K16,IF(COUNT(O16,S16,W16,AA16)=0,"",MAX(O16,S16,W16,AA16))) -> 46318 | L16: 郑士旺 | M16: 已完成 | N16: 46223 | O16: 46227 | P16: 石军磊、刘凯 | Q16: 进行中 | R16: 46272 | S16: 46279 | T16: 贺航 | U16: 进行中 | V16: 46272 | W16: 46279 | X16: 袁丽荣 | Y16: 未开始 | Z16: 46307 | AA16: 46318 | AB16: =(IF(M16="已完成",1,IF(M16="进行中",0.5,0))*15%+IF(Q16="已完成",1,IF(Q16="进行中",0.5,0))*35%+IF(U16="已完成",1,IF(U16="进行中",0.5,0))*30%+IF(Y16="已完成",1,IF(Y16="进行中",0.5,0))*20%) -> 0.475 | AC16: =IF(G16="已完成","正常",IF(OR(G16="暂停",G16="挂起"),"暂停",IF(J16="","日期缺失",IF(J16<项目驾驶舱!$B$3,"已延期",IF(J16<=项目驾驶舱!$B$3+7,"临近到期","正常"))))) -> 正常 | AD16: 69 | AE16: 69
A17: T014 | B17: 网上营业厅 | C17: 结算条款管理 | D17: 结算条款审批 | E17: / | F17: 第二批次 | G17: =IF(OR(M17="挂起",M17="暂停",Q17="挂起",Q17="暂停",U17="挂起",U17="暂停",Y17="挂起",Y17="暂停"),"暂停","进行中") -> 进行中 | H17: =IF(L17<>"",L17,IF(P17<>"",P17,IF(T17<>"",T17,X17))) -> 郑士旺 | I17: =IF(COUNT(N17,R17,V17,Z17)=0,"",MIN(N17,R17,V17,Z17)) -> 46223 | J17: =IF(ISNUMBER(K17),K17,IF(COUNT(O17,S17,W17,AA17)=0,"",MAX(O17,S17,W17,AA17))) -> 46318 | L17: 郑士旺 | M17: 已完成 | N17: 46223 | O17: 46227 | P17: 石军磊、刘凯 | Q17: 进行中 | R17: 46272 | S17: 46279 | T17: 贺航 | U17: 进行中 | V17: 46272 | W17: 46279 | X17: 袁丽荣 | Y17: 未开始 | Z17: 46307 | AA17: 46318 | AB17: =(IF(M17="已完成",1,IF(M17="进行中",0.5,0))*15%+IF(Q17="已完成",1,IF(Q17="进行中",0.5,0))*35%+IF(U17="已完成",1,IF(U17="进行中",0.5,0))*30%+IF(Y17="已完成",1,IF(Y17="进行中",0.5,0))*20%) -> 0.475 | AC17: =IF(G17="已完成","正常",IF(OR(G17="暂停",G17="挂起"),"暂停",IF(J17="","日期缺失",IF(J17<项目驾驶舱!$B$3,"已延期",IF(J17<=项目驾驶舱!$B$3+7,"临近到期","正常"))))) -> 正常 | AD17: 69 | AE17: 69
A18: T015 | B18: 网上营业厅 | C18: 结算条款管理 | D18: 修改结算条款 | E18: / | F18: 第二批次 | G18: =IF(OR(M18="挂起",M18="暂停",Q18="挂起",Q18="暂停",U18="挂起",U18="暂停",Y18="挂起",Y18="暂停"),"暂停","进行中") -> 进行中 | H18: =IF(L18<>"",L18,IF(P18<>"",P18,IF(T18<>"",T18,X18))) -> 郑士旺 | I18: =IF(COUNT(N18,R18,V18,Z18)=0,"",MIN(N18,R18,V18,Z18)) -> 46223 | J18: =IF(ISNUMBER(K18),K18,IF(COUNT(O18,S18,W18,AA18)=0,"",MAX(O18,S18,W18,AA18))) -> 46318 | L18: 郑士旺 | M18: 已完成 | N18: 46223 | O18: 46227 | P18: 石军磊、刘凯 | Q18: 进行中 | R18: 46272 | S18: 46279 | T18: 贺航 | U18: 进行中 | V18: 46272 | W18: 46279 | X18: 袁丽荣 | Y18: 未开始 | Z18: 46307 | AA18: 46318 | AB18: =(IF(M18="已完成",1,IF(M18="进行中",0.5,0))*15%+IF(Q18="已完成",1,IF(Q18="进行中",0.5,0))*35%+IF(U18="已完成",1,IF(U18="进行中",0.5,0))*30%+IF(Y18="已完成",1,IF(Y18="进行中",0.5,0))*20%) -> 0.475 | AC18: =IF(G18="已完成","正常",IF(OR(G18="暂停",G18="挂起"),"暂停",IF(J18="","日期缺失",IF(J18<项目驾驶舱!$B$3,"已延期",IF(J18<=项目驾驶舱!$B$3+7,"临近到期","正常"))))) -> 正常 | AD18: 69 | AE18: 69
A19: T016 | B19: 网上营业厅 | C19: 结算条款管理 | D19: 删除结算条款 | E19: / | F19: 第二批次 | G19: =IF(OR(M19="挂起",M19="暂停",Q19="挂起",Q19="暂停",U19="挂起",U19="暂停",Y19="挂起",Y19="暂停"),"暂停","进行中") -> 进行中 | H19: =IF(L19<>"",L19,IF(P19<>"",P19,IF(T19<>"",T19,X19))) -> 郑士旺 | I19: =IF(COUNT(N19,R19,V19,Z19)=0,"",MIN(N19,R19,V19,Z19)) -> 46223 | J19: =IF(ISNUMBER(K19),K19,IF(COUNT(O19,S19,W19,AA19)=0,"",MAX(O19,S19,W19,AA19))) -> 46318 | L19: 郑士旺 | M19: 已完成 | N19: 46223 | O19: 46227 | P19: 石军磊、刘凯 | Q19: 进行中 | R19: 46272 | S19: 46279 | T19: 贺航 | U19: 进行中 | V19: 46272 | W19: 46279 | X19: 袁丽荣 | Y19: 未开始 | Z19: 46307 | AA19: 46318 | AB19: =(IF(M19="已完成",1,IF(M19="进行中",0.5,0))*15%+IF(Q19="已完成",1,IF(Q19="进行中",0.5,0))*35%+IF(U19="已完成",1,IF(U19="进行中",0.5,0))*30%+IF(Y19="已完成",1,IF(Y19="进行中",0.5,0))*20%) -> 0.475 | AC19: =IF(G19="已完成","正常",IF(OR(G19="暂停",G19="挂起"),"暂停",IF(J19="","日期缺失",IF(J19<项目驾驶舱!$B$3,"已延期",IF(J19<=项目驾驶舱!$B$3+7,"临近到期","正常"))))) -> 正常 | AD19: 69 | AE19: 69
A20: T017 | B20: 网上营业厅 | C20: 结算条款管理 | D20: 查询展示结算条款 | E20: / | F20: 第二批次 | G20: =IF(OR(M20="挂起",M20="暂停",Q20="挂起",Q20="暂停",U20="挂起",U20="暂停",Y20="挂起",Y20="暂停"),"暂停","进行中") -> 进行中 | H20: =IF(L20<>"",L20,IF(P20<>"",P20,IF(T20<>"",T20,X20))) -> 郑士旺 | I20: =IF(COUNT(N20,R20,V20,Z20)=0,"",MIN(N20,R20,V20,Z20)) -> 46223 | J20: =IF(ISNUMBER(K20),K20,IF(COUNT(O20,S20,W20,AA20)=0,"",MAX(O20,S20,W20,AA20))) -> 46318 | L20: 郑士旺 | M20: 已完成 | N20: 46223 | O20: 46227 | P20: 石军磊、刘凯 | Q20: 进行中 | R20: 46272 | S20: 46279 | T20: 贺航 | U20: 进行中 | V20: 46272 | W20: 46279 | X20: 袁丽荣 | Y20: 未开始 | Z20: 46307 | AA20: 46318 | AB20: =(IF(M20="已完成",1,IF(M20="进行中",0.5,0))*15%+IF(Q20="已完成",1,IF(Q20="进行中",0.5,0))*35%+IF(U20="已完成",1,IF(U20="进行中",0.5,0))*30%+IF(Y20="已完成",1,IF(Y20="进行中",0.5,0))*20%) -> 0.475 | AC20: =IF(G20="已完成","正常",IF(OR(G20="暂停",G20="挂起"),"暂停",IF(J20="","日期缺失",IF(J20<项目驾驶舱!$B$3,"已延期",IF(J20<=项目驾驶舱!$B$3+7,"临近到期","正常"))))) -> 正常 | AD20: 69 | AE20: 69
A21: T018 | B21: 网上营业厅 | C21: 结算条款管理 | D21: 结算条款推送法务系统 | E21: / | F21: 第二批次 | G21: =IF(OR(M21="挂起",M21="暂停",Q21="挂起",Q21="暂停",U21="挂起",U21="暂停",Y21="挂起",Y21="暂停"),"暂停","未开始") -> 未开始 | H21: =IF(L21<>"",L21,IF(P21<>"",P21,IF(T21<>"",T21,X21))) -> 郑士旺 | I21: =IF(COUNT(N21,R21,V21,Z21)=0,"",MIN(N21,R21,V21,Z21)) -> 46223 | J21: =IF(ISNUMBER(K21),K21,IF(COUNT(O21,S21,W21,AA21)=0,"",MAX(O21,S21,W21,AA21))) -> 46318 | L21: 郑士旺 | M21: 未开始 | N21: 46223 | O21: 46227 | P21: 石军磊、刘凯 | Q21: 未开始 | R21: 46272 | S21: 46304 | T21: 贺航 | U21: 未开始 | V21: 46272 | W21: 46304 | X21: 袁丽荣 | Y21: 未开始 | Z21: 46307 | AA21: 46318 | AB21: =(IF(M21="已完成",1,IF(M21="进行中",0.5,0))*15%+IF(Q21="已完成",1,IF(Q21="进行中",0.5,0))*35%+IF(U21="已完成",1,IF(U21="进行中",0.5,0))*30%+IF(Y21="已完成",1,IF(Y21="进行中",0.5,0))*20%) -> 0 | AC21: =IF(G21="已完成","正常",IF(OR(G21="暂停",G21="挂起"),"暂停",IF(J21="","日期缺失",IF(J21<项目驾驶舱!$B$3,"已延期",IF(J21<=项目驾驶舱!$B$3+7,"临近到期","正常"))))) -> 正常 | AD21: 69 | AE21: 69
A22: T019 | B22: 网上营业厅 | C22: 卸船作业 | D22: 卸船计划 | E22: 对接卸船计划 | F22: 第二批次 | G22: =IF(OR(M22="挂起",M22="暂停",Q22="挂起",Q22="暂停",U22="挂起",U22="暂停",Y22="挂起",Y22="暂停"),"暂停","进行中") -> 进行中 | H22: =IF(L22<>"",L22,IF(P22<>"",P22,IF(T22<>"",T22,X22))) -> 郑士旺 | I22: =IF(COUNT(N22,R22,V22,Z22)=0,"",MIN(N22,R22,V22,Z22)) -> 46230 | J22: =IF(ISNUMBER(K22),K22,IF(COUNT(O22,S22,W22,AA22)=0,"",MAX(O22,S22,W22,AA22))) -> 46353 | L22: 郑士旺 | M22: 已完成 | N22: 46230 | O22: 46241 | P22: 石军磊、刘凯 | Q22: 未开始 | R22: 46307 | S22: 46339 | T22: 贺航 | U22: 未开始 | V22: 46307 | W22: 46339 | X22: 袁丽荣 | Y22: 未开始 | Z22: 46342 | AA22: 46353 | AB22: =(IF(M22="已完成",1,IF(M22="进行中",0.5,0))*15%+IF(Q22="已完成",1,IF(Q22="进行中",0.5,0))*35%+IF(U22="已完成",1,IF(U22="进行中",0.5,0))*30%+IF(Y22="已完成",1,IF(Y22="进行中",0.5,0))*20%) -> 0.15 | AC22: =IF(G22="已完成","正常",IF(OR(G22="暂停",G22="挂起"),"暂停",IF(J22="","日期缺失",IF(J22<项目驾驶舱!$B$3,"已延期",IF(J22<=项目驾驶舱!$B$3+7,"临近到期","正常"))))) -> 正常 | AD22: 69 | AE22: 69
A23: T020 | B23: 网上营业厅 | C23: 卸船作业 | D23: 卸船计划 | E23: 查询卸车计划 | F23: 第二批次 | G23: =IF(OR(M23="挂起",M23="暂停",Q23="挂起",Q23="暂停",U23="挂起",U23="暂停",Y23="挂起",Y23="暂停"),"暂停","进行中") -> 进行中 | H23: =IF(L23<>"",L23,IF(P23<>"",P23,IF(T23<>"",T23,X23))) -> 郑士旺 | I23: =IF(COUNT(N23,R23,V23,Z23)=0,"",MIN(N23,R23,V23,Z23)) -> 46230 | J23: =IF(ISNUMBER(K23),K23,IF(COUNT(O23,S23,W23,AA23)=0,"",MAX(O23,S23,W23,AA23))) -> 46353 | L23: 郑士旺 | M23: 已完成 | N23: 46230 | O23: 46241 | P23: 石军磊、刘凯 | Q23: 已完成 | R23: 46266 | S23: 46272 | T23: 贺航 | U23: 已完成 | V23: 46266 | W23: 46272 | X23: 袁丽荣 | Y23: 进行中 | Z23: 46342 | AA23: 46353 | AB23: =(IF(M23="已完成",1,IF(M23="进行中",0.5,0))*15%+IF(Q23="已完成",1,IF(Q23="进行中",0.5,0))*35%+IF(U23="已完成",1,IF(U23="进行中",0.5,0))*30%+IF(Y23="已完成",1,IF(Y23="进行中",0.5,0))*20%) -> 0.9 | AC23: =IF(G23="已完成","正常",IF(OR(G23="暂停",G23="挂起"),"暂停",IF(J23="","日期缺失",IF(J23<项目驾驶舱!$B$3,"已延期",IF(J23<=项目驾驶舱!$B$3+7,"临近到期","正常"))))) -> 正常 | AD23: 69 | AE23: 69
A24: T021 | B24: 网上营业厅 | C24: 卸船作业 | D24: 卸船计划 | E24: 外部客户确认 | F24: 第二批次 | G24: =IF(OR(M24="挂起",M24="暂停",Q24="挂起",Q24="暂停",U24="挂起",U24="暂停",Y24="挂起",Y24="暂停"),"暂停","进行中") -> 进行中 | H24: =IF(L24<>"",L24,IF(P24<>"",P24,IF(T24<>"",T24,X24))) -> 郑士旺 | I24: =IF(COUNT(N24,R24,V24,Z24)=0,"",MIN(N24,R24,V24,Z24)) -> 46230 | J24: =IF(ISNUMBER(K24),K24,IF(COUNT(O24,S24,W24,AA24)=0,"",MAX(O24,S24,W24,AA24))) -> 46353 | L24: 郑士旺 | M24: 已完成 | N24: 46230 | O24: 46241 | P24: 石军磊、刘凯 | Q24: 已完成 | R24: 46266 | S24: 46272 | T24: 贺航 | U24: 已完成 | V24: 46266 | W24: 46272 | X24: 袁丽荣 | Y24: 进行中 | Z24: 46342 | AA24: 46353 | AB24: =(IF(M24="已完成",1,IF(M24="进行中",0.5,0))*15%+IF(Q24="已完成",1,IF(Q24="进行中",0.5,0))*35%+IF(U24="已完成",1,IF(U24="进行中",0.5,0))*30%+IF(Y24="已完成",1,IF(Y24="进行中",0.5,0))*20%) -> 0.9 | AC24: =IF(G24="已完成","正常",IF(OR(G24="暂停",G24="挂起"),"暂停",IF(J24="","日期缺失",IF(J24<项目驾驶舱!$B$3,"已延期",IF(J24<=项目驾驶舱!$B$3+7,"临近到期","正常"))))) -> 正常 | AD24: 69 | AE24: 69
A25: T022 | B25: 网上营业厅 | C25: 卸船作业 | D25: 卸船作业信息管理 | E25: 对接卸船作业信息 | F25: 第二批次 | G25: =IF(OR(M25="挂起",M25="暂停",Q25="挂起",Q25="暂停",U25="挂起",U25="暂停",Y25="挂起",Y25="暂停"),"暂停","未开始") -> 未开始 | H25: =IF(L25<>"",L25,IF(P25<>"",P25,IF(T25<>"",T25,X25))) -> 郑士旺 | I25: =IF(COUNT(N25,R25,V25,Z25)=0,"",MIN(N25,R25,V25,Z25)) -> 46230 | J25: =IF(ISNUMBER(K25),K25,IF(COUNT(O25,S25,W25,AA25)=0,"",MAX(O25,S25,W25,AA25))) -> 46353 | L25: 郑士旺 | M25: 未开始 | N25: 46230 | O25: 46241 | P25: 石军磊、刘凯 | Q25: 未开始 | R25: 46307 | S25: 46339 | T25: 贺航 | U25: 未开始 | V25: 46307 | W25: 46339 | X25: 袁丽荣 | Y25: 未开始 | Z25: 46342 | AA25: 46353 | AB25: =(IF(M25="已完成",1,IF(M25="进行中",0.5,0))*15%+IF(Q25="已完成",1,IF(Q25="进行中",0.5,0))*35%+IF(U25="已完成",1,IF(U25="进行中",0.5,0))*30%+IF(Y25="已完成",1,IF(Y25="进行中",0.5,0))*20%) -> 0 | AC25: =IF(G25="已完成","正常",IF(OR(G25="暂停",G25="挂起"),"暂停",IF(J25="","日期缺失",IF(J25<项目驾驶舱!$B$3,"已延期",IF(J25<=项目驾驶舱!$B$3+7,"临近到期","正常"))))) -> 正常 | AD25: 69 | AE25: 69
A26: T023 | B26: 网上营业厅 | C26: 卸船作业 | D26: 卸船作业信息管理 | E26: 查询卸船作业信息 | F26: 第二批次 | G26: =IF(OR(M26="挂起",M26="暂停",Q26="挂起",Q26="暂停",U26="挂起",U26="暂停",Y26="挂起",Y26="暂停"),"暂停","未开始") -> 未开始 | H26: =IF(L26<>"",L26,IF(P26<>"",P26,IF(T26<>"",T26,X26))) -> 郑士旺 | I26: =IF(COUNT(N26,R26,V26,Z26)=0,"",MIN(N26,R26,V26,Z26)) -> 46230 | J26: =IF(ISNUMBER(K26),K26,IF(COUNT(O26,S26,W26,AA26)=0,"",MAX(O26,S26,W26,AA26))) -> 46353 | L26: 郑士旺 | M26: 未开始 | N26: 46230 | O26: 46241 | P26: 石军磊、刘凯 | Q26: 未开始 | R26: 46307 | S26: 46339 | T26: 贺航 | U26: 未开始 | V26: 46307 | W26: 46339 | X26: 袁丽荣 | Y26: 未开始 | Z26: 46342 | AA26: 46353 | AB26: =(IF(M26="已完成",1,IF(M26="进行中",0.5,0))*15%+IF(Q26="已完成",1,IF(Q26="进行中",0.5,0))*35%+IF(U26="已完成",1,IF(U26="进行中",0.5,0))*30%+IF(Y26="已完成",1,IF(Y26="进行中",0.5,0))*20%) -> 0 | AC26: =IF(G26="已完成","正常",IF(OR(G26="暂停",G26="挂起"),"暂停",IF(J26="","日期缺失",IF(J26<项目驾驶舱!$B$3,"已延期",IF(J26<=项目驾驶舱!$B$3+7,"临近到期","正常"))))) -> 正常 | AD26: 69 | AE26: 69
A27: T024 | B27: 网上营业厅 | C27: 卸船作业 | D27: 卸船查询 | E27: 卸船查询列表 | F27: 第二批次 | G27: =IF(OR(M27="挂起",M27="暂停",Q27="挂起",Q27="暂停",U27="挂起",U27="暂停",Y27="挂起",Y27="暂停"),"暂停","未开始") -> 未开始 | H27: =IF(L27<>"",L27,IF(P27<>"",P27,IF(T27<>"",T27,X27))) -> 郑士旺 | I27: =IF(COUNT(N27,R27,V27,Z27)=0,"",MIN(N27,R27,V27,Z27)) -> 46230 | J27: =IF(ISNUMBER(K27),K27,IF(COUNT(O27,S27,W27,AA27)=0,"",MAX(O27,S27,W27,AA27))) -> 46353 | L27: 郑士旺 | M27: 未开始 | N27: 46230 | O27: 46241 | P27: 石军磊、刘凯 | Q27: 未开始 | R27: 46307 | S27: 46339 | T27: 贺航 | U27: 未开始 | V27: 46307 | W27: 46339 | X27: 袁丽荣 | Y27: 未开始 | Z27: 46342 | AA27: 46353 | AB27: =(IF(M27="已完成",1,IF(M27="进行中",0.5,0))*15%+IF(Q27="已完成",1,IF(Q27="进行中",0.5,0))*35%+IF(U27="已完成",1,IF(U27="进行中",0.5,0))*30%+IF(Y27="已完成",1,IF(Y27="进行中",0.5,0))*20%) -> 0 | AC27: =IF(G27="已完成","正常",IF(OR(G27="暂停",G27="挂起"),"暂停",IF(J27="","日期缺失",IF(J27<项目驾驶舱!$B$3,"已延期",IF(J27<=项目驾驶舱!$B$3+7,"临近到期","正常"))))) -> 正常 | AD27: 69 | AE27: 69
A28: T025 | B28: 网上营业厅 | C28: 卸船作业 | D28: 卸船查询 | E28: 卸船查询详情 | F28: 第二批次 | G28: =IF(OR(M28="挂起",M28="暂停",Q28="挂起",Q28="暂停",U28="挂起",U28="暂停",Y28="挂起",Y28="暂停"),"暂停","未开始") -> 未开始 | H28: =IF(L28<>"",L28,IF(P28<>"",P28,IF(T28<>"",T28,X28))) -> 郑士旺 | I28: =IF(COUNT(N28,R28,V28,Z28)=0,"",MIN(N28,R28,V28,Z28)) -> 46230 | J28: =IF(ISNUMBER(K28),K28,IF(COUNT(O28,S28,W28,AA28)=0,"",MAX(O28,S28,W28,AA28))) -> 46261 | K28: 46261 | L28: 郑士旺 | M28: 未开始 | N28: 46230 | O28: 46241 | P28: 石军磊、刘凯 | Q28: 未开始 | R28: 46307 | S28: 46339 | T28: 贺航 | U28: 未开始 | V28: 46307 | W28: 46339 | X28: 袁丽荣 | Y28: 未开始 | Z28: 46342 | AA28: 46353 | AB28: =(IF(M28="已完成",1,IF(M28="进行中",0.5,0))*15%+IF(Q28="已完成",1,IF(Q28="进行中",0.5,0))*35%+IF(U28="已完成",1,IF(U28="进行中",0.5,0))*30%+IF(Y28="已完成",1,IF(Y28="进行中",0.5,0))*20%) -> 0 | AC28: =IF(G28="已完成","正常",IF(OR(G28="暂停",G28="挂起"),"暂停",IF(J28="","日期缺失",IF(J28<项目驾驶舱!$B$3,"已延期",IF(J28<=项目驾驶舱!$B$3+7,"临近到期","正常"))))) -> 已延期 | AD28: 69 | AE28: 69
A29: T026 | B29: 网上营业厅 | C29: 卸船作业 | D29: 卸船作业委托 | E29: 创建卸船作业委托信息 | F29: 第二批次 | G29: =IF(OR(M29="挂起",M29="暂停",Q29="挂起",Q29="暂停",U29="挂起",U29="暂停",Y29="挂起",Y29="暂停"),"暂停","进行中") -> 进行中 | H29: =IF(L29<>"",L29,IF(P29<>"",P29,IF(T29<>"",T29,X29))) -> 郑士旺 | I29: =IF(COUNT(N29,R29,V29,Z29)=0,"",MIN(N29,R29,V29,Z29)) -> 46230 | J29: =IF(ISNUMBER(K29),K29,IF(COUNT(O29,S29,W29,AA29)=0,"",MAX(O29,S29,W29,AA29))) -> 46261 | K29: 46261 | L29: 郑士旺 | M29: 已完成 | N29: 46230 | O29: 46241 | P29: 石军磊、刘凯 | Q29: 已完成 | R29: 46266 | S29: 46272 | T29: 贺航 | U29: 已完成 | V29: 46266 | W29: 46272 | X29: 袁丽荣 | Y29: 进行中 | Z29: 46342 | AA29: 46353 | AB29: =(IF(M29="已完成",1,IF(M29="进行中",0.5,0))*15%+IF(Q29="已完成",1,IF(Q29="进行中",0.5,0))*35%+IF(U29="已完成",1,IF(U29="进行中",0.5,0))*30%+IF(Y29="已完成",1,IF(Y29="进行中",0.5,0))*20%) -> 0.9 | AC29: =IF(G29="已完成","正常",IF(OR(G29="暂停",G29="挂起"),"暂停",IF(J29="","日期缺失",IF(J29<项目驾驶舱!$B$3,"已延期",IF(J29<=项目驾驶舱!$B$3+7,"临近到期","正常"))))) -> 已延期 | AD29: 69 | AE29: 69
A30: T027 | B30: 网上营业厅 | C30: 卸船作业 | D30: 卸船作业委托 | E30: 修改卸船作业委托信息 | F30: 第二批次 | G30: =IF(OR(M30="挂起",M30="暂停",Q30="挂起",Q30="暂停",U30="挂起",U30="暂停",Y30="挂起",Y30="暂停"),"暂停","进行中") -> 进行中 | H30: =IF(L30<>"",L30,IF(P30<>"",P30,IF(T30<>"",T30,X30))) -> 郑士旺 | I30: =IF(COUNT(N30,R30,V30,Z30)=0,"",MIN(N30,R30,V30,Z30)) -> 46230 | J30: =IF(ISNUMBER(K30),K30,IF(COUNT(O30,S30,W30,AA30)=0,"",MAX(O30,S30,W30,AA30))) -> 46261 | K30: 46261 | L30: 郑士旺 | M30: 已完成 | N30: 46230 | O30: 46241 | P30: 石军磊、刘凯 | Q30: 已完成 | R30: 46266 | S30: 46272 | T30: 贺航 | U30: 已完成 | V30: 46266 | W30: 46272 | X30: 袁丽荣 | Y30: 进行中 | Z30: 46342 | AA30: 46353 | AB30: =(IF(M30="已完成",1,IF(M30="进行中",0.5,0))*15%+IF(Q30="已完成",1,IF(Q30="进行中",0.5,0))*35%+IF(U30="已完成",1,IF(U30="进行中",0.5,0))*30%+IF(Y30="已完成",1,IF(Y30="进行中",0.5,0))*20%) -> 0.9 | AC30: =IF(G30="已完成","正常",IF(OR(G30="暂停",G30="挂起"),"暂停",IF(J30="","日期缺失",IF(J30<项目驾驶舱!$B$3,"已延期",IF(J30<=项目驾驶舱!$B$3+7,"临近到期","正常"))))) -> 已延期 | AD30: 69 | AE30: 69
A31: T028 | B31: 网上营业厅 | C31: 卸船作业 | D31: 卸船作业委托 | E31: 作废卸船作业委托信息 | F31: 第二批次 | G31: =IF(OR(M31="挂起",M31="暂停",Q31="挂起",Q31="暂停",U31="挂起",U31="暂停",Y31="挂起",Y31="暂停"),"暂停","进行中") -> 进行中 | H31: =IF(L31<>"",L31,IF(P31<>"",P31,IF(T31<>"",T31,X31))) -> 郑士旺 | I31: =IF(COUNT(N31,R31,V31,Z31)=0,"",MIN(N31,R31,V31,Z31)) -> 46230 | J31: =IF(ISNUMBER(K31),K31,IF(COUNT(O31,S31,W31,AA31)=0,"",MAX(O31,S31,W31,AA31))) -> 46261 | K31: 46261 | L31: 郑士旺 | M31: 进行中 | N31: 46230 | O31: 46241 | P31: 石军磊、刘凯 | Q31: 未开始 | R31: 46307 | S31: 46339 | T31: 贺航 | U31: 未开始 | V31: 46307 | W31: 46339 | X31: 袁丽荣 | Y31: 未开始 | Z31: 46342 | AA31: 46353 | AB31: =(IF(M31="已完成",1,IF(M31="进行中",0.5,0))*15%+IF(Q31="已完成",1,IF(Q31="进行中",0.5,0))*35%+IF(U31="已完成",1,IF(U31="进行中",0.5,0))*30%+IF(Y31="已完成",1,IF(Y31="进行中",0.5,0))*20%) -> 0.075 | AC31: =IF(G31="已完成","正常",IF(OR(G31="暂停",G31="挂起"),"暂停",IF(J31="","日期缺失",IF(J31<项目驾驶舱!$B$3,"已延期",IF(J31<=项目驾驶舱!$B$3+7,"临近到期","正常"))))) -> 已延期 | AD31: 69 | AE31: 69
A32: T029 | B32: 网上营业厅 | C32: 卸船作业 | D32: 卸船作业委托 | E32: 推送卸船作业委托信息 | F32: 第二批次 | G32: =IF(OR(M32="挂起",M32="暂停",Q32="挂起",Q32="暂停",U32="挂起",U32="暂停",Y32="挂起",Y32="暂停"),"暂停","进行中") -> 进行中 | H32: =IF(L32<>"",L32,IF(P32<>"",P32,IF(T32<>"",T32,X32))) -> 郑士旺 | I32: =IF(COUNT(N32,R32,V32,Z32)=0,"",MIN(N32,R32,V32,Z32)) -> 46230 | J32: =IF(ISNUMBER(K32),K32,IF(COUNT(O32,S32,W32,AA32)=0,"",MAX(O32,S32,W32,AA32))) -> 46261 | K32: 46261 | L32: 郑士旺 | M32: 进行中 | N32: 46230 | O32: 46241 | P32: 石军磊、刘凯 | Q32: 未开始 | R32: 46307 | S32: 46339 | T32: 贺航 | U32: 未开始 | V32: 46307 | W32: 46339 | X32: 袁丽荣 | Y32: 未开始 | Z32: 46342 | AA32: 46353 | AB32: =(IF(M32="已完成",1,IF(M32="进行中",0.5,0))*15%+IF(Q32="已完成",1,IF(Q32="进行中",0.5,0))*35%+IF(U32="已完成",1,IF(U32="进行中",0.5,0))*30%+IF(Y32="已完成",1,IF(Y32="进行中",0.5,0))*20%) -> 0.075 | AC32: =IF(G32="已完成","正常",IF(OR(G32="暂停",G32="挂起"),"暂停",IF(J32="","日期缺失",IF(J32<项目驾驶舱!$B$3,"已延期",IF(J32<=项目驾驶舱!$B$3+7,"临近到期","正常"))))) -> 已延期 | AD32: 69 | AE32: 69
A33: T030 | B33: 网上营业厅 | C33: 卸船作业 | D33: 卸船作业委托 | E33: 查询卸船作业委托信息 | F33: 第二批次 | G33: =IF(OR(M33="挂起",M33="暂停",Q33="挂起",Q33="暂停",U33="挂起",U33="暂停",Y33="挂起",Y33="暂停"),"暂停","进行中") -> 进行中 | H33: =IF(L33<>"",L33,IF(P33<>"",P33,IF(T33<>"",T33,X33))) -> 郑士旺 | I33: =IF(COUNT(N33,R33,V33,Z33)=0,"",MIN(N33,R33,V33,Z33)) -> 46230 | J33: =IF(ISNUMBER(K33),K33,IF(COUNT(O33,S33,W33,AA33)=0,"",MAX(O33,S33,W33,AA33))) -> 46261 | K33: 46261 | L33: 郑士旺 | M33: 已完成 | N33: 46230 | O33: 46241 | P33: 石军磊、刘凯 | Q33: 已完成 | R33: 46266 | S33: 46272 | T33: 贺航 | U33: 已完成 | V33: 46266 | W33: 46272 | X33: 袁丽荣 | Y33: 进行中 | Z33: 46342 | AA33: 46353 | AB33: =(IF(M33="已完成",1,IF(M33="进行中",0.5,0))*15%+IF(Q33="已完成",1,IF(Q33="进行中",0.5,0))*35%+IF(U33="已完成",1,IF(U33="进行中",0.5,0))*30%+IF(Y33="已完成",1,IF(Y33="进行中",0.5,0))*20%) -> 0.9 | AC33: =IF(G33="已完成","正常",IF(OR(G33="暂停",G33="挂起"),"暂停",IF(J33="","日期缺失",IF(J33<项目驾驶舱!$B$3,"已延期",IF(J33<=项目驾驶舱!$B$3+7,"临近到期","正常"))))) -> 已延期 | AD33: 69 | AE33: 69
A34: T031 | B34: 网上营业厅 | C34: 卸船作业 | D34: 外轮转内贸业务 | E34: 创建外轮转内贸业务信息 | F34: 第二批次 | G34: =IF(OR(M34="挂起",M34="暂停",Q34="挂起",Q34="暂停",U34="挂起",U34="暂停",Y34="挂起",Y34="暂停"),"暂停","未开始") -> 未开始 | H34: =IF(L34<>"",L34,IF(P34<>"",P34,IF(T34<>"",T34,X34))) -> 郑士旺 | I34: =IF(COUNT(N34,R34,V34,Z34)=0,"",MIN(N34,R34,V34,Z34)) -> 46230 | J34: =IF(ISNUMBER(K34),K34,IF(COUNT(O34,S34,W34,AA34)=0,"",MAX(O34,S34,W34,AA34))) -> 46353 | L34: 郑士旺 | M34: 未开始 | N34: 46230 | O34: 46241 | P34: 常浩 | Q34: 未开始 | R34: 46286 | S34: 46289 | T34: 常浩 | U34: 未开始 | V34: 46286 | W34: 46289 | X34: 袁丽荣 | Y34: 未开始 | Z34: 46342 | AA34: 46353 | AB34: =(IF(M34="已完成",1,IF(M34="进行中",0.5,0))*15%+IF(Q34="已完成",1,IF(Q34="进行中",0.5,0))*35%+IF(U34="已完成",1,IF(U34="进行中",0.5,0))*30%+IF(Y34="已完成",1,IF(Y34="进行中",0.5,0))*20%) -> 0 | AC34: =IF(G34="已完成","正常",IF(OR(G34="暂停",G34="挂起"),"暂停",IF(J34="","日期缺失",IF(J34<项目驾驶舱!$B$3,"已延期",IF(J34<=项目驾驶舱!$B$3+7,"临近到期","正常"))))) -> 正常 | AD34: 69 | AE34: 69
A35: T032 | B35: 网上营业厅 | C35: 卸船作业 | D35: 外轮转内贸业务 | E35: 作废外轮转内贸业务信息 | F35: 第二批次 | G35: =IF(OR(M35="挂起",M35="暂停",Q35="挂起",Q35="暂停",U35="挂起",U35="暂停",Y35="挂起",Y35="暂停"),"暂停","未开始") -> 未开始 | H35: =IF(L35<>"",L35,IF(P35<>"",P35,IF(T35<>"",T35,X35))) -> 郑士旺 | I35: =IF(COUNT(N35,R35,V35,Z35)=0,"",MIN(N35,R35,V35,Z35)) -> 46230 | J35: =IF(ISNUMBER(K35),K35,IF(COUNT(O35,S35,W35,AA35)=0,"",MAX(O35,S35,W35,AA35))) -> 46353 | L35: 郑士旺 | M35: 未开始 | N35: 46230 | O35: 46241 | P35: 常浩 | Q35: 未开始 | R35: 46286 | S35: 46289 | T35: 常浩 | U35: 未开始 | V35: 46286 | W35: 46289 | X35: 袁丽荣 | Y35: 未开始 | Z35: 46342 | AA35: 46353 | AB35: =(IF(M35="已完成",1,IF(M35="进行中",0.5,0))*15%+IF(Q35="已完成",1,IF(Q35="进行中",0.5,0))*35%+IF(U35="已完成",1,IF(U35="进行中",0.5,0))*30%+IF(Y35="已完成",1,IF(Y35="进行中",0.5,0))*20%) -> 0 | AC35: =IF(G35="已完成","正常",IF(OR(G35="暂停",G35="挂起"),"暂停",IF(J35="","日期缺失",IF(J35<项目驾驶舱!$B$3,"已延期",IF(J35<=项目驾驶舱!$B$3+7,"临近到期","正常"))))) -> 正常 | AD35: 69 | AE35: 69
A36: T033 | B36: 网上营业厅 | C36: 卸船作业 | D36: 外轮转内贸业务 | E36: 查询外轮转内贸业务信息 | F36: 第二批次 | G36: =IF(OR(M36="挂起",M36="暂停",Q36="挂起",Q36="暂停",U36="挂起",U36="暂停",Y36="挂起",Y36="暂停"),"暂停","未开始") -> 未开始 | H36: =IF(L36<>"",L36,IF(P36<>"",P36,IF(T36<>"",T36,X36))) -> 郑士旺 | I36: =IF(COUNT(N36,R36,V36,Z36)=0,"",MIN(N36,R36,V36,Z36)) -> 46230 | J36: =IF(ISNUMBER(K36),K36,IF(COUNT(O36,S36,W36,AA36)=0,"",MAX(O36,S36,W36,AA36))) -> 46353 | L36: 郑士旺 | M36: 未开始 | N36: 46230 | O36: 46241 | P36: 常浩 | Q36: 未开始 | R36: 46286 | S36: 46289 | T36: 常浩 | U36: 未开始 | V36: 46286 | W36: 46289 | X36: 袁丽荣 | Y36: 未开始 | Z36: 46342 | AA36: 46353 | AB36: =(IF(M36="已完成",1,IF(M36="进行中",0.5,0))*15%+IF(Q36="已完成",1,IF(Q36="进行中",0.5,0))*35%+IF(U36="已完成",1,IF(U36="进行中",0.5,0))*30%+IF(Y36="已完成",1,IF(Y36="进行中",0.5,0))*20%) -> 0 | AC36: =IF(G36="已完成","正常",IF(OR(G36="暂停",G36="挂起"),"暂停",IF(J36="","日期缺失",IF(J36<项目驾驶舱!$B$3,"已延期",IF(J36<=项目驾驶舱!$B$3+7,"临近到期","正常"))))) -> 正常 | AD36: 69 | AE36: 69
A37: T034 | B37: 网上营业厅 | C37: 卸船作业 | D37: 船舶靠泊通知单 | E37: 新增船舶靠泊通知单 | F37: 第二批次 | G37: =IF(OR(M37="挂起",M37="暂停",Q37="挂起",Q37="暂停",U37="挂起",U37="暂停",Y37="挂起",Y37="暂停"),"暂停","进行中") -> 进行中 | H37: =IF(L37<>"",L37,IF(P37<>"",P37,IF(T37<>"",T37,X37))) -> 郑士旺 | I37: =IF(COUNT(N37,R37,V37,Z37)=0,"",MIN(N37,R37,V37,Z37)) -> 46230 | J37: =IF(ISNUMBER(K37),K37,IF(COUNT(O37,S37,W37,AA37)=0,"",MAX(O37,S37,W37,AA37))) -> 46353 | L37: 郑士旺 | M37: 已完成 | N37: 46230 | O37: 46241 | P37: 石军磊、刘凯 | Q37: 已完成 | R37: 46266 | S37: 46272 | T37: 贺航 | U37: 已完成 | V37: 46266 | W37: 46272 | X37: 袁丽荣 | Y37: 进行中 | Z37: 46342 | AA37: 46353 | AB37: =(IF(M37="已完成",1,IF(M37="进行中",0.5,0))*15%+IF(Q37="已完成",1,IF(Q37="进行中",0.5,0))*35%+IF(U37="已完成",1,IF(U37="进行中",0.5,0))*30%+IF(Y37="已完成",1,IF(Y37="进行中",0.5,0))*20%) -> 0.9 | AC37: =IF(G37="已完成","正常",IF(OR(G37="暂停",G37="挂起"),"暂停",IF(J37="","日期缺失",IF(J37<项目驾驶舱!$B$3,"已延期",IF(J37<=项目驾驶舱!$B$3+7,"临近到期","正常"))))) -> 正常 | AD37: 69 | AE37: 69
A38: T035 | B38: 网上营业厅 | C38: 卸船作业 | D38: 船舶靠泊通知单 | E38: 审批船舶靠泊通知单 | F38: 第二批次 | G38: =IF(OR(M38="挂起",M38="暂停",Q38="挂起",Q38="暂停",U38="挂起",U38="暂停",Y38="挂起",Y38="暂停"),"暂停","进行中") -> 进行中 | H38: =IF(L38<>"",L38,IF(P38<>"",P38,IF(T38<>"",T38,X38))) -> 郑士旺 | I38: =IF(COUNT(N38,R38,V38,Z38)=0,"",MIN(N38,R38,V38,Z38)) -> 46230 | J38: =IF(ISNUMBER(K38),K38,IF(COUNT(O38,S38,W38,AA38)=0,"",MAX(O38,S38,W38,AA38))) -> 46353 | L38: 郑士旺 | M38: 已完成 | N38: 46230 | O38: 46241 | P38: 石军磊、刘凯 | Q38: 已完成 | R38: 46266 | S38: 46272 | T38: 贺航 | U38: 已完成 | V38: 46266 | W38: 46272 | X38: 袁丽荣 | Y38: 进行中 | Z38: 46342 | AA38: 46353 | AB38: =(IF(M38="已完成",1,IF(M38="进行中",0.5,0))*15%+IF(Q38="已完成",1,IF(Q38="进行中",0.5,0))*35%+IF(U38="已完成",1,IF(U38="进行中",0.5,0))*30%+IF(Y38="已完成",1,IF(Y38="进行中",0.5,0))*20%) -> 0.9 | AC38: =IF(G38="已完成","正常",IF(OR(G38="暂停",G38="挂起"),"暂停",IF(J38="","日期缺失",IF(J38<项目驾驶舱!$B$3,"已延期",IF(J38<=项目驾驶舱!$B$3+7,"临近到期","正常"))))) -> 正常 | AD38: 69 | AE38: 69
A39: T036 | B39: 网上营业厅 | C39: 卸船作业 | D39: 船舶靠泊通知单 | E39: 查询船舶靠泊通知单 | F39: 第二批次 | G39: =IF(OR(M39="挂起",M39="暂停",Q39="挂起",Q39="暂停",U39="挂起",U39="暂停",Y39="挂起",Y39="暂停"),"暂停","进行中") -> 进行中 | H39: =IF(L39<>"",L39,IF(P39<>"",P39,IF(T39<>"",T39,X39))) -> 郑士旺 | I39: =IF(COUNT(N39,R39,V39,Z39)=0,"",MIN(N39,R39,V39,Z39)) -> 46230 | J39: =IF(ISNUMBER(K39),K39,IF(COUNT(O39,S39,W39,AA39)=0,"",MAX(O39,S39,W39,AA39))) -> 46353 | L39: 郑士旺 | M39: 已完成 | N39: 46230 | O39: 46241 | P39: 石军磊、刘凯 | Q39: 已完成 | R39: 46266 | S39: 46272 | T39: 贺航 | U39: 已完成 | V39: 46266 | W39: 46272 | X39: 袁丽荣 | Y39: 进行中 | Z39: 46342 | AA39: 46353 | AB39: =(IF(M39="已完成",1,IF(M39="进行中",0.5,0))*15%+IF(Q39="已完成",1,IF(Q39="进行中",0.5,0))*35%+IF(U39="已完成",1,IF(U39="进行中",0.5,0))*30%+IF(Y39="已完成",1,IF(Y39="进行中",0.5,0))*20%) -> 0.9 | AC39: =IF(G39="已完成","正常",IF(OR(G39="暂停",G39="挂起"),"暂停",IF(J39="","日期缺失",IF(J39<项目驾驶舱!$B$3,"已延期",IF(J39<=项目驾驶舱!$B$3+7,"临近到期","正常"))))) -> 正常 | AD39: 69 | AE39: 69
A40: T037 | B40: 网上营业厅 | C40: 卸车流程跟踪 | D40: 创建卸车流程 | E40: / | F40: 第一批次 | G40: =IF(OR(M40="挂起",M40="暂停",Q40="挂起",Q40="暂停",U40="挂起",U40="暂停",Y40="挂起",Y40="暂停"),"暂停","已完成") -> 已完成 | H40: =IF(L40<>"",L40,IF(P40<>"",P40,IF(T40<>"",T40,X40))) -> 郑士旺 | I40: =IF(COUNT(N40,R40,V40,Z40)=0,"",MIN(N40,R40,V40,Z40)) -> 46209 | J40: =IF(ISNUMBER(K40),K40,IF(COUNT(O40,S40,W40,AA40)=0,"",MAX(O40,S40,W40,AA40))) -> 46261 | K40: 46261 | L40: 郑士旺 | M40: 已完成 | N40: 46209 | O40: 46213 | P40: 石军磊、刘凯 | Q40: 已完成 | R40: 46230 | S40: 46262 | T40: 贺航 | U40: 已完成 | V40: 46230 | W40: 46262 | X40: 袁丽荣 | Y40: 已完成 | Z40: 46253 | AA40: 46269 | AB40: =(IF(M40="已完成",1,IF(M40="进行中",0.5,0))*15%+IF(Q40="已完成",1,IF(Q40="进行中",0.5,0))*35%+IF(U40="已完成",1,IF(U40="进行中",0.5,0))*30%+IF(Y40="已完成",1,IF(Y40="进行中",0.5,0))*20%) -> 1 | AC40: =IF(G40="已完成","正常",IF(OR(G40="暂停",G40="挂起"),"暂停",IF(J40="","日期缺失",IF(J40<项目驾驶舱!$B$3,"已延期",IF(J40<=项目驾驶舱!$B$3+7,"临近到期","正常"))))) -> 正常 | AD40: 69 | AE40: 69
A41: T038 | B41: 网上营业厅 | C41: 卸车流程跟踪 | D41: 查询卸车流程 | E41: / | F41: 第一批次 | G41: =IF(OR(M41="挂起",M41="暂停",Q41="挂起",Q41="暂停",U41="挂起",U41="暂停",Y41="挂起",Y41="暂停"),"暂停","已完成") -> 已完成 | H41: =IF(L41<>"",L41,IF(P41<>"",P41,IF(T41<>"",T41,X41))) -> 郑士旺 | I41: =IF(COUNT(N41,R41,V41,Z41)=0,"",MIN(N41,R41,V41,Z41)) -> 46209 | J41: =IF(ISNUMBER(K41),K41,IF(COUNT(O41,S41,W41,AA41)=0,"",MAX(O41,S41,W41,AA41))) -> 46261 | K41: 46261 | L41: 郑士旺 | M41: 已完成 | N41: 46209 | O41: 46213 | P41: 石军磊、刘凯 | Q41: 已完成 | R41: 46230 | S41: 46262 | T41: 贺航 | U41: 已完成 | V41: 46230 | W41: 46262 | X41: 袁丽荣 | Y41: 已完成 | Z41: 46253 | AA41: 46269 | AB41: =(IF(M41="已完成",1,IF(M41="进行中",0.5,0))*15%+IF(Q41="已完成",1,IF(Q41="进行中",0.5,0))*35%+IF(U41="已完成",1,IF(U41="进行中",0.5,0))*30%+IF(Y41="已完成",1,IF(Y41="进行中",0.5,0))*20%) -> 1 | AC41: =IF(G41="已完成","正常",IF(OR(G41="暂停",G41="挂起"),"暂停",IF(J41="","日期缺失",IF(J41<项目驾驶舱!$B$3,"已延期",IF(J41<=项目驾驶舱!$B$3+7,"临近到期","正常"))))) -> 正常 | AD41: 69 | AE41: 69
A42: T039 | B42: 网上营业厅 | C42: 卸车流程跟踪 | D42: 修改卸车流程 | E42: / | F42: 第一批次 | G42: =IF(OR(M42="挂起",M42="暂停",Q42="挂起",Q42="暂停",U42="挂起",U42="暂停",Y42="挂起",Y42="暂停"),"暂停","已完成") -> 已完成 | H42: =IF(L42<>"",L42,IF(P42<>"",P42,IF(T42<>"",T42,X42))) -> 郑士旺 | I42: =IF(COUNT(N42,R42,V42,Z42)=0,"",MIN(N42,R42,V42,Z42)) -> 46209 | J42: =IF(ISNUMBER(K42),K42,IF(COUNT(O42,S42,W42,AA42)=0,"",MAX(O42,S42,W42,AA42))) -> 46261 | K42: 46261 | L42: 郑士旺 | M42: 已完成 | N42: 46209 | O42: 46213 | P42: 石军磊、刘凯 | Q42: 已完成 | R42: 46230 | S42: 46262 | T42: 贺航 | U42: 已完成 | V42: 46230 | W42: 46262 | X42: 袁丽荣 | Y42: 已完成 | Z42: 46253 | AA42: 46269 | AB42: =(IF(M42="已完成",1,IF(M42="进行中",0.5,0))*15%+IF(Q42="已完成",1,IF(Q42="进行中",0.5,0))*35%+IF(U42="已完成",1,IF(U42="进行中",0.5,0))*30%+IF(Y42="已完成",1,IF(Y42="进行中",0.5,0))*20%) -> 1 | AC42: =IF(G42="已完成","正常",IF(OR(G42="暂停",G42="挂起"),"暂停",IF(J42="","日期缺失",IF(J42<项目驾驶舱!$B$3,"已延期",IF(J42<=项目驾驶舱!$B$3+7,"临近到期","正常"))))) -> 正常 | AD42: 69 | AE42: 69
A43: T040 | B43: 网上营业厅 | C43: 装船流程跟踪 | D43: 创建装船流程 | E43: / | F43: 第一批次 | G43: =IF(OR(M43="挂起",M43="暂停",Q43="挂起",Q43="暂停",U43="挂起",U43="暂停",Y43="挂起",Y43="暂停"),"暂停","已完成") -> 已完成 | H43: =IF(L43<>"",L43,IF(P43<>"",P43,IF(T43<>"",T43,X43))) -> 郑士旺 | I43: =IF(COUNT(N43,R43,V43,Z43)=0,"",MIN(N43,R43,V43,Z43)) -> 46209 | J43: =IF(ISNUMBER(K43),K43,IF(COUNT(O43,S43,W43,AA43)=0,"",MAX(O43,S43,W43,AA43))) -> 46261 | K43: 46261 | L43: 郑士旺 | M43: 已完成 | N43: 46209 | O43: 46213 | P43: 石军磊、刘凯 | Q43: 已完成 | R43: 46230 | S43: 46262 | T43: 贺航 | U43: 已完成 | V43: 46230 | W43: 46262 | X43: 袁丽荣 | Y43: 已完成 | Z43: 46253 | AA43: 46269 | AB43: =(IF(M43="已完成",1,IF(M43="进行中",0.5,0))*15%+IF(Q43="已完成",1,IF(Q43="进行中",0.5,0))*35%+IF(U43="已完成",1,IF(U43="进行中",0.5,0))*30%+IF(Y43="已完成",1,IF(Y43="进行中",0.5,0))*20%) -> 1 | AC43: =IF(G43="已完成","正常",IF(OR(G43="暂停",G43="挂起"),"暂停",IF(J43="","日期缺失",IF(J43<项目驾驶舱!$B$3,"已延期",IF(J43<=项目驾驶舱!$B$3+7,"临近到期","正常"))))) -> 正常 | AD43: 69 | AE43: 69
A44: T041 | B44: 网上营业厅 | C44: 装船流程跟踪 | D44: 查询装船流程 | E44: / | F44: 第一批次 | G44: =IF(OR(M44="挂起",M44="暂停",Q44="挂起",Q44="暂停",U44="挂起",U44="暂停",Y44="挂起",Y44="暂停"),"暂停","已完成") -> 已完成 | H44: =IF(L44<>"",L44,IF(P44<>"",P44,IF(T44<>"",T44,X44))) -> 郑士旺 | I44: =IF(COUNT(N44,R44,V44,Z44)=0,"",MIN(N44,R44,V44,Z44)) -> 46209 | J44: =IF(ISNUMBER(K44),K44,IF(COUNT(O44,S44,W44,AA44)=0,"",MAX(O44,S44,W44,AA44))) -> 46261 | K44: 46261 | L44: 郑士旺 | M44: 已完成 | N44: 46209 | O44: 46213 | P44: 石军磊、刘凯 | Q44: 已完成 | R44: 46230 | S44: 46262 | T44: 贺航 | U44: 已完成 | V44: 46230 | W44: 46262 | X44: 袁丽荣 | Y44: 已完成 | Z44: 46253 | AA44: 46269 | AB44: =(IF(M44="已完成",1,IF(M44="进行中",0.5,0))*15%+IF(Q44="已完成",1,IF(Q44="进行中",0.5,0))*35%+IF(U44="已完成",1,IF(U44="进行中",0.5,0))*30%+IF(Y44="已完成",1,IF(Y44="进行中",0.5,0))*20%) -> 1 | AC44: =IF(G44="已完成","正常",IF(OR(G44="暂停",G44="挂起"),"暂停",IF(J44="","日期缺失",IF(J44<项目驾驶舱!$B$3,"已延期",IF(J44<=项目驾驶舱!$B$3+7,"临近到期","正常"))))) -> 正常 | AD44: 69 | AE44: 69
A45: T042 | B45: 网上营业厅 | C45: 装船流程跟踪 | D45: 修改装船流程 | E45: / | F45: 第一批次 | G45: =IF(OR(M45="挂起",M45="暂停",Q45="挂起",Q45="暂停",U45="挂起",U45="暂停",Y45="挂起",Y45="暂停"),"暂停","已完成") -> 已完成 | H45: =IF(L45<>"",L45,IF(P45<>"",P45,IF(T45<>"",T45,X45))) -> 郑士旺 | I45: =IF(COUNT(N45,R45,V45,Z45)=0,"",MIN(N45,R45,V45,Z45)) -> 46209 | J45: =IF(ISNUMBER(K45),K45,IF(COUNT(O45,S45,W45,AA45)=0,"",MAX(O45,S45,W45,AA45))) -> 46261 | K45: 46261 | L45: 郑士旺 | M45: 已完成 | N45: 46209 | O45: 46213 | P45: 石军磊、刘凯 | Q45: 已完成 | R45: 46230 | S45: 46262 | T45: 贺航 | U45: 已完成 | V45: 46230 | W45: 46262 | X45: 袁丽荣 | Y45: 已完成 | Z45: 46253 | AA45: 46269 | AB45: =(IF(M45="已完成",1,IF(M45="进行中",0.5,0))*15%+IF(Q45="已完成",1,IF(Q45="进行中",0.5,0))*35%+IF(U45="已完成",1,IF(U45="进行中",0.5,0))*30%+IF(Y45="已完成",1,IF(Y45="进行中",0.5,0))*20%) -> 1 | AC45: =IF(G45="已完成","正常",IF(OR(G45="暂停",G45="挂起"),"暂停",IF(J45="","日期缺失",IF(J45<项目驾驶舱!$B$3,"已延期",IF(J45<=项目驾驶舱!$B$3+7,"临近到期","正常"))))) -> 正常 | AD45: 69 | AE45: 69
A46: T043 | B46: 网上营业厅 | C46: 卸船流程跟踪 | D46: 创建卸船流程 | E46: / | F46: 第二批次 | G46: =IF(OR(M46="挂起",M46="暂停",Q46="挂起",Q46="暂停",U46="挂起",U46="暂停",Y46="挂起",Y46="暂停"),"暂停","已完成") -> 已完成 | H46: =IF(L46<>"",L46,IF(P46<>"",P46,IF(T46<>"",T46,X46))) -> 郑士旺 | I46: =IF(COUNT(N46,R46,V46,Z46)=0,"",MIN(N46,R46,V46,Z46)) -> 46209 | J46: =IF(ISNUMBER(K46),K46,IF(COUNT(O46,S46,W46,AA46)=0,"",MAX(O46,S46,W46,AA46))) -> 46269 | L46: 郑士旺 | M46: 已完成 | N46: 46209 | O46: 46213 | P46: 石军磊、刘凯 | Q46: 已完成 | R46: 46230 | S46: 46262 | T46: 贺航 | U46: 已完成 | V46: 46230 | W46: 46262 | X46: 袁丽荣 | Y46: 已完成 | Z46: 46253 | AA46: 46269 | AB46: =(IF(M46="已完成",1,IF(M46="进行中",0.5,0))*15%+IF(Q46="已完成",1,IF(Q46="进行中",0.5,0))*35%+IF(U46="已完成",1,IF(U46="进行中",0.5,0))*30%+IF(Y46="已完成",1,IF(Y46="进行中",0.5,0))*20%) -> 1 | AC46: =IF(G46="已完成","正常",IF(OR(G46="暂停",G46="挂起"),"暂停",IF(J46="","日期缺失",IF(J46<项目驾驶舱!$B$3,"已延期",IF(J46<=项目驾驶舱!$B$3+7,"临近到期","正常"))))) -> 正常 | AD46: 69 | AE46: 69
A47: T044 | B47: 网上营业厅 | C47: 卸船流程跟踪 | D47: 查询卸船流程 | E47: / | F47: 第二批次 | G47: =IF(OR(M47="挂起",M47="暂停",Q47="挂起",Q47="暂停",U47="挂起",U47="暂停",Y47="挂起",Y47="暂停"),"暂停","已完成") -> 已完成 | H47: =IF(L47<>"",L47,IF(P47<>"",P47,IF(T47<>"",T47,X47))) -> 郑士旺 | I47: =IF(COUNT(N47,R47,V47,Z47)=0,"",MIN(N47,R47,V47,Z47)) -> 46209 | J47: =IF(ISNUMBER(K47),K47,IF(COUNT(O47,S47,W47,AA47)=0,"",MAX(O47,S47,W47,AA47))) -> 46269 | L47: 郑士旺 | M47: 已完成 | N47: 46209 | O47: 46213 | P47: 石军磊、刘凯 | Q47: 已完成 | R47: 46230 | S47: 46262 | T47: 贺航 | U47: 已完成 | V47: 46230 | W47: 46262 | X47: 袁丽荣 | Y47: 已完成 | Z47: 46253 | AA47: 46269 | AB47: =(IF(M47="已完成",1,IF(M47="进行中",0.5,0))*15%+IF(Q47="已完成",1,IF(Q47="进行中",0.5,0))*35%+IF(U47="已完成",1,IF(U47="进行中",0.5,0))*30%+IF(Y47="已完成",1,IF(Y47="进行中",0.5,0))*20%) -> 1 | AC47: =IF(G47="已完成","正常",IF(OR(G47="暂停",G47="挂起"),"暂停",IF(J47="","日期缺失",IF(J47<项目驾驶舱!$B$3,"已延期",IF(J47<=项目驾驶舱!$B$3+7,"临近到期","正常"))))) -> 正常 | AD47: 69 | AE47: 69
A48: T045 | B48: 网上营业厅 | C48: 卸船流程跟踪 | D48: 修改卸船流程 | E48: / | F48: 第二批次 | G48: =IF(OR(M48="挂起",M48="暂停",Q48="挂起",Q48="暂停",U48="挂起",U48="暂停",Y48="挂起",Y48="暂停"),"暂停","已完成") -> 已完成 | H48: =IF(L48<>"",L48,IF(P48<>"",P48,IF(T48<>"",T48,X48))) -> 郑士旺 | I48: =IF(COUNT(N48,R48,V48,Z48)=0,"",MIN(N48,R48,V48,Z48)) -> 46209 | J48: =IF(ISNUMBER(K48),K48,IF(COUNT(O48,S48,W48,AA48)=0,"",MAX(O48,S48,W48,AA48))) -> 46269 | L48: 郑士旺 | M48: 已完成 | N48: 46209 | O48: 46213 | P48: 石军磊、刘凯 | Q48: 已完成 | R48: 46230 | S48: 46262 | T48: 贺航 | U48: 已完成 | V48: 46230 | W48: 46262 | X48: 袁丽荣 | Y48: 已完成 | Z48: 46253 | AA48: 46269 | AB48: =(IF(M48="已完成",1,IF(M48="进行中",0.5,0))*15%+IF(Q48="已完成",1,IF(Q48="进行中",0.5,0))*35%+IF(U48="已完成",1,IF(U48="进行中",0.5,0))*30%+IF(Y48="已完成",1,IF(Y48="进行中",0.5,0))*20%) -> 1 | AC48: =IF(G48="已完成","正常",IF(OR(G48="暂停",G48="挂起"),"暂停",IF(J48="","日期缺失",IF(J48<项目驾驶舱!$B$3,"已延期",IF(J48<=项目驾驶舱!$B$3+7,"临近到期","正常"))))) -> 正常 | AD48: 69 | AE48: 69
A49: T046 | B49: 网上营业厅 | C49: 船舶预到（外贸） | D49: 新增船舶预到（外贸） | E49: / | F49: 第二批次 | G49: =IF(OR(M49="挂起",M49="暂停",Q49="挂起",Q49="暂停",U49="挂起",U49="暂停",Y49="挂起",Y49="暂停"),"暂停","已完成") -> 已完成 | H49: =IF(L49<>"",L49,IF(P49<>"",P49,IF(T49<>"",T49,X49))) -> 郑士旺 | I49: =IF(COUNT(N49,R49,V49,Z49)=0,"",MIN(N49,R49,V49,Z49)) -> 46230 | J49: =IF(ISNUMBER(K49),K49,IF(COUNT(O49,S49,W49,AA49)=0,"",MAX(O49,S49,W49,AA49))) -> 46353 | K49: / | L49: 郑士旺 | M49: 已完成 | N49: 46230 | O49: 46241 | P49: 石军磊、刘凯 | Q49: 已完成 | R49: 46307 | S49: 46339 | T49: 贺航 | U49: 已完成 | V49: 46307 | W49: 46339 | X49: 袁丽荣 | Y49: 已完成 | Z49: 46342 | AA49: 46353 | AB49: =(IF(M49="已完成",1,IF(M49="进行中",0.5,0))*15%+IF(Q49="已完成",1,IF(Q49="进行中",0.5,0))*35%+IF(U49="已完成",1,IF(U49="进行中",0.5,0))*30%+IF(Y49="已完成",1,IF(Y49="进行中",0.5,0))*20%) -> 1 | AC49: =IF(G49="已完成","正常",IF(OR(G49="暂停",G49="挂起"),"暂停",IF(J49="","日期缺失",IF(J49<项目驾驶舱!$B$3,"已延期",IF(J49<=项目驾驶舱!$B$3+7,"临近到期","正常"))))) -> 正常 | AD49: 69 | AE49: 69
A50: T047 | B50: 网上营业厅 | C50: 船舶预到（外贸） | D50: 退回船舶预到（外贸） | E50: / | F50: 第二批次 | G50: =IF(OR(M50="挂起",M50="暂停",Q50="挂起",Q50="暂停",U50="挂起",U50="暂停",Y50="挂起",Y50="暂停"),"暂停","未开始") -> 未开始 | H50: =IF(L50<>"",L50,IF(P50<>"",P50,IF(T50<>"",T50,X50))) -> 郑士旺 | I50: =IF(COUNT(N50,R50,V50,Z50)=0,"",MIN(N50,R50,V50,Z50)) -> 46230 | J50: =IF(ISNUMBER(K50),K50,IF(COUNT(O50,S50,W50,AA50)=0,"",MAX(O50,S50,W50,AA50))) -> 46353 | L50: 郑士旺 | M50: 未开始 | N50: 46230 | O50: 46241 | P50: 石军磊、刘凯 | Q50: 未开始 | R50: 46307 | S50: 46339 | T50: 贺航 | U50: 未开始 | V50: 46307 | W50: 46339 | X50: 袁丽荣 | Y50: 未开始 | Z50: 46342 | AA50: 46353 | AB50: =(IF(M50="已完成",1,IF(M50="进行中",0.5,0))*15%+IF(Q50="已完成",1,IF(Q50="进行中",0.5,0))*35%+IF(U50="已完成",1,IF(U50="进行中",0.5,0))*30%+IF(Y50="已完成",1,IF(Y50="进行中",0.5,0))*20%) -> 0 | AC50: =IF(G50="已完成","正常",IF(OR(G50="暂停",G50="挂起"),"暂停",IF(J50="","日期缺失",IF(J50<项目驾驶舱!$B$3,"已延期",IF(J50<=项目驾驶舱!$B$3+7,"临近到期","正常"))))) -> 正常 | AD50: 69 | AE50: 69
A51: T048 | B51: 网上营业厅 | C51: 船舶预到（内贸） | D51: 退回船舶预到（外贸） | E51: / | F51: 第二批次 | G51: =IF(OR(M51="挂起",M51="暂停",Q51="挂起",Q51="暂停",U51="挂起",U51="暂停",Y51="挂起",Y51="暂停"),"暂停","未开始") -> 未开始 | H51: =IF(L51<>"",L51,IF(P51<>"",P51,IF(T51<>"",T51,X51))) -> 郑士旺 | I51: =IF(COUNT(N51,R51,V51,Z51)=0,"",MIN(N51,R51,V51,Z51)) -> 46230 | J51: =IF(ISNUMBER(K51),K51,IF(COUNT(O51,S51,W51,AA51)=0,"",MAX(O51,S51,W51,AA51))) -> 46261 | K51: 46261 | L51: 郑士旺 | M51: 未开始 | N51: 46230 | O51: 46241 | P51: 石军磊、刘凯 | Q51: 未开始 | R51: 46307 | S51: 46339 | T51: 贺航 | U51: 未开始 | V51: 46307 | W51: 46339 | X51: 袁丽荣 | Y51: 未开始 | Z51: 46342 | AA51: 46353 | AB51: =(IF(M51="已完成",1,IF(M51="进行中",0.5,0))*15%+IF(Q51="已完成",1,IF(Q51="进行中",0.5,0))*35%+IF(U51="已完成",1,IF(U51="进行中",0.5,0))*30%+IF(Y51="已完成",1,IF(Y51="进行中",0.5,0))*20%) -> 0 | AC51: =IF(G51="已完成","正常",IF(OR(G51="暂停",G51="挂起"),"暂停",IF(J51="","日期缺失",IF(J51<项目驾驶舱!$B$3,"已延期",IF(J51<=项目驾驶舱!$B$3+7,"临近到期","正常"))))) -> 已延期 | AD51: 69 | AE51: 69
A52: T049 | B52: 网上营业厅 | C52: 采样申请（外贸） | D52: 申请采样申请（外贸） | E52: / | F52: 第二批次 | G52: =IF(OR(M52="挂起",M52="暂停",Q52="挂起",Q52="暂停",U52="挂起",U52="暂停",Y52="挂起",Y52="暂停"),"暂停","已完成") -> 已完成 | H52: =IF(L52<>"",L52,IF(P52<>"",P52,IF(T52<>"",T52,X52))) -> 郑士旺 | I52: =IF(COUNT(N52,R52,V52,Z52)=0,"",MIN(N52,R52,V52,Z52)) -> 46230 | J52: =IF(ISNUMBER(K52),K52,IF(COUNT(O52,S52,W52,AA52)=0,"",MAX(O52,S52,W52,AA52))) -> 46261 | K52: 46261 | L52: 郑士旺 | M52: 已完成 | N52: 46230 | O52: 46241 | P52: 石军磊、刘凯 | Q52: 已完成 | R52: 46307 | S52: 46339 | T52: 贺航 | U52: 已完成 | V52: 46307 | W52: 46339 | X52: 袁丽荣 | Y52: 已完成 | Z52: 46342 | AA52: 46353 | AB52: =(IF(M52="已完成",1,IF(M52="进行中",0.5,0))*15%+IF(Q52="已完成",1,IF(Q52="进行中",0.5,0))*35%+IF(U52="已完成",1,IF(U52="进行中",0.5,0))*30%+IF(Y52="已完成",1,IF(Y52="进行中",0.5,0))*20%) -> 1 | AC52: =IF(G52="已完成","正常",IF(OR(G52="暂停",G52="挂起"),"暂停",IF(J52="","日期缺失",IF(J52<项目驾驶舱!$B$3,"已延期",IF(J52<=项目驾驶舱!$B$3+7,"临近到期","正常"))))) -> 正常 | AD52: 69 | AE52: 69
A53: T050 | B53: 网上营业厅 | C53: 船舶轨迹跟踪 | D53: 维护需跟踪船舶清单 | E53: / | F53: 第一批次 | G53: =IF(OR(M53="挂起",M53="暂停",Q53="挂起",Q53="暂停",U53="挂起",U53="暂停",Y53="挂起",Y53="暂停"),"暂停","进行中") -> 进行中 | H53: =IF(L53<>"",L53,IF(P53<>"",P53,IF(T53<>"",T53,X53))) -> 郑士旺 | I53: =IF(COUNT(N53,R53,V53,Z53)=0,"",MIN(N53,R53,V53,Z53)) -> 46202 | J53: =IF(ISNUMBER(K53),K53,IF(COUNT(O53,S53,W53,AA53)=0,"",MAX(O53,S53,W53,AA53))) -> 46265 | K53: / | L53: 郑士旺 | M53: 已完成 | N53: 46202 | O53: 46206 | P53: 常浩 | Q53: 已完成 | R53: 46212 | S53: 46265 | T53: 贺航 | U53: 已完成 | V53: 46212 | W53: 46265 | X53: 袁丽荣 | Y53: 进行中 | Z53: 46216 | AA53: 46234 | AB53: =(IF(M53="已完成",1,IF(M53="进行中",0.5,0))*15%+IF(Q53="已完成",1,IF(Q53="进行中",0.5,0))*35%+IF(U53="已完成",1,IF(U53="进行中",0.5,0))*30%+IF(Y53="已完成",1,IF(Y53="进行中",0.5,0))*20%) -> 0.9 | AC53: =IF(G53="已完成","正常",IF(OR(G53="暂停",G53="挂起"),"暂停",IF(J53="","日期缺失",IF(J53<项目驾驶舱!$B$3,"已延期",IF(J53<=项目驾驶舱!$B$3+7,"临近到期","正常"))))) -> 已延期 | AD53: 69 | AE53: 69
A54: T051 | B54: 网上营业厅 | C54: 船舶轨迹跟踪 | D54: 根据船舶清单更新第三方系统推送数据船舶清单 | E54: / | F54: 第一批次 | G54: =IF(OR(M54="挂起",M54="暂停",Q54="挂起",Q54="暂停",U54="挂起",U54="暂停",Y54="挂起",Y54="暂停"),"暂停","进行中") -> 进行中 | H54: =IF(L54<>"",L54,IF(P54<>"",P54,IF(T54<>"",T54,X54))) -> 郑士旺 | I54: =IF(COUNT(N54,R54,V54,Z54)=0,"",MIN(N54,R54,V54,Z54)) -> 46202 | J54: =IF(ISNUMBER(K54),K54,IF(COUNT(O54,S54,W54,AA54)=0,"",MAX(O54,S54,W54,AA54))) -> 46261 | K54: 46261 | L54: 郑士旺 | M54: 已完成 | N54: 46202 | O54: 46206 | P54: 常浩 | Q54: 已完成 | R54: 46212 | S54: 46265 | T54: 贺航 | U54: 已完成 | V54: 46212 | W54: 46265 | X54: 袁丽荣 | Y54: 进行中 | Z54: 46216 | AA54: 46234 | AB54: =(IF(M54="已完成",1,IF(M54="进行中",0.5,0))*15%+IF(Q54="已完成",1,IF(Q54="进行中",0.5,0))*35%+IF(U54="已完成",1,IF(U54="进行中",0.5,0))*30%+IF(Y54="已完成",1,IF(Y54="进行中",0.5,0))*20%) -> 0.9 | AC54: =IF(G54="已完成","正常",IF(OR(G54="暂停",G54="挂起"),"暂停",IF(J54="","日期缺失",IF(J54<项目驾驶舱!$B$3,"已延期",IF(J54<=项目驾驶舱!$B$3+7,"临近到期","正常"))))) -> 已延期 | AD54: 69 | AE54: 69
A55: T052 | B55: 网上营业厅 | C55: 船舶轨迹跟踪 | D55: 船舶轨迹跟踪 | E55: / | F55: 第一批次 | G55: =IF(OR(M55="挂起",M55="暂停",Q55="挂起",Q55="暂停",U55="挂起",U55="暂停",Y55="挂起",Y55="暂停"),"暂停","进行中") -> 进行中 | H55: =IF(L55<>"",L55,IF(P55<>"",P55,IF(T55<>"",T55,X55))) -> 郑士旺 | I55: =IF(COUNT(N55,R55,V55,Z55)=0,"",MIN(N55,R55,V55,Z55)) -> 46202 | J55: =IF(ISNUMBER(K55),K55,IF(COUNT(O55,S55,W55,AA55)=0,"",MAX(O55,S55,W55,AA55))) -> 46261 | K55: 46261 | L55: 郑士旺 | M55: 已完成 | N55: 46202 | O55: 46206 | P55: 常浩 | Q55: 已完成 | R55: 46212 | S55: 46265 | T55: 贺航 | U55: 已完成 | V55: 46212 | W55: 46265 | X55: 袁丽荣 | Y55: 进行中 | Z55: 46216 | AA55: 46234 | AB55: =(IF(M55="已完成",1,IF(M55="进行中",0.5,0))*15%+IF(Q55="已完成",1,IF(Q55="进行中",0.5,0))*35%+IF(U55="已完成",1,IF(U55="进行中",0.5,0))*30%+IF(Y55="已完成",1,IF(Y55="进行中",0.5,0))*20%) -> 0.9 | AC55: =IF(G55="已完成","正常",IF(OR(G55="暂停",G55="挂起"),"暂停",IF(J55="","日期缺失",IF(J55<项目驾驶舱!$B$3,"已延期",IF(J55<=项目驾驶舱!$B$3+7,"临近到期","正常"))))) -> 已延期 | AD55: 69 | AE55: 69
A56: T053 | B56: 网上营业厅 | C56: 协同视览 | D56: 接入港口侧视频监控 | E56: / | F56: 第二批次 | G56: =IF(OR(M56="挂起",M56="暂停",Q56="挂起",Q56="暂停",U56="挂起",U56="暂停",Y56="挂起",Y56="暂停"),"暂停","未开始") -> 未开始 | H56: =IF(L56<>"",L56,IF(P56<>"",P56,IF(T56<>"",T56,X56))) -> 郑士旺 | I56: =IF(COUNT(N56,R56,V56,Z56)=0,"",MIN(N56,R56,V56,Z56)) -> 46223 | J56: =IF(ISNUMBER(K56),K56,IF(COUNT(O56,S56,W56,AA56)=0,"",MAX(O56,S56,W56,AA56))) -> 46224 | K56: 46224 | L56: 郑士旺 | M56: 未开始 | N56: 46223 | O56: 46227 | P56: 石军磊、刘凯 | Q56: 未开始 | R56: 46272 | S56: 46304 | T56: 贺航 | U56: 未开始 | V56: 46272 | W56: 46304 | X56: 袁丽荣 | Y56: 未开始 | Z56: 46307 | AA56: 46318 | AB56: =(IF(M56="已完成",1,IF(M56="进行中",0.5,0))*15%+IF(Q56="已完成",1,IF(Q56="进行中",0.5,0))*35%+IF(U56="已完成",1,IF(U56="进行中",0.5,0))*30%+IF(Y56="已完成",1,IF(Y56="进行中",0.5,0))*20%) -> 0 | AC56: =IF(G56="已完成","正常",IF(OR(G56="暂停",G56="挂起"),"暂停",IF(J56="","日期缺失",IF(J56<项目驾驶舱!$B$3,"已延期",IF(J56<=项目驾驶舱!$B$3+7,"临近到期","正常"))))) -> 已延期 | AD56: 69 | AE56: 69
A57: T054 | B57: 网上营业厅 | C57: 协同视览 | D57: 视频查看权限申请 | E57: / | F57: 第二批次 | G57: =IF(OR(M57="挂起",M57="暂停",Q57="挂起",Q57="暂停",U57="挂起",U57="暂停",Y57="挂起",Y57="暂停"),"暂停","未开始") -> 未开始 | H57: =IF(L57<>"",L57,IF(P57<>"",P57,IF(T57<>"",T57,X57))) -> 郑士旺 | I57: =IF(COUNT(N57,R57,V57,Z57)=0,"",MIN(N57,R57,V57,Z57)) -> 46223 | J57: =IF(ISNUMBER(K57),K57,IF(COUNT(O57,S57,W57,AA57)=0,"",MAX(O57,S57,W57,AA57))) -> 46224 | K57: 46224 | L57: 郑士旺 | M57: 未开始 | N57: 46223 | O57: 46227 | P57: 石军磊、刘凯 | Q57: 未开始 | R57: 46272 | S57: 46304 | T57: 贺航 | U57: 未开始 | V57: 46272 | W57: 46304 | X57: 袁丽荣 | Y57: 未开始 | Z57: 46307 | AA57: 46318 | AB57: =(IF(M57="已完成",1,IF(M57="进行中",0.5,0))*15%+IF(Q57="已完成",1,IF(Q57="进行中",0.5,0))*35%+IF(U57="已完成",1,IF(U57="进行中",0.5,0))*30%+IF(Y57="已完成",1,IF(Y57="进行中",0.5,0))*20%) -> 0 | AC57: =IF(G57="已完成","正常",IF(OR(G57="暂停",G57="挂起"),"暂停",IF(J57="","日期缺失",IF(J57<项目驾驶舱!$B$3,"已延期",IF(J57<=项目驾驶舱!$B$3+7,"临近到期","正常"))))) -> 已延期 | AD57: 69 | AE57: 69
A58: T055 | B58: 网上营业厅 | C58: 协同视览 | D58: 视频查看权限审批 | E58: / | F58: 第二批次 | G58: =IF(OR(M58="挂起",M58="暂停",Q58="挂起",Q58="暂停",U58="挂起",U58="暂停",Y58="挂起",Y58="暂停"),"暂停","未开始") -> 未开始 | H58: =IF(L58<>"",L58,IF(P58<>"",P58,IF(T58<>"",T58,X58))) -> 郑士旺 | I58: =IF(COUNT(N58,R58,V58,Z58)=0,"",MIN(N58,R58,V58,Z58)) -> 46223 | J58: =IF(ISNUMBER(K58),K58,IF(COUNT(O58,S58,W58,AA58)=0,"",MAX(O58,S58,W58,AA58))) -> 46224 | K58: 46224 | L58: 郑士旺 | M58: 未开始 | N58: 46223 | O58: 46227 | P58: 石军磊、刘凯 | Q58: 未开始 | R58: 46272 | S58: 46304 | T58: 贺航 | U58: 未开始 | V58: 46272 | W58: 46304 | X58: 袁丽荣 | Y58: 未开始 | Z58: 46307 | AA58: 46318 | AB58: =(IF(M58="已完成",1,IF(M58="进行中",0.5,0))*15%+IF(Q58="已完成",1,IF(Q58="进行中",0.5,0))*35%+IF(U58="已完成",1,IF(U58="进行中",0.5,0))*30%+IF(Y58="已完成",1,IF(Y58="进行中",0.5,0))*20%) -> 0 | AC58: =IF(G58="已完成","正常",IF(OR(G58="暂停",G58="挂起"),"暂停",IF(J58="","日期缺失",IF(J58<项目驾驶舱!$B$3,"已延期",IF(J58<=项目驾驶舱!$B$3+7,"临近到期","正常"))))) -> 已延期 | AD58: 69 | AE58: 69
A59: T056 | B59: 网上营业厅 | C59: 协同视览 | D59: 视频查看权限有效期控制 | E59: / | F59: 第二批次 | G59: =IF(OR(M59="挂起",M59="暂停",Q59="挂起",Q59="暂停",U59="挂起",U59="暂停",Y59="挂起",Y59="暂停"),"暂停","未开始") -> 未开始 | H59: =IF(L59<>"",L59,IF(P59<>"",P59,IF(T59<>"",T59,X59))) -> 郑士旺 | I59: =IF(COUNT(N59,R59,V59,Z59)=0,"",MIN(N59,R59,V59,Z59)) -> 46223 | J59: =IF(ISNUMBER(K59),K59,IF(COUNT(O59,S59,W59,AA59)=0,"",MAX(O59,S59,W59,AA59))) -> 46318 | L59: 郑士旺 | M59: 未开始 | N59: 46223 | O59: 46227 | P59: 石军磊、刘凯 | Q59: 未开始 | R59: 46272 | S59: 46304 | T59: 贺航 | U59: 未开始 | V59: 46272 | W59: 46304 | X59: 袁丽荣 | Y59: 未开始 | Z59: 46307 | AA59: 46318 | AB59: =(IF(M59="已完成",1,IF(M59="进行中",0.5,0))*15%+IF(Q59="已完成",1,IF(Q59="进行中",0.5,0))*35%+IF(U59="已完成",1,IF(U59="进行中",0.5,0))*30%+IF(Y59="已完成",1,IF(Y59="进行中",0.5,0))*20%) -> 0 | AC59: =IF(G59="已完成","正常",IF(OR(G59="暂停",G59="挂起"),"暂停",IF(J59="","日期缺失",IF(J59<项目驾驶舱!$B$3,"已延期",IF(J59<=项目驾驶舱!$B$3+7,"临近到期","正常"))))) -> 正常 | AD59: 69 | AE59: 69
A60: T057 | B60: 网上营业厅 | C60: 协同视览 | D60: 外网PC端视频监控查询 | E60: / | F60: 第二批次 | G60: =IF(OR(M60="挂起",M60="暂停",Q60="挂起",Q60="暂停",U60="挂起",U60="暂停",Y60="挂起",Y60="暂停"),"暂停","未开始") -> 未开始 | H60: =IF(L60<>"",L60,IF(P60<>"",P60,IF(T60<>"",T60,X60))) -> 郑士旺 | I60: =IF(COUNT(N60,R60,V60,Z60)=0,"",MIN(N60,R60,V60,Z60)) -> 46223 | J60: =IF(ISNUMBER(K60),K60,IF(COUNT(O60,S60,W60,AA60)=0,"",MAX(O60,S60,W60,AA60))) -> 46224 | K60: 46224 | L60: 郑士旺 | M60: 未开始 | N60: 46223 | O60: 46227 | P60: 石军磊、刘凯 | Q60: 未开始 | R60: 46272 | S60: 46304 | T60: 贺航 | U60: 未开始 | V60: 46272 | W60: 46304 | X60: 袁丽荣 | Y60: 未开始 | Z60: 46307 | AA60: 46318 | AB60: =(IF(M60="已完成",1,IF(M60="进行中",0.5,0))*15%+IF(Q60="已完成",1,IF(Q60="进行中",0.5,0))*35%+IF(U60="已完成",1,IF(U60="进行中",0.5,0))*30%+IF(Y60="已完成",1,IF(Y60="进行中",0.5,0))*20%) -> 0 | AC60: =IF(G60="已完成","正常",IF(OR(G60="暂停",G60="挂起"),"暂停",IF(J60="","日期缺失",IF(J60<项目驾驶舱!$B$3,"已延期",IF(J60<=项目驾驶舱!$B$3+7,"临近到期","正常"))))) -> 已延期 | AD60: 69 | AE60: 69
A61: T058 | B61: 网上营业厅 | C61: 装船计划编制及推送 | D61: OCR识别及编辑 | E61: / | F61: 第一批次 | G61: =IF(OR(M61="挂起",M61="暂停",Q61="挂起",Q61="暂停",U61="挂起",U61="暂停",Y61="挂起",Y61="暂停"),"暂停","已完成") -> 已完成 | H61: =IF(L61<>"",L61,IF(P61<>"",P61,IF(T61<>"",T61,X61))) -> 郑士旺 | I61: =IF(COUNT(N61,R61,V61,Z61)=0,"",MIN(N61,R61,V61,Z61)) -> 46195 | J61: =IF(ISNUMBER(K61),K61,IF(COUNT(O61,S61,W61,AA61)=0,"",MAX(O61,S61,W61,AA61))) -> 46224 | K61: 46224 | L61: 郑士旺 | M61: 已完成 | N61: / | O61: / | P61: 石军磊、刘凯 | Q61: 已完成 | R61: 46195 | S61: 46206 | T61: 贺航 | U61: 已完成 | V61: 46195 | W61: 46206 | X61: 袁丽荣 | Y61: 已完成 | Z61: 46202 | AA61: 46213 | AB61: =(IF(M61="已完成",1,IF(M61="进行中",0.5,0))*15%+IF(Q61="已完成",1,IF(Q61="进行中",0.5,0))*35%+IF(U61="已完成",1,IF(U61="进行中",0.5,0))*30%+IF(Y61="已完成",1,IF(Y61="进行中",0.5,0))*20%) -> 1 | AC61: =IF(G61="已完成","正常",IF(OR(G61="暂停",G61="挂起"),"暂停",IF(J61="","日期缺失",IF(J61<项目驾驶舱!$B$3,"已延期",IF(J61<=项目驾驶舱!$B$3+7,"临近到期","正常"))))) -> 正常 | AD61: 69 | AE61: 69
A62: T059 | B62: 网上营业厅 | C62: 优化装车作业信息录入 | D62: 优化新增装车作业信息 | E62: / | F62: 第一批次 | G62: =IF(OR(M62="挂起",M62="暂停",Q62="挂起",Q62="暂停",U62="挂起",U62="暂停",Y62="挂起",Y62="暂停"),"暂停","已完成") -> 已完成 | H62: =IF(L62<>"",L62,IF(P62<>"",P62,IF(T62<>"",T62,X62))) -> 郑士旺 | I62: =IF(COUNT(N62,R62,V62,Z62)=0,"",MIN(N62,R62,V62,Z62)) -> 46230 | J62: =IF(ISNUMBER(K62),K62,IF(COUNT(O62,S62,W62,AA62)=0,"",MAX(O62,S62,W62,AA62))) -> 46318 | K62: / | L62: 郑士旺 | M62: 已完成 | N62: 46230 | O62: 46241 | P62: 石军磊、刘凯 | Q62: 已完成 | R62: 46230 | S62: 46241 | T62: 贺航 | U62: 已完成 | V62: 46230 | W62: 46241 | X62: 袁丽荣 | Y62: 已完成 | Z62: 46307 | AA62: 46318 | AB62: =(IF(M62="已完成",1,IF(M62="进行中",0.5,0))*15%+IF(Q62="已完成",1,IF(Q62="进行中",0.5,0))*35%+IF(U62="已完成",1,IF(U62="进行中",0.5,0))*30%+IF(Y62="已完成",1,IF(Y62="进行中",0.5,0))*20%) -> 1 | AC62: =IF(G62="已完成","正常",IF(OR(G62="暂停",G62="挂起"),"暂停",IF(J62="","日期缺失",IF(J62<项目驾驶舱!$B$3,"已延期",IF(J62<=项目驾驶舱!$B$3+7,"临近到期","正常"))))) -> 正常 | AD62: 69 | AE62: 69
A63: T060 | B63: 网上营业厅 | C63: 货权跟踪 | D63: 货权录入 | E63: / | F63: 第一批次 | G63: =IF(OR(M63="挂起",M63="暂停",Q63="挂起",Q63="暂停",U63="挂起",U63="暂停",Y63="挂起",Y63="暂停"),"暂停","已完成") -> 已完成 | H63: =IF(L63<>"",L63,IF(P63<>"",P63,IF(T63<>"",T63,X63))) -> 郑士旺 | I63: =IF(COUNT(N63,R63,V63,Z63)=0,"",MIN(N63,R63,V63,Z63)) -> 46202 | J63: =IF(ISNUMBER(K63),K63,IF(COUNT(O63,S63,W63,AA63)=0,"",MAX(O63,S63,W63,AA63))) -> 46261 | K63: 46261 | L63: 郑士旺 | M63: 已完成 | N63: 46202 | O63: 46206 | P63: 石军磊、刘凯 | Q63: 已完成 | R63: 46209 | S63: 46227 | T63: 贺航 | U63: 已完成 | V63: 46209 | W63: 46227 | X63: 袁丽荣 | Y63: 已完成 | Z63: 46216 | AA63: 46234 | AB63: =(IF(M63="已完成",1,IF(M63="进行中",0.5,0))*15%+IF(Q63="已完成",1,IF(Q63="进行中",0.5,0))*35%+IF(U63="已完成",1,IF(U63="进行中",0.5,0))*30%+IF(Y63="已完成",1,IF(Y63="进行中",0.5,0))*20%) -> 1 | AC63: =IF(G63="已完成","正常",IF(OR(G63="暂停",G63="挂起"),"暂停",IF(J63="","日期缺失",IF(J63<项目驾驶舱!$B$3,"已延期",IF(J63<=项目驾驶舱!$B$3+7,"临近到期","正常"))))) -> 正常 | AD63: 69 | AE63: 69
A64: T061 | B64: 网上营业厅 | C64: 货权跟踪 | D64: 货权修改 | E64: / | F64: 第一批次 | G64: =IF(OR(M64="挂起",M64="暂停",Q64="挂起",Q64="暂停",U64="挂起",U64="暂停",Y64="挂起",Y64="暂停"),"暂停","已完成") -> 已完成 | H64: =IF(L64<>"",L64,IF(P64<>"",P64,IF(T64<>"",T64,X64))) -> 郑士旺 | I64: =IF(COUNT(N64,R64,V64,Z64)=0,"",MIN(N64,R64,V64,Z64)) -> 46202 | J64: =IF(ISNUMBER(K64),K64,IF(COUNT(O64,S64,W64,AA64)=0,"",MAX(O64,S64,W64,AA64))) -> 46261 | K64: 46261 | L64: 郑士旺 | M64: 已完成 | N64: 46202 | O64: 46206 | P64: 石军磊、刘凯 | Q64: 已完成 | R64: 46209 | S64: 46227 | T64: 贺航 | U64: 已完成 | V64: 46209 | W64: 46227 | X64: 袁丽荣 | Y64: 已完成 | Z64: 46216 | AA64: 46234 | AB64: =(IF(M64="已完成",1,IF(M64="进行中",0.5,0))*15%+IF(Q64="已完成",1,IF(Q64="进行中",0.5,0))*35%+IF(U64="已完成",1,IF(U64="进行中",0.5,0))*30%+IF(Y64="已完成",1,IF(Y64="进行中",0.5,0))*20%) -> 1 | AC64: =IF(G64="已完成","正常",IF(OR(G64="暂停",G64="挂起"),"暂停",IF(J64="","日期缺失",IF(J64<项目驾驶舱!$B$3,"已延期",IF(J64<=项目驾驶舱!$B$3+7,"临近到期","正常"))))) -> 正常 | AD64: 69 | AE64: 69
A65: T062 | B65: 网上营业厅 | C65: 货权跟踪 | D65: 获取查询 | E65: / | F65: 第一批次 | G65: =IF(OR(M65="挂起",M65="暂停",Q65="挂起",Q65="暂停",U65="挂起",U65="暂停",Y65="挂起",Y65="暂停"),"暂停","已完成") -> 已完成 | H65: =IF(L65<>"",L65,IF(P65<>"",P65,IF(T65<>"",T65,X65))) -> 郑士旺 | I65: =IF(COUNT(N65,R65,V65,Z65)=0,"",MIN(N65,R65,V65,Z65)) -> 46202 | J65: =IF(ISNUMBER(K65),K65,IF(COUNT(O65,S65,W65,AA65)=0,"",MAX(O65,S65,W65,AA65))) -> 46261 | K65: 46261 | L65: 郑士旺 | M65: 已完成 | N65: 46202 | O65: 46206 | P65: 石军磊、刘凯 | Q65: 已完成 | R65: 46209 | S65: 46227 | T65: 贺航 | U65: 已完成 | V65: 46209 | W65: 46227 | X65: 袁丽荣 | Y65: 已完成 | Z65: 46216 | AA65: 46234 | AB65: =(IF(M65="已完成",1,IF(M65="进行中",0.5,0))*15%+IF(Q65="已完成",1,IF(Q65="进行中",0.5,0))*35%+IF(U65="已完成",1,IF(U65="进行中",0.5,0))*30%+IF(Y65="已完成",1,IF(Y65="进行中",0.5,0))*20%) -> 1 | AC65: =IF(G65="已完成","正常",IF(OR(G65="暂停",G65="挂起"),"暂停",IF(J65="","日期缺失",IF(J65<项目驾驶舱!$B$3,"已延期",IF(J65<=项目驾驶舱!$B$3+7,"临近到期","正常"))))) -> 正常 | AD65: 69 | AE65: 69
A66: T063 | B66: 网上营业厅 | C66: 货权提醒 | D66: 卸船作业货权跟踪 | E66: / | F66: 第一批次 | G66: =IF(OR(M66="挂起",M66="暂停",Q66="挂起",Q66="暂停",U66="挂起",U66="暂停",Y66="挂起",Y66="暂停"),"暂停","已完成") -> 已完成 | H66: =IF(L66<>"",L66,IF(P66<>"",P66,IF(T66<>"",T66,X66))) -> 郑士旺 | I66: =IF(COUNT(N66,R66,V66,Z66)=0,"",MIN(N66,R66,V66,Z66)) -> 46202 | J66: =IF(ISNUMBER(K66),K66,IF(COUNT(O66,S66,W66,AA66)=0,"",MAX(O66,S66,W66,AA66))) -> 46261 | K66: 46261 | L66: 郑士旺 | M66: 已完成 | N66: 46202 | O66: 46206 | P66: 石军磊、刘凯 | Q66: 已完成 | R66: 46209 | S66: 46227 | T66: 贺航 | U66: 已完成 | V66: 46209 | W66: 46227 | X66: 袁丽荣 | Y66: 已完成 | Z66: 46216 | AA66: 46234 | AB66: =(IF(M66="已完成",1,IF(M66="进行中",0.5,0))*15%+IF(Q66="已完成",1,IF(Q66="进行中",0.5,0))*35%+IF(U66="已完成",1,IF(U66="进行中",0.5,0))*30%+IF(Y66="已完成",1,IF(Y66="进行中",0.5,0))*20%) -> 1 | AC66: =IF(G66="已完成","正常",IF(OR(G66="暂停",G66="挂起"),"暂停",IF(J66="","日期缺失",IF(J66<项目驾驶舱!$B$3,"已延期",IF(J66<=项目驾驶舱!$B$3+7,"临近到期","正常"))))) -> 正常 | AD66: 69 | AE66: 69
A67: T064 | B67: 网上营业厅 | C67: 货权提醒 | D67: 卸船作业货权跟踪 | E67: / | F67: 第一批次 | G67: =IF(OR(M67="挂起",M67="暂停",Q67="挂起",Q67="暂停",U67="挂起",U67="暂停",Y67="挂起",Y67="暂停"),"暂停","已完成") -> 已完成 | H67: =IF(L67<>"",L67,IF(P67<>"",P67,IF(T67<>"",T67,X67))) -> 郑士旺 | I67: =IF(COUNT(N67,R67,V67,Z67)=0,"",MIN(N67,R67,V67,Z67)) -> 46202 | J67: =IF(ISNUMBER(K67),K67,IF(COUNT(O67,S67,W67,AA67)=0,"",MAX(O67,S67,W67,AA67))) -> 46261 | K67: 46261 | L67: 郑士旺 | M67: 已完成 | N67: 46202 | O67: 46206 | P67: 石军磊、刘凯 | Q67: 已完成 | R67: 46209 | S67: 46227 | T67: 贺航 | U67: 已完成 | V67: 46209 | W67: 46227 | X67: 袁丽荣 | Y67: 已完成 | Z67: 46216 | AA67: 46234 | AB67: =(IF(M67="已完成",1,IF(M67="进行中",0.5,0))*15%+IF(Q67="已完成",1,IF(Q67="进行中",0.5,0))*35%+IF(U67="已完成",1,IF(U67="进行中",0.5,0))*30%+IF(Y67="已完成",1,IF(Y67="进行中",0.5,0))*20%) -> 1 | AC67: =IF(G67="已完成","正常",IF(OR(G67="暂停",G67="挂起"),"暂停",IF(J67="","日期缺失",IF(J67<项目驾驶舱!$B$3,"已延期",IF(J67<=项目驾驶舱!$B$3+7,"临近到期","正常"))))) -> 正常 | AD67: 69 | AE67: 69
A68: T065 | B68: 网上营业厅 | C68: 货权提醒 | D68: 装船作业货权跟踪 | E68: / | F68: 第一批次 | G68: =IF(OR(M68="挂起",M68="暂停",Q68="挂起",Q68="暂停",U68="挂起",U68="暂停",Y68="挂起",Y68="暂停"),"暂停","已完成") -> 已完成 | H68: =IF(L68<>"",L68,IF(P68<>"",P68,IF(T68<>"",T68,X68))) -> 郑士旺 | I68: =IF(COUNT(N68,R68,V68,Z68)=0,"",MIN(N68,R68,V68,Z68)) -> 46202 | J68: =IF(ISNUMBER(K68),K68,IF(COUNT(O68,S68,W68,AA68)=0,"",MAX(O68,S68,W68,AA68))) -> 46261 | K68: 46261 | L68: 郑士旺 | M68: 已完成 | N68: 46202 | O68: 46206 | P68: 石军磊、刘凯 | Q68: 已完成 | R68: 46209 | S68: 46227 | T68: 贺航 | U68: 已完成 | V68: 46209 | W68: 46227 | X68: 袁丽荣 | Y68: 已完成 | Z68: 46216 | AA68: 46234 | AB68: =(IF(M68="已完成",1,IF(M68="进行中",0.5,0))*15%+IF(Q68="已完成",1,IF(Q68="进行中",0.5,0))*35%+IF(U68="已完成",1,IF(U68="进行中",0.5,0))*30%+IF(Y68="已完成",1,IF(Y68="进行中",0.5,0))*20%) -> 1 | AC68: =IF(G68="已完成","正常",IF(OR(G68="暂停",G68="挂起"),"暂停",IF(J68="","日期缺失",IF(J68<项目驾驶舱!$B$3,"已延期",IF(J68<=项目驾驶舱!$B$3+7,"临近到期","正常"))))) -> 正常 | AD68: 69 | AE68: 69
A69: T066 | B69: 网上营业厅 | C69: 货权提醒 | D69: 装船作业货权跟踪 | E69: / | F69: 第一批次 | G69: =IF(OR(M69="挂起",M69="暂停",Q69="挂起",Q69="暂停",U69="挂起",U69="暂停",Y69="挂起",Y69="暂停"),"暂停","已完成") -> 已完成 | H69: =IF(L69<>"",L69,IF(P69<>"",P69,IF(T69<>"",T69,X69))) -> 郑士旺 | I69: =IF(COUNT(N69,R69,V69,Z69)=0,"",MIN(N69,R69,V69,Z69)) -> 46202 | J69: =IF(ISNUMBER(K69),K69,IF(COUNT(O69,S69,W69,AA69)=0,"",MAX(O69,S69,W69,AA69))) -> 46261 | K69: 46261 | L69: 郑士旺 | M69: 已完成 | N69: 46202 | O69: 46206 | P69: 石军磊、刘凯 | Q69: 已完成 | R69: 46209 | S69: 46227 | T69: 贺航 | U69: 已完成 | V69: 46209 | W69: 46227 | X69: 袁丽荣 | Y69: 已完成 | Z69: 46216 | AA69: 46234 | AB69: =(IF(M69="已完成",1,IF(M69="进行中",0.5,0))*15%+IF(Q69="已完成",1,IF(Q69="进行中",0.5,0))*35%+IF(U69="已完成",1,IF(U69="进行中",0.5,0))*30%+IF(Y69="已完成",1,IF(Y69="进行中",0.5,0))*20%) -> 1 | AC69: =IF(G69="已完成","正常",IF(OR(G69="暂停",G69="挂起"),"暂停",IF(J69="","日期缺失",IF(J69<项目驾驶舱!$B$3,"已延期",IF(J69<=项目驾驶舱!$B$3+7,"临近到期","正常"))))) -> 正常 | AD69: 69 | AE69: 69
A70: T067 | B70: 网上营业厅 | C70: 货权提醒 | D70: 装船作业货权跟踪 | E70: / | F70: 第一批次 | G70: =IF(OR(M70="挂起",M70="暂停",Q70="挂起",Q70="暂停",U70="挂起",U70="暂停",Y70="挂起",Y70="暂停"),"暂停","已完成") -> 已完成 | H70: =IF(L70<>"",L70,IF(P70<>"",P70,IF(T70<>"",T70,X70))) -> 郑士旺 | I70: =IF(COUNT(N70,R70,V70,Z70)=0,"",MIN(N70,R70,V70,Z70)) -> 46202 | J70: =IF(ISNUMBER(K70),K70,IF(COUNT(O70,S70,W70,AA70)=0,"",MAX(O70,S70,W70,AA70))) -> 46261 | K70: 46261 | L70: 郑士旺 | M70: 已完成 | N70: 46202 | O70: 46206 | P70: 石军磊、刘凯 | Q70: 已完成 | R70: 46209 | S70: 46227 | T70: 贺航 | U70: 已完成 | V70: 46209 | W70: 46227 | X70: 袁丽荣 | Y70: 已完成 | Z70: 46216 | AA70: 46234 | AB70: =(IF(M70="已完成",1,IF(M70="进行中",0.5,0))*15%+IF(Q70="已完成",1,IF(Q70="进行中",0.5,0))*35%+IF(U70="已完成",1,IF(U70="进行中",0.5,0))*30%+IF(Y70="已完成",1,IF(Y70="进行中",0.5,0))*20%) -> 1 | AC70: =IF(G70="已完成","正常",IF(OR(G70="暂停",G70="挂起"),"暂停",IF(J70="","日期缺失",IF(J70<项目驾驶舱!$B$3,"已延期",IF(J70<=项目驾驶舱!$B$3+7,"临近到期","正常"))))) -> 正常 | AD70: 69 | AE70: 69
A71: T068 | B71: 网上营业厅 | C71: 货权提醒 | D71: 装船作业货权跟踪 | E71: / | F71: 第一批次 | G71: =IF(OR(M71="挂起",M71="暂停",Q71="挂起",Q71="暂停",U71="挂起",U71="暂停",Y71="挂起",Y71="暂停"),"暂停","已完成") -> 已完成 | H71: =IF(L71<>"",L71,IF(P71<>"",P71,IF(T71<>"",T71,X71))) -> 郑士旺 | I71: =IF(COUNT(N71,R71,V71,Z71)=0,"",MIN(N71,R71,V71,Z71)) -> 46202 | J71: =IF(ISNUMBER(K71),K71,IF(COUNT(O71,S71,W71,AA71)=0,"",MAX(O71,S71,W71,AA71))) -> 46261 | K71: 46261 | L71: 郑士旺 | M71: 已完成 | N71: 46202 | O71: 46206 | P71: 石军磊、刘凯 | Q71: 已完成 | R71: 46209 | S71: 46227 | T71: 贺航 | U71: 已完成 | V71: 46209 | W71: 46227 | X71: 袁丽荣 | Y71: 已完成 | Z71: 46216 | AA71: 46234 | AB71: =(IF(M71="已完成",1,IF(M71="进行中",0.5,0))*15%+IF(Q71="已完成",1,IF(Q71="进行中",0.5,0))*35%+IF(U71="已完成",1,IF(U71="进行中",0.5,0))*30%+IF(Y71="已完成",1,IF(Y71="进行中",0.5,0))*20%) -> 1 | AC71: =IF(G71="已完成","正常",IF(OR(G71="暂停",G71="挂起"),"暂停",IF(J71="","日期缺失",IF(J71<项目驾驶舱!$B$3,"已延期",IF(J71<=项目驾驶舱!$B$3+7,"临近到期","正常"))))) -> 正常 | AD71: 69 | AE71: 69
A72: T069 | B72: 网上营业厅 | C72: 卸船作业信息录入优化（太仓） | D72: 新增、详情、修改页内容调整 | E72: / | F72: 第一批次 | G72: =IF(OR(M72="挂起",M72="暂停",Q72="挂起",Q72="暂停",U72="挂起",U72="暂停",Y72="挂起",Y72="暂停"),"暂停","已完成") -> 已完成 | H72: =IF(L72<>"",L72,IF(P72<>"",P72,IF(T72<>"",T72,X72))) -> 郑士旺 | I72: =IF(COUNT(N72,R72,V72,Z72)=0,"",MIN(N72,R72,V72,Z72)) -> 46195 | J72: =IF(ISNUMBER(K72),K72,IF(COUNT(O72,S72,W72,AA72)=0,"",MAX(O72,S72,W72,AA72))) -> 46224 | K72: 46224 | L72: 郑士旺 | M72: 已完成 | N72: / | O72: / | P72: 石军磊、刘凯 | Q72: 已完成 | R72: 46195 | S72: 46206 | T72: 贺航 | U72: 已完成 | V72: 46195 | W72: 46206 | X72: 袁丽荣 | Y72: 已完成 | Z72: 46216 | AA72: 46234 | AB72: =(IF(M72="已完成",1,IF(M72="进行中",0.5,0))*15%+IF(Q72="已完成",1,IF(Q72="进行中",0.5,0))*35%+IF(U72="已完成",1,IF(U72="进行中",0.5,0))*30%+IF(Y72="已完成",1,IF(Y72="进行中",0.5,0))*20%) -> 1 | AC72: =IF(G72="已完成","正常",IF(OR(G72="暂停",G72="挂起"),"暂停",IF(J72="","日期缺失",IF(J72<项目驾驶舱!$B$3,"已延期",IF(J72<=项目驾驶舱!$B$3+7,"临近到期","正常"))))) -> 正常 | AD72: 69 | AE72: 69
A73: T070 | B73: 网上营业厅 | C73: 卸船作业信息录入优化（太仓） | D73: 生成报告 | E73: / | F73: 第一批次 | G73: =IF(OR(M73="挂起",M73="暂停",Q73="挂起",Q73="暂停",U73="挂起",U73="暂停",Y73="挂起",Y73="暂停"),"暂停","已完成") -> 已完成 | H73: =IF(L73<>"",L73,IF(P73<>"",P73,IF(T73<>"",T73,X73))) -> 郑士旺 | I73: =IF(COUNT(N73,R73,V73,Z73)=0,"",MIN(N73,R73,V73,Z73)) -> 46195 | J73: =IF(ISNUMBER(K73),K73,IF(COUNT(O73,S73,W73,AA73)=0,"",MAX(O73,S73,W73,AA73))) -> 46224 | K73: 46224 | L73: 郑士旺 | M73: 已完成 | N73: / | O73: / | P73: 石军磊、刘凯 | Q73: 已完成 | R73: 46195 | S73: 46206 | T73: 贺航 | U73: 已完成 | V73: 46195 | W73: 46206 | X73: 袁丽荣 | Y73: 已完成 | Z73: 46202 | AA73: 46213 | AB73: =(IF(M73="已完成",1,IF(M73="进行中",0.5,0))*15%+IF(Q73="已完成",1,IF(Q73="进行中",0.5,0))*35%+IF(U73="已完成",1,IF(U73="进行中",0.5,0))*30%+IF(Y73="已完成",1,IF(Y73="进行中",0.5,0))*20%) -> 1 | AC73: =IF(G73="已完成","正常",IF(OR(G73="暂停",G73="挂起"),"暂停",IF(J73="","日期缺失",IF(J73<项目驾驶舱!$B$3,"已延期",IF(J73<=项目驾驶舱!$B$3+7,"临近到期","正常"))))) -> 正常 | AD73: 69 | AE73: 69
A74: T071 | B74: 网上营业厅 | C74: 装船作业信息录入优化（太仓） | D74: / | E74: / | F74: 第一批次 | G74: =IF(OR(M74="挂起",M74="暂停",Q74="挂起",Q74="暂停",U74="挂起",U74="暂停",Y74="挂起",Y74="暂停"),"暂停","已完成") -> 已完成 | H74: =IF(L74<>"",L74,IF(P74<>"",P74,IF(T74<>"",T74,X74))) -> 郑士旺 | I74: =IF(COUNT(N74,R74,V74,Z74)=0,"",MIN(N74,R74,V74,Z74)) -> 46195 | J74: =IF(ISNUMBER(K74),K74,IF(COUNT(O74,S74,W74,AA74)=0,"",MAX(O74,S74,W74,AA74))) -> 46224 | K74: 46224 | L74: 郑士旺 | M74: 已完成 | N74: / | O74: / | P74: 石军磊、刘凯 | Q74: 已完成 | R74: 46195 | S74: 46206 | T74: 贺航 | U74: 已完成 | V74: 46195 | W74: 46206 | X74: 袁丽荣 | Y74: 已完成 | Z74: 46202 | AA74: 46213 | AB74: =(IF(M74="已完成",1,IF(M74="进行中",0.5,0))*15%+IF(Q74="已完成",1,IF(Q74="进行中",0.5,0))*35%+IF(U74="已完成",1,IF(U74="进行中",0.5,0))*30%+IF(Y74="已完成",1,IF(Y74="进行中",0.5,0))*20%) -> 1 | AC74: =IF(G74="已完成","正常",IF(OR(G74="暂停",G74="挂起"),"暂停",IF(J74="","日期缺失",IF(J74<项目驾驶舱!$B$3,"已延期",IF(J74<=项目驾驶舱!$B$3+7,"临近到期","正常"))))) -> 正常 | AD74: 69 | AE74: 69
A75: T072 | B75: 网上营业厅 | C75: 船舶预到优化（太仓） | D75: OCR识别 | E75: / | F75: 第一批次 | G75: =IF(OR(M75="挂起",M75="暂停",Q75="挂起",Q75="暂停",U75="挂起",U75="暂停",Y75="挂起",Y75="暂停"),"暂停","已完成") -> 已完成 | H75: =IF(L75<>"",L75,IF(P75<>"",P75,IF(T75<>"",T75,X75))) -> 郑士旺 | I75: =IF(COUNT(N75,R75,V75,Z75)=0,"",MIN(N75,R75,V75,Z75)) -> 46202 | J75: =IF(ISNUMBER(K75),K75,IF(COUNT(O75,S75,W75,AA75)=0,"",MAX(O75,S75,W75,AA75))) -> 46234 | K75: / | L75: 郑士旺 | M75: 已完成 | N75: 46202 | O75: 46206 | P75: 石军磊、刘凯 | Q75: 已完成 | R75: 46209 | S75: 46225 | T75: 贺航 | U75: 已完成 | V75: 46209 | W75: 46225 | X75: 袁丽荣 | Y75: 已完成 | Z75: 46216 | AA75: 46234 | AB75: =(IF(M75="已完成",1,IF(M75="进行中",0.5,0))*15%+IF(Q75="已完成",1,IF(Q75="进行中",0.5,0))*35%+IF(U75="已完成",1,IF(U75="进行中",0.5,0))*30%+IF(Y75="已完成",1,IF(Y75="进行中",0.5,0))*20%) -> 1 | AC75: =IF(G75="已完成","正常",IF(OR(G75="暂停",G75="挂起"),"暂停",IF(J75="","日期缺失",IF(J75<项目驾驶舱!$B$3,"已延期",IF(J75<=项目驾驶舱!$B$3+7,"临近到期","正常"))))) -> 正常 | AD75: 69 | AE75: 69
A76: T073 | B76: 网上营业厅 | C76: 采样作业信息录入 | D76: 采样作业信息录入新增 | E76: / | F76: 第一批次 | G76: =IF(OR(M76="挂起",M76="暂停",Q76="挂起",Q76="暂停",U76="挂起",U76="暂停",Y76="挂起",Y76="暂停"),"暂停","已完成") -> 已完成 | H76: =IF(L76<>"",L76,IF(P76<>"",P76,IF(T76<>"",T76,X76))) -> 郑士旺 | I76: =IF(COUNT(N76,R76,V76,Z76)=0,"",MIN(N76,R76,V76,Z76)) -> 46202 | J76: =IF(ISNUMBER(K76),K76,IF(COUNT(O76,S76,W76,AA76)=0,"",MAX(O76,S76,W76,AA76))) -> 46224 | K76: 46224 | L76: 郑士旺 | M76: 已完成 | N76: 46202 | O76: 46206 | P76: 石军磊、刘凯 | Q76: 已完成 | R76: 46227 | S76: 46227 | T76: 贺航 | U76: 已完成 | V76: 46227 | W76: 46227 | X76: 袁丽荣 | Y76: 已完成 | Z76: 46216 | AA76: 46234 | AB76: =(IF(M76="已完成",1,IF(M76="进行中",0.5,0))*15%+IF(Q76="已完成",1,IF(Q76="进行中",0.5,0))*35%+IF(U76="已完成",1,IF(U76="进行中",0.5,0))*30%+IF(Y76="已完成",1,IF(Y76="进行中",0.5,0))*20%) -> 1 | AC76: =IF(G76="已完成","正常",IF(OR(G76="暂停",G76="挂起"),"暂停",IF(J76="","日期缺失",IF(J76<项目驾驶舱!$B$3,"已延期",IF(J76<=项目驾驶舱!$B$3+7,"临近到期","正常"))))) -> 正常 | AD76: 69 | AE76: 69
A77: T074 | B77: 网上营业厅 | C77: 采样作业信息录入 | D77: 采样作业信息录入编辑 | E77: / | F77: 第一批次 | G77: =IF(OR(M77="挂起",M77="暂停",Q77="挂起",Q77="暂停",U77="挂起",U77="暂停",Y77="挂起",Y77="暂停"),"暂停","已完成") -> 已完成 | H77: =IF(L77<>"",L77,IF(P77<>"",P77,IF(T77<>"",T77,X77))) -> 郑士旺 | I77: =IF(COUNT(N77,R77,V77,Z77)=0,"",MIN(N77,R77,V77,Z77)) -> 46202 | J77: =IF(ISNUMBER(K77),K77,IF(COUNT(O77,S77,W77,AA77)=0,"",MAX(O77,S77,W77,AA77))) -> 46224 | K77: 46224 | L77: 郑士旺 | M77: 已完成 | N77: 46202 | O77: 46206 | P77: 石军磊、刘凯 | Q77: 已完成 | R77: 46227 | S77: 46227 | T77: 贺航 | U77: 已完成 | V77: 46227 | W77: 46227 | X77: 袁丽荣 | Y77: 已完成 | Z77: 46216 | AA77: 46234 | AB77: =(IF(M77="已完成",1,IF(M77="进行中",0.5,0))*15%+IF(Q77="已完成",1,IF(Q77="进行中",0.5,0))*35%+IF(U77="已完成",1,IF(U77="进行中",0.5,0))*30%+IF(Y77="已完成",1,IF(Y77="进行中",0.5,0))*20%) -> 1 | AC77: =IF(G77="已完成","正常",IF(OR(G77="暂停",G77="挂起"),"暂停",IF(J77="","日期缺失",IF(J77<项目驾驶舱!$B$3,"已延期",IF(J77<=项目驾驶舱!$B$3+7,"临近到期","正常"))))) -> 正常 | AD77: 69 | AE77: 69
A78: T075 | B78: 网上营业厅 | C78: 采样作业信息录入 | D78: 采样作业信息录入详情 | E78: / | F78: 第一批次 | G78: =IF(OR(M78="挂起",M78="暂停",Q78="挂起",Q78="暂停",U78="挂起",U78="暂停",Y78="挂起",Y78="暂停"),"暂停","已完成") -> 已完成 | H78: =IF(L78<>"",L78,IF(P78<>"",P78,IF(T78<>"",T78,X78))) -> 郑士旺 | I78: =IF(COUNT(N78,R78,V78,Z78)=0,"",MIN(N78,R78,V78,Z78)) -> 46202 | J78: =IF(ISNUMBER(K78),K78,IF(COUNT(O78,S78,W78,AA78)=0,"",MAX(O78,S78,W78,AA78))) -> 46224 | K78: 46224 | L78: 郑士旺 | M78: 已完成 | N78: 46202 | O78: 46206 | P78: 石军磊、刘凯 | Q78: 已完成 | R78: 46227 | S78: 46227 | T78: 贺航 | U78: 已完成 | V78: 46227 | W78: 46227 | X78: 袁丽荣 | Y78: 已完成 | Z78: 46216 | AA78: 46234 | AB78: =(IF(M78="已完成",1,IF(M78="进行中",0.5,0))*15%+IF(Q78="已完成",1,IF(Q78="进行中",0.5,0))*35%+IF(U78="已完成",1,IF(U78="进行中",0.5,0))*30%+IF(Y78="已完成",1,IF(Y78="进行中",0.5,0))*20%) -> 1 | AC78: =IF(G78="已完成","正常",IF(OR(G78="暂停",G78="挂起"),"暂停",IF(J78="","日期缺失",IF(J78<项目驾驶舱!$B$3,"已延期",IF(J78<=项目驾驶舱!$B$3+7,"临近到期","正常"))))) -> 正常 | AD78: 69 | AE78: 69
A79: T076 | B79: 网上营业厅 | C79: 采样作业信息录入 | D79: 采样作业信息录入删除 | E79: / | F79: 第一批次 | G79: =IF(OR(M79="挂起",M79="暂停",Q79="挂起",Q79="暂停",U79="挂起",U79="暂停",Y79="挂起",Y79="暂停"),"暂停","已完成") -> 已完成 | H79: =IF(L79<>"",L79,IF(P79<>"",P79,IF(T79<>"",T79,X79))) -> 郑士旺 | I79: =IF(COUNT(N79,R79,V79,Z79)=0,"",MIN(N79,R79,V79,Z79)) -> 46202 | J79: =IF(ISNUMBER(K79),K79,IF(COUNT(O79,S79,W79,AA79)=0,"",MAX(O79,S79,W79,AA79))) -> 46224 | K79: 46224 | L79: 郑士旺 | M79: 已完成 | N79: 46202 | O79: 46206 | P79: 石军磊、刘凯 | Q79: 已完成 | R79: 46227 | S79: 46227 | T79: 贺航 | U79: 已完成 | V79: 46227 | W79: 46227 | X79: 袁丽荣 | Y79: 已完成 | Z79: 46216 | AA79: 46234 | AB79: =(IF(M79="已完成",1,IF(M79="进行中",0.5,0))*15%+IF(Q79="已完成",1,IF(Q79="进行中",0.5,0))*35%+IF(U79="已完成",1,IF(U79="进行中",0.5,0))*30%+IF(Y79="已完成",1,IF(Y79="进行中",0.5,0))*20%) -> 1 | AC79: =IF(G79="已完成","正常",IF(OR(G79="暂停",G79="挂起"),"暂停",IF(J79="","日期缺失",IF(J79<项目驾驶舱!$B$3,"已延期",IF(J79<=项目驾驶舱!$B$3+7,"临近到期","正常"))))) -> 正常 | AD79: 69 | AE79: 69
A80: T077 | B80: 网上营业厅 | C80: 采样作业信息录入 | D80: 采样作业信息录入列表 | E80: / | F80: 第一批次 | G80: =IF(OR(M80="挂起",M80="暂停",Q80="挂起",Q80="暂停",U80="挂起",U80="暂停",Y80="挂起",Y80="暂停"),"暂停","已完成") -> 已完成 | H80: =IF(L80<>"",L80,IF(P80<>"",P80,IF(T80<>"",T80,X80))) -> 郑士旺 | I80: =IF(COUNT(N80,R80,V80,Z80)=0,"",MIN(N80,R80,V80,Z80)) -> 46202 | J80: =IF(ISNUMBER(K80),K80,IF(COUNT(O80,S80,W80,AA80)=0,"",MAX(O80,S80,W80,AA80))) -> 46224 | K80: 46224 | L80: 郑士旺 | M80: 已完成 | N80: 46202 | O80: 46206 | P80: 石军磊、刘凯 | Q80: 已完成 | R80: 46227 | S80: 46227 | T80: 贺航 | U80: 已完成 | V80: 46227 | W80: 46227 | X80: 袁丽荣 | Y80: 已完成 | Z80: 46216 | AA80: 46234 | AB80: =(IF(M80="已完成",1,IF(M80="进行中",0.5,0))*15%+IF(Q80="已完成",1,IF(Q80="进行中",0.5,0))*35%+IF(U80="已完成",1,IF(U80="进行中",0.5,0))*30%+IF(Y80="已完成",1,IF(Y80="进行中",0.5,0))*20%) -> 1 | AC80: =IF(G80="已完成","正常",IF(OR(G80="暂停",G80="挂起"),"暂停",IF(J80="","日期缺失",IF(J80<项目驾驶舱!$B$3,"已延期",IF(J80<=项目驾驶舱!$B$3+7,"临近到期","正常"))))) -> 正常 | AD80: 69 | AE80: 69
A81: T078 | B81: 费用结算 | C81: 费用合同签订校验 | D81: 业务数据合同签订校验 | E81: / | F81: 第二批次 | G81: =IF(OR(M81="挂起",M81="暂停",Q81="挂起",Q81="暂停",U81="挂起",U81="暂停",Y81="挂起",Y81="暂停"),"暂停","进行中") -> 进行中 | H81: =IF(L81<>"",L81,IF(P81<>"",P81,IF(T81<>"",T81,X81))) -> 郑士旺 | I81: =IF(COUNT(N81,R81,V81,Z81)=0,"",MIN(N81,R81,V81,Z81)) -> 46223 | J81: =IF(ISNUMBER(K81),K81,IF(COUNT(O81,S81,W81,AA81)=0,"",MAX(O81,S81,W81,AA81))) -> 46318 | L81: 郑士旺 | M81: 已完成 | N81: 46223 | O81: 46227 | P81: 石军磊、刘凯 | Q81: 进行中 | R81: 46272 | S81: 46279 | T81: 贺航 | U81: 进行中 | V81: 46272 | W81: 46279 | X81: 袁丽荣 | Y81: 未开始 | Z81: 46307 | AA81: 46318 | AB81: =(IF(M81="已完成",1,IF(M81="进行中",0.5,0))*15%+IF(Q81="已完成",1,IF(Q81="进行中",0.5,0))*35%+IF(U81="已完成",1,IF(U81="进行中",0.5,0))*30%+IF(Y81="已完成",1,IF(Y81="进行中",0.5,0))*20%) -> 0.475 | AC81: =IF(G81="已完成","正常",IF(OR(G81="暂停",G81="挂起"),"暂停",IF(J81="","日期缺失",IF(J81<项目驾驶舱!$B$3,"已延期",IF(J81<=项目驾驶舱!$B$3+7,"临近到期","正常"))))) -> 正常 | AD81: 69 | AE81: 69
A82: T079 | B82: 费用结算 | C82: 费用合同签订校验 | D82: 结算数据合同签订校验 | E82: / | F82: 第二批次 | G82: =IF(OR(M82="挂起",M82="暂停",Q82="挂起",Q82="暂停",U82="挂起",U82="暂停",Y82="挂起",Y82="暂停"),"暂停","进行中") -> 进行中 | H82: =IF(L82<>"",L82,IF(P82<>"",P82,IF(T82<>"",T82,X82))) -> 郑士旺 | I82: =IF(COUNT(N82,R82,V82,Z82)=0,"",MIN(N82,R82,V82,Z82)) -> 46223 | J82: =IF(ISNUMBER(K82),K82,IF(COUNT(O82,S82,W82,AA82)=0,"",MAX(O82,S82,W82,AA82))) -> 46318 | L82: 郑士旺 | M82: 已完成 | N82: 46223 | O82: 46227 | P82: 石军磊、刘凯 | Q82: 进行中 | R82: 46272 | S82: 46279 | T82: 贺航 | U82: 进行中 | V82: 46272 | W82: 46279 | X82: 袁丽荣 | Y82: 未开始 | Z82: 46307 | AA82: 46318 | AB82: =(IF(M82="已完成",1,IF(M82="进行中",0.5,0))*15%+IF(Q82="已完成",1,IF(Q82="进行中",0.5,0))*35%+IF(U82="已完成",1,IF(U82="进行中",0.5,0))*30%+IF(Y82="已完成",1,IF(Y82="进行中",0.5,0))*20%) -> 0.475 | AC82: =IF(G82="已完成","正常",IF(OR(G82="暂停",G82="挂起"),"暂停",IF(J82="","日期缺失",IF(J82<项目驾驶舱!$B$3,"已延期",IF(J82<=项目驾驶舱!$B$3+7,"临近到期","正常"))))) -> 正常 | AD82: 69 | AE82: 69
A83: T080 | B83: 费用结算 | C83: 费用合同签订校验 | D83: 合同校验结果查询 | E83: / | F83: 第二批次 | G83: =IF(OR(M83="挂起",M83="暂停",Q83="挂起",Q83="暂停",U83="挂起",U83="暂停",Y83="挂起",Y83="暂停"),"暂停","进行中") -> 进行中 | H83: =IF(L83<>"",L83,IF(P83<>"",P83,IF(T83<>"",T83,X83))) -> 郑士旺 | I83: =IF(COUNT(N83,R83,V83,Z83)=0,"",MIN(N83,R83,V83,Z83)) -> 46223 | J83: =IF(ISNUMBER(K83),K83,IF(COUNT(O83,S83,W83,AA83)=0,"",MAX(O83,S83,W83,AA83))) -> 46261 | K83: 46261 | L83: 郑士旺 | M83: 已完成 | N83: 46223 | O83: 46227 | P83: 石军磊、刘凯 | Q83: 进行中 | R83: 46272 | S83: 46279 | T83: 贺航 | U83: 进行中 | V83: 46272 | W83: 46279 | X83: 袁丽荣 | Y83: 未开始 | Z83: 46307 | AA83: 46318 | AB83: =(IF(M83="已完成",1,IF(M83="进行中",0.5,0))*15%+IF(Q83="已完成",1,IF(Q83="进行中",0.5,0))*35%+IF(U83="已完成",1,IF(U83="进行中",0.5,0))*30%+IF(Y83="已完成",1,IF(Y83="进行中",0.5,0))*20%) -> 0.475 | AC83: =IF(G83="已完成","正常",IF(OR(G83="暂停",G83="挂起"),"暂停",IF(J83="","日期缺失",IF(J83<项目驾驶舱!$B$3,"已延期",IF(J83<=项目驾驶舱!$B$3+7,"临近到期","正常"))))) -> 已延期 | AD83: 69 | AE83: 69
A84: T081 | B84: 费用结算 | C84: 停泊费（外贸） | D84: 数据对接 | E84: / | F84: 第二批次 | G84: =IF(OR(M84="挂起",M84="暂停",Q84="挂起",Q84="暂停",U84="挂起",U84="暂停",Y84="挂起",Y84="暂停"),"暂停","未开始") -> 未开始 | H84: =IF(L84<>"",L84,IF(P84<>"",P84,IF(T84<>"",T84,X84))) -> 郑士旺 | I84: =IF(COUNT(N84,R84,V84,Z84)=0,"",MIN(N84,R84,V84,Z84)) -> 46230 | J84: =IF(ISNUMBER(K84),K84,IF(COUNT(O84,S84,W84,AA84)=0,"",MAX(O84,S84,W84,AA84))) -> 46353 | L84: 郑士旺 | M84: 未开始 | N84: 46230 | O84: 46241 | P84: 石军磊、刘凯 | Q84: 未开始 | R84: 46307 | S84: 46339 | T84: 贺航 | U84: 未开始 | V84: 46307 | W84: 46339 | X84: 袁丽荣 | Y84: 未开始 | Z84: 46342 | AA84: 46353 | AB84: =(IF(M84="已完成",1,IF(M84="进行中",0.5,0))*15%+IF(Q84="已完成",1,IF(Q84="进行中",0.5,0))*35%+IF(U84="已完成",1,IF(U84="进行中",0.5,0))*30%+IF(Y84="已完成",1,IF(Y84="进行中",0.5,0))*20%) -> 0 | AC84: =IF(G84="已完成","正常",IF(OR(G84="暂停",G84="挂起"),"暂停",IF(J84="","日期缺失",IF(J84<项目驾驶舱!$B$3,"已延期",IF(J84<=项目驾驶舱!$B$3+7,"临近到期","正常"))))) -> 正常 | AD84: 69 | AE84: 69
A85: T082 | B85: 费用结算 | C85: 停泊费（外贸） | D85: 数据展示 | E85: / | F85: 第二批次 | G85: =IF(OR(M85="挂起",M85="暂停",Q85="挂起",Q85="暂停",U85="挂起",U85="暂停",Y85="挂起",Y85="暂停"),"暂停","未开始") -> 未开始 | H85: =IF(L85<>"",L85,IF(P85<>"",P85,IF(T85<>"",T85,X85))) -> 郑士旺 | I85: =IF(COUNT(N85,R85,V85,Z85)=0,"",MIN(N85,R85,V85,Z85)) -> 46230 | J85: =IF(ISNUMBER(K85),K85,IF(COUNT(O85,S85,W85,AA85)=0,"",MAX(O85,S85,W85,AA85))) -> 46224 | K85: 46224 | L85: 郑士旺 | M85: 未开始 | N85: 46230 | O85: 46241 | P85: 石军磊、刘凯 | Q85: 未开始 | R85: 46307 | S85: 46339 | T85: 贺航 | U85: 未开始 | V85: 46307 | W85: 46339 | X85: 袁丽荣 | Y85: 未开始 | Z85: 46342 | AA85: 46353 | AB85: =(IF(M85="已完成",1,IF(M85="进行中",0.5,0))*15%+IF(Q85="已完成",1,IF(Q85="进行中",0.5,0))*35%+IF(U85="已完成",1,IF(U85="进行中",0.5,0))*30%+IF(Y85="已完成",1,IF(Y85="进行中",0.5,0))*20%) -> 0 | AC85: =IF(G85="已完成","正常",IF(OR(G85="暂停",G85="挂起"),"暂停",IF(J85="","日期缺失",IF(J85<项目驾驶舱!$B$3,"已延期",IF(J85<=项目驾驶舱!$B$3+7,"临近到期","正常"))))) -> 已延期 | AD85: 69 | AE85: 69
A86: T083 | B86: 费用结算 | C86: 锚泊费（外贸） | D86: 数据对接 | E86: / | F86: 第二批次 | G86: =IF(OR(M86="挂起",M86="暂停",Q86="挂起",Q86="暂停",U86="挂起",U86="暂停",Y86="挂起",Y86="暂停"),"暂停","未开始") -> 未开始 | H86: =IF(L86<>"",L86,IF(P86<>"",P86,IF(T86<>"",T86,X86))) -> 郑士旺 | I86: =IF(COUNT(N86,R86,V86,Z86)=0,"",MIN(N86,R86,V86,Z86)) -> 46230 | J86: =IF(ISNUMBER(K86),K86,IF(COUNT(O86,S86,W86,AA86)=0,"",MAX(O86,S86,W86,AA86))) -> 46224 | K86: 46224 | L86: 郑士旺 | M86: 未开始 | N86: 46230 | O86: 46241 | P86: 石军磊、刘凯 | Q86: 未开始 | R86: 46307 | S86: 46339 | T86: 贺航 | U86: 未开始 | V86: 46307 | W86: 46339 | X86: 袁丽荣 | Y86: 未开始 | Z86: 46342 | AA86: 46353 | AB86: =(IF(M86="已完成",1,IF(M86="进行中",0.5,0))*15%+IF(Q86="已完成",1,IF(Q86="进行中",0.5,0))*35%+IF(U86="已完成",1,IF(U86="进行中",0.5,0))*30%+IF(Y86="已完成",1,IF(Y86="进行中",0.5,0))*20%) -> 0 | AC86: =IF(G86="已完成","正常",IF(OR(G86="暂停",G86="挂起"),"暂停",IF(J86="","日期缺失",IF(J86<项目驾驶舱!$B$3,"已延期",IF(J86<=项目驾驶舱!$B$3+7,"临近到期","正常"))))) -> 已延期 | AD86: 69 | AE86: 69
A87: T084 | B87: 费用结算 | C87: 锚泊费（外贸） | D87: 数据产生 | E87: / | F87: 第二批次 | G87: =IF(OR(M87="挂起",M87="暂停",Q87="挂起",Q87="暂停",U87="挂起",U87="暂停",Y87="挂起",Y87="暂停"),"暂停","未开始") -> 未开始 | H87: =IF(L87<>"",L87,IF(P87<>"",P87,IF(T87<>"",T87,X87))) -> 郑士旺 | I87: =IF(COUNT(N87,R87,V87,Z87)=0,"",MIN(N87,R87,V87,Z87)) -> 46230 | J87: =IF(ISNUMBER(K87),K87,IF(COUNT(O87,S87,W87,AA87)=0,"",MAX(O87,S87,W87,AA87))) -> 46224 | K87: 46224 | L87: 郑士旺 | M87: 未开始 | N87: 46230 | O87: 46241 | P87: 石军磊、刘凯 | Q87: 未开始 | R87: 46307 | S87: 46339 | T87: 贺航 | U87: 未开始 | V87: 46307 | W87: 46339 | X87: 袁丽荣 | Y87: 未开始 | Z87: 46342 | AA87: 46353 | AB87: =(IF(M87="已完成",1,IF(M87="进行中",0.5,0))*15%+IF(Q87="已完成",1,IF(Q87="进行中",0.5,0))*35%+IF(U87="已完成",1,IF(U87="进行中",0.5,0))*30%+IF(Y87="已完成",1,IF(Y87="进行中",0.5,0))*20%) -> 0 | AC87: =IF(G87="已完成","正常",IF(OR(G87="暂停",G87="挂起"),"暂停",IF(J87="","日期缺失",IF(J87<项目驾驶舱!$B$3,"已延期",IF(J87<=项目驾驶舱!$B$3+7,"临近到期","正常"))))) -> 已延期 | AD87: 69 | AE87: 69
A88: T085 | B88: 费用结算 | C88: 堆存费（外贸） | D88: 数据对接 | E88: / | F88: 第二批次 | G88: =IF(OR(M88="挂起",M88="暂停",Q88="挂起",Q88="暂停",U88="挂起",U88="暂停",Y88="挂起",Y88="暂停"),"暂停","未开始") -> 未开始 | H88: =IF(L88<>"",L88,IF(P88<>"",P88,IF(T88<>"",T88,X88))) -> 郑士旺 | I88: =IF(COUNT(N88,R88,V88,Z88)=0,"",MIN(N88,R88,V88,Z88)) -> 46230 | J88: =IF(ISNUMBER(K88),K88,IF(COUNT(O88,S88,W88,AA88)=0,"",MAX(O88,S88,W88,AA88))) -> 46224 | K88: 46224 | L88: 郑士旺 | M88: 未开始 | N88: 46230 | O88: 46241 | P88: 常浩 | Q88: 未开始 | R88: 46293 | S88: 46311 | T88: 常浩 | U88: 未开始 | V88: 46293 | W88: 46311 | X88: 袁丽荣 | Y88: 未开始 | Z88: 46342 | AA88: 46353 | AB88: =(IF(M88="已完成",1,IF(M88="进行中",0.5,0))*15%+IF(Q88="已完成",1,IF(Q88="进行中",0.5,0))*35%+IF(U88="已完成",1,IF(U88="进行中",0.5,0))*30%+IF(Y88="已完成",1,IF(Y88="进行中",0.5,0))*20%) -> 0 | AC88: =IF(G88="已完成","正常",IF(OR(G88="暂停",G88="挂起"),"暂停",IF(J88="","日期缺失",IF(J88<项目驾驶舱!$B$3,"已延期",IF(J88<=项目驾驶舱!$B$3+7,"临近到期","正常"))))) -> 已延期 | AD88: 69 | AE88: 69
A89: T086 | B89: 费用结算 | C89: 堆存费（外贸） | D89: 数据展示 | E89: / | F89: 第二批次 | G89: =IF(OR(M89="挂起",M89="暂停",Q89="挂起",Q89="暂停",U89="挂起",U89="暂停",Y89="挂起",Y89="暂停"),"暂停","未开始") -> 未开始 | H89: =IF(L89<>"",L89,IF(P89<>"",P89,IF(T89<>"",T89,X89))) -> 郑士旺 | I89: =IF(COUNT(N89,R89,V89,Z89)=0,"",MIN(N89,R89,V89,Z89)) -> 46230 | J89: =IF(ISNUMBER(K89),K89,IF(COUNT(O89,S89,W89,AA89)=0,"",MAX(O89,S89,W89,AA89))) -> 46224 | K89: 46224 | L89: 郑士旺 | M89: 未开始 | N89: 46230 | O89: 46241 | P89: 常浩 | Q89: 未开始 | R89: 46293 | S89: 46311 | T89: 贺航 | U89: 未开始 | V89: 46293 | W89: 46311 | X89: 袁丽荣 | Y89: 未开始 | Z89: 46342 | AA89: 46353 | AB89: =(IF(M89="已完成",1,IF(M89="进行中",0.5,0))*15%+IF(Q89="已完成",1,IF(Q89="进行中",0.5,0))*35%+IF(U89="已完成",1,IF(U89="进行中",0.5,0))*30%+IF(Y89="已完成",1,IF(Y89="进行中",0.5,0))*20%) -> 0 | AC89: =IF(G89="已完成","正常",IF(OR(G89="暂停",G89="挂起"),"暂停",IF(J89="","日期缺失",IF(J89<项目驾驶舱!$B$3,"已延期",IF(J89<=项目驾驶舱!$B$3+7,"临近到期","正常"))))) -> 已延期 | AD89: 69 | AE89: 69
A90: T087 | B90: 费用结算 | C90: 卸船费（外贸） | D90: 数据对接 | E90: / | F90: 第二批次 | G90: =IF(OR(M90="挂起",M90="暂停",Q90="挂起",Q90="暂停",U90="挂起",U90="暂停",Y90="挂起",Y90="暂停"),"暂停","未开始") -> 未开始 | H90: =IF(L90<>"",L90,IF(P90<>"",P90,IF(T90<>"",T90,X90))) -> 郑士旺 | I90: =IF(COUNT(N90,R90,V90,Z90)=0,"",MIN(N90,R90,V90,Z90)) -> 46230 | J90: =IF(ISNUMBER(K90),K90,IF(COUNT(O90,S90,W90,AA90)=0,"",MAX(O90,S90,W90,AA90))) -> 46224 | K90: 46224 | L90: 郑士旺 | M90: 未开始 | N90: 46230 | O90: 46241 | P90: 常浩 | Q90: 未开始 | R90: 46293 | S90: 46311 | T90: 常浩 | U90: 未开始 | V90: 46293 | W90: 46311 | X90: 袁丽荣 | Y90: 未开始 | Z90: 46342 | AA90: 46353 | AB90: =(IF(M90="已完成",1,IF(M90="进行中",0.5,0))*15%+IF(Q90="已完成",1,IF(Q90="进行中",0.5,0))*35%+IF(U90="已完成",1,IF(U90="进行中",0.5,0))*30%+IF(Y90="已完成",1,IF(Y90="进行中",0.5,0))*20%) -> 0 | AC90: =IF(G90="已完成","正常",IF(OR(G90="暂停",G90="挂起"),"暂停",IF(J90="","日期缺失",IF(J90<项目驾驶舱!$B$3,"已延期",IF(J90<=项目驾驶舱!$B$3+7,"临近到期","正常"))))) -> 已延期 | AD90: 69 | AE90: 69
A91: T088 | B91: 费用结算 | C91: 卸船费（外贸） | D91: 数据展示 | E91: / | F91: 第二批次 | G91: =IF(OR(M91="挂起",M91="暂停",Q91="挂起",Q91="暂停",U91="挂起",U91="暂停",Y91="挂起",Y91="暂停"),"暂停","未开始") -> 未开始 | H91: =IF(L91<>"",L91,IF(P91<>"",P91,IF(T91<>"",T91,X91))) -> 郑士旺 | I91: =IF(COUNT(N91,R91,V91,Z91)=0,"",MIN(N91,R91,V91,Z91)) -> 46230 | J91: =IF(ISNUMBER(K91),K91,IF(COUNT(O91,S91,W91,AA91)=0,"",MAX(O91,S91,W91,AA91))) -> 46353 | L91: 郑士旺 | M91: 未开始 | N91: 46230 | O91: 46241 | P91: 常浩 | Q91: 未开始 | R91: 46293 | S91: 46311 | T91: 常浩 | U91: 未开始 | V91: 46293 | W91: 46311 | X91: 袁丽荣 | Y91: 未开始 | Z91: 46342 | AA91: 46353 | AB91: =(IF(M91="已完成",1,IF(M91="进行中",0.5,0))*15%+IF(Q91="已完成",1,IF(Q91="进行中",0.5,0))*35%+IF(U91="已完成",1,IF(U91="进行中",0.5,0))*30%+IF(Y91="已完成",1,IF(Y91="进行中",0.5,0))*20%) -> 0 | AC91: =IF(G91="已完成","正常",IF(OR(G91="暂停",G91="挂起"),"暂停",IF(J91="","日期缺失",IF(J91<项目驾驶舱!$B$3,"已延期",IF(J91<=项目驾驶舱!$B$3+7,"临近到期","正常"))))) -> 正常 | AD91: 69 | AE91: 69
A92: T089 | B92: 费用结算 | C92: 采样服务费（外贸） | D92: 新增采样服务费（外贸） | E92: / | F92: 第二批次 | G92: =IF(OR(M92="挂起",M92="暂停",Q92="挂起",Q92="暂停",U92="挂起",U92="暂停",Y92="挂起",Y92="暂停"),"暂停","未开始") -> 未开始 | H92: =IF(L92<>"",L92,IF(P92<>"",P92,IF(T92<>"",T92,X92))) -> 郑士旺 | I92: =IF(COUNT(N92,R92,V92,Z92)=0,"",MIN(N92,R92,V92,Z92)) -> 46230 | J92: =IF(ISNUMBER(K92),K92,IF(COUNT(O92,S92,W92,AA92)=0,"",MAX(O92,S92,W92,AA92))) -> 46353 | L92: 郑士旺 | M92: 未开始 | N92: 46230 | O92: 46241 | P92: 石军磊、刘凯 | Q92: 未开始 | R92: 46307 | S92: 46339 | T92: 贺航 | U92: 未开始 | V92: 46307 | W92: 46339 | X92: 袁丽荣 | Y92: 未开始 | Z92: 46342 | AA92: 46353 | AB92: =(IF(M92="已完成",1,IF(M92="进行中",0.5,0))*15%+IF(Q92="已完成",1,IF(Q92="进行中",0.5,0))*35%+IF(U92="已完成",1,IF(U92="进行中",0.5,0))*30%+IF(Y92="已完成",1,IF(Y92="进行中",0.5,0))*20%) -> 0 | AC92: =IF(G92="已完成","正常",IF(OR(G92="暂停",G92="挂起"),"暂停",IF(J92="","日期缺失",IF(J92<项目驾驶舱!$B$3,"已延期",IF(J92<=项目驾驶舱!$B$3+7,"临近到期","正常"))))) -> 正常 | AD92: 69 | AE92: 69
A93: T090 | B93: 费用结算 | C93: 采样服务费（外贸） | D93: 审批采样服务费（外贸） | E93: / | F93: 第二批次 | G93: =IF(OR(M93="挂起",M93="暂停",Q93="挂起",Q93="暂停",U93="挂起",U93="暂停",Y93="挂起",Y93="暂停"),"暂停","未开始") -> 未开始 | H93: =IF(L93<>"",L93,IF(P93<>"",P93,IF(T93<>"",T93,X93))) -> 郑士旺 | I93: =IF(COUNT(N93,R93,V93,Z93)=0,"",MIN(N93,R93,V93,Z93)) -> 46230 | J93: =IF(ISNUMBER(K93),K93,IF(COUNT(O93,S93,W93,AA93)=0,"",MAX(O93,S93,W93,AA93))) -> 46353 | L93: 郑士旺 | M93: 未开始 | N93: 46230 | O93: 46241 | P93: 石军磊、刘凯 | Q93: 未开始 | R93: 46307 | S93: 46339 | T93: 贺航 | U93: 未开始 | V93: 46307 | W93: 46339 | X93: 袁丽荣 | Y93: 未开始 | Z93: 46342 | AA93: 46353 | AB93: =(IF(M93="已完成",1,IF(M93="进行中",0.5,0))*15%+IF(Q93="已完成",1,IF(Q93="进行中",0.5,0))*35%+IF(U93="已完成",1,IF(U93="进行中",0.5,0))*30%+IF(Y93="已完成",1,IF(Y93="进行中",0.5,0))*20%) -> 0 | AC93: =IF(G93="已完成","正常",IF(OR(G93="暂停",G93="挂起"),"暂停",IF(J93="","日期缺失",IF(J93<项目驾驶舱!$B$3,"已延期",IF(J93<=项目驾驶舱!$B$3+7,"临近到期","正常"))))) -> 正常 | AD93: 69 | AE93: 69
A94: T091 | B94: 费用结算 | C94: 采样服务费（外贸） | D94: 单据签章 | E94: / | F94: 第二批次 | G94: =IF(OR(M94="挂起",M94="暂停",Q94="挂起",Q94="暂停",U94="挂起",U94="暂停",Y94="挂起",Y94="暂停"),"暂停","未开始") -> 未开始 | H94: =IF(L94<>"",L94,IF(P94<>"",P94,IF(T94<>"",T94,X94))) -> 郑士旺 | I94: =IF(COUNT(N94,R94,V94,Z94)=0,"",MIN(N94,R94,V94,Z94)) -> 46230 | J94: =IF(ISNUMBER(K94),K94,IF(COUNT(O94,S94,W94,AA94)=0,"",MAX(O94,S94,W94,AA94))) -> 46353 | L94: 郑士旺 | M94: 未开始 | N94: 46230 | O94: 46241 | P94: 石军磊、刘凯 | Q94: 未开始 | R94: 46307 | S94: 46339 | T94: 贺航 | U94: 未开始 | V94: 46307 | W94: 46339 | X94: 袁丽荣 | Y94: 未开始 | Z94: 46342 | AA94: 46353 | AB94: =(IF(M94="已完成",1,IF(M94="进行中",0.5,0))*15%+IF(Q94="已完成",1,IF(Q94="进行中",0.5,0))*35%+IF(U94="已完成",1,IF(U94="进行中",0.5,0))*30%+IF(Y94="已完成",1,IF(Y94="进行中",0.5,0))*20%) -> 0 | AC94: =IF(G94="已完成","正常",IF(OR(G94="暂停",G94="挂起"),"暂停",IF(J94="","日期缺失",IF(J94<项目驾驶舱!$B$3,"已延期",IF(J94<=项目驾驶舱!$B$3+7,"临近到期","正常"))))) -> 正常 | AD94: 69 | AE94: 69
A95: T092 | B95: 费用结算 | C95: 采样服务费（外贸） | D95: 数据推送 | E95: / | F95: 第二批次 | G95: =IF(OR(M95="挂起",M95="暂停",Q95="挂起",Q95="暂停",U95="挂起",U95="暂停",Y95="挂起",Y95="暂停"),"暂停","未开始") -> 未开始 | H95: =IF(L95<>"",L95,IF(P95<>"",P95,IF(T95<>"",T95,X95))) -> 郑士旺 | I95: =IF(COUNT(N95,R95,V95,Z95)=0,"",MIN(N95,R95,V95,Z95)) -> 46230 | J95: =IF(ISNUMBER(K95),K95,IF(COUNT(O95,S95,W95,AA95)=0,"",MAX(O95,S95,W95,AA95))) -> 46353 | L95: 郑士旺 | M95: 未开始 | N95: 46230 | O95: 46241 | P95: 石军磊、刘凯 | Q95: 未开始 | R95: 46307 | S95: 46339 | T95: 贺航 | U95: 未开始 | V95: 46307 | W95: 46339 | X95: 袁丽荣 | Y95: 未开始 | Z95: 46342 | AA95: 46353 | AB95: =(IF(M95="已完成",1,IF(M95="进行中",0.5,0))*15%+IF(Q95="已完成",1,IF(Q95="进行中",0.5,0))*35%+IF(U95="已完成",1,IF(U95="进行中",0.5,0))*30%+IF(Y95="已完成",1,IF(Y95="进行中",0.5,0))*20%) -> 0 | AC95: =IF(G95="已完成","正常",IF(OR(G95="暂停",G95="挂起"),"暂停",IF(J95="","日期缺失",IF(J95<项目驾驶舱!$B$3,"已延期",IF(J95<=项目驾驶舱!$B$3+7,"临近到期","正常"))))) -> 正常 | AD95: 69 | AE95: 69
A96: T093 | B96: 费用结算 | C96: 船舶供应服务费（外贸） | D96: 数据对接 | E96: / | F96: 第二批次 | G96: =IF(OR(M96="挂起",M96="暂停",Q96="挂起",Q96="暂停",U96="挂起",U96="暂停",Y96="挂起",Y96="暂停"),"暂停","未开始") -> 未开始 | H96: =IF(L96<>"",L96,IF(P96<>"",P96,IF(T96<>"",T96,X96))) -> 郑士旺 | I96: =IF(COUNT(N96,R96,V96,Z96)=0,"",MIN(N96,R96,V96,Z96)) -> 46230 | J96: =IF(ISNUMBER(K96),K96,IF(COUNT(O96,S96,W96,AA96)=0,"",MAX(O96,S96,W96,AA96))) -> 46353 | L96: 郑士旺 | M96: 未开始 | N96: 46230 | O96: 46241 | P96: 石军磊、刘凯 | Q96: 未开始 | R96: 46307 | S96: 46339 | T96: 贺航 | U96: 未开始 | V96: 46307 | W96: 46339 | X96: 袁丽荣 | Y96: 未开始 | Z96: 46342 | AA96: 46353 | AB96: =(IF(M96="已完成",1,IF(M96="进行中",0.5,0))*15%+IF(Q96="已完成",1,IF(Q96="进行中",0.5,0))*35%+IF(U96="已完成",1,IF(U96="进行中",0.5,0))*30%+IF(Y96="已完成",1,IF(Y96="进行中",0.5,0))*20%) -> 0 | AC96: =IF(G96="已完成","正常",IF(OR(G96="暂停",G96="挂起"),"暂停",IF(J96="","日期缺失",IF(J96<项目驾驶舱!$B$3,"已延期",IF(J96<=项目驾驶舱!$B$3+7,"临近到期","正常"))))) -> 正常 | AD96: 69 | AE96: 69
A97: T094 | B97: 费用结算 | C97: 船舶供应服务费（外贸） | D97: 数据展示 | E97: / | F97: 第二批次 | G97: =IF(OR(M97="挂起",M97="暂停",Q97="挂起",Q97="暂停",U97="挂起",U97="暂停",Y97="挂起",Y97="暂停"),"暂停","未开始") -> 未开始 | H97: =IF(L97<>"",L97,IF(P97<>"",P97,IF(T97<>"",T97,X97))) -> 郑士旺 | I97: =IF(COUNT(N97,R97,V97,Z97)=0,"",MIN(N97,R97,V97,Z97)) -> 46230 | J97: =IF(ISNUMBER(K97),K97,IF(COUNT(O97,S97,W97,AA97)=0,"",MAX(O97,S97,W97,AA97))) -> 46353 | L97: 郑士旺 | M97: 未开始 | N97: 46230 | O97: 46241 | P97: 石军磊、刘凯 | Q97: 未开始 | R97: 46307 | S97: 46339 | T97: 贺航 | U97: 未开始 | V97: 46307 | W97: 46339 | X97: 袁丽荣 | Y97: 未开始 | Z97: 46342 | AA97: 46353 | AB97: =(IF(M97="已完成",1,IF(M97="进行中",0.5,0))*15%+IF(Q97="已完成",1,IF(Q97="进行中",0.5,0))*35%+IF(U97="已完成",1,IF(U97="进行中",0.5,0))*30%+IF(Y97="已完成",1,IF(Y97="进行中",0.5,0))*20%) -> 0 | AC97: =IF(G97="已完成","正常",IF(OR(G97="暂停",G97="挂起"),"暂停",IF(J97="","日期缺失",IF(J97<项目驾驶舱!$B$3,"已延期",IF(J97<=项目驾驶舱!$B$3+7,"临近到期","正常"))))) -> 正常 | AD97: 69 | AE97: 69
A98: T095 | B98: 费用结算 | C98: 堆存费优化（太仓） | D98: 自动生成堆存费 | E98: / | F98: 第一批次 | G98: =IF(OR(M98="挂起",M98="暂停",Q98="挂起",Q98="暂停",U98="挂起",U98="暂停",Y98="挂起",Y98="暂停"),"暂停","进行中") -> 进行中 | H98: =IF(L98<>"",L98,IF(P98<>"",P98,IF(T98<>"",T98,X98))) -> 郑士旺 | I98: =IF(COUNT(N98,R98,V98,Z98)=0,"",MIN(N98,R98,V98,Z98)) -> 46202 | J98: =IF(ISNUMBER(K98),K98,IF(COUNT(O98,S98,W98,AA98)=0,"",MAX(O98,S98,W98,AA98))) -> 46273 | L98: 郑士旺 | M98: 已完成 | N98: 46202 | O98: 46206 | P98: 常浩 | Q98: 已完成 | R98: 46265 | S98: 46273 | T98: 常浩 | U98: 已完成 | V98: 46265 | W98: 46273 | X98: 袁丽荣 | Y98: 进行中 | Z98: 46216 | AA98: 46234 | AB98: =(IF(M98="已完成",1,IF(M98="进行中",0.5,0))*15%+IF(Q98="已完成",1,IF(Q98="进行中",0.5,0))*35%+IF(U98="已完成",1,IF(U98="进行中",0.5,0))*30%+IF(Y98="已完成",1,IF(Y98="进行中",0.5,0))*20%) -> 0.9 | AC98: =IF(G98="已完成","正常",IF(OR(G98="暂停",G98="挂起"),"暂停",IF(J98="","日期缺失",IF(J98<项目驾驶舱!$B$3,"已延期",IF(J98<=项目驾驶舱!$B$3+7,"临近到期","正常"))))) -> 已延期 | AD98: 69 | AE98: 69
A99: T096 | B99: 费用结算 | C99: 港杂费优化(太仓） | D99: 自动生成装船港杂费 | E99: / | F99: 第一批次 | G99: =IF(OR(M99="挂起",M99="暂停",Q99="挂起",Q99="暂停",U99="挂起",U99="暂停",Y99="挂起",Y99="暂停"),"暂停","已完成") -> 已完成 | H99: =IF(L99<>"",L99,IF(P99<>"",P99,IF(T99<>"",T99,X99))) -> 郑士旺 | I99: =IF(COUNT(N99,R99,V99,Z99)=0,"",MIN(N99,R99,V99,Z99)) -> 46202 | J99: =IF(ISNUMBER(K99),K99,IF(COUNT(O99,S99,W99,AA99)=0,"",MAX(O99,S99,W99,AA99))) -> 46261 | K99: 46261 | L99: 郑士旺 | M99: 已完成 | N99: 46202 | O99: 46206 | P99: 石军磊、刘凯 | Q99: 已完成 | R99: 46209 | S99: 46225 | T99: 贺航 | U99: 已完成 | V99: 46209 | W99: 46225 | X99: 袁丽荣 | Y99: 已完成 | Z99: 46216 | AA99: 46234 | AB99: =(IF(M99="已完成",1,IF(M99="进行中",0.5,0))*15%+IF(Q99="已完成",1,IF(Q99="进行中",0.5,0))*35%+IF(U99="已完成",1,IF(U99="进行中",0.5,0))*30%+IF(Y99="已完成",1,IF(Y99="进行中",0.5,0))*20%) -> 1 | AC99: =IF(G99="已完成","正常",IF(OR(G99="暂停",G99="挂起"),"暂停",IF(J99="","日期缺失",IF(J99<项目驾驶舱!$B$3,"已延期",IF(J99<=项目驾驶舱!$B$3+7,"临近到期","正常"))))) -> 正常 | AD99: 69 | AE99: 69
A100: T097 | B100: 费用结算 | C100: 租赁费优化（太仓） | D100: 自动生成租赁费 | E100: / | F100: 第一批次 | G100: =IF(OR(M100="挂起",M100="暂停",Q100="挂起",Q100="暂停",U100="挂起",U100="暂停",Y100="挂起",Y100="暂停"),"暂停","已完成") -> 已完成 | H100: =IF(L100<>"",L100,IF(P100<>"",P100,IF(T100<>"",T100,X100))) -> 郑士旺 | I100: =IF(COUNT(N100,R100,V100,Z100)=0,"",MIN(N100,R100,V100,Z100)) -> 46202 | J100: =IF(ISNUMBER(K100),K100,IF(COUNT(O100,S100,W100,AA100)=0,"",MAX(O100,S100,W100,AA100))) -> 46234 | L100: 郑士旺 | M100: 已完成 | N100: 46202 | O100: 46206 | P100: 石军磊、刘凯 | Q100: 已完成 | R100: 46227 | S100: 46227 | T100: 贺航 | U100: 已完成 | V100: 46227 | W100: 46227 | X100: 袁丽荣 | Y100: 已完成 | Z100: 46216 | AA100: 46234 | AB100: =(IF(M100="已完成",1,IF(M100="进行中",0.5,0))*15%+IF(Q100="已完成",1,IF(Q100="进行中",0.5,0))*35%+IF(U100="已完成",1,IF(U100="进行中",0.5,0))*30%+IF(Y100="已完成",1,IF(Y100="进行中",0.5,0))*20%) -> 1 | AC100: =IF(G100="已完成","正常",IF(OR(G100="暂停",G100="挂起"),"暂停",IF(J100="","日期缺失",IF(J100<项目驾驶舱!$B$3,"已延期",IF(J100<=项目驾驶舱!$B$3+7,"临近到期","正常"))))) -> 正常 | AD100: 69 | AE100: 69
...

Sheet 资源计划
A1: 资源计划
A2: 汇总业务、后端、前端和测试任务分配。黄色区域用于填写可用工时、任务投入工时和资源调整说明。
A4: 人员 | B4: 角色 | C4: 任务数 | D4: 未完成任务 | E4: 最早开始 | F4: 最晚结束 | G4: 周可用工时 | H4: 计划投入工时 | I4: 负荷率 | J4: 负荷判断 | K4: 资源建议 | L4: 备注
A5: 刘凯 | B5: 后端 | C5: 125 | D5: 125 | E5: 46195 | F5: 46339 | G5: 40 | H5: 840 | I5: 1 | J5: 高负荷 | K5: 确认优先级并预留缓冲
A6: 常浩 | B6: 全栈、后端 | C6: 14 | D6: 14 | E6: 46212 | F6: 46339 | G6: 40 | H6: 720 | I6: 0.94736842 | J6: 高负荷 | K6: 确认优先级并预留缓冲
A7: 石军磊 | B7: 后端 | C7: 125 | D7: 125 | E7: 46195 | F7: 46339 | G7: 40 | H7: 840 | I7: 1 | J7: 高负荷 | K7: 确认优先级并预留缓冲
A8: 袁丽荣 | B8: 测试 | C8: 139 | D8: 139 | E8: 46202 | F8: 46353 | G8: 40 | H8: 520 | I8: 0.59090909 | J8: 正常 | K8: 按计划跟踪
A9: 贺航 | B9: 前端 | C9: 129 | D9: 129 | E9: 46195 | F9: 46339 | G9: 40 | H9: 840 | I9: 1 | J9: 高负荷 | K9: 确认优先级并预留缓冲
A10: 郑士旺 | B10: 业务 | C10: 139 | D10: 139 | E10: 46202 | F10: 46241 | G10: 40 | H10: 240 | I10: 1 | J10: 高负荷 | K10: 确认优先级并预留缓冲
A13: 资源周计划
A14: 任务名称、状态和日期直接引用总控台账；新增任务或调整责任人后，重新执行V2更新以扩展明细行。
A15: 人员 | B15: 周开始 | C15: 周结束 | D15: 是否有任务 | E15: 任务数 | F15: 周计划工时 | G15: 负荷率 | H15: 负荷判断 | I15: 任务清单
A16: 刘凯 | B16: 46195 | C16: 46201 | D16: 有 | E16: 4 | F16: 40 | G16: 1 | H16: 高负荷 | I16: T058 OCR识别及编辑；T069 新增、详情、修改页内容调整；T070 生成报告；T071 装船作业信息录入优化（太仓） | L16: 刘凯
B17: 46202 | C17: 46208 | D17: 有 | E17: 4 | F17: 40 | G17: 1 | H17: 高负荷 | I17: T058 OCR识别及编辑；T069 新增、详情、修改页内容调整；T070 生成报告；T071 装船作业信息录入优化（太仓） | L17: 刘凯
B18: 46209 | C18: 46215 | D18: 有 | E18: 22 | F18: 40 | G18: 1 | H18: 高负荷 | I18: T001 新增车辆信息；T002 修改车辆信息；T003 删除车辆信息；T004 查询展示车辆信息；T006 优化收费标准（装卸费）新增；T007 优化收费标准（装卸费）编辑；T008 优化收费标准（装卸费）详情；T009 优化采样方式新增；T010 优化采样方式编辑；T011 获取报单数据及展示；T012 应单入口；T060 货权录入；T061 货权修改；T062 获取查询；T063 卸船作业货权跟踪；T064 卸船作业货权跟踪；T065 装船作业货权跟踪；T066 装船作业货权跟踪；T067 装船作业货权跟踪；T068 装船作业货权跟踪；T072 OCR识别；T096 自动生成装船港杂费 | L18: 刘凯
B19: 46216 | C19: 46222 | D19: 有 | E19: 22 | F19: 40 | G19: 1 | H19: 高负荷 | I19: T001 新增车辆信息；T002 修改车辆信息；T003 删除车辆信息；T004 查询展示车辆信息；T006 优化收费标准（装卸费）新增；T007 优化收费标准（装卸费）编辑；T008 优化收费标准（装卸费）详情；T009 优化采样方式新增；T010 优化采样方式编辑；T011 获取报单数据及展示；T012 应单入口；T060 货权录入；T061 货权修改；T062 获取查询；T063 卸船作业货权跟踪；T064 卸船作业货权跟踪；T065 装船作业货权跟踪；T066 装船作业货权跟踪；T067 装船作业货权跟踪；T068 装船作业货权跟踪；T072 OCR识别；T096 自动生成装船港杂费 | L19: 刘凯
B20: 46223 | C20: 46229 | D20: 有 | E20: 30 | F20: 40 | G20: 1 | H20: 高负荷 | I20: T001 新增车辆信息；T002 修改车辆信息；T003 删除车辆信息；T004 查询展示车辆信息；T006 优化收费标准（装卸费）新增；T007 优化收费标准（装卸费）编辑；T008 优化收费标准（装卸费）详情；T009 优化采样方式新增；T010 优化采样方式编辑；T011 获取报单数据及展示；T012 应单入口；T060 货权录入；T061 货权修改；T062 获取查询；T063 卸船作业货权跟踪；T064 卸船作业货权跟踪；T065 装船作业货权跟踪；T066 装船作业货权跟踪；T067 装船作业货权跟踪；T068 装船作业货权跟踪；T072 OCR识别；T096 自动生成装船港杂费；T073 采样作业信息录入新增；T074 采样作业信息录入编辑；T075 采样作业信息录入详情；T076 采样作业信息录入删除；T077 采样作业信息录入列表；T097 自动生成租赁费；T098 优化装卸费新增；T099 优化装卸费编辑 | L20: 刘凯
B21: 46230 | C21: 46236 | D21: 有 | E21: 28 | F21: 40 | G21: 1 | H21: 高负荷 | I21: T037 创建卸车流程；T038 查询卸车流程；T039 修改卸车流程；T040 创建装船流程；T041 查询装船流程；T042 修改装船流程；T043 创建卸船流程；T044 查询卸船流程；T045 修改卸船流程；T059 优化新增装车作业信息；T100 创建行业资讯数据；T101 修改行业资讯数据；T102 删除行业资讯数据；T103 展示行业资讯数据；T104 吞吐量统计（曹妃甸）；T105 泊位占用率分析（曹妃甸）；T106 堆存库存统计（曹妃甸）；T107 分货主实时统计表（曹妃甸）；T108 综合装船效率分析（曹妃甸）；T109 综合卸车效率分析（曹妃甸）；T110 综合卸船效率分析（曹妃甸）；T117 经营任务情况分析报告；T118 客户月报报告；T119 月度客户情况报告；T120 商务计划周报；T138 查询卸车流程；T139 查询装船流程；T140 查询卸船流程 | L21: 刘凯
B22: 46237 | C22: 46243 | D22: 有 | E22: 31 | F22: 40 | G22: 1 | H22: 高负荷 | I22: T037 创建卸车流程；T038 查询卸车流程；T039 修改卸车流程；T040 创建装船流程；T041 查询装船流程；T042 修改装船流程；T043 创建卸船流程；T044 查询卸船流程；T045 修改卸船流程；T059 优化新增装车作业信息；T100 创建行业资讯数据；T101 修改行业资讯数据；T102 删除行业资讯数据；T103 展示行业资讯数据；T104 吞吐量统计（曹妃甸）；T105 泊位占用率分析（曹妃甸）；T106 堆存库存统计（曹妃甸）；T107 分货主实时统计表（曹妃甸）；T108 综合装船效率分析（曹妃甸）；T109 综合卸车效率分析（曹妃甸）；T110 综合卸船效率分析（曹妃甸）；T117 经营任务情况分析报告；T118 客户月报报告；T119 月度客户情况报告；T120 商务计划周报；T138 查询卸车流程；T139 查询装船流程；T140 查询卸船流程；T143 图片上传；T144 图片上传；T145 图片上传 | L22: 刘凯
B23: 46244 | C23: 46250 | D23: 有 | E23: 30 | F23: 40 | G23: 1 | H23: 高负荷 | I23: T037 创建卸车流程；T038 查询卸车流程；T039 修改卸车流程；T040 创建装船流程；T041 查询装船流程；T042 修改装船流程；T043 创建卸船流程；T044 查询卸船流程；T045 修改卸船流程；T100 创建行业资讯数据；T101 修改行业资讯数据；T102 删除行业资讯数据；T103 展示行业资讯数据；T104 吞吐量统计（曹妃甸）；T105 泊位占用率分析（曹妃甸）；T106 堆存库存统计（曹妃甸）；T107 分货主实时统计表（曹妃甸）；T108 综合装船效率分析（曹妃甸）；T109 综合卸车效率分析（曹妃甸）；T110 综合卸船效率分析（曹妃甸）；T117 经营任务情况分析报告；T118 客户月报报告；T119 月度客户情况报告；T120 商务计划周报；T138 查询卸车流程；T139 查询装船流程；T140 查询卸船流程；T143 图片上传；T144 图片上传；T145 图片上传 | L23: 刘凯
B24: 46251 | C24: 46257 | D24: 有 | E24: 30 | F24: 40 | G24: 1 | H24: 高负荷 | I24: T037 创建卸车流程；T038 查询卸车流程；T039 修改卸车流程；T040 创建装船流程；T041 查询装船流程；T042 修改装船流程；T043 创建卸船流程；T044 查询卸船流程；T045 修改卸船流程；T100 创建行业资讯数据；T101 修改行业资讯数据；T102 删除行业资讯数据；T103 展示行业资讯数据；T104 吞吐量统计（曹妃甸）；T105 泊位占用率分析（曹妃甸）；T106 堆存库存统计（曹妃甸）；T107 分货主实时统计表（曹妃甸）；T108 综合装船效率分析（曹妃甸）；T109 综合卸车效率分析（曹妃甸）；T110 综合卸船效率分析（曹妃甸）；T117 经营任务情况分析报告；T118 客户月报报告；T119 月度客户情况报告；T120 商务计划周报；T138 查询卸车流程；T139 查询装船流程；T140 查询卸船流程；T143 图片上传；T144 图片上传；T145 图片上传 | L24: 刘凯
B25: 46258 | C25: 46264 | D25: 有 | E25: 27 | F25: 40 | G25: 1 | H25: 高负荷 | I25: T037 创建卸车流程；T038 查询卸车流程；T039 修改卸车流程；T040 创建装船流程；T041 查询装船流程；T042 修改装船流程；T043 创建卸船流程；T044 查询卸船流程；T045 修改卸船流程；T100 创建行业资讯数据；T101 修改行业资讯数据；T102 删除行业资讯数据；T103 展示行业资讯数据；T104 吞吐量统计（曹妃甸）；T105 泊位占用率分析（曹妃甸）；T106 堆存库存统计（曹妃甸）；T107 分货主实时统计表（曹妃甸）；T108 综合装船效率分析（曹妃甸）；T109 综合卸车效率分析（曹妃甸）；T110 综合卸船效率分析（曹妃甸）；T117 经营任务情况分析报告；T118 客户月报报告；T119 月度客户情况报告；T120 商务计划周报；T138 查询卸车流程；T139 查询装船流程；T140 查询卸船流程 | L25: 刘凯
B26: 46265 | C26: 46271 | D26: 有 | E26: 13 | F26: 40 | G26: 1 | H26: 高负荷 | I26: T121 船舶供应服务查询；T122 船舶预到（内贸）查询；T123 台账查询；T124 停泊费（内贸）查询；T125 船舶供应服务费（内贸）查询；T020 查询卸车计划；T021 外部客户确认；T026 创建卸船作业委托信息；T027 修改卸船作业委托信息；T030 查询卸船作业委托信息；T034 新增船舶靠泊通知单；T035 审批船舶靠泊通知单；T036 查询船舶靠泊通知单 | L26: 刘凯
B27: 46272 | C27: 46278 | D27: 有 | E27: 23 | F27: 40 | G27: 1 | H27: 高负荷 | I27: T020 查询卸车计划；T021 外部客户确认；T026 创建卸船作业委托信息；T027 修改卸船作业委托信息；T030 查询卸船作业委托信息；T034 新增船舶靠泊通知单；T035 审批船舶靠泊通知单；T036 查询船舶靠泊通知单；T013 新增结算条款；T014 结算条款审批；T015 修改结算条款；T016 删除结算条款；T017 查询展示结算条款；T018 结算条款推送法务系统；T053 接入港口侧视频监控；T054 视频查看权限申请；T055 视频查看权限审批；T056 视频查看权限有效期控制；T057 外网PC端视频监控查询；T078 业务数据合同签订校验；T079 结算数据合同签订校验；T080 合同校验结果查询；T141 视频监控查询 | L27: 刘凯
B28: 46279 | C28: 46285 | D28: 有 | E28: 15 | F28: 40 | G28: 1 | H28: 高负荷 | I28: T013 新增结算条款；T014 结算条款审批；T015 修改结算条款；T016 删除结算条款；T017 查询展示结算条款；T018 结算条款推送法务系统；T053 接入港口侧视频监控；T054 视频查看权限申请；T055 视频查看权限审批；T056 视频查看权限有效期控制；T057 外网PC端视频监控查询；T078 业务数据合同签订校验；T079 结算数据合同签订校验；T080 合同校验结果查询；T141 视频监控查询 | L28: 刘凯
... B36: 46335 | C36: 46341 | D36: 有 | E36: 32 | F36: 40 | G36: 1 | H36: 高负荷 | I36: T005 船舶唯一性校验；T019 对接卸船计划；T022 对接卸船作业信息；T023 查询卸船作业信息；T024 卸船查询列表；T025 卸船查询详情；T028 作废卸船作业委托信息；T029 推送卸船作业委托信息；T046 新增船舶预到（外贸）；T047 退回船舶预到（外贸）；T048 退回船舶预到（外贸）；T049 申请采样申请（外贸）；T081 数据对接；T082 数据展示；T083 数据对接；T084 数据产生；T089 新增采样服务费（外贸）；T090 审批采样服务费（外贸）；T091 单据签章；T092 数据推送；T093 数据对接；T094 数据展示；T126 停泊费（外贸）查询；T127 锚泊费（外贸）查询；T130 采样服务费（外贸）查询；T131 船舶供应服务费（外贸）查询；T132 新增船舶靠泊通知单；T133 查询船舶靠泊通知单；T134 卸船计划查询；T135 卸船查询；T136 卸船作业委托；T142 审批船舶靠泊通知单 | L36: 刘凯
B37: 46342 | C37: 46348 | D37: 无 | E37: 0 | F37: 0 | G37: 0 | H37: 无任务 | L37: 刘凯
B38: 46349 | C38: 46355 | D38: 无 | E38: 0 | F38: 0 | G38: 0 | H38: 无任务 | L38: 刘凯
A39: 常浩 | B39: 46195 | C39: 46201 | D39: 无 | E39: 0 | F39: 0 | G39: 0 | H39: 无任务 | L39: 常浩
B40: 46202 | C40: 46208 | D40: 无 | E40: 0 | F40: 0 | G40: 0 | H40: 无任务 | L40: 常浩
B41: 46209 | C41: 46215 | D41: 有 | E41: 3 | F41: 40 | G41: 1 | H41: 高负荷 | I41: T050 维护需跟踪船舶清单；T051 根据船舶清单更新第三方系统推送数据船舶清单；T052 船舶轨迹跟踪 | L41: 常浩
B42: 46216 | C42: 46222 | D42: 有 | E42: 3 | F42: 40 | G42: 1 | H42: 高负荷 | I42: T050 维护需跟踪船舶清单；T051 根据船舶清单更新第三方系统推送数据船舶清单；T052 船舶轨迹跟踪 | L42: 常浩
B43: 46223 | C43: 46229 | D43: 有 | E43: 3 | F43: 40 | G43: 1 | H43: 高负荷 | I43: T050 维护需跟踪船舶清单；T051 根据船舶清单更新第三方系统推送数据船舶清单；T052 船舶轨迹跟踪 | L43: 常浩
B44: 46230 | C44: 46236 | D44: 有 | E44: 3 | F44: 40 | G44: 1 | H44: 高负荷 | I44: T050 维护需跟踪船舶清单；T051 根据船舶清单更新第三方系统推送数据船舶清单；T052 船舶轨迹跟踪 | L44: 常浩
B45: 46237 | C45: 46243 | D45: 有 | E45: 3 | F45: 40 | G45: 1 | H45: 高负荷 | I45: T050 维护需跟踪船舶清单；T051 根据船舶清单更新第三方系统推送数据船舶清单；T052 船舶轨迹跟踪 | L45: 常浩
B46: 46244 | C46: 46250 | D46: 有 | E46: 3 | F46: 40 | G46: 1 | H46: 高负荷 | I46: T050 维护需跟踪船舶清单；T051 根据船舶清单更新第三方系统推送数据船舶清单；T052 船舶轨迹跟踪 | L46: 常浩
B47: 46251 | C47: 46257 | D47: 有 | E47: 3 | F47: 40 | G47: 1 | H47: 高负荷 | I47: T050 维护需跟踪船舶清单；T051 根据船舶清单更新第三方系统推送数据船舶清单；T052 船舶轨迹跟踪 | L47: 常浩
B48: 46258 | C48: 46264 | D48: 有 | E48: 3 | F48: 40 | G48: 1 | H48: 高负荷 | I48: T050 维护需跟踪船舶清单；T051 根据船舶清单更新第三方系统推送数据船舶清单；T052 船舶轨迹跟踪 | L48: 常浩
B49: 46265 | C49: 46271 | D49: 有 | E49: 4 | F49: 40 | G49: 1 | H49: 高负荷 | I49: T095 自动生成堆存费；T050 维护需跟踪船舶清单；T051 根据船舶清单更新第三方系统推送数据船舶清单；T052 船舶轨迹跟踪 | L49: 常浩
B50: 46272 | C50: 46278 | D50: 有 | E50: 1 | F50: 40 | G50: 1 | H50: 高负荷 | I50: T095 自动生成堆存费 | L50: 常浩
B51: 46279 | C51: 46285 | D51: 无 | E51: 0 | F51: 0 | G51: 0 | H51: 无任务 | L51: 常浩
B52: 46286 | C52: 46292 | D52: 有 | E52: 3 | F52: 40 | G52: 1 | H52: 高负荷 | I52: T031 创建外轮转内贸业务信息；T032 作废外轮转内贸业务信息；T033 查询外轮转内贸业务信息 | L52: 常浩
B53: 46293 | C53: 46299 | D53: 有 | E53: 4 | F53: 40 | G53: 1 | H53: 高负荷 | I53: T085 数据对接；T087 数据对接；T088 数据展示；T086 数据展示 | L53: 常浩
B54: 46300 | C54: 46306 | D54: 有 | E54: 4 | F54: 40 | G54: 1 | H54: 高负荷 | I54: T085 数据对接；T087 数据对接；T088 数据展示；T086 数据展示 | L54: 常浩
B55: 46307 | C55: 46313 | D55: 有 | E55: 7 | F55: 40 | G55: 1 | H55: 高负荷 | I55: T085 数据对接；T087 数据对接；T088 数据展示；T128 堆存费（外贸）查询；T129 卸船费（外贸）查询；T137 外轮转内贸业务查询；T086 数据展示 | L55: 常浩
B56: 46314 | C56: 46320 | D56: 有 | E56: 3 | F56: 40 | G56: 1 | H56: 高负荷 | I56: T128 堆存费（外贸）查询；T129 卸船费（外贸）查询；T137 外轮转内贸业务查询 | L56: 常浩
B57: 46321 | C57: 46327 | D57: 有 | E57: 3 | F57: 40 | G57: 1 | H57: 高负荷 | I57: T128 堆存费（外贸）查询；T129 卸船费（外贸）查询；T137 外轮转内贸业务查询 | L57: 常浩
B58: 46328 | C58: 46334 | D58: 有 | E58: 3 | F58: 40 | G58: 1 | H58: 高负荷 | I58: T128 堆存费（外贸）查询；T129 卸船费（外贸）查询；T137 外轮转内贸业务查询 | L58: 常浩
B59: 46335 | C59: 46341 | D59: 有 | E59: 3 | F59: 40 | G59: 1 | H59: 高负荷 | I59: T128 堆存费（外贸）查询；T129 卸船费（外贸）查询；T137 外轮转内贸业务查询 | L59: 常浩
B60: 46342 | C60: 46348 | D60: 无 | E60: 0 | F60: 0 | G60: 0 | H60: 无任务 | L60: 常浩
B61: 46349 | C61: 46355 | D61: 无 | E61: 0 | F61: 0 | G61: 0 | H61: 无任务 | L61: 常浩
A62: 石军磊 | B62: 46195 | C62: 46201 | D62: 有 | E62: 4 | F62: 40 | G62: 1 | H62: 高负荷 | I62: T058 OCR识别及编辑；T069 新增、详情、修改页内容调整；T070 生成报告；T071 装船作业信息录入优化（太仓） | L62: 石军磊
B63: 46202 | C63: 46208 | D63: 有 | E63: 4 | F63: 40 | G63: 1 | H63: 高负荷 | I63: T058 OCR识别及编辑；T069 新增、详情、修改页内容调整；T070 生成报告；T071 装船作业信息录入优化（太仓） | L63: 石军磊
B64: 46209 | C64: 46215 | D64: 有 | E64: 22 | F64: 40 | G64: 1 | H64: 高负荷 | I64: T001 新增车辆信息；T002 修改车辆信息；T003 删除车辆信息；T004 查询展示车辆信息；T006 优化收费标准（装卸费）新增；T007 优化收费标准（装卸费）编辑；T008 优化收费标准（装卸费）详情；T009 优化采样方式新增；T010 优化采样方式编辑；T011 获取报单数据及展示；T012 应单入口；T060 货权录入；T061 货权修改；T062 获取查询；T063 卸船作业货权跟踪；T064 卸船作业货权跟踪；T065 装船作业货权跟踪；T066 装船作业货权跟踪；T067 装船作业货权跟踪；T068 装船作业货权跟踪；T072 OCR识别；T096 自动生成装船港杂费 | L64: 石军磊
B65: 46216 | C65: 46222 | D65: 有 | E65: 22 | F65: 40 | G65: 1 | H65: 高负荷 | I65: T001 新增车辆信息；T002 修改车辆信息；T003 删除车辆信息；T004 查询展示车辆信息；T006 优化收费标准（装卸费）新增；T007 优化收费标准（装卸费）编辑；T008 优化收费标准（装卸费）详情；T009 优化采样方式新增；T010 优化采样方式编辑；T011 获取报单数据及展示；T012 应单入口；T060 货权录入；T061 货权修改；T062 获取查询；T063 卸船作业货权跟踪；T064 卸船作业货权跟踪；T065 装船作业货权跟踪；T066 装船作业货权跟踪；T067 装船作业货权跟踪；T068 装船作业货权跟踪；T072 OCR识别；T096 自动生成装船港杂费 | L65: 石军磊
B66: 46223 | C66: 46229 | D66: 有 | E66: 30 | F66: 40 | G66: 1 | H66: 高负荷 | I66: T001 新增车辆信息；T002 修改车辆信息；T003 删除车辆信息；T004 查询展示车辆信息；T006 优化收费标准（装卸费）新增；T007 优化收费标准（装卸费）编辑；T008 优化收费标准（装卸费）详情；T009 优化采样方式新增；T010 优化采样方式编辑；T011 获取报单数据及展示；T012 应单入口；T060 货权录入；T061 货权修改；T062 获取查询；T063 卸船作业货权跟踪；T064 卸船作业货权跟踪；T065 装船作业货权跟踪；T066 装船作业货权跟踪；T067 装船作业货权跟踪；T068 装船作业货权跟踪；T072 OCR识别；T096 自动生成装船港杂费；T073 采样作业信息录入新增；T074 采样作业信息录入编辑；T075 采样作业信息录入详情；T076 采样作业信息录入删除；T077 采样作业信息录入列表；T097 自动生成租赁费；T098 优化装卸费新增；T099 优化装卸费编辑 | L66: 石军磊
B67: 46230 | C67: 46236 | D67: 有 | E67: 28 | F67: 40 | G67: 1 | H67: 高负荷 | I67: T037 创建卸车流程；T038 查询卸车流程；T039 修改卸车流程；T040 创建装船流程；T041 查询装船流程；T042 修改装船流程；T043 创建卸船流程；T044 查询卸船流程；T045 修改卸船流程；T059 优化新增装车作业信息；T100 创建行业资讯数据；T101 修改行业资讯数据；T102 删除行业资讯数据；T103 展示行业资讯数据；T104 吞吐量统计（曹妃甸）；T105 泊位占用率分析（曹妃甸）；T106 堆存库存统计（曹妃甸）；T107 分货主实时统计表（曹妃甸）；T108 综合装船效率分析（曹妃甸）；T109 综合卸车效率分析（曹妃甸）；T110 综合卸船效率分析（曹妃甸）；T117 经营任务情况分析报告；T118 客户月报报告；T119 月度客户情况报告；T120 商务计划周报；T138 查询卸车流程；T139 查询装船流程；T140 查询卸船流程 | L67: 石军磊
B68: 46237 | C68: 46243 | D68: 有 | E68: 31 | F68: 40 | G68: 1 | H68: 高负荷 | I68: T037 创建卸车流程；T038 查询卸车流程；T039 修改卸车流程；T040 创建装船流程；T041 查询装船流程；T042 修改装船流程；T043 创建卸船流程；T044 查询卸船流程；T045 修改卸船流程；T059 优化新增装车作业信息；T100 创建行业资讯数据；T101 修改行业资讯数据；T102 删除行业资讯数据；T103 展示行业资讯数据；T104 吞吐量统计（曹妃甸）；T105 泊位占用率分析（曹妃甸）；T106 堆存库存统计（曹妃甸）；T107 分货主实时统计表（曹妃甸）；T108 综合装船效率分析（曹妃甸）；T109 综合卸车效率分析（曹妃甸）；T110 综合卸船效率分析（曹妃甸）；T117 经营任务情况分析报告；T118 客户月报报告；T119 月度客户情况报告；T120 商务计划周报；T138 查询卸车流程；T139 查询装船流程；T140 查询卸船流程；T143 图片上传；T144 图片上传；T145 图片上传 | L68: 石军磊
B69: 46244 | C69: 46250 | D69: 有 | E69: 30 | F69: 40 | G69: 1 | H69: 高负荷 | I69: T037 创建卸车流程；T038 查询卸车流程；T039 修改卸车流程；T040 创建装船流程；T041 查询装船流程；T042 修改装船流程；T043 创建卸船流程；T044 查询卸船流程；T045 修改卸船流程；T100 创建行业资讯数据；T101 修改行业资讯数据；T102 删除行业资讯数据；T103 展示行业资讯数据；T104 吞吐量统计（曹妃甸）；T105 泊位占用率分析（曹妃甸）；T106 堆存库存统计（曹妃甸）；T107 分货主实时统计表（曹妃甸）；T108 综合装船效率分析（曹妃甸）；T109 综合卸车效率分析（曹妃甸）；T110 综合卸船效率分析（曹妃甸）；T117 经营任务情况分析报告；T118 客户月报报告；T119 月度客户情况报告；T120 商务计划周报；T138 查询卸车流程；T139 查询装船流程；T140 查询卸船流程；T143 图片上传；T144 图片上传；T145 图片上传 | L69: 石军磊
B70: 46251 | C70: 46257 | D70: 有 | E70: 30 | F70: 40 | G70: 1 | H70: 高负荷 | I70: T037 创建卸车流程；T038 查询卸车流程；T039 修改卸车流程；T040 创建装船流程；T041 查询装船流程；T042 修改装船流程；T043 创建卸船流程；T044 查询卸船流程；T045 修改卸船流程；T100 创建行业资讯数据；T101 修改行业资讯数据；T102 删除行业资讯数据；T103 展示行业资讯数据；T104 吞吐量统计（曹妃甸）；T105 泊位占用率分析（曹妃甸）；T106 堆存库存统计（曹妃甸）；T107 分货主实时统计表（曹妃甸）；T108 综合装船效率分析（曹妃甸）；T109 综合卸车效率分析（曹妃甸）；T110 综合卸船效率分析（曹妃甸）；T117 经营任务情况分析报告；T118 客户月报报告；T119 月度客户情况报告；T120 商务计划周报；T138 查询卸车流程；T139 查询装船流程；T140 查询卸船流程；T143 图片上传；T144 图片上传；T145 图片上传 | L70: 石军磊
B71: 46258 | C71: 46264 | D71: 有 | E71: 27 | F71: 40 | G71: 1 | H71: 高负荷 | I71: T037 创建卸车流程；T038 查询卸车流程；T039 修改卸车流程；T040 创建装船流程；T041 查询装船流程；T042 修改装船流程；T043 创建卸船流程；T044 查询卸船流程；T045 修改卸船流程；T100 创建行业资讯数据；T101 修改行业资讯数据；T102 删除行业资讯数据；T103 展示行业资讯数据；T104 吞吐量统计（曹妃甸）；T105 泊位占用率分析（曹妃甸）；T106 堆存库存统计（曹妃甸）；T107 分货主实时统计表（曹妃甸）；T108 综合装船效率分析（曹妃甸）；T109 综合卸车效率分析（曹妃甸）；T110 综合卸船效率分析（曹妃甸）；T117 经营任务情况分析报告；T118 客户月报报告；T119 月度客户情况报告；T120 商务计划周报；T138 查询卸车流程；T139 查询装船流程；T140 查询卸船流程 | L71: 石军磊
B72: 46265 | C72: 46271 | D72: 有 | E72: 13 | F72: 40 | G72: 1 | H72: 高负荷 | I72: T121 船舶供应服务查询；T122 船舶预到（内贸）查询；T123 台账查询；T124 停泊费（内贸）查询；T125 船舶供应服务费（内贸）查询；T020 查询卸车计划；T021 外部客户确认；T026 创建卸船作业委托信息；T027 修改卸船作业委托信息；T030 查询卸船作业委托信息；T034 新增船舶靠泊通知单；T035 审批船舶靠泊通知单；T036 查询船舶靠泊通知单 | L72: 石军磊
B73: 46272 | C73: 46278 | D73: 有 | E73: 23 | F73: 40 | G73: 1 | H73: 高负荷 | I73: T020 查询卸车计划；T021 外部客户确认；T026 创建卸船作业委托信息；T027 修改卸船作业委托信息；T030 查询卸船作业委托信息；T034 新增船舶靠泊通知单；T035 审批船舶靠泊通知单；T036 查询船舶靠泊通知单；T013 新增结算条款；T014 结算条款审批；T015 修改结算条款；T016 删除结算条款；T017 查询展示结算条款；T018 结算条款推送法务系统；T053 接入港口侧视频监控；T054 视频查看权限申请；T055 视频查看权限审批；T056 视频查看权限有效期控制；T057 外网PC端视频监控查询；T078 业务数据合同签订校验；T079 结算数据合同签订校验；T080 合同校验结果查询；T141 视频监控查询 | L73: 石军磊
B74: 46279 | C74: 46285 | D74: 有 | E74: 15 | F74: 40 | G74: 1 | H74: 高负荷 | I74: T013 新增结算条款；T014 结算条款审批；T015 修改结算条款；T016 删除结算条款；T017 查询展示结算条款；T018 结算条款推送法务系统；T053 接入港口侧视频监控；T054 视频查看权限申请；T055 视频查看权限审批；T056 视频查看权限有效期控制；T057 外网PC端视频监控查询；T078 业务数据合同签订校验；T079 结算数据合同签订校验；T080 合同校验结果查询；T141 视频监控查询 | L74: 石军磊
... B82: 46335 | C82: 46341 | D82: 有 | E82: 32 | F82: 40 | G82: 1 | H82: 高负荷 | I82: T005 船舶唯一性校验；T019 对接卸船计划；T022 对接卸船作业信息；T023 查询卸船作业信息；T024 卸船查询列表；T025 卸船查询详情；T028 作废卸船作业委托信息；T029 推送卸船作业委托信息；T046 新增船舶预到（外贸）；T047 退回船舶预到（外贸）；T048 退回船舶预到（外贸）；T049 申请采样申请（外贸）；T081 数据对接；T082 数据展示；T083 数据对接；T084 数据产生；T089 新增采样服务费（外贸）；T090 审批采样服务费（外贸）；T091 单据签章；T092 数据推送；T093 数据对接；T094 数据展示；T126 停泊费（外贸）查询；T127 锚泊费（外贸）查询；T130 采样服务费（外贸）查询；T131 船舶供应服务费（外贸）查询；T132 新增船舶靠泊通知单；T133 查询船舶靠泊通知单；T134 卸船计划查询；T135 卸船查询；T136 卸船作业委托；T142 审批船舶靠泊通知单 | L82: 石军磊
B83: 46342 | C83: 46348 | D83: 无 | E83: 0 | F83: 0 | G83: 0 | H83: 无任务 | L83: 石军磊
B84: 46349 | C84: 46355 | D84: 无 | E84: 0 | F84: 0 | G84: 0 | H84: 无任务 | L84: 石军磊
A85: 袁丽荣 | B85: 46195 | C85: 46201 | D85: 无 | E85: 0 | F85: 0 | G85: 0 | H85: 无任务 | L85: 袁丽荣
B86: 46202 | C86: 46208 | D86: 有 | E86: 3 | F86: 40 | G86: 1 | H86: 高负荷 | I86: T058 OCR识别及编辑；T070 生成报告；T071 装船作业信息录入优化（太仓） | L86: 袁丽荣
B87: 46209 | C87: 46215 | D87: 有 | E87: 3 | F87: 40 | G87: 1 | H87: 高负荷 | I87: T058 OCR识别及编辑；T070 生成报告；T071 装船作业信息录入优化（太仓） | L87: 袁丽荣
B88: 46216 | C88: 46222 | D88: 有 | E88: 35 | F88: 40 | G88: 1 | H88: 高负荷 | I88: T001 新增车辆信息；T002 修改车辆信息；T003 删除车辆信息；T004 查询展示车辆信息；T006 优化收费标准（装卸费）新增；T007 优化收费标准（装卸费）编辑；T008 优化收费标准（装卸费）详情；T009 优化采样方式新增；T010 优化采样方式编辑；T011 获取报单数据及展示；T012 应单入口；T050 维护需跟踪船舶清单；T051 根据船舶清单更新第三方系统推送数据船舶清单；T052 船舶轨迹跟踪；T060 货权录入；T061 货权修改；T062 获取查询；T063 卸船作业货权跟踪；T064 卸船作业货权跟踪；T065 装船作业货权跟踪；T066 装船作业货权跟踪；T067 装船作业货权跟踪；T068 装船作业货权跟踪；T069 新增、详情、修改页内容调整；T072 OCR识别；T073 采样作业信息录入新增；T074 采样作业信息录入编辑；T075 采样作业信息录入详情；T076 采样作业信息录入删除；T077 采样作业信息录入列表；T095 自动生成堆存费；T096 自动生成装船港杂费；T097 自动生成租赁费；T098 优化装卸费新增；T099 优化装卸费编辑 | L88: 袁丽荣
B89: 46223 | C89: 46229 | D89: 有 | E89: 35 | F89: 40 | G89: 1 | H89: 高负荷 | I89: T001 新增车辆信息；T002 修改车辆信息；T003 删除车辆信息；T004 查询展示车辆信息；T006 优化收费标准（装卸费）新增；T007 优化收费标准（装卸费）编辑；T008 优化收费标准（装卸费）详情；T009 优化采样方式新增；T010 优化采样方式编辑；T011 获取报单数据及展示；T012 应单入口；T050 维护需跟踪船舶清单；T051 根据船舶清单更新第三方系统推送数据船舶清单；T052 船舶轨迹跟踪；T060 货权录入；T061 货权修改；T062 获取查询；T063 卸船作业货权跟踪；T064 卸船作业货权跟踪；T065 装船作业货权跟踪；T066 装船作业货权跟踪；T067 装船作业货权跟踪；T068 装船作业货权跟踪；T069 新增、详情、修改页内容调整；T072 OCR识别；T073 采样作业信息录入新增；T074 采样作业信息录入编辑；T075 采样作业信息录入详情；T076 采样作业信息录入删除；T077 采样作业信息录入列表；T095 自动生成堆存费；T096 自动生成装船港杂费；T097 自动生成租赁费；T098 优化装卸费新增；T099 优化装卸费编辑 | L89: 袁丽荣
B90: 46230 | C90: 46236 | D90: 有 | E90: 35 | F90: 40 | G90: 1 | H90: 高负荷 | I90: T001 新增车辆信息；T002 修改车辆信息；T003 删除车辆信息；T004 查询展示车辆信息；T006 优化收费标准（装卸费）新增；T007 优化收费标准（装卸费）编辑；T008 优化收费标准（装卸费）详情；T009 优化采样方式新增；T010 优化采样方式编辑；T011 获取报单数据及展示；T012 应单入口；T050 维护需跟踪船舶清单；T051 根据船舶清单更新第三方系统推送数据船舶清单；T052 船舶轨迹跟踪；T060 货权录入；T061 货权修改；T062 获取查询；T063 卸船作业货权跟踪；T064 卸船作业货权跟踪；T065 装船作业货权跟踪；T066 装船作业货权跟踪；T067 装船作业货权跟踪；T068 装船作业货权跟踪；T069 新增、详情、修改页内容调整；T072 OCR识别；T073 采样作业信息录入新增；T074 采样作业信息录入编辑；T075 采样作业信息录入详情；T076 采样作业信息录入删除；T077 采样作业信息录入列表；T095 自动生成堆存费；T096 自动生成装船港杂费；T097 自动生成租赁费；T098 优化装卸费新增；T099 优化装卸费编辑 | L90: 袁丽荣
B91: 46237 | C91: 46243 | D91: 无 | E91: 0 | F91: 0 | G91: 0 | H91: 无任务 | L91: 袁丽荣
B92: 46244 | C92: 46250 | D92: 无 | E92: 0 | F92: 0 | G92: 0 | H92: 无任务 | L92: 袁丽荣
B93: 46251 | C93: 46257 | D93: 有 | E93: 27 | F93: 40 | G93: 1 | H93: 高负荷 | I93: T143 图片上传；T144 图片上传；T145 图片上传；T037 创建卸车流程；T038 查询卸车流程；T039 修改卸车流程；T040 创建装船流程；T041 查询装船流程；T042 修改装船流程；T043 创建卸船流程；T044 查询卸船流程；T045 修改卸船流程；T100 创建行业资讯数据；T101 修改行业资讯数据；T102 删除行业资讯数据；T103 展示行业资讯数据；T104 吞吐量统计（曹妃甸）；T105 泊位占用率分析（曹妃甸）；T106 堆存库存统计（曹妃甸）；T107 分货主实时统计表（曹妃甸）；T108 综合装船效率分析（曹妃甸）；T109 综合卸车效率分析（曹妃甸）；T110 综合卸船效率分析（曹妃甸）；T117 经营任务情况分析报告；T118 客户月报报告；T119 月度客户情况报告；T120 商务计划周报 | L93: 袁丽荣
B94: 46258 | C94: 46264 | D94: 有 | E94: 27 | F94: 40 | G94: 1 | H94: 高负荷 | I94: T143 图片上传；T144 图片上传；T145 图片上传；T037 创建卸车流程；T038 查询卸车流程；T039 修改卸车流程；T040 创建装船流程；T041 查询装船流程；T042 修改装船流程；T043 创建卸船流程；T044 查询卸船流程；T045 修改卸船流程；T100 创建行业资讯数据；T101 修改行业资讯数据；T102 删除行业资讯数据；T103 展示行业资讯数据；T104 吞吐量统计（曹妃甸）；T105 泊位占用率分析（曹妃甸）；T106 堆存库存统计（曹妃甸）；T107 分货主实时统计表（曹妃甸）；T108 综合装船效率分析（曹妃甸）；T109 综合卸车效率分析（曹妃甸）；T110 综合卸船效率分析（曹妃甸）；T117 经营任务情况分析报告；T118 客户月报报告；T119 月度客户情况报告；T120 商务计划周报 | L94: 袁丽荣
B95: 46265 | C95: 46271 | D95: 有 | E95: 27 | F95: 40 | G95: 1 | H95: 高负荷 | I95: T143 图片上传；T144 图片上传；T145 图片上传；T037 创建卸车流程；T038 查询卸车流程；T039 修改卸车流程；T040 创建装船流程；T041 查询装船流程；T042 修改装船流程；T043 创建卸船流程；T044 查询卸船流程；T045 修改卸船流程；T100 创建行业资讯数据；T101 修改行业资讯数据；T102 删除行业资讯数据；T103 展示行业资讯数据；T104 吞吐量统计（曹妃甸）；T105 泊位占用率分析（曹妃甸）；T106 堆存库存统计（曹妃甸）；T107 分货主实时统计表（曹妃甸）；T108 综合装船效率分析（曹妃甸）；T109 综合卸车效率分析（曹妃甸）；T110 综合卸船效率分析（曹妃甸）；T117 经营任务情况分析报告；T118 客户月报报告；T119 月度客户情况报告；T120 商务计划周报 | L95: 袁丽荣
B96: 46272 | C96: 46278 | D96: 有 | E96: 5 | F96: 40 | G96: 1 | H96: 高负荷 | I96: T121 船舶供应服务查询；T122 船舶预到（内贸）查询；T123 台账查询；T124 停泊费（内贸）查询；T125 船舶供应服务费（内贸）查询 | L96: 袁丽荣
B97: 46279 | C97: 46285 | D97: 无 | E97: 0 | F97: 0 | G97: 0 | H97: 无任务 | L97: 袁丽荣
B98: 46286 | C98: 46292 | D98: 无 | E98: 0 | F98: 0 | G98: 0 | H98: 无任务 | L98: 袁丽荣
B99: 46293 | C99: 46299 | D99: 无 | E99: 0 | F99: 0 | G99: 0 | H99: 无任务 | L99: 袁丽荣
B100: 46300 | C100: 46306 | D100: 无 | E100: 0 | F100: 0 | G100: 0 | H100: 无任务 | L100: 袁丽荣
B101: 46307 | C101: 46313 | D101: 有 | E101: 16 | F101: 40 | G101: 1 | H101: 高负荷 | I101: T013 新增结算条款；T014 结算条款审批；T015 修改结算条款；T016 删除结算条款；T017 查询展示结算条款；T018 结算条款推送法务系统；T053 接入港口侧视频监控；T054 视频查看权限申请；T055 视频查看权限审批；T056 视频查看权限有效期控制；T057 外网PC端视频监控查询；T059 优化新增装车作业信息；T078 业务数据合同签订校验；T079 结算数据合同签订校验；T080 合同校验结果查询；T141 视频监控查询 | L101: 袁丽荣
B102: 46314 | C102: 46320 | D102: 有 | E102: 16 | F102: 40 | G102: 1 | H102: 高负荷 | I102: T013 新增结算条款；T014 结算条款审批；T015 修改结算条款；T016 删除结算条款；T017 查询展示结算条款；T018 结算条款推送法务系统；T053 接入港口侧视频监控；T054 视频查看权限申请；T055 视频查看权限审批；T056 视频查看权限有效期控制；T057 外网PC端视频监控查询；T059 优化新增装车作业信息；T078 业务数据合同签订校验；T079 结算数据合同签订校验；T080 合同校验结果查询；T141 视频监控查询 | L102: 袁丽荣
B103: 46321 | C103: 46327 | D103: 无 | E103: 0 | F103: 0 | G103: 0 | H103: 无任务 | L103: 袁丽荣
B104: 46328 | C104: 46334 | D104: 无 | E104: 0 | F104: 0 | G104: 0 | H104: 无任务 | L104: 袁丽荣
B105: 46335 | C105: 46341 | D105: 无 | E105: 0 | F105: 0 | G105: 0 | H105: 无任务 | L105: 袁丽荣
B106: 46342 | C106: 46348 | D106: 有 | E106: 53 | F106: 40 | G106: 1 | H106: 高负荷 | I106: T005 船舶唯一性校验；T019 对接卸船计划；T020 查询卸车计划；T021 外部客户确认；T022 对接卸船作业信息；T023 查询卸船作业信息；T024 卸船查询列表；T025 卸船查询详情；T026 创建卸船作业委托信息；T027 修改卸船作业委托信息；T028 作废卸船作业委托信息；T029 推送卸船作业委托信息；T030 查询卸船作业委托信息；T031 创建外轮转内贸业务信息；T032 作废外轮转内贸业务信息；T033 查询外轮转内贸业务信息；T034 新增船舶靠泊通知单；T035 审批船舶靠泊通知单；T036 查询船舶靠泊通知单；T046 新增船舶预到（外贸）；T047 退回船舶预到（外贸）；T048 退回船舶预到（外贸）；T049 申请采样申请（外贸）；T081 数据对接；T082 数据展示；T083 数据对接；T084 数据产生；T085 数据对接；T086 数据展示；T087 数据对接；T088 数据展示；T089 新增采样服务费（外贸）；T090 审批采样服务费（外贸）；T091 单据签章；T092 数据推送；T093 数据对接；T094 数据展示；T126 停泊费（外贸）查询；T127 锚泊费（外贸）查询；T128 堆存费（外贸）查询；T129 卸船费（外贸）查询；T130 采样服务费（外贸）查询；T131 船舶供应服务费（外贸）查询；T132 新增船舶靠泊通知单；T133 查询船舶靠泊通知单；T134 卸船计划查询；T135 卸船查询；T136 卸船作业委托；T137 外轮转内贸业务查询；T138 查询卸车流程；T139 查询装船流程；T140 查询卸船流程；T142 审批船舶靠泊通知单 | L106: 袁丽荣
B107: 46349 | C107: 46355 | D107: 有 | E107: 53 | F107: 40 | G107: 1 | H107: 高负荷 | I107: T005 船舶唯一性校验；T019 对接卸船计划；T020 查询卸车计划；T021 外部客户确认；T022 对接卸船作业信息；T023 查询卸船作业信息；T024 卸船查询列表；T025 卸船查询详情；T026 创建卸船作业委托信息；T027 修改卸船作业委托信息；T028 作废卸船作业委托信息；T029 推送卸船作业委托信息；T030 查询卸船作业委托信息；T031 创建外轮转内贸业务信息；T032 作废外轮转内贸业务信息；T033 查询外轮转内贸业务信息；T034 新增船舶靠泊通知单；T035 审批船舶靠泊通知单；T036 查询船舶靠泊通知单；T046 新增船舶预到（外贸）；T047 退回船舶预到（外贸）；T048 退回船舶预到（外贸）；T049 申请采样申请（外贸）；T081 数据对接；T082 数据展示；T083 数据对接；T084 数据产生；T085 数据对接；T086 数据展示；T087 数据对接；T088 数据展示；T089 新增采样服务费（外贸）；T090 审批采样服务费（外贸）；T091 单据签章；T092 数据推送；T093 数据对接；T094 数据展示；T126 停泊费（外贸）查询；T127 锚泊费（外贸）查询；T128 堆存费（外贸）查询；T129 卸船费（外贸）查询；T130 采样服务费（外贸）查询；T131 船舶供应服务费（外贸）查询；T132 新增船舶靠泊通知单；T133 查询船舶靠泊通知单；T134 卸船计划查询；T135 卸船查询；T136 卸船作业委托；T137 外轮转内贸业务查询；T138 查询卸车流程；T139 查询装船流程；T140 查询卸船流程；T142 审批船舶靠泊通知单 | L107: 袁丽荣
A108: 贺航 | B108: 46195 | C108: 46201 | D108: 有 | E108: 4 | F108: 40 | G108: 1 | H108: 高负荷 | I108: T058 OCR识别及编辑；T069 新增、详情、修改页内容调整；T070 生成报告；T071 装船作业信息录入优化（太仓） | L108: 贺航
B109: 46202 | C109: 46208 | D109: 有 | E109: 4 | F109: 40 | G109: 1 | H109: 高负荷 | I109: T058 OCR识别及编辑；T069 新增、详情、修改页内容调整；T070 生成报告；T071 装船作业信息录入优化（太仓） | L109: 贺航
B110: 46209 | C110: 46215 | D110: 有 | E110: 25 | F110: 40 | G110: 1 | H110: 高负荷 | I110: T001 新增车辆信息；T002 修改车辆信息；T003 删除车辆信息；T004 查询展示车辆信息；T006 优化收费标准（装卸费）新增；T007 优化收费标准（装卸费）编辑；T008 优化收费标准（装卸费）详情；T009 优化采样方式新增；T010 优化采样方式编辑；T011 获取报单数据及展示；T012 应单入口；T060 货权录入；T061 货权修改；T062 获取查询；T063 卸船作业货权跟踪；T064 卸船作业货权跟踪；T065 装船作业货权跟踪；T066 装船作业货权跟踪；T067 装船作业货权跟踪；T068 装船作业货权跟踪；T072 OCR识别；T096 自动生成装船港杂费；T050 维护需跟踪船舶清单；T051 根据船舶清单更新第三方系统推送数据船舶清单；T052 船舶轨迹跟踪 | L110: 贺航
B111: 46216 | C111: 46222 | D111: 有 | E111: 25 | F111: 40 | G111: 1 | H111: 高负荷 | I111: T001 新增车辆信息；T002 修改车辆信息；T003 删除车辆信息；T004 查询展示车辆信息；T006 优化收费标准（装卸费）新增；T007 优化收费标准（装卸费）编辑；T008 优化收费标准（装卸费）详情；T009 优化采样方式新增；T010 优化采样方式编辑；T011 获取报单数据及展示；T012 应单入口；T060 货权录入；T061 货权修改；T062 获取查询；T063 卸船作业货权跟踪；T064 卸船作业货权跟踪；T065 装船作业货权跟踪；T066 装船作业货权跟踪；T067 装船作业货权跟踪；T068 装船作业货权跟踪；T072 OCR识别；T096 自动生成装船港杂费；T050 维护需跟踪船舶清单；T051 根据船舶清单更新第三方系统推送数据船舶清单；T052 船舶轨迹跟踪 | L111: 贺航
B112: 46223 | C112: 46229 | D112: 有 | E112: 33 | F112: 40 | G112: 1 | H112: 高负荷 | I112: T001 新增车辆信息；T002 修改车辆信息；T003 删除车辆信息；T004 查询展示车辆信息；T006 优化收费标准（装卸费）新增；T007 优化收费标准（装卸费）编辑；T008 优化收费标准（装卸费）详情；T009 优化采样方式新增；T010 优化采样方式编辑；T011 获取报单数据及展示；T012 应单入口；T060 货权录入；T061 货权修改；T062 获取查询；T063 卸船作业货权跟踪；T064 卸船作业货权跟踪；T065 装船作业货权跟踪；T066 装船作业货权跟踪；T067 装船作业货权跟踪；T068 装船作业货权跟踪；T072 OCR识别；T096 自动生成装船港杂费；T050 维护需跟踪船舶清单；T051 根据船舶清单更新第三方系统推送数据船舶清单；T052 船舶轨迹跟踪；T073 采样作业信息录入新增；T074 采样作业信息录入编辑；T075 采样作业信息录入详情；T076 采样作业信息录入删除；T077 采样作业信息录入列表；T097 自动生成租赁费；T098 优化装卸费新增；T099 优化装卸费编辑 | L112: 贺航
B113: 46230 | C113: 46236 | D113: 有 | E113: 31 | F113: 40 | G113: 1 | H113: 高负荷 | I113: T050 维护需跟踪船舶清单；T051 根据船舶清单更新第三方系统推送数据船舶清单；T052 船舶轨迹跟踪；T037 创建卸车流程；T038 查询卸车流程；T039 修改卸车流程；T040 创建装船流程；T041 查询装船流程；T042 修改装船流程；T043 创建卸船流程；T044 查询卸船流程；T045 修改卸船流程；T059 优化新增装车作业信息；T100 创建行业资讯数据；T101 修改行业资讯数据；T102 删除行业资讯数据；T103 展示行业资讯数据；T104 吞吐量统计（曹妃甸）；T105 泊位占用率分析（曹妃甸）；T106 堆存库存统计（曹妃甸）；T107 分货主实时统计表（曹妃甸）；T108 综合装船效率分析（曹妃甸）；T109 综合卸车效率分析（曹妃甸）；T110 综合卸船效率分析（曹妃甸）；T117 经营任务情况分析报告；T118 客户月报报告；T119 月度客户情况报告；T120 商务计划周报；T138 查询卸车流程；T139 查询装船流程；T140 查询卸船流程 | L113: 贺航
B114: 46237 | C114: 46243 | D114: 有 | E114: 34 | F114: 40 | G114: 1 | H114: 高负荷 | I114: T050 维护需跟踪船舶清单；T051 根据船舶清单更新第三方系统推送数据船舶清单；T052 船舶轨迹跟踪；T037 创建卸车流程；T038 查询卸车流程；T039 修改卸车流程；T040 创建装船流程；T041 查询装船流程；T042 修改装船流程；T043 创建卸船流程；T044 查询卸船流程；T045 修改卸船流程；T059 优化新增装车作业信息；T100 创建行业资讯数据；T101 修改行业资讯数据；T102 删除行业资讯数据；T103 展示行业资讯数据；T104 吞吐量统计（曹妃甸）；T105 泊位占用率分析（曹妃甸）；T106 堆存库存统计（曹妃甸）；T107 分货主实时统计表（曹妃甸）；T108 综合装船效率分析（曹妃甸）；T109 综合卸车效率分析（曹妃甸）；T110 综合卸船效率分析（曹妃甸）；T117 经营任务情况分析报告；T118 客户月报报告；T119 月度客户情况报告；T120 商务计划周报；T138 查询卸车流程；T139 查询装船流程；T140 查询卸船流程；T143 图片上传；T144 图片上传；T145 图片上传 | L114: 贺航
B115: 46244 | C115: 46250 | D115: 有 | E115: 33 | F115: 40 | G115: 1 | H115: 高负荷 | I115: T050 维护需跟踪船舶清单；T051 根据船舶清单更新第三方系统推送数据船舶清单；T052 船舶轨迹跟踪；T037 创建卸车流程；T038 查询卸车流程；T039 修改卸车流程；T040 创建装船流程；T041 查询装船流程；T042 修改装船流程；T043 创建卸船流程；T044 查询卸船流程；T045 修改卸船流程；T100 创建行业资讯数据；T101 修改行业资讯数据；T102 删除行业资讯数据；T103 展示行业资讯数据；T104 吞吐量统计（曹妃甸）；T105 泊位占用率分析（曹妃甸）；T106 堆存库存统计（曹妃甸）；T107 分货主实时统计表（曹妃甸）；T108 综合装船效率分析（曹妃甸）；T109 综合卸车效率分析（曹妃甸）；T110 综合卸船效率分析（曹妃甸）；T117 经营任务情况分析报告；T118 客户月报报告；T119 月度客户情况报告；T120 商务计划周报；T138 查询卸车流程；T139 查询装船流程；T140 查询卸船流程；T143 图片上传；T144 图片上传；T145 图片上传 | L115: 贺航
B116: 46251 | C116: 46257 | D116: 有 | E116: 33 | F116: 40 | G116: 1 | H116: 高负荷 | I116: T050 维护需跟踪船舶清单；T051 根据船舶清单更新第三方系统推送数据船舶清单；T052 船舶轨迹跟踪；T037 创建卸车流程；T038 查询卸车流程；T039 修改卸车流程；T040 创建装船流程；T041 查询装船流程；T042 修改装船流程；T043 创建卸船流程；T044 查询卸船流程；T045 修改卸船流程；T100 创建行业资讯数据；T101 修改行业资讯数据；T102 删除行业资讯数据；T103 展示行业资讯数据；T104 吞吐量统计（曹妃甸）；T105 泊位占用率分析（曹妃甸）；T106 堆存库存统计（曹妃甸）；T107 分货主实时统计表（曹妃甸）；T108 综合装船效率分析（曹妃甸）；T109 综合卸车效率分析（曹妃甸）；T110 综合卸船效率分析（曹妃甸）；T117 经营任务情况分析报告；T118 客户月报报告；T119 月度客户情况报告；T120 商务计划周报；T138 查询卸车流程；T139 查询装船流程；T140 查询卸船流程；T143 图片上传；T144 图片上传；T145 图片上传 | L116: 贺航
B117: 46258 | C117: 46264 | D117: 有 | E117: 30 | F117: 40 | G117: 1 | H117: 高负荷 | I117: T050 维护需跟踪船舶清单；T051 根据船舶清单更新第三方系统推送数据船舶清单；T052 船舶轨迹跟踪；T037 创建卸车流程；T038 查询卸车流程；T039 修改卸车流程；T040 创建装船流程；T041 查询装船流程；T042 修改装船流程；T043 创建卸船流程；T044 查询卸船流程；T045 修改卸船流程；T100 创建行业资讯数据；T101 修改行业资讯数据；T102 删除行业资讯数据；T103 展示行业资讯数据；T104 吞吐量统计（曹妃甸）；T105 泊位占用率分析（曹妃甸）；T106 堆存库存统计（曹妃甸）；T107 分货主实时统计表（曹妃甸）；T108 综合装船效率分析（曹妃甸）；T109 综合卸车效率分析（曹妃甸）；T110 综合卸船效率分析（曹妃甸）；T117 经营任务情况分析报告；T118 客户月报报告；T119 月度客户情况报告；T120 商务计划周报；T138 查询卸车流程；T139 查询装船流程；T140 查询卸船流程 | L117: 贺航
...

Sheet 相关方管理
A1: 项目相关方管理
A2: 持续跟踪影响力、支持度、沟通节奏和待办行动，黄色单元格由项目团队维护。
A4: 相关方总数 | D4: 高权力相关方 | G4: 重点管理人数 | J4: 当前不支持人数 | M4: 存在支持差距 | P4: 沟通逾期人数 | S4: 未关闭行动数 | V4: 待升级事项
A5: =COUNTIFS($B$9:$B$108,"<>") -> 0 | D5: =COUNTIFS($B$9:$B$108,"<>",$H$9:$H$108,"高") -> 0 | G5: =COUNTIFS($B$9:$B$108,"<>",$N$9:$N$108,"重点管理") -> 0 | J5: =COUNTIFS($B$9:$B$108,"<>",$J$9:$J$108,"抵触")+COUNTIFS($B$9:$B$108,"<>",$J$9:$J$108,"不支持") -> 0 | M5: =COUNTIFS($B$9:$B$108,"<>",$L$9:$L$108,">0") -> 0 | P5: =COUNTIFS($B$9:$B$108,"<>",$T$9:$T$108,"<"&项目驾驶舱!$B$3,$T$9:$T$108,"<>") -> 0 | S5: =COUNTIFS($B$9:$B$108,"<>",$Y$9:$Y$108,"<>已完成",$V$9:$V$108,"<>") -> 0 | V5: =COUNTIFS($B$9:$B$108,"<>",$Z$9:$Z$108,"是") -> 0
A7: 相关方管理明细
A8: 相关方ID | B8: 姓名/组织 | C8: 所属单位/部门 | D8: 职务/角色 | E8: 相关方类别 | F8: 项目责任 | G8: 关注事项 | H8: 权力等级 | I8: 关注度 | J8: 当前支持度 | K8: 目标支持度 | L8: 支持差距 | M8: 影响方向 | N8: 管理策略 | O8: 沟通方式 | P8: 沟通频率 | Q8: 沟通内容 | R8: 关系责任人 | S8: 最近沟通日期 | T8: 下次沟通日期 | U8: 当前诉求/意见 | V8: 待办行动 | W8: 行动责任人 | X8: 承诺完成日期 | Y8: 行动状态 | Z8: 是否需要升级 | AA8: 升级对象 | AB8: 风险提示 | AC8: 备注
A9: =IF(B9="","","SH-"&TEXT(ROW()-8,"000")) | L9: =IF(OR(J9="",K9=""),"",IF(K9="抵触",1,IF(K9="不支持",2,IF(K9="中立",3,IF(K9="支持",4,IF(K9="积极推动",5,"")))))-IF(J9="抵触",1,IF(J9="不支持",2,IF(J9="中立",3,IF(J9="支持",4,IF(J9="积极推动",5,"")))))) | N9: =IF(OR(H9="",I9=""),"",IF(AND(H9="高",I9="高"),"重点管理",IF(H9="高","保持满意",IF(I9="高","保持沟通","监督观察")))) | AB9: =IF(B9="","",IF(AND(H9="高",OR(J9="抵触",J9="不支持")),"高权力不支持；","")&IF(L9>0,"存在支持差距；","")&IF(AND(T9<>"",T9<项目驾驶舱!$B$3),"沟通逾期；","")&IF(AND(V9<>"",X9<项目驾驶舱!$B$3,Y9<>"已完成"),"行动逾期；","")&IF(AND(Z9="是",AA9=""),"未填升级对象",""))
A10: =IF(B10="","","SH-"&TEXT(ROW()-8,"000")) | L10: =IF(OR(J10="",K10=""),"",IF(K10="抵触",1,IF(K10="不支持",2,IF(K10="中立",3,IF(K10="支持",4,IF(K10="积极推动",5,"")))))-IF(J10="抵触",1,IF(J10="不支持",2,IF(J10="中立",3,IF(J10="支持",4,IF(J10="积极推动",5,"")))))) | N10: =IF(OR(H10="",I10=""),"",IF(AND(H10="高",I10="高"),"重点管理",IF(H10="高","保持满意",IF(I10="高","保持沟通","监督观察")))) | AB10: =IF(B10="","",IF(AND(H10="高",OR(J10="抵触",J10="不支持")),"高权力不支持；","")&IF(L10>0,"存在支持差距；","")&IF(AND(T10<>"",T10<项目驾驶舱!$B$3),"沟通逾期；","")&IF(AND(V10<>"",X10<项目驾驶舱!$B$3,Y10<>"已完成"),"行动逾期；","")&IF(AND(Z10="是",AA10=""),"未填升级对象",""))
A11: =IF(B11="","","SH-"&TEXT(ROW()-8,"000")) | L11: =IF(OR(J11="",K11=""),"",IF(K11="抵触",1,IF(K11="不支持",2,IF(K11="中立",3,IF(K11="支持",4,IF(K11="积极推动",5,"")))))-IF(J11="抵触",1,IF(J11="不支持",2,IF(J11="中立",3,IF(J11="支持",4,IF(J11="积极推动",5,"")))))) | N11: =IF(OR(H11="",I11=""),"",IF(AND(H11="高",I11="高"),"重点管理",IF(H11="高","保持满意",IF(I11="高","保持沟通","监督观察")))) | AB11: =IF(B11="","",IF(AND(H11="高",OR(J11="抵触",J11="不支持")),"高权力不支持；","")&IF(L11>0,"存在支持差距；","")&IF(AND(T11<>"",T11<项目驾驶舱!$B$3),"沟通逾期；","")&IF(AND(V11<>"",X11<项目驾驶舱!$B$3,Y11<>"已完成"),"行动逾期；","")&IF(AND(Z11="是",AA11=""),"未填升级对象",""))
A12: =IF(B12="","","SH-"&TEXT(ROW()-8,"000")) | L12: =IF(OR(J12="",K12=""),"",IF(K12="抵触",1,IF(K12="不支持",2,IF(K12="中立",3,IF(K12="支持",4,IF(K12="积极推动",5,"")))))-IF(J12="抵触",1,IF(J12="不支持",2,IF(J12="中立",3,IF(J12="支持",4,IF(J12="积极推动",5,"")))))) | N12: =IF(OR(H12="",I12=""),"",IF(AND(H12="高",I12="高"),"重点管理",IF(H12="高","保持满意",IF(I12="高","保持沟通","监督观察")))) | AB12: =IF(B12="","",IF(AND(H12="高",OR(J12="抵触",J12="不支持")),"高权力不支持；","")&IF(L12>0,"存在支持差距；","")&IF(AND(T12<>"",T12<项目驾驶舱!$B$3),"沟通逾期；","")&IF(AND(V12<>"",X12<项目驾驶舱!$B$3,Y12<>"已完成"),"行动逾期；","")&IF(AND(Z12="是",AA12=""),"未填升级对象",""))
A13: =IF(B13="","","SH-"&TEXT(ROW()-8,"000")) | L13: =IF(OR(J13="",K13=""),"",IF(K13="抵触",1,IF(K13="不支持",2,IF(K13="中立",3,IF(K13="支持",4,IF(K13="积极推动",5,"")))))-IF(J13="抵触",1,IF(J13="不支持",2,IF(J13="中立",3,IF(J13="支持",4,IF(J13="积极推动",5,"")))))) | N13: =IF(OR(H13="",I13=""),"",IF(AND(H13="高",I13="高"),"重点管理",IF(H13="高","保持满意",IF(I13="高","保持沟通","监督观察")))) | AB13: =IF(B13="","",IF(AND(H13="高",OR(J13="抵触",J13="不支持")),"高权力不支持；","")&IF(L13>0,"存在支持差距；","")&IF(AND(T13<>"",T13<项目驾驶舱!$B$3),"沟通逾期；","")&IF(AND(V13<>"",X13<项目驾驶舱!$B$3,Y13<>"已完成"),"行动逾期；","")&IF(AND(Z13="是",AA13=""),"未填升级对象",""))
A14: =IF(B14="","","SH-"&TEXT(ROW()-8,"000")) | L14: =IF(OR(J14="",K14=""),"",IF(K14="抵触",1,IF(K14="不支持",2,IF(K14="中立",3,IF(K14="支持",4,IF(K14="积极推动",5,"")))))-IF(J14="抵触",1,IF(J14="不支持",2,IF(J14="中立",3,IF(J14="支持",4,IF(J14="积极推动",5,"")))))) | N14: =IF(OR(H14="",I14=""),"",IF(AND(H14="高",I14="高"),"重点管理",IF(H14="高","保持满意",IF(I14="高","保持沟通","监督观察")))) | AB14: =IF(B14="","",IF(AND(H14="高",OR(J14="抵触",J14="不支持")),"高权力不支持；","")&IF(L14>0,"存在支持差距；","")&IF(AND(T14<>"",T14<项目驾驶舱!$B$3),"沟通逾期；","")&IF(AND(V14<>"",X14<项目驾驶舱!$B$3,Y14<>"已完成"),"行动逾期；","")&IF(AND(Z14="是",AA14=""),"未填升级对象",""))
A15: =IF(B15="","","SH-"&TEXT(ROW()-8,"000")) | L15: =IF(OR(J15="",K15=""),"",IF(K15="抵触",1,IF(K15="不支持",2,IF(K15="中立",3,IF(K15="支持",4,IF(K15="积极推动",5,"")))))-IF(J15="抵触",1,IF(J15="不支持",2,IF(J15="中立",3,IF(J15="支持",4,IF(J15="积极推动",5,"")))))) | N15: =IF(OR(H15="",I15=""),"",IF(AND(H15="高",I15="高"),"重点管理",IF(H15="高","保持满意",IF(I15="高","保持沟通","监督观察")))) | AB15: =IF(B15="","",IF(AND(H15="高",OR(J15="抵触",J15="不支持")),"高权力不支持；","")&IF(L15>0,"存在支持差距；","")&IF(AND(T15<>"",T15<项目驾驶舱!$B$3),"沟通逾期；","")&IF(AND(V15<>"",X15<项目驾驶舱!$B$3,Y15<>"已完成"),"行动逾期；","")&IF(AND(Z15="是",AA15=""),"未填升级对象",""))
A16: =IF(B16="","","SH-"&TEXT(ROW()-8,"000")) | L16: =IF(OR(J16="",K16=""),"",IF(K16="抵触",1,IF(K16="不支持",2,IF(K16="中立",3,IF(K16="支持",4,IF(K16="积极推动",5,"")))))-IF(J16="抵触",1,IF(J16="不支持",2,IF(J16="中立",3,IF(J16="支持",4,IF(J16="积极推动",5,"")))))) | N16: =IF(OR(H16="",I16=""),"",IF(AND(H16="高",I16="高"),"重点管理",IF(H16="高","保持满意",IF(I16="高","保持沟通","监督观察")))) | AB16: =IF(B16="","",IF(AND(H16="高",OR(J16="抵触",J16="不支持")),"高权力不支持；","")&IF(L16>0,"存在支持差距；","")&IF(AND(T16<>"",T16<项目驾驶舱!$B$3),"沟通逾期；","")&IF(AND(V16<>"",X16<项目驾驶舱!$B$3,Y16<>"已完成"),"行动逾期；","")&IF(AND(Z16="是",AA16=""),"未填升级对象",""))
A17: =IF(B17="","","SH-"&TEXT(ROW()-8,"000")) | L17: =IF(OR(J17="",K17=""),"",IF(K17="抵触",1,IF(K17="不支持",2,IF(K17="中立",3,IF(K17="支持",4,IF(K17="积极推动",5,"")))))-IF(J17="抵触",1,IF(J17="不支持",2,IF(J17="中立",3,IF(J17="支持",4,IF(J17="积极推动",5,"")))))) | N17: =IF(OR(H17="",I17=""),"",IF(AND(H17="高",I17="高"),"重点管理",IF(H17="高","保持满意",IF(I17="高","保持沟通","监督观察")))) | AB17: =IF(B17="","",IF(AND(H17="高",OR(J17="抵触",J17="不支持")),"高权力不支持；","")&IF(L17>0,"存在支持差距；","")&IF(AND(T17<>"",T17<项目驾驶舱!$B$3),"沟通逾期；","")&IF(AND(V17<>"",X17<项目驾驶舱!$B$3,Y17<>"已完成"),"行动逾期；","")&IF(AND(Z17="是",AA17=""),"未填升级对象",""))
A18: =IF(B18="","","SH-"&TEXT(ROW()-8,"000")) | L18: =IF(OR(J18="",K18=""),"",IF(K18="抵触",1,IF(K18="不支持",2,IF(K18="中立",3,IF(K18="支持",4,IF(K18="积极推动",5,"")))))-IF(J18="抵触",1,IF(J18="不支持",2,IF(J18="中立",3,IF(J18="支持",4,IF(J18="积极推动",5,"")))))) | N18: =IF(OR(H18="",I18=""),"",IF(AND(H18="高",I18="高"),"重点管理",IF(H18="高","保持满意",IF(I18="高","保持沟通","监督观察")))) | AB18: =IF(B18="","",IF(AND(H18="高",OR(J18="抵触",J18="不支持")),"高权力不支持；","")&IF(L18>0,"存在支持差距；","")&IF(AND(T18<>"",T18<项目驾驶舱!$B$3),"沟通逾期；","")&IF(AND(V18<>"",X18<项目驾驶舱!$B$3,Y18<>"已完成"),"行动逾期；","")&IF(AND(Z18="是",AA18=""),"未填升级对象",""))
A19: =IF(B19="","","SH-"&TEXT(ROW()-8,"000")) | L19: =IF(OR(J19="",K19=""),"",IF(K19="抵触",1,IF(K19="不支持",2,IF(K19="中立",3,IF(K19="支持",4,IF(K19="积极推动",5,"")))))-IF(J19="抵触",1,IF(J19="不支持",2,IF(J19="中立",3,IF(J19="支持",4,IF(J19="积极推动",5,"")))))) | N19: =IF(OR(H19="",I19=""),"",IF(AND(H19="高",I19="高"),"重点管理",IF(H19="高","保持满意",IF(I19="高","保持沟通","监督观察")))) | AB19: =IF(B19="","",IF(AND(H19="高",OR(J19="抵触",J19="不支持")),"高权力不支持；","")&IF(L19>0,"存在支持差距；","")&IF(AND(T19<>"",T19<项目驾驶舱!$B$3),"沟通逾期；","")&IF(AND(V19<>"",X19<项目驾驶舱!$B$3,Y19<>"已完成"),"行动逾期；","")&IF(AND(Z19="是",AA19=""),"未填升级对象",""))
A20: =IF(B20="","","SH-"&TEXT(ROW()-8,"000")) | L20: =IF(OR(J20="",K20=""),"",IF(K20="抵触",1,IF(K20="不支持",2,IF(K20="中立",3,IF(K20="支持",4,IF(K20="积极推动",5,"")))))-IF(J20="抵触",1,IF(J20="不支持",2,IF(J20="中立",3,IF(J20="支持",4,IF(J20="积极推动",5,"")))))) | N20: =IF(OR(H20="",I20=""),"",IF(AND(H20="高",I20="高"),"重点管理",IF(H20="高","保持满意",IF(I20="高","保持沟通","监督观察")))) | AB20: =IF(B20="","",IF(AND(H20="高",OR(J20="抵触",J20="不支持")),"高权力不支持；","")&IF(L20>0,"存在支持差距；","")&IF(AND(T20<>"",T20<项目驾驶舱!$B$3),"沟通逾期；","")&IF(AND(V20<>"",X20<项目驾驶舱!$B$3,Y20<>"已完成"),"行动逾期；","")&IF(AND(Z20="是",AA20=""),"未填升级对象",""))
... A108: =IF(B108="","","SH-"&TEXT(ROW()-8,"000")) | L108: =IF(OR(J108="",K108=""),"",IF(K108="抵触",1,IF(K108="不支持",2,IF(K108="中立",3,IF(K108="支持",4,IF(K108="积极推动",5,"")))))-IF(J108="抵触",1,IF(J108="不支持",2,IF(J108="中立",3,IF(J108="支持",4,IF(J108="积极推动",5,"")))))) | N108: =IF(OR(H108="",I108=""),"",IF(AND(H108="高",I108="高"),"重点管理",IF(H108="高","保持满意",IF(I108="高","保持沟通","监督观察")))) | AB108: =IF(B108="","",IF(AND(H108="高",OR(J108="抵触",J108="不支持")),"高权力不支持；","")&IF(L108>0,"存在支持差距；","")&IF(AND(T108<>"",T108<项目驾驶舱!$B$3),"沟通逾期；","")&IF(AND(V108<>"",X108<项目驾驶舱!$B$3,Y108<>"已完成"),"行动逾期；","")&IF(AND(Z108="是",AA108=""),"未填升级对象",""))

Sheet 风险管理计划
A1: 项目风险管理计划
A2: 定义风险分类、评分、升级、评审和责任规则；本项目同时管理威胁与机会。
A4: 项目名称 | B4: 华能交易中心港口交易平台 | F4: 风险管理负责人 | G4: 项目经理
A5: 项目阶段 | B5: 开发与集成测试 | F5: 重大风险批准人 | G5: 项目发起人/项目总监
A6: 统计日期 | B6: =项目驾驶舱!B3 -> 46276 | F6: 常规评审频率 | G6: 每周
A7: 重大风险评审 | B7: 触发后立即召集 | F7: 风险报告周期 | G7: 随PMO周报
A9: 角色与责任
A10: 角色 | B10: 核心责任 | C10: 输入 | D10: 输出 | E10: 升级权限
A11: 项目发起人 | B11: 批准重大风险策略和储备使用 | C11: 重大风险专项分析 | D11: 批准结论 | E11: 最终决策
A12: 项目经理 | B12: 组织识别、分析、应对、监控和升级 | C12: 项目信息 | D12: 风险报告 | E12: 高风险升级
A13: 风险责任人 | B13: 对风险结果及剩余风险负责 | C13: 评分和触发信号 | D13: 处置决策 | E13: 提请升级
A14: 应对责任人 | B14: 按期完成具体应对行动 | C14: 应对计划 | D14: 完成证据 | E14: 报告阻塞
A15: PMO | B15: 维护规则、检查逾期和生成报告 | C15: 各类台账 | D15: 重点风险清单 | E15: 治理升级
A17: 风险分类结构（RBS）
A18: 业务与需求 | C18: 范围与变更 | E18: 计划与进度 | G18: 资源与关键人员
A19: 技术与架构 | C19: 数据与迁移 | E19: 接口与外部依赖 | G19: 测试与质量
A20: 安全与合规 | C20: 部署与上线 | E20: 运维与服务 | G20: 采购与供应商
A21: 合同与成本 | C21: 相关方与决策 | E21: 外部环境 | G21: 机会类风险
A23: 概率与影响评分
A24: 等级 | B24: 概率参考 | C24: 影响描述 | D24: 分值 | E24: 风险等级 | F24: 管理要求
A25: 1 | B25: ≤10% | C25: 极低 | D25: 1–4 | E25: 低 | F25: 月度观察
A26: 2 | B26: 11%–30% | C26: 较低 | D26: 5–9 | E26: 中 | F26: 每两周检查
A27: 3 | B27: 31%–50% | C27: 中等 | D27: 10–16 | E27: 高 | F27: 每周检查
A28: 4 | B28: 51%–70% | C28: 较高 | D28: 17–25 | E28: 重大 | F28: 立即升级
A29: 5 | B29: ＞70% | C29: 极高 | D29: 影响=5 | E29: 重大 | F29: 可按单项重大处理

Sheet 风险登记册
A1: 项目风险登记册
A2: 用“原因—事件—影响”描述风险；区分固有风险与应对后剩余风险。黄色为人工输入。
A4: 风险总数 | D4: 重大风险 | G4: 高风险 | J4: 已发生 | M4: 应对逾期 | P4: 无责任人 | S4: 剩余暴露值
A5: =COUNTIFS($B$9:$B$108,"<>") -> 0 | D5: =COUNTIFS($B$9:$B$108,"<>",$AH$9:$AH$108,"重大") -> 0 | G5: =COUNTIFS($B$9:$B$108,"<>",$AH$9:$AH$108,"高") -> 0 | J5: =COUNTIFS($B$9:$B$108,"<>",$AJ$9:$AJ$108,"是") -> 0 | M5: =COUNTIFS($B$9:$B$108,"<>",$AB$9:$AB$108,"<"&项目驾驶舱!$B$3,$AB$9:$AB$108,"<>",$AC$9:$AC$108,"<>已关闭") -> 0 | P5: =COUNTIFS($B$9:$B$108,"<>",$W$9:$W$108,"") -> 0 | S5: =SUMIFS($AG$9:$AG$108,$B$9:$B$108,"<>") -> 0
A7: 风险明细
A8: 风险ID | B8: 风险名称 | C8: 类型 | D8: 风险类别 | E8: 项目阶段 | F8: 原因 | G8: 风险事件 | H8: 可能影响 | I8: 识别人 | J8: 识别日期 | K8: 信息来源 | L8: 概率 | M8: 进度影响 | N8: 成本影响 | O8: 范围影响 | P8: 质量影响 | Q8: 业务价值影响 | R8: 安全合规影响 | S8: 相关方影响 | T8: 综合影响 | U8: 固有风险分值 | V8: 固有风险等级 | W8: 风险责任人 | X8: 责任部门 | Y8: 应对策略 | Z8: 触发条件 | AA8: 预警指标 | AB8: 最迟应对日期 | AC8: 状态 | AD8: 应对完成率 | AE8: 剩余概率 | AF8: 剩余影响 | AG8: 剩余风险分值 | AH8: 剩余风险等级 | AI8: 趋势 | AJ8: 是否已发生 | AK8: 关联问题ID | AL8: 最近评审日期 | AM8: 下次评审日期 | AN8: 关闭日期 | AO8: 关闭证据 | AP8: 是否重点 | AQ8: 数据质量提示 | AR8: _key_order
A9: =IF(B9="","","RSK-"&TEXT(ROW()-8,"000")) | T9: =IF(B9="","",MAX(M9:S9)) | U9: =IF(OR(L9="",T9=""),"",L9*T9) | V9: =IF(U9="","",IF(OR(U9>=17,T9=5),"重大",IF(U9>=10,"高",IF(U9>=5,"中","低")))) | AG9: =IF(OR(AE9="",AF9=""),"",AE9*AF9) | AH9: =IF(AG9="","",IF(OR(AG9>=17,AF9=5),"重大",IF(AG9>=10,"高",IF(AG9>=5,"中","低")))) | AP9: =IF(B9="","",IF(OR(V9="重大",AH9="重大",AH9="高",AI9="上升",AJ9="是",AND(AB9<>"",AB9<项目驾驶舱!$B$3,AC9<>"已关闭")),"是","否")) | AQ9: =IF(B9="","",IF(W9="","缺风险责任人",IF(AND(OR(V9="重大",V9="高"),Y9=""),"高风险缺应对策略",IF(AND(AJ9="是",AK9=""),"已发生未关联问题",IF(AND(AC9="已关闭",AO9=""),"关闭缺证据",IF(AND(AM9<>"",AM9<项目驾驶舱!$B$3),"评审逾期","")))))) | AR9: =IF(AP9="是",COUNTIFS($AP$9:AP9,"是"),"")
A10: =IF(B10="","","RSK-"&TEXT(ROW()-8,"000")) | T10: =IF(B10="","",MAX(M10:S10)) | U10: =IF(OR(L10="",T10=""),"",L10*T10) | V10: =IF(U10="","",IF(OR(U10>=17,T10=5),"重大",IF(U10>=10,"高",IF(U10>=5,"中","低")))) | AG10: =IF(OR(AE10="",AF10=""),"",AE10*AF10) | AH10: =IF(AG10="","",IF(OR(AG10>=17,AF10=5),"重大",IF(AG10>=10,"高",IF(AG10>=5,"中","低")))) | AP10: =IF(B10="","",IF(OR(V10="重大",AH10="重大",AH10="高",AI10="上升",AJ10="是",AND(AB10<>"",AB10<项目驾驶舱!$B$3,AC10<>"已关闭")),"是","否")) | AQ10: =IF(B10="","",IF(W10="","缺风险责任人",IF(AND(OR(V10="重大",V10="高"),Y10=""),"高风险缺应对策略",IF(AND(AJ10="是",AK10=""),"已发生未关联问题",IF(AND(AC10="已关闭",AO10=""),"关闭缺证据",IF(AND(AM10<>"",AM10<项目驾驶舱!$B$3),"评审逾期","")))))) | AR10: =IF(AP10="是",COUNTIFS($AP$9:AP10,"是"),"")
A11: =IF(B11="","","RSK-"&TEXT(ROW()-8,"000")) | T11: =IF(B11="","",MAX(M11:S11)) | U11: =IF(OR(L11="",T11=""),"",L11*T11) | V11: =IF(U11="","",IF(OR(U11>=17,T11=5),"重大",IF(U11>=10,"高",IF(U11>=5,"中","低")))) | AG11: =IF(OR(AE11="",AF11=""),"",AE11*AF11) | AH11: =IF(AG11="","",IF(OR(AG11>=17,AF11=5),"重大",IF(AG11>=10,"高",IF(AG11>=5,"中","低")))) | AP11: =IF(B11="","",IF(OR(V11="重大",AH11="重大",AH11="高",AI11="上升",AJ11="是",AND(AB11<>"",AB11<项目驾驶舱!$B$3,AC11<>"已关闭")),"是","否")) | AQ11: =IF(B11="","",IF(W11="","缺风险责任人",IF(AND(OR(V11="重大",V11="高"),Y11=""),"高风险缺应对策略",IF(AND(AJ11="是",AK11=""),"已发生未关联问题",IF(AND(AC11="已关闭",AO11=""),"关闭缺证据",IF(AND(AM11<>"",AM11<项目驾驶舱!$B$3),"评审逾期","")))))) | AR11: =IF(AP11="是",COUNTIFS($AP$9:AP11,"是"),"")
A12: =IF(B12="","","RSK-"&TEXT(ROW()-8,"000")) | T12: =IF(B12="","",MAX(M12:S12)) | U12: =IF(OR(L12="",T12=""),"",L12*T12) | V12: =IF(U12="","",IF(OR(U12>=17,T12=5),"重大",IF(U12>=10,"高",IF(U12>=5,"中","低")))) | AG12: =IF(OR(AE12="",AF12=""),"",AE12*AF12) | AH12: =IF(AG12="","",IF(OR(AG12>=17,AF12=5),"重大",IF(AG12>=10,"高",IF(AG12>=5,"中","低")))) | AP12: =IF(B12="","",IF(OR(V12="重大",AH12="重大",AH12="高",AI12="上升",AJ12="是",AND(AB12<>"",AB12<项目驾驶舱!$B$3,AC12<>"已关闭")),"是","否")) | AQ12: =IF(B12="","",IF(W12="","缺风险责任人",IF(AND(OR(V12="重大",V12="高"),Y12=""),"高风险缺应对策略",IF(AND(AJ12="是",AK12=""),"已发生未关联问题",IF(AND(AC12="已关闭",AO12=""),"关闭缺证据",IF(AND(AM12<>"",AM12<项目驾驶舱!$B$3),"评审逾期","")))))) | AR12: =IF(AP12="是",COUNTIFS($AP$9:AP12,"是"),"")
A13: =IF(B13="","","RSK-"&TEXT(ROW()-8,"000")) | T13: =IF(B13="","",MAX(M13:S13)) | U13: =IF(OR(L13="",T13=""),"",L13*T13) | V13: =IF(U13="","",IF(OR(U13>=17,T13=5),"重大",IF(U13>=10,"高",IF(U13>=5,"中","低")))) | AG13: =IF(OR(AE13="",AF13=""),"",AE13*AF13) | AH13: =IF(AG13="","",IF(OR(AG13>=17,AF13=5),"重大",IF(AG13>=10,"高",IF(AG13>=5,"中","低")))) | AP13: =IF(B13="","",IF(OR(V13="重大",AH13="重大",AH13="高",AI13="上升",AJ13="是",AND(AB13<>"",AB13<项目驾驶舱!$B$3,AC13<>"已关闭")),"是","否")) | AQ13: =IF(B13="","",IF(W13="","缺风险责任人",IF(AND(OR(V13="重大",V13="高"),Y13=""),"高风险缺应对策略",IF(AND(AJ13="是",AK13=""),"已发生未关联问题",IF(AND(AC13="已关闭",AO13=""),"关闭缺证据",IF(AND(AM13<>"",AM13<项目驾驶舱!$B$3),"评审逾期","")))))) | AR13: =IF(AP13="是",COUNTIFS($AP$9:AP13,"是"),"")
A14: =IF(B14="","","RSK-"&TEXT(ROW()-8,"000")) | T14: =IF(B14="","",MAX(M14:S14)) | U14: =IF(OR(L14="",T14=""),"",L14*T14) | V14: =IF(U14="","",IF(OR(U14>=17,T14=5),"重大",IF(U14>=10,"高",IF(U14>=5,"中","低")))) | AG14: =IF(OR(AE14="",AF14=""),"",AE14*AF14) | AH14: =IF(AG14="","",IF(OR(AG14>=17,AF14=5),"重大",IF(AG14>=10,"高",IF(AG14>=5,"中","低")))) | AP14: =IF(B14="","",IF(OR(V14="重大",AH14="重大",AH14="高",AI14="上升",AJ14="是",AND(AB14<>"",AB14<项目驾驶舱!$B$3,AC14<>"已关闭")),"是","否")) | AQ14: =IF(B14="","",IF(W14="","缺风险责任人",IF(AND(OR(V14="重大",V14="高"),Y14=""),"高风险缺应对策略",IF(AND(AJ14="是",AK14=""),"已发生未关联问题",IF(AND(AC14="已关闭",AO14=""),"关闭缺证据",IF(AND(AM14<>"",AM14<项目驾驶舱!$B$3),"评审逾期","")))))) | AR14: =IF(AP14="是",COUNTIFS($AP$9:AP14,"是"),"")
A15: =IF(B15="","","RSK-"&TEXT(ROW()-8,"000")) | T15: =IF(B15="","",MAX(M15:S15)) | U15: =IF(OR(L15="",T15=""),"",L15*T15) | V15: =IF(U15="","",IF(OR(U15>=17,T15=5),"重大",IF(U15>=10,"高",IF(U15>=5,"中","低")))) | AG15: =IF(OR(AE15="",AF15=""),"",AE15*AF15) | AH15: =IF(AG15="","",IF(OR(AG15>=17,AF15=5),"重大",IF(AG15>=10,"高",IF(AG15>=5,"中","低")))) | AP15: =IF(B15="","",IF(OR(V15="重大",AH15="重大",AH15="高",AI15="上升",AJ15="是",AND(AB15<>"",AB15<项目驾驶舱!$B$3,AC15<>"已关闭")),"是","否")) | AQ15: =IF(B15="","",IF(W15="","缺风险责任人",IF(AND(OR(V15="重大",V15="高"),Y15=""),"高风险缺应对策略",IF(AND(AJ15="是",AK15=""),"已发生未关联问题",IF(AND(AC15="已关闭",AO15=""),"关闭缺证据",IF(AND(AM15<>"",AM15<项目驾驶舱!$B$3),"评审逾期","")))))) | AR15: =IF(AP15="是",COUNTIFS($AP$9:AP15,"是"),"")
A16: =IF(B16="","","RSK-"&TEXT(ROW()-8,"000")) | T16: =IF(B16="","",MAX(M16:S16)) | U16: =IF(OR(L16="",T16=""),"",L16*T16) | V16: =IF(U16="","",IF(OR(U16>=17,T16=5),"重大",IF(U16>=10,"高",IF(U16>=5,"中","低")))) | AG16: =IF(OR(AE16="",AF16=""),"",AE16*AF16) | AH16: =IF(AG16="","",IF(OR(AG16>=17,AF16=5),"重大",IF(AG16>=10,"高",IF(AG16>=5,"中","低")))) | AP16: =IF(B16="","",IF(OR(V16="重大",AH16="重大",AH16="高",AI16="上升",AJ16="是",AND(AB16<>"",AB16<项目驾驶舱!$B$3,AC16<>"已关闭")),"是","否")) | AQ16: =IF(B16="","",IF(W16="","缺风险责任人",IF(AND(OR(V16="重大",V16="高"),Y16=""),"高风险缺应对策略",IF(AND(AJ16="是",AK16=""),"已发生未关联问题",IF(AND(AC16="已关闭",AO16=""),"关闭缺证据",IF(AND(AM16<>"",AM16<项目驾驶舱!$B$3),"评审逾期","")))))) | AR16: =IF(AP16="是",COUNTIFS($AP$9:AP16,"是"),"")
A17: =IF(B17="","","RSK-"&TEXT(ROW()-8,"000")) | T17: =IF(B17="","",MAX(M17:S17)) | U17: =IF(OR(L17="",T17=""),"",L17*T17) | V17: =IF(U17="","",IF(OR(U17>=17,T17=5),"重大",IF(U17>=10,"高",IF(U17>=5,"中","低")))) | AG17: =IF(OR(AE17="",AF17=""),"",AE17*AF17) | AH17: =IF(AG17="","",IF(OR(AG17>=17,AF17=5),"重大",IF(AG17>=10,"高",IF(AG17>=5,"中","低")))) | AP17: =IF(B17="","",IF(OR(V17="重大",AH17="重大",AH17="高",AI17="上升",AJ17="是",AND(AB17<>"",AB17<项目驾驶舱!$B$3,AC17<>"已关闭")),"是","否")) | AQ17: =IF(B17="","",IF(W17="","缺风险责任人",IF(AND(OR(V17="重大",V17="高"),Y17=""),"高风险缺应对策略",IF(AND(AJ17="是",AK17=""),"已发生未关联问题",IF(AND(AC17="已关闭",AO17=""),"关闭缺证据",IF(AND(AM17<>"",AM17<项目驾驶舱!$B$3),"评审逾期","")))))) | AR17: =IF(AP17="是",COUNTIFS($AP$9:AP17,"是"),"")
A18: =IF(B18="","","RSK-"&TEXT(ROW()-8,"000")) | T18: =IF(B18="","",MAX(M18:S18)) | U18: =IF(OR(L18="",T18=""),"",L18*T18) | V18: =IF(U18="","",IF(OR(U18>=17,T18=5),"重大",IF(U18>=10,"高",IF(U18>=5,"中","低")))) | AG18: =IF(OR(AE18="",AF18=""),"",AE18*AF18) | AH18: =IF(AG18="","",IF(OR(AG18>=17,AF18=5),"重大",IF(AG18>=10,"高",IF(AG18>=5,"中","低")))) | AP18: =IF(B18="","",IF(OR(V18="重大",AH18="重大",AH18="高",AI18="上升",AJ18="是",AND(AB18<>"",AB18<项目驾驶舱!$B$3,AC18<>"已关闭")),"是","否")) | AQ18: =IF(B18="","",IF(W18="","缺风险责任人",IF(AND(OR(V18="重大",V18="高"),Y18=""),"高风险缺应对策略",IF(AND(AJ18="是",AK18=""),"已发生未关联问题",IF(AND(AC18="已关闭",AO18=""),"关闭缺证据",IF(AND(AM18<>"",AM18<项目驾驶舱!$B$3),"评审逾期","")))))) | AR18: =IF(AP18="是",COUNTIFS($AP$9:AP18,"是"),"")
A19: =IF(B19="","","RSK-"&TEXT(ROW()-8,"000")) | T19: =IF(B19="","",MAX(M19:S19)) | U19: =IF(OR(L19="",T19=""),"",L19*T19) | V19: =IF(U19="","",IF(OR(U19>=17,T19=5),"重大",IF(U19>=10,"高",IF(U19>=5,"中","低")))) | AG19: =IF(OR(AE19="",AF19=""),"",AE19*AF19) | AH19: =IF(AG19="","",IF(OR(AG19>=17,AF19=5),"重大",IF(AG19>=10,"高",IF(AG19>=5,"中","低")))) | AP19: =IF(B19="","",IF(OR(V19="重大",AH19="重大",AH19="高",AI19="上升",AJ19="是",AND(AB19<>"",AB19<项目驾驶舱!$B$3,AC19<>"已关闭")),"是","否")) | AQ19: =IF(B19="","",IF(W19="","缺风险责任人",IF(AND(OR(V19="重大",V19="高"),Y19=""),"高风险缺应对策略",IF(AND(AJ19="是",AK19=""),"已发生未关联问题",IF(AND(AC19="已关闭",AO19=""),"关闭缺证据",IF(AND(AM19<>"",AM19<项目驾驶舱!$B$3),"评审逾期","")))))) | AR19: =IF(AP19="是",COUNTIFS($AP$9:AP19,"是"),"")
A20: =IF(B20="","","RSK-"&TEXT(ROW()-8,"000")) | T20: =IF(B20="","",MAX(M20:S20)) | U20: =IF(OR(L20="",T20=""),"",L20*T20) | V20: =IF(U20="","",IF(OR(U20>=17,T20=5),"重大",IF(U20>=10,"高",IF(U20>=5,"中","低")))) | AG20: =IF(OR(AE20="",AF20=""),"",AE20*AF20) | AH20: =IF(AG20="","",IF(OR(AG20>=17,AF20=5),"重大",IF(AG20>=10,"高",IF(AG20>=5,"中","低")))) | AP20: =IF(B20="","",IF(OR(V20="重大",AH20="重大",AH20="高",AI20="上升",AJ20="是",AND(AB20<>"",AB20<项目驾驶舱!$B$3,AC20<>"已关闭")),"是","否")) | AQ20: =IF(B20="","",IF(W20="","缺风险责任人",IF(AND(OR(V20="重大",V20="高"),Y20=""),"高风险缺应对策略",IF(AND(AJ20="是",AK20=""),"已发生未关联问题",IF(AND(AC20="已关闭",AO20=""),"关闭缺证据",IF(AND(AM20<>"",AM20<项目驾驶舱!$B$3),"评审逾期","")))))) | AR20: =IF(AP20="是",COUNTIFS($AP$9:AP20,"是"),"")
... A108: =IF(B108="","","RSK-"&TEXT(ROW()-8,"000")) | T108: =IF(B108="","",MAX(M108:S108)) | U108: =IF(OR(L108="",T108=""),"",L108*T108) | V108: =IF(U108="","",IF(OR(U108>=17,T108=5),"重大",IF(U108>=10,"高",IF(U108>=5,"中","低")))) | AG108: =IF(OR(AE108="",AF108=""),"",AE108*AF108) | AH108: =IF(AG108="","",IF(OR(AG108>=17,AF108=5),"重大",IF(AG108>=10,"高",IF(AG108>=5,"中","低")))) | AP108: =IF(B108="","",IF(OR(V108="重大",AH108="重大",AH108="高",AI108="上升",AJ108="是",AND(AB108<>"",AB108<项目驾驶舱!$B$3,AC108<>"已关闭")),"是","否")) | AQ108: =IF(B108="","",IF(W108="","缺风险责任人",IF(AND(OR(V108="重大",V108="高"),Y108=""),"高风险缺应对策略",IF(AND(AJ108="是",AK108=""),"已发生未关联问题",IF(AND(AC108="已关闭",AO108=""),"关闭缺证据",IF(AND(AM108<>"",AM108<项目驾驶舱!$B$3),"评审逾期","")))))) | AR108: =IF(AP108="是",COUNTIFS($AP$9:AP108,"是"),"")

Sheet 风险热力图
A1: 项目风险热力图
A2: 左侧展示固有风险，右侧展示应对后剩余风险；数字为对应概率和影响组合中的风险数量。
A4: 风险总数 | D4: 重大风险 | G4: 高风险 | J4: 应对逾期
A5: =COUNTIFS(风险登记册!$B$9:$B$108,"<>") -> 0 | D5: =COUNTIFS(风险登记册!$AH$9:$AH$108,"重大") -> 0 | G5: =COUNTIFS(风险登记册!$AH$9:$AH$108,"高") -> 0 | J5: =COUNTIFS(风险登记册!$AB$9:$AB$108,"<"&项目驾驶舱!$B$3,风险登记册!$AB$9:$AB$108,"<>",风险登记册!$AC$9:$AC$108,"<>已关闭") -> 0
A8: 固有风险 | I8: 剩余风险
A9: 影响\概率 | B9: 1 | C9: 2 | D9: 3 | E9: 4 | F9: 5 | I9: 影响\概率 | J9: 1 | K9: 2 | L9: 3 | M9: 4 | N9: 5
A10: 5 | B10: =COUNTIFS(风险登记册!$L$9:$L$108,1,风险登记册!$T$9:$T$108,5,风险登记册!$B$9:$B$108,"<>") -> 0 | C10: =COUNTIFS(风险登记册!$L$9:$L$108,2,风险登记册!$T$9:$T$108,5,风险登记册!$B$9:$B$108,"<>") -> 0 | D10: =COUNTIFS(风险登记册!$L$9:$L$108,3,风险登记册!$T$9:$T$108,5,风险登记册!$B$9:$B$108,"<>") -> 0 | E10: =COUNTIFS(风险登记册!$L$9:$L$108,4,风险登记册!$T$9:$T$108,5,风险登记册!$B$9:$B$108,"<>") -> 0 | F10: =COUNTIFS(风险登记册!$L$9:$L$108,5,风险登记册!$T$9:$T$108,5,风险登记册!$B$9:$B$108,"<>") -> 0 | I10: 5 | J10: =COUNTIFS(风险登记册!$AE$9:$AE$108,1,风险登记册!$AF$9:$AF$108,5,风险登记册!$B$9:$B$108,"<>") -> 0 | K10: =COUNTIFS(风险登记册!$AE$9:$AE$108,2,风险登记册!$AF$9:$AF$108,5,风险登记册!$B$9:$B$108,"<>") -> 0 | L10: =COUNTIFS(风险登记册!$AE$9:$AE$108,3,风险登记册!$AF$9:$AF$108,5,风险登记册!$B$9:$B$108,"<>") -> 0 | M10: =COUNTIFS(风险登记册!$AE$9:$AE$108,4,风险登记册!$AF$9:$AF$108,5,风险登记册!$B$9:$B$108,"<>") -> 0 | N10: =COUNTIFS(风险登记册!$AE$9:$AE$108,5,风险登记册!$AF$9:$AF$108,5,风险登记册!$B$9:$B$108,"<>") -> 0
A11: 4 | B11: =COUNTIFS(风险登记册!$L$9:$L$108,1,风险登记册!$T$9:$T$108,4,风险登记册!$B$9:$B$108,"<>") -> 0 | C11: =COUNTIFS(风险登记册!$L$9:$L$108,2,风险登记册!$T$9:$T$108,4,风险登记册!$B$9:$B$108,"<>") -> 0 | D11: =COUNTIFS(风险登记册!$L$9:$L$108,3,风险登记册!$T$9:$T$108,4,风险登记册!$B$9:$B$108,"<>") -> 0 | E11: =COUNTIFS(风险登记册!$L$9:$L$108,4,风险登记册!$T$9:$T$108,4,风险登记册!$B$9:$B$108,"<>") -> 0 | F11: =COUNTIFS(风险登记册!$L$9:$L$108,5,风险登记册!$T$9:$T$108,4,风险登记册!$B$9:$B$108,"<>") -> 0 | I11: 4 | J11: =COUNTIFS(风险登记册!$AE$9:$AE$108,1,风险登记册!$AF$9:$AF$108,4,风险登记册!$B$9:$B$108,"<>") -> 0 | K11: =COUNTIFS(风险登记册!$AE$9:$AE$108,2,风险登记册!$AF$9:$AF$108,4,风险登记册!$B$9:$B$108,"<>") -> 0 | L11: =COUNTIFS(风险登记册!$AE$9:$AE$108,3,风险登记册!$AF$9:$AF$108,4,风险登记册!$B$9:$B$108,"<>") -> 0 | M11: =COUNTIFS(风险登记册!$AE$9:$AE$108,4,风险登记册!$AF$9:$AF$108,4,风险登记册!$B$9:$B$108,"<>") -> 0 | N11: =COUNTIFS(风险登记册!$AE$9:$AE$108,5,风险登记册!$AF$9:$AF$108,4,风险登记册!$B$9:$B$108,"<>") -> 0
A12: 3 | B12: =COUNTIFS(风险登记册!$L$9:$L$108,1,风险登记册!$T$9:$T$108,3,风险登记册!$B$9:$B$108,"<>") -> 0 | C12: =COUNTIFS(风险登记册!$L$9:$L$108,2,风险登记册!$T$9:$T$108,3,风险登记册!$B$9:$B$108,"<>") -> 0 | D12: =COUNTIFS(风险登记册!$L$9:$L$108,3,风险登记册!$T$9:$T$108,3,风险登记册!$B$9:$B$108,"<>") -> 0 | E12: =COUNTIFS(风险登记册!$L$9:$L$108,4,风险登记册!$T$9:$T$108,3,风险登记册!$B$9:$B$108,"<>") -> 0 | F12: =COUNTIFS(风险登记册!$L$9:$L$108,5,风险登记册!$T$9:$T$108,3,风险登记册!$B$9:$B$108,"<>") -> 0 | I12: 3 | J12: =COUNTIFS(风险登记册!$AE$9:$AE$108,1,风险登记册!$AF$9:$AF$108,3,风险登记册!$B$9:$B$108,"<>") -> 0 | K12: =COUNTIFS(风险登记册!$AE$9:$AE$108,2,风险登记册!$AF$9:$AF$108,3,风险登记册!$B$9:$B$108,"<>") -> 0 | L12: =COUNTIFS(风险登记册!$AE$9:$AE$108,3,风险登记册!$AF$9:$AF$108,3,风险登记册!$B$9:$B$108,"<>") -> 0 | M12: =COUNTIFS(风险登记册!$AE$9:$AE$108,4,风险登记册!$AF$9:$AF$108,3,风险登记册!$B$9:$B$108,"<>") -> 0 | N12: =COUNTIFS(风险登记册!$AE$9:$AE$108,5,风险登记册!$AF$9:$AF$108,3,风险登记册!$B$9:$B$108,"<>") -> 0
A13: 2 | B13: =COUNTIFS(风险登记册!$L$9:$L$108,1,风险登记册!$T$9:$T$108,2,风险登记册!$B$9:$B$108,"<>") -> 0 | C13: =COUNTIFS(风险登记册!$L$9:$L$108,2,风险登记册!$T$9:$T$108,2,风险登记册!$B$9:$B$108,"<>") -> 0 | D13: =COUNTIFS(风险登记册!$L$9:$L$108,3,风险登记册!$T$9:$T$108,2,风险登记册!$B$9:$B$108,"<>") -> 0 | E13: =COUNTIFS(风险登记册!$L$9:$L$108,4,风险登记册!$T$9:$T$108,2,风险登记册!$B$9:$B$108,"<>") -> 0 | F13: =COUNTIFS(风险登记册!$L$9:$L$108,5,风险登记册!$T$9:$T$108,2,风险登记册!$B$9:$B$108,"<>") -> 0 | I13: 2 | J13: =COUNTIFS(风险登记册!$AE$9:$AE$108,1,风险登记册!$AF$9:$AF$108,2,风险登记册!$B$9:$B$108,"<>") -> 0 | K13: =COUNTIFS(风险登记册!$AE$9:$AE$108,2,风险登记册!$AF$9:$AF$108,2,风险登记册!$B$9:$B$108,"<>") -> 0 | L13: =COUNTIFS(风险登记册!$AE$9:$AE$108,3,风险登记册!$AF$9:$AF$108,2,风险登记册!$B$9:$B$108,"<>") -> 0 | M13: =COUNTIFS(风险登记册!$AE$9:$AE$108,4,风险登记册!$AF$9:$AF$108,2,风险登记册!$B$9:$B$108,"<>") -> 0 | N13: =COUNTIFS(风险登记册!$AE$9:$AE$108,5,风险登记册!$AF$9:$AF$108,2,风险登记册!$B$9:$B$108,"<>") -> 0
A14: 1 | B14: =COUNTIFS(风险登记册!$L$9:$L$108,1,风险登记册!$T$9:$T$108,1,风险登记册!$B$9:$B$108,"<>") -> 0 | C14: =COUNTIFS(风险登记册!$L$9:$L$108,2,风险登记册!$T$9:$T$108,1,风险登记册!$B$9:$B$108,"<>") -> 0 | D14: =COUNTIFS(风险登记册!$L$9:$L$108,3,风险登记册!$T$9:$T$108,1,风险登记册!$B$9:$B$108,"<>") -> 0 | E14: =COUNTIFS(风险登记册!$L$9:$L$108,4,风险登记册!$T$9:$T$108,1,风险登记册!$B$9:$B$108,"<>") -> 0 | F14: =COUNTIFS(风险登记册!$L$9:$L$108,5,风险登记册!$T$9:$T$108,1,风险登记册!$B$9:$B$108,"<>") -> 0 | I14: 1 | J14: =COUNTIFS(风险登记册!$AE$9:$AE$108,1,风险登记册!$AF$9:$AF$108,1,风险登记册!$B$9:$B$108,"<>") -> 0 | K14: =COUNTIFS(风险登记册!$AE$9:$AE$108,2,风险登记册!$AF$9:$AF$108,1,风险登记册!$B$9:$B$108,"<>") -> 0 | L14: =COUNTIFS(风险登记册!$AE$9:$AE$108,3,风险登记册!$AF$9:$AF$108,1,风险登记册!$B$9:$B$108,"<>") -> 0 | M14: =COUNTIFS(风险登记册!$AE$9:$AE$108,4,风险登记册!$AF$9:$AF$108,1,风险登记册!$B$9:$B$108,"<>") -> 0 | N14: =COUNTIFS(风险登记册!$AE$9:$AE$108,5,风险登记册!$AF$9:$AF$108,1,风险登记册!$B$9:$B$108,"<>") -> 0
A17: 等级说明
A18: 低（1–4）
A19: 中（5–9）
A20: 高（10–16）
A21: 重大（17–25或影响=5）

Sheet 重点风险清单
A1: 重点风险清单
A2: 自动纳入重大/高剩余风险、趋势上升、已发生或应对逾期的风险。
A4: 序号 | B4: 风险ID | C4: 风险名称 | D4: 类别 | E4: 类型 | F4: 剩余等级 | G4: 趋势 | H4: 触发条件 | I4: 当前状态 | J4: 风险责任人 | K4: 最迟应对日期 | L4: 下一步行动 | M4: 需要支持 | N4: 管理层结论 | O4: _source_index
A5: =IF(O5="","",ROWS($A$5:A5)) | B5: =IF($O5="","",INDEX(风险登记册!$A$9:$A$108,$O5)) | C5: =IF($O5="","",INDEX(风险登记册!$B$9:$B$108,$O5)) | D5: =IF($O5="","",INDEX(风险登记册!$D$9:$D$108,$O5)) | E5: =IF($O5="","",INDEX(风险登记册!$C$9:$C$108,$O5)) | F5: =IF($O5="","",INDEX(风险登记册!$AH$9:$AH$108,$O5)) | G5: =IF($O5="","",INDEX(风险登记册!$AI$9:$AI$108,$O5)) | H5: =IF($O5="","",INDEX(风险登记册!$Z$9:$Z$108,$O5)) | I5: =IF($O5="","",INDEX(风险登记册!$AC$9:$AC$108,$O5)) | J5: =IF($O5="","",INDEX(风险登记册!$W$9:$W$108,$O5)) | K5: =IF($O5="","",INDEX(风险登记册!$AB$9:$AB$108,$O5)) | L5: =IF($B5="","",IFERROR(INDEX(风险应对计划!$E$9:$E$108,MATCH($B5,风险应对计划!$B$9:$B$108,0)),"")) | O5: =IFERROR(MATCH(ROWS($A$5:A5),风险登记册!$AR$9:$AR$108,0),"")
A6: =IF(O6="","",ROWS($A$5:A6)) | B6: =IF($O6="","",INDEX(风险登记册!$A$9:$A$108,$O6)) | C6: =IF($O6="","",INDEX(风险登记册!$B$9:$B$108,$O6)) | D6: =IF($O6="","",INDEX(风险登记册!$D$9:$D$108,$O6)) | E6: =IF($O6="","",INDEX(风险登记册!$C$9:$C$108,$O6)) | F6: =IF($O6="","",INDEX(风险登记册!$AH$9:$AH$108,$O6)) | G6: =IF($O6="","",INDEX(风险登记册!$AI$9:$AI$108,$O6)) | H6: =IF($O6="","",INDEX(风险登记册!$Z$9:$Z$108,$O6)) | I6: =IF($O6="","",INDEX(风险登记册!$AC$9:$AC$108,$O6)) | J6: =IF($O6="","",INDEX(风险登记册!$W$9:$W$108,$O6)) | K6: =IF($O6="","",INDEX(风险登记册!$AB$9:$AB$108,$O6)) | L6: =IF($B6="","",IFERROR(INDEX(风险应对计划!$E$9:$E$108,MATCH($B6,风险应对计划!$B$9:$B$108,0)),"")) | O6: =IFERROR(MATCH(ROWS($A$5:A6),风险登记册!$AR$9:$AR$108,0),"")
A7: =IF(O7="","",ROWS($A$5:A7)) | B7: =IF($O7="","",INDEX(风险登记册!$A$9:$A$108,$O7)) | C7: =IF($O7="","",INDEX(风险登记册!$B$9:$B$108,$O7)) | D7: =IF($O7="","",INDEX(风险登记册!$D$9:$D$108,$O7)) | E7: =IF($O7="","",INDEX(风险登记册!$C$9:$C$108,$O7)) | F7: =IF($O7="","",INDEX(风险登记册!$AH$9:$AH$108,$O7)) | G7: =IF($O7="","",INDEX(风险登记册!$AI$9:$AI$108,$O7)) | H7: =IF($O7="","",INDEX(风险登记册!$Z$9:$Z$108,$O7)) | I7: =IF($O7="","",INDEX(风险登记册!$AC$9:$AC$108,$O7)) | J7: =IF($O7="","",INDEX(风险登记册!$W$9:$W$108,$O7)) | K7: =IF($O7="","",INDEX(风险登记册!$AB$9:$AB$108,$O7)) | L7: =IF($B7="","",IFERROR(INDEX(风险应对计划!$E$9:$E$108,MATCH($B7,风险应对计划!$B$9:$B$108,0)),"")) | O7: =IFERROR(MATCH(ROWS($A$5:A7),风险登记册!$AR$9:$AR$108,0),"")
A8: =IF(O8="","",ROWS($A$5:A8)) | B8: =IF($O8="","",INDEX(风险登记册!$A$9:$A$108,$O8)) | C8: =IF($O8="","",INDEX(风险登记册!$B$9:$B$108,$O8)) | D8: =IF($O8="","",INDEX(风险登记册!$D$9:$D$108,$O8)) | E8: =IF($O8="","",INDEX(风险登记册!$C$9:$C$108,$O8)) | F8: =IF($O8="","",INDEX(风险登记册!$AH$9:$AH$108,$O8)) | G8: =IF($O8="","",INDEX(风险登记册!$AI$9:$AI$108,$O8)) | H8: =IF($O8="","",INDEX(风险登记册!$Z$9:$Z$108,$O8)) | I8: =IF($O8="","",INDEX(风险登记册!$AC$9:$AC$108,$O8)) | J8: =IF($O8="","",INDEX(风险登记册!$W$9:$W$108,$O8)) | K8: =IF($O8="","",INDEX(风险登记册!$AB$9:$AB$108,$O8)) | L8: =IF($B8="","",IFERROR(INDEX(风险应对计划!$E$9:$E$108,MATCH($B8,风险应对计划!$B$9:$B$108,0)),"")) | O8: =IFERROR(MATCH(ROWS($A$5:A8),风险登记册!$AR$9:$AR$108,0),"")
A9: =IF(O9="","",ROWS($A$5:A9)) | B9: =IF($O9="","",INDEX(风险登记册!$A$9:$A$108,$O9)) | C9: =IF($O9="","",INDEX(风险登记册!$B$9:$B$108,$O9)) | D9: =IF($O9="","",INDEX(风险登记册!$D$9:$D$108,$O9)) | E9: =IF($O9="","",INDEX(风险登记册!$C$9:$C$108,$O9)) | F9: =IF($O9="","",INDEX(风险登记册!$AH$9:$AH$108,$O9)) | G9: =IF($O9="","",INDEX(风险登记册!$AI$9:$AI$108,$O9)) | H9: =IF($O9="","",INDEX(风险登记册!$Z$9:$Z$108,$O9)) | I9: =IF($O9="","",INDEX(风险登记册!$AC$9:$AC$108,$O9)) | J9: =IF($O9="","",INDEX(风险登记册!$W$9:$W$108,$O9)) | K9: =IF($O9="","",INDEX(风险登记册!$AB$9:$AB$108,$O9)) | L9: =IF($B9="","",IFERROR(INDEX(风险应对计划!$E$9:$E$108,MATCH($B9,风险应对计划!$B$9:$B$108,0)),"")) | O9: =IFERROR(MATCH(ROWS($A$5:A9),风险登记册!$AR$9:$AR$108,0),"")
A10: =IF(O10="","",ROWS($A$5:A10)) | B10: =IF($O10="","",INDEX(风险登记册!$A$9:$A$108,$O10)) | C10: =IF($O10="","",INDEX(风险登记册!$B$9:$B$108,$O10)) | D10: =IF($O10="","",INDEX(风险登记册!$D$9:$D$108,$O10)) | E10: =IF($O10="","",INDEX(风险登记册!$C$9:$C$108,$O10)) | F10: =IF($O10="","",INDEX(风险登记册!$AH$9:$AH$108,$O10)) | G10: =IF($O10="","",INDEX(风险登记册!$AI$9:$AI$108,$O10)) | H10: =IF($O10="","",INDEX(风险登记册!$Z$9:$Z$108,$O10)) | I10: =IF($O10="","",INDEX(风险登记册!$AC$9:$AC$108,$O10)) | J10: =IF($O10="","",INDEX(风险登记册!$W$9:$W$108,$O10)) | K10: =IF($O10="","",INDEX(风险登记册!$AB$9:$AB$108,$O10)) | L10: =IF($B10="","",IFERROR(INDEX(风险应对计划!$E$9:$E$108,MATCH($B10,风险应对计划!$B$9:$B$108,0)),"")) | O10: =IFERROR(MATCH(ROWS($A$5:A10),风险登记册!$AR$9:$AR$108,0),"")
A11: =IF(O11="","",ROWS($A$5:A11)) | B11: =IF($O11="","",INDEX(风险登记册!$A$9:$A$108,$O11)) | C11: =IF($O11="","",INDEX(风险登记册!$B$9:$B$108,$O11)) | D11: =IF($O11="","",INDEX(风险登记册!$D$9:$D$108,$O11)) | E11: =IF($O11="","",INDEX(风险登记册!$C$9:$C$108,$O11)) | F11: =IF($O11="","",INDEX(风险登记册!$AH$9:$AH$108,$O11)) | G11: =IF($O11="","",INDEX(风险登记册!$AI$9:$AI$108,$O11)) | H11: =IF($O11="","",INDEX(风险登记册!$Z$9:$Z$108,$O11)) | I11: =IF($O11="","",INDEX(风险登记册!$AC$9:$AC$108,$O11)) | J11: =IF($O11="","",INDEX(风险登记册!$W$9:$W$108,$O11)) | K11: =IF($O11="","",INDEX(风险登记册!$AB$9:$AB$108,$O11)) | L11: =IF($B11="","",IFERROR(INDEX(风险应对计划!$E$9:$E$108,MATCH($B11,风险应对计划!$B$9:$B$108,0)),"")) | O11: =IFERROR(MATCH(ROWS($A$5:A11),风险登记册!$AR$9:$AR$108,0),"")
A12: =IF(O12="","",ROWS($A$5:A12)) | B12: =IF($O12="","",INDEX(风险登记册!$A$9:$A$108,$O12)) | C12: =IF($O12="","",INDEX(风险登记册!$B$9:$B$108,$O12)) | D12: =IF($O12="","",INDEX(风险登记册!$D$9:$D$108,$O12)) | E12: =IF($O12="","",INDEX(风险登记册!$C$9:$C$108,$O12)) | F12: =IF($O12="","",INDEX(风险登记册!$AH$9:$AH$108,$O12)) | G12: =IF($O12="","",INDEX(风险登记册!$AI$9:$AI$108,$O12)) | H12: =IF($O12="","",INDEX(风险登记册!$Z$9:$Z$108,$O12)) | I12: =IF($O12="","",INDEX(风险登记册!$AC$9:$AC$108,$O12)) | J12: =IF($O12="","",INDEX(风险登记册!$W$9:$W$108,$O12)) | K12: =IF($O12="","",INDEX(风险登记册!$AB$9:$AB$108,$O12)) | L12: =IF($B12="","",IFERROR(INDEX(风险应对计划!$E$9:$E$108,MATCH($B12,风险应对计划!$B$9:$B$108,0)),"")) | O12: =IFERROR(MATCH(ROWS($A$5:A12),风险登记册!$AR$9:$AR$108,0),"")
A13: =IF(O13="","",ROWS($A$5:A13)) | B13: =IF($O13="","",INDEX(风险登记册!$A$9:$A$108,$O13)) | C13: =IF($O13="","",INDEX(风险登记册!$B$9:$B$108,$O13)) | D13: =IF($O13="","",INDEX(风险登记册!$D$9:$D$108,$O13)) | E13: =IF($O13="","",INDEX(风险登记册!$C$9:$C$108,$O13)) | F13: =IF($O13="","",INDEX(风险登记册!$AH$9:$AH$108,$O13)) | G13: =IF($O13="","",INDEX(风险登记册!$AI$9:$AI$108,$O13)) | H13: =IF($O13="","",INDEX(风险登记册!$Z$9:$Z$108,$O13)) | I13: =IF($O13="","",INDEX(风险登记册!$AC$9:$AC$108,$O13)) | J13: =IF($O13="","",INDEX(风险登记册!$W$9:$W$108,$O13)) | K13: =IF($O13="","",INDEX(风险登记册!$AB$9:$AB$108,$O13)) | L13: =IF($B13="","",IFERROR(INDEX(风险应对计划!$E$9:$E$108,MATCH($B13,风险应对计划!$B$9:$B$108,0)),"")) | O13: =IFERROR(MATCH(ROWS($A$5:A13),风险登记册!$AR$9:$AR$108,0),"")
A14: =IF(O14="","",ROWS($A$5:A14)) | B14: =IF($O14="","",INDEX(风险登记册!$A$9:$A$108,$O14)) | C14: =IF($O14="","",INDEX(风险登记册!$B$9:$B$108,$O14)) | D14: =IF($O14="","",INDEX(风险登记册!$D$9:$D$108,$O14)) | E14: =IF($O14="","",INDEX(风险登记册!$C$9:$C$108,$O14)) | F14: =IF($O14="","",INDEX(风险登记册!$AH$9:$AH$108,$O14)) | G14: =IF($O14="","",INDEX(风险登记册!$AI$9:$AI$108,$O14)) | H14: =IF($O14="","",INDEX(风险登记册!$Z$9:$Z$108,$O14)) | I14: =IF($O14="","",INDEX(风险登记册!$AC$9:$AC$108,$O14)) | J14: =IF($O14="","",INDEX(风险登记册!$W$9:$W$108,$O14)) | K14: =IF($O14="","",INDEX(风险登记册!$AB$9:$AB$108,$O14)) | L14: =IF($B14="","",IFERROR(INDEX(风险应对计划!$E$9:$E$108,MATCH($B14,风险应对计划!$B$9:$B$108,0)),"")) | O14: =IFERROR(MATCH(ROWS($A$5:A14),风险登记册!$AR$9:$AR$108,0),"")
A15: =IF(O15="","",ROWS($A$5:A15)) | B15: =IF($O15="","",INDEX(风险登记册!$A$9:$A$108,$O15)) | C15: =IF($O15="","",INDEX(风险登记册!$B$9:$B$108,$O15)) | D15: =IF($O15="","",INDEX(风险登记册!$D$9:$D$108,$O15)) | E15: =IF($O15="","",INDEX(风险登记册!$C$9:$C$108,$O15)) | F15: =IF($O15="","",INDEX(风险登记册!$AH$9:$AH$108,$O15)) | G15: =IF($O15="","",INDEX(风险登记册!$AI$9:$AI$108,$O15)) | H15: =IF($O15="","",INDEX(风险登记册!$Z$9:$Z$108,$O15)) | I15: =IF($O15="","",INDEX(风险登记册!$AC$9:$AC$108,$O15)) | J15: =IF($O15="","",INDEX(风险登记册!$W$9:$W$108,$O15)) | K15: =IF($O15="","",INDEX(风险登记册!$AB$9:$AB$108,$O15)) | L15: =IF($B15="","",IFERROR(INDEX(风险应对计划!$E$9:$E$108,MATCH($B15,风险应对计划!$B$9:$B$108,0)),"")) | O15: =IFERROR(MATCH(ROWS($A$5:A15),风险登记册!$AR$9:$AR$108,0),"")
A16: =IF(O16="","",ROWS($A$5:A16)) | B16: =IF($O16="","",INDEX(风险登记册!$A$9:$A$108,$O16)) | C16: =IF($O16="","",INDEX(风险登记册!$B$9:$B$108,$O16)) | D16: =IF($O16="","",INDEX(风险登记册!$D$9:$D$108,$O16)) | E16: =IF($O16="","",INDEX(风险登记册!$C$9:$C$108,$O16)) | F16: =IF($O16="","",INDEX(风险登记册!$AH$9:$AH$108,$O16)) | G16: =IF($O16="","",INDEX(风险登记册!$AI$9:$AI$108,$O16)) | H16: =IF($O16="","",INDEX(风险登记册!$Z$9:$Z$108,$O16)) | I16: =IF($O16="","",INDEX(风险登记册!$AC$9:$AC$108,$O16)) | J16: =IF($O16="","",INDEX(风险登记册!$W$9:$W$108,$O16)) | K16: =IF($O16="","",INDEX(风险登记册!$AB$9:$AB$108,$O16)) | L16: =IF($B16="","",IFERROR(INDEX(风险应对计划!$E$9:$E$108,MATCH($B16,风险应对计划!$B$9:$B$108,0)),"")) | O16: =IFERROR(MATCH(ROWS($A$5:A16),风险登记册!$AR$9:$AR$108,0),"")
... A34: =IF(O34="","",ROWS($A$5:A34)) | B34: =IF($O34="","",INDEX(风险登记册!$A$9:$A$108,$O34)) | C34: =IF($O34="","",INDEX(风险登记册!$B$9:$B$108,$O34)) | D34: =IF($O34="","",INDEX(风险登记册!$D$9:$D$108,$O34)) | E34: =IF($O34="","",INDEX(风险登记册!$C$9:$C$108,$O34)) | F34: =IF($O34="","",INDEX(风险登记册!$AH$9:$AH$108,$O34)) | G34: =IF($O34="","",INDEX(风险登记册!$AI$9:$AI$108,$O34)) | H34: =IF($O34="","",INDEX(风险登记册!$Z$9:$Z$108,$O34)) | I34: =IF($O34="","",INDEX(风险登记册!$AC$9:$AC$108,$O34)) | J34: =IF($O34="","",INDEX(风险登记册!$W$9:$W$108,$O34)) | K34: =IF($O34="","",INDEX(风险登记册!$AB$9:$AB$108,$O34)) | L34: =IF($B34="","",IFERROR(INDEX(风险应对计划!$E$9:$E$108,MATCH($B34,风险应对计划!$B$9:$B$108,0)),"")) | O34: =IFERROR(MATCH(ROWS($A$5:A34),风险登记册!$AR$9:$AR$108,0),"")

Sheet 重大风险应对
A1: 重大风险专项应对
A2: 用于重大风险的场景分析、应急计划、备用计划、储备和正式批准。
A4: 专项ID | B4: 风险ID | C4: 风险名称 | D4: 影响目标 | E4: 关联里程碑/交付物 | F4: 最坏情景 | G4: 较可能情景 | H4: 最好情景 | I4: 发生窗口 | J4: 关键假设 | K4: 依赖事项 | L4: 应对策略 | M4: 主应对方案 | N4: 触发条件 | O4: 应急计划 | P4: 备用计划 | Q4: 应急储备 | R4: 决策权限 | S4: 升级路径 | T4: 基准影响 | U4: 批准人 | V4: 决策日期 | W4: 决策结论 | X4: 接受的剩余风险 | Y4: 下次专项评审日期
A5: =IF(B5="","","MR-"&TEXT(ROW()-4,"000")) | C5: =IF(B5="","",IFERROR(INDEX(风险登记册!$B$9:$B$108,MATCH(B5,风险登记册!$A$9:$A$108,0)),""))
A6: =IF(B6="","","MR-"&TEXT(ROW()-4,"000")) | C6: =IF(B6="","",IFERROR(INDEX(风险登记册!$B$9:$B$108,MATCH(B6,风险登记册!$A$9:$A$108,0)),""))
A7: =IF(B7="","","MR-"&TEXT(ROW()-4,"000")) | C7: =IF(B7="","",IFERROR(INDEX(风险登记册!$B$9:$B$108,MATCH(B7,风险登记册!$A$9:$A$108,0)),""))
A8: =IF(B8="","","MR-"&TEXT(ROW()-4,"000")) | C8: =IF(B8="","",IFERROR(INDEX(风险登记册!$B$9:$B$108,MATCH(B8,风险登记册!$A$9:$A$108,0)),""))
A9: =IF(B9="","","MR-"&TEXT(ROW()-4,"000")) | C9: =IF(B9="","",IFERROR(INDEX(风险登记册!$B$9:$B$108,MATCH(B9,风险登记册!$A$9:$A$108,0)),""))
A10: =IF(B10="","","MR-"&TEXT(ROW()-4,"000")) | C10: =IF(B10="","",IFERROR(INDEX(风险登记册!$B$9:$B$108,MATCH(B10,风险登记册!$A$9:$A$108,0)),""))
A11: =IF(B11="","","MR-"&TEXT(ROW()-4,"000")) | C11: =IF(B11="","",IFERROR(INDEX(风险登记册!$B$9:$B$108,MATCH(B11,风险登记册!$A$9:$A$108,0)),""))
A12: =IF(B12="","","MR-"&TEXT(ROW()-4,"000")) | C12: =IF(B12="","",IFERROR(INDEX(风险登记册!$B$9:$B$108,MATCH(B12,风险登记册!$A$9:$A$108,0)),""))
A13: =IF(B13="","","MR-"&TEXT(ROW()-4,"000")) | C13: =IF(B13="","",IFERROR(INDEX(风险登记册!$B$9:$B$108,MATCH(B13,风险登记册!$A$9:$A$108,0)),""))
A14: =IF(B14="","","MR-"&TEXT(ROW()-4,"000")) | C14: =IF(B14="","",IFERROR(INDEX(风险登记册!$B$9:$B$108,MATCH(B14,风险登记册!$A$9:$A$108,0)),""))
A15: =IF(B15="","","MR-"&TEXT(ROW()-4,"000")) | C15: =IF(B15="","",IFERROR(INDEX(风险登记册!$B$9:$B$108,MATCH(B15,风险登记册!$A$9:$A$108,0)),""))
A16: =IF(B16="","","MR-"&TEXT(ROW()-4,"000")) | C16: =IF(B16="","",IFERROR(INDEX(风险登记册!$B$9:$B$108,MATCH(B16,风险登记册!$A$9:$A$108,0)),""))
... A24: =IF(B24="","","MR-"&TEXT(ROW()-4,"000")) | C24: =IF(B24="","",IFERROR(INDEX(风险登记册!$B$9:$B$108,MATCH(B24,风险登记册!$A$9:$A$108,0)),""))

Sheet 风险应对计划
A1: 风险应对计划
A2: 将风险应对策略拆解为可执行、可验收、可追踪的行动。
A4: 行动ID | B4: 风险ID | C4: 风险名称 | D4: 应对策略 | E4: 应对措施 | F4: 行动类型 | G4: 行动责任人 | H4: 配合部门 | I4: 计划开始日期 | J4: 计划完成日期 | K4: 实际完成日期 | L4: 所需工时 | M4: 预算 | N4: 交付证据 | O4: 完成百分比 | P4: 行动状态 | Q4: 是否逾期 | R4: 实施效果 | S4: 剩余风险评价 | T4: 备注
A5: =IF(B5="","","RA-"&TEXT(ROW()-4,"000")) | C5: =IF(B5="","",IFERROR(INDEX(风险登记册!$B$9:$B$108,MATCH(B5,风险登记册!$A$9:$A$108,0)),"")) | Q5: =IF(B5="","",IF(AND(J5<项目驾驶舱!$B$3,P5<>"已完成"),"是","否"))
A6: =IF(B6="","","RA-"&TEXT(ROW()-4,"000")) | C6: =IF(B6="","",IFERROR(INDEX(风险登记册!$B$9:$B$108,MATCH(B6,风险登记册!$A$9:$A$108,0)),"")) | Q6: =IF(B6="","",IF(AND(J6<项目驾驶舱!$B$3,P6<>"已完成"),"是","否"))
A7: =IF(B7="","","RA-"&TEXT(ROW()-4,"000")) | C7: =IF(B7="","",IFERROR(INDEX(风险登记册!$B$9:$B$108,MATCH(B7,风险登记册!$A$9:$A$108,0)),"")) | Q7: =IF(B7="","",IF(AND(J7<项目驾驶舱!$B$3,P7<>"已完成"),"是","否"))
A8: =IF(B8="","","RA-"&TEXT(ROW()-4,"000")) | C8: =IF(B8="","",IFERROR(INDEX(风险登记册!$B$9:$B$108,MATCH(B8,风险登记册!$A$9:$A$108,0)),"")) | Q8: =IF(B8="","",IF(AND(J8<项目驾驶舱!$B$3,P8<>"已完成"),"是","否"))
A9: =IF(B9="","","RA-"&TEXT(ROW()-4,"000")) | C9: =IF(B9="","",IFERROR(INDEX(风险登记册!$B$9:$B$108,MATCH(B9,风险登记册!$A$9:$A$108,0)),"")) | Q9: =IF(B9="","",IF(AND(J9<项目驾驶舱!$B$3,P9<>"已完成"),"是","否"))
A10: =IF(B10="","","RA-"&TEXT(ROW()-4,"000")) | C10: =IF(B10="","",IFERROR(INDEX(风险登记册!$B$9:$B$108,MATCH(B10,风险登记册!$A$9:$A$108,0)),"")) | Q10: =IF(B10="","",IF(AND(J10<项目驾驶舱!$B$3,P10<>"已完成"),"是","否"))
A11: =IF(B11="","","RA-"&TEXT(ROW()-4,"000")) | C11: =IF(B11="","",IFERROR(INDEX(风险登记册!$B$9:$B$108,MATCH(B11,风险登记册!$A$9:$A$108,0)),"")) | Q11: =IF(B11="","",IF(AND(J11<项目驾驶舱!$B$3,P11<>"已完成"),"是","否"))
A12: =IF(B12="","","RA-"&TEXT(ROW()-4,"000")) | C12: =IF(B12="","",IFERROR(INDEX(风险登记册!$B$9:$B$108,MATCH(B12,风险登记册!$A$9:$A$108,0)),"")) | Q12: =IF(B12="","",IF(AND(J12<项目驾驶舱!$B$3,P12<>"已完成"),"是","否"))
A13: =IF(B13="","","RA-"&TEXT(ROW()-4,"000")) | C13: =IF(B13="","",IFERROR(INDEX(风险登记册!$B$9:$B$108,MATCH(B13,风险登记册!$A$9:$A$108,0)),"")) | Q13: =IF(B13="","",IF(AND(J13<项目驾驶舱!$B$3,P13<>"已完成"),"是","否"))
A14: =IF(B14="","","RA-"&TEXT(ROW()-4,"000")) | C14: =IF(B14="","",IFERROR(INDEX(风险登记册!$B$9:$B$108,MATCH(B14,风险登记册!$A$9:$A$108,0)),"")) | Q14: =IF(B14="","",IF(AND(J14<项目驾驶舱!$B$3,P14<>"已完成"),"是","否"))
A15: =IF(B15="","","RA-"&TEXT(ROW()-4,"000")) | C15: =IF(B15="","",IFERROR(INDEX(风险登记册!$B$9:$B$108,MATCH(B15,风险登记册!$A$9:$A$108,0)),"")) | Q15: =IF(B15="","",IF(AND(J15<项目驾驶舱!$B$3,P15<>"已完成"),"是","否"))
A16: =IF(B16="","","RA-"&TEXT(ROW()-4,"000")) | C16: =IF(B16="","",IFERROR(INDEX(风险登记册!$B$9:$B$108,MATCH(B16,风险登记册!$A$9:$A$108,0)),"")) | Q16: =IF(B16="","",IF(AND(J16<项目驾驶舱!$B$3,P16<>"已完成"),"是","否"))
... A104: =IF(B104="","","RA-"&TEXT(ROW()-4,"000")) | C104: =IF(B104="","",IFERROR(INDEX(风险登记册!$B$9:$B$108,MATCH(B104,风险登记册!$A$9:$A$108,0)),"")) | Q104: =IF(B104="","",IF(AND(J104<项目驾驶舱!$B$3,P104<>"已完成"),"是","否"))

Sheet 里程碑计划
A1: 里程碑计划与阶段门管理
A3: 里程碑ID | B3: 里程碑名称 | C3: 批次 | D3: 验收/完成标准 | E3: 责任人 | F3: 计划日期 | G3: 状态 | H3: 实际日期 | I3: 偏差天数 | J3: 健康度 | K3: 说明
A4: M01 | B4: 第一批次业务设计完成 | C4: 第一批次 | D4: 第一批次业务设计状态全部完成 | E4: 郑士旺 | F4: 46241 | G4: 未开始 | I4: =IF(H4<>"",H4-F4,MAX(0,项目驾驶舱!$B$3-F4)) -> 35 | J4: =IF(G4="已完成","绿",IF(F4<项目驾驶舱!$B$3,"红",IF(F4<=项目驾驶舱!$B$3+7,"黄","绿"))) -> 红 | K4: 69
A5: M02 | B5: 第一批次前后端开发完成 | C5: 第一批次 | D5: 第一批次前端、后端状态全部完成 | E5: 开发组 | F5: 46262 | G5: 未开始 | I5: =IF(H5<>"",H5-F5,MAX(0,项目驾驶舱!$B$3-F5)) -> 14 | J5: =IF(G5="已完成","绿",IF(F5<项目驾驶舱!$B$3,"红",IF(F5<=项目驾驶舱!$B$3+7,"黄","绿"))) -> 红 | K5: 69
A6: M03 | B6: 第一批次测试完成 | C6: 第一批次 | D6: 第一批次测试状态全部完成且无阻断缺陷 | E6: 袁丽荣 | F6: 46318 | G6: 未开始 | I6: =IF(H6<>"",H6-F6,MAX(0,项目驾驶舱!$B$3-F6)) -> 0 | J6: =IF(G6="已完成","绿",IF(F6<项目驾驶舱!$B$3,"红",IF(F6<=项目驾驶舱!$B$3+7,"黄","绿"))) -> 绿 | K6: 69
A7: M04 | B7: 第一批次上线 | C7: 第一批次 | D7: 完成上线审批、部署及回归验证 | E7: 项目经理 | F7: 46261 | G7: 未开始 | I7: =IF(H7<>"",H7-F7,MAX(0,项目驾驶舱!$B$3-F7)) -> 15 | J7: =IF(G7="已完成","绿",IF(F7<项目驾驶舱!$B$3,"红",IF(F7<=项目驾驶舱!$B$3+7,"黄","绿"))) -> 红 | K7: 69
A8: M05 | B8: 第二批次业务设计完成 | C8: 第二批次 | D8: 第二批次业务设计状态全部完成 | E8: 郑士旺 | F8: 46241 | G8: 未开始 | I8: =IF(H8<>"",H8-F8,MAX(0,项目驾驶舱!$B$3-F8)) -> 35 | J8: =IF(G8="已完成","绿",IF(F8<项目驾驶舱!$B$3,"红",IF(F8<=项目驾驶舱!$B$3+7,"黄","绿"))) -> 红 | K8: 69
A9: M06 | B9: 第二批次前后端开发完成 | C9: 第二批次 | D9: 第二批次前端、后端状态全部完成 | E9: 开发组 | F9: 46339 | G9: 未开始 | I9: =IF(H9<>"",H9-F9,MAX(0,项目驾驶舱!$B$3-F9)) -> 0 | J9: =IF(G9="已完成","绿",IF(F9<项目驾驶舱!$B$3,"红",IF(F9<=项目驾驶舱!$B$3+7,"黄","绿"))) -> 绿 | K9: 69
A10: M07 | B10: 第二批次测试完成 | C10: 第二批次 | D10: 第二批次测试状态全部完成且无阻断缺陷 | E10: 袁丽荣 | F10: 46353 | G10: 未开始 | I10: =IF(H10<>"",H10-F10,MAX(0,项目驾驶舱!$B$3-F10)) -> 0 | J10: =IF(G10="已完成","绿",IF(F10<项目驾驶舱!$B$3,"红",IF(F10<=项目驾驶舱!$B$3+7,"黄","绿"))) -> 绿 | K10: 69
A11: M08 | B11: 第二批次上线 | C11: 第二批次 | D11: 完成上线审批、部署及回归验证 | E11: 项目经理 | F11: 46261 | G11: 未开始 | I11: =IF(H11<>"",H11-F11,MAX(0,项目驾驶舱!$B$3-F11)) -> 15 | J11: =IF(G11="已完成","绿",IF(F11<项目驾驶舱!$B$3,"红",IF(F11<=项目驾驶舱!$B$3+7,"黄","绿"))) -> 红 | K11: 69
A12: M09 | B12: 外部系统集成联调完成 | C12: 全项目 | D12: 6个外部系统均完成联调确认 | E12: 集成负责人 | F12: 46346 | G12: 未开始 | I12: =IF(H12<>"",H12-F12,MAX(0,项目驾驶舱!$B$3-F12)) -> 0 | J12: =IF(G12="已完成","绿",IF(F12<项目驾驶舱!$B$3,"红",IF(F12<=项目驾驶舱!$B$3+7,"黄","绿"))) -> 绿 | K12: 69
A13: M10 | B13: 项目验收 | C13: 全项目 | D13: 完成用户验收并签署验收材料 | E13: 项目经理 | F13: 46356 | G13: 未开始 | I13: =IF(H13<>"",H13-F13,MAX(0,项目驾驶舱!$B$3-F13)) -> 0 | J13: =IF(G13="已完成","绿",IF(F13<项目驾驶舱!$B$3,"红",IF(F13<=项目驾驶舱!$B$3+7,"黄","绿"))) -> 绿 | K13: 69

Sheet 周迭代计划
A1: 周迭代计划与完成跟踪
A2: 上方汇总承诺完成、延期和暂停；下方按总控任务四阶段展开。周目标和复盘人工填写，其余内容更新V2时重建。
A4: 迭代周 | B4: 开始日期 | C4: 结束日期 | D4: 周目标 | E4: 原周计划摘要 | F4: 计划完成阶段数 | G4: 实际完成阶段数 | H4: 承诺完成率 | I4: 延期数 | J4: 暂停数 | K4: 周状态 | L4: 复盘结论 | O4: _key
A5: 1 | B5: 46195 | C5: 46199 | E5: 功能设计：装船计划编制及推送、卸船作业信息录入优化（太仓）、装船作业信息录入优化（太仓） 前端：装船计划编制及推送、卸船作业信息录入优化（太仓）、装船作业信息录入优化（太仓） 后端：装船计划编制及推送、卸船作业信息录入优化（太仓）、装船作业信息录入优化（太仓） | F5: 0 | G5: 0 | H5: 无计划任务 | I5: 0 | J5: 0 | K5: 已结束 | O5: W001
A6: 2 | B6: 46202 | C6: 46206 | D6: 完成42个计划阶段 | E6: 功能设计：车辆信息维护、交易中心报单信息展示及应单入口、船舶轨迹跟踪、货权跟踪、货权提醒、船舶预到优化（太仓）、堆存费优化（太仓）、港杂费优化(太仓）、收费标准信息维护、采样方式信息维护、装卸费结算、租赁费结算、采样作业信息录入 测试：装船计划编制及推送、卸船作业信息录入优化（太仓）、装船作业信息录入优化（太仓） | F6: 42 | G6: 42 | H6: 1 | I6: 0 | J6: 0 | K6: 已结束 | L6: 人工复盘保留验证 | O6: W002
A7: 3 | B7: 46209 | C7: 46213 | E7: 功能设计：卸车流程跟踪、装船流程跟踪、卸船流程跟踪、行业资讯、统计分析 前端：车辆信息维护、交易中心报单信息展示及应单入口、船舶轨迹跟踪、货权跟踪、货权提醒、船舶预到优化（太仓）、堆存费优化（太仓）、港杂费优化(太仓）、收费标准信息维护、采样方式信息维护、装卸费结算、租赁费结算、采样作业信息录入 后端：车辆信息维护、交易中心报单信息展示及应单入口、船舶轨迹跟踪、货权跟踪、货权提醒、船舶预到优化（太仓）、堆存费优化（太仓）、港杂费优化(太仓）、收费标准信息维护、采样方式信息维护、装卸费结算、租赁费结算、采样作业信息录入 | F7: 29 | G7: 29 | H7: 1 | I7: 0 | J7: 0 | K7: 已结束 | O7: W003
A8: 4 | B8: 46216 | C8: 46220 | E8: 功能设计：APP：船舶供应服务查询、船舶预到（内贸）查询、台账查询、停泊费（内贸）查询、船舶供应服务费（内贸）查询 测试：车辆信息维护、交易中心报单信息展示及应单入口、船舶轨迹跟踪、货权跟踪、货权提醒、船舶预到优化（太仓）、堆存费优化（太仓）、港杂费优化（太仓）、收费标准信息维护、采样方式信息维护、装卸费结算、租赁费结算、采样作业信息录入 | F8: 5 | G8: 5 | H8: 1 | I8: 0 | J8: 0 | K8: 已结束 | O8: W004
A9: 5 | B9: 46223 | C9: 46227 | E9: 功能设计：结算条款管理、协同视览、费用合同签订校验 | F9: 75 | G9: 68 | H9: 0.90666667 | I9: 7 | J9: 0 | K9: 已结束 | O9: W005
A10: 6 | B10: 46230 | C10: 46234 | E10: 功能设计：船舶唯一性校验、卸船作业、船舶预到（外贸）、退回船舶预到（外贸）、采样申请（外贸）、停泊费（外贸）、锚泊费（外贸）、堆存费（外贸）、卸船费（外贸）、采样服务费（外贸）、船舶供应服务费（外贸） 前端：卸车流程跟踪、装船流程跟踪、卸船流程跟踪、行业资讯、统计分析、自动报告 后端：卸车流程跟踪、装船流程跟踪、卸船流程跟踪、行业资讯、统计分析、自动报告 | F10: 35 | G10: 31 | H10: 0.88571429 | I10: 4 | J10: 0 | K10: 已结束 | O10: W006
A11: 7 | B11: 46237 | C11: 46241 | F11: 53 | G11: 15 | H11: 0.28301887 | I11: 38 | J11: 0 | K11: 已结束 | O11: W007
A12: 8 | B12: 46244 | C12: 46248 | F12: 0 | G12: 0 | H12: 无计划任务 | I12: 0 | J12: 0 | K12: 已结束 | O12: W008
A13: 9 | B13: 46251 | C13: 46255 | E13: 测试：卸车流程跟踪、装船流程跟踪、卸船流程跟踪、行业资讯、统计分析、自动报告 | F13: 6 | G13: 6 | H13: 1 | I13: 0 | J13: 0 | K13: 已结束 | O13: W009
A14: 10 | B14: 46258 | C14: 46262 | F14: 54 | G14: 54 | H14: 1 | I14: 0 | J14: 0 | K14: 已结束 | O14: W010
A15: 11 | B15: 46265 | C15: 46269 | E15: 前端：APP：船舶供应服务查询、船舶预到（内贸）查询、台账查询、停泊费（内贸）查询、船舶供应服务费（内贸）查询 后端：APP：船舶供应服务查询、船舶预到（内贸）查询、台账查询、停泊费（内贸）查询、船舶供应服务费（内贸）查询 | F15: 43 | G15: 43 | H15: 1 | I15: 0 | J15: 0 | K15: 进行中 | O15: W011
A16: 12 | B16: 46272 | C16: 46276 | E16: 前端：结算条款管理、协同视览、费用合同签订校验 后端：结算条款管理、协同视览、费用合同签订校验 测试：APP：船舶供应服务查询、船舶预到（内贸）查询、台账查询、停泊费（内贸）查询、船舶供应服务费（内贸）查询 | F16: 23 | G16: 23 | I16: 0 | J16: 0 | K16: 未开始 | O16: W012
A17: 13 | B17: 46279 | C17: 46283 | F17: 16 | G17: 0 | I17: 0 | J17: 0 | K17: 未开始 | O17: W013
A18: 14 | B18: 46286 | C18: 46290 | F18: 6 | G18: 0 | I18: 0 | J18: 0 | K18: 未开始 | O18: W014
A19: 15 | B19: 46293 | C19: 46297 | F19: 0 | G19: 0 | I19: 0 | J19: 0 | K19: 未开始 | O19: W015
A20: 16 | B20: 46300 | C20: 46304 | F20: 14 | G20: 0 | I20: 0 | J20: 0 | K20: 未开始 | O20: W016
A21: 17 | B21: 46307 | C21: 46311 | E21: 前端：船舶唯一性校验、卸船作业、船舶预到（外贸）、退回船舶预到（外贸）、采样申请（外贸）、停泊费（外贸）、锚泊费（外贸）、堆存费（外贸）、卸船费（外贸）、采样服务费（外贸）、船舶供应服务费（外贸） 后端：船舶唯一性校验、卸船作业、船舶预到（外贸）、退回船舶预到（外贸）、采样申请（外贸）、停泊费（外贸）、锚泊费（外贸）、堆存费（外贸）、卸船费（外贸）、采样服务费（外贸）、船舶供应服务费（外贸） 测试：结算条款管理、协同视览、费用合同签订校验 | F21: 8 | G21: 0 | I21: 0 | J21: 0 | K21: 未开始 | O21: W017
A22: 18 | B22: 46314 | C22: 46318 | F22: 16 | G22: 1 | I22: 0 | J22: 0 | K22: 未开始 | O22: W018
A23: 19 | B23: 46321 | C23: 46325 | F23: 0 | G23: 0 | I23: 0 | J23: 0 | K23: 未开始 | O23: W019
A24: 20 | B24: 46328 | C24: 46332 | F24: 0 | G24: 0 | I24: 0 | J24: 0 | K24: 未开始 | O24: W020
A25: 21 | B25: 46335 | C25: 46339 | F25: 70 | G25: 6 | I25: 0 | J25: 0 | K25: 未开始 | O25: W021
A26: 22 | B26: 46342 | C26: 46346 | E26: 测试：船舶唯一性校验、卸船作业、船舶预到（外贸）、退回船舶预到（外贸）、采样申请（外贸）、停泊费（外贸）、锚泊费（外贸）、堆存费（外贸）、卸船费（外贸）、采样服务费（外贸）、船舶供应服务费（外贸） | F26: 0 | G26: 0 | I26: 0 | J26: 0 | K26: 未开始 | O26: W022
A27: 23 | B27: 46349 | C27: 46353 | F27: 53 | G27: 6 | I27: 0 | J27: 0 | K27: 未开始 | O27: W023
A29: 周任务明细
A30: 迭代周 | B30: 任务ID | C30: 任务名称 | D30: 批次 | E30: 专业阶段 | F30: 负责人 | G30: 计划开始 | H30: 计划完成 | I30: 阶段状态 | J30: 总体状态 | K30: 实际完成日期 | L30: 是否延期 | M30: 异常提示 | N30: 复盘说明 | O30: _detail_key
A31: 2 | B31: T001 | C31: 新增车辆信息 | D31: 第一批次 | E31: 业务 | F31: 郑士旺 | G31: 46202 | H31: 46206 | I31: 已完成 | J31: 已完成 | L31: 否 | M31: 完成日期待补充 | O31: W002|tsk-33c582966f67#001|业务
A32: 2 | B32: T002 | C32: 修改车辆信息 | D32: 第一批次 | E32: 业务 | F32: 郑士旺 | G32: 46202 | H32: 46206 | I32: 已完成 | J32: 已完成 | L32: 否 | M32: 完成日期待补充 | O32: W002|tsk-23275116439b#001|业务
A33: 2 | B33: T003 | C33: 删除车辆信息 | D33: 第一批次 | E33: 业务 | F33: 郑士旺 | G33: 46202 | H33: 46206 | I33: 已完成 | J33: 已完成 | L33: 否 | M33: 完成日期待补充 | O33: W002|tsk-f668411c7176#001|业务
A34: 2 | B34: T004 | C34: 查询展示车辆信息 | D34: 第一批次 | E34: 业务 | F34: 郑士旺 | G34: 46202 | H34: 46206 | I34: 已完成 | J34: 已完成 | L34: 否 | M34: 完成日期待补充 | O34: W002|tsk-9344390f42cf#001|业务
A35: 2 | B35: T006 | C35: 优化收费标准（装卸费）新增 | D35: 第一批次 | E35: 业务 | F35: 郑士旺 | G35: 46202 | H35: 46206 | I35: 已完成 | J35: 已完成 | K35: 46224 | L35: 否 | O35: W002|tsk-ed149daad87d#001|业务
A36: 2 | B36: T007 | C36: 优化收费标准（装卸费）编辑 | D36: 第一批次 | E36: 业务 | F36: 郑士旺 | G36: 46202 | H36: 46206 | I36: 已完成 | J36: 已完成 | K36: 46224 | L36: 否 | O36: W002|tsk-97a98e6009e6#001|业务
A37: 2 | B37: T008 | C37: 优化收费标准（装卸费）详情 | D37: 第一批次 | E37: 业务 | F37: 郑士旺 | G37: 46202 | H37: 46206 | I37: 已完成 | J37: 已完成 | K37: 46224 | L37: 否 | O37: W002|tsk-a12265c00afb#001|业务
A38: 2 | B38: T009 | C38: 优化采样方式新增 | D38: 第一批次 | E38: 业务 | F38: 郑士旺 | G38: 46202 | H38: 46206 | I38: 已完成 | J38: 已完成 | K38: 46224 | L38: 否 | O38: W002|tsk-e3cb05a8752f#001|业务
A39: 2 | B39: T010 | C39: 优化采样方式编辑 | D39: 第一批次 | E39: 业务 | F39: 郑士旺 | G39: 46202 | H39: 46206 | I39: 已完成 | J39: 已完成 | K39: 46224 | L39: 否 | O39: W002|tsk-b7577ba49e91#001|业务
A40: 2 | B40: T011 | C40: 获取报单数据及展示 | D40: 第一批次 | E40: 业务 | F40: 郑士旺 | G40: 46202 | H40: 46206 | I40: 已完成 | J40: 已完成 | K40: 46224 | L40: 否 | O40: W002|tsk-7f2aa4709d11#001|业务
A41: 2 | B41: T012 | C41: 应单入口 | D41: 第一批次 | E41: 业务 | F41: 郑士旺 | G41: 46202 | H41: 46206 | I41: 已完成 | J41: 已完成 | K41: 46224 | L41: 否 | O41: W002|tsk-702fd2cdf48f#001|业务
A42: 2 | B42: T050 | C42: 维护需跟踪船舶清单 | D42: 第一批次 | E42: 业务 | F42: 郑士旺 | G42: 46202 | H42: 46206 | I42: 已完成 | J42: 进行中 | L42: 否 | M42: 完成日期待补充 | O42: W002|tsk-d0de99d77921#001|业务
A43: 2 | B43: T051 | C43: 根据船舶清单更新第三方系统推送数据船舶清单 | D43: 第一批次 | E43: 业务 | F43: 郑士旺 | G43: 46202 | H43: 46206 | I43: 已完成 | J43: 进行中 | K43: 46261 | L43: 否 | O43: W002|tsk-8e0f61ad2405#001|业务
A44: 2 | B44: T052 | C44: 船舶轨迹跟踪 | D44: 第一批次 | E44: 业务 | F44: 郑士旺 | G44: 46202 | H44: 46206 | I44: 已完成 | J44: 进行中 | K44: 46261 | L44: 否 | O44: W002|tsk-a12801ccffa6#001|业务
A45: 2 | B45: T060 | C45: 货权录入 | D45: 第一批次 | E45: 业务 | F45: 郑士旺 | G45: 46202 | H45: 46206 | I45: 已完成 | J45: 已完成 | K45: 46261 | L45: 否 | O45: W002|tsk-978d907ae469#001|业务
A46: 2 | B46: T061 | C46: 货权修改 | D46: 第一批次 | E46: 业务 | F46: 郑士旺 | G46: 46202 | H46: 46206 | I46: 已完成 | J46: 已完成 | K46: 46261 | L46: 否 | O46: W002|tsk-f4466ad5469c#001|业务
A47: 2 | B47: T062 | C47: 获取查询 | D47: 第一批次 | E47: 业务 | F47: 郑士旺 | G47: 46202 | H47: 46206 | I47: 已完成 | J47: 已完成 | K47: 46261 | L47: 否 | O47: W002|tsk-7d88bf49e933#001|业务
A48: 2 | B48: T063 | C48: 卸船作业货权跟踪 | D48: 第一批次 | E48: 业务 | F48: 郑士旺 | G48: 46202 | H48: 46206 | I48: 已完成 | J48: 已完成 | K48: 46261 | L48: 否 | O48: W002|tsk-7d592b89a46f#001|业务
A49: 2 | B49: T064 | C49: 卸船作业货权跟踪 | D49: 第一批次 | E49: 业务 | F49: 郑士旺 | G49: 46202 | H49: 46206 | I49: 已完成 | J49: 已完成 | K49: 46261 | L49: 否 | O49: W002|tsk-7d592b89a46f#002|业务
A50: 2 | B50: T065 | C50: 装船作业货权跟踪 | D50: 第一批次 | E50: 业务 | F50: 郑士旺 | G50: 46202 | H50: 46206 | I50: 已完成 | J50: 已完成 | K50: 46261 | L50: 否 | O50: W002|tsk-10c71dc857f0#001|业务
A51: 2 | B51: T066 | C51: 装船作业货权跟踪 | D51: 第一批次 | E51: 业务 | F51: 郑士旺 | G51: 46202 | H51: 46206 | I51: 已完成 | J51: 已完成 | K51: 46261 | L51: 否 | O51: W002|tsk-10c71dc857f0#002|业务
A52: 2 | B52: T067 | C52: 装船作业货权跟踪 | D52: 第一批次 | E52: 业务 | F52: 郑士旺 | G52: 46202 | H52: 46206 | I52: 已完成 | J52: 已完成 | K52: 46261 | L52: 否 | O52: W002|tsk-10c71dc857f0#003|业务
A53: 2 | B53: T068 | C53: 装船作业货权跟踪 | D53: 第一批次 | E53: 业务 | F53: 郑士旺 | G53: 46202 | H53: 46206 | I53: 已完成 | J53: 已完成 | K53: 46261 | L53: 否 | O53: W002|tsk-10c71dc857f0#004|业务
A54: 2 | B54: T072 | C54: OCR识别 | D54: 第一批次 | E54: 业务 | F54: 郑士旺 | G54: 46202 | H54: 46206 | I54: 已完成 | J54: 已完成 | L54: 否 | M54: 完成日期待补充 | O54: W002|tsk-57b8e280d274#001|业务
A55: 2 | B55: T073 | C55: 采样作业信息录入新增 | D55: 第一批次 | E55: 业务 | F55: 郑士旺 | G55: 46202 | H55: 46206 | I55: 已完成 | J55: 已完成 | K55: 46224 | L55: 否 | O55: W002|tsk-211024d6f6de#001|业务
A56: 2 | B56: T074 | C56: 采样作业信息录入编辑 | D56: 第一批次 | E56: 业务 | F56: 郑士旺 | G56: 46202 | H56: 46206 | I56: 已完成 | J56: 已完成 | K56: 46224 | L56: 否 | O56: W002|tsk-c0d2087ea559#001|业务
A57: 2 | B57: T075 | C57: 采样作业信息录入详情 | D57: 第一批次 | E57: 业务 | F57: 郑士旺 | G57: 46202 | H57: 46206 | I57: 已完成 | J57: 已完成 | K57: 46224 | L57: 否 | O57: W002|tsk-ef409224d46b#001|业务
A58: 2 | B58: T076 | C58: 采样作业信息录入删除 | D58: 第一批次 | E58: 业务 | F58: 郑士旺 | G58: 46202 | H58: 46206 | I58: 已完成 | J58: 已完成 | K58: 46224 | L58: 否 | O58: W002|tsk-febee99e5a1e#001|业务
A59: 2 | B59: T077 | C59: 采样作业信息录入列表 | D59: 第一批次 | E59: 业务 | F59: 郑士旺 | G59: 46202 | H59: 46206 | I59: 已完成 | J59: 已完成 | K59: 46224 | L59: 否 | O59: W002|tsk-177bff8cf7f9#001|业务
A60: 2 | B60: T095 | C60: 自动生成堆存费 | D60: 第一批次 | E60: 业务 | F60: 郑士旺 | G60: 46202 | H60: 46206 | I60: 已完成 | J60: 进行中 | L60: 否 | M60: 完成日期待补充 | O60: W002|tsk-15570328b3e1#001|业务
A61: 2 | B61: T096 | C61: 自动生成装船港杂费 | D61: 第一批次 | E61: 业务 | F61: 郑士旺 | G61: 46202 | H61: 46206 | I61: 已完成 | J61: 已完成 | K61: 46261 | L61: 否 | O61: W002|tsk-2f7c5586317d#001|业务
A62: 2 | B62: T097 | C62: 自动生成租赁费 | D62: 第一批次 | E62: 业务 | F62: 郑士旺 | G62: 46202 | H62: 46206 | I62: 已完成 | J62: 已完成 | L62: 否 | M62: 完成日期待补充 | O62: W002|tsk-a5528f60d6ad#001|业务
A63: 2 | B63: T098 | C63: 优化装卸费新增 | D63: 第一批次 | E63: 业务 | F63: 郑士旺 | G63: 46202 | H63: 46206 | I63: 已完成 | J63: 已完成 | K63: 46224 | L63: 否 | O63: W002|tsk-e8fdac8072e1#001|业务
A64: 2 | B64: T099 | C64: 优化装卸费编辑 | D64: 第一批次 | E64: 业务 | F64: 郑士旺 | G64: 46202 | H64: 46206 | I64: 已完成 | J64: 已完成 | K64: 46224 | L64: 否 | O64: W002|tsk-628e22896d5e#001|业务
A65: 2 | B65: T058 | C65: OCR识别及编辑 | D65: 第一批次 | E65: 前端 | F65: 贺航 | G65: 46195 | H65: 46206 | I65: 已完成 | J65: 已完成 | K65: 46224 | L65: 否 | O65: W002|tsk-8e34ce8f4239#001|前端
A66: 2 | B66: T069 | C66: 新增、详情、修改页内容调整 | D66: 第一批次 | E66: 前端 | F66: 贺航 | G66: 46195 | H66: 46206 | I66: 已完成 | J66: 已完成 | K66: 46224 | L66: 否 | O66: W002|tsk-965e74d49261#001|前端
A67: 2 | B67: T070 | C67: 生成报告 | D67: 第一批次 | E67: 前端 | F67: 贺航 | G67: 46195 | H67: 46206 | I67: 已完成 | J67: 已完成 | K67: 46224 | L67: 否 | O67: W002|tsk-38a802bbe105#001|前端
A68: 2 | B68: T071 | C68: 装船作业信息录入优化（太仓） | D68: 第一批次 | E68: 前端 | F68: 贺航 | G68: 46195 | H68: 46206 | I68: 已完成 | J68: 已完成 | K68: 46224 | L68: 否 | O68: W002|tsk-cb19eab07c79#001|前端
A69: 2 | B69: T058 | C69: OCR识别及编辑 | D69: 第一批次 | E69: 后端 | F69: 石军磊、刘凯 | G69: 46195 | H69: 46206 | I69: 已完成 | J69: 已完成 | K69: 46224 | L69: 否 | O69: W002|tsk-8e34ce8f4239#001|后端
A70: 2 | B70: T069 | C70: 新增、详情、修改页内容调整 | D70: 第一批次 | E70: 后端 | F70: 石军磊、刘凯 | G70: 46195 | H70: 46206 | I70: 已完成 | J70: 已完成 | K70: 46224 | L70: 否 | O70: W002|tsk-965e74d49261#001|后端
A71: 2 | B71: T070 | C71: 生成报告 | D71: 第一批次 | E71: 后端 | F71: 石军磊、刘凯 | G71: 46195 | H71: 46206 | I71: 已完成 | J71: 已完成 | K71: 46224 | L71: 否 | O71: W002|tsk-38a802bbe105#001|后端
A72: 2 | B72: T071 | C72: 装船作业信息录入优化（太仓） | D72: 第一批次 | E72: 后端 | F72: 石军磊、刘凯 | G72: 46195 | H72: 46206 | I72: 已完成 | J72: 已完成 | K72: 46224 | L72: 否 | O72: W002|tsk-cb19eab07c79#001|后端
A73: 3 | B73: T037 | C73: 创建卸车流程 | D73: 第一批次 | E73: 业务 | F73: 郑士旺 | G73: 46209 | H73: 46213 | I73: 已完成 | J73: 已完成 | K73: 46261 | L73: 否 | O73: W003|tsk-41f84a2dbee7#001|业务
A74: 3 | B74: T038 | C74: 查询卸车流程 | D74: 第一批次 | E74: 业务 | F74: 郑士旺 | G74: 46209 | H74: 46213 | I74: 已完成 | J74: 已完成 | K74: 46261 | L74: 否 | O74: W003|tsk-720110050036#001|业务
... A78: 3 | B78: T042 | C78: 修改装船流程 | D78: 第一批次 | E78: 业务 | F78: 郑士旺 | G78: 46209 | H78: 46213 | I78: 已完成 | J78: 已完成 | K78: 46261 | L78: 否 | O78: W003|tsk-b0bfc16bb18d#001|业务
A79: 3 | B79: T043 | C79: 创建卸船流程 | D79: 第二批次 | E79: 业务 | F79: 郑士旺 | G79: 46209 | H79: 46213 | I79: 已完成 | J79: 已完成 | L79: 否 | M79: 完成日期待补充 | O79: W003|tsk-e7e708d55c95#001|业务
A80: 3 | B80: T044 | C80: 查询卸船流程 | D80: 第二批次 | E80: 业务 | F80: 郑士旺 | G80: 46209 | H80: 46213 | I80: 已完成 | J80: 已完成 | L80: 否 | M80: 完成日期待补充 | O80: W003|tsk-ae0234715f64#001|业务
A81: 3 | B81: T045 | C81: 修改卸船流程 | D81: 第二批次 | E81: 业务 | F81: 郑士旺 | G81: 46209 | H81: 46213 | I81: 已完成 | J81: 已完成 | L81: 否 | M81: 完成日期待补充 | O81: W003|tsk-58da4f05f2c4#001|业务
A82: 3 | B82: T100 | C82: 创建行业资讯数据 | D82: 第一批次 | E82: 业务 | F82: 郑士旺 | G82: 46209 | H82: 46213 | I82: 已完成 | J82: 已完成 | K82: 46224 | L82: 否 | O82: W003|tsk-86a7a8f2d6d2#001|业务
A83: 3 | B83: T101 | C83: 修改行业资讯数据 | D83: 第一批次 | E83: 业务 | F83: 郑士旺 | G83: 46209 | H83: 46213 | I83: 已完成 | J83: 已完成 | K83: 46224 | L83: 否 | O83: W003|tsk-5dde71d1afa6#001|业务
A84: 3 | B84: T102 | C84: 删除行业资讯数据 | D84: 第一批次 | E84: 业务 | F84: 郑士旺 | G84: 46209 | H84: 46213 | I84: 已完成 | J84: 已完成 | K84: 46224 | L84: 否 | O84: W003|tsk-b414c5bb0e5c#001|业务
A85: 3 | B85: T103 | C85: 展示行业资讯数据 | D85: 第一批次 | E85: 业务 | F85: 郑士旺 | G85: 46209 | H85: 46213 | I85: 已完成 | J85: 已完成 | K85: 46224 | L85: 否 | O85: W003|tsk-d8cee4246d76#001|业务
A86: 3 | B86: T104 | C86: 吞吐量统计（曹妃甸） | D86: 第一批次 | E86: 业务 | F86: 郑士旺 | G86: 46209 | H86: 46213 | I86: 已完成 | J86: 已完成 | L86: 否 | M86: 完成日期待补充 | O86: W003|tsk-2383292632d6#001|业务
A87: 3 | B87: T105 | C87: 泊位占用率分析（曹妃甸） | D87: 第一批次 | E87: 业务 | F87: 郑士旺 | G87: 46209 | H87: 46213 | I87: 已完成 | J87: 已完成 | L87: 否 | M87: 完成日期待补充 | O87: W003|tsk-6844eefcb09f#001|业务
A88: 3 | B88: T106 | C88: 堆存库存统计（曹妃甸） | D88: 第一批次 | E88: 业务 | F88: 郑士旺 | G88: 46209 | H88: 46213 | I88: 已完成 | J88: 已完成 | L88: 否 | M88: 完成日期待补充 | O88: W003|tsk-c0b615e95db5#001|业务
A89: 3 | B89: T107 | C89: 分货主实时统计表（曹妃甸） | D89: 第一批次 | E89: 业务 | F89: 郑士旺 | G89: 46209 | H89: 46213 | I89: 已完成 | J89: 已完成 | L89: 否 | M89: 完成日期待补充 | O89: W003|tsk-010f2f0578d8#001|业务
A90: 3 | B90: T108 | C90: 综合装船效率分析（曹妃甸） | D90: 第一批次 | E90: 业务 | F90: 郑士旺 | G90: 46209 | H90: 46213 | I90: 已完成 | J90: 已完成 | L90: 否 | M90: 完成日期待补充 | O90: W003|tsk-ba126ef0228f#001|业务
A91: 3 | B91: T109 | C91: 综合卸车效率分析（曹妃甸） | D91: 第一批次 | E91: 业务 | F91: 郑士旺 | G91: 46209 | H91: 46213 | I91: 已完成 | J91: 已完成 | L91: 否 | M91: 完成日期待补充 | O91: W003|tsk-13ad283484a7#001|业务
A92: 3 | B92: T110 | C92: 综合卸船效率分析（曹妃甸） | D92: 第二批次 | E92: 业务 | F92: 郑士旺 | G92: 46209 | H92: 46213 | I92: 已完成 | J92: 已完成 | L92: 否 | M92: 完成日期待补充 | O92: W003|tsk-f441c61f54ad#001|业务
A93: 3 | B93: T138 | C93: 查询卸车流程 | D93: 第二批次 | E93: 业务 | F93: 郑士旺 | G93: 46209 | H93: 46213 | I93: 已完成 | J93: 已完成 | K93: 46261 | L93: 否 | O93: W003|tsk-a9cbee439438#001|业务
A94: 3 | B94: T139 | C94: 查询装船流程 | D94: 第二批次 | E94: 业务 | F94: 郑士旺 | G94: 46209 | H94: 46213 | I94: 已完成 | J94: 已完成 | K94: 46261 | L94: 否 | O94: W003|tsk-b174cf36c1c8#001|业务
A95: 3 | B95: T140 | C95: 查询卸船流程 | D95: 第二批次 | E95: 业务 | F95: 郑士旺 | G95: 46209 | H95: 46213 | I95: 已完成 | J95: 已完成 | L95: 否 | M95: 完成日期待补充 | O95: W003|tsk-b782224c74f5#001|业务
A96: 3 | B96: T143 | C96: 图片上传 | D96: 第一批次 | E96: 业务 | F96: 郑士旺 | G96: 46209 | H96: 46213 | I96: 已完成 | J96: 已完成 | K96: 46261 | L96: 否 | O96: W003|tsk-b14957c92331#001|业务
A97: 3 | B97: T144 | C97: 图片上传 | D97: 第一批次 | E97: 业务 | F97: 郑士旺 | G97: 46209 | H97: 46213 | I97: 已完成 | J97: 已完成 | K97: 46261 | L97: 否 | O97: W003|tsk-d942dd328122#001|业务
A98: 3 | B98: T145 | C98: 图片上传 | D98: 第二批次 | E98: 业务 | F98: 郑士旺 | G98: 46209 | H98: 46213 | I98: 已完成 | J98: 已完成 | L98: 否 | M98: 完成日期待补充 | O98: W003|tsk-577f9f403da5#001|业务
A99: 3 | B99: T058 | C99: OCR识别及编辑 | D99: 第一批次 | E99: 测试 | F99: 袁丽荣 | G99: 46202 | H99: 46213 | I99: 已完成 | J99: 已完成 | K99: 46224 | L99: 否 | O99: W003|tsk-8e34ce8f4239#001|测试
A100: 3 | B100: T070 | C100: 生成报告 | D100: 第一批次 | E100: 测试 | F100: 袁丽荣 | G100: 46202 | H100: 46213 | I100: 已完成 | J100: 已完成 | K100: 46224 | L100: 否 | O100: W003|tsk-38a802bbe105#001|测试
A101: 3 | B101: T071 | C101: 装船作业信息录入优化（太仓） | D101: 第一批次 | E101: 测试 | F101: 袁丽荣 | G101: 46202 | H101: 46213 | I101: 已完成 | J101: 已完成 | K101: 46224 | L101: 否 | O101: W003|tsk-cb19eab07c79#001|测试
A102: 4 | B102: T121 | C102: 船舶供应服务查询 | D102: 第二批次 | E102: 业务 | F102: 郑士旺 | G102: 46216 | H102: 46220 | I102: 已完成 | J102: 已完成 | K102: 46261 | L102: 否 | O102: W004|tsk-3c49a764e4d0#001|业务
A103: 4 | B103: T122 | C103: 船舶预到（内贸）查询 | D103: 第二批次 | E103: 业务 | F103: 郑士旺 | G103: 46216 | H103: 46220 | I103: 已完成 | J103: 已完成 | K103: 46261 | L103: 否 | O103: W004|tsk-7adc76236513#001|业务
A104: 4 | B104: T123 | C104: 台账查询 | D104: 第二批次 | E104: 业务 | F104: 郑士旺 | G104: 46216 | H104: 46220 | I104: 已完成 | J104: 已完成 | K104: 46261 | L104: 否 | O104: W004|tsk-27502e8eb665#001|业务
A105: 4 | B105: T124 | C105: 停泊费（内贸）查询 | D105: 第二批次 | E105: 业务 | F105: 郑士旺 | G105: 46216 | H105: 46220 | I105: 已完成 | J105: 已完成 | K105: 46261 | L105: 否 | O105: W004|tsk-4bbd9b69bf8e#001|业务
...

Sheet 集成管理
A1: 外部系统集成管理
A3: 集成ID | B3: 集成系统 | C3: 交互方式 | D3: 对接人 | E3: 集成内容 | F3: 原计划进展 | G3: 管理状态 | H3: 计划完成 | I3: 实际完成 | J3: 依赖事项 | K3: 风险等级 | L3: 风险/备注
A4: INT-01 | B4: 调运系统 | C4: 接入 | D4: 佘万明 | E4: 船舶轨迹位置、船舶档案、海图信息 | F4: 已完成 | G4: 已完成 | K4: 中
A5: INT-02 | B5: 法治平台 | C5: 接入 | D5: 许祥 | E5: 曹妃甸港、太仓港合同信息 | F5: 已初步对接，对方已提供接口文档，数据清单 | G5: 进行中 | K5: 高 | L5: 1.进度风险：法制平台7月上线试点运行，会在10月份全面上线，相关功能应用需在10月份后才能上线； 2.功能风险：企法部要求法制平台咱不提供接收合同接口，无法满足客户在本系统录入合同的需求，已与用户反馈，用户内部需进行评估
A6: INT-03 | B6: 集团大模型服务 | C6: 接入 | D6: 李超来 | E6: OCR能力 | F6: 已完成 | G6: 已完成 | K6: 高 | L6: 1.效率风险：文件识别效率偏低，需1分钟左右
A7: INT-04 | B7: 港航部科技项目系统 | C7: 接入 | E7: 曹妃甸港、太仓港视频监控数据 | F7: 已初步对接，对方预计10月份具备接口联调条件 | G7: 进行中 | K7: 高 | L7: 1.科技项目不会对接全部生产作业视频监控数据，需确认科技项目对接范围后确认是否满足用户需求
A8: INT-05 | B8: 曹妃甸管控一体化系统 | C8: 接入、推送 | D8: 张应龙 | E8: 基础数据、业务数据、结算数据 | F8: 未对接 | G8: 未开始 | K8: 中 | L8: 暂无
A9: INT-06 | B9: 太仓港管控一体化系统 | C9: 接入、推送 | D9: / | E9: 基础数据、业务数据、结算数据 | F9: 未对接 | G9: 未开始 | K9: 高 | L9: 1.太仓港管控一体化系统刚立项，集成工作暂时无法开展

Sheet 风险问题台账
A1: 风险与问题闭环台账
A3: 编号 | B3: 类型 | C3: 风险/问题描述 | D3: 等级 | E3: 影响范围 | F3: 责任人 | G3: 应对措施 | H3: 计划关闭 | I3: 实际关闭 | J3: 触发条件/根因 | K3: 状态 | L3: 剩余天数 | M3: 是否逾期 | N3: 跟踪记录
A4: R-001 | B4: 风险 | C4: 法治平台全面上线时间影响相关功能投产 | D4: 高 | E4: 合同信息集成 | F4: 集成负责人 | G4: 确认对方正式上线窗口，制定模拟数据和延期切换方案 | H4: 46310 | J4: 对方10月后方可正式支撑 | K4: 处理中 | L4: =IF(H4="","",H4-项目驾驶舱!$B$3) -> 34 | M4: =IF(OR(K4="已关闭",H4=""),"否",IF(H4<项目驾驶舱!$B$3,"是","否")) -> 否 | N4: 来源：原计划-集成工作
A5: R-002 | B5: 风险 | C5: 法治平台不提供合同接收接口，可能无法满足本系统录入合同需求 | D5: 高 | E5: 合同业务闭环 | F5: 项目经理 | G5: 推动用户决策，形成接口边界与替代方案确认单 | H5: 46283 | J5: 接口能力与业务诉求不一致 | K5: 待处理 | L5: =IF(H5="","",H5-项目驾驶舱!$B$3) -> 7 | M5: =IF(OR(K5="已关闭",H5=""),"否",IF(H5<项目驾驶舱!$B$3,"是","否")) -> 否 | N5: 来源：原计划-集成工作
A6: R-003 | B6: 风险 | C6: OCR识别耗时约1分钟，影响业务效率 | D6: 中 | E6: OCR能力 | F6: 技术负责人 | G6: 压测典型文件，确定超时阈值、异步处理与结果回调方案 | H6: 46290 | J6: 外部大模型服务性能 | K6: 处理中 | L6: =IF(H6="","",H6-项目驾驶舱!$B$3) -> 14 | M6: =IF(OR(K6="已关闭",H6=""),"否",IF(H6<项目驾驶舱!$B$3,"是","否")) -> 否 | N6: 来源：原计划-集成工作
A7: R-004 | B7: 风险 | C7: 视频监控数据对接范围尚未明确 | D7: 高 | E7: 视频监控 | F7: 集成负责人 | G7: 确认科技项目覆盖清单并补充缺口方案 | H7: 46280 | J7: 上游系统范围不确定 | K7: 待处理 | L7: =IF(H7="","",H7-项目驾驶舱!$B$3) -> 4 | M7: =IF(OR(K7="已关闭",H7=""),"否",IF(H7<项目驾驶舱!$B$3,"是","否")) -> 否 | N7: 来源：原计划-集成工作
A8: R-005 | B8: 风险 | C8: 太仓港管控一体化系统刚立项，集成工作无法按期开展 | D8: 高 | E8: 太仓港数据集成 | F8: 项目经理 | G8: 拆分依赖与非依赖工作，设立外部条件就绪门槛 | H8: 46326 | J8: 外部项目未形成可对接环境 | K8: 处理中 | L8: =IF(H8="","",H8-项目驾驶舱!$B$3) -> 50 | M8: =IF(OR(K8="已关闭",H8=""),"否",IF(H8<项目驾驶舱!$B$3,"是","否")) -> 否 | N8: 来源：原计划-集成工作
A9: R-006 | B9: 风险 | C9: 第二批次存在大量未开始任务，后续开发测试窗口集中 | D9: 高 | E9: 第二批次 | F9: 开发负责人 | G9: 按关键路径重排优先级，按周跟踪启动率与完成率 | H9: 46276 | J9: 资源与工作量集中 | K9: 待处理 | L9: =IF(H9="","",H9-项目驾驶舱!$B$3) -> 0 | M9: =IF(OR(K9="已关闭",H9=""),"否",IF(H9<项目驾驶舱!$B$3,"是","否")) -> 否 | N9: 基于开发计划识别
L10: =IF(H10="","",H10-项目驾驶舱!$B$3) | M10: =IF(OR(K10="已关闭",H10=""),"否",IF(H10<项目驾驶舱!$B$3,"是","否")) -> 否
L11: =IF(H11="","",H11-项目驾驶舱!$B$3) | M11: =IF(OR(K11="已关闭",H11=""),"否",IF(H11<项目驾驶舱!$B$3,"是","否")) -> 否
L12: =IF(H12="","",H12-项目驾驶舱!$B$3) | M12: =IF(OR(K12="已关闭",H12=""),"否",IF(H12<项目驾驶舱!$B$3,"是","否")) -> 否
L13: =IF(H13="","",H13-项目驾驶舱!$B$3) | M13: =IF(OR(K13="已关闭",H13=""),"否",IF(H13<项目驾驶舱!$B$3,"是","否")) -> 否
L14: =IF(H14="","",H14-项目驾驶舱!$B$3) | M14: =IF(OR(K14="已关闭",H14=""),"否",IF(H14<项目驾驶舱!$B$3,"是","否")) -> 否
L15: =IF(H15="","",H15-项目驾驶舱!$B$3) | M15: =IF(OR(K15="已关闭",H15=""),"否",IF(H15<项目驾驶舱!$B$3,"是","否")) -> 否
L16: =IF(H16="","",H16-项目驾驶舱!$B$3) | M16: =IF(OR(K16="已关闭",H16=""),"否",IF(H16<项目驾驶舱!$B$3,"是","否")) -> 否
L17: =IF(H17="","",H17-项目驾驶舱!$B$3) | M17: =IF(OR(K17="已关闭",H17=""),"否",IF(H17<项目驾驶舱!$B$3,"是","否")) -> 否
L18: =IF(H18="","",H18-项目驾驶舱!$B$3) | M18: =IF(OR(K18="已关闭",H18=""),"否",IF(H18<项目驾驶舱!$B$3,"是","否")) -> 否
L19: =IF(H19="","",H19-项目驾驶舱!$B$3) | M19: =IF(OR(K19="已关闭",H19=""),"否",IF(H19<项目驾驶舱!$B$3,"是","否")) -> 否
L20: =IF(H20="","",H20-项目驾驶舱!$B$3) | M20: =IF(OR(K20="已关闭",H20=""),"否",IF(H20<项目驾驶舱!$B$3,"是","否")) -> 否
L21: =IF(H21="","",H21-项目驾驶舱!$B$3) | M21: =IF(OR(K21="已关闭",H21=""),"否",IF(H21<项目驾驶舱!$B$3,"是","否")) -> 否
... L103: =IF(H103="","",H103-项目驾驶舱!$B$3) | M103: =IF(OR(K103="已关闭",H103=""),"否",IF(H103<项目驾驶舱!$B$3,"是","否")) -> 否

Sheet 变更台账
A1: 项目变更台账
A3: 变更编号 | B3: 提出日期 | C3: 提出人 | D3: 变更内容 | E3: 变更原因 | F3: 优先级 | G3: 审批状态 | H3: 范围影响 | I3: 工期影响(天) | J3: 成本影响 | K3: 评估人 | L3: 批准人 | M3: 实施日期 | N3: 关闭说明

Sheet 交付物台账
A1: 项目交付物与质量门禁
A3: 交付物ID | B3: 交付物名称 | C3: 类别 | D3: 责任人 | E3: 计划完成 | F3: 实际完成 | G3: 状态 | H3: 评审人 | I3: 评审结论 | J3: 版本/存放位置 | K3: 备注
A4: D-001 | B4: 项目管理计划 | C4: 管理 | D4: 项目经理 | E4: 46192 | G4: 进行中 | H4: 项目负责人 | I4: 待评审 | J4: 69 | K4: 69
A5: D-002 | B5: 业务需求规格说明书 | C5: 需求 | D5: 郑士旺 | E5: 46241 | G5: 进行中 | H5: 业务负责人 | I5: 待评审 | J5: 69 | K5: 69
A6: D-003 | B6: 系统总体设计说明书 | C6: 设计 | D6: 技术负责人 | E6: 46248 | G6: 进行中 | H6: 架构负责人 | I6: 待评审 | J6: 69 | K6: 69
A7: D-004 | B7: 接口清单及接口设计说明 | C7: 集成 | D7: 集成负责人 | E7: 46283 | G7: 进行中 | H7: 技术负责人 | I7: 待评审 | J7: 69 | K7: 69
A8: D-005 | B8: 第一批次测试报告 | C8: 测试 | D8: 袁丽荣 | E8: 46318 | G8: 进行中 | H8: 项目经理 | I8: 待评审 | J8: 69 | K8: 69
A9: D-006 | B9: 第二批次测试报告 | C9: 测试 | D9: 袁丽荣 | E9: 46353 | G9: 未开始 | H9: 项目经理 | I9: 待评审 | J9: 69 | K9: 69
A10: D-007 | B10: 上线方案及回退方案 | C10: 上线 | D10: 运维负责人 | E10: 46346 | G10: 未开始 | H10: 项目经理 | I10: 待评审 | J10: 69 | K10: 69
A11: D-008 | B11: 用户操作手册 | C11: 培训 | D11: 实施负责人 | E11: 46349 | G11: 未开始 | H11: 业务负责人 | I11: 待评审 | J11: 69 | K11: 69
A12: D-009 | B12: 用户验收报告 | C12: 验收 | D12: 项目经理 | E12: 46356 | G12: 未开始 | H12: 项目负责人 | I12: 待评审 | J12: 69 | K12: 69
A13: D-010 | B13: 项目总结与移交清单 | C13: 收尾 | D13: 项目经理 | E13: 46360 | G13: 未开始 | H13: 项目负责人 | I13: 待评审 | J13: 69 | K13: 69

Sheet 会议行动项
A1: 会议纪要与行动项跟踪
A3: 行动项ID | B3: 会议日期 | C3: 会议主题 | D3: 决策/行动事项 | E3: 责任人 | F3: 协同人 | G3: 截止日期 | H3: 状态 | I3: 完成日期 | J3: 逾期天数 | K3: 优先级 | L3: 结果说明
J4: =IF(OR(G4="",H4="已完成"),0,MAX(0,项目驾驶舱!$B$3-G4)) -> 0
J5: =IF(OR(G5="",H5="已完成"),0,MAX(0,项目驾驶舱!$B$3-G5)) -> 0
J6: =IF(OR(G6="",H6="已完成"),0,MAX(0,项目驾驶舱!$B$3-G6)) -> 0
J7: =IF(OR(G7="",H7="已完成"),0,MAX(0,项目驾驶舱!$B$3-G7)) -> 0
J8: =IF(OR(G8="",H8="已完成"),0,MAX(0,项目驾驶舱!$B$3-G8)) -> 0
J9: =IF(OR(G9="",H9="已完成"),0,MAX(0,项目驾驶舱!$B$3-G9)) -> 0
J10: =IF(OR(G10="",H10="已完成"),0,MAX(0,项目驾驶舱!$B$3-G10)) -> 0
J11: =IF(OR(G11="",H11="已完成"),0,MAX(0,项目驾驶舱!$B$3-G11)) -> 0
J12: =IF(OR(G12="",H12="已完成"),0,MAX(0,项目驾驶舱!$B$3-G12)) -> 0
J13: =IF(OR(G13="",H13="已完成"),0,MAX(0,项目驾驶舱!$B$3-G13)) -> 0
J14: =IF(OR(G14="",H14="已完成"),0,MAX(0,项目驾驶舱!$B$3-G14)) -> 0
J15: =IF(OR(G15="",H15="已完成"),0,MAX(0,项目驾驶舱!$B$3-G15)) -> 0
... J103: =IF(OR(G103="",H103="已完成"),0,MAX(0,项目驾驶舱!$B$3-G103)) -> 0

Sheet 使用说明
A1: 项目管理工作簿使用说明
A3: 标准更新流程 | B3: 1. 将最新项目计划放入inputs目录；2. 发起“更新V2模板”；3. 系统按文件修改时间选择最新Excel；4. 核对总控、诊断、督办和资源计划。
A4: 输入目录 | B4: 固定从项目目录下的inputs文件夹读取；支持.xlsx和.xlsm，并自动忽略以~$开头的Excel临时文件。
A5: 本次数据来源 | B5: RLMGH-PBG-PLN-华能交易中心-港口交易平台开发计划-20260910-V2.xlsx
A6: 任务范围 | B6: 根据最新开发计划动态识别任务行，本次共145条任务；任务增减时，总控及相关明细范围同步调整。
A7: 统计日期 | B7: 在“项目驾驶舱”B3修改统计日期，延期、剩余天数、临近到期和两周督办会同步变化。
A8: 挂起与暂停 | B8: 业务、后端、前端或测试任一环节为“挂起”或“暂停”时，总体状态自动显示“暂停”；延期状态同步显示“暂停”。
A9: 综合进度口径 | B9: 业务设计15%、后端开发35%、前端开发30%、测试20%；进行中按该阶段50%计，完成按100%计。
A10: 延期口径 | B10: 总体状态不是“已完成”或“暂停”，且计划完成日期早于统计日期，判定为“已延期”；7天内到期为“临近到期”。
A11: 资源计划 | B11: 资源汇总和周计划直接根据总控台账生成；周计划按人员分组合并，用于查看每周是否有任务及任务清单。
A12: 资源录入 | B12: 每人每周可用工时固定为40小时，并在同一周的并行任务间平均分配到0.5小时档位；取整超额从部分任务中调减，确保该人员当周合计仍为40小时。跨周任务累计各周分摊工时。
A13: 成本口径 | B13: 统一人员单价为1200元/人天，按8小时/人天折算为150元/小时。驾驶舱计划人工成本根据资源汇总的计划投入工时计算。
A14: 周迭代计划 | B14: 上方周汇总承诺完成、延期、暂停；下方按总控任务四阶段展开；周目标和复盘由人工填写，其余内容在更新V2时重建。
... A19: 风险管理工具 | B19: 按风险管理计划统一评分和升级口径；风险登记册是唯一风险数据源；热力图、重点清单和驾驶舱自动读取登记册；重大风险填写专项应对，具体行动进入风险应对计划。

Sheet AI项目诊断
A1: AI项目诊断
A2: 数据日期引用“项目驾驶舱”B3；红黄绿由客观规则计算，管理判断由项目经理确认。
A4: 数据日期 | B4: =项目驾驶舱!B3 -> 46276 | D4: 项目经理判断 | E4: 待确认 | G4: 判断说明 | H4: 根据诊断指标补充总体判断、最大失控点和需要的支持。
A6: 任务总数 | D6: 已完成任务 | G6: 逾期任务 | J6: 未来14天到期
A7: =COUNTIF(项目总控台账!$A$4:$A$148,"<>") -> 145 | D7: =COUNTIF(项目总控台账!$G$4:$G$148,"已完成") -> 73 | G7: =COUNTIF(项目总控台账!$AC$4:$AC$148,"已延期")+COUNTIF(项目总控台账!$AC$4:$AC$148,"延期") -> 24 | J7: =COUNTIFS(项目总控台账!$J$4:$J$148,">="&项目驾驶舱!$B$3,项目总控台账!$J$4:$J$148,"<="&项目驾驶舱!$B$3+14,项目总控台账!$G$4:$G$148,"<>已完成") -> 0
A9: 未关闭高风险 | D9: 逾期风险/问题 | G9: 逾期行动项 | J9: 数据质量问题
A10: =COUNTIFS(风险问题台账!$D$4:$D$102,"高",风险问题台账!$K$4:$K$102,"<>已关闭") -> 5 | D10: =COUNTIF(风险问题台账!$M$4:$M$102,"是") -> 0 | G10: =COUNTIFS(会议行动项!$J$4:$J$102,">0",会议行动项!$H$4:$H$102,"<>已完成") -> 0 | J10: =COUNTIF(数据质量检查!$H$5:$H$149,"需整改") -> 12
A13: 项目健康规则 | H13: 状态分布
A14: 维度 | B14: 状态 | C14: 客观判断 | D14: 触发规则 | E14: 建议动作 | F14: 责任角色 | H14: 状态 | I14: 数量
A15: 进度 | B15: =IF(COUNTIF(项目总控台账!$AC$4:$AC$148,"*延期*")>=5,"红",IF(OR(COUNTIF(项目总控台账!$AC$4:$AC$148,"*延期*")>0,COUNTIF(项目总控台账!$G$4:$G$148,"暂停")>0),"黄","绿")) -> 红 | C15: =COUNTIF(项目总控台账!$AC$4:$AC$148,"*延期*")&"项任务延期；"&COUNTIF(项目总控台账!$G$4:$G$148,"暂停")&"项任务暂停" -> 24项任务延期；6项任务暂停 | D15: 延期≥5红；有延期或暂停黄；否则绿 | E15: 确认关键路径、暂停原因和恢复条件 | F15: 项目经理 | H15: 绿 | I15: =COUNTIF($B$15:$B$20,H15) -> 3
A16: 风险 | B16: =IF(COUNTIFS(风险问题台账!$D$4:$D$102,"高",风险问题台账!$K$4:$K$102,"<>已关闭")>=3,"红",IF(COUNTIFS(风险问题台账!$D$4:$D$102,"高",风险问题台账!$K$4:$K$102,"<>已关闭")>0,"黄","绿")) -> 红 | C16: =COUNTIFS(风险问题台账!$D$4:$D$102,"高",风险问题台账!$K$4:$K$102,"<>已关闭")&"项高风险未关闭" -> 5项高风险未关闭 | D16: 高风险≥3红；1-2黄；0绿 | E16: 逐项落实责任人和关闭证据 | F16: 风险责任人 | H16: 黄 | I16: =COUNTIF($B$15:$B$20,H16) -> 0
A17: 行动 | B17: =IF(COUNTIFS(会议行动项!$J$4:$J$102,">7",会议行动项!$H$4:$H$102,"<>已完成")>0,"红",IF(COUNTIFS(会议行动项!$J$4:$J$102,">0",会议行动项!$H$4:$H$102,"<>已完成")>0,"黄","绿")) -> 绿 | C17: =COUNTIFS(会议行动项!$J$4:$J$102,">0",会议行动项!$H$4:$H$102,"<>已完成")&"项行动逾期" -> 0项行动逾期 | D17: 逾期>7天红；有逾期黄；无逾期绿 | E17: 升级逾期事项并确认新承诺 | F17: PMO | H17: 红 | I17: =COUNTIF($B$15:$B$20,H17) -> 3
A18: 数据 | B18: =IF(COUNTIF(数据质量检查!$H$5:$H$149,"需整改")>=10,"红",IF(COUNTIF(数据质量检查!$H$5:$H$149,"需整改")>0,"黄","绿")) -> 红 | C18: =COUNTIF(数据质量检查!$H$5:$H$149,"需整改")&"条数据需整改" -> 12条数据需整改 | D18: 缺陷≥10红；1-9黄；0绿 | E18: 补齐责任人、日期和状态 | F18: 台账维护人 | H18: 灰 | I18: =COUNTIF($B$15:$B$20,H18) -> 0
A19: 相关方 | B19: =IF(COUNTIFS(相关方管理!$H$9:$H$108,"高",相关方管理!$J$9:$J$108,"抵触")+COUNTIFS(相关方管理!$H$9:$H$108,"高",相关方管理!$J$9:$J$108,"不支持")>0,"红",IF(COUNTIFS(相关方管理!$L$9:$L$108,">0")+COUNTIFS(相关方管理!$T$9:$T$108,"<"&项目驾驶舱!$B$3,相关方管理!$T$9:$T$108,"<>")>0,"黄","绿")) -> 绿 | C19: =COUNTIFS(相关方管理!$L$9:$L$108,">0")&"人存在支持差距；"&COUNTIFS(相关方管理!$Z$9:$Z$108,"是")&"项需升级" -> 0人存在支持差距；0项需升级 | D19: 高权力不支持红；存在支持差距或沟通逾期黄；否则绿 | E19: 确认诉求、沟通计划、责任人和升级路径 | F19: 项目经理
A20: 风险治理 | B20: =IF(COUNTIFS(风险登记册!$AH$9:$AH$108,"重大")>0,"红",IF(COUNTIFS(风险登记册!$AH$9:$AH$108,"高")+COUNTIFS(风险应对计划!$Q$5:$Q$104,"是")>0,"黄","绿")) -> 绿 | C20: =COUNTIFS(风险登记册!$AH$9:$AH$108,"重大")&"项重大剩余风险；"&COUNTIFS(风险应对计划!$Q$5:$Q$104,"是")&"项应对逾期" -> 0项重大剩余风险；0项应对逾期 | D20: 有重大剩余风险红；有高风险或应对逾期黄；否则绿 | E20: 确认重大风险决策、应对责任和关闭证据 | F20: PMO

Sheet 数据质量检查
A1: 数据质量检查
A2: 逐条检查项目总控台账中的关键管理字段。状态为“需整改”的记录应在源台账中修正。
A4: 来源 | B4: 记录ID | C4: 任务名称 | D4: 责任人 | E4: 计划开始 | F4: 计划完成 | G4: 发现的问题 | H4: 检查状态 | I4: 建议动作 | J4: 源行号
A5: 项目总控台账 | B5: =项目总控台账!A4 -> T001 | C5: =IF(AND(项目总控台账!E4<>"",项目总控台账!E4<>"/"),项目总控台账!E4,IF(AND(项目总控台账!D4<>"",项目总控台账!D4<>"/"),项目总控台账!D4,项目总控台账!C4)) -> 新增车辆信息 | D5: =项目总控台账!H4 -> 郑士旺 | E5: =项目总控台账!I4 -> 46202 | F5: =项目总控台账!J4 -> 46234 | G5: =IF(B5="","",IF(OR(C5="",C5="/"),"缺少任务名称；","")&IF(OR(D5="",D5="/"),"缺少有效主责人；","")&IF(OR(E5="",E5<DATE(2000,1,1)),"缺少有效计划开始；","")&IF(OR(F5="",F5<DATE(2000,1,1)),"缺少有效计划完成；","")&IF(项目总控台账!G4="","缺少总体状态；","")&IF(AND(ISNUMBER(E5),ISNUMBER(F5),E5>=DATE(2000,1,1),F5>=DATE(2000,1,1),E5>F5),"开始晚于完成；","")&IF(AND(项目总控台账!G4="已完成",项目总控台账!AB4<1),"已完成但进度不足100%；","")) | H5: =IF(B5="","",IF(G5="","通过","需整改")) -> 通过 | I5: =IF(H5="需整改","回到项目总控台账第"&J5&"行补齐或修正","无需处理") -> 无需处理 | J5: 4
A6: 项目总控台账 | B6: =项目总控台账!A5 -> T002 | C6: =IF(AND(项目总控台账!E5<>"",项目总控台账!E5<>"/"),项目总控台账!E5,IF(AND(项目总控台账!D5<>"",项目总控台账!D5<>"/"),项目总控台账!D5,项目总控台账!C5)) -> 修改车辆信息 | D6: =项目总控台账!H5 -> 郑士旺 | E6: =项目总控台账!I5 -> 46202 | F6: =项目总控台账!J5 -> 46234 | G6: =IF(B6="","",IF(OR(C6="",C6="/"),"缺少任务名称；","")&IF(OR(D6="",D6="/"),"缺少有效主责人；","")&IF(OR(E6="",E6<DATE(2000,1,1)),"缺少有效计划开始；","")&IF(OR(F6="",F6<DATE(2000,1,1)),"缺少有效计划完成；","")&IF(项目总控台账!G5="","缺少总体状态；","")&IF(AND(ISNUMBER(E6),ISNUMBER(F6),E6>=DATE(2000,1,1),F6>=DATE(2000,1,1),E6>F6),"开始晚于完成；","")&IF(AND(项目总控台账!G5="已完成",项目总控台账!AB5<1),"已完成但进度不足100%；","")) | H6: =IF(B6="","",IF(G6="","通过","需整改")) -> 通过 | I6: =IF(H6="需整改","回到项目总控台账第"&J6&"行补齐或修正","无需处理") -> 无需处理 | J6: 5
A7: 项目总控台账 | B7: =项目总控台账!A6 -> T003 | C7: =IF(AND(项目总控台账!E6<>"",项目总控台账!E6<>"/"),项目总控台账!E6,IF(AND(项目总控台账!D6<>"",项目总控台账!D6<>"/"),项目总控台账!D6,项目总控台账!C6)) -> 删除车辆信息 | D7: =项目总控台账!H6 -> 郑士旺 | E7: =项目总控台账!I6 -> 46202 | F7: =项目总控台账!J6 -> 46234 | G7: =IF(B7="","",IF(OR(C7="",C7="/"),"缺少任务名称；","")&IF(OR(D7="",D7="/"),"缺少有效主责人；","")&IF(OR(E7="",E7<DATE(2000,1,1)),"缺少有效计划开始；","")&IF(OR(F7="",F7<DATE(2000,1,1)),"缺少有效计划完成；","")&IF(项目总控台账!G6="","缺少总体状态；","")&IF(AND(ISNUMBER(E7),ISNUMBER(F7),E7>=DATE(2000,1,1),F7>=DATE(2000,1,1),E7>F7),"开始晚于完成；","")&IF(AND(项目总控台账!G6="已完成",项目总控台账!AB6<1),"已完成但进度不足100%；","")) | H7: =IF(B7="","",IF(G7="","通过","需整改")) -> 通过 | I7: =IF(H7="需整改","回到项目总控台账第"&J7&"行补齐或修正","无需处理") -> 无需处理 | J7: 6
A8: 项目总控台账 | B8: =项目总控台账!A7 -> T004 | C8: =IF(AND(项目总控台账!E7<>"",项目总控台账!E7<>"/"),项目总控台账!E7,IF(AND(项目总控台账!D7<>"",项目总控台账!D7<>"/"),项目总控台账!D7,项目总控台账!C7)) -> 查询展示车辆信息 | D8: =项目总控台账!H7 -> 郑士旺 | E8: =项目总控台账!I7 -> 46202 | F8: =项目总控台账!J7 -> 46234 | G8: =IF(B8="","",IF(OR(C8="",C8="/"),"缺少任务名称；","")&IF(OR(D8="",D8="/"),"缺少有效主责人；","")&IF(OR(E8="",E8<DATE(2000,1,1)),"缺少有效计划开始；","")&IF(OR(F8="",F8<DATE(2000,1,1)),"缺少有效计划完成；","")&IF(项目总控台账!G7="","缺少总体状态；","")&IF(AND(ISNUMBER(E8),ISNUMBER(F8),E8>=DATE(2000,1,1),F8>=DATE(2000,1,1),E8>F8),"开始晚于完成；","")&IF(AND(项目总控台账!G7="已完成",项目总控台账!AB7<1),"已完成但进度不足100%；","")) | H8: =IF(B8="","",IF(G8="","通过","需整改")) -> 通过 | I8: =IF(H8="需整改","回到项目总控台账第"&J8&"行补齐或修正","无需处理") -> 无需处理 | J8: 7
A9: 项目总控台账 | B9: =项目总控台账!A8 -> T005 | C9: =IF(AND(项目总控台账!E8<>"",项目总控台账!E8<>"/"),项目总控台账!E8,IF(AND(项目总控台账!D8<>"",项目总控台账!D8<>"/"),项目总控台账!D8,项目总控台账!C8)) -> 船舶唯一性校验 | D9: =项目总控台账!H8 -> 郑士旺 | E9: =项目总控台账!I8 -> 46230 | F9: =项目总控台账!J8 -> 46353 | G9: =IF(B9="","",IF(OR(C9="",C9="/"),"缺少任务名称；","")&IF(OR(D9="",D9="/"),"缺少有效主责人；","")&IF(OR(E9="",E9<DATE(2000,1,1)),"缺少有效计划开始；","")&IF(OR(F9="",F9<DATE(2000,1,1)),"缺少有效计划完成；","")&IF(项目总控台账!G8="","缺少总体状态；","")&IF(AND(ISNUMBER(E9),ISNUMBER(F9),E9>=DATE(2000,1,1),F9>=DATE(2000,1,1),E9>F9),"开始晚于完成；","")&IF(AND(项目总控台账!G8="已完成",项目总控台账!AB8<1),"已完成但进度不足100%；","")) | H9: =IF(B9="","",IF(G9="","通过","需整改")) -> 通过 | I9: =IF(H9="需整改","回到项目总控台账第"&J9&"行补齐或修正","无需处理") -> 无需处理 | J9: 8
A10: 项目总控台账 | B10: =项目总控台账!A9 -> T006 | C10: =IF(AND(项目总控台账!E9<>"",项目总控台账!E9<>"/"),项目总控台账!E9,IF(AND(项目总控台账!D9<>"",项目总控台账!D9<>"/"),项目总控台账!D9,项目总控台账!C9)) -> 优化收费标准（装卸费）新增 | D10: =项目总控台账!H9 -> 郑士旺 | E10: =项目总控台账!I9 -> 46202 | F10: =项目总控台账!J9 -> 46224 | G10: =IF(B10="","",IF(OR(C10="",C10="/"),"缺少任务名称；","")&IF(OR(D10="",D10="/"),"缺少有效主责人；","")&IF(OR(E10="",E10<DATE(2000,1,1)),"缺少有效计划开始；","")&IF(OR(F10="",F10<DATE(2000,1,1)),"缺少有效计划完成；","")&IF(项目总控台账!G9="","缺少总体状态；","")&IF(AND(ISNUMBER(E10),ISNUMBER(F10),E10>=DATE(2000,1,1),F10>=DATE(2000,1,1),E10>F10),"开始晚于完成；","")&IF(AND(项目总控台账!G9="已完成",项目总控台账!AB9<1),"已完成但进度不足100%；","")) | H10: =IF(B10="","",IF(G10="","通过","需整改")) -> 通过 | I10: =IF(H10="需整改","回到项目总控台账第"&J10&"行补齐或修正","无需处理") -> 无需处理 | J10: 9
A11: 项目总控台账 | B11: =项目总控台账!A10 -> T007 | C11: =IF(AND(项目总控台账!E10<>"",项目总控台账!E10<>"/"),项目总控台账!E10,IF(AND(项目总控台账!D10<>"",项目总控台账!D10<>"/"),项目总控台账!D10,项目总控台账!C10)) -> 优化收费标准（装卸费）编辑 | D11: =项目总控台账!H10 -> 郑士旺 | E11: =项目总控台账!I10 -> 46202 | F11: =项目总控台账!J10 -> 46224 | G11: =IF(B11="","",IF(OR(C11="",C11="/"),"缺少任务名称；","")&IF(OR(D11="",D11="/"),"缺少有效主责人；","")&IF(OR(E11="",E11<DATE(2000,1,1)),"缺少有效计划开始；","")&IF(OR(F11="",F11<DATE(2000,1,1)),"缺少有效计划完成；","")&IF(项目总控台账!G10="","缺少总体状态；","")&IF(AND(ISNUMBER(E11),ISNUMBER(F11),E11>=DATE(2000,1,1),F11>=DATE(2000,1,1),E11>F11),"开始晚于完成；","")&IF(AND(项目总控台账!G10="已完成",项目总控台账!AB10<1),"已完成但进度不足100%；","")) | H11: =IF(B11="","",IF(G11="","通过","需整改")) -> 通过 | I11: =IF(H11="需整改","回到项目总控台账第"&J11&"行补齐或修正","无需处理") -> 无需处理 | J11: 10
A12: 项目总控台账 | B12: =项目总控台账!A11 -> T008 | C12: =IF(AND(项目总控台账!E11<>"",项目总控台账!E11<>"/"),项目总控台账!E11,IF(AND(项目总控台账!D11<>"",项目总控台账!D11<>"/"),项目总控台账!D11,项目总控台账!C11)) -> 优化收费标准（装卸费）详情 | D12: =项目总控台账!H11 -> 郑士旺 | E12: =项目总控台账!I11 -> 46202 | F12: =项目总控台账!J11 -> 46224 | G12: =IF(B12="","",IF(OR(C12="",C12="/"),"缺少任务名称；","")&IF(OR(D12="",D12="/"),"缺少有效主责人；","")&IF(OR(E12="",E12<DATE(2000,1,1)),"缺少有效计划开始；","")&IF(OR(F12="",F12<DATE(2000,1,1)),"缺少有效计划完成；","")&IF(项目总控台账!G11="","缺少总体状态；","")&IF(AND(ISNUMBER(E12),ISNUMBER(F12),E12>=DATE(2000,1,1),F12>=DATE(2000,1,1),E12>F12),"开始晚于完成；","")&IF(AND(项目总控台账!G11="已完成",项目总控台账!AB11<1),"已完成但进度不足100%；","")) | H12: =IF(B12="","",IF(G12="","通过","需整改")) -> 通过 | I12: =IF(H12="需整改","回到项目总控台账第"&J12&"行补齐或修正","无需处理") -> 无需处理 | J12: 11
A13: 项目总控台账 | B13: =项目总控台账!A12 -> T009 | C13: =IF(AND(项目总控台账!E12<>"",项目总控台账!E12<>"/"),项目总控台账!E12,IF(AND(项目总控台账!D12<>"",项目总控台账!D12<>"/"),项目总控台账!D12,项目总控台账!C12)) -> 优化采样方式新增 | D13: =项目总控台账!H12 -> 郑士旺 | E13: =项目总控台账!I12 -> 46202 | F13: =项目总控台账!J12 -> 46224 | G13: =IF(B13="","",IF(OR(C13="",C13="/"),"缺少任务名称；","")&IF(OR(D13="",D13="/"),"缺少有效主责人；","")&IF(OR(E13="",E13<DATE(2000,1,1)),"缺少有效计划开始；","")&IF(OR(F13="",F13<DATE(2000,1,1)),"缺少有效计划完成；","")&IF(项目总控台账!G12="","缺少总体状态；","")&IF(AND(ISNUMBER(E13),ISNUMBER(F13),E13>=DATE(2000,1,1),F13>=DATE(2000,1,1),E13>F13),"开始晚于完成；","")&IF(AND(项目总控台账!G12="已完成",项目总控台账!AB12<1),"已完成但进度不足100%；","")) | H13: =IF(B13="","",IF(G13="","通过","需整改")) -> 通过 | I13: =IF(H13="需整改","回到项目总控台账第"&J13&"行补齐或修正","无需处理") -> 无需处理 | J13: 12
