Workbook

Sheet 项目驾驶舱
A1: 华能交易中心港口交易平台｜项目管理驾驶舱
A3: 统计日期 | B3: 46268
A5: 总任务数 | B5: 已完成 | C5: 进行中 | D5: 未开始 | E5: 暂停 | F5: 平均进度 | G5: 已延期 | H5: 临近到期 | I5: 高风险 | J5: 未关闭问题 | K5: 待决变更 | L5: 里程碑达成 | M5: 集成完成 | N5: 交付物完成
A6: =COUNTA(项目总控台账!$A$4:$A$203) | B6: =COUNTIF(项目总控台账!$G$4:$G$203,"已完成") | C6: =COUNTIF(项目总控台账!$G$4:$G$203,"进行中") | D6: =COUNTIF(项目总控台账!$G$4:$G$203,"未开始") | E6: =COUNTIF(项目总控台账!$G$4:$G$203,"暂停") | F6: =AVERAGE(项目总控台账!$AB$4:$AB$203) | G6: =COUNTIF(项目总控台账!$AC$4:$AC$203,"已延期") | H6: =COUNTIF(项目总控台账!$AC$4:$AC$203,"临近到期") | I6: =COUNTIFS(风险问题台账!$D$4:$D$103,"高",风险问题台账!$K$4:$K$103,"<>已关闭") | J6: =COUNTIF(风险问题台账!$K$4:$K$103,"处理中")+COUNTIF(风险问题台账!$K$4:$K$103,"待处理") | K6: =COUNTIF(变更台账!$G$4:$G$53,"评估中")+COUNTIF(变更台账!$G$4:$G$53,"待审批") | L6: =IFERROR(COUNTIF(里程碑计划!$G$4:$G$23,"已完成")/COUNTA(里程碑计划!$A$4:$A$23),0) | M6: =IFERROR(COUNTIF(集成管理!$G$4:$G$53,"已完成")/COUNTA(集成管理!$A$4:$A$53),0) | N6: =IFERROR(COUNTIF(交付物台账!$G$4:$G$53,"已完成")/COUNTA(交付物台账!$A$4:$A$53),0)
A9: 状态 | B9: 任务数 | D9: 批次 | E9: 任务数 | F9: 已完成 | G9: 完成率
A10: 已完成 | B10: =B6 | D10: 第一批次 | E10: =COUNTIF(项目总控台账!$F$4:$F$203,D10) | F10: =COUNTIFS(项目总控台账!$F$4:$F$203,D10,项目总控台账!$G$4:$G$203,"已完成") | G10: =IFERROR(F10/E10,0)
A11: 进行中 | B11: =C6 | D11: 第二批次 | E11: =COUNTIF(项目总控台账!$F$4:$F$203,D11) | F11: =COUNTIFS(项目总控台账!$F$4:$F$203,D11,项目总控台账!$G$4:$G$203,"已完成") | G11: =IFERROR(F11/E11,0)
A12: 未开始 | B12: =D6 | D12: 其他 | E12: =$A$6-E10-E11 | F12: =$B$6-F10-F11 | G12: =IFERROR(F12/E12,0)
A13: 暂停 | B13: =E6
A16: 管理关注点
A17: ="截至 "&TEXT($B$3,"yyyy-mm-dd")&"：延期任务 "&G6&" 项，临近到期 "&H6&" 项，高风险 "&I6&" 项。建议优先处理外部系统集成依赖、第二批次未启动任务及无明确上线日期的功能。"
J22: 进度与成本指标
J23: 综合进度 | K23: =AVERAGE('项目总控台账'!$AB$4:$AB$148) | M23: 人日单价 | N23: 1200
J24: 任务完成率 | K24: =COUNTIF('项目总控台账'!$G$4:$G$148,"已完成")/COUNTIF('项目总控台账'!$A$4:$A$148,"<>") | M24: 小时单价 | N24: =N23/8
J25: 计划投入人天 | K25: =SUM('资源计划'!$I$16:$I$707)/8 | M25: 计划人工成本 | N25: =K25*N23
J26: 已完成任务人天 | K26: =SUMIFS('资源计划'!$I$16:$I$707,'资源计划'!$F$16:$F$707,"已完成")/8 | M26: 已完成任务成本 | N26: =K26*N23
J27: 剩余计划人天 | K27: =MAX(K25-K26,0) | M27: 剩余计划成本 | N27: =K27*N23
J29: 成本指标按计划工时计算；实际成本、CPI和EAC将在补充实际工时后启用。

Sheet 项目总控台账
A1: 华能交易中心港口交易平台｜项目总控台账
A2: 蓝色字段来自原开发计划；黄色字段为管理补充项；进度与延期由公式自动计算。
A3: 任务ID | B3: 一级功能 | C3: 二级功能 | D3: 三级功能 | E3: 四级功能 | F3: 批次 | G3: 总体状态 | H3: 主责人 | I3: 计划开始 | J3: 计划完成 | K3: 计划上线 | L3: 业务负责人 | M3: 业务状态 | N3: 业务开始 | O3: 业务结束 | P3: 后端负责人 | Q3: 后端状态 | R3: 后端开始 | S3: 后端结束 | T3: 前端负责人 | U3: 前端状态 | V3: 前端开始 | W3: 前端结束 | X3: 测试负责人 | Y3: 测试状态 | Z3: 测试开始 | AA3: 测试结束 | AB3: 综合进度 | AC3: 延期状态 | AD3: 当前问题/阻塞 | AE3: 备注
A4: T001 | B4: 基础数据 | C4: 车辆信息维护 | D4: 新增车辆信息 | E4: / | F4: 第一批次 | G4: =IF(OR(M4="挂起",M4="暂停",Q4="挂起",Q4="暂停",U4="挂起",U4="暂停",Y4="挂起",Y4="暂停"),"暂停","已完成") | H4: =IF(L4<>"",L4,IF(P4<>"",P4,IF(T4<>"",T4,X4))) | I4: =IF(COUNT(N4,R4,V4,Z4)=0,"",MIN(N4,R4,V4,Z4)) | J4: =IF(ISNUMBER(K4),K4,IF(COUNT(O4,S4,W4,AA4)=0,"",MAX(O4,S4,W4,AA4))) | K4: / | L4: 郑士旺 | M4: 已完成 | N4: 46202 | O4: 46206 | P4: 石军磊、刘凯 | Q4: 已完成 | R4: 46209 | S4: 46225 | T4: 贺航 | U4: 已完成 | V4: 46209 | W4: 46225 | X4: 袁丽荣 | Y4: 已完成 | Z4: 46216 | AA4: 46234 | AB4: =(IF(M4="已完成",1,IF(M4="进行中",0.5,0))*15%+IF(Q4="已完成",1,IF(Q4="进行中",0.5,0))*35%+IF(U4="已完成",1,IF(U4="进行中",0.5,0))*30%+IF(Y4="已完成",1,IF(Y4="进行中",0.5,0))*20%) | AC4: =IF(G4="已完成","正常",IF(OR(G4="暂停",G4="挂起"),"暂停",IF(J4="","日期缺失",IF(J4<'项目驾驶舱'!$B$3,"已延期",IF(J4<='项目驾驶舱'!$B$3+7,"临近到期","正常")))))
A5: T002 | B5: 基础数据 | C5: 车辆信息维护 | D5: 修改车辆信息 | E5: / | F5: 第一批次 | G5: =IF(OR(M5="挂起",M5="暂停",Q5="挂起",Q5="暂停",U5="挂起",U5="暂停",Y5="挂起",Y5="暂停"),"暂停","已完成") | H5: =IF(L5<>"",L5,IF(P5<>"",P5,IF(T5<>"",T5,X5))) | I5: =IF(COUNT(N5,R5,V5,Z5)=0,"",MIN(N5,R5,V5,Z5)) | J5: =IF(ISNUMBER(K5),K5,IF(COUNT(O5,S5,W5,AA5)=0,"",MAX(O5,S5,W5,AA5))) | K5: / | L5: 郑士旺 | M5: 已完成 | N5: 46202 | O5: 46206 | P5: 石军磊、刘凯 | Q5: 已完成 | R5: 46209 | S5: 46225 | T5: 贺航 | U5: 已完成 | V5: 46209 | W5: 46225 | X5: 袁丽荣 | Y5: 已完成 | Z5: 46216 | AA5: 46234 | AB5: =(IF(M5="已完成",1,IF(M5="进行中",0.5,0))*15%+IF(Q5="已完成",1,IF(Q5="进行中",0.5,0))*35%+IF(U5="已完成",1,IF(U5="进行中",0.5,0))*30%+IF(Y5="已完成",1,IF(Y5="进行中",0.5,0))*20%) | AC5: =IF(G5="已完成","正常",IF(OR(G5="暂停",G5="挂起"),"暂停",IF(J5="","日期缺失",IF(J5<'项目驾驶舱'!$B$3,"已延期",IF(J5<='项目驾驶舱'!$B$3+7,"临近到期","正常")))))
A6: T003 | B6: 基础数据 | C6: 车辆信息维护 | D6: 删除车辆信息 | E6: / | F6: 第一批次 | G6: =IF(OR(M6="挂起",M6="暂停",Q6="挂起",Q6="暂停",U6="挂起",U6="暂停",Y6="挂起",Y6="暂停"),"暂停","已完成") | H6: =IF(L6<>"",L6,IF(P6<>"",P6,IF(T6<>"",T6,X6))) | I6: =IF(COUNT(N6,R6,V6,Z6)=0,"",MIN(N6,R6,V6,Z6)) | J6: =IF(ISNUMBER(K6),K6,IF(COUNT(O6,S6,W6,AA6)=0,"",MAX(O6,S6,W6,AA6))) | K6: / | L6: 郑士旺 | M6: 已完成 | N6: 46202 | O6: 46206 | P6: 石军磊、刘凯 | Q6: 已完成 | R6: 46209 | S6: 46225 | T6: 贺航 | U6: 已完成 | V6: 46209 | W6: 46225 | X6: 袁丽荣 | Y6: 已完成 | Z6: 46216 | AA6: 46234 | AB6: =(IF(M6="已完成",1,IF(M6="进行中",0.5,0))*15%+IF(Q6="已完成",1,IF(Q6="进行中",0.5,0))*35%+IF(U6="已完成",1,IF(U6="进行中",0.5,0))*30%+IF(Y6="已完成",1,IF(Y6="进行中",0.5,0))*20%) | AC6: =IF(G6="已完成","正常",IF(OR(G6="暂停",G6="挂起"),"暂停",IF(J6="","日期缺失",IF(J6<'项目驾驶舱'!$B$3,"已延期",IF(J6<='项目驾驶舱'!$B$3+7,"临近到期","正常")))))
A7: T004 | B7: 基础数据 | C7: 车辆信息维护 | D7: 查询展示车辆信息 | E7: / | F7: 第一批次 | G7: =IF(OR(M7="挂起",M7="暂停",Q7="挂起",Q7="暂停",U7="挂起",U7="暂停",Y7="挂起",Y7="暂停"),"暂停","已完成") | H7: =IF(L7<>"",L7,IF(P7<>"",P7,IF(T7<>"",T7,X7))) | I7: =IF(COUNT(N7,R7,V7,Z7)=0,"",MIN(N7,R7,V7,Z7)) | J7: =IF(ISNUMBER(K7),K7,IF(COUNT(O7,S7,W7,AA7)=0,"",MAX(O7,S7,W7,AA7))) | K7: / | L7: 郑士旺 | M7: 已完成 | N7: 46202 | O7: 46206 | P7: 石军磊、刘凯 | Q7: 已完成 | R7: 46209 | S7: 46225 | T7: 贺航 | U7: 已完成 | V7: 46209 | W7: 46225 | X7: 袁丽荣 | Y7: 已完成 | Z7: 46216 | AA7: 46234 | AB7: =(IF(M7="已完成",1,IF(M7="进行中",0.5,0))*15%+IF(Q7="已完成",1,IF(Q7="进行中",0.5,0))*35%+IF(U7="已完成",1,IF(U7="进行中",0.5,0))*30%+IF(Y7="已完成",1,IF(Y7="进行中",0.5,0))*20%) | AC7: =IF(G7="已完成","正常",IF(OR(G7="暂停",G7="挂起"),"暂停",IF(J7="","日期缺失",IF(J7<'项目驾驶舱'!$B$3,"已延期",IF(J7<='项目驾驶舱'!$B$3+7,"临近到期","正常")))))
A8: T005 | B8: 基础数据 | C8: 船舶信息维护 | D8: 船舶唯一性校验 | E8: / | F8: 第二批次 | G8: =IF(OR(M8="挂起",M8="暂停",Q8="挂起",Q8="暂停",U8="挂起",U8="暂停",Y8="挂起",Y8="暂停"),"暂停","已完成") | H8: =IF(L8<>"",L8,IF(P8<>"",P8,IF(T8<>"",T8,X8))) | I8: =IF(COUNT(N8,R8,V8,Z8)=0,"",MIN(N8,R8,V8,Z8)) | J8: =IF(ISNUMBER(K8),K8,IF(COUNT(O8,S8,W8,AA8)=0,"",MAX(O8,S8,W8,AA8))) | K8: / | L8: 郑士旺 | M8: 已完成 | N8: 46230 | O8: 46241 | P8: 石军磊、刘凯 | Q8: 已完成 | R8: 46307 | S8: 46339 | T8: 贺航 | U8: 已完成 | V8: 46307 | W8: 46339 | X8: 袁丽荣 | Y8: 已完成 | Z8: 46342 | AA8: 46353 | AB8: =(IF(M8="已完成",1,IF(M8="进行中",0.5,0))*15%+IF(Q8="已完成",1,IF(Q8="进行中",0.5,0))*35%+IF(U8="已完成",1,IF(U8="进行中",0.5,0))*30%+IF(Y8="已完成",1,IF(Y8="进行中",0.5,0))*20%) | AC8: =IF(G8="已完成","正常",IF(OR(G8="暂停",G8="挂起"),"暂停",IF(J8="","日期缺失",IF(J8<'项目驾驶舱'!$B$3,"已延期",IF(J8<='项目驾驶舱'!$B$3+7,"临近到期","正常")))))
A9: T006 | B9: 基础数据 | C9: 收费标准信息维护 | D9: 优化收费标准（装卸费）新增 | E9: / | F9: 第一批次 | G9: =IF(OR(M9="挂起",M9="暂停",Q9="挂起",Q9="暂停",U9="挂起",U9="暂停",Y9="挂起",Y9="暂停"),"暂停","已完成") | H9: =IF(L9<>"",L9,IF(P9<>"",P9,IF(T9<>"",T9,X9))) | I9: =IF(COUNT(N9,R9,V9,Z9)=0,"",MIN(N9,R9,V9,Z9)) | J9: =IF(ISNUMBER(K9),K9,IF(COUNT(O9,S9,W9,AA9)=0,"",MAX(O9,S9,W9,AA9))) | K9: 46224 | L9: 郑士旺 | M9: 已完成 | N9: 46202 | O9: 46206 | P9: 石军磊、刘凯 | Q9: 已完成 | R9: 46209 | S9: 46227 | T9: 贺航 | U9: 已完成 | V9: 46209 | W9: 46227 | X9: 袁丽荣 | Y9: 已完成 | Z9: 46216 | AA9: 46234 | AB9: =(IF(M9="已完成",1,IF(M9="进行中",0.5,0))*15%+IF(Q9="已完成",1,IF(Q9="进行中",0.5,0))*35%+IF(U9="已完成",1,IF(U9="进行中",0.5,0))*30%+IF(Y9="已完成",1,IF(Y9="进行中",0.5,0))*20%) | AC9: =IF(G9="已完成","正常",IF(OR(G9="暂停",G9="挂起"),"暂停",IF(J9="","日期缺失",IF(J9<'项目驾驶舱'!$B$3,"已延期",IF(J9<='项目驾驶舱'!$B$3+7,"临近到期","正常")))))
A10: T007 | B10: 基础数据 | C10: 收费标准信息维护 | D10: 优化收费标准（装卸费）编辑 | E10: / | F10: 第一批次 | G10: =IF(OR(M10="挂起",M10="暂停",Q10="挂起",Q10="暂停",U10="挂起",U10="暂停",Y10="挂起",Y10="暂停"),"暂停","已完成") | H10: =IF(L10<>"",L10,IF(P10<>"",P10,IF(T10<>"",T10,X10))) | I10: =IF(COUNT(N10,R10,V10,Z10)=0,"",MIN(N10,R10,V10,Z10)) | J10: =IF(ISNUMBER(K10),K10,IF(COUNT(O10,S10,W10,AA10)=0,"",MAX(O10,S10,W10,AA10))) | K10: 46224 | L10: 郑士旺 | M10: 已完成 | N10: 46202 | O10: 46206 | P10: 石军磊、刘凯 | Q10: 已完成 | R10: 46209 | S10: 46227 | T10: 贺航 | U10: 已完成 | V10: 46209 | W10: 46227 | X10: 袁丽荣 | Y10: 已完成 | Z10: 46216 | AA10: 46234 | AB10: =(IF(M10="已完成",1,IF(M10="进行中",0.5,0))*15%+IF(Q10="已完成",1,IF(Q10="进行中",0.5,0))*35%+IF(U10="已完成",1,IF(U10="进行中",0.5,0))*30%+IF(Y10="已完成",1,IF(Y10="进行中",0.5,0))*20%) | AC10: =IF(G10="已完成","正常",IF(OR(G10="暂停",G10="挂起"),"暂停",IF(J10="","日期缺失",IF(J10<'项目驾驶舱'!$B$3,"已延期",IF(J10<='项目驾驶舱'!$B$3+7,"临近到期","正常")))))
A11: T008 | B11: 基础数据 | C11: 收费标准信息维护 | D11: 优化收费标准（装卸费）详情 | E11: / | F11: 第一批次 | G11: =IF(OR(M11="挂起",M11="暂停",Q11="挂起",Q11="暂停",U11="挂起",U11="暂停",Y11="挂起",Y11="暂停"),"暂停","已完成") | H11: =IF(L11<>"",L11,IF(P11<>"",P11,IF(T11<>"",T11,X11))) | I11: =IF(COUNT(N11,R11,V11,Z11)=0,"",MIN(N11,R11,V11,Z11)) | J11: =IF(ISNUMBER(K11),K11,IF(COUNT(O11,S11,W11,AA11)=0,"",MAX(O11,S11,W11,AA11))) | K11: 46224 | L11: 郑士旺 | M11: 已完成 | N11: 46202 | O11: 46206 | P11: 石军磊、刘凯 | Q11: 已完成 | R11: 46209 | S11: 46227 | T11: 贺航 | U11: 已完成 | V11: 46209 | W11: 46227 | X11: 袁丽荣 | Y11: 已完成 | Z11: 46216 | AA11: 46234 | AB11: =(IF(M11="已完成",1,IF(M11="进行中",0.5,0))*15%+IF(Q11="已完成",1,IF(Q11="进行中",0.5,0))*35%+IF(U11="已完成",1,IF(U11="进行中",0.5,0))*30%+IF(Y11="已完成",1,IF(Y11="进行中",0.5,0))*20%) | AC11: =IF(G11="已完成","正常",IF(OR(G11="暂停",G11="挂起"),"暂停",IF(J11="","日期缺失",IF(J11<'项目驾驶舱'!$B$3,"已延期",IF(J11<='项目驾驶舱'!$B$3+7,"临近到期","正常")))))
A12: T009 | B12: 基础数据 | C12: 采样方式信息维护 | D12: 优化采样方式新增 | E12: / | F12: 第一批次 | G12: =IF(OR(M12="挂起",M12="暂停",Q12="挂起",Q12="暂停",U12="挂起",U12="暂停",Y12="挂起",Y12="暂停"),"暂停","已完成") | H12: =IF(L12<>"",L12,IF(P12<>"",P12,IF(T12<>"",T12,X12))) | I12: =IF(COUNT(N12,R12,V12,Z12)=0,"",MIN(N12,R12,V12,Z12)) | J12: =IF(ISNUMBER(K12),K12,IF(COUNT(O12,S12,W12,AA12)=0,"",MAX(O12,S12,W12,AA12))) | K12: 46224 | L12: 郑士旺 | M12: 已完成 | N12: 46202 | O12: 46206 | P12: 石军磊、刘凯 | Q12: 已完成 | R12: 46209 | S12: 46227 | T12: 贺航 | U12: 已完成 | V12: 46209 | W12: 46227 | X12: 袁丽荣 | Y12: 已完成 | Z12: 46216 | AA12: 46234 | AB12: =(IF(M12="已完成",1,IF(M12="进行中",0.5,0))*15%+IF(Q12="已完成",1,IF(Q12="进行中",0.5,0))*35%+IF(U12="已完成",1,IF(U12="进行中",0.5,0))*30%+IF(Y12="已完成",1,IF(Y12="进行中",0.5,0))*20%) | AC12: =IF(G12="已完成","正常",IF(OR(G12="暂停",G12="挂起"),"暂停",IF(J12="","日期缺失",IF(J12<'项目驾驶舱'!$B$3,"已延期",IF(J12<='项目驾驶舱'!$B$3+7,"临近到期","正常")))))
A13: T010 | B13: 基础数据 | C13: 采样方式信息维护 | D13: 优化采样方式编辑 | E13: / | F13: 第一批次 | G13: =IF(OR(M13="挂起",M13="暂停",Q13="挂起",Q13="暂停",U13="挂起",U13="暂停",Y13="挂起",Y13="暂停"),"暂停","已完成") | H13: =IF(L13<>"",L13,IF(P13<>"",P13,IF(T13<>"",T13,X13))) | I13: =IF(COUNT(N13,R13,V13,Z13)=0,"",MIN(N13,R13,V13,Z13)) | J13: =IF(ISNUMBER(K13),K13,IF(COUNT(O13,S13,W13,AA13)=0,"",MAX(O13,S13,W13,AA13))) | K13: 46224 | L13: 郑士旺 | M13: 已完成 | N13: 46202 | O13: 46206 | P13: 石军磊、刘凯 | Q13: 已完成 | R13: 46209 | S13: 46227 | T13: 贺航 | U13: 已完成 | V13: 46209 | W13: 46227 | X13: 袁丽荣 | Y13: 已完成 | Z13: 46216 | AA13: 46234 | AB13: =(IF(M13="已完成",1,IF(M13="进行中",0.5,0))*15%+IF(Q13="已完成",1,IF(Q13="进行中",0.5,0))*35%+IF(U13="已完成",1,IF(U13="进行中",0.5,0))*30%+IF(Y13="已完成",1,IF(Y13="进行中",0.5,0))*20%) | AC13: =IF(G13="已完成","正常",IF(OR(G13="暂停",G13="挂起"),"暂停",IF(J13="","日期缺失",IF(J13<'项目驾驶舱'!$B$3,"已延期",IF(J13<='项目驾驶舱'!$B$3+7,"临近到期","正常")))))
A14: T011 | B14: 网上营业厅 | C14: 交易中心报单信息展示及应单入口 | D14: 获取报单数据及展示 | E14: / | F14: 第一批次 | G14: =IF(OR(M14="挂起",M14="暂停",Q14="挂起",Q14="暂停",U14="挂起",U14="暂停",Y14="挂起",Y14="暂停"),"暂停","已完成") | H14: =IF(L14<>"",L14,IF(P14<>"",P14,IF(T14<>"",T14,X14))) | I14: =IF(COUNT(N14,R14,V14,Z14)=0,"",MIN(N14,R14,V14,Z14)) | J14: =IF(ISNUMBER(K14),K14,IF(COUNT(O14,S14,W14,AA14)=0,"",MAX(O14,S14,W14,AA14))) | K14: 46224 | L14: 郑士旺 | M14: 已完成 | N14: 46202 | O14: 46206 | P14: 石军磊、刘凯 | Q14: 已完成 | R14: 46209 | S14: 46227 | T14: 贺航 | U14: 已完成 | V14: 46209 | W14: 46225 | X14: 袁丽荣 | Y14: 已完成 | Z14: 46216 | AA14: 46234 | AB14: =(IF(M14="已完成",1,IF(M14="进行中",0.5,0))*15%+IF(Q14="已完成",1,IF(Q14="进行中",0.5,0))*35%+IF(U14="已完成",1,IF(U14="进行中",0.5,0))*30%+IF(Y14="已完成",1,IF(Y14="进行中",0.5,0))*20%) | AC14: =IF(G14="已完成","正常",IF(OR(G14="暂停",G14="挂起"),"暂停",IF(J14="","日期缺失",IF(J14<'项目驾驶舱'!$B$3,"已延期",IF(J14<='项目驾驶舱'!$B$3+7,"临近到期","正常")))))
A15: T012 | B15: 网上营业厅 | C15: 交易中心报单信息展示及应单入口 | D15: 应单入口 | E15: / | F15: 第一批次 | G15: =IF(OR(M15="挂起",M15="暂停",Q15="挂起",Q15="暂停",U15="挂起",U15="暂停",Y15="挂起",Y15="暂停"),"暂停","已完成") | H15: =IF(L15<>"",L15,IF(P15<>"",P15,IF(T15<>"",T15,X15))) | I15: =IF(COUNT(N15,R15,V15,Z15)=0,"",MIN(N15,R15,V15,Z15)) | J15: =IF(ISNUMBER(K15),K15,IF(COUNT(O15,S15,W15,AA15)=0,"",MAX(O15,S15,W15,AA15))) | K15: 46224 | L15: 郑士旺 | M15: 已完成 | N15: 46202 | O15: 46206 | P15: 石军磊、刘凯 | Q15: 已完成 | R15: 46209 | S15: 46227 | T15: 贺航 | U15: 已完成 | V15: 46209 | W15: 46225 | X15: 袁丽荣 | Y15: 已完成 | Z15: 46216 | AA15: 46234 | AB15: =(IF(M15="已完成",1,IF(M15="进行中",0.5,0))*15%+IF(Q15="已完成",1,IF(Q15="进行中",0.5,0))*35%+IF(U15="已完成",1,IF(U15="进行中",0.5,0))*30%+IF(Y15="已完成",1,IF(Y15="进行中",0.5,0))*20%) | AC15: =IF(G15="已完成","正常",IF(OR(G15="暂停",G15="挂起"),"暂停",IF(J15="","日期缺失",IF(J15<'项目驾驶舱'!$B$3,"已延期",IF(J15<='项目驾驶舱'!$B$3+7,"临近到期","正常")))))
A16: T013 | B16: 网上营业厅 | C16: 结算条款管理 | D16: 新增结算条款 | E16: / | F16: 第二批次 | G16: =IF(OR(M16="挂起",M16="暂停",Q16="挂起",Q16="暂停",U16="挂起",U16="暂停",Y16="挂起",Y16="暂停"),"暂停","未开始") | H16: =IF(L16<>"",L16,IF(P16<>"",P16,IF(T16<>"",T16,X16))) | I16: =IF(COUNT(N16,R16,V16,Z16)=0,"",MIN(N16,R16,V16,Z16)) | J16: =IF(ISNUMBER(K16),K16,IF(COUNT(O16,S16,W16,AA16)=0,"",MAX(O16,S16,W16,AA16))) | L16: 郑士旺 | M16: 未开始 | N16: 46223 | O16: 46227 | P16: 石军磊、刘凯 | Q16: 未开始 | R16: 46272 | S16: 46304 | T16: 贺航 | U16: 未开始 | V16: 46272 | W16: 46304 | X16: 袁丽荣 | Y16: 未开始 | Z16: 46307 | AA16: 46318 | AB16: =(IF(M16="已完成",1,IF(M16="进行中",0.5,0))*15%+IF(Q16="已完成",1,IF(Q16="进行中",0.5,0))*35%+IF(U16="已完成",1,IF(U16="进行中",0.5,0))*30%+IF(Y16="已完成",1,IF(Y16="进行中",0.5,0))*20%) | AC16: =IF(G16="已完成","正常",IF(OR(G16="暂停",G16="挂起"),"暂停",IF(J16="","日期缺失",IF(J16<'项目驾驶舱'!$B$3,"已延期",IF(J16<='项目驾驶舱'!$B$3+7,"临近到期","正常")))))
A17: T014 | B17: 网上营业厅 | C17: 结算条款管理 | D17: 结算条款审批 | E17: / | F17: 第二批次 | G17: =IF(OR(M17="挂起",M17="暂停",Q17="挂起",Q17="暂停",U17="挂起",U17="暂停",Y17="挂起",Y17="暂停"),"暂停","未开始") | H17: =IF(L17<>"",L17,IF(P17<>"",P17,IF(T17<>"",T17,X17))) | I17: =IF(COUNT(N17,R17,V17,Z17)=0,"",MIN(N17,R17,V17,Z17)) | J17: =IF(ISNUMBER(K17),K17,IF(COUNT(O17,S17,W17,AA17)=0,"",MAX(O17,S17,W17,AA17))) | L17: 郑士旺 | M17: 未开始 | N17: 46223 | O17: 46227 | P17: 石军磊、刘凯 | Q17: 未开始 | R17: 46272 | S17: 46304 | T17: 贺航 | U17: 未开始 | V17: 46272 | W17: 46304 | X17: 袁丽荣 | Y17: 未开始 | Z17: 46307 | AA17: 46318 | AB17: =(IF(M17="已完成",1,IF(M17="进行中",0.5,0))*15%+IF(Q17="已完成",1,IF(Q17="进行中",0.5,0))*35%+IF(U17="已完成",1,IF(U17="进行中",0.5,0))*30%+IF(Y17="已完成",1,IF(Y17="进行中",0.5,0))*20%) | AC17: =IF(G17="已完成","正常",IF(OR(G17="暂停",G17="挂起"),"暂停",IF(J17="","日期缺失",IF(J17<'项目驾驶舱'!$B$3,"已延期",IF(J17<='项目驾驶舱'!$B$3+7,"临近到期","正常")))))
A18: T015 | B18: 网上营业厅 | C18: 结算条款管理 | D18: 修改结算条款 | E18: / | F18: 第二批次 | G18: =IF(OR(M18="挂起",M18="暂停",Q18="挂起",Q18="暂停",U18="挂起",U18="暂停",Y18="挂起",Y18="暂停"),"暂停","未开始") | H18: =IF(L18<>"",L18,IF(P18<>"",P18,IF(T18<>"",T18,X18))) | I18: =IF(COUNT(N18,R18,V18,Z18)=0,"",MIN(N18,R18,V18,Z18)) | J18: =IF(ISNUMBER(K18),K18,IF(COUNT(O18,S18,W18,AA18)=0,"",MAX(O18,S18,W18,AA18))) | L18: 郑士旺 | M18: 未开始 | N18: 46223 | O18: 46227 | P18: 石军磊、刘凯 | Q18: 未开始 | R18: 46272 | S18: 46304 | T18: 贺航 | U18: 未开始 | V18: 46272 | W18: 46304 | X18: 袁丽荣 | Y18: 未开始 | Z18: 46307 | AA18: 46318 | AB18: =(IF(M18="已完成",1,IF(M18="进行中",0.5,0))*15%+IF(Q18="已完成",1,IF(Q18="进行中",0.5,0))*35%+IF(U18="已完成",1,IF(U18="进行中",0.5,0))*30%+IF(Y18="已完成",1,IF(Y18="进行中",0.5,0))*20%) | AC18: =IF(G18="已完成","正常",IF(OR(G18="暂停",G18="挂起"),"暂停",IF(J18="","日期缺失",IF(J18<'项目驾驶舱'!$B$3,"已延期",IF(J18<='项目驾驶舱'!$B$3+7,"临近到期","正常")))))
A19: T016 | B19: 网上营业厅 | C19: 结算条款管理 | D19: 删除结算条款 | E19: / | F19: 第二批次 | G19: =IF(OR(M19="挂起",M19="暂停",Q19="挂起",Q19="暂停",U19="挂起",U19="暂停",Y19="挂起",Y19="暂停"),"暂停","未开始") | H19: =IF(L19<>"",L19,IF(P19<>"",P19,IF(T19<>"",T19,X19))) | I19: =IF(COUNT(N19,R19,V19,Z19)=0,"",MIN(N19,R19,V19,Z19)) | J19: =IF(ISNUMBER(K19),K19,IF(COUNT(O19,S19,W19,AA19)=0,"",MAX(O19,S19,W19,AA19))) | L19: 郑士旺 | M19: 未开始 | N19: 46223 | O19: 46227 | P19: 石军磊、刘凯 | Q19: 未开始 | R19: 46272 | S19: 46304 | T19: 贺航 | U19: 未开始 | V19: 46272 | W19: 46304 | X19: 袁丽荣 | Y19: 未开始 | Z19: 46307 | AA19: 46318 | AB19: =(IF(M19="已完成",1,IF(M19="进行中",0.5,0))*15%+IF(Q19="已完成",1,IF(Q19="进行中",0.5,0))*35%+IF(U19="已完成",1,IF(U19="进行中",0.5,0))*30%+IF(Y19="已完成",1,IF(Y19="进行中",0.5,0))*20%) | AC19: =IF(G19="已完成","正常",IF(OR(G19="暂停",G19="挂起"),"暂停",IF(J19="","日期缺失",IF(J19<'项目驾驶舱'!$B$3,"已延期",IF(J19<='项目驾驶舱'!$B$3+7,"临近到期","正常")))))
A20: T017 | B20: 网上营业厅 | C20: 结算条款管理 | D20: 查询展示结算条款 | E20: / | F20: 第二批次 | G20: =IF(OR(M20="挂起",M20="暂停",Q20="挂起",Q20="暂停",U20="挂起",U20="暂停",Y20="挂起",Y20="暂停"),"暂停","未开始") | H20: =IF(L20<>"",L20,IF(P20<>"",P20,IF(T20<>"",T20,X20))) | I20: =IF(COUNT(N20,R20,V20,Z20)=0,"",MIN(N20,R20,V20,Z20)) | J20: =IF(ISNUMBER(K20),K20,IF(COUNT(O20,S20,W20,AA20)=0,"",MAX(O20,S20,W20,AA20))) | L20: 郑士旺 | M20: 未开始 | N20: 46223 | O20: 46227 | P20: 石军磊、刘凯 | Q20: 未开始 | R20: 46272 | S20: 46304 | T20: 贺航 | U20: 未开始 | V20: 46272 | W20: 46304 | X20: 袁丽荣 | Y20: 未开始 | Z20: 46307 | AA20: 46318 | AB20: =(IF(M20="已完成",1,IF(M20="进行中",0.5,0))*15%+IF(Q20="已完成",1,IF(Q20="进行中",0.5,0))*35%+IF(U20="已完成",1,IF(U20="进行中",0.5,0))*30%+IF(Y20="已完成",1,IF(Y20="进行中",0.5,0))*20%) | AC20: =IF(G20="已完成","正常",IF(OR(G20="暂停",G20="挂起"),"暂停",IF(J20="","日期缺失",IF(J20<'项目驾驶舱'!$B$3,"已延期",IF(J20<='项目驾驶舱'!$B$3+7,"临近到期","正常")))))
A21: T018 | B21: 网上营业厅 | C21: 结算条款管理 | D21: 结算条款推送法务系统 | E21: / | F21: 第二批次 | G21: =IF(OR(M21="挂起",M21="暂停",Q21="挂起",Q21="暂停",U21="挂起",U21="暂停",Y21="挂起",Y21="暂停"),"暂停","未开始") | H21: =IF(L21<>"",L21,IF(P21<>"",P21,IF(T21<>"",T21,X21))) | I21: =IF(COUNT(N21,R21,V21,Z21)=0,"",MIN(N21,R21,V21,Z21)) | J21: =IF(ISNUMBER(K21),K21,IF(COUNT(O21,S21,W21,AA21)=0,"",MAX(O21,S21,W21,AA21))) | L21: 郑士旺 | M21: 未开始 | N21: 46223 | O21: 46227 | P21: 石军磊、刘凯 | Q21: 未开始 | R21: 46272 | S21: 46304 | T21: 贺航 | U21: 未开始 | V21: 46272 | W21: 46304 | X21: 袁丽荣 | Y21: 未开始 | Z21: 46307 | AA21: 46318 | AB21: =(IF(M21="已完成",1,IF(M21="进行中",0.5,0))*15%+IF(Q21="已完成",1,IF(Q21="进行中",0.5,0))*35%+IF(U21="已完成",1,IF(U21="进行中",0.5,0))*30%+IF(Y21="已完成",1,IF(Y21="进行中",0.5,0))*20%) | AC21: =IF(G21="已完成","正常",IF(OR(G21="暂停",G21="挂起"),"暂停",IF(J21="","日期缺失",IF(J21<'项目驾驶舱'!$B$3,"已延期",IF(J21<='项目驾驶舱'!$B$3+7,"临近到期","正常")))))
A22: T019 | B22: 网上营业厅 | C22: 卸船作业 | D22: 卸船计划 | E22: 对接卸船计划 | F22: 第二批次 | G22: =IF(OR(M22="挂起",M22="暂停",Q22="挂起",Q22="暂停",U22="挂起",U22="暂停",Y22="挂起",Y22="暂停"),"暂停","进行中") | H22: =IF(L22<>"",L22,IF(P22<>"",P22,IF(T22<>"",T22,X22))) | I22: =IF(COUNT(N22,R22,V22,Z22)=0,"",MIN(N22,R22,V22,Z22)) | J22: =IF(ISNUMBER(K22),K22,IF(COUNT(O22,S22,W22,AA22)=0,"",MAX(O22,S22,W22,AA22))) | L22: 郑士旺 | M22: 已完成 | N22: 46230 | O22: 46241 | P22: 石军磊、刘凯 | Q22: 未开始 | R22: 46307 | S22: 46339 | T22: 贺航 | U22: 未开始 | V22: 46307 | W22: 46339 | X22: 袁丽荣 | Y22: 未开始 | Z22: 46342 | AA22: 46353 | AB22: =(IF(M22="已完成",1,IF(M22="进行中",0.5,0))*15%+IF(Q22="已完成",1,IF(Q22="进行中",0.5,0))*35%+IF(U22="已完成",1,IF(U22="进行中",0.5,0))*30%+IF(Y22="已完成",1,IF(Y22="进行中",0.5,0))*20%) | AC22: =IF(G22="已完成","正常",IF(OR(G22="暂停",G22="挂起"),"暂停",IF(J22="","日期缺失",IF(J22<'项目驾驶舱'!$B$3,"已延期",IF(J22<='项目驾驶舱'!$B$3+7,"临近到期","正常")))))
A23: T020 | B23: 网上营业厅 | C23: 卸船作业 | D23: 卸船计划 | E23: 查询卸车计划 | F23: 第二批次 | G23: =IF(OR(M23="挂起",M23="暂停",Q23="挂起",Q23="暂停",U23="挂起",U23="暂停",Y23="挂起",Y23="暂停"),"暂停","进行中") | H23: =IF(L23<>"",L23,IF(P23<>"",P23,IF(T23<>"",T23,X23))) | I23: =IF(COUNT(N23,R23,V23,Z23)=0,"",MIN(N23,R23,V23,Z23)) | J23: =IF(ISNUMBER(K23),K23,IF(COUNT(O23,S23,W23,AA23)=0,"",MAX(O23,S23,W23,AA23))) | L23: 郑士旺 | M23: 已完成 | N23: 46230 | O23: 46241 | P23: 石军磊、刘凯 | Q23: 进行中 | R23: 46307 | S23: 46339 | T23: 贺航 | U23: 进行中 | V23: 46307 | W23: 46339 | X23: 袁丽荣 | Y23: 未开始 | Z23: 46342 | AA23: 46353 | AB23: =(IF(M23="已完成",1,IF(M23="进行中",0.5,0))*15%+IF(Q23="已完成",1,IF(Q23="进行中",0.5,0))*35%+IF(U23="已完成",1,IF(U23="进行中",0.5,0))*30%+IF(Y23="已完成",1,IF(Y23="进行中",0.5,0))*20%) | AC23: =IF(G23="已完成","正常",IF(OR(G23="暂停",G23="挂起"),"暂停",IF(J23="","日期缺失",IF(J23<'项目驾驶舱'!$B$3,"已延期",IF(J23<='项目驾驶舱'!$B$3+7,"临近到期","正常")))))
A24: T021 | B24: 网上营业厅 | C24: 卸船作业 | D24: 卸船计划 | E24: 外部客户确认 | F24: 第二批次 | G24: =IF(OR(M24="挂起",M24="暂停",Q24="挂起",Q24="暂停",U24="挂起",U24="暂停",Y24="挂起",Y24="暂停"),"暂停","进行中") | H24: =IF(L24<>"",L24,IF(P24<>"",P24,IF(T24<>"",T24,X24))) | I24: =IF(COUNT(N24,R24,V24,Z24)=0,"",MIN(N24,R24,V24,Z24)) | J24: =IF(ISNUMBER(K24),K24,IF(COUNT(O24,S24,W24,AA24)=0,"",MAX(O24,S24,W24,AA24))) | L24: 郑士旺 | M24: 已完成 | N24: 46230 | O24: 46241 | P24: 石军磊、刘凯 | Q24: 进行中 | R24: 46307 | S24: 46339 | T24: 贺航 | U24: 进行中 | V24: 46307 | W24: 46339 | X24: 袁丽荣 | Y24: 未开始 | Z24: 46342 | AA24: 46353 | AB24: =(IF(M24="已完成",1,IF(M24="进行中",0.5,0))*15%+IF(Q24="已完成",1,IF(Q24="进行中",0.5,0))*35%+IF(U24="已完成",1,IF(U24="进行中",0.5,0))*30%+IF(Y24="已完成",1,IF(Y24="进行中",0.5,0))*20%) | AC24: =IF(G24="已完成","正常",IF(OR(G24="暂停",G24="挂起"),"暂停",IF(J24="","日期缺失",IF(J24<'项目驾驶舱'!$B$3,"已延期",IF(J24<='项目驾驶舱'!$B$3+7,"临近到期","正常")))))
A25: T022 | B25: 网上营业厅 | C25: 卸船作业 | D25: 卸船作业信息管理 | E25: 对接卸船作业信息 | F25: 第二批次 | G25: =IF(OR(M25="挂起",M25="暂停",Q25="挂起",Q25="暂停",U25="挂起",U25="暂停",Y25="挂起",Y25="暂停"),"暂停","未开始") | H25: =IF(L25<>"",L25,IF(P25<>"",P25,IF(T25<>"",T25,X25))) | I25: =IF(COUNT(N25,R25,V25,Z25)=0,"",MIN(N25,R25,V25,Z25)) | J25: =IF(ISNUMBER(K25),K25,IF(COUNT(O25,S25,W25,AA25)=0,"",MAX(O25,S25,W25,AA25))) | L25: 郑士旺 | M25: 未开始 | N25: 46230 | O25: 46241 | P25: 石军磊、刘凯 | Q25: 未开始 | R25: 46307 | S25: 46339 | T25: 贺航 | U25: 未开始 | V25: 46307 | W25: 46339 | X25: 袁丽荣 | Y25: 未开始 | Z25: 46342 | AA25: 46353 | AB25: =(IF(M25="已完成",1,IF(M25="进行中",0.5,0))*15%+IF(Q25="已完成",1,IF(Q25="进行中",0.5,0))*35%+IF(U25="已完成",1,IF(U25="进行中",0.5,0))*30%+IF(Y25="已完成",1,IF(Y25="进行中",0.5,0))*20%) | AC25: =IF(G25="已完成","正常",IF(OR(G25="暂停",G25="挂起"),"暂停",IF(J25="","日期缺失",IF(J25<'项目驾驶舱'!$B$3,"已延期",IF(J25<='项目驾驶舱'!$B$3+7,"临近到期","正常")))))
A26: T023 | B26: 网上营业厅 | C26: 卸船作业 | D26: 卸船作业信息管理 | E26: 查询卸船作业信息 | F26: 第二批次 | G26: =IF(OR(M26="挂起",M26="暂停",Q26="挂起",Q26="暂停",U26="挂起",U26="暂停",Y26="挂起",Y26="暂停"),"暂停","未开始") | H26: =IF(L26<>"",L26,IF(P26<>"",P26,IF(T26<>"",T26,X26))) | I26: =IF(COUNT(N26,R26,V26,Z26)=0,"",MIN(N26,R26,V26,Z26)) | J26: =IF(ISNUMBER(K26),K26,IF(COUNT(O26,S26,W26,AA26)=0,"",MAX(O26,S26,W26,AA26))) | L26: 郑士旺 | M26: 未开始 | N26: 46230 | O26: 46241 | P26: 石军磊、刘凯 | Q26: 未开始 | R26: 46307 | S26: 46339 | T26: 贺航 | U26: 未开始 | V26: 46307 | W26: 46339 | X26: 袁丽荣 | Y26: 未开始 | Z26: 46342 | AA26: 46353 | AB26: =(IF(M26="已完成",1,IF(M26="进行中",0.5,0))*15%+IF(Q26="已完成",1,IF(Q26="进行中",0.5,0))*35%+IF(U26="已完成",1,IF(U26="进行中",0.5,0))*30%+IF(Y26="已完成",1,IF(Y26="进行中",0.5,0))*20%) | AC26: =IF(G26="已完成","正常",IF(OR(G26="暂停",G26="挂起"),"暂停",IF(J26="","日期缺失",IF(J26<'项目驾驶舱'!$B$3,"已延期",IF(J26<='项目驾驶舱'!$B$3+7,"临近到期","正常")))))
A27: T024 | B27: 网上营业厅 | C27: 卸船作业 | D27: 卸船查询 | E27: 卸船查询列表 | F27: 第二批次 | G27: =IF(OR(M27="挂起",M27="暂停",Q27="挂起",Q27="暂停",U27="挂起",U27="暂停",Y27="挂起",Y27="暂停"),"暂停","未开始") | H27: =IF(L27<>"",L27,IF(P27<>"",P27,IF(T27<>"",T27,X27))) | I27: =IF(COUNT(N27,R27,V27,Z27)=0,"",MIN(N27,R27,V27,Z27)) | J27: =IF(ISNUMBER(K27),K27,IF(COUNT(O27,S27,W27,AA27)=0,"",MAX(O27,S27,W27,AA27))) | L27: 郑士旺 | M27: 未开始 | N27: 46230 | O27: 46241 | P27: 石军磊、刘凯 | Q27: 未开始 | R27: 46307 | S27: 46339 | T27: 贺航 | U27: 未开始 | V27: 46307 | W27: 46339 | X27: 袁丽荣 | Y27: 未开始 | Z27: 46342 | AA27: 46353 | AB27: =(IF(M27="已完成",1,IF(M27="进行中",0.5,0))*15%+IF(Q27="已完成",1,IF(Q27="进行中",0.5,0))*35%+IF(U27="已完成",1,IF(U27="进行中",0.5,0))*30%+IF(Y27="已完成",1,IF(Y27="进行中",0.5,0))*20%) | AC27: =IF(G27="已完成","正常",IF(OR(G27="暂停",G27="挂起"),"暂停",IF(J27="","日期缺失",IF(J27<'项目驾驶舱'!$B$3,"已延期",IF(J27<='项目驾驶舱'!$B$3+7,"临近到期","正常")))))
A28: T025 | B28: 网上营业厅 | C28: 卸船作业 | D28: 卸船查询 | E28: 卸船查询详情 | F28: 第二批次 | G28: =IF(OR(M28="挂起",M28="暂停",Q28="挂起",Q28="暂停",U28="挂起",U28="暂停",Y28="挂起",Y28="暂停"),"暂停","未开始") | H28: =IF(L28<>"",L28,IF(P28<>"",P28,IF(T28<>"",T28,X28))) | I28: =IF(COUNT(N28,R28,V28,Z28)=0,"",MIN(N28,R28,V28,Z28)) | J28: =IF(ISNUMBER(K28),K28,IF(COUNT(O28,S28,W28,AA28)=0,"",MAX(O28,S28,W28,AA28))) | K28: 46261 | L28: 郑士旺 | M28: 未开始 | N28: 46230 | O28: 46241 | P28: 石军磊、刘凯 | Q28: 未开始 | R28: 46307 | S28: 46339 | T28: 贺航 | U28: 未开始 | V28: 46307 | W28: 46339 | X28: 袁丽荣 | Y28: 未开始 | Z28: 46342 | AA28: 46353 | AB28: =(IF(M28="已完成",1,IF(M28="进行中",0.5,0))*15%+IF(Q28="已完成",1,IF(Q28="进行中",0.5,0))*35%+IF(U28="已完成",1,IF(U28="进行中",0.5,0))*30%+IF(Y28="已完成",1,IF(Y28="进行中",0.5,0))*20%) | AC28: =IF(G28="已完成","正常",IF(OR(G28="暂停",G28="挂起"),"暂停",IF(J28="","日期缺失",IF(J28<'项目驾驶舱'!$B$3,"已延期",IF(J28<='项目驾驶舱'!$B$3+7,"临近到期","正常")))))
A29: T026 | B29: 网上营业厅 | C29: 卸船作业 | D29: 卸船作业委托 | E29: 创建卸船作业委托信息 | F29: 第二批次 | G29: =IF(OR(M29="挂起",M29="暂停",Q29="挂起",Q29="暂停",U29="挂起",U29="暂停",Y29="挂起",Y29="暂停"),"暂停","进行中") | H29: =IF(L29<>"",L29,IF(P29<>"",P29,IF(T29<>"",T29,X29))) | I29: =IF(COUNT(N29,R29,V29,Z29)=0,"",MIN(N29,R29,V29,Z29)) | J29: =IF(ISNUMBER(K29),K29,IF(COUNT(O29,S29,W29,AA29)=0,"",MAX(O29,S29,W29,AA29))) | K29: 46261 | L29: 郑士旺 | M29: 已完成 | N29: 46230 | O29: 46241 | P29: 石军磊、刘凯 | Q29: 进行中 | R29: 46307 | S29: 46339 | T29: 贺航 | U29: 进行中 | V29: 46307 | W29: 46339 | X29: 袁丽荣 | Y29: 未开始 | Z29: 46342 | AA29: 46353 | AB29: =(IF(M29="已完成",1,IF(M29="进行中",0.5,0))*15%+IF(Q29="已完成",1,IF(Q29="进行中",0.5,0))*35%+IF(U29="已完成",1,IF(U29="进行中",0.5,0))*30%+IF(Y29="已完成",1,IF(Y29="进行中",0.5,0))*20%) | AC29: =IF(G29="已完成","正常",IF(OR(G29="暂停",G29="挂起"),"暂停",IF(J29="","日期缺失",IF(J29<'项目驾驶舱'!$B$3,"已延期",IF(J29<='项目驾驶舱'!$B$3+7,"临近到期","正常")))))
A30: T027 | B30: 网上营业厅 | C30: 卸船作业 | D30: 卸船作业委托 | E30: 修改卸船作业委托信息 | F30: 第二批次 | G30: =IF(OR(M30="挂起",M30="暂停",Q30="挂起",Q30="暂停",U30="挂起",U30="暂停",Y30="挂起",Y30="暂停"),"暂停","进行中") | H30: =IF(L30<>"",L30,IF(P30<>"",P30,IF(T30<>"",T30,X30))) | I30: =IF(COUNT(N30,R30,V30,Z30)=0,"",MIN(N30,R30,V30,Z30)) | J30: =IF(ISNUMBER(K30),K30,IF(COUNT(O30,S30,W30,AA30)=0,"",MAX(O30,S30,W30,AA30))) | K30: 46261 | L30: 郑士旺 | M30: 已完成 | N30: 46230 | O30: 46241 | P30: 石军磊、刘凯 | Q30: 进行中 | R30: 46307 | S30: 46339 | T30: 贺航 | U30: 进行中 | V30: 46307 | W30: 46339 | X30: 袁丽荣 | Y30: 未开始 | Z30: 46342 | AA30: 46353 | AB30: =(IF(M30="已完成",1,IF(M30="进行中",0.5,0))*15%+IF(Q30="已完成",1,IF(Q30="进行中",0.5,0))*35%+IF(U30="已完成",1,IF(U30="进行中",0.5,0))*30%+IF(Y30="已完成",1,IF(Y30="进行中",0.5,0))*20%) | AC30: =IF(G30="已完成","正常",IF(OR(G30="暂停",G30="挂起"),"暂停",IF(J30="","日期缺失",IF(J30<'项目驾驶舱'!$B$3,"已延期",IF(J30<='项目驾驶舱'!$B$3+7,"临近到期","正常")))))
A31: T028 | B31: 网上营业厅 | C31: 卸船作业 | D31: 卸船作业委托 | E31: 作废卸船作业委托信息 | F31: 第二批次 | G31: =IF(OR(M31="挂起",M31="暂停",Q31="挂起",Q31="暂停",U31="挂起",U31="暂停",Y31="挂起",Y31="暂停"),"暂停","进行中") | H31: =IF(L31<>"",L31,IF(P31<>"",P31,IF(T31<>"",T31,X31))) | I31: =IF(COUNT(N31,R31,V31,Z31)=0,"",MIN(N31,R31,V31,Z31)) | J31: =IF(ISNUMBER(K31),K31,IF(COUNT(O31,S31,W31,AA31)=0,"",MAX(O31,S31,W31,AA31))) | K31: 46261 | L31: 郑士旺 | M31: 进行中 | N31: 46230 | O31: 46241 | P31: 石军磊、刘凯 | Q31: 未开始 | R31: 46307 | S31: 46339 | T31: 贺航 | U31: 未开始 | V31: 46307 | W31: 46339 | X31: 袁丽荣 | Y31: 未开始 | Z31: 46342 | AA31: 46353 | AB31: =(IF(M31="已完成",1,IF(M31="进行中",0.5,0))*15%+IF(Q31="已完成",1,IF(Q31="进行中",0.5,0))*35%+IF(U31="已完成",1,IF(U31="进行中",0.5,0))*30%+IF(Y31="已完成",1,IF(Y31="进行中",0.5,0))*20%) | AC31: =IF(G31="已完成","正常",IF(OR(G31="暂停",G31="挂起"),"暂停",IF(J31="","日期缺失",IF(J31<'项目驾驶舱'!$B$3,"已延期",IF(J31<='项目驾驶舱'!$B$3+7,"临近到期","正常")))))
A32: T029 | B32: 网上营业厅 | C32: 卸船作业 | D32: 卸船作业委托 | E32: 推送卸船作业委托信息 | F32: 第二批次 | G32: =IF(OR(M32="挂起",M32="暂停",Q32="挂起",Q32="暂停",U32="挂起",U32="暂停",Y32="挂起",Y32="暂停"),"暂停","进行中") | H32: =IF(L32<>"",L32,IF(P32<>"",P32,IF(T32<>"",T32,X32))) | I32: =IF(COUNT(N32,R32,V32,Z32)=0,"",MIN(N32,R32,V32,Z32)) | J32: =IF(ISNUMBER(K32),K32,IF(COUNT(O32,S32,W32,AA32)=0,"",MAX(O32,S32,W32,AA32))) | K32: 46261 | L32: 郑士旺 | M32: 进行中 | N32: 46230 | O32: 46241 | P32: 石军磊、刘凯 | Q32: 未开始 | R32: 46307 | S32: 46339 | T32: 贺航 | U32: 未开始 | V32: 46307 | W32: 46339 | X32: 袁丽荣 | Y32: 未开始 | Z32: 46342 | AA32: 46353 | AB32: =(IF(M32="已完成",1,IF(M32="进行中",0.5,0))*15%+IF(Q32="已完成",1,IF(Q32="进行中",0.5,0))*35%+IF(U32="已完成",1,IF(U32="进行中",0.5,0))*30%+IF(Y32="已完成",1,IF(Y32="进行中",0.5,0))*20%) | AC32: =IF(G32="已完成","正常",IF(OR(G32="暂停",G32="挂起"),"暂停",IF(J32="","日期缺失",IF(J32<'项目驾驶舱'!$B$3,"已延期",IF(J32<='项目驾驶舱'!$B$3+7,"临近到期","正常")))))
A33: T030 | B33: 网上营业厅 | C33: 卸船作业 | D33: 卸船作业委托 | E33: 查询卸船作业委托信息 | F33: 第二批次 | G33: =IF(OR(M33="挂起",M33="暂停",Q33="挂起",Q33="暂停",U33="挂起",U33="暂停",Y33="挂起",Y33="暂停"),"暂停","进行中") | H33: =IF(L33<>"",L33,IF(P33<>"",P33,IF(T33<>"",T33,X33))) | I33: =IF(COUNT(N33,R33,V33,Z33)=0,"",MIN(N33,R33,V33,Z33)) | J33: =IF(ISNUMBER(K33),K33,IF(COUNT(O33,S33,W33,AA33)=0,"",MAX(O33,S33,W33,AA33))) | K33: 46261 | L33: 郑士旺 | M33: 已完成 | N33: 46230 | O33: 46241 | P33: 石军磊、刘凯 | Q33: 进行中 | R33: 46307 | S33: 46339 | T33: 贺航 | U33: 进行中 | V33: 46307 | W33: 46339 | X33: 袁丽荣 | Y33: 未开始 | Z33: 46342 | AA33: 46353 | AB33: =(IF(M33="已完成",1,IF(M33="进行中",0.5,0))*15%+IF(Q33="已完成",1,IF(Q33="进行中",0.5,0))*35%+IF(U33="已完成",1,IF(U33="进行中",0.5,0))*30%+IF(Y33="已完成",1,IF(Y33="进行中",0.5,0))*20%) | AC33: =IF(G33="已完成","正常",IF(OR(G33="暂停",G33="挂起"),"暂停",IF(J33="","日期缺失",IF(J33<'项目驾驶舱'!$B$3,"已延期",IF(J33<='项目驾驶舱'!$B$3+7,"临近到期","正常")))))
A34: T031 | B34: 网上营业厅 | C34: 卸船作业 | D34: 外轮转内贸业务 | E34: 创建外轮转内贸业务信息 | F34: 第二批次 | G34: =IF(OR(M34="挂起",M34="暂停",Q34="挂起",Q34="暂停",U34="挂起",U34="暂停",Y34="挂起",Y34="暂停"),"暂停","未开始") | H34: =IF(L34<>"",L34,IF(P34<>"",P34,IF(T34<>"",T34,X34))) | I34: =IF(COUNT(N34,R34,V34,Z34)=0,"",MIN(N34,R34,V34,Z34)) | J34: =IF(ISNUMBER(K34),K34,IF(COUNT(O34,S34,W34,AA34)=0,"",MAX(O34,S34,W34,AA34))) | L34: 郑士旺 | M34: 未开始 | N34: 46230 | O34: 46241 | P34: 石军磊、刘凯 | Q34: 未开始 | R34: 46307 | S34: 46339 | T34: 贺航 | U34: 未开始 | V34: 46307 | W34: 46339 | X34: 袁丽荣 | Y34: 未开始 | Z34: 46342 | AA34: 46353 | AB34: =(IF(M34="已完成",1,IF(M34="进行中",0.5,0))*15%+IF(Q34="已完成",1,IF(Q34="进行中",0.5,0))*35%+IF(U34="已完成",1,IF(U34="进行中",0.5,0))*30%+IF(Y34="已完成",1,IF(Y34="进行中",0.5,0))*20%) | AC34: =IF(G34="已完成","正常",IF(OR(G34="暂停",G34="挂起"),"暂停",IF(J34="","日期缺失",IF(J34<'项目驾驶舱'!$B$3,"已延期",IF(J34<='项目驾驶舱'!$B$3+7,"临近到期","正常")))))
A35: T032 | B35: 网上营业厅 | C35: 卸船作业 | D35: 外轮转内贸业务 | E35: 作废外轮转内贸业务信息 | F35: 第二批次 | G35: =IF(OR(M35="挂起",M35="暂停",Q35="挂起",Q35="暂停",U35="挂起",U35="暂停",Y35="挂起",Y35="暂停"),"暂停","未开始") | H35: =IF(L35<>"",L35,IF(P35<>"",P35,IF(T35<>"",T35,X35))) | I35: =IF(COUNT(N35,R35,V35,Z35)=0,"",MIN(N35,R35,V35,Z35)) | J35: =IF(ISNUMBER(K35),K35,IF(COUNT(O35,S35,W35,AA35)=0,"",MAX(O35,S35,W35,AA35))) | L35: 郑士旺 | M35: 未开始 | N35: 46230 | O35: 46241 | P35: 石军磊、刘凯 | Q35: 未开始 | R35: 46307 | S35: 46339 | T35: 贺航 | U35: 未开始 | V35: 46307 | W35: 46339 | X35: 袁丽荣 | Y35: 未开始 | Z35: 46342 | AA35: 46353 | AB35: =(IF(M35="已完成",1,IF(M35="进行中",0.5,0))*15%+IF(Q35="已完成",1,IF(Q35="进行中",0.5,0))*35%+IF(U35="已完成",1,IF(U35="进行中",0.5,0))*30%+IF(Y35="已完成",1,IF(Y35="进行中",0.5,0))*20%) | AC35: =IF(G35="已完成","正常",IF(OR(G35="暂停",G35="挂起"),"暂停",IF(J35="","日期缺失",IF(J35<'项目驾驶舱'!$B$3,"已延期",IF(J35<='项目驾驶舱'!$B$3+7,"临近到期","正常")))))
A36: T033 | B36: 网上营业厅 | C36: 卸船作业 | D36: 外轮转内贸业务 | E36: 查询外轮转内贸业务信息 | F36: 第二批次 | G36: =IF(OR(M36="挂起",M36="暂停",Q36="挂起",Q36="暂停",U36="挂起",U36="暂停",Y36="挂起",Y36="暂停"),"暂停","未开始") | H36: =IF(L36<>"",L36,IF(P36<>"",P36,IF(T36<>"",T36,X36))) | I36: =IF(COUNT(N36,R36,V36,Z36)=0,"",MIN(N36,R36,V36,Z36)) | J36: =IF(ISNUMBER(K36),K36,IF(COUNT(O36,S36,W36,AA36)=0,"",MAX(O36,S36,W36,AA36))) | L36: 郑士旺 | M36: 未开始 | N36: 46230 | O36: 46241 | P36: 石军磊、刘凯 | Q36: 未开始 | R36: 46307 | S36: 46339 | T36: 贺航 | U36: 未开始 | V36: 46307 | W36: 46339 | X36: 袁丽荣 | Y36: 未开始 | Z36: 46342 | AA36: 46353 | AB36: =(IF(M36="已完成",1,IF(M36="进行中",0.5,0))*15%+IF(Q36="已完成",1,IF(Q36="进行中",0.5,0))*35%+IF(U36="已完成",1,IF(U36="进行中",0.5,0))*30%+IF(Y36="已完成",1,IF(Y36="进行中",0.5,0))*20%) | AC36: =IF(G36="已完成","正常",IF(OR(G36="暂停",G36="挂起"),"暂停",IF(J36="","日期缺失",IF(J36<'项目驾驶舱'!$B$3,"已延期",IF(J36<='项目驾驶舱'!$B$3+7,"临近到期","正常")))))
A37: T034 | B37: 网上营业厅 | C37: 卸船作业 | D37: 船舶靠泊通知单 | E37: 新增船舶靠泊通知单 | F37: 第二批次 | G37: =IF(OR(M37="挂起",M37="暂停",Q37="挂起",Q37="暂停",U37="挂起",U37="暂停",Y37="挂起",Y37="暂停"),"暂停","进行中") | H37: =IF(L37<>"",L37,IF(P37<>"",P37,IF(T37<>"",T37,X37))) | I37: =IF(COUNT(N37,R37,V37,Z37)=0,"",MIN(N37,R37,V37,Z37)) | J37: =IF(ISNUMBER(K37),K37,IF(COUNT(O37,S37,W37,AA37)=0,"",MAX(O37,S37,W37,AA37))) | L37: 郑士旺 | M37: 已完成 | N37: 46230 | O37: 46241 | P37: 石军磊、刘凯 | Q37: 进行中 | R37: 46307 | S37: 46339 | T37: 贺航 | U37: 进行中 | V37: 46307 | W37: 46339 | X37: 袁丽荣 | Y37: 未开始 | Z37: 46342 | AA37: 46353 | AB37: =(IF(M37="已完成",1,IF(M37="进行中",0.5,0))*15%+IF(Q37="已完成",1,IF(Q37="进行中",0.5,0))*35%+IF(U37="已完成",1,IF(U37="进行中",0.5,0))*30%+IF(Y37="已完成",1,IF(Y37="进行中",0.5,0))*20%) | AC37: =IF(G37="已完成","正常",IF(OR(G37="暂停",G37="挂起"),"暂停",IF(J37="","日期缺失",IF(J37<'项目驾驶舱'!$B$3,"已延期",IF(J37<='项目驾驶舱'!$B$3+7,"临近到期","正常")))))
A38: T035 | B38: 网上营业厅 | C38: 卸船作业 | D38: 船舶靠泊通知单 | E38: 审批船舶靠泊通知单 | F38: 第二批次 | G38: =IF(OR(M38="挂起",M38="暂停",Q38="挂起",Q38="暂停",U38="挂起",U38="暂停",Y38="挂起",Y38="暂停"),"暂停","进行中") | H38: =IF(L38<>"",L38,IF(P38<>"",P38,IF(T38<>"",T38,X38))) | I38: =IF(COUNT(N38,R38,V38,Z38)=0,"",MIN(N38,R38,V38,Z38)) | J38: =IF(ISNUMBER(K38),K38,IF(COUNT(O38,S38,W38,AA38)=0,"",MAX(O38,S38,W38,AA38))) | L38: 郑士旺 | M38: 已完成 | N38: 46230 | O38: 46241 | P38: 石军磊、刘凯 | Q38: 进行中 | R38: 46307 | S38: 46339 | T38: 贺航 | U38: 进行中 | V38: 46307 | W38: 46339 | X38: 袁丽荣 | Y38: 未开始 | Z38: 46342 | AA38: 46353 | AB38: =(IF(M38="已完成",1,IF(M38="进行中",0.5,0))*15%+IF(Q38="已完成",1,IF(Q38="进行中",0.5,0))*35%+IF(U38="已完成",1,IF(U38="进行中",0.5,0))*30%+IF(Y38="已完成",1,IF(Y38="进行中",0.5,0))*20%) | AC38: =IF(G38="已完成","正常",IF(OR(G38="暂停",G38="挂起"),"暂停",IF(J38="","日期缺失",IF(J38<'项目驾驶舱'!$B$3,"已延期",IF(J38<='项目驾驶舱'!$B$3+7,"临近到期","正常")))))
A39: T036 | B39: 网上营业厅 | C39: 卸船作业 | D39: 船舶靠泊通知单 | E39: 查询船舶靠泊通知单 | F39: 第二批次 | G39: =IF(OR(M39="挂起",M39="暂停",Q39="挂起",Q39="暂停",U39="挂起",U39="暂停",Y39="挂起",Y39="暂停"),"暂停","进行中") | H39: =IF(L39<>"",L39,IF(P39<>"",P39,IF(T39<>"",T39,X39))) | I39: =IF(COUNT(N39,R39,V39,Z39)=0,"",MIN(N39,R39,V39,Z39)) | J39: =IF(ISNUMBER(K39),K39,IF(COUNT(O39,S39,W39,AA39)=0,"",MAX(O39,S39,W39,AA39))) | L39: 郑士旺 | M39: 已完成 | N39: 46230 | O39: 46241 | P39: 石军磊、刘凯 | Q39: 进行中 | R39: 46307 | S39: 46339 | T39: 贺航 | U39: 进行中 | V39: 46307 | W39: 46339 | X39: 袁丽荣 | Y39: 未开始 | Z39: 46342 | AA39: 46353 | AB39: =(IF(M39="已完成",1,IF(M39="进行中",0.5,0))*15%+IF(Q39="已完成",1,IF(Q39="进行中",0.5,0))*35%+IF(U39="已完成",1,IF(U39="进行中",0.5,0))*30%+IF(Y39="已完成",1,IF(Y39="进行中",0.5,0))*20%) | AC39: =IF(G39="已完成","正常",IF(OR(G39="暂停",G39="挂起"),"暂停",IF(J39="","日期缺失",IF(J39<'项目驾驶舱'!$B$3,"已延期",IF(J39<='项目驾驶舱'!$B$3+7,"临近到期","正常")))))
A40: T037 | B40: 网上营业厅 | C40: 卸车流程跟踪 | D40: 创建卸车流程 | E40: / | F40: 第一批次 | G40: =IF(OR(M40="挂起",M40="暂停",Q40="挂起",Q40="暂停",U40="挂起",U40="暂停",Y40="挂起",Y40="暂停"),"暂停","已完成") | H40: =IF(L40<>"",L40,IF(P40<>"",P40,IF(T40<>"",T40,X40))) | I40: =IF(COUNT(N40,R40,V40,Z40)=0,"",MIN(N40,R40,V40,Z40)) | J40: =IF(ISNUMBER(K40),K40,IF(COUNT(O40,S40,W40,AA40)=0,"",MAX(O40,S40,W40,AA40))) | K40: 46261 | L40: 郑士旺 | M40: 已完成 | N40: 46209 | O40: 46213 | P40: 石军磊、刘凯 | Q40: 已完成 | R40: 46230 | S40: 46262 | T40: 贺航 | U40: 已完成 | V40: 46230 | W40: 46262 | X40: 袁丽荣 | Y40: 已完成 | Z40: 46253 | AA40: 46269 | AB40: =(IF(M40="已完成",1,IF(M40="进行中",0.5,0))*15%+IF(Q40="已完成",1,IF(Q40="进行中",0.5,0))*35%+IF(U40="已完成",1,IF(U40="进行中",0.5,0))*30%+IF(Y40="已完成",1,IF(Y40="进行中",0.5,0))*20%) | AC40: =IF(G40="已完成","正常",IF(OR(G40="暂停",G40="挂起"),"暂停",IF(J40="","日期缺失",IF(J40<'项目驾驶舱'!$B$3,"已延期",IF(J40<='项目驾驶舱'!$B$3+7,"临近到期","正常")))))
A41: T038 | B41: 网上营业厅 | C41: 卸车流程跟踪 | D41: 查询卸车流程 | E41: / | F41: 第一批次 | G41: =IF(OR(M41="挂起",M41="暂停",Q41="挂起",Q41="暂停",U41="挂起",U41="暂停",Y41="挂起",Y41="暂停"),"暂停","已完成") | H41: =IF(L41<>"",L41,IF(P41<>"",P41,IF(T41<>"",T41,X41))) | I41: =IF(COUNT(N41,R41,V41,Z41)=0,"",MIN(N41,R41,V41,Z41)) | J41: =IF(ISNUMBER(K41),K41,IF(COUNT(O41,S41,W41,AA41)=0,"",MAX(O41,S41,W41,AA41))) | K41: 46261 | L41: 郑士旺 | M41: 已完成 | N41: 46209 | O41: 46213 | P41: 石军磊、刘凯 | Q41: 已完成 | R41: 46230 | S41: 46262 | T41: 贺航 | U41: 已完成 | V41: 46230 | W41: 46262 | X41: 袁丽荣 | Y41: 已完成 | Z41: 46253 | AA41: 46269 | AB41: =(IF(M41="已完成",1,IF(M41="进行中",0.5,0))*15%+IF(Q41="已完成",1,IF(Q41="进行中",0.5,0))*35%+IF(U41="已完成",1,IF(U41="进行中",0.5,0))*30%+IF(Y41="已完成",1,IF(Y41="进行中",0.5,0))*20%) | AC41: =IF(G41="已完成","正常",IF(OR(G41="暂停",G41="挂起"),"暂停",IF(J41="","日期缺失",IF(J41<'项目驾驶舱'!$B$3,"已延期",IF(J41<='项目驾驶舱'!$B$3+7,"临近到期","正常")))))
A42: T039 | B42: 网上营业厅 | C42: 卸车流程跟踪 | D42: 修改卸车流程 | E42: / | F42: 第一批次 | G42: =IF(OR(M42="挂起",M42="暂停",Q42="挂起",Q42="暂停",U42="挂起",U42="暂停",Y42="挂起",Y42="暂停"),"暂停","已完成") | H42: =IF(L42<>"",L42,IF(P42<>"",P42,IF(T42<>"",T42,X42))) | I42: =IF(COUNT(N42,R42,V42,Z42)=0,"",MIN(N42,R42,V42,Z42)) | J42: =IF(ISNUMBER(K42),K42,IF(COUNT(O42,S42,W42,AA42)=0,"",MAX(O42,S42,W42,AA42))) | K42: 46261 | L42: 郑士旺 | M42: 已完成 | N42: 46209 | O42: 46213 | P42: 石军磊、刘凯 | Q42: 已完成 | R42: 46230 | S42: 46262 | T42: 贺航 | U42: 已完成 | V42: 46230 | W42: 46262 | X42: 袁丽荣 | Y42: 已完成 | Z42: 46253 | AA42: 46269 | AB42: =(IF(M42="已完成",1,IF(M42="进行中",0.5,0))*15%+IF(Q42="已完成",1,IF(Q42="进行中",0.5,0))*35%+IF(U42="已完成",1,IF(U42="进行中",0.5,0))*30%+IF(Y42="已完成",1,IF(Y42="进行中",0.5,0))*20%) | AC42: =IF(G42="已完成","正常",IF(OR(G42="暂停",G42="挂起"),"暂停",IF(J42="","日期缺失",IF(J42<'项目驾驶舱'!$B$3,"已延期",IF(J42<='项目驾驶舱'!$B$3+7,"临近到期","正常")))))
A43: T040 | B43: 网上营业厅 | C43: 装船流程跟踪 | D43: 创建装船流程 | E43: / | F43: 第一批次 | G43: =IF(OR(M43="挂起",M43="暂停",Q43="挂起",Q43="暂停",U43="挂起",U43="暂停",Y43="挂起",Y43="暂停"),"暂停","已完成") | H43: =IF(L43<>"",L43,IF(P43<>"",P43,IF(T43<>"",T43,X43))) | I43: =IF(COUNT(N43,R43,V43,Z43)=0,"",MIN(N43,R43,V43,Z43)) | J43: =IF(ISNUMBER(K43),K43,IF(COUNT(O43,S43,W43,AA43)=0,"",MAX(O43,S43,W43,AA43))) | K43: 46261 | L43: 郑士旺 | M43: 已完成 | N43: 46209 | O43: 46213 | P43: 石军磊、刘凯 | Q43: 已完成 | R43: 46230 | S43: 46262 | T43: 贺航 | U43: 已完成 | V43: 46230 | W43: 46262 | X43: 袁丽荣 | Y43: 已完成 | Z43: 46253 | AA43: 46269 | AB43: =(IF(M43="已完成",1,IF(M43="进行中",0.5,0))*15%+IF(Q43="已完成",1,IF(Q43="进行中",0.5,0))*35%+IF(U43="已完成",1,IF(U43="进行中",0.5,0))*30%+IF(Y43="已完成",1,IF(Y43="进行中",0.5,0))*20%) | AC43: =IF(G43="已完成","正常",IF(OR(G43="暂停",G43="挂起"),"暂停",IF(J43="","日期缺失",IF(J43<'项目驾驶舱'!$B$3,"已延期",IF(J43<='项目驾驶舱'!$B$3+7,"临近到期","正常")))))
A44: T041 | B44: 网上营业厅 | C44: 装船流程跟踪 | D44: 查询装船流程 | E44: / | F44: 第一批次 | G44: =IF(OR(M44="挂起",M44="暂停",Q44="挂起",Q44="暂停",U44="挂起",U44="暂停",Y44="挂起",Y44="暂停"),"暂停","已完成") | H44: =IF(L44<>"",L44,IF(P44<>"",P44,IF(T44<>"",T44,X44))) | I44: =IF(COUNT(N44,R44,V44,Z44)=0,"",MIN(N44,R44,V44,Z44)) | J44: =IF(ISNUMBER(K44),K44,IF(COUNT(O44,S44,W44,AA44)=0,"",MAX(O44,S44,W44,AA44))) | K44: 46261 | L44: 郑士旺 | M44: 已完成 | N44: 46209 | O44: 46213 | P44: 石军磊、刘凯 | Q44: 已完成 | R44: 46230 | S44: 46262 | T44: 贺航 | U44: 已完成 | V44: 46230 | W44: 46262 | X44: 袁丽荣 | Y44: 已完成 | Z44: 46253 | AA44: 46269 | AB44: =(IF(M44="已完成",1,IF(M44="进行中",0.5,0))*15%+IF(Q44="已完成",1,IF(Q44="进行中",0.5,0))*35%+IF(U44="已完成",1,IF(U44="进行中",0.5,0))*30%+IF(Y44="已完成",1,IF(Y44="进行中",0.5,0))*20%) | AC44: =IF(G44="已完成","正常",IF(OR(G44="暂停",G44="挂起"),"暂停",IF(J44="","日期缺失",IF(J44<'项目驾驶舱'!$B$3,"已延期",IF(J44<='项目驾驶舱'!$B$3+7,"临近到期","正常")))))
A45: T042 | B45: 网上营业厅 | C45: 装船流程跟踪 | D45: 修改装船流程 | E45: / | F45: 第一批次 | G45: =IF(OR(M45="挂起",M45="暂停",Q45="挂起",Q45="暂停",U45="挂起",U45="暂停",Y45="挂起",Y45="暂停"),"暂停","已完成") | H45: =IF(L45<>"",L45,IF(P45<>"",P45,IF(T45<>"",T45,X45))) | I45: =IF(COUNT(N45,R45,V45,Z45)=0,"",MIN(N45,R45,V45,Z45)) | J45: =IF(ISNUMBER(K45),K45,IF(COUNT(O45,S45,W45,AA45)=0,"",MAX(O45,S45,W45,AA45))) | K45: 46261 | L45: 郑士旺 | M45: 已完成 | N45: 46209 | O45: 46213 | P45: 石军磊、刘凯 | Q45: 已完成 | R45: 46230 | S45: 46262 | T45: 贺航 | U45: 已完成 | V45: 46230 | W45: 46262 | X45: 袁丽荣 | Y45: 已完成 | Z45: 46253 | AA45: 46269 | AB45: =(IF(M45="已完成",1,IF(M45="进行中",0.5,0))*15%+IF(Q45="已完成",1,IF(Q45="进行中",0.5,0))*35%+IF(U45="已完成",1,IF(U45="进行中",0.5,0))*30%+IF(Y45="已完成",1,IF(Y45="进行中",0.5,0))*20%) | AC45: =IF(G45="已完成","正常",IF(OR(G45="暂停",G45="挂起"),"暂停",IF(J45="","日期缺失",IF(J45<'项目驾驶舱'!$B$3,"已延期",IF(J45<='项目驾驶舱'!$B$3+7,"临近到期","正常")))))
A46: T043 | B46: 网上营业厅 | C46: 卸船流程跟踪 | D46: 创建卸船流程 | E46: / | F46: 第二批次 | G46: =IF(OR(M46="挂起",M46="暂停",Q46="挂起",Q46="暂停",U46="挂起",U46="暂停",Y46="挂起",Y46="暂停"),"暂停","已完成") | H46: =IF(L46<>"",L46,IF(P46<>"",P46,IF(T46<>"",T46,X46))) | I46: =IF(COUNT(N46,R46,V46,Z46)=0,"",MIN(N46,R46,V46,Z46)) | J46: =IF(ISNUMBER(K46),K46,IF(COUNT(O46,S46,W46,AA46)=0,"",MAX(O46,S46,W46,AA46))) | L46: 郑士旺 | M46: 已完成 | N46: 46209 | O46: 46213 | P46: 石军磊、刘凯 | Q46: 已完成 | R46: 46230 | S46: 46262 | T46: 贺航 | U46: 已完成 | V46: 46230 | W46: 46262 | X46: 袁丽荣 | Y46: 已完成 | Z46: 46253 | AA46: 46269 | AB46: =(IF(M46="已完成",1,IF(M46="进行中",0.5,0))*15%+IF(Q46="已完成",1,IF(Q46="进行中",0.5,0))*35%+IF(U46="已完成",1,IF(U46="进行中",0.5,0))*30%+IF(Y46="已完成",1,IF(Y46="进行中",0.5,0))*20%) | AC46: =IF(G46="已完成","正常",IF(OR(G46="暂停",G46="挂起"),"暂停",IF(J46="","日期缺失",IF(J46<'项目驾驶舱'!$B$3,"已延期",IF(J46<='项目驾驶舱'!$B$3+7,"临近到期","正常")))))
A47: T044 | B47: 网上营业厅 | C47: 卸船流程跟踪 | D47: 查询卸船流程 | E47: / | F47: 第二批次 | G47: =IF(OR(M47="挂起",M47="暂停",Q47="挂起",Q47="暂停",U47="挂起",U47="暂停",Y47="挂起",Y47="暂停"),"暂停","已完成") | H47: =IF(L47<>"",L47,IF(P47<>"",P47,IF(T47<>"",T47,X47))) | I47: =IF(COUNT(N47,R47,V47,Z47)=0,"",MIN(N47,R47,V47,Z47)) | J47: =IF(ISNUMBER(K47),K47,IF(COUNT(O47,S47,W47,AA47)=0,"",MAX(O47,S47,W47,AA47))) | L47: 郑士旺 | M47: 已完成 | N47: 46209 | O47: 46213 | P47: 石军磊、刘凯 | Q47: 已完成 | R47: 46230 | S47: 46262 | T47: 贺航 | U47: 已完成 | V47: 46230 | W47: 46262 | X47: 袁丽荣 | Y47: 已完成 | Z47: 46253 | AA47: 46269 | AB47: =(IF(M47="已完成",1,IF(M47="进行中",0.5,0))*15%+IF(Q47="已完成",1,IF(Q47="进行中",0.5,0))*35%+IF(U47="已完成",1,IF(U47="进行中",0.5,0))*30%+IF(Y47="已完成",1,IF(Y47="进行中",0.5,0))*20%) | AC47: =IF(G47="已完成","正常",IF(OR(G47="暂停",G47="挂起"),"暂停",IF(J47="","日期缺失",IF(J47<'项目驾驶舱'!$B$3,"已延期",IF(J47<='项目驾驶舱'!$B$3+7,"临近到期","正常")))))
A48: T045 | B48: 网上营业厅 | C48: 卸船流程跟踪 | D48: 修改卸船流程 | E48: / | F48: 第二批次 | G48: =IF(OR(M48="挂起",M48="暂停",Q48="挂起",Q48="暂停",U48="挂起",U48="暂停",Y48="挂起",Y48="暂停"),"暂停","已完成") | H48: =IF(L48<>"",L48,IF(P48<>"",P48,IF(T48<>"",T48,X48))) | I48: =IF(COUNT(N48,R48,V48,Z48)=0,"",MIN(N48,R48,V48,Z48)) | J48: =IF(ISNUMBER(K48),K48,IF(COUNT(O48,S48,W48,AA48)=0,"",MAX(O48,S48,W48,AA48))) | L48: 郑士旺 | M48: 已完成 | N48: 46209 | O48: 46213 | P48: 石军磊、刘凯 | Q48: 已完成 | R48: 46230 | S48: 46262 | T48: 贺航 | U48: 已完成 | V48: 46230 | W48: 46262 | X48: 袁丽荣 | Y48: 已完成 | Z48: 46253 | AA48: 46269 | AB48: =(IF(M48="已完成",1,IF(M48="进行中",0.5,0))*15%+IF(Q48="已完成",1,IF(Q48="进行中",0.5,0))*35%+IF(U48="已完成",1,IF(U48="进行中",0.5,0))*30%+IF(Y48="已完成",1,IF(Y48="进行中",0.5,0))*20%) | AC48: =IF(G48="已完成","正常",IF(OR(G48="暂停",G48="挂起"),"暂停",IF(J48="","日期缺失",IF(J48<'项目驾驶舱'!$B$3,"已延期",IF(J48<='项目驾驶舱'!$B$3+7,"临近到期","正常")))))
A49: T046 | B49: 网上营业厅 | C49: 船舶预到（外贸） | D49: 新增船舶预到（外贸） | E49: / | F49: 第二批次 | G49: =IF(OR(M49="挂起",M49="暂停",Q49="挂起",Q49="暂停",U49="挂起",U49="暂停",Y49="挂起",Y49="暂停"),"暂停","已完成") | H49: =IF(L49<>"",L49,IF(P49<>"",P49,IF(T49<>"",T49,X49))) | I49: =IF(COUNT(N49,R49,V49,Z49)=0,"",MIN(N49,R49,V49,Z49)) | J49: =IF(ISNUMBER(K49),K49,IF(COUNT(O49,S49,W49,AA49)=0,"",MAX(O49,S49,W49,AA49))) | K49: / | L49: 郑士旺 | M49: 已完成 | N49: 46230 | O49: 46241 | P49: 石军磊、刘凯 | Q49: 已完成 | R49: 46307 | S49: 46339 | T49: 贺航 | U49: 已完成 | V49: 46307 | W49: 46339 | X49: 袁丽荣 | Y49: 已完成 | Z49: 46342 | AA49: 46353 | AB49: =(IF(M49="已完成",1,IF(M49="进行中",0.5,0))*15%+IF(Q49="已完成",1,IF(Q49="进行中",0.5,0))*35%+IF(U49="已完成",1,IF(U49="进行中",0.5,0))*30%+IF(Y49="已完成",1,IF(Y49="进行中",0.5,0))*20%) | AC49: =IF(G49="已完成","正常",IF(OR(G49="暂停",G49="挂起"),"暂停",IF(J49="","日期缺失",IF(J49<'项目驾驶舱'!$B$3,"已延期",IF(J49<='项目驾驶舱'!$B$3+7,"临近到期","正常")))))
A50: T047 | B50: 网上营业厅 | C50: 船舶预到（外贸） | D50: 退回船舶预到（外贸） | E50: / | F50: 第二批次 | G50: =IF(OR(M50="挂起",M50="暂停",Q50="挂起",Q50="暂停",U50="挂起",U50="暂停",Y50="挂起",Y50="暂停"),"暂停","未开始") | H50: =IF(L50<>"",L50,IF(P50<>"",P50,IF(T50<>"",T50,X50))) | I50: =IF(COUNT(N50,R50,V50,Z50)=0,"",MIN(N50,R50,V50,Z50)) | J50: =IF(ISNUMBER(K50),K50,IF(COUNT(O50,S50,W50,AA50)=0,"",MAX(O50,S50,W50,AA50))) | L50: 郑士旺 | M50: 未开始 | N50: 46230 | O50: 46241 | P50: 石军磊、刘凯 | Q50: 未开始 | R50: 46307 | S50: 46339 | T50: 贺航 | U50: 未开始 | V50: 46307 | W50: 46339 | X50: 袁丽荣 | Y50: 未开始 | Z50: 46342 | AA50: 46353 | AB50: =(IF(M50="已完成",1,IF(M50="进行中",0.5,0))*15%+IF(Q50="已完成",1,IF(Q50="进行中",0.5,0))*35%+IF(U50="已完成",1,IF(U50="进行中",0.5,0))*30%+IF(Y50="已完成",1,IF(Y50="进行中",0.5,0))*20%) | AC50: =IF(G50="已完成","正常",IF(OR(G50="暂停",G50="挂起"),"暂停",IF(J50="","日期缺失",IF(J50<'项目驾驶舱'!$B$3,"已延期",IF(J50<='项目驾驶舱'!$B$3+7,"临近到期","正常")))))
A51: T048 | B51: 网上营业厅 | C51: 船舶预到（内贸） | D51: 退回船舶预到（外贸） | E51: / | F51: 第二批次 | G51: =IF(OR(M51="挂起",M51="暂停",Q51="挂起",Q51="暂停",U51="挂起",U51="暂停",Y51="挂起",Y51="暂停"),"暂停","未开始") | H51: =IF(L51<>"",L51,IF(P51<>"",P51,IF(T51<>"",T51,X51))) | I51: =IF(COUNT(N51,R51,V51,Z51)=0,"",MIN(N51,R51,V51,Z51)) | J51: =IF(ISNUMBER(K51),K51,IF(COUNT(O51,S51,W51,AA51)=0,"",MAX(O51,S51,W51,AA51))) | K51: 46261 | L51: 郑士旺 | M51: 未开始 | N51: 46230 | O51: 46241 | P51: 石军磊、刘凯 | Q51: 未开始 | R51: 46307 | S51: 46339 | T51: 贺航 | U51: 未开始 | V51: 46307 | W51: 46339 | X51: 袁丽荣 | Y51: 未开始 | Z51: 46342 | AA51: 46353 | AB51: =(IF(M51="已完成",1,IF(M51="进行中",0.5,0))*15%+IF(Q51="已完成",1,IF(Q51="进行中",0.5,0))*35%+IF(U51="已完成",1,IF(U51="进行中",0.5,0))*30%+IF(Y51="已完成",1,IF(Y51="进行中",0.5,0))*20%) | AC51: =IF(G51="已完成","正常",IF(OR(G51="暂停",G51="挂起"),"暂停",IF(J51="","日期缺失",IF(J51<'项目驾驶舱'!$B$3,"已延期",IF(J51<='项目驾驶舱'!$B$3+7,"临近到期","正常")))))
A52: T049 | B52: 网上营业厅 | C52: 采样申请（外贸） | D52: 申请采样申请（外贸） | E52: / | F52: 第二批次 | G52: =IF(OR(M52="挂起",M52="暂停",Q52="挂起",Q52="暂停",U52="挂起",U52="暂停",Y52="挂起",Y52="暂停"),"暂停","已完成") | H52: =IF(L52<>"",L52,IF(P52<>"",P52,IF(T52<>"",T52,X52))) | I52: =IF(COUNT(N52,R52,V52,Z52)=0,"",MIN(N52,R52,V52,Z52)) | J52: =IF(ISNUMBER(K52),K52,IF(COUNT(O52,S52,W52,AA52)=0,"",MAX(O52,S52,W52,AA52))) | K52: 46261 | L52: 郑士旺 | M52: 已完成 | N52: 46230 | O52: 46241 | P52: 石军磊、刘凯 | Q52: 已完成 | R52: 46307 | S52: 46339 | T52: 贺航 | U52: 已完成 | V52: 46307 | W52: 46339 | X52: 袁丽荣 | Y52: 已完成 | Z52: 46342 | AA52: 46353 | AB52: =(IF(M52="已完成",1,IF(M52="进行中",0.5,0))*15%+IF(Q52="已完成",1,IF(Q52="进行中",0.5,0))*35%+IF(U52="已完成",1,IF(U52="进行中",0.5,0))*30%+IF(Y52="已完成",1,IF(Y52="进行中",0.5,0))*20%) | AC52: =IF(G52="已完成","正常",IF(OR(G52="暂停",G52="挂起"),"暂停",IF(J52="","日期缺失",IF(J52<'项目驾驶舱'!$B$3,"已延期",IF(J52<='项目驾驶舱'!$B$3+7,"临近到期","正常")))))
A53: T050 | B53: 网上营业厅 | C53: 船舶轨迹跟踪 | D53: 维护需跟踪船舶清单 | E53: / | F53: 第一批次 | G53: =IF(OR(M53="挂起",M53="暂停",Q53="挂起",Q53="暂停",U53="挂起",U53="暂停",Y53="挂起",Y53="暂停"),"暂停","进行中") | H53: =IF(L53<>"",L53,IF(P53<>"",P53,IF(T53<>"",T53,X53))) | I53: =IF(COUNT(N53,R53,V53,Z53)=0,"",MIN(N53,R53,V53,Z53)) | J53: =IF(ISNUMBER(K53),K53,IF(COUNT(O53,S53,W53,AA53)=0,"",MAX(O53,S53,W53,AA53))) | K53: / | L53: 郑士旺 | M53: 已完成 | N53: 46202 | O53: 46206 | P53: 石军磊、常浩 | Q53: 已完成 | R53: 46209 | S53: 46227 | T53: 贺航、常浩 | U53: 已完成 | V53: 46209 | W53: 46227 | X53: 袁丽荣 | Y53: 进行中 | Z53: 46216 | AA53: 46234 | AB53: =(IF(M53="已完成",1,IF(M53="进行中",0.5,0))*15%+IF(Q53="已完成",1,IF(Q53="进行中",0.5,0))*35%+IF(U53="已完成",1,IF(U53="进行中",0.5,0))*30%+IF(Y53="已完成",1,IF(Y53="进行中",0.5,0))*20%) | AC53: =IF(G53="已完成","正常",IF(OR(G53="暂停",G53="挂起"),"暂停",IF(J53="","日期缺失",IF(J53<'项目驾驶舱'!$B$3,"已延期",IF(J53<='项目驾驶舱'!$B$3+7,"临近到期","正常")))))
A54: T051 | B54: 网上营业厅 | C54: 船舶轨迹跟踪 | D54: 根据船舶清单更新第三方系统推送数据船舶清单 | E54: / | F54: 第一批次 | G54: =IF(OR(M54="挂起",M54="暂停",Q54="挂起",Q54="暂停",U54="挂起",U54="暂停",Y54="挂起",Y54="暂停"),"暂停","进行中") | H54: =IF(L54<>"",L54,IF(P54<>"",P54,IF(T54<>"",T54,X54))) | I54: =IF(COUNT(N54,R54,V54,Z54)=0,"",MIN(N54,R54,V54,Z54)) | J54: =IF(ISNUMBER(K54),K54,IF(COUNT(O54,S54,W54,AA54)=0,"",MAX(O54,S54,W54,AA54))) | K54: 46261 | L54: 郑士旺 | M54: 已完成 | N54: 46202 | O54: 46206 | P54: 石军磊、常浩 | Q54: 已完成 | R54: 46209 | S54: 46227 | T54: 贺航、常浩 | U54: 已完成 | V54: 46209 | W54: 46227 | X54: 袁丽荣 | Y54: 进行中 | Z54: 46216 | AA54: 46234 | AB54: =(IF(M54="已完成",1,IF(M54="进行中",0.5,0))*15%+IF(Q54="已完成",1,IF(Q54="进行中",0.5,0))*35%+IF(U54="已完成",1,IF(U54="进行中",0.5,0))*30%+IF(Y54="已完成",1,IF(Y54="进行中",0.5,0))*20%) | AC54: =IF(G54="已完成","正常",IF(OR(G54="暂停",G54="挂起"),"暂停",IF(J54="","日期缺失",IF(J54<'项目驾驶舱'!$B$3,"已延期",IF(J54<='项目驾驶舱'!$B$3+7,"临近到期","正常")))))
A55: T052 | B55: 网上营业厅 | C55: 船舶轨迹跟踪 | D55: 船舶轨迹跟踪 | E55: / | F55: 第一批次 | G55: =IF(OR(M55="挂起",M55="暂停",Q55="挂起",Q55="暂停",U55="挂起",U55="暂停",Y55="挂起",Y55="暂停"),"暂停","进行中") | H55: =IF(L55<>"",L55,IF(P55<>"",P55,IF(T55<>"",T55,X55))) | I55: =IF(COUNT(N55,R55,V55,Z55)=0,"",MIN(N55,R55,V55,Z55)) | J55: =IF(ISNUMBER(K55),K55,IF(COUNT(O55,S55,W55,AA55)=0,"",MAX(O55,S55,W55,AA55))) | K55: 46261 | L55: 郑士旺 | M55: 已完成 | N55: 46202 | O55: 46206 | P55: 石军磊、常浩 | Q55: 已完成 | R55: 46209 | S55: 46227 | T55: 贺航、常浩 | U55: 已完成 | V55: 46209 | W55: 46227 | X55: 袁丽荣 | Y55: 进行中 | Z55: 46216 | AA55: 46234 | AB55: =(IF(M55="已完成",1,IF(M55="进行中",0.5,0))*15%+IF(Q55="已完成",1,IF(Q55="进行中",0.5,0))*35%+IF(U55="已完成",1,IF(U55="进行中",0.5,0))*30%+IF(Y55="已完成",1,IF(Y55="进行中",0.5,0))*20%) | AC55: =IF(G55="已完成","正常",IF(OR(G55="暂停",G55="挂起"),"暂停",IF(J55="","日期缺失",IF(J55<'项目驾驶舱'!$B$3,"已延期",IF(J55<='项目驾驶舱'!$B$3+7,"临近到期","正常")))))
A56: T053 | B56: 网上营业厅 | C56: 协同视览 | D56: 接入港口侧视频监控 | E56: / | F56: 第二批次 | G56: =IF(OR(M56="挂起",M56="暂停",Q56="挂起",Q56="暂停",U56="挂起",U56="暂停",Y56="挂起",Y56="暂停"),"暂停","未开始") | H56: =IF(L56<>"",L56,IF(P56<>"",P56,IF(T56<>"",T56,X56))) | I56: =IF(COUNT(N56,R56,V56,Z56)=0,"",MIN(N56,R56,V56,Z56)) | J56: =IF(ISNUMBER(K56),K56,IF(COUNT(O56,S56,W56,AA56)=0,"",MAX(O56,S56,W56,AA56))) | K56: 46224 | L56: 郑士旺 | M56: 未开始 | N56: 46223 | O56: 46227 | P56: 石军磊、刘凯 | Q56: 未开始 | R56: 46272 | S56: 46304 | T56: 贺航 | U56: 未开始 | V56: 46272 | W56: 46304 | X56: 袁丽荣 | Y56: 未开始 | Z56: 46307 | AA56: 46318 | AB56: =(IF(M56="已完成",1,IF(M56="进行中",0.5,0))*15%+IF(Q56="已完成",1,IF(Q56="进行中",0.5,0))*35%+IF(U56="已完成",1,IF(U56="进行中",0.5,0))*30%+IF(Y56="已完成",1,IF(Y56="进行中",0.5,0))*20%) | AC56: =IF(G56="已完成","正常",IF(OR(G56="暂停",G56="挂起"),"暂停",IF(J56="","日期缺失",IF(J56<'项目驾驶舱'!$B$3,"已延期",IF(J56<='项目驾驶舱'!$B$3+7,"临近到期","正常")))))
A57: T054 | B57: 网上营业厅 | C57: 协同视览 | D57: 视频查看权限申请 | E57: / | F57: 第二批次 | G57: =IF(OR(M57="挂起",M57="暂停",Q57="挂起",Q57="暂停",U57="挂起",U57="暂停",Y57="挂起",Y57="暂停"),"暂停","未开始") | H57: =IF(L57<>"",L57,IF(P57<>"",P57,IF(T57<>"",T57,X57))) | I57: =IF(COUNT(N57,R57,V57,Z57)=0,"",MIN(N57,R57,V57,Z57)) | J57: =IF(ISNUMBER(K57),K57,IF(COUNT(O57,S57,W57,AA57)=0,"",MAX(O57,S57,W57,AA57))) | K57: 46224 | L57: 郑士旺 | M57: 未开始 | N57: 46223 | O57: 46227 | P57: 石军磊、刘凯 | Q57: 未开始 | R57: 46272 | S57: 46304 | T57: 贺航 | U57: 未开始 | V57: 46272 | W57: 46304 | X57: 袁丽荣 | Y57: 未开始 | Z57: 46307 | AA57: 46318 | AB57: =(IF(M57="已完成",1,IF(M57="进行中",0.5,0))*15%+IF(Q57="已完成",1,IF(Q57="进行中",0.5,0))*35%+IF(U57="已完成",1,IF(U57="进行中",0.5,0))*30%+IF(Y57="已完成",1,IF(Y57="进行中",0.5,0))*20%) | AC57: =IF(G57="已完成","正常",IF(OR(G57="暂停",G57="挂起"),"暂停",IF(J57="","日期缺失",IF(J57<'项目驾驶舱'!$B$3,"已延期",IF(J57<='项目驾驶舱'!$B$3+7,"临近到期","正常")))))
A58: T055 | B58: 网上营业厅 | C58: 协同视览 | D58: 视频查看权限审批 | E58: / | F58: 第二批次 | G58: =IF(OR(M58="挂起",M58="暂停",Q58="挂起",Q58="暂停",U58="挂起",U58="暂停",Y58="挂起",Y58="暂停"),"暂停","未开始") | H58: =IF(L58<>"",L58,IF(P58<>"",P58,IF(T58<>"",T58,X58))) | I58: =IF(COUNT(N58,R58,V58,Z58)=0,"",MIN(N58,R58,V58,Z58)) | J58: =IF(ISNUMBER(K58),K58,IF(COUNT(O58,S58,W58,AA58)=0,"",MAX(O58,S58,W58,AA58))) | K58: 46224 | L58: 郑士旺 | M58: 未开始 | N58: 46223 | O58: 46227 | P58: 石军磊、刘凯 | Q58: 未开始 | R58: 46272 | S58: 46304 | T58: 贺航 | U58: 未开始 | V58: 46272 | W58: 46304 | X58: 袁丽荣 | Y58: 未开始 | Z58: 46307 | AA58: 46318 | AB58: =(IF(M58="已完成",1,IF(M58="进行中",0.5,0))*15%+IF(Q58="已完成",1,IF(Q58="进行中",0.5,0))*35%+IF(U58="已完成",1,IF(U58="进行中",0.5,0))*30%+IF(Y58="已完成",1,IF(Y58="进行中",0.5,0))*20%) | AC58: =IF(G58="已完成","正常",IF(OR(G58="暂停",G58="挂起"),"暂停",IF(J58="","日期缺失",IF(J58<'项目驾驶舱'!$B$3,"已延期",IF(J58<='项目驾驶舱'!$B$3+7,"临近到期","正常")))))
A59: T056 | B59: 网上营业厅 | C59: 协同视览 | D59: 视频查看权限有效期控制 | E59: / | F59: 第二批次 | G59: =IF(OR(M59="挂起",M59="暂停",Q59="挂起",Q59="暂停",U59="挂起",U59="暂停",Y59="挂起",Y59="暂停"),"暂停","未开始") | H59: =IF(L59<>"",L59,IF(P59<>"",P59,IF(T59<>"",T59,X59))) | I59: =IF(COUNT(N59,R59,V59,Z59)=0,"",MIN(N59,R59,V59,Z59)) | J59: =IF(ISNUMBER(K59),K59,IF(COUNT(O59,S59,W59,AA59)=0,"",MAX(O59,S59,W59,AA59))) | L59: 郑士旺 | M59: 未开始 | N59: 46223 | O59: 46227 | P59: 石军磊、刘凯 | Q59: 未开始 | R59: 46272 | S59: 46304 | T59: 贺航 | U59: 未开始 | V59: 46272 | W59: 46304 | X59: 袁丽荣 | Y59: 未开始 | Z59: 46307 | AA59: 46318 | AB59: =(IF(M59="已完成",1,IF(M59="进行中",0.5,0))*15%+IF(Q59="已完成",1,IF(Q59="进行中",0.5,0))*35%+IF(U59="已完成",1,IF(U59="进行中",0.5,0))*30%+IF(Y59="已完成",1,IF(Y59="进行中",0.5,0))*20%) | AC59: =IF(G59="已完成","正常",IF(OR(G59="暂停",G59="挂起"),"暂停",IF(J59="","日期缺失",IF(J59<'项目驾驶舱'!$B$3,"已延期",IF(J59<='项目驾驶舱'!$B$3+7,"临近到期","正常")))))
A60: T057 | B60: 网上营业厅 | C60: 协同视览 | D60: 外网PC端视频监控查询 | E60: / | F60: 第二批次 | G60: =IF(OR(M60="挂起",M60="暂停",Q60="挂起",Q60="暂停",U60="挂起",U60="暂停",Y60="挂起",Y60="暂停"),"暂停","未开始") | H60: =IF(L60<>"",L60,IF(P60<>"",P60,IF(T60<>"",T60,X60))) | I60: =IF(COUNT(N60,R60,V60,Z60)=0,"",MIN(N60,R60,V60,Z60)) | J60: =IF(ISNUMBER(K60),K60,IF(COUNT(O60,S60,W60,AA60)=0,"",MAX(O60,S60,W60,AA60))) | K60: 46224 | L60: 郑士旺 | M60: 未开始 | N60: 46223 | O60: 46227 | P60: 石军磊、刘凯 | Q60: 未开始 | R60: 46272 | S60: 46304 | T60: 贺航 | U60: 未开始 | V60: 46272 | W60: 46304 | X60: 袁丽荣 | Y60: 未开始 | Z60: 46307 | AA60: 46318 | AB60: =(IF(M60="已完成",1,IF(M60="进行中",0.5,0))*15%+IF(Q60="已完成",1,IF(Q60="进行中",0.5,0))*35%+IF(U60="已完成",1,IF(U60="进行中",0.5,0))*30%+IF(Y60="已完成",1,IF(Y60="进行中",0.5,0))*20%) | AC60: =IF(G60="已完成","正常",IF(OR(G60="暂停",G60="挂起"),"暂停",IF(J60="","日期缺失",IF(J60<'项目驾驶舱'!$B$3,"已延期",IF(J60<='项目驾驶舱'!$B$3+7,"临近到期","正常")))))
A61: T058 | B61: 网上营业厅 | C61: 装船计划编制及推送 | D61: OCR识别及编辑 | E61: / | F61: 第一批次 | G61: =IF(OR(M61="挂起",M61="暂停",Q61="挂起",Q61="暂停",U61="挂起",U61="暂停",Y61="挂起",Y61="暂停"),"暂停","已完成") | H61: =IF(L61<>"",L61,IF(P61<>"",P61,IF(T61<>"",T61,X61))) | I61: =IF(COUNT(N61,R61,V61,Z61)=0,"",MIN(N61,R61,V61,Z61)) | J61: =IF(ISNUMBER(K61),K61,IF(COUNT(O61,S61,W61,AA61)=0,"",MAX(O61,S61,W61,AA61))) | K61: 46224 | L61: 郑士旺 | M61: 已完成 | N61: / | O61: / | P61: 石军磊、刘凯 | Q61: 已完成 | R61: 46195 | S61: 46206 | T61: 贺航 | U61: 已完成 | V61: 46195 | W61: 46206 | X61: 袁丽荣 | Y61: 已完成 | Z61: 46202 | AA61: 46213 | AB61: =(IF(M61="已完成",1,IF(M61="进行中",0.5,0))*15%+IF(Q61="已完成",1,IF(Q61="进行中",0.5,0))*35%+IF(U61="已完成",1,IF(U61="进行中",0.5,0))*30%+IF(Y61="已完成",1,IF(Y61="进行中",0.5,0))*20%) | AC61: =IF(G61="已完成","正常",IF(OR(G61="暂停",G61="挂起"),"暂停",IF(J61="","日期缺失",IF(J61<'项目驾驶舱'!$B$3,"已延期",IF(J61<='项目驾驶舱'!$B$3+7,"临近到期","正常")))))
A62: T059 | B62: 网上营业厅 | C62: 优化装车作业信息录入 | D62: 优化新增装车作业信息 | E62: / | F62: 第一批次 | G62: =IF(OR(M62="挂起",M62="暂停",Q62="挂起",Q62="暂停",U62="挂起",U62="暂停",Y62="挂起",Y62="暂停"),"暂停","已完成") | H62: =IF(L62<>"",L62,IF(P62<>"",P62,IF(T62<>"",T62,X62))) | I62: =IF(COUNT(N62,R62,V62,Z62)=0,"",MIN(N62,R62,V62,Z62)) | J62: =IF(ISNUMBER(K62),K62,IF(COUNT(O62,S62,W62,AA62)=0,"",MAX(O62,S62,W62,AA62))) | K62: / | L62: 郑士旺 | M62: 已完成 | N62: 46230 | O62: 46241 | P62: 石军磊、刘凯 | Q62: 已完成 | R62: 46230 | S62: 46241 | T62: 贺航 | U62: 已完成 | V62: 46230 | W62: 46241 | X62: 袁丽荣 | Y62: 已完成 | Z62: 46307 | AA62: 46318 | AB62: =(IF(M62="已完成",1,IF(M62="进行中",0.5,0))*15%+IF(Q62="已完成",1,IF(Q62="进行中",0.5,0))*35%+IF(U62="已完成",1,IF(U62="进行中",0.5,0))*30%+IF(Y62="已完成",1,IF(Y62="进行中",0.5,0))*20%) | AC62: =IF(G62="已完成","正常",IF(OR(G62="暂停",G62="挂起"),"暂停",IF(J62="","日期缺失",IF(J62<'项目驾驶舱'!$B$3,"已延期",IF(J62<='项目驾驶舱'!$B$3+7,"临近到期","正常")))))
A63: T060 | B63: 网上营业厅 | C63: 货权跟踪 | D63: 货权录入 | E63: / | F63: 第一批次 | G63: =IF(OR(M63="挂起",M63="暂停",Q63="挂起",Q63="暂停",U63="挂起",U63="暂停",Y63="挂起",Y63="暂停"),"暂停","已完成") | H63: =IF(L63<>"",L63,IF(P63<>"",P63,IF(T63<>"",T63,X63))) | I63: =IF(COUNT(N63,R63,V63,Z63)=0,"",MIN(N63,R63,V63,Z63)) | J63: =IF(ISNUMBER(K63),K63,IF(COUNT(O63,S63,W63,AA63)=0,"",MAX(O63,S63,W63,AA63))) | K63: 46261 | L63: 郑士旺 | M63: 已完成 | N63: 46202 | O63: 46206 | P63: 石军磊、刘凯 | Q63: 已完成 | R63: 46209 | S63: 46227 | T63: 贺航 | U63: 已完成 | V63: 46209 | W63: 46227 | X63: 袁丽荣 | Y63: 已完成 | Z63: 46216 | AA63: 46234 | AB63: =(IF(M63="已完成",1,IF(M63="进行中",0.5,0))*15%+IF(Q63="已完成",1,IF(Q63="进行中",0.5,0))*35%+IF(U63="已完成",1,IF(U63="进行中",0.5,0))*30%+IF(Y63="已完成",1,IF(Y63="进行中",0.5,0))*20%) | AC63: =IF(G63="已完成","正常",IF(OR(G63="暂停",G63="挂起"),"暂停",IF(J63="","日期缺失",IF(J63<'项目驾驶舱'!$B$3,"已延期",IF(J63<='项目驾驶舱'!$B$3+7,"临近到期","正常")))))
A64: T061 | B64: 网上营业厅 | C64: 货权跟踪 | D64: 货权修改 | E64: / | F64: 第一批次 | G64: =IF(OR(M64="挂起",M64="暂停",Q64="挂起",Q64="暂停",U64="挂起",U64="暂停",Y64="挂起",Y64="暂停"),"暂停","已完成") | H64: =IF(L64<>"",L64,IF(P64<>"",P64,IF(T64<>"",T64,X64))) | I64: =IF(COUNT(N64,R64,V64,Z64)=0,"",MIN(N64,R64,V64,Z64)) | J64: =IF(ISNUMBER(K64),K64,IF(COUNT(O64,S64,W64,AA64)=0,"",MAX(O64,S64,W64,AA64))) | K64: 46261 | L64: 郑士旺 | M64: 已完成 | N64: 46202 | O64: 46206 | P64: 石军磊、刘凯 | Q64: 已完成 | R64: 46209 | S64: 46227 | T64: 贺航 | U64: 已完成 | V64: 46209 | W64: 46227 | X64: 袁丽荣 | Y64: 已完成 | Z64: 46216 | AA64: 46234 | AB64: =(IF(M64="已完成",1,IF(M64="进行中",0.5,0))*15%+IF(Q64="已完成",1,IF(Q64="进行中",0.5,0))*35%+IF(U64="已完成",1,IF(U64="进行中",0.5,0))*30%+IF(Y64="已完成",1,IF(Y64="进行中",0.5,0))*20%) | AC64: =IF(G64="已完成","正常",IF(OR(G64="暂停",G64="挂起"),"暂停",IF(J64="","日期缺失",IF(J64<'项目驾驶舱'!$B$3,"已延期",IF(J64<='项目驾驶舱'!$B$3+7,"临近到期","正常")))))
A65: T062 | B65: 网上营业厅 | C65: 货权跟踪 | D65: 获取查询 | E65: / | F65: 第一批次 | G65: =IF(OR(M65="挂起",M65="暂停",Q65="挂起",Q65="暂停",U65="挂起",U65="暂停",Y65="挂起",Y65="暂停"),"暂停","已完成") | H65: =IF(L65<>"",L65,IF(P65<>"",P65,IF(T65<>"",T65,X65))) | I65: =IF(COUNT(N65,R65,V65,Z65)=0,"",MIN(N65,R65,V65,Z65)) | J65: =IF(ISNUMBER(K65),K65,IF(COUNT(O65,S65,W65,AA65)=0,"",MAX(O65,S65,W65,AA65))) | K65: 46261 | L65: 郑士旺 | M65: 已完成 | N65: 46202 | O65: 46206 | P65: 石军磊、刘凯 | Q65: 已完成 | R65: 46209 | S65: 46227 | T65: 贺航 | U65: 已完成 | V65: 46209 | W65: 46227 | X65: 袁丽荣 | Y65: 已完成 | Z65: 46216 | AA65: 46234 | AB65: =(IF(M65="已完成",1,IF(M65="进行中",0.5,0))*15%+IF(Q65="已完成",1,IF(Q65="进行中",0.5,0))*35%+IF(U65="已完成",1,IF(U65="进行中",0.5,0))*30%+IF(Y65="已完成",1,IF(Y65="进行中",0.5,0))*20%) | AC65: =IF(G65="已完成","正常",IF(OR(G65="暂停",G65="挂起"),"暂停",IF(J65="","日期缺失",IF(J65<'项目驾驶舱'!$B$3,"已延期",IF(J65<='项目驾驶舱'!$B$3+7,"临近到期","正常")))))
A66: T063 | B66: 网上营业厅 | C66: 货权提醒 | D66: 卸船作业货权跟踪 | E66: / | F66: 第一批次 | G66: =IF(OR(M66="挂起",M66="暂停",Q66="挂起",Q66="暂停",U66="挂起",U66="暂停",Y66="挂起",Y66="暂停"),"暂停","已完成") | H66: =IF(L66<>"",L66,IF(P66<>"",P66,IF(T66<>"",T66,X66))) | I66: =IF(COUNT(N66,R66,V66,Z66)=0,"",MIN(N66,R66,V66,Z66)) | J66: =IF(ISNUMBER(K66),K66,IF(COUNT(O66,S66,W66,AA66)=0,"",MAX(O66,S66,W66,AA66))) | K66: 46261 | L66: 郑士旺 | M66: 已完成 | N66: 46202 | O66: 46206 | P66: 石军磊、刘凯 | Q66: 已完成 | R66: 46209 | S66: 46227 | T66: 贺航 | U66: 已完成 | V66: 46209 | W66: 46227 | X66: 袁丽荣 | Y66: 已完成 | Z66: 46216 | AA66: 46234 | AB66: =(IF(M66="已完成",1,IF(M66="进行中",0.5,0))*15%+IF(Q66="已完成",1,IF(Q66="进行中",0.5,0))*35%+IF(U66="已完成",1,IF(U66="进行中",0.5,0))*30%+IF(Y66="已完成",1,IF(Y66="进行中",0.5,0))*20%) | AC66: =IF(G66="已完成","正常",IF(OR(G66="暂停",G66="挂起"),"暂停",IF(J66="","日期缺失",IF(J66<'项目驾驶舱'!$B$3,"已延期",IF(J66<='项目驾驶舱'!$B$3+7,"临近到期","正常")))))
A67: T064 | B67: 网上营业厅 | C67: 货权提醒 | D67: 卸船作业货权跟踪 | E67: / | F67: 第一批次 | G67: =IF(OR(M67="挂起",M67="暂停",Q67="挂起",Q67="暂停",U67="挂起",U67="暂停",Y67="挂起",Y67="暂停"),"暂停","已完成") | H67: =IF(L67<>"",L67,IF(P67<>"",P67,IF(T67<>"",T67,X67))) | I67: =IF(COUNT(N67,R67,V67,Z67)=0,"",MIN(N67,R67,V67,Z67)) | J67: =IF(ISNUMBER(K67),K67,IF(COUNT(O67,S67,W67,AA67)=0,"",MAX(O67,S67,W67,AA67))) | K67: 46261 | L67: 郑士旺 | M67: 已完成 | N67: 46202 | O67: 46206 | P67: 石军磊、刘凯 | Q67: 已完成 | R67: 46209 | S67: 46227 | T67: 贺航 | U67: 已完成 | V67: 46209 | W67: 46227 | X67: 袁丽荣 | Y67: 已完成 | Z67: 46216 | AA67: 46234 | AB67: =(IF(M67="已完成",1,IF(M67="进行中",0.5,0))*15%+IF(Q67="已完成",1,IF(Q67="进行中",0.5,0))*35%+IF(U67="已完成",1,IF(U67="进行中",0.5,0))*30%+IF(Y67="已完成",1,IF(Y67="进行中",0.5,0))*20%) | AC67: =IF(G67="已完成","正常",IF(OR(G67="暂停",G67="挂起"),"暂停",IF(J67="","日期缺失",IF(J67<'项目驾驶舱'!$B$3,"已延期",IF(J67<='项目驾驶舱'!$B$3+7,"临近到期","正常")))))
A68: T065 | B68: 网上营业厅 | C68: 货权提醒 | D68: 装船作业货权跟踪 | E68: / | F68: 第一批次 | G68: =IF(OR(M68="挂起",M68="暂停",Q68="挂起",Q68="暂停",U68="挂起",U68="暂停",Y68="挂起",Y68="暂停"),"暂停","已完成") | H68: =IF(L68<>"",L68,IF(P68<>"",P68,IF(T68<>"",T68,X68))) | I68: =IF(COUNT(N68,R68,V68,Z68)=0,"",MIN(N68,R68,V68,Z68)) | J68: =IF(ISNUMBER(K68),K68,IF(COUNT(O68,S68,W68,AA68)=0,"",MAX(O68,S68,W68,AA68))) | K68: 46261 | L68: 郑士旺 | M68: 已完成 | N68: 46202 | O68: 46206 | P68: 石军磊、刘凯 | Q68: 已完成 | R68: 46209 | S68: 46227 | T68: 贺航 | U68: 已完成 | V68: 46209 | W68: 46227 | X68: 袁丽荣 | Y68: 已完成 | Z68: 46216 | AA68: 46234 | AB68: =(IF(M68="已完成",1,IF(M68="进行中",0.5,0))*15%+IF(Q68="已完成",1,IF(Q68="进行中",0.5,0))*35%+IF(U68="已完成",1,IF(U68="进行中",0.5,0))*30%+IF(Y68="已完成",1,IF(Y68="进行中",0.5,0))*20%) | AC68: =IF(G68="已完成","正常",IF(OR(G68="暂停",G68="挂起"),"暂停",IF(J68="","日期缺失",IF(J68<'项目驾驶舱'!$B$3,"已延期",IF(J68<='项目驾驶舱'!$B$3+7,"临近到期","正常")))))
A69: T066 | B69: 网上营业厅 | C69: 货权提醒 | D69: 装船作业货权跟踪 | E69: / | F69: 第一批次 | G69: =IF(OR(M69="挂起",M69="暂停",Q69="挂起",Q69="暂停",U69="挂起",U69="暂停",Y69="挂起",Y69="暂停"),"暂停","已完成") | H69: =IF(L69<>"",L69,IF(P69<>"",P69,IF(T69<>"",T69,X69))) | I69: =IF(COUNT(N69,R69,V69,Z69)=0,"",MIN(N69,R69,V69,Z69)) | J69: =IF(ISNUMBER(K69),K69,IF(COUNT(O69,S69,W69,AA69)=0,"",MAX(O69,S69,W69,AA69))) | K69: 46261 | L69: 郑士旺 | M69: 已完成 | N69: 46202 | O69: 46206 | P69: 石军磊、刘凯 | Q69: 已完成 | R69: 46209 | S69: 46227 | T69: 贺航 | U69: 已完成 | V69: 46209 | W69: 46227 | X69: 袁丽荣 | Y69: 已完成 | Z69: 46216 | AA69: 46234 | AB69: =(IF(M69="已完成",1,IF(M69="进行中",0.5,0))*15%+IF(Q69="已完成",1,IF(Q69="进行中",0.5,0))*35%+IF(U69="已完成",1,IF(U69="进行中",0.5,0))*30%+IF(Y69="已完成",1,IF(Y69="进行中",0.5,0))*20%) | AC69: =IF(G69="已完成","正常",IF(OR(G69="暂停",G69="挂起"),"暂停",IF(J69="","日期缺失",IF(J69<'项目驾驶舱'!$B$3,"已延期",IF(J69<='项目驾驶舱'!$B$3+7,"临近到期","正常")))))
A70: T067 | B70: 网上营业厅 | C70: 货权提醒 | D70: 装船作业货权跟踪 | E70: / | F70: 第一批次 | G70: =IF(OR(M70="挂起",M70="暂停",Q70="挂起",Q70="暂停",U70="挂起",U70="暂停",Y70="挂起",Y70="暂停"),"暂停","已完成") | H70: =IF(L70<>"",L70,IF(P70<>"",P70,IF(T70<>"",T70,X70))) | I70: =IF(COUNT(N70,R70,V70,Z70)=0,"",MIN(N70,R70,V70,Z70)) | J70: =IF(ISNUMBER(K70),K70,IF(COUNT(O70,S70,W70,AA70)=0,"",MAX(O70,S70,W70,AA70))) | K70: 46261 | L70: 郑士旺 | M70: 已完成 | N70: 46202 | O70: 46206 | P70: 石军磊、刘凯 | Q70: 已完成 | R70: 46209 | S70: 46227 | T70: 贺航 | U70: 已完成 | V70: 46209 | W70: 46227 | X70: 袁丽荣 | Y70: 已完成 | Z70: 46216 | AA70: 46234 | AB70: =(IF(M70="已完成",1,IF(M70="进行中",0.5,0))*15%+IF(Q70="已完成",1,IF(Q70="进行中",0.5,0))*35%+IF(U70="已完成",1,IF(U70="进行中",0.5,0))*30%+IF(Y70="已完成",1,IF(Y70="进行中",0.5,0))*20%) | AC70: =IF(G70="已完成","正常",IF(OR(G70="暂停",G70="挂起"),"暂停",IF(J70="","日期缺失",IF(J70<'项目驾驶舱'!$B$3,"已延期",IF(J70<='项目驾驶舱'!$B$3+7,"临近到期","正常")))))
A71: T068 | B71: 网上营业厅 | C71: 货权提醒 | D71: 装船作业货权跟踪 | E71: / | F71: 第一批次 | G71: =IF(OR(M71="挂起",M71="暂停",Q71="挂起",Q71="暂停",U71="挂起",U71="暂停",Y71="挂起",Y71="暂停"),"暂停","已完成") | H71: =IF(L71<>"",L71,IF(P71<>"",P71,IF(T71<>"",T71,X71))) | I71: =IF(COUNT(N71,R71,V71,Z71)=0,"",MIN(N71,R71,V71,Z71)) | J71: =IF(ISNUMBER(K71),K71,IF(COUNT(O71,S71,W71,AA71)=0,"",MAX(O71,S71,W71,AA71))) | K71: 46261 | L71: 郑士旺 | M71: 已完成 | N71: 46202 | O71: 46206 | P71: 石军磊、刘凯 | Q71: 已完成 | R71: 46209 | S71: 46227 | T71: 贺航 | U71: 已完成 | V71: 46209 | W71: 46227 | X71: 袁丽荣 | Y71: 已完成 | Z71: 46216 | AA71: 46234 | AB71: =(IF(M71="已完成",1,IF(M71="进行中",0.5,0))*15%+IF(Q71="已完成",1,IF(Q71="进行中",0.5,0))*35%+IF(U71="已完成",1,IF(U71="进行中",0.5,0))*30%+IF(Y71="已完成",1,IF(Y71="进行中",0.5,0))*20%) | AC71: =IF(G71="已完成","正常",IF(OR(G71="暂停",G71="挂起"),"暂停",IF(J71="","日期缺失",IF(J71<'项目驾驶舱'!$B$3,"已延期",IF(J71<='项目驾驶舱'!$B$3+7,"临近到期","正常")))))
A72: T069 | B72: 网上营业厅 | C72: 卸船作业信息录入优化（太仓） | D72: 新增、详情、修改页内容调整 | E72: / | F72: 第一批次 | G72: =IF(OR(M72="挂起",M72="暂停",Q72="挂起",Q72="暂停",U72="挂起",U72="暂停",Y72="挂起",Y72="暂停"),"暂停","已完成") | H72: =IF(L72<>"",L72,IF(P72<>"",P72,IF(T72<>"",T72,X72))) | I72: =IF(COUNT(N72,R72,V72,Z72)=0,"",MIN(N72,R72,V72,Z72)) | J72: =IF(ISNUMBER(K72),K72,IF(COUNT(O72,S72,W72,AA72)=0,"",MAX(O72,S72,W72,AA72))) | K72: 46224 | L72: 郑士旺 | M72: 已完成 | N72: / | O72: / | P72: 常浩 | Q72: 已完成 | R72: 46195 | S72: 46206 | T72: 常浩 | U72: 已完成 | V72: 46195 | W72: 46206 | X72: 袁丽荣 | Y72: 已完成 | Z72: 46216 | AA72: 46234 | AB72: =(IF(M72="已完成",1,IF(M72="进行中",0.5,0))*15%+IF(Q72="已完成",1,IF(Q72="进行中",0.5,0))*35%+IF(U72="已完成",1,IF(U72="进行中",0.5,0))*30%+IF(Y72="已完成",1,IF(Y72="进行中",0.5,0))*20%) | AC72: =IF(G72="已完成","正常",IF(OR(G72="暂停",G72="挂起"),"暂停",IF(J72="","日期缺失",IF(J72<'项目驾驶舱'!$B$3,"已延期",IF(J72<='项目驾驶舱'!$B$3+7,"临近到期","正常")))))
A73: T070 | B73: 网上营业厅 | C73: 卸船作业信息录入优化（太仓） | D73: 生成报告 | E73: / | F73: 第一批次 | G73: =IF(OR(M73="挂起",M73="暂停",Q73="挂起",Q73="暂停",U73="挂起",U73="暂停",Y73="挂起",Y73="暂停"),"暂停","已完成") | H73: =IF(L73<>"",L73,IF(P73<>"",P73,IF(T73<>"",T73,X73))) | I73: =IF(COUNT(N73,R73,V73,Z73)=0,"",MIN(N73,R73,V73,Z73)) | J73: =IF(ISNUMBER(K73),K73,IF(COUNT(O73,S73,W73,AA73)=0,"",MAX(O73,S73,W73,AA73))) | K73: 46224 | L73: 郑士旺 | M73: 已完成 | N73: / | O73: / | P73: 石军磊、刘凯 | Q73: 已完成 | R73: 46195 | S73: 46206 | T73: 贺航 | U73: 已完成 | V73: 46195 | W73: 46206 | X73: 袁丽荣 | Y73: 已完成 | Z73: 46202 | AA73: 46213 | AB73: =(IF(M73="已完成",1,IF(M73="进行中",0.5,0))*15%+IF(Q73="已完成",1,IF(Q73="进行中",0.5,0))*35%+IF(U73="已完成",1,IF(U73="进行中",0.5,0))*30%+IF(Y73="已完成",1,IF(Y73="进行中",0.5,0))*20%) | AC73: =IF(G73="已完成","正常",IF(OR(G73="暂停",G73="挂起"),"暂停",IF(J73="","日期缺失",IF(J73<'项目驾驶舱'!$B$3,"已延期",IF(J73<='项目驾驶舱'!$B$3+7,"临近到期","正常")))))
A74: T071 | B74: 网上营业厅 | C74: 装船作业信息录入优化（太仓） | D74: / | E74: / | F74: 第一批次 | G74: =IF(OR(M74="挂起",M74="暂停",Q74="挂起",Q74="暂停",U74="挂起",U74="暂停",Y74="挂起",Y74="暂停"),"暂停","已完成") | H74: =IF(L74<>"",L74,IF(P74<>"",P74,IF(T74<>"",T74,X74))) | I74: =IF(COUNT(N74,R74,V74,Z74)=0,"",MIN(N74,R74,V74,Z74)) | J74: =IF(ISNUMBER(K74),K74,IF(COUNT(O74,S74,W74,AA74)=0,"",MAX(O74,S74,W74,AA74))) | K74: 46224 | L74: 郑士旺 | M74: 已完成 | N74: / | O74: / | P74: 石军磊、刘凯 | Q74: 已完成 | R74: 46195 | S74: 46206 | T74: 贺航 | U74: 已完成 | V74: 46195 | W74: 46206 | X74: 袁丽荣 | Y74: 已完成 | Z74: 46202 | AA74: 46213 | AB74: =(IF(M74="已完成",1,IF(M74="进行中",0.5,0))*15%+IF(Q74="已完成",1,IF(Q74="进行中",0.5,0))*35%+IF(U74="已完成",1,IF(U74="进行中",0.5,0))*30%+IF(Y74="已完成",1,IF(Y74="进行中",0.5,0))*20%) | AC74: =IF(G74="已完成","正常",IF(OR(G74="暂停",G74="挂起"),"暂停",IF(J74="","日期缺失",IF(J74<'项目驾驶舱'!$B$3,"已延期",IF(J74<='项目驾驶舱'!$B$3+7,"临近到期","正常")))))
A75: T072 | B75: 网上营业厅 | C75: 船舶预到优化（太仓） | D75: OCR识别 | E75: / | F75: 第一批次 | G75: =IF(OR(M75="挂起",M75="暂停",Q75="挂起",Q75="暂停",U75="挂起",U75="暂停",Y75="挂起",Y75="暂停"),"暂停","已完成") | H75: =IF(L75<>"",L75,IF(P75<>"",P75,IF(T75<>"",T75,X75))) | I75: =IF(COUNT(N75,R75,V75,Z75)=0,"",MIN(N75,R75,V75,Z75)) | J75: =IF(ISNUMBER(K75),K75,IF(COUNT(O75,S75,W75,AA75)=0,"",MAX(O75,S75,W75,AA75))) | K75: / | L75: 郑士旺 | M75: 已完成 | N75: 46202 | O75: 46206 | P75: 石军磊、刘凯 | Q75: 已完成 | R75: 46209 | S75: 46225 | T75: 贺航 | U75: 已完成 | V75: 46209 | W75: 46225 | X75: 袁丽荣 | Y75: 已完成 | Z75: 46216 | AA75: 46234 | AB75: =(IF(M75="已完成",1,IF(M75="进行中",0.5,0))*15%+IF(Q75="已完成",1,IF(Q75="进行中",0.5,0))*35%+IF(U75="已完成",1,IF(U75="进行中",0.5,0))*30%+IF(Y75="已完成",1,IF(Y75="进行中",0.5,0))*20%) | AC75: =IF(G75="已完成","正常",IF(OR(G75="暂停",G75="挂起"),"暂停",IF(J75="","日期缺失",IF(J75<'项目驾驶舱'!$B$3,"已延期",IF(J75<='项目驾驶舱'!$B$3+7,"临近到期","正常")))))
A76: T073 | B76: 网上营业厅 | C76: 采样作业信息录入 | D76: 采样作业信息录入新增 | E76: / | F76: 第一批次 | G76: =IF(OR(M76="挂起",M76="暂停",Q76="挂起",Q76="暂停",U76="挂起",U76="暂停",Y76="挂起",Y76="暂停"),"暂停","已完成") | H76: =IF(L76<>"",L76,IF(P76<>"",P76,IF(T76<>"",T76,X76))) | I76: =IF(COUNT(N76,R76,V76,Z76)=0,"",MIN(N76,R76,V76,Z76)) | J76: =IF(ISNUMBER(K76),K76,IF(COUNT(O76,S76,W76,AA76)=0,"",MAX(O76,S76,W76,AA76))) | K76: 46224 | L76: 郑士旺 | M76: 已完成 | N76: 46202 | O76: 46206 | P76: 石军磊、刘凯 | Q76: 已完成 | R76: 46227 | S76: 46227 | T76: 贺航 | U76: 已完成 | V76: 46227 | W76: 46227 | X76: 袁丽荣 | Y76: 已完成 | Z76: 46216 | AA76: 46234 | AB76: =(IF(M76="已完成",1,IF(M76="进行中",0.5,0))*15%+IF(Q76="已完成",1,IF(Q76="进行中",0.5,0))*35%+IF(U76="已完成",1,IF(U76="进行中",0.5,0))*30%+IF(Y76="已完成",1,IF(Y76="进行中",0.5,0))*20%) | AC76: =IF(G76="已完成","正常",IF(OR(G76="暂停",G76="挂起"),"暂停",IF(J76="","日期缺失",IF(J76<'项目驾驶舱'!$B$3,"已延期",IF(J76<='项目驾驶舱'!$B$3+7,"临近到期","正常")))))
A77: T074 | B77: 网上营业厅 | C77: 采样作业信息录入 | D77: 采样作业信息录入编辑 | E77: / | F77: 第一批次 | G77: =IF(OR(M77="挂起",M77="暂停",Q77="挂起",Q77="暂停",U77="挂起",U77="暂停",Y77="挂起",Y77="暂停"),"暂停","已完成") | H77: =IF(L77<>"",L77,IF(P77<>"",P77,IF(T77<>"",T77,X77))) | I77: =IF(COUNT(N77,R77,V77,Z77)=0,"",MIN(N77,R77,V77,Z77)) | J77: =IF(ISNUMBER(K77),K77,IF(COUNT(O77,S77,W77,AA77)=0,"",MAX(O77,S77,W77,AA77))) | K77: 46224 | L77: 郑士旺 | M77: 已完成 | N77: 46202 | O77: 46206 | P77: 石军磊、刘凯 | Q77: 已完成 | R77: 46227 | S77: 46227 | T77: 贺航 | U77: 已完成 | V77: 46227 | W77: 46227 | X77: 袁丽荣 | Y77: 已完成 | Z77: 46216 | AA77: 46234 | AB77: =(IF(M77="已完成",1,IF(M77="进行中",0.5,0))*15%+IF(Q77="已完成",1,IF(Q77="进行中",0.5,0))*35%+IF(U77="已完成",1,IF(U77="进行中",0.5,0))*30%+IF(Y77="已完成",1,IF(Y77="进行中",0.5,0))*20%) | AC77: =IF(G77="已完成","正常",IF(OR(G77="暂停",G77="挂起"),"暂停",IF(J77="","日期缺失",IF(J77<'项目驾驶舱'!$B$3,"已延期",IF(J77<='项目驾驶舱'!$B$3+7,"临近到期","正常")))))
A78: T075 | B78: 网上营业厅 | C78: 采样作业信息录入 | D78: 采样作业信息录入详情 | E78: / | F78: 第一批次 | G78: =IF(OR(M78="挂起",M78="暂停",Q78="挂起",Q78="暂停",U78="挂起",U78="暂停",Y78="挂起",Y78="暂停"),"暂停","已完成") | H78: =IF(L78<>"",L78,IF(P78<>"",P78,IF(T78<>"",T78,X78))) | I78: =IF(COUNT(N78,R78,V78,Z78)=0,"",MIN(N78,R78,V78,Z78)) | J78: =IF(ISNUMBER(K78),K78,IF(COUNT(O78,S78,W78,AA78)=0,"",MAX(O78,S78,W78,AA78))) | K78: 46224 | L78: 郑士旺 | M78: 已完成 | N78: 46202 | O78: 46206 | P78: 石军磊、刘凯 | Q78: 已完成 | R78: 46227 | S78: 46227 | T78: 贺航 | U78: 已完成 | V78: 46227 | W78: 46227 | X78: 袁丽荣 | Y78: 已完成 | Z78: 46216 | AA78: 46234 | AB78: =(IF(M78="已完成",1,IF(M78="进行中",0.5,0))*15%+IF(Q78="已完成",1,IF(Q78="进行中",0.5,0))*35%+IF(U78="已完成",1,IF(U78="进行中",0.5,0))*30%+IF(Y78="已完成",1,IF(Y78="进行中",0.5,0))*20%) | AC78: =IF(G78="已完成","正常",IF(OR(G78="暂停",G78="挂起"),"暂停",IF(J78="","日期缺失",IF(J78<'项目驾驶舱'!$B$3,"已延期",IF(J78<='项目驾驶舱'!$B$3+7,"临近到期","正常")))))
A79: T076 | B79: 网上营业厅 | C79: 采样作业信息录入 | D79: 采样作业信息录入删除 | E79: / | F79: 第一批次 | G79: =IF(OR(M79="挂起",M79="暂停",Q79="挂起",Q79="暂停",U79="挂起",U79="暂停",Y79="挂起",Y79="暂停"),"暂停","已完成") | H79: =IF(L79<>"",L79,IF(P79<>"",P79,IF(T79<>"",T79,X79))) | I79: =IF(COUNT(N79,R79,V79,Z79)=0,"",MIN(N79,R79,V79,Z79)) | J79: =IF(ISNUMBER(K79),K79,IF(COUNT(O79,S79,W79,AA79)=0,"",MAX(O79,S79,W79,AA79))) | K79: 46224 | L79: 郑士旺 | M79: 已完成 | N79: 46202 | O79: 46206 | P79: 石军磊、刘凯 | Q79: 已完成 | R79: 46227 | S79: 46227 | T79: 贺航 | U79: 已完成 | V79: 46227 | W79: 46227 | X79: 袁丽荣 | Y79: 已完成 | Z79: 46216 | AA79: 46234 | AB79: =(IF(M79="已完成",1,IF(M79="进行中",0.5,0))*15%+IF(Q79="已完成",1,IF(Q79="进行中",0.5,0))*35%+IF(U79="已完成",1,IF(U79="进行中",0.5,0))*30%+IF(Y79="已完成",1,IF(Y79="进行中",0.5,0))*20%) | AC79: =IF(G79="已完成","正常",IF(OR(G79="暂停",G79="挂起"),"暂停",IF(J79="","日期缺失",IF(J79<'项目驾驶舱'!$B$3,"已延期",IF(J79<='项目驾驶舱'!$B$3+7,"临近到期","正常")))))
A80: T077 | B80: 网上营业厅 | C80: 采样作业信息录入 | D80: 采样作业信息录入列表 | E80: / | F80: 第一批次 | G80: =IF(OR(M80="挂起",M80="暂停",Q80="挂起",Q80="暂停",U80="挂起",U80="暂停",Y80="挂起",Y80="暂停"),"暂停","已完成") | H80: =IF(L80<>"",L80,IF(P80<>"",P80,IF(T80<>"",T80,X80))) | I80: =IF(COUNT(N80,R80,V80,Z80)=0,"",MIN(N80,R80,V80,Z80)) | J80: =IF(ISNUMBER(K80),K80,IF(COUNT(O80,S80,W80,AA80)=0,"",MAX(O80,S80,W80,AA80))) | K80: 46224 | L80: 郑士旺 | M80: 已完成 | N80: 46202 | O80: 46206 | P80: 石军磊、刘凯 | Q80: 已完成 | R80: 46227 | S80: 46227 | T80: 贺航 | U80: 已完成 | V80: 46227 | W80: 46227 | X80: 袁丽荣 | Y80: 已完成 | Z80: 46216 | AA80: 46234 | AB80: =(IF(M80="已完成",1,IF(M80="进行中",0.5,0))*15%+IF(Q80="已完成",1,IF(Q80="进行中",0.5,0))*35%+IF(U80="已完成",1,IF(U80="进行中",0.5,0))*30%+IF(Y80="已完成",1,IF(Y80="进行中",0.5,0))*20%) | AC80: =IF(G80="已完成","正常",IF(OR(G80="暂停",G80="挂起"),"暂停",IF(J80="","日期缺失",IF(J80<'项目驾驶舱'!$B$3,"已延期",IF(J80<='项目驾驶舱'!$B$3+7,"临近到期","正常")))))
A81: T078 | B81: 费用结算 | C81: 费用合同签订校验 | D81: 业务数据合同签订校验 | E81: / | F81: 第二批次 | G81: =IF(OR(M81="挂起",M81="暂停",Q81="挂起",Q81="暂停",U81="挂起",U81="暂停",Y81="挂起",Y81="暂停"),"暂停","未开始") | H81: =IF(L81<>"",L81,IF(P81<>"",P81,IF(T81<>"",T81,X81))) | I81: =IF(COUNT(N81,R81,V81,Z81)=0,"",MIN(N81,R81,V81,Z81)) | J81: =IF(ISNUMBER(K81),K81,IF(COUNT(O81,S81,W81,AA81)=0,"",MAX(O81,S81,W81,AA81))) | L81: 郑士旺 | M81: 未开始 | N81: 46223 | O81: 46227 | P81: 石军磊、刘凯 | Q81: 未开始 | R81: 46307 | S81: 46339 | T81: 贺航 | U81: 未开始 | V81: 46307 | W81: 46339 | X81: 袁丽荣 | Y81: 未开始 | Z81: 46307 | AA81: 46318 | AB81: =(IF(M81="已完成",1,IF(M81="进行中",0.5,0))*15%+IF(Q81="已完成",1,IF(Q81="进行中",0.5,0))*35%+IF(U81="已完成",1,IF(U81="进行中",0.5,0))*30%+IF(Y81="已完成",1,IF(Y81="进行中",0.5,0))*20%) | AC81: =IF(G81="已完成","正常",IF(OR(G81="暂停",G81="挂起"),"暂停",IF(J81="","日期缺失",IF(J81<'项目驾驶舱'!$B$3,"已延期",IF(J81<='项目驾驶舱'!$B$3+7,"临近到期","正常")))))
A82: T079 | B82: 费用结算 | C82: 费用合同签订校验 | D82: 结算数据合同签订校验 | E82: / | F82: 第二批次 | G82: =IF(OR(M82="挂起",M82="暂停",Q82="挂起",Q82="暂停",U82="挂起",U82="暂停",Y82="挂起",Y82="暂停"),"暂停","未开始") | H82: =IF(L82<>"",L82,IF(P82<>"",P82,IF(T82<>"",T82,X82))) | I82: =IF(COUNT(N82,R82,V82,Z82)=0,"",MIN(N82,R82,V82,Z82)) | J82: =IF(ISNUMBER(K82),K82,IF(COUNT(O82,S82,W82,AA82)=0,"",MAX(O82,S82,W82,AA82))) | L82: 郑士旺 | M82: 未开始 | N82: 46223 | O82: 46227 | P82: 石军磊、刘凯 | Q82: 未开始 | R82: 46307 | S82: 46339 | T82: 贺航 | U82: 未开始 | V82: 46307 | W82: 46339 | X82: 袁丽荣 | Y82: 未开始 | Z82: 46307 | AA82: 46318 | AB82: =(IF(M82="已完成",1,IF(M82="进行中",0.5,0))*15%+IF(Q82="已完成",1,IF(Q82="进行中",0.5,0))*35%+IF(U82="已完成",1,IF(U82="进行中",0.5,0))*30%+IF(Y82="已完成",1,IF(Y82="进行中",0.5,0))*20%) | AC82: =IF(G82="已完成","正常",IF(OR(G82="暂停",G82="挂起"),"暂停",IF(J82="","日期缺失",IF(J82<'项目驾驶舱'!$B$3,"已延期",IF(J82<='项目驾驶舱'!$B$3+7,"临近到期","正常")))))
A83: T080 | B83: 费用结算 | C83: 费用合同签订校验 | D83: 合同校验结果查询 | E83: / | F83: 第二批次 | G83: =IF(OR(M83="挂起",M83="暂停",Q83="挂起",Q83="暂停",U83="挂起",U83="暂停",Y83="挂起",Y83="暂停"),"暂停","未开始") | H83: =IF(L83<>"",L83,IF(P83<>"",P83,IF(T83<>"",T83,X83))) | I83: =IF(COUNT(N83,R83,V83,Z83)=0,"",MIN(N83,R83,V83,Z83)) | J83: =IF(ISNUMBER(K83),K83,IF(COUNT(O83,S83,W83,AA83)=0,"",MAX(O83,S83,W83,AA83))) | K83: 46261 | L83: 郑士旺 | M83: 未开始 | N83: 46223 | O83: 46227 | P83: 石军磊、刘凯 | Q83: 未开始 | R83: 46307 | S83: 46339 | T83: 贺航 | U83: 未开始 | V83: 46307 | W83: 46339 | X83: 袁丽荣 | Y83: 未开始 | Z83: 46307 | AA83: 46318 | AB83: =(IF(M83="已完成",1,IF(M83="进行中",0.5,0))*15%+IF(Q83="已完成",1,IF(Q83="进行中",0.5,0))*35%+IF(U83="已完成",1,IF(U83="进行中",0.5,0))*30%+IF(Y83="已完成",1,IF(Y83="进行中",0.5,0))*20%) | AC83: =IF(G83="已完成","正常",IF(OR(G83="暂停",G83="挂起"),"暂停",IF(J83="","日期缺失",IF(J83<'项目驾驶舱'!$B$3,"已延期",IF(J83<='项目驾驶舱'!$B$3+7,"临近到期","正常")))))
A84: T081 | B84: 费用结算 | C84: 停泊费（外贸） | D84: 数据对接 | E84: / | F84: 第二批次 | G84: =IF(OR(M84="挂起",M84="暂停",Q84="挂起",Q84="暂停",U84="挂起",U84="暂停",Y84="挂起",Y84="暂停"),"暂停","未开始") | H84: =IF(L84<>"",L84,IF(P84<>"",P84,IF(T84<>"",T84,X84))) | I84: =IF(COUNT(N84,R84,V84,Z84)=0,"",MIN(N84,R84,V84,Z84)) | J84: =IF(ISNUMBER(K84),K84,IF(COUNT(O84,S84,W84,AA84)=0,"",MAX(O84,S84,W84,AA84))) | L84: 郑士旺 | M84: 未开始 | N84: 46230 | O84: 46241 | P84: 石军磊、刘凯 | Q84: 未开始 | R84: 46307 | S84: 46339 | T84: 贺航 | U84: 未开始 | V84: 46307 | W84: 46339 | X84: 袁丽荣 | Y84: 未开始 | Z84: 46342 | AA84: 46353 | AB84: =(IF(M84="已完成",1,IF(M84="进行中",0.5,0))*15%+IF(Q84="已完成",1,IF(Q84="进行中",0.5,0))*35%+IF(U84="已完成",1,IF(U84="进行中",0.5,0))*30%+IF(Y84="已完成",1,IF(Y84="进行中",0.5,0))*20%) | AC84: =IF(G84="已完成","正常",IF(OR(G84="暂停",G84="挂起"),"暂停",IF(J84="","日期缺失",IF(J84<'项目驾驶舱'!$B$3,"已延期",IF(J84<='项目驾驶舱'!$B$3+7,"临近到期","正常")))))
A85: T082 | B85: 费用结算 | C85: 停泊费（外贸） | D85: 数据展示 | E85: / | F85: 第二批次 | G85: =IF(OR(M85="挂起",M85="暂停",Q85="挂起",Q85="暂停",U85="挂起",U85="暂停",Y85="挂起",Y85="暂停"),"暂停","未开始") | H85: =IF(L85<>"",L85,IF(P85<>"",P85,IF(T85<>"",T85,X85))) | I85: =IF(COUNT(N85,R85,V85,Z85)=0,"",MIN(N85,R85,V85,Z85)) | J85: =IF(ISNUMBER(K85),K85,IF(COUNT(O85,S85,W85,AA85)=0,"",MAX(O85,S85,W85,AA85))) | K85: 46224 | L85: 郑士旺 | M85: 未开始 | N85: 46230 | O85: 46241 | P85: 石军磊、刘凯 | Q85: 未开始 | R85: 46307 | S85: 46339 | T85: 贺航 | U85: 未开始 | V85: 46307 | W85: 46339 | X85: 袁丽荣 | Y85: 未开始 | Z85: 46342 | AA85: 46353 | AB85: =(IF(M85="已完成",1,IF(M85="进行中",0.5,0))*15%+IF(Q85="已完成",1,IF(Q85="进行中",0.5,0))*35%+IF(U85="已完成",1,IF(U85="进行中",0.5,0))*30%+IF(Y85="已完成",1,IF(Y85="进行中",0.5,0))*20%) | AC85: =IF(G85="已完成","正常",IF(OR(G85="暂停",G85="挂起"),"暂停",IF(J85="","日期缺失",IF(J85<'项目驾驶舱'!$B$3,"已延期",IF(J85<='项目驾驶舱'!$B$3+7,"临近到期","正常")))))
A86: T083 | B86: 费用结算 | C86: 锚泊费（外贸） | D86: 数据对接 | E86: / | F86: 第二批次 | G86: =IF(OR(M86="挂起",M86="暂停",Q86="挂起",Q86="暂停",U86="挂起",U86="暂停",Y86="挂起",Y86="暂停"),"暂停","未开始") | H86: =IF(L86<>"",L86,IF(P86<>"",P86,IF(T86<>"",T86,X86))) | I86: =IF(COUNT(N86,R86,V86,Z86)=0,"",MIN(N86,R86,V86,Z86)) | J86: =IF(ISNUMBER(K86),K86,IF(COUNT(O86,S86,W86,AA86)=0,"",MAX(O86,S86,W86,AA86))) | K86: 46224 | L86: 郑士旺 | M86: 未开始 | N86: 46230 | O86: 46241 | P86: 石军磊、刘凯 | Q86: 未开始 | R86: 46307 | S86: 46339 | T86: 贺航 | U86: 未开始 | V86: 46307 | W86: 46339 | X86: 袁丽荣 | Y86: 未开始 | Z86: 46342 | AA86: 46353 | AB86: =(IF(M86="已完成",1,IF(M86="进行中",0.5,0))*15%+IF(Q86="已完成",1,IF(Q86="进行中",0.5,0))*35%+IF(U86="已完成",1,IF(U86="进行中",0.5,0))*30%+IF(Y86="已完成",1,IF(Y86="进行中",0.5,0))*20%) | AC86: =IF(G86="已完成","正常",IF(OR(G86="暂停",G86="挂起"),"暂停",IF(J86="","日期缺失",IF(J86<'项目驾驶舱'!$B$3,"已延期",IF(J86<='项目驾驶舱'!$B$3+7,"临近到期","正常")))))
A87: T084 | B87: 费用结算 | C87: 锚泊费（外贸） | D87: 数据产生 | E87: / | F87: 第二批次 | G87: =IF(OR(M87="挂起",M87="暂停",Q87="挂起",Q87="暂停",U87="挂起",U87="暂停",Y87="挂起",Y87="暂停"),"暂停","未开始") | H87: =IF(L87<>"",L87,IF(P87<>"",P87,IF(T87<>"",T87,X87))) | I87: =IF(COUNT(N87,R87,V87,Z87)=0,"",MIN(N87,R87,V87,Z87)) | J87: =IF(ISNUMBER(K87),K87,IF(COUNT(O87,S87,W87,AA87)=0,"",MAX(O87,S87,W87,AA87))) | K87: 46224 | L87: 郑士旺 | M87: 未开始 | N87: 46230 | O87: 46241 | P87: 石军磊、刘凯 | Q87: 未开始 | R87: 46307 | S87: 46339 | T87: 贺航 | U87: 未开始 | V87: 46307 | W87: 46339 | X87: 袁丽荣 | Y87: 未开始 | Z87: 46342 | AA87: 46353 | AB87: =(IF(M87="已完成",1,IF(M87="进行中",0.5,0))*15%+IF(Q87="已完成",1,IF(Q87="进行中",0.5,0))*35%+IF(U87="已完成",1,IF(U87="进行中",0.5,0))*30%+IF(Y87="已完成",1,IF(Y87="进行中",0.5,0))*20%) | AC87: =IF(G87="已完成","正常",IF(OR(G87="暂停",G87="挂起"),"暂停",IF(J87="","日期缺失",IF(J87<'项目驾驶舱'!$B$3,"已延期",IF(J87<='项目驾驶舱'!$B$3+7,"临近到期","正常")))))
A88: T085 | B88: 费用结算 | C88: 堆存费（外贸） | D88: 数据对接 | E88: / | F88: 第二批次 | G88: =IF(OR(M88="挂起",M88="暂停",Q88="挂起",Q88="暂停",U88="挂起",U88="暂停",Y88="挂起",Y88="暂停"),"暂停","未开始") | H88: =IF(L88<>"",L88,IF(P88<>"",P88,IF(T88<>"",T88,X88))) | I88: =IF(COUNT(N88,R88,V88,Z88)=0,"",MIN(N88,R88,V88,Z88)) | J88: =IF(ISNUMBER(K88),K88,IF(COUNT(O88,S88,W88,AA88)=0,"",MAX(O88,S88,W88,AA88))) | K88: 46224 | L88: 郑士旺 | M88: 未开始 | N88: 46230 | O88: 46241 | P88: 石军磊、刘凯 | Q88: 未开始 | R88: 46307 | S88: 46339 | T88: 贺航 | U88: 未开始 | V88: 46307 | W88: 46339 | X88: 袁丽荣 | Y88: 未开始 | Z88: 46342 | AA88: 46353 | AB88: =(IF(M88="已完成",1,IF(M88="进行中",0.5,0))*15%+IF(Q88="已完成",1,IF(Q88="进行中",0.5,0))*35%+IF(U88="已完成",1,IF(U88="进行中",0.5,0))*30%+IF(Y88="已完成",1,IF(Y88="进行中",0.5,0))*20%) | AC88: =IF(G88="已完成","正常",IF(OR(G88="暂停",G88="挂起"),"暂停",IF(J88="","日期缺失",IF(J88<'项目驾驶舱'!$B$3,"已延期",IF(J88<='项目驾驶舱'!$B$3+7,"临近到期","正常")))))
A89: T086 | B89: 费用结算 | C89: 堆存费（外贸） | D89: 数据展示 | E89: / | F89: 第二批次 | G89: =IF(OR(M89="挂起",M89="暂停",Q89="挂起",Q89="暂停",U89="挂起",U89="暂停",Y89="挂起",Y89="暂停"),"暂停","未开始") | H89: =IF(L89<>"",L89,IF(P89<>"",P89,IF(T89<>"",T89,X89))) | I89: =IF(COUNT(N89,R89,V89,Z89)=0,"",MIN(N89,R89,V89,Z89)) | J89: =IF(ISNUMBER(K89),K89,IF(COUNT(O89,S89,W89,AA89)=0,"",MAX(O89,S89,W89,AA89))) | K89: 46224 | L89: 郑士旺 | M89: 未开始 | N89: 46230 | O89: 46241 | P89: 石军磊、刘凯 | Q89: 未开始 | R89: 46307 | S89: 46339 | T89: 贺航 | U89: 未开始 | V89: 46307 | W89: 46339 | X89: 袁丽荣 | Y89: 未开始 | Z89: 46342 | AA89: 46353 | AB89: =(IF(M89="已完成",1,IF(M89="进行中",0.5,0))*15%+IF(Q89="已完成",1,IF(Q89="进行中",0.5,0))*35%+IF(U89="已完成",1,IF(U89="进行中",0.5,0))*30%+IF(Y89="已完成",1,IF(Y89="进行中",0.5,0))*20%) | AC89: =IF(G89="已完成","正常",IF(OR(G89="暂停",G89="挂起"),"暂停",IF(J89="","日期缺失",IF(J89<'项目驾驶舱'!$B$3,"已延期",IF(J89<='项目驾驶舱'!$B$3+7,"临近到期","正常")))))
A90: T087 | B90: 费用结算 | C90: 卸船费（外贸） | D90: 数据对接 | E90: / | F90: 第二批次 | G90: =IF(OR(M90="挂起",M90="暂停",Q90="挂起",Q90="暂停",U90="挂起",U90="暂停",Y90="挂起",Y90="暂停"),"暂停","未开始") | H90: =IF(L90<>"",L90,IF(P90<>"",P90,IF(T90<>"",T90,X90))) | I90: =IF(COUNT(N90,R90,V90,Z90)=0,"",MIN(N90,R90,V90,Z90)) | J90: =IF(ISNUMBER(K90),K90,IF(COUNT(O90,S90,W90,AA90)=0,"",MAX(O90,S90,W90,AA90))) | K90: 46224 | L90: 郑士旺 | M90: 未开始 | N90: 46230 | O90: 46241 | P90: 石军磊、刘凯 | Q90: 未开始 | R90: 46307 | S90: 46339 | T90: 贺航 | U90: 未开始 | V90: 46307 | W90: 46339 | X90: 袁丽荣 | Y90: 未开始 | Z90: 46342 | AA90: 46353 | AB90: =(IF(M90="已完成",1,IF(M90="进行中",0.5,0))*15%+IF(Q90="已完成",1,IF(Q90="进行中",0.5,0))*35%+IF(U90="已完成",1,IF(U90="进行中",0.5,0))*30%+IF(Y90="已完成",1,IF(Y90="进行中",0.5,0))*20%) | AC90: =IF(G90="已完成","正常",IF(OR(G90="暂停",G90="挂起"),"暂停",IF(J90="","日期缺失",IF(J90<'项目驾驶舱'!$B$3,"已延期",IF(J90<='项目驾驶舱'!$B$3+7,"临近到期","正常")))))
A91: T088 | B91: 费用结算 | C91: 卸船费（外贸） | D91: 数据展示 | E91: / | F91: 第二批次 | G91: =IF(OR(M91="挂起",M91="暂停",Q91="挂起",Q91="暂停",U91="挂起",U91="暂停",Y91="挂起",Y91="暂停"),"暂停","未开始") | H91: =IF(L91<>"",L91,IF(P91<>"",P91,IF(T91<>"",T91,X91))) | I91: =IF(COUNT(N91,R91,V91,Z91)=0,"",MIN(N91,R91,V91,Z91)) | J91: =IF(ISNUMBER(K91),K91,IF(COUNT(O91,S91,W91,AA91)=0,"",MAX(O91,S91,W91,AA91))) | L91: 郑士旺 | M91: 未开始 | N91: 46230 | O91: 46241 | P91: 石军磊、刘凯 | Q91: 未开始 | R91: 46307 | S91: 46339 | T91: 贺航 | U91: 未开始 | V91: 46307 | W91: 46339 | X91: 袁丽荣 | Y91: 未开始 | Z91: 46342 | AA91: 46353 | AB91: =(IF(M91="已完成",1,IF(M91="进行中",0.5,0))*15%+IF(Q91="已完成",1,IF(Q91="进行中",0.5,0))*35%+IF(U91="已完成",1,IF(U91="进行中",0.5,0))*30%+IF(Y91="已完成",1,IF(Y91="进行中",0.5,0))*20%) | AC91: =IF(G91="已完成","正常",IF(OR(G91="暂停",G91="挂起"),"暂停",IF(J91="","日期缺失",IF(J91<'项目驾驶舱'!$B$3,"已延期",IF(J91<='项目驾驶舱'!$B$3+7,"临近到期","正常")))))
A92: T089 | B92: 费用结算 | C92: 采样服务费（外贸） | D92: 新增采样服务费（外贸） | E92: / | F92: 第二批次 | G92: =IF(OR(M92="挂起",M92="暂停",Q92="挂起",Q92="暂停",U92="挂起",U92="暂停",Y92="挂起",Y92="暂停"),"暂停","未开始") | H92: =IF(L92<>"",L92,IF(P92<>"",P92,IF(T92<>"",T92,X92))) | I92: =IF(COUNT(N92,R92,V92,Z92)=0,"",MIN(N92,R92,V92,Z92)) | J92: =IF(ISNUMBER(K92),K92,IF(COUNT(O92,S92,W92,AA92)=0,"",MAX(O92,S92,W92,AA92))) | L92: 郑士旺 | M92: 未开始 | N92: 46230 | O92: 46241 | P92: 石军磊、刘凯 | Q92: 未开始 | R92: 46307 | S92: 46339 | T92: 贺航 | U92: 未开始 | V92: 46307 | W92: 46339 | X92: 袁丽荣 | Y92: 未开始 | Z92: 46342 | AA92: 46353 | AB92: =(IF(M92="已完成",1,IF(M92="进行中",0.5,0))*15%+IF(Q92="已完成",1,IF(Q92="进行中",0.5,0))*35%+IF(U92="已完成",1,IF(U92="进行中",0.5,0))*30%+IF(Y92="已完成",1,IF(Y92="进行中",0.5,0))*20%) | AC92: =IF(G92="已完成","正常",IF(OR(G92="暂停",G92="挂起"),"暂停",IF(J92="","日期缺失",IF(J92<'项目驾驶舱'!$B$3,"已延期",IF(J92<='项目驾驶舱'!$B$3+7,"临近到期","正常")))))
A93: T090 | B93: 费用结算 | C93: 采样服务费（外贸） | D93: 审批采样服务费（外贸） | E93: / | F93: 第二批次 | G93: =IF(OR(M93="挂起",M93="暂停",Q93="挂起",Q93="暂停",U93="挂起",U93="暂停",Y93="挂起",Y93="暂停"),"暂停","未开始") | H93: =IF(L93<>"",L93,IF(P93<>"",P93,IF(T93<>"",T93,X93))) | I93: =IF(COUNT(N93,R93,V93,Z93)=0,"",MIN(N93,R93,V93,Z93)) | J93: =IF(ISNUMBER(K93),K93,IF(COUNT(O93,S93,W93,AA93)=0,"",MAX(O93,S93,W93,AA93))) | L93: 郑士旺 | M93: 未开始 | N93: 46230 | O93: 46241 | P93: 石军磊、刘凯 | Q93: 未开始 | R93: 46307 | S93: 46339 | T93: 贺航 | U93: 未开始 | V93: 46307 | W93: 46339 | X93: 袁丽荣 | Y93: 未开始 | Z93: 46342 | AA93: 46353 | AB93: =(IF(M93="已完成",1,IF(M93="进行中",0.5,0))*15%+IF(Q93="已完成",1,IF(Q93="进行中",0.5,0))*35%+IF(U93="已完成",1,IF(U93="进行中",0.5,0))*30%+IF(Y93="已完成",1,IF(Y93="进行中",0.5,0))*20%) | AC93: =IF(G93="已完成","正常",IF(OR(G93="暂停",G93="挂起"),"暂停",IF(J93="","日期缺失",IF(J93<'项目驾驶舱'!$B$3,"已延期",IF(J93<='项目驾驶舱'!$B$3+7,"临近到期","正常")))))
A94: T091 | B94: 费用结算 | C94: 采样服务费（外贸） | D94: 单据签章 | E94: / | F94: 第二批次 | G94: =IF(OR(M94="挂起",M94="暂停",Q94="挂起",Q94="暂停",U94="挂起",U94="暂停",Y94="挂起",Y94="暂停"),"暂停","未开始") | H94: =IF(L94<>"",L94,IF(P94<>"",P94,IF(T94<>"",T94,X94))) | I94: =IF(COUNT(N94,R94,V94,Z94)=0,"",MIN(N94,R94,V94,Z94)) | J94: =IF(ISNUMBER(K94),K94,IF(COUNT(O94,S94,W94,AA94)=0,"",MAX(O94,S94,W94,AA94))) | L94: 郑士旺 | M94: 未开始 | N94: 46230 | O94: 46241 | P94: 石军磊、刘凯 | Q94: 未开始 | R94: 46307 | S94: 46339 | T94: 贺航 | U94: 未开始 | V94: 46307 | W94: 46339 | X94: 袁丽荣 | Y94: 未开始 | Z94: 46342 | AA94: 46353 | AB94: =(IF(M94="已完成",1,IF(M94="进行中",0.5,0))*15%+IF(Q94="已完成",1,IF(Q94="进行中",0.5,0))*35%+IF(U94="已完成",1,IF(U94="进行中",0.5,0))*30%+IF(Y94="已完成",1,IF(Y94="进行中",0.5,0))*20%) | AC94: =IF(G94="已完成","正常",IF(OR(G94="暂停",G94="挂起"),"暂停",IF(J94="","日期缺失",IF(J94<'项目驾驶舱'!$B$3,"已延期",IF(J94<='项目驾驶舱'!$B$3+7,"临近到期","正常")))))
A95: T092 | B95: 费用结算 | C95: 采样服务费（外贸） | D95: 数据推送 | E95: / | F95: 第二批次 | G95: =IF(OR(M95="挂起",M95="暂停",Q95="挂起",Q95="暂停",U95="挂起",U95="暂停",Y95="挂起",Y95="暂停"),"暂停","未开始") | H95: =IF(L95<>"",L95,IF(P95<>"",P95,IF(T95<>"",T95,X95))) | I95: =IF(COUNT(N95,R95,V95,Z95)=0,"",MIN(N95,R95,V95,Z95)) | J95: =IF(ISNUMBER(K95),K95,IF(COUNT(O95,S95,W95,AA95)=0,"",MAX(O95,S95,W95,AA95))) | L95: 郑士旺 | M95: 未开始 | N95: 46230 | O95: 46241 | P95: 石军磊、刘凯 | Q95: 未开始 | R95: 46307 | S95: 46339 | T95: 贺航 | U95: 未开始 | V95: 46307 | W95: 46339 | X95: 袁丽荣 | Y95: 未开始 | Z95: 46342 | AA95: 46353 | AB95: =(IF(M95="已完成",1,IF(M95="进行中",0.5,0))*15%+IF(Q95="已完成",1,IF(Q95="进行中",0.5,0))*35%+IF(U95="已完成",1,IF(U95="进行中",0.5,0))*30%+IF(Y95="已完成",1,IF(Y95="进行中",0.5,0))*20%) | AC95: =IF(G95="已完成","正常",IF(OR(G95="暂停",G95="挂起"),"暂停",IF(J95="","日期缺失",IF(J95<'项目驾驶舱'!$B$3,"已延期",IF(J95<='项目驾驶舱'!$B$3+7,"临近到期","正常")))))
A96: T093 | B96: 费用结算 | C96: 船舶供应服务费（外贸） | D96: 数据对接 | E96: / | F96: 第二批次 | G96: =IF(OR(M96="挂起",M96="暂停",Q96="挂起",Q96="暂停",U96="挂起",U96="暂停",Y96="挂起",Y96="暂停"),"暂停","未开始") | H96: =IF(L96<>"",L96,IF(P96<>"",P96,IF(T96<>"",T96,X96))) | I96: =IF(COUNT(N96,R96,V96,Z96)=0,"",MIN(N96,R96,V96,Z96)) | J96: =IF(ISNUMBER(K96),K96,IF(COUNT(O96,S96,W96,AA96)=0,"",MAX(O96,S96,W96,AA96))) | L96: 郑士旺 | M96: 未开始 | N96: 46230 | O96: 46241 | P96: 石军磊、刘凯 | Q96: 未开始 | R96: 46307 | S96: 46339 | T96: 贺航 | U96: 未开始 | V96: 46307 | W96: 46339 | X96: 袁丽荣 | Y96: 未开始 | Z96: 46342 | AA96: 46353 | AB96: =(IF(M96="已完成",1,IF(M96="进行中",0.5,0))*15%+IF(Q96="已完成",1,IF(Q96="进行中",0.5,0))*35%+IF(U96="已完成",1,IF(U96="进行中",0.5,0))*30%+IF(Y96="已完成",1,IF(Y96="进行中",0.5,0))*20%) | AC96: =IF(G96="已完成","正常",IF(OR(G96="暂停",G96="挂起"),"暂停",IF(J96="","日期缺失",IF(J96<'项目驾驶舱'!$B$3,"已延期",IF(J96<='项目驾驶舱'!$B$3+7,"临近到期","正常")))))
A97: T094 | B97: 费用结算 | C97: 船舶供应服务费（外贸） | D97: 数据展示 | E97: / | F97: 第二批次 | G97: =IF(OR(M97="挂起",M97="暂停",Q97="挂起",Q97="暂停",U97="挂起",U97="暂停",Y97="挂起",Y97="暂停"),"暂停","未开始") | H97: =IF(L97<>"",L97,IF(P97<>"",P97,IF(T97<>"",T97,X97))) | I97: =IF(COUNT(N97,R97,V97,Z97)=0,"",MIN(N97,R97,V97,Z97)) | J97: =IF(ISNUMBER(K97),K97,IF(COUNT(O97,S97,W97,AA97)=0,"",MAX(O97,S97,W97,AA97))) | L97: 郑士旺 | M97: 未开始 | N97: 46230 | O97: 46241 | P97: 石军磊、刘凯 | Q97: 未开始 | R97: 46307 | S97: 46339 | T97: 贺航 | U97: 未开始 | V97: 46307 | W97: 46339 | X97: 袁丽荣 | Y97: 未开始 | Z97: 46342 | AA97: 46353 | AB97: =(IF(M97="已完成",1,IF(M97="进行中",0.5,0))*15%+IF(Q97="已完成",1,IF(Q97="进行中",0.5,0))*35%+IF(U97="已完成",1,IF(U97="进行中",0.5,0))*30%+IF(Y97="已完成",1,IF(Y97="进行中",0.5,0))*20%) | AC97: =IF(G97="已完成","正常",IF(OR(G97="暂停",G97="挂起"),"暂停",IF(J97="","日期缺失",IF(J97<'项目驾驶舱'!$B$3,"已延期",IF(J97<='项目驾驶舱'!$B$3+7,"临近到期","正常")))))
A98: T095 | B98: 费用结算 | C98: 堆存费优化（太仓） | D98: 自动生成堆存费 | E98: / | F98: 第一批次 | G98: =IF(OR(M98="挂起",M98="暂停",Q98="挂起",Q98="暂停",U98="挂起",U98="暂停",Y98="挂起",Y98="暂停"),"暂停","进行中") | H98: =IF(L98<>"",L98,IF(P98<>"",P98,IF(T98<>"",T98,X98))) | I98: =IF(COUNT(N98,R98,V98,Z98)=0,"",MIN(N98,R98,V98,Z98)) | J98: =IF(ISNUMBER(K98),K98,IF(COUNT(O98,S98,W98,AA98)=0,"",MAX(O98,S98,W98,AA98))) | L98: 郑士旺 | M98: 已完成 | N98: 46202 | O98: 46206 | P98: 常浩 | Q98: 进行中 | R98: 46209 | S98: 46225 | T98: 常浩 | U98: 进行中 | V98: 46209 | W98: 46225 | X98: 袁丽荣 | Y98: 未开始 | Z98: 46216 | AA98: 46234 | AB98: =(IF(M98="已完成",1,IF(M98="进行中",0.5,0))*15%+IF(Q98="已完成",1,IF(Q98="进行中",0.5,0))*35%+IF(U98="已完成",1,IF(U98="进行中",0.5,0))*30%+IF(Y98="已完成",1,IF(Y98="进行中",0.5,0))*20%) | AC98: =IF(G98="已完成","正常",IF(OR(G98="暂停",G98="挂起"),"暂停",IF(J98="","日期缺失",IF(J98<'项目驾驶舱'!$B$3,"已延期",IF(J98<='项目驾驶舱'!$B$3+7,"临近到期","正常")))))
A99: T096 | B99: 费用结算 | C99: 港杂费优化(太仓） | D99: 自动生成装船港杂费 | E99: / | F99: 第一批次 | G99: =IF(OR(M99="挂起",M99="暂停",Q99="挂起",Q99="暂停",U99="挂起",U99="暂停",Y99="挂起",Y99="暂停"),"暂停","已完成") | H99: =IF(L99<>"",L99,IF(P99<>"",P99,IF(T99<>"",T99,X99))) | I99: =IF(COUNT(N99,R99,V99,Z99)=0,"",MIN(N99,R99,V99,Z99)) | J99: =IF(ISNUMBER(K99),K99,IF(COUNT(O99,S99,W99,AA99)=0,"",MAX(O99,S99,W99,AA99))) | K99: 46261 | L99: 郑士旺 | M99: 已完成 | N99: 46202 | O99: 46206 | P99: 石军磊、刘凯 | Q99: 已完成 | R99: 46209 | S99: 46225 | T99: 贺航 | U99: 已完成 | V99: 46209 | W99: 46225 | X99: 袁丽荣 | Y99: 已完成 | Z99: 46216 | AA99: 46234 | AB99: =(IF(M99="已完成",1,IF(M99="进行中",0.5,0))*15%+IF(Q99="已完成",1,IF(Q99="进行中",0.5,0))*35%+IF(U99="已完成",1,IF(U99="进行中",0.5,0))*30%+IF(Y99="已完成",1,IF(Y99="进行中",0.5,0))*20%) | AC99: =IF(G99="已完成","正常",IF(OR(G99="暂停",G99="挂起"),"暂停",IF(J99="","日期缺失",IF(J99<'项目驾驶舱'!$B$3,"已延期",IF(J99<='项目驾驶舱'!$B$3+7,"临近到期","正常")))))
A100: T097 | B100: 费用结算 | C100: 租赁费优化（太仓） | D100: 自动生成租赁费 | E100: / | F100: 第一批次 | G100: =IF(OR(M100="挂起",M100="暂停",Q100="挂起",Q100="暂停",U100="挂起",U100="暂停",Y100="挂起",Y100="暂停"),"暂停","已完成") | H100: =IF(L100<>"",L100,IF(P100<>"",P100,IF(T100<>"",T100,X100))) | I100: =IF(COUNT(N100,R100,V100,Z100)=0,"",MIN(N100,R100,V100,Z100)) | J100: =IF(ISNUMBER(K100),K100,IF(COUNT(O100,S100,W100,AA100)=0,"",MAX(O100,S100,W100,AA100))) | L100: 郑士旺 | M100: 已完成 | N100: 46202 | O100: 46206 | P100: 石军磊、刘凯 | Q100: 已完成 | R100: 46227 | S100: 46227 | T100: 贺航 | U100: 已完成 | V100: 46227 | W100: 46227 | X100: 袁丽荣 | Y100: 已完成 | Z100: 46216 | AA100: 46234 | AB100: =(IF(M100="已完成",1,IF(M100="进行中",0.5,0))*15%+IF(Q100="已完成",1,IF(Q100="进行中",0.5,0))*35%+IF(U100="已完成",1,IF(U100="进行中",0.5,0))*30%+IF(Y100="已完成",1,IF(Y100="进行中",0.5,0))*20%) | AC100: =IF(G100="已完成","正常",IF(OR(G100="暂停",G100="挂起"),"暂停",IF(J100="","日期缺失",IF(J100<'项目驾驶舱'!$B$3,"已延期",IF(J100<='项目驾驶舱'!$B$3+7,"临近到期","正常")))))
...

Sheet 里程碑计划
A1: 里程碑计划与阶段门管理
A3: 里程碑ID | B3: 里程碑名称 | C3: 批次 | D3: 验收/完成标准 | E3: 责任人 | F3: 计划日期 | G3: 状态 | H3: 实际日期 | I3: 偏差天数 | J3: 健康度 | K3: 说明
A4: M01 | B4: 第一批次业务设计完成 | C4: 第一批次 | D4: 第一批次业务设计状态全部完成 | E4: 郑士旺 | F4: 46241 | G4: 未开始 | I4: =IF(H4<>"",H4-F4,MAX(0,项目驾驶舱!$B$3-F4)) | J4: =IF(G4="已完成","绿",IF(F4<项目驾驶舱!$B$3,"红",IF(F4<=项目驾驶舱!$B$3+7,"黄","绿")))
A5: M02 | B5: 第一批次前后端开发完成 | C5: 第一批次 | D5: 第一批次前端、后端状态全部完成 | E5: 开发组 | F5: 46262 | G5: 未开始 | I5: =IF(H5<>"",H5-F5,MAX(0,项目驾驶舱!$B$3-F5)) | J5: =IF(G5="已完成","绿",IF(F5<项目驾驶舱!$B$3,"红",IF(F5<=项目驾驶舱!$B$3+7,"黄","绿")))
A6: M03 | B6: 第一批次测试完成 | C6: 第一批次 | D6: 第一批次测试状态全部完成且无阻断缺陷 | E6: 袁丽荣 | F6: 46318 | G6: 未开始 | I6: =IF(H6<>"",H6-F6,MAX(0,项目驾驶舱!$B$3-F6)) | J6: =IF(G6="已完成","绿",IF(F6<项目驾驶舱!$B$3,"红",IF(F6<=项目驾驶舱!$B$3+7,"黄","绿")))
A7: M04 | B7: 第一批次上线 | C7: 第一批次 | D7: 完成上线审批、部署及回归验证 | E7: 项目经理 | F7: 46261 | G7: 未开始 | I7: =IF(H7<>"",H7-F7,MAX(0,项目驾驶舱!$B$3-F7)) | J7: =IF(G7="已完成","绿",IF(F7<项目驾驶舱!$B$3,"红",IF(F7<=项目驾驶舱!$B$3+7,"黄","绿")))
A8: M05 | B8: 第二批次业务设计完成 | C8: 第二批次 | D8: 第二批次业务设计状态全部完成 | E8: 郑士旺 | F8: 46241 | G8: 未开始 | I8: =IF(H8<>"",H8-F8,MAX(0,项目驾驶舱!$B$3-F8)) | J8: =IF(G8="已完成","绿",IF(F8<项目驾驶舱!$B$3,"红",IF(F8<=项目驾驶舱!$B$3+7,"黄","绿")))
A9: M06 | B9: 第二批次前后端开发完成 | C9: 第二批次 | D9: 第二批次前端、后端状态全部完成 | E9: 开发组 | F9: 46339 | G9: 未开始 | I9: =IF(H9<>"",H9-F9,MAX(0,项目驾驶舱!$B$3-F9)) | J9: =IF(G9="已完成","绿",IF(F9<项目驾驶舱!$B$3,"红",IF(F9<=项目驾驶舱!$B$3+7,"黄","绿")))
A10: M07 | B10: 第二批次测试完成 | C10: 第二批次 | D10: 第二批次测试状态全部完成且无阻断缺陷 | E10: 袁丽荣 | F10: 46353 | G10: 未开始 | I10: =IF(H10<>"",H10-F10,MAX(0,项目驾驶舱!$B$3-F10)) | J10: =IF(G10="已完成","绿",IF(F10<项目驾驶舱!$B$3,"红",IF(F10<=项目驾驶舱!$B$3+7,"黄","绿")))
A11: M08 | B11: 第二批次上线 | C11: 第二批次 | D11: 完成上线审批、部署及回归验证 | E11: 项目经理 | F11: 46261 | G11: 未开始 | I11: =IF(H11<>"",H11-F11,MAX(0,项目驾驶舱!$B$3-F11)) | J11: =IF(G11="已完成","绿",IF(F11<项目驾驶舱!$B$3,"红",IF(F11<=项目驾驶舱!$B$3+7,"黄","绿")))
A12: M09 | B12: 外部系统集成联调完成 | C12: 全项目 | D12: 6个外部系统均完成联调确认 | E12: 集成负责人 | F12: 46346 | G12: 未开始 | I12: =IF(H12<>"",H12-F12,MAX(0,项目驾驶舱!$B$3-F12)) | J12: =IF(G12="已完成","绿",IF(F12<项目驾驶舱!$B$3,"红",IF(F12<=项目驾驶舱!$B$3+7,"黄","绿")))
A13: M10 | B13: 项目验收 | C13: 全项目 | D13: 完成用户验收并签署验收材料 | E13: 项目经理 | F13: 46356 | G13: 未开始 | I13: =IF(H13<>"",H13-F13,MAX(0,项目驾驶舱!$B$3-F13)) | J13: =IF(G13="已完成","绿",IF(F13<项目驾驶舱!$B$3,"红",IF(F13<=项目驾驶舱!$B$3+7,"黄","绿")))

Sheet 周迭代计划
A1: 周迭代计划与完成跟踪
A3: 迭代周 | B3: 开始日期 | C3: 结束日期 | D3: 功能设计 | E3: 前端开发 | F3: 后端开发 | G3: 功能测试 | H3: 本周完成率 | I3: 复盘说明
A4: 1 | B4: 46195 | C4: 46199 | D4: 装船计划编制及推送、卸船作业信息录入优化（太仓）、装船作业信息录入优化（太仓） | E4: 装船计划编制及推送、卸船作业信息录入优化（太仓）、装船作业信息录入优化（太仓） | F4: 装船计划编制及推送、卸船作业信息录入优化（太仓）、装船作业信息录入优化（太仓） | G4: / | H4: =IF(COUNTA(D4:G4)=0,0,(IF(AND(D4<>"",D4<>"/"),1,0)+IF(AND(E4<>"",E4<>"/"),1,0)+IF(AND(F4<>"",F4<>"/"),1,0)+IF(AND(G4<>"",G4<>"/"),1,0))/4)
A5: 2 | B5: 46202 | C5: 46206 | D5: 车辆信息维护、交易中心报单信息展示及应单入口、船舶轨迹跟踪、货权跟踪、货权提醒、船舶预到优化（太仓）、堆存费优化（太仓）、港杂费优化(太仓）、收费标准信息维护、采样方式信息维护、装卸费结算、租赁费结算、采样作业信息录入 | G5: 装船计划编制及推送、卸船作业信息录入优化（太仓）、装船作业信息录入优化（太仓） | H5: =IF(COUNTA(D5:G5)=0,0,(IF(AND(D5<>"",D5<>"/"),1,0)+IF(AND(E5<>"",E5<>"/"),1,0)+IF(AND(F5<>"",F5<>"/"),1,0)+IF(AND(G5<>"",G5<>"/"),1,0))/4)
A6: 3 | B6: 46209 | C6: 46213 | D6: 卸车流程跟踪、装船流程跟踪、卸船流程跟踪、行业资讯、统计分析 | E6: 车辆信息维护、交易中心报单信息展示及应单入口、船舶轨迹跟踪、货权跟踪、货权提醒、船舶预到优化（太仓）、堆存费优化（太仓）、港杂费优化(太仓）、收费标准信息维护、采样方式信息维护、装卸费结算、租赁费结算、采样作业信息录入 | F6: 车辆信息维护、交易中心报单信息展示及应单入口、船舶轨迹跟踪、货权跟踪、货权提醒、船舶预到优化（太仓）、堆存费优化（太仓）、港杂费优化(太仓）、收费标准信息维护、采样方式信息维护、装卸费结算、租赁费结算、采样作业信息录入 | H6: =IF(COUNTA(D6:G6)=0,0,(IF(AND(D6<>"",D6<>"/"),1,0)+IF(AND(E6<>"",E6<>"/"),1,0)+IF(AND(F6<>"",F6<>"/"),1,0)+IF(AND(G6<>"",G6<>"/"),1,0))/4)
A7: 4 | B7: 46216 | C7: 46220 | D7: APP：船舶供应服务查询、船舶预到（内贸）查询、台账查询、停泊费（内贸）查询、船舶供应服务费（内贸）查询 | G7: 车辆信息维护、交易中心报单信息展示及应单入口、船舶轨迹跟踪、货权跟踪、货权提醒、船舶预到优化（太仓）、堆存费优化（太仓）、港杂费优化（太仓）、收费标准信息维护、采样方式信息维护、装卸费结算、租赁费结算、采样作业信息录入 | H7: =IF(COUNTA(D7:G7)=0,0,(IF(AND(D7<>"",D7<>"/"),1,0)+IF(AND(E7<>"",E7<>"/"),1,0)+IF(AND(F7<>"",F7<>"/"),1,0)+IF(AND(G7<>"",G7<>"/"),1,0))/4)
A8: 5 | B8: 46223 | C8: 46227 | D8: 结算条款管理、协同视览、费用合同签订校验 | H8: =IF(COUNTA(D8:G8)=0,0,(IF(AND(D8<>"",D8<>"/"),1,0)+IF(AND(E8<>"",E8<>"/"),1,0)+IF(AND(F8<>"",F8<>"/"),1,0)+IF(AND(G8<>"",G8<>"/"),1,0))/4)
A9: 6 | B9: 46230 | C9: 46234 | D9: 船舶唯一性校验、卸船作业、船舶预到（外贸）、退回船舶预到（外贸）、采样申请（外贸）、停泊费（外贸）、锚泊费（外贸）、堆存费（外贸）、卸船费（外贸）、采样服务费（外贸）、船舶供应服务费（外贸） | E9: 卸车流程跟踪、装船流程跟踪、卸船流程跟踪、行业资讯、统计分析、自动报告 | F9: 卸车流程跟踪、装船流程跟踪、卸船流程跟踪、行业资讯、统计分析、自动报告 | H9: =IF(COUNTA(D9:G9)=0,0,(IF(AND(D9<>"",D9<>"/"),1,0)+IF(AND(E9<>"",E9<>"/"),1,0)+IF(AND(F9<>"",F9<>"/"),1,0)+IF(AND(G9<>"",G9<>"/"),1,0))/4)
A10: 7 | B10: 46237 | C10: 46241 | H10: =IF(COUNTA(D10:G10)=0,0,(IF(AND(D10<>"",D10<>"/"),1,0)+IF(AND(E10<>"",E10<>"/"),1,0)+IF(AND(F10<>"",F10<>"/"),1,0)+IF(AND(G10<>"",G10<>"/"),1,0))/4)
A11: 8 | B11: 46244 | C11: 46248 | H11: =IF(COUNTA(D11:G11)=0,0,(IF(AND(D11<>"",D11<>"/"),1,0)+IF(AND(E11<>"",E11<>"/"),1,0)+IF(AND(F11<>"",F11<>"/"),1,0)+IF(AND(G11<>"",G11<>"/"),1,0))/4)
A12: 9 | B12: 46251 | C12: 46255 | G12: 卸车流程跟踪、装船流程跟踪、卸船流程跟踪、行业资讯、统计分析、自动报告 | H12: =IF(COUNTA(D12:G12)=0,0,(IF(AND(D12<>"",D12<>"/"),1,0)+IF(AND(E12<>"",E12<>"/"),1,0)+IF(AND(F12<>"",F12<>"/"),1,0)+IF(AND(G12<>"",G12<>"/"),1,0))/4)
A13: 10 | B13: 46258 | C13: 46262 | H13: =IF(COUNTA(D13:G13)=0,0,(IF(AND(D13<>"",D13<>"/"),1,0)+IF(AND(E13<>"",E13<>"/"),1,0)+IF(AND(F13<>"",F13<>"/"),1,0)+IF(AND(G13<>"",G13<>"/"),1,0))/4)
A14: 11 | B14: 46265 | C14: 46269 | E14: APP：船舶供应服务查询、船舶预到（内贸）查询、台账查询、停泊费（内贸）查询、船舶供应服务费（内贸）查询 | F14: APP：船舶供应服务查询、船舶预到（内贸）查询、台账查询、停泊费（内贸）查询、船舶供应服务费（内贸）查询 | H14: =IF(COUNTA(D14:G14)=0,0,(IF(AND(D14<>"",D14<>"/"),1,0)+IF(AND(E14<>"",E14<>"/"),1,0)+IF(AND(F14<>"",F14<>"/"),1,0)+IF(AND(G14<>"",G14<>"/"),1,0))/4)
A15: 12 | B15: 46272 | C15: 46276 | E15: 结算条款管理、协同视览、费用合同签订校验 | F15: 结算条款管理、协同视览、费用合同签订校验 | G15: APP：船舶供应服务查询、船舶预到（内贸）查询、台账查询、停泊费（内贸）查询、船舶供应服务费（内贸）查询 | H15: =IF(COUNTA(D15:G15)=0,0,(IF(AND(D15<>"",D15<>"/"),1,0)+IF(AND(E15<>"",E15<>"/"),1,0)+IF(AND(F15<>"",F15<>"/"),1,0)+IF(AND(G15<>"",G15<>"/"),1,0))/4)
A16: 13 | B16: 46279 | C16: 46283 | H16: =IF(COUNTA(D16:G16)=0,0,(IF(AND(D16<>"",D16<>"/"),1,0)+IF(AND(E16<>"",E16<>"/"),1,0)+IF(AND(F16<>"",F16<>"/"),1,0)+IF(AND(G16<>"",G16<>"/"),1,0))/4)
A17: 14 | B17: 46286 | C17: 46290 | H17: =IF(COUNTA(D17:G17)=0,0,(IF(AND(D17<>"",D17<>"/"),1,0)+IF(AND(E17<>"",E17<>"/"),1,0)+IF(AND(F17<>"",F17<>"/"),1,0)+IF(AND(G17<>"",G17<>"/"),1,0))/4)
A18: 15 | B18: 46293 | C18: 46297 | H18: =IF(COUNTA(D18:G18)=0,0,(IF(AND(D18<>"",D18<>"/"),1,0)+IF(AND(E18<>"",E18<>"/"),1,0)+IF(AND(F18<>"",F18<>"/"),1,0)+IF(AND(G18<>"",G18<>"/"),1,0))/4)
A19: 16 | B19: 46300 | C19: 46304 | H19: =IF(COUNTA(D19:G19)=0,0,(IF(AND(D19<>"",D19<>"/"),1,0)+IF(AND(E19<>"",E19<>"/"),1,0)+IF(AND(F19<>"",F19<>"/"),1,0)+IF(AND(G19<>"",G19<>"/"),1,0))/4)
A20: 17 | B20: 46307 | C20: 46311 | E20: 船舶唯一性校验、卸船作业、船舶预到（外贸）、退回船舶预到（外贸）、采样申请（外贸）、停泊费（外贸）、锚泊费（外贸）、堆存费（外贸）、卸船费（外贸）、采样服务费（外贸）、船舶供应服务费（外贸） | F20: 船舶唯一性校验、卸船作业、船舶预到（外贸）、退回船舶预到（外贸）、采样申请（外贸）、停泊费（外贸）、锚泊费（外贸）、堆存费（外贸）、卸船费（外贸）、采样服务费（外贸）、船舶供应服务费（外贸） | G20: 结算条款管理、协同视览、费用合同签订校验 | H20: =IF(COUNTA(D20:G20)=0,0,(IF(AND(D20<>"",D20<>"/"),1,0)+IF(AND(E20<>"",E20<>"/"),1,0)+IF(AND(F20<>"",F20<>"/"),1,0)+IF(AND(G20<>"",G20<>"/"),1,0))/4)
A21: 18 | B21: 46314 | C21: 46318 | H21: =IF(COUNTA(D21:G21)=0,0,(IF(AND(D21<>"",D21<>"/"),1,0)+IF(AND(E21<>"",E21<>"/"),1,0)+IF(AND(F21<>"",F21<>"/"),1,0)+IF(AND(G21<>"",G21<>"/"),1,0))/4)
A22: 19 | B22: 46321 | C22: 46325 | H22: =IF(COUNTA(D22:G22)=0,0,(IF(AND(D22<>"",D22<>"/"),1,0)+IF(AND(E22<>"",E22<>"/"),1,0)+IF(AND(F22<>"",F22<>"/"),1,0)+IF(AND(G22<>"",G22<>"/"),1,0))/4)
A23: 20 | B23: 46328 | C23: 46332 | H23: =IF(COUNTA(D23:G23)=0,0,(IF(AND(D23<>"",D23<>"/"),1,0)+IF(AND(E23<>"",E23<>"/"),1,0)+IF(AND(F23<>"",F23<>"/"),1,0)+IF(AND(G23<>"",G23<>"/"),1,0))/4)
A24: 21 | B24: 46335 | C24: 46339 | H24: =IF(COUNTA(D24:G24)=0,0,(IF(AND(D24<>"",D24<>"/"),1,0)+IF(AND(E24<>"",E24<>"/"),1,0)+IF(AND(F24<>"",F24<>"/"),1,0)+IF(AND(G24<>"",G24<>"/"),1,0))/4)
A25: 22 | B25: 46342 | C25: 46346 | G25: 船舶唯一性校验、卸船作业、船舶预到（外贸）、退回船舶预到（外贸）、采样申请（外贸）、停泊费（外贸）、锚泊费（外贸）、堆存费（外贸）、卸船费（外贸）、采样服务费（外贸）、船舶供应服务费（外贸） | H25: =IF(COUNTA(D25:G25)=0,0,(IF(AND(D25<>"",D25<>"/"),1,0)+IF(AND(E25<>"",E25<>"/"),1,0)+IF(AND(F25<>"",F25<>"/"),1,0)+IF(AND(G25<>"",G25<>"/"),1,0))/4)
A26: 23 | B26: 46349 | C26: 46353 | H26: =IF(COUNTA(D26:G26)=0,0,(IF(AND(D26<>"",D26<>"/"),1,0)+IF(AND(E26<>"",E26<>"/"),1,0)+IF(AND(F26<>"",F26<>"/"),1,0)+IF(AND(G26<>"",G26<>"/"),1,0))/4)

Sheet 集成管理
A1: 外部系统集成管理
A3: 集成ID | B3: 集成系统 | C3: 交互方式 | D3: 对接人 | E3: 集成内容 | F3: 原计划进展 | G3: 管理状态 | H3: 计划完成 | I3: 实际完成 | J3: 依赖事项 | K3: 风险等级 | L3: 风险/备注
A4: INT-01 | B4: 调运系统 | C4: 接入 | D4: 佘万明 | E4: 船舶轨迹位置、船舶档案、海图信息 | F4: 已完成 | G4: 已完成 | K4: 中
A5: INT-02 | B5: 法治平台 | C5: 接入 | D5: 许祥 | E5: 曹妃甸港、太仓港合同信息 | F5: 已初步对接，对方已提供接口文档，数据清单 | G5: 进行中 | K5: 高 | L5: 1.进度风险：法制平台7月上线试点运行，会在10月份全面上线，相关功能应用需在10月份后才能上线； 2.功能风险：企法部要求法制平台咱不提供接收合同接口，无法满足客户在本系统录入合同的需求，已与用户反馈，用户内部需进行评估
A6: INT-03 | B6: 集团大模型服务 | C6: 接入 | D6: 李超来 | E6: OCR能力 | F6: 已完成 | G6: 已完成 | K6: 高 | L6: 1.效率风险：文件识别效率偏低，需1分钟左右
A7: INT-04 | B7: 港航部科技项目系统 | C7: 接入 | E7: 曹妃甸港、太仓港视频监控数据 | F7: 已初步对接，对方预计10月份具备接口联调条件 | G7: 进行中 | K7: 高 | L7: 1.科技项目不会对接全部生产作业视频监控数据，需确认科技项目对接范围后确认是否满足用户需求
A8: INT-05 | B8: 曹妃甸管控一体化系统 | C8: 接入、推送 | D8: 张应龙 | E8: 基础数据、业务数据、结算数据 | F8: 未对接 | G8: 未开始 | K8: 中 | L8: 暂无
A9: INT-06 | B9: 太仓港管控一体化系统 | C9: 接入、推送 | D9: / | E9: 基础数据、业务数据、结算数据 | F9: 未对接 | G9: 未开始 | K9: 高 | L9: 1.太仓港管控一体化系统刚立项，集成工作暂时无法开展

Sheet 风险问题台账
A1: 风险与问题闭环台账
A3: 编号 | B3: 类型 | C3: 风险/问题描述 | D3: 等级 | E3: 影响范围 | F3: 责任人 | G3: 应对措施 | H3: 计划关闭 | I3: 实际关闭 | J3: 触发条件/根因 | K3: 状态 | L3: 剩余天数 | M3: 是否逾期 | N3: 跟踪记录
A4: R-001 | B4: 风险 | C4: 法治平台全面上线时间影响相关功能投产 | D4: 高 | E4: 合同信息集成 | F4: 集成负责人 | G4: 确认对方正式上线窗口，制定模拟数据和延期切换方案 | H4: 46310 | J4: 对方10月后方可正式支撑 | K4: 处理中 | L4: =IF(H4="","",H4-项目驾驶舱!$B$3) | M4: =IF(OR(K4="已关闭",H4=""),"否",IF(H4<项目驾驶舱!$B$3,"是","否")) | N4: 来源：原计划-集成工作
A5: R-002 | B5: 风险 | C5: 法治平台不提供合同接收接口，可能无法满足本系统录入合同需求 | D5: 高 | E5: 合同业务闭环 | F5: 项目经理 | G5: 推动用户决策，形成接口边界与替代方案确认单 | H5: 46283 | J5: 接口能力与业务诉求不一致 | K5: 待处理 | L5: =IF(H5="","",H5-项目驾驶舱!$B$3) | M5: =IF(OR(K5="已关闭",H5=""),"否",IF(H5<项目驾驶舱!$B$3,"是","否")) | N5: 来源：原计划-集成工作
A6: R-003 | B6: 风险 | C6: OCR识别耗时约1分钟，影响业务效率 | D6: 中 | E6: OCR能力 | F6: 技术负责人 | G6: 压测典型文件，确定超时阈值、异步处理与结果回调方案 | H6: 46290 | J6: 外部大模型服务性能 | K6: 处理中 | L6: =IF(H6="","",H6-项目驾驶舱!$B$3) | M6: =IF(OR(K6="已关闭",H6=""),"否",IF(H6<项目驾驶舱!$B$3,"是","否")) | N6: 来源：原计划-集成工作
A7: R-004 | B7: 风险 | C7: 视频监控数据对接范围尚未明确 | D7: 高 | E7: 视频监控 | F7: 集成负责人 | G7: 确认科技项目覆盖清单并补充缺口方案 | H7: 46280 | J7: 上游系统范围不确定 | K7: 待处理 | L7: =IF(H7="","",H7-项目驾驶舱!$B$3) | M7: =IF(OR(K7="已关闭",H7=""),"否",IF(H7<项目驾驶舱!$B$3,"是","否")) | N7: 来源：原计划-集成工作
A8: R-005 | B8: 风险 | C8: 太仓港管控一体化系统刚立项，集成工作无法按期开展 | D8: 高 | E8: 太仓港数据集成 | F8: 项目经理 | G8: 拆分依赖与非依赖工作，设立外部条件就绪门槛 | H8: 46326 | J8: 外部项目未形成可对接环境 | K8: 处理中 | L8: =IF(H8="","",H8-项目驾驶舱!$B$3) | M8: =IF(OR(K8="已关闭",H8=""),"否",IF(H8<项目驾驶舱!$B$3,"是","否")) | N8: 来源：原计划-集成工作
A9: R-006 | B9: 风险 | C9: 第二批次存在大量未开始任务，后续开发测试窗口集中 | D9: 高 | E9: 第二批次 | F9: 开发负责人 | G9: 按关键路径重排优先级，按周跟踪启动率与完成率 | H9: 46276 | J9: 资源与工作量集中 | K9: 待处理 | L9: =IF(H9="","",H9-项目驾驶舱!$B$3) | M9: =IF(OR(K9="已关闭",H9=""),"否",IF(H9<项目驾驶舱!$B$3,"是","否")) | N9: 基于开发计划识别
L10: =IF(H10="","",H10-项目驾驶舱!$B$3) | M10: =IF(OR(K10="已关闭",H10=""),"否",IF(H10<项目驾驶舱!$B$3,"是","否"))
L11: =IF(H11="","",H11-项目驾驶舱!$B$3) | M11: =IF(OR(K11="已关闭",H11=""),"否",IF(H11<项目驾驶舱!$B$3,"是","否"))
L12: =IF(H12="","",H12-项目驾驶舱!$B$3) | M12: =IF(OR(K12="已关闭",H12=""),"否",IF(H12<项目驾驶舱!$B$3,"是","否"))
L13: =IF(H13="","",H13-项目驾驶舱!$B$3) | M13: =IF(OR(K13="已关闭",H13=""),"否",IF(H13<项目驾驶舱!$B$3,"是","否"))
L14: =IF(H14="","",H14-项目驾驶舱!$B$3) | M14: =IF(OR(K14="已关闭",H14=""),"否",IF(H14<项目驾驶舱!$B$3,"是","否"))
L15: =IF(H15="","",H15-项目驾驶舱!$B$3) | M15: =IF(OR(K15="已关闭",H15=""),"否",IF(H15<项目驾驶舱!$B$3,"是","否"))
L16: =IF(H16="","",H16-项目驾驶舱!$B$3) | M16: =IF(OR(K16="已关闭",H16=""),"否",IF(H16<项目驾驶舱!$B$3,"是","否"))
L17: =IF(H17="","",H17-项目驾驶舱!$B$3) | M17: =IF(OR(K17="已关闭",H17=""),"否",IF(H17<项目驾驶舱!$B$3,"是","否"))
L18: =IF(H18="","",H18-项目驾驶舱!$B$3) | M18: =IF(OR(K18="已关闭",H18=""),"否",IF(H18<项目驾驶舱!$B$3,"是","否"))
L19: =IF(H19="","",H19-项目驾驶舱!$B$3) | M19: =IF(OR(K19="已关闭",H19=""),"否",IF(H19<项目驾驶舱!$B$3,"是","否"))
L20: =IF(H20="","",H20-项目驾驶舱!$B$3) | M20: =IF(OR(K20="已关闭",H20=""),"否",IF(H20<项目驾驶舱!$B$3,"是","否"))
L21: =IF(H21="","",H21-项目驾驶舱!$B$3) | M21: =IF(OR(K21="已关闭",H21=""),"否",IF(H21<项目驾驶舱!$B$3,"是","否"))
... L103: =IF(H103="","",H103-项目驾驶舱!$B$3) | M103: =IF(OR(K103="已关闭",H103=""),"否",IF(H103<项目驾驶舱!$B$3,"是","否"))

Sheet 变更台账
A1: 项目变更台账
A3: 变更编号 | B3: 提出日期 | C3: 提出人 | D3: 变更内容 | E3: 变更原因 | F3: 优先级 | G3: 审批状态 | H3: 范围影响 | I3: 工期影响(天) | J3: 成本影响 | K3: 评估人 | L3: 批准人 | M3: 实施日期 | N3: 关闭说明

Sheet 交付物台账
A1: 项目交付物与质量门禁
A3: 交付物ID | B3: 交付物名称 | C3: 类别 | D3: 责任人 | E3: 计划完成 | F3: 实际完成 | G3: 状态 | H3: 评审人 | I3: 评审结论 | J3: 版本/存放位置 | K3: 备注
A4: D-001 | B4: 项目管理计划 | C4: 管理 | D4: 项目经理 | E4: 46192 | G4: 进行中 | H4: 项目负责人 | I4: 待评审
A5: D-002 | B5: 业务需求规格说明书 | C5: 需求 | D5: 郑士旺 | E5: 46241 | G5: 进行中 | H5: 业务负责人 | I5: 待评审
A6: D-003 | B6: 系统总体设计说明书 | C6: 设计 | D6: 技术负责人 | E6: 46248 | G6: 进行中 | H6: 架构负责人 | I6: 待评审
A7: D-004 | B7: 接口清单及接口设计说明 | C7: 集成 | D7: 集成负责人 | E7: 46283 | G7: 进行中 | H7: 技术负责人 | I7: 待评审
A8: D-005 | B8: 第一批次测试报告 | C8: 测试 | D8: 袁丽荣 | E8: 46318 | G8: 进行中 | H8: 项目经理 | I8: 待评审
A9: D-006 | B9: 第二批次测试报告 | C9: 测试 | D9: 袁丽荣 | E9: 46353 | G9: 未开始 | H9: 项目经理 | I9: 待评审
A10: D-007 | B10: 上线方案及回退方案 | C10: 上线 | D10: 运维负责人 | E10: 46346 | G10: 未开始 | H10: 项目经理 | I10: 待评审
A11: D-008 | B11: 用户操作手册 | C11: 培训 | D11: 实施负责人 | E11: 46349 | G11: 未开始 | H11: 业务负责人 | I11: 待评审
A12: D-009 | B12: 用户验收报告 | C12: 验收 | D12: 项目经理 | E12: 46356 | G12: 未开始 | H12: 项目负责人 | I12: 待评审
A13: D-010 | B13: 项目总结与移交清单 | C13: 收尾 | D13: 项目经理 | E13: 46360 | G13: 未开始 | H13: 项目负责人 | I13: 待评审

Sheet 会议行动项
A1: 会议纪要与行动项跟踪
A3: 行动项ID | B3: 会议日期 | C3: 会议主题 | D3: 决策/行动事项 | E3: 责任人 | F3: 协同人 | G3: 截止日期 | H3: 状态 | I3: 完成日期 | J3: 逾期天数 | K3: 优先级 | L3: 结果说明
J4: =IF(OR(G4="",H4="已完成"),0,MAX(0,项目驾驶舱!$B$3-G4))
J5: =IF(OR(G5="",H5="已完成"),0,MAX(0,项目驾驶舱!$B$3-G5))
J6: =IF(OR(G6="",H6="已完成"),0,MAX(0,项目驾驶舱!$B$3-G6))
J7: =IF(OR(G7="",H7="已完成"),0,MAX(0,项目驾驶舱!$B$3-G7))
J8: =IF(OR(G8="",H8="已完成"),0,MAX(0,项目驾驶舱!$B$3-G8))
J9: =IF(OR(G9="",H9="已完成"),0,MAX(0,项目驾驶舱!$B$3-G9))
J10: =IF(OR(G10="",H10="已完成"),0,MAX(0,项目驾驶舱!$B$3-G10))
J11: =IF(OR(G11="",H11="已完成"),0,MAX(0,项目驾驶舱!$B$3-G11))
J12: =IF(OR(G12="",H12="已完成"),0,MAX(0,项目驾驶舱!$B$3-G12))
J13: =IF(OR(G13="",H13="已完成"),0,MAX(0,项目驾驶舱!$B$3-G13))
J14: =IF(OR(G14="",H14="已完成"),0,MAX(0,项目驾驶舱!$B$3-G14))
J15: =IF(OR(G15="",H15="已完成"),0,MAX(0,项目驾驶舱!$B$3-G15))
... J103: =IF(OR(G103="",H103="已完成"),0,MAX(0,项目驾驶舱!$B$3-G103))

Sheet 使用说明
A1: 项目管理工作簿使用说明
A3: 标准更新流程 | B3: 1. 将最新项目计划放入inputs目录；2. 发起“更新V2模板”；3. 系统按文件修改时间选择最新Excel；4. 核对总控、诊断、督办和资源计划。
A4: 输入目录 | B4: 固定从项目目录下的inputs文件夹读取；支持.xlsx和.xlsm，并自动忽略以~$开头的Excel临时文件。
A5: 本次数据来源 | B5: 华能交易中心-港口交易平台开发计划-20260903-V2.xlsx
A6: 任务范围 | B6: 根据最新开发计划动态识别任务行，本次共145条任务；任务增减时，总控及相关明细范围同步调整。
A7: 统计日期 | B7: 在“项目驾驶舱”B3修改统计日期，延期、剩余天数、临近到期和两周督办会同步变化。
A8: 挂起与暂停 | B8: 业务、后端、前端或测试任一环节为“挂起”或“暂停”时，总体状态自动显示“暂停”；延期状态同步显示“暂停”。
A9: 综合进度口径 | B9: 业务设计15%、后端开发35%、前端开发30%、测试20%；进行中按该阶段50%计，完成按100%计。
A10: 延期口径 | B10: 总体状态不是“已完成”或“暂停”，且计划完成日期早于统计日期，判定为“已延期”；7天内到期为“临近到期”。
A11: 资源计划 | B11: 资源明细按人员、角色、任务排序；人员和角色每12行重复分组合并，便于滚动查看。任务字段仍可按批次、状态和日期筛选。
A12: 资源录入 | B12: 任务资源明细的计划投入工时默认按每周40小时预填，并保留黄色可编辑格式；项目经理可按实际投入调整。周可用工时、资源调整说明和备注由项目经理维护。
A13: 成本口径 | B13: 统一人员单价为1200元/人天，按8小时/人天折算为150元/小时。驾驶舱计划人工成本根据资源明细的计划投入工时计算。
A14: 周迭代计划 | B14: 保留源文件周迭代内容，并计算本周完成率、保留复盘说明。
... A17: 注意事项 | B17: 源计划中的空白或“/”保持为空。刷新后重点核对新增任务、暂停任务、外部接口完成时间、上线窗口和实际完成日期。

Sheet AI项目诊断
A1: AI项目诊断
A2: 数据日期引用“项目驾驶舱”B3；红黄绿由客观规则计算，管理判断由项目经理确认。
A4: 数据日期 | B4: ='项目驾驶舱'!B3 | D4: 项目经理判断 | E4: 待确认 | G4: 判断说明 | H4: 根据诊断指标补充总体判断、最大失控点和需要的支持。
A6: 任务总数 | D6: 已完成任务 | G6: 逾期任务 | J6: 未来14天到期
A7: =COUNTIF('项目总控台账'!$A$4:$A$148,"<>") | D7: =COUNTIF('项目总控台账'!$G$4:$G$148,"已完成") | G7: =COUNTIF('项目总控台账'!$AC$4:$AC$148,"已延期")+COUNTIF('项目总控台账'!$AC$4:$AC$148,"延期") | J7: =COUNTIFS('项目总控台账'!$J$4:$J$148,">="&'项目驾驶舱'!$B$3,'项目总控台账'!$J$4:$J$148,"<="&'项目驾驶舱'!$B$3+14,'项目总控台账'!$G$4:$G$148,"<>已完成")
A9: 未关闭高风险 | D9: 逾期风险/问题 | G9: 逾期行动项 | J9: 数据质量问题
A10: =COUNTIFS('风险问题台账'!$D$4:$D$102,"高",'风险问题台账'!$K$4:$K$102,"<>已关闭") | D10: =COUNTIF('风险问题台账'!$M$4:$M$102,"是") | G10: =COUNTIFS('会议行动项'!$J$4:$J$102,">0",'会议行动项'!$H$4:$H$102,"<>已完成") | J10: =COUNTIF('数据质量检查'!$H$5:$H$149,"需整改")
A13: 项目健康规则 | H13: 状态分布
A14: 维度 | B14: 状态 | C14: 客观判断 | D14: 触发规则 | E14: 建议动作 | F14: 责任角色 | H14: 状态 | I14: 数量
A15: 进度 | B15: =IF(COUNTIF('项目总控台账'!$AC$4:$AC$148,"*延期*")>=5,"红",IF(OR(COUNTIF('项目总控台账'!$AC$4:$AC$148,"*延期*")>0,COUNTIF('项目总控台账'!$G$4:$G$148,"暂停")>0),"黄","绿")) | C15: =COUNTIF('项目总控台账'!$AC$4:$AC$148,"*延期*")&"项任务延期；"&COUNTIF('项目总控台账'!$G$4:$G$148,"暂停")&"项任务暂停" | D15: 延期≥5红；有延期或暂停黄；否则绿 | E15: 确认关键路径、暂停原因和恢复条件 | F15: 项目经理 | H15: 绿 | I15: =COUNTIF($B$15:$B$18,H15)
A16: 风险 | B16: =IF(COUNTIFS('风险问题台账'!$D$4:$D$102,"高",'风险问题台账'!$K$4:$K$102,"<>已关闭")>=3,"红",IF(COUNTIFS('风险问题台账'!$D$4:$D$102,"高",'风险问题台账'!$K$4:$K$102,"<>已关闭")>0,"黄","绿")) | C16: =COUNTIFS('风险问题台账'!$D$4:$D$102,"高",'风险问题台账'!$K$4:$K$102,"<>已关闭")&"项高风险未关闭" | D16: 高风险≥3红；1-2黄；0绿 | E16: 逐项落实责任人和关闭证据 | F16: 风险责任人 | H16: 黄 | I16: =COUNTIF($B$15:$B$18,H16)
A17: 行动 | B17: =IF(COUNTIFS('会议行动项'!$J$4:$J$102,">7",'会议行动项'!$H$4:$H$102,"<>已完成")>0,"红",IF(COUNTIFS('会议行动项'!$J$4:$J$102,">0",'会议行动项'!$H$4:$H$102,"<>已完成")>0,"黄","绿")) | C17: =COUNTIFS('会议行动项'!$J$4:$J$102,">0",'会议行动项'!$H$4:$H$102,"<>已完成")&"项行动逾期" | D17: 逾期>7天红；有逾期黄；无逾期绿 | E17: 升级逾期事项并确认新承诺 | F17: PMO | H17: 红 | I17: =COUNTIF($B$15:$B$18,H17)
A18: 数据 | B18: =IF(COUNTIF('数据质量检查'!$H$5:$H$149,"需整改")>=10,"红",IF(COUNTIF('数据质量检查'!$H$5:$H$149,"需整改")>0,"黄","绿")) | C18: =COUNTIF('数据质量检查'!$H$5:$H$149,"需整改")&"条数据需整改" | D18: 缺陷≥10红；1-9黄；0绿 | E18: 补齐责任人、日期和状态 | F18: 台账维护人 | H18: 灰 | I18: =COUNTIF($B$15:$B$18,H18)

Sheet 数据质量检查
A1: 数据质量检查
A2: 逐条检查项目总控台账中的关键管理字段。状态为“需整改”的记录应在源台账中修正。
A4: 来源 | B4: 记录ID | C4: 任务名称 | D4: 责任人 | E4: 计划开始 | F4: 计划完成 | G4: 发现的问题 | H4: 检查状态 | I4: 建议动作 | J4: 源行号
A5: 项目总控台账 | B5: ='项目总控台账'!A4 | C5: =IF(AND('项目总控台账'!E4<>"",'项目总控台账'!E4<>"/"),'项目总控台账'!E4,IF(AND('项目总控台账'!D4<>"",'项目总控台账'!D4<>"/"),'项目总控台账'!D4,'项目总控台账'!C4)) | D5: ='项目总控台账'!H4 | E5: ='项目总控台账'!I4 | F5: ='项目总控台账'!J4 | G5: =IF(B5="","",IF(OR(C5="",C5="/"),"缺少任务名称；","")&IF(OR(D5="",D5="/"),"缺少有效主责人；","")&IF(OR(E5="",E5<DATE(2000,1,1)),"缺少有效计划开始；","")&IF(OR(F5="",F5<DATE(2000,1,1)),"缺少有效计划完成；","")&IF('项目总控台账'!G4="","缺少总体状态；","")&IF(AND(ISNUMBER(E5),ISNUMBER(F5),E5>=DATE(2000,1,1),F5>=DATE(2000,1,1),E5>F5),"开始晚于完成；","")&IF(AND('项目总控台账'!G4="已完成",'项目总控台账'!AB4<1),"已完成但进度不足100%；","")) | H5: =IF(B5="","",IF(G5="","通过","需整改")) | I5: =IF(H5="需整改","回到项目总控台账第"&J5&"行补齐或修正","无需处理") | J5: 4
A6: 项目总控台账 | B6: ='项目总控台账'!A5 | C6: =IF(AND('项目总控台账'!E5<>"",'项目总控台账'!E5<>"/"),'项目总控台账'!E5,IF(AND('项目总控台账'!D5<>"",'项目总控台账'!D5<>"/"),'项目总控台账'!D5,'项目总控台账'!C5)) | D6: ='项目总控台账'!H5 | E6: ='项目总控台账'!I5 | F6: ='项目总控台账'!J5 | G6: =IF(B6="","",IF(OR(C6="",C6="/"),"缺少任务名称；","")&IF(OR(D6="",D6="/"),"缺少有效主责人；","")&IF(OR(E6="",E6<DATE(2000,1,1)),"缺少有效计划开始；","")&IF(OR(F6="",F6<DATE(2000,1,1)),"缺少有效计划完成；","")&IF('项目总控台账'!G5="","缺少总体状态；","")&IF(AND(ISNUMBER(E6),ISNUMBER(F6),E6>=DATE(2000,1,1),F6>=DATE(2000,1,1),E6>F6),"开始晚于完成；","")&IF(AND('项目总控台账'!G5="已完成",'项目总控台账'!AB5<1),"已完成但进度不足100%；","")) | H6: =IF(B6="","",IF(G6="","通过","需整改")) | I6: =IF(H6="需整改","回到项目总控台账第"&J6&"行补齐或修正","无需处理") | J6: 5
A7: 项目总控台账 | B7: ='项目总控台账'!A6 | C7: =IF(AND('项目总控台账'!E6<>"",'项目总控台账'!E6<>"/"),'项目总控台账'!E6,IF(AND('项目总控台账'!D6<>"",'项目总控台账'!D6<>"/"),'项目总控台账'!D6,'项目总控台账'!C6)) | D7: ='项目总控台账'!H6 | E7: ='项目总控台账'!I6 | F7: ='项目总控台账'!J6 | G7: =IF(B7="","",IF(OR(C7="",C7="/"),"缺少任务名称；","")&IF(OR(D7="",D7="/"),"缺少有效主责人；","")&IF(OR(E7="",E7<DATE(2000,1,1)),"缺少有效计划开始；","")&IF(OR(F7="",F7<DATE(2000,1,1)),"缺少有效计划完成；","")&IF('项目总控台账'!G6="","缺少总体状态；","")&IF(AND(ISNUMBER(E7),ISNUMBER(F7),E7>=DATE(2000,1,1),F7>=DATE(2000,1,1),E7>F7),"开始晚于完成；","")&IF(AND('项目总控台账'!G6="已完成",'项目总控台账'!AB6<1),"已完成但进度不足100%；","")) | H7: =IF(B7="","",IF(G7="","通过","需整改")) | I7: =IF(H7="需整改","回到项目总控台账第"&J7&"行补齐或修正","无需处理") | J7: 6
A8: 项目总控台账 | B8: ='项目总控台账'!A7 | C8: =IF(AND('项目总控台账'!E7<>"",'项目总控台账'!E7<>"/"),'项目总控台账'!E7,IF(AND('项目总控台账'!D7<>"",'项目总控台账'!D7<>"/"),'项目总控台账'!D7,'项目总控台账'!C7)) | D8: ='项目总控台账'!H7 | E8: ='项目总控台账'!I7 | F8: ='项目总控台账'!J7 | G8: =IF(B8="","",IF(OR(C8="",C8="/"),"缺少任务名称；","")&IF(OR(D8="",D8="/"),"缺少有效主责人；","")&IF(OR(E8="",E8<DATE(2000,1,1)),"缺少有效计划开始；","")&IF(OR(F8="",F8<DATE(2000,1,1)),"缺少有效计划完成；","")&IF('项目总控台账'!G7="","缺少总体状态；","")&IF(AND(ISNUMBER(E8),ISNUMBER(F8),E8>=DATE(2000,1,1),F8>=DATE(2000,1,1),E8>F8),"开始晚于完成；","")&IF(AND('项目总控台账'!G7="已完成",'项目总控台账'!AB7<1),"已完成但进度不足100%；","")) | H8: =IF(B8="","",IF(G8="","通过","需整改")) | I8: =IF(H8="需整改","回到项目总控台账第"&J8&"行补齐或修正","无需处理") | J8: 7
A9: 项目总控台账 | B9: ='项目总控台账'!A8 | C9: =IF(AND('项目总控台账'!E8<>"",'项目总控台账'!E8<>"/"),'项目总控台账'!E8,IF(AND('项目总控台账'!D8<>"",'项目总控台账'!D8<>"/"),'项目总控台账'!D8,'项目总控台账'!C8)) | D9: ='项目总控台账'!H8 | E9: ='项目总控台账'!I8 | F9: ='项目总控台账'!J8 | G9: =IF(B9="","",IF(OR(C9="",C9="/"),"缺少任务名称；","")&IF(OR(D9="",D9="/"),"缺少有效主责人；","")&IF(OR(E9="",E9<DATE(2000,1,1)),"缺少有效计划开始；","")&IF(OR(F9="",F9<DATE(2000,1,1)),"缺少有效计划完成；","")&IF('项目总控台账'!G8="","缺少总体状态；","")&IF(AND(ISNUMBER(E9),ISNUMBER(F9),E9>=DATE(2000,1,1),F9>=DATE(2000,1,1),E9>F9),"开始晚于完成；","")&IF(AND('项目总控台账'!G8="已完成",'项目总控台账'!AB8<1),"已完成但进度不足100%；","")) | H9: =IF(B9="","",IF(G9="","通过","需整改")) | I9: =IF(H9="需整改","回到项目总控台账第"&J9&"行补齐或修正","无需处理") | J9: 8
A10: 项目总控台账 | B10: ='项目总控台账'!A9 | C10: =IF(AND('项目总控台账'!E9<>"",'项目总控台账'!E9<>"/"),'项目总控台账'!E9,IF(AND('项目总控台账'!D9<>"",'项目总控台账'!D9<>"/"),'项目总控台账'!D9,'项目总控台账'!C9)) | D10: ='项目总控台账'!H9 | E10: ='项目总控台账'!I9 | F10: ='项目总控台账'!J9 | G10: =IF(B10="","",IF(OR(C10="",C10="/"),"缺少任务名称；","")&IF(OR(D10="",D10="/"),"缺少有效主责人；","")&IF(OR(E10="",E10<DATE(2000,1,1)),"缺少有效计划开始；","")&IF(OR(F10="",F10<DATE(2000,1,1)),"缺少有效计划完成；","")&IF('项目总控台账'!G9="","缺少总体状态；","")&IF(AND(ISNUMBER(E10),ISNUMBER(F10),E10>=DATE(2000,1,1),F10>=DATE(2000,1,1),E10>F10),"开始晚于完成；","")&IF(AND('项目总控台账'!G9="已完成",'项目总控台账'!AB9<1),"已完成但进度不足100%；","")) | H10: =IF(B10="","",IF(G10="","通过","需整改")) | I10: =IF(H10="需整改","回到项目总控台账第"&J10&"行补齐或修正","无需处理") | J10: 9
A11: 项目总控台账 | B11: ='项目总控台账'!A10 | C11: =IF(AND('项目总控台账'!E10<>"",'项目总控台账'!E10<>"/"),'项目总控台账'!E10,IF(AND('项目总控台账'!D10<>"",'项目总控台账'!D10<>"/"),'项目总控台账'!D10,'项目总控台账'!C10)) | D11: ='项目总控台账'!H10 | E11: ='项目总控台账'!I10 | F11: ='项目总控台账'!J10 | G11: =IF(B11="","",IF(OR(C11="",C11="/"),"缺少任务名称；","")&IF(OR(D11="",D11="/"),"缺少有效主责人；","")&IF(OR(E11="",E11<DATE(2000,1,1)),"缺少有效计划开始；","")&IF(OR(F11="",F11<DATE(2000,1,1)),"缺少有效计划完成；","")&IF('项目总控台账'!G10="","缺少总体状态；","")&IF(AND(ISNUMBER(E11),ISNUMBER(F11),E11>=DATE(2000,1,1),F11>=DATE(2000,1,1),E11>F11),"开始晚于完成；","")&IF(AND('项目总控台账'!G10="已完成",'项目总控台账'!AB10<1),"已完成但进度不足100%；","")) | H11: =IF(B11="","",IF(G11="","通过","需整改")) | I11: =IF(H11="需整改","回到项目总控台账第"&J11&"行补齐或修正","无需处理") | J11: 10
A12: 项目总控台账 | B12: ='项目总控台账'!A11 | C12: =IF(AND('项目总控台账'!E11<>"",'项目总控台账'!E11<>"/"),'项目总控台账'!E11,IF(AND('项目总控台账'!D11<>"",'项目总控台账'!D11<>"/"),'项目总控台账'!D11,'项目总控台账'!C11)) | D12: ='项目总控台账'!H11 | E12: ='项目总控台账'!I11 | F12: ='项目总控台账'!J11 | G12: =IF(B12="","",IF(OR(C12="",C12="/"),"缺少任务名称；","")&IF(OR(D12="",D12="/"),"缺少有效主责人；","")&IF(OR(E12="",E12<DATE(2000,1,1)),"缺少有效计划开始；","")&IF(OR(F12="",F12<DATE(2000,1,1)),"缺少有效计划完成；","")&IF('项目总控台账'!G11="","缺少总体状态；","")&IF(AND(ISNUMBER(E12),ISNUMBER(F12),E12>=DATE(2000,1,1),F12>=DATE(2000,1,1),E12>F12),"开始晚于完成；","")&IF(AND('项目总控台账'!G11="已完成",'项目总控台账'!AB11<1),"已完成但进度不足100%；","")) | H12: =IF(B12="","",IF(G12="","通过","需整改")) | I12: =IF(H12="需整改","回到项目总控台账第"&J12&"行补齐或修正","无需处理") | J12: 11
A13: 项目总控台账 | B13: ='项目总控台账'!A12 | C13: =IF(AND('项目总控台账'!E12<>"",'项目总控台账'!E12<>"/"),'项目总控台账'!E12,IF(AND('项目总控台账'!D12<>"",'项目总控台账'!D12<>"/"),'项目总控台账'!D12,'项目总控台账'!C12)) | D13: ='项目总控台账'!H12 | E13: ='项目总控台账'!I12 | F13: ='项目总控台账'!J12 | G13: =IF(B13="","",IF(OR(C13="",C13="/"),"缺少任务名称；","")&IF(OR(D13="",D13="/"),"缺少有效主责人；","")&IF(OR(E13="",E13<DATE(2000,1,1)),"缺少有效计划开始；","")&IF(OR(F13="",F13<DATE(2000,1,1)),"缺少有效计划完成；","")&IF('项目总控台账'!G12="","缺少总体状态；","")&IF(AND(ISNUMBER(E13),ISNUMBER(F13),E13>=DATE(2000,1,1),F13>=DATE(2000,1,1),E13>F13),"开始晚于完成；","")&IF(AND('项目总控台账'!G12="已完成",'项目总控台账'!AB12<1),"已完成但进度不足100%；","")) | H13: =IF(B13="","",IF(G13="","通过","需整改")) | I13: =IF(H13="需整改","回到项目总控台账第"&J13&"行补齐或修正","无需处理") | J13: 12
A14: 项目总控台账 | B14: ='项目总控台账'!A13 | C14: =IF(AND('项目总控台账'!E13<>"",'项目总控台账'!E13<>"/"),'项目总控台账'!E13,IF(AND('项目总控台账'!D13<>"",'项目总控台账'!D13<>"/"),'项目总控台账'!D13,'项目总控台账'!C13)) | D14: ='项目总控台账'!H13 | E14: ='项目总控台账'!I13 | F14: ='项目总控台账'!J13 | G14: =IF(B14="","",IF(OR(C14="",C14="/"),"缺少任务名称；","")&IF(OR(D14="",D14="/"),"缺少有效主责人；","")&IF(OR(E14="",E14<DATE(2000,1,1)),"缺少有效计划开始；","")&IF(OR(F14="",F14<DATE(2000,1,1)),"缺少有效计划完成；","")&IF('项目总控台账'!G13="","缺少总体状态；","")&IF(AND(ISNUMBER(E14),ISNUMBER(F14),E14>=DATE(2000,1,1),F14>=DATE(2000,1,1),E14>F14),"开始晚于完成；","")&IF(AND('项目总控台账'!G13="已完成",'项目总控台账'!AB13<1),"已完成但进度不足100%；","")) | H14: =IF(B14="","",IF(G14="","通过","需整改")) | I14: =IF(H14="需整改","回到项目总控台账第"&J14&"行补齐或修正","无需处理") | J14: 13
A15: 项目总控台账 | B15: ='项目总控台账'!A14 | C15: =IF(AND('项目总控台账'!E14<>"",'项目总控台账'!E14<>"/"),'项目总控台账'!E14,IF(AND('项目总控台账'!D14<>"",'项目总控台账'!D14<>"/"),'项目总控台账'!D14,'项目总控台账'!C14)) | D15: ='项目总控台账'!H14 | E15: ='项目总控台账'!I14 | F15: ='项目总控台账'!J14 | G15: =IF(B15="","",IF(OR(C15="",C15="/"),"缺少任务名称；","")&IF(OR(D15="",D15="/"),"缺少有效主责人；","")&IF(OR(E15="",E15<DATE(2000,1,1)),"缺少有效计划开始；","")&IF(OR(F15="",F15<DATE(2000,1,1)),"缺少有效计划完成；","")&IF('项目总控台账'!G14="","缺少总体状态；","")&IF(AND(ISNUMBER(E15),ISNUMBER(F15),E15>=DATE(2000,1,1),F15>=DATE(2000,1,1),E15>F15),"开始晚于完成；","")&IF(AND('项目总控台账'!G14="已完成",'项目总控台账'!AB14<1),"已完成但进度不足100%；","")) | H15: =IF(B15="","",IF(G15="","通过","需整改")) | I15: =IF(H15="需整改","回到项目总控台账第"&J15&"行补齐或修正","无需处理") | J15: 14
A16: 项目总控台账 | B16: ='项目总控台账'!A15 | C16: =IF(AND('项目总控台账'!E15<>"",'项目总控台账'!E15<>"/"),'项目总控台账'!E15,IF(AND('项目总控台账'!D15<>"",'项目总控台账'!D15<>"/"),'项目总控台账'!D15,'项目总控台账'!C15)) | D16: ='项目总控台账'!H15 | E16: ='项目总控台账'!I15 | F16: ='项目总控台账'!J15 | G16: =IF(B16="","",IF(OR(C16="",C16="/"),"缺少任务名称；","")&IF(OR(D16="",D16="/"),"缺少有效主责人；","")&IF(OR(E16="",E16<DATE(2000,1,1)),"缺少有效计划开始；","")&IF(OR(F16="",F16<DATE(2000,1,1)),"缺少有效计划完成；","")&IF('项目总控台账'!G15="","缺少总体状态；","")&IF(AND(ISNUMBER(E16),ISNUMBER(F16),E16>=DATE(2000,1,1),F16>=DATE(2000,1,1),E16>F16),"开始晚于完成；","")&IF(AND('项目总控台账'!G15="已完成",'项目总控台账'!AB15<1),"已完成但进度不足100%；","")) | H16: =IF(B16="","",IF(G16="","通过","需整改")) | I16: =IF(H16="需整改","回到项目总控台账第"&J16&"行补齐或修正","无需处理") | J16: 15
... A149: 项目总控台账 | B149: ='项目总控台账'!A148 | C149: =IF(AND('项目总控台账'!E148<>"",'项目总控台账'!E148<>"/"),'项目总控台账'!E148,IF(AND('项目总控台账'!D148<>"",'项目总控台账'!D148<>"/"),'项目总控台账'!D148,'项目总控台账'!C148)) | D149: ='项目总控台账'!H148 | E149: ='项目总控台账'!I148 | F149: ='项目总控台账'!J148 | G149: =IF(B149="","",IF(OR(C149="",C149="/"),"缺少任务名称；","")&IF(OR(D149="",D149="/"),"缺少有效主责人；","")&IF(OR(E149="",E149<DATE(2000,1,1)),"缺少有效计划开始；","")&IF(OR(F149="",F149<DATE(2000,1,1)),"缺少有效计划完成；","")&IF('项目总控台账'!G148="","缺少总体状态；","")&IF(AND(ISNUMBER(E149),ISNUMBER(F149),E149>=DATE(2000,1,1),F149>=DATE(2000,1,1),E149>F149),"开始晚于完成；","")&IF(AND('项目总控台账'!G148="已完成",'项目总控台账'!AB148<1),"已完成但进度不足100%；","")) | H149: =IF(B149="","",IF(G149="","通过","需整改")) | I149: =IF(H149="需整改","回到项目总控台账第"&J149&"行补齐或修正","无需处理") | J149: 148

Sheet 待决策事项
A1: 待决策事项
A2: 记录超出项目团队权限、需要管理层或业务方明确取舍的事项。黄色单元格需要人工维护。
A4: 决策ID | B4: 提出日期 | C4: 决策主题 | D4: 背景与现状 | E4: 可选方案 | F4: 建议方案 | G4: 决策人 | H4: 需要日期 | I4: 当前状态 | J4: 逾期天数 | K4: 影响范围 | L4: 决策结果 | M4: 关闭日期
A5: =IF(C5="","","D-"&TEXT(ROW()-4,"000")) | J5: =IF(OR(H5="",I5="已决策"),0,MAX(0,'项目驾驶舱'!$B$3-H5))
A6: =IF(C6="","","D-"&TEXT(ROW()-4,"000")) | J6: =IF(OR(H6="",I6="已决策"),0,MAX(0,'项目驾驶舱'!$B$3-H6))
A7: =IF(C7="","","D-"&TEXT(ROW()-4,"000")) | J7: =IF(OR(H7="",I7="已决策"),0,MAX(0,'项目驾驶舱'!$B$3-H7))
A8: =IF(C8="","","D-"&TEXT(ROW()-4,"000")) | J8: =IF(OR(H8="",I8="已决策"),0,MAX(0,'项目驾驶舱'!$B$3-H8))
A9: =IF(C9="","","D-"&TEXT(ROW()-4,"000")) | J9: =IF(OR(H9="",I9="已决策"),0,MAX(0,'项目驾驶舱'!$B$3-H9))
A10: =IF(C10="","","D-"&TEXT(ROW()-4,"000")) | J10: =IF(OR(H10="",I10="已决策"),0,MAX(0,'项目驾驶舱'!$B$3-H10))
A11: =IF(C11="","","D-"&TEXT(ROW()-4,"000")) | J11: =IF(OR(H11="",I11="已决策"),0,MAX(0,'项目驾驶舱'!$B$3-H11))
A12: =IF(C12="","","D-"&TEXT(ROW()-4,"000")) | J12: =IF(OR(H12="",I12="已决策"),0,MAX(0,'项目驾驶舱'!$B$3-H12))
A13: =IF(C13="","","D-"&TEXT(ROW()-4,"000")) | J13: =IF(OR(H13="",I13="已决策"),0,MAX(0,'项目驾驶舱'!$B$3-H13))
A14: =IF(C14="","","D-"&TEXT(ROW()-4,"000")) | J14: =IF(OR(H14="",I14="已决策"),0,MAX(0,'项目驾驶舱'!$B$3-H14))
A15: =IF(C15="","","D-"&TEXT(ROW()-4,"000")) | J15: =IF(OR(H15="",I15="已决策"),0,MAX(0,'项目驾驶舱'!$B$3-H15))
A16: =IF(C16="","","D-"&TEXT(ROW()-4,"000")) | J16: =IF(OR(H16="",I16="已决策"),0,MAX(0,'项目驾驶舱'!$B$3-H16))
... A54: =IF(C54="","","D-"&TEXT(ROW()-4,"000")) | J54: =IF(OR(H54="",I54="已决策"),0,MAX(0,'项目驾驶舱'!$B$3-H54))

Sheet 两周督办
A1: 两周督办
A2: 自动识别未来14天到期及已经逾期的未完成任务。使用“是否纳入”筛选出需要督办的记录。
A4: 是否纳入 | B4: 任务ID | C4: 任务名称 | D4: 批次 | E4: 总体状态 | F4: 主责人 | G4: 计划完成 | H4: 距截止天数 | I4: 延期状态 | J4: 当前问题/阻塞 | K4: 建议动作 | L4: 承诺完成 | M4: 完成证据
A5: =IF(B5="","",IF(AND(E5<>"已完成",ISNUMBER(G5),G5<='项目驾驶舱'!$B$3+14),"是","否")) | B5: ='项目总控台账'!A4 | C5: =IF(AND('项目总控台账'!E4<>"",'项目总控台账'!E4<>"/"),'项目总控台账'!E4,IF(AND('项目总控台账'!D4<>"",'项目总控台账'!D4<>"/"),'项目总控台账'!D4,'项目总控台账'!C4)) | D5: ='项目总控台账'!F4 | E5: ='项目总控台账'!G4 | F5: ='项目总控台账'!H4 | G5: ='项目总控台账'!J4 | H5: =IF(G5="","",G5-'项目驾驶舱'!$B$3) | I5: ='项目总控台账'!AC4 | J5: ='项目总控台账'!AD4 | K5: =IF(A5<>"是","",IF(OR(E5="暂停",E5="挂起"),"确认暂停原因、恢复条件和责任人",IF(H5<0,"立即确认延期原因、影响及补救计划",IF(H5<=7,"本周确认交付承诺和完成证据","提前检查依赖与风险"))))
A6: =IF(B6="","",IF(AND(E6<>"已完成",ISNUMBER(G6),G6<='项目驾驶舱'!$B$3+14),"是","否")) | B6: ='项目总控台账'!A5 | C6: =IF(AND('项目总控台账'!E5<>"",'项目总控台账'!E5<>"/"),'项目总控台账'!E5,IF(AND('项目总控台账'!D5<>"",'项目总控台账'!D5<>"/"),'项目总控台账'!D5,'项目总控台账'!C5)) | D6: ='项目总控台账'!F5 | E6: ='项目总控台账'!G5 | F6: ='项目总控台账'!H5 | G6: ='项目总控台账'!J5 | H6: =IF(G6="","",G6-'项目驾驶舱'!$B$3) | I6: ='项目总控台账'!AC5 | J6: ='项目总控台账'!AD5 | K6: =IF(A6<>"是","",IF(OR(E6="暂停",E6="挂起"),"确认暂停原因、恢复条件和责任人",IF(H6<0,"立即确认延期原因、影响及补救计划",IF(H6<=7,"本周确认交付承诺和完成证据","提前检查依赖与风险"))))
A7: =IF(B7="","",IF(AND(E7<>"已完成",ISNUMBER(G7),G7<='项目驾驶舱'!$B$3+14),"是","否")) | B7: ='项目总控台账'!A6 | C7: =IF(AND('项目总控台账'!E6<>"",'项目总控台账'!E6<>"/"),'项目总控台账'!E6,IF(AND('项目总控台账'!D6<>"",'项目总控台账'!D6<>"/"),'项目总控台账'!D6,'项目总控台账'!C6)) | D7: ='项目总控台账'!F6 | E7: ='项目总控台账'!G6 | F7: ='项目总控台账'!H6 | G7: ='项目总控台账'!J6 | H7: =IF(G7="","",G7-'项目驾驶舱'!$B$3) | I7: ='项目总控台账'!AC6 | J7: ='项目总控台账'!AD6 | K7: =IF(A7<>"是","",IF(OR(E7="暂停",E7="挂起"),"确认暂停原因、恢复条件和责任人",IF(H7<0,"立即确认延期原因、影响及补救计划",IF(H7<=7,"本周确认交付承诺和完成证据","提前检查依赖与风险"))))
A8: =IF(B8="","",IF(AND(E8<>"已完成",ISNUMBER(G8),G8<='项目驾驶舱'!$B$3+14),"是","否")) | B8: ='项目总控台账'!A7 | C8: =IF(AND('项目总控台账'!E7<>"",'项目总控台账'!E7<>"/"),'项目总控台账'!E7,IF(AND('项目总控台账'!D7<>"",'项目总控台账'!D7<>"/"),'项目总控台账'!D7,'项目总控台账'!C7)) | D8: ='项目总控台账'!F7 | E8: ='项目总控台账'!G7 | F8: ='项目总控台账'!H7 | G8: ='项目总控台账'!J7 | H8: =IF(G8="","",G8-'项目驾驶舱'!$B$3) | I8: ='项目总控台账'!AC7 | J8: ='项目总控台账'!AD7 | K8: =IF(A8<>"是","",IF(OR(E8="暂停",E8="挂起"),"确认暂停原因、恢复条件和责任人",IF(H8<0,"立即确认延期原因、影响及补救计划",IF(H8<=7,"本周确认交付承诺和完成证据","提前检查依赖与风险"))))
A9: =IF(B9="","",IF(AND(E9<>"已完成",ISNUMBER(G9),G9<='项目驾驶舱'!$B$3+14),"是","否")) | B9: ='项目总控台账'!A8 | C9: =IF(AND('项目总控台账'!E8<>"",'项目总控台账'!E8<>"/"),'项目总控台账'!E8,IF(AND('项目总控台账'!D8<>"",'项目总控台账'!D8<>"/"),'项目总控台账'!D8,'项目总控台账'!C8)) | D9: ='项目总控台账'!F8 | E9: ='项目总控台账'!G8 | F9: ='项目总控台账'!H8 | G9: ='项目总控台账'!J8 | H9: =IF(G9="","",G9-'项目驾驶舱'!$B$3) | I9: ='项目总控台账'!AC8 | J9: ='项目总控台账'!AD8 | K9: =IF(A9<>"是","",IF(OR(E9="暂停",E9="挂起"),"确认暂停原因、恢复条件和责任人",IF(H9<0,"立即确认延期原因、影响及补救计划",IF(H9<=7,"本周确认交付承诺和完成证据","提前检查依赖与风险"))))
A10: =IF(B10="","",IF(AND(E10<>"已完成",ISNUMBER(G10),G10<='项目驾驶舱'!$B$3+14),"是","否")) | B10: ='项目总控台账'!A9 | C10: =IF(AND('项目总控台账'!E9<>"",'项目总控台账'!E9<>"/"),'项目总控台账'!E9,IF(AND('项目总控台账'!D9<>"",'项目总控台账'!D9<>"/"),'项目总控台账'!D9,'项目总控台账'!C9)) | D10: ='项目总控台账'!F9 | E10: ='项目总控台账'!G9 | F10: ='项目总控台账'!H9 | G10: ='项目总控台账'!J9 | H10: =IF(G10="","",G10-'项目驾驶舱'!$B$3) | I10: ='项目总控台账'!AC9 | J10: ='项目总控台账'!AD9 | K10: =IF(A10<>"是","",IF(OR(E10="暂停",E10="挂起"),"确认暂停原因、恢复条件和责任人",IF(H10<0,"立即确认延期原因、影响及补救计划",IF(H10<=7,"本周确认交付承诺和完成证据","提前检查依赖与风险"))))
A11: =IF(B11="","",IF(AND(E11<>"已完成",ISNUMBER(G11),G11<='项目驾驶舱'!$B$3+14),"是","否")) | B11: ='项目总控台账'!A10 | C11: =IF(AND('项目总控台账'!E10<>"",'项目总控台账'!E10<>"/"),'项目总控台账'!E10,IF(AND('项目总控台账'!D10<>"",'项目总控台账'!D10<>"/"),'项目总控台账'!D10,'项目总控台账'!C10)) | D11: ='项目总控台账'!F10 | E11: ='项目总控台账'!G10 | F11: ='项目总控台账'!H10 | G11: ='项目总控台账'!J10 | H11: =IF(G11="","",G11-'项目驾驶舱'!$B$3) | I11: ='项目总控台账'!AC10 | J11: ='项目总控台账'!AD10 | K11: =IF(A11<>"是","",IF(OR(E11="暂停",E11="挂起"),"确认暂停原因、恢复条件和责任人",IF(H11<0,"立即确认延期原因、影响及补救计划",IF(H11<=7,"本周确认交付承诺和完成证据","提前检查依赖与风险"))))
A12: =IF(B12="","",IF(AND(E12<>"已完成",ISNUMBER(G12),G12<='项目驾驶舱'!$B$3+14),"是","否")) | B12: ='项目总控台账'!A11 | C12: =IF(AND('项目总控台账'!E11<>"",'项目总控台账'!E11<>"/"),'项目总控台账'!E11,IF(AND('项目总控台账'!D11<>"",'项目总控台账'!D11<>"/"),'项目总控台账'!D11,'项目总控台账'!C11)) | D12: ='项目总控台账'!F11 | E12: ='项目总控台账'!G11 | F12: ='项目总控台账'!H11 | G12: ='项目总控台账'!J11 | H12: =IF(G12="","",G12-'项目驾驶舱'!$B$3) | I12: ='项目总控台账'!AC11 | J12: ='项目总控台账'!AD11 | K12: =IF(A12<>"是","",IF(OR(E12="暂停",E12="挂起"),"确认暂停原因、恢复条件和责任人",IF(H12<0,"立即确认延期原因、影响及补救计划",IF(H12<=7,"本周确认交付承诺和完成证据","提前检查依赖与风险"))))
A13: =IF(B13="","",IF(AND(E13<>"已完成",ISNUMBER(G13),G13<='项目驾驶舱'!$B$3+14),"是","否")) | B13: ='项目总控台账'!A12 | C13: =IF(AND('项目总控台账'!E12<>"",'项目总控台账'!E12<>"/"),'项目总控台账'!E12,IF(AND('项目总控台账'!D12<>"",'项目总控台账'!D12<>"/"),'项目总控台账'!D12,'项目总控台账'!C12)) | D13: ='项目总控台账'!F12 | E13: ='项目总控台账'!G12 | F13: ='项目总控台账'!H12 | G13: ='项目总控台账'!J12 | H13: =IF(G13="","",G13-'项目驾驶舱'!$B$3) | I13: ='项目总控台账'!AC12 | J13: ='项目总控台账'!AD12 | K13: =IF(A13<>"是","",IF(OR(E13="暂停",E13="挂起"),"确认暂停原因、恢复条件和责任人",IF(H13<0,"立即确认延期原因、影响及补救计划",IF(H13<=7,"本周确认交付承诺和完成证据","提前检查依赖与风险"))))
A14: =IF(B14="","",IF(AND(E14<>"已完成",ISNUMBER(G14),G14<='项目驾驶舱'!$B$3+14),"是","否")) | B14: ='项目总控台账'!A13 | C14: =IF(AND('项目总控台账'!E13<>"",'项目总控台账'!E13<>"/"),'项目总控台账'!E13,IF(AND('项目总控台账'!D13<>"",'项目总控台账'!D13<>"/"),'项目总控台账'!D13,'项目总控台账'!C13)) | D14: ='项目总控台账'!F13 | E14: ='项目总控台账'!G13 | F14: ='项目总控台账'!H13 | G14: ='项目总控台账'!J13 | H14: =IF(G14="","",G14-'项目驾驶舱'!$B$3) | I14: ='项目总控台账'!AC13 | J14: ='项目总控台账'!AD13 | K14: =IF(A14<>"是","",IF(OR(E14="暂停",E14="挂起"),"确认暂停原因、恢复条件和责任人",IF(H14<0,"立即确认延期原因、影响及补救计划",IF(H14<=7,"本周确认交付承诺和完成证据","提前检查依赖与风险"))))
A15: =IF(B15="","",IF(AND(E15<>"已完成",ISNUMBER(G15),G15<='项目驾驶舱'!$B$3+14),"是","否")) | B15: ='项目总控台账'!A14 | C15: =IF(AND('项目总控台账'!E14<>"",'项目总控台账'!E14<>"/"),'项目总控台账'!E14,IF(AND('项目总控台账'!D14<>"",'项目总控台账'!D14<>"/"),'项目总控台账'!D14,'项目总控台账'!C14)) | D15: ='项目总控台账'!F14 | E15: ='项目总控台账'!G14 | F15: ='项目总控台账'!H14 | G15: ='项目总控台账'!J14 | H15: =IF(G15="","",G15-'项目驾驶舱'!$B$3) | I15: ='项目总控台账'!AC14 | J15: ='项目总控台账'!AD14 | K15: =IF(A15<>"是","",IF(OR(E15="暂停",E15="挂起"),"确认暂停原因、恢复条件和责任人",IF(H15<0,"立即确认延期原因、影响及补救计划",IF(H15<=7,"本周确认交付承诺和完成证据","提前检查依赖与风险"))))
A16: =IF(B16="","",IF(AND(E16<>"已完成",ISNUMBER(G16),G16<='项目驾驶舱'!$B$3+14),"是","否")) | B16: ='项目总控台账'!A15 | C16: =IF(AND('项目总控台账'!E15<>"",'项目总控台账'!E15<>"/"),'项目总控台账'!E15,IF(AND('项目总控台账'!D15<>"",'项目总控台账'!D15<>"/"),'项目总控台账'!D15,'项目总控台账'!C15)) | D16: ='项目总控台账'!F15 | E16: ='项目总控台账'!G15 | F16: ='项目总控台账'!H15 | G16: ='项目总控台账'!J15 | H16: =IF(G16="","",G16-'项目驾驶舱'!$B$3) | I16: ='项目总控台账'!AC15 | J16: ='项目总控台账'!AD15 | K16: =IF(A16<>"是","",IF(OR(E16="暂停",E16="挂起"),"确认暂停原因、恢复条件和责任人",IF(H16<0,"立即确认延期原因、影响及补救计划",IF(H16<=7,"本周确认交付承诺和完成证据","提前检查依赖与风险"))))
... A149: =IF(B149="","",IF(AND(E149<>"已完成",ISNUMBER(G149),G149<='项目驾驶舱'!$B$3+14),"是","否")) | B149: ='项目总控台账'!A148 | C149: =IF(AND('项目总控台账'!E148<>"",'项目总控台账'!E148<>"/"),'项目总控台账'!E148,IF(AND('项目总控台账'!D148<>"",'项目总控台账'!D148<>"/"),'项目总控台账'!D148,'项目总控台账'!C148)) | D149: ='项目总控台账'!F148 | E149: ='项目总控台账'!G148 | F149: ='项目总控台账'!H148 | G149: ='项目总控台账'!J148 | H149: =IF(G149="","",G149-'项目驾驶舱'!$B$3) | I149: ='项目总控台账'!AC148 | J149: ='项目总控台账'!AD148 | K149: =IF(A149<>"是","",IF(OR(E149="暂停",E149="挂起"),"确认暂停原因、恢复条件和责任人",IF(H149<0,"立即确认延期原因、影响及补救计划",IF(H149<=7,"本周确认交付承诺和完成证据","提前检查依赖与风险"))))

Sheet 资源计划
A1: 资源计划
A2: 汇总业务、后端、前端和测试任务分配。黄色区域用于填写可用工时、任务投入工时和资源调整说明。
A4: 人员 | B4: 角色 | C4: 任务数 | D4: 未完成任务 | E4: 最早开始 | F4: 最晚结束 | G4: 周可用工时 | H4: 计划投入工时 | I4: 负荷率 | J4: 负荷判断 | K4: 资源建议 | L4: 备注
A5: 刘凯 | B5: 后端 | C5: =COUNTA($C$16:$C$145) | D5: =COUNTIFS($F$16:$F$145,"<>已完成") | E5: =IFERROR(MINIFS($G$16:$G$145,$G$16:$G$145,">0"),"") | F5: =IFERROR(MAX($H$16:$H$145),"") | G5: 40 | H5: =SUM($I$16:$I$145) | I5: =IF(OR(G5=0,H5=0),"",H5/(G5*MAX(1,NETWORKDAYS(E5,F5)/5))) | J5: =IF(D5=0,"无在途任务",IF(H5=0,"待估算",IF(I5>1,"超负荷",IF(I5>0.85,"高负荷",IF(I5<0.4,"低负荷","正常"))))) | K5: =IF(J5="超负荷","调整任务或增加资源",IF(J5="高负荷","确认优先级并预留缓冲",IF(J5="待估算","补充任务投入工时","按计划跟踪")))
A6: 常浩 | B6: 前端、后端 | C6: =COUNTA($C$146:$C$163) | D6: =COUNTIFS($F$146:$F$163,"<>已完成") | E6: =IFERROR(MINIFS($G$146:$G$163,$G$146:$G$163,">0"),"") | F6: =IFERROR(MAX($H$146:$H$163),"") | G6: 40 | H6: =SUM($I$146:$I$163) | I6: =IF(OR(G6=0,H6=0),"",H6/(G6*MAX(1,NETWORKDAYS(E6,F6)/5))) | J6: =IF(D6=0,"无在途任务",IF(H6=0,"待估算",IF(I6>1,"超负荷",IF(I6>0.85,"高负荷",IF(I6<0.4,"低负荷","正常"))))) | K6: =IF(J6="超负荷","调整任务或增加资源",IF(J6="高负荷","确认优先级并预留缓冲",IF(J6="待估算","补充任务投入工时","按计划跟踪")))
A7: 石军磊 | B7: 后端 | C7: =COUNTA($C$164:$C$296) | D7: =COUNTIFS($F$164:$F$296,"<>已完成") | E7: =IFERROR(MINIFS($G$164:$G$296,$G$164:$G$296,">0"),"") | F7: =IFERROR(MAX($H$164:$H$296),"") | G7: 40 | H7: =SUM($I$164:$I$296) | I7: =IF(OR(G7=0,H7=0),"",H7/(G7*MAX(1,NETWORKDAYS(E7,F7)/5))) | J7: =IF(D7=0,"无在途任务",IF(H7=0,"待估算",IF(I7>1,"超负荷",IF(I7>0.85,"高负荷",IF(I7<0.4,"低负荷","正常"))))) | K7: =IF(J7="超负荷","调整任务或增加资源",IF(J7="高负荷","确认优先级并预留缓冲",IF(J7="待估算","补充任务投入工时","按计划跟踪")))
A8: 袁丽荣 | B8: 测试 | C8: =COUNTA($C$297:$C$435) | D8: =COUNTIFS($F$297:$F$435,"<>已完成") | E8: =IFERROR(MINIFS($G$297:$G$435,$G$297:$G$435,">0"),"") | F8: =IFERROR(MAX($H$297:$H$435),"") | G8: 40 | H8: =SUM($I$297:$I$435) | I8: =IF(OR(G8=0,H8=0),"",H8/(G8*MAX(1,NETWORKDAYS(E8,F8)/5))) | J8: =IF(D8=0,"无在途任务",IF(H8=0,"待估算",IF(I8>1,"超负荷",IF(I8>0.85,"高负荷",IF(I8<0.4,"低负荷","正常"))))) | K8: =IF(J8="超负荷","调整任务或增加资源",IF(J8="高负荷","确认优先级并预留缓冲",IF(J8="待估算","补充任务投入工时","按计划跟踪")))
A9: 贺航 | B9: 前端 | C9: =COUNTA($C$436:$C$568) | D9: =COUNTIFS($F$436:$F$568,"<>已完成") | E9: =IFERROR(MINIFS($G$436:$G$568,$G$436:$G$568,">0"),"") | F9: =IFERROR(MAX($H$436:$H$568),"") | G9: 40 | H9: =SUM($I$436:$I$568) | I9: =IF(OR(G9=0,H9=0),"",H9/(G9*MAX(1,NETWORKDAYS(E9,F9)/5))) | J9: =IF(D9=0,"无在途任务",IF(H9=0,"待估算",IF(I9>1,"超负荷",IF(I9>0.85,"高负荷",IF(I9<0.4,"低负荷","正常"))))) | K9: =IF(J9="超负荷","调整任务或增加资源",IF(J9="高负荷","确认优先级并预留缓冲",IF(J9="待估算","补充任务投入工时","按计划跟踪")))
A10: 郑士旺 | B10: 业务 | C10: =COUNTA($C$569:$C$707) | D10: =COUNTIFS($F$569:$F$707,"<>已完成") | E10: =IFERROR(MINIFS($G$569:$G$707,$G$569:$G$707,">0"),"") | F10: =IFERROR(MAX($H$569:$H$707),"") | G10: 40 | H10: =SUM($I$569:$I$707) | I10: =IF(OR(G10=0,H10=0),"",H10/(G10*MAX(1,NETWORKDAYS(E10,F10)/5))) | J10: =IF(D10=0,"无在途任务",IF(H10=0,"待估算",IF(I10>1,"超负荷",IF(I10>0.85,"高负荷",IF(I10<0.4,"低负荷","正常"))))) | K10: =IF(J10="超负荷","调整任务或增加资源",IF(J10="高负荷","确认优先级并预留缓冲",IF(J10="待估算","补充任务投入工时","按计划跟踪")))
A13: 任务资源明细
A15: 人员 | B15: 角色 | C15: 任务ID | D15: 任务名称 | E15: 批次 | F15: 总体状态 | G15: 计划开始 | H15: 计划结束 | I15: 计划投入工时 | J15: 分配状态 | K15: 调整建议 | L15: 说明
A16: 刘凯 | B16: 后端 | C16: T058 | D16: OCR识别及编辑 | E16: 第一批次 | F16: =IF(OR(M61="挂起",M61="暂停",Q61="挂起",Q61="暂停",U61="挂起",U61="暂停",Y61="挂起",Y61="暂停"),"暂停","已完成") | G16: 46195 | H16: 46206 | I16: 40 | J16: =IF(I16="","待估算",IF(F16="已完成","已结束",IF(AND(ISNUMBER(G16),ISNUMBER(H16),G16<='项目驾驶舱'!$B$3,H16>='项目驾驶舱'!$B$3),"进行中","计划中"))) | K16: =IF(J16="待估算","补充投入工时",IF(AND(H16<'项目驾驶舱'!$B$3,F16<>"已完成"),"确认延期和后续安排","按计划跟踪"))
C17: T070 | D17: 生成报告 | E17: 第一批次 | F17: =IF(OR(M73="挂起",M73="暂停",Q73="挂起",Q73="暂停",U73="挂起",U73="暂停",Y73="挂起",Y73="暂停"),"暂停","已完成") | G17: 46195 | H17: 46206 | I17: 40 | J17: =IF(I17="","待估算",IF(F17="已完成","已结束",IF(AND(ISNUMBER(G17),ISNUMBER(H17),G17<='项目驾驶舱'!$B$3,H17>='项目驾驶舱'!$B$3),"进行中","计划中"))) | K17: =IF(J17="待估算","补充投入工时",IF(AND(H17<'项目驾驶舱'!$B$3,F17<>"已完成"),"确认延期和后续安排","按计划跟踪"))
C18: T071 | D18: 装船作业信息录入优化（太仓） | E18: 第一批次 | F18: =IF(OR(M74="挂起",M74="暂停",Q74="挂起",Q74="暂停",U74="挂起",U74="暂停",Y74="挂起",Y74="暂停"),"暂停","已完成") | G18: 46195 | H18: 46206 | I18: 40 | J18: =IF(I18="","待估算",IF(F18="已完成","已结束",IF(AND(ISNUMBER(G18),ISNUMBER(H18),G18<='项目驾驶舱'!$B$3,H18>='项目驾驶舱'!$B$3),"进行中","计划中"))) | K18: =IF(J18="待估算","补充投入工时",IF(AND(H18<'项目驾驶舱'!$B$3,F18<>"已完成"),"确认延期和后续安排","按计划跟踪"))
C19: T001 | D19: 新增车辆信息 | E19: 第一批次 | F19: =IF(OR(M4="挂起",M4="暂停",Q4="挂起",Q4="暂停",U4="挂起",U4="暂停",Y4="挂起",Y4="暂停"),"暂停","已完成") | G19: 46209 | H19: 46225 | I19: 40 | J19: =IF(I19="","待估算",IF(F19="已完成","已结束",IF(AND(ISNUMBER(G19),ISNUMBER(H19),G19<='项目驾驶舱'!$B$3,H19>='项目驾驶舱'!$B$3),"进行中","计划中"))) | K19: =IF(J19="待估算","补充投入工时",IF(AND(H19<'项目驾驶舱'!$B$3,F19<>"已完成"),"确认延期和后续安排","按计划跟踪"))
C20: T002 | D20: 修改车辆信息 | E20: 第一批次 | F20: =IF(OR(M5="挂起",M5="暂停",Q5="挂起",Q5="暂停",U5="挂起",U5="暂停",Y5="挂起",Y5="暂停"),"暂停","已完成") | G20: 46209 | H20: 46225 | I20: 40 | J20: =IF(I20="","待估算",IF(F20="已完成","已结束",IF(AND(ISNUMBER(G20),ISNUMBER(H20),G20<='项目驾驶舱'!$B$3,H20>='项目驾驶舱'!$B$3),"进行中","计划中"))) | K20: =IF(J20="待估算","补充投入工时",IF(AND(H20<'项目驾驶舱'!$B$3,F20<>"已完成"),"确认延期和后续安排","按计划跟踪"))
C21: T003 | D21: 删除车辆信息 | E21: 第一批次 | F21: =IF(OR(M6="挂起",M6="暂停",Q6="挂起",Q6="暂停",U6="挂起",U6="暂停",Y6="挂起",Y6="暂停"),"暂停","已完成") | G21: 46209 | H21: 46225 | I21: 40 | J21: =IF(I21="","待估算",IF(F21="已完成","已结束",IF(AND(ISNUMBER(G21),ISNUMBER(H21),G21<='项目驾驶舱'!$B$3,H21>='项目驾驶舱'!$B$3),"进行中","计划中"))) | K21: =IF(J21="待估算","补充投入工时",IF(AND(H21<'项目驾驶舱'!$B$3,F21<>"已完成"),"确认延期和后续安排","按计划跟踪"))
C22: T004 | D22: 查询展示车辆信息 | E22: 第一批次 | F22: =IF(OR(M7="挂起",M7="暂停",Q7="挂起",Q7="暂停",U7="挂起",U7="暂停",Y7="挂起",Y7="暂停"),"暂停","已完成") | G22: 46209 | H22: 46225 | I22: 40 | J22: =IF(I22="","待估算",IF(F22="已完成","已结束",IF(AND(ISNUMBER(G22),ISNUMBER(H22),G22<='项目驾驶舱'!$B$3,H22>='项目驾驶舱'!$B$3),"进行中","计划中"))) | K22: =IF(J22="待估算","补充投入工时",IF(AND(H22<'项目驾驶舱'!$B$3,F22<>"已完成"),"确认延期和后续安排","按计划跟踪"))
C23: T006 | D23: 优化收费标准（装卸费）新增 | E23: 第一批次 | F23: =IF(OR(M9="挂起",M9="暂停",Q9="挂起",Q9="暂停",U9="挂起",U9="暂停",Y9="挂起",Y9="暂停"),"暂停","已完成") | G23: 46209 | H23: 46227 | I23: 40 | J23: =IF(I23="","待估算",IF(F23="已完成","已结束",IF(AND(ISNUMBER(G23),ISNUMBER(H23),G23<='项目驾驶舱'!$B$3,H23>='项目驾驶舱'!$B$3),"进行中","计划中"))) | K23: =IF(J23="待估算","补充投入工时",IF(AND(H23<'项目驾驶舱'!$B$3,F23<>"已完成"),"确认延期和后续安排","按计划跟踪"))
C24: T007 | D24: 优化收费标准（装卸费）编辑 | E24: 第一批次 | F24: =IF(OR(M10="挂起",M10="暂停",Q10="挂起",Q10="暂停",U10="挂起",U10="暂停",Y10="挂起",Y10="暂停"),"暂停","已完成") | G24: 46209 | H24: 46227 | I24: 40 | J24: =IF(I24="","待估算",IF(F24="已完成","已结束",IF(AND(ISNUMBER(G24),ISNUMBER(H24),G24<='项目驾驶舱'!$B$3,H24>='项目驾驶舱'!$B$3),"进行中","计划中"))) | K24: =IF(J24="待估算","补充投入工时",IF(AND(H24<'项目驾驶舱'!$B$3,F24<>"已完成"),"确认延期和后续安排","按计划跟踪"))
C25: T008 | D25: 优化收费标准（装卸费）详情 | E25: 第一批次 | F25: =IF(OR(M11="挂起",M11="暂停",Q11="挂起",Q11="暂停",U11="挂起",U11="暂停",Y11="挂起",Y11="暂停"),"暂停","已完成") | G25: 46209 | H25: 46227 | I25: 40 | J25: =IF(I25="","待估算",IF(F25="已完成","已结束",IF(AND(ISNUMBER(G25),ISNUMBER(H25),G25<='项目驾驶舱'!$B$3,H25>='项目驾驶舱'!$B$3),"进行中","计划中"))) | K25: =IF(J25="待估算","补充投入工时",IF(AND(H25<'项目驾驶舱'!$B$3,F25<>"已完成"),"确认延期和后续安排","按计划跟踪"))
C26: T009 | D26: 优化采样方式新增 | E26: 第一批次 | F26: =IF(OR(M12="挂起",M12="暂停",Q12="挂起",Q12="暂停",U12="挂起",U12="暂停",Y12="挂起",Y12="暂停"),"暂停","已完成") | G26: 46209 | H26: 46227 | I26: 40 | J26: =IF(I26="","待估算",IF(F26="已完成","已结束",IF(AND(ISNUMBER(G26),ISNUMBER(H26),G26<='项目驾驶舱'!$B$3,H26>='项目驾驶舱'!$B$3),"进行中","计划中"))) | K26: =IF(J26="待估算","补充投入工时",IF(AND(H26<'项目驾驶舱'!$B$3,F26<>"已完成"),"确认延期和后续安排","按计划跟踪"))
C27: T010 | D27: 优化采样方式编辑 | E27: 第一批次 | F27: =IF(OR(M13="挂起",M13="暂停",Q13="挂起",Q13="暂停",U13="挂起",U13="暂停",Y13="挂起",Y13="暂停"),"暂停","已完成") | G27: 46209 | H27: 46227 | I27: 40 | J27: =IF(I27="","待估算",IF(F27="已完成","已结束",IF(AND(ISNUMBER(G27),ISNUMBER(H27),G27<='项目驾驶舱'!$B$3,H27>='项目驾驶舱'!$B$3),"进行中","计划中"))) | K27: =IF(J27="待估算","补充投入工时",IF(AND(H27<'项目驾驶舱'!$B$3,F27<>"已完成"),"确认延期和后续安排","按计划跟踪"))
A28: 刘凯 | B28: 后端 | C28: T011 | D28: 获取报单数据及展示 | E28: 第一批次 | F28: =IF(OR(M14="挂起",M14="暂停",Q14="挂起",Q14="暂停",U14="挂起",U14="暂停",Y14="挂起",Y14="暂停"),"暂停","已完成") | G28: 46209 | H28: 46227 | I28: 40 | J28: =IF(I28="","待估算",IF(F28="已完成","已结束",IF(AND(ISNUMBER(G28),ISNUMBER(H28),G28<='项目驾驶舱'!$B$3,H28>='项目驾驶舱'!$B$3),"进行中","计划中"))) | K28: =IF(J28="待估算","补充投入工时",IF(AND(H28<'项目驾驶舱'!$B$3,F28<>"已完成"),"确认延期和后续安排","按计划跟踪"))
C29: T012 | D29: 应单入口 | E29: 第一批次 | F29: =IF(OR(M15="挂起",M15="暂停",Q15="挂起",Q15="暂停",U15="挂起",U15="暂停",Y15="挂起",Y15="暂停"),"暂停","已完成") | G29: 46209 | H29: 46227 | I29: 40 | J29: =IF(I29="","待估算",IF(F29="已完成","已结束",IF(AND(ISNUMBER(G29),ISNUMBER(H29),G29<='项目驾驶舱'!$B$3,H29>='项目驾驶舱'!$B$3),"进行中","计划中"))) | K29: =IF(J29="待估算","补充投入工时",IF(AND(H29<'项目驾驶舱'!$B$3,F29<>"已完成"),"确认延期和后续安排","按计划跟踪"))
C30: T060 | D30: 货权录入 | E30: 第一批次 | F30: =IF(OR(M63="挂起",M63="暂停",Q63="挂起",Q63="暂停",U63="挂起",U63="暂停",Y63="挂起",Y63="暂停"),"暂停","已完成") | G30: 46209 | H30: 46227 | I30: 40 | J30: =IF(I30="","待估算",IF(F30="已完成","已结束",IF(AND(ISNUMBER(G30),ISNUMBER(H30),G30<='项目驾驶舱'!$B$3,H30>='项目驾驶舱'!$B$3),"进行中","计划中"))) | K30: =IF(J30="待估算","补充投入工时",IF(AND(H30<'项目驾驶舱'!$B$3,F30<>"已完成"),"确认延期和后续安排","按计划跟踪"))
C31: T061 | D31: 货权修改 | E31: 第一批次 | F31: =IF(OR(M64="挂起",M64="暂停",Q64="挂起",Q64="暂停",U64="挂起",U64="暂停",Y64="挂起",Y64="暂停"),"暂停","已完成") | G31: 46209 | H31: 46227 | I31: 40 | J31: =IF(I31="","待估算",IF(F31="已完成","已结束",IF(AND(ISNUMBER(G31),ISNUMBER(H31),G31<='项目驾驶舱'!$B$3,H31>='项目驾驶舱'!$B$3),"进行中","计划中"))) | K31: =IF(J31="待估算","补充投入工时",IF(AND(H31<'项目驾驶舱'!$B$3,F31<>"已完成"),"确认延期和后续安排","按计划跟踪"))
C32: T062 | D32: 获取查询 | E32: 第一批次 | F32: =IF(OR(M65="挂起",M65="暂停",Q65="挂起",Q65="暂停",U65="挂起",U65="暂停",Y65="挂起",Y65="暂停"),"暂停","已完成") | G32: 46209 | H32: 46227 | I32: 40 | J32: =IF(I32="","待估算",IF(F32="已完成","已结束",IF(AND(ISNUMBER(G32),ISNUMBER(H32),G32<='项目驾驶舱'!$B$3,H32>='项目驾驶舱'!$B$3),"进行中","计划中"))) | K32: =IF(J32="待估算","补充投入工时",IF(AND(H32<'项目驾驶舱'!$B$3,F32<>"已完成"),"确认延期和后续安排","按计划跟踪"))
C33: T063 | D33: 卸船作业货权跟踪 | E33: 第一批次 | F33: =IF(OR(M66="挂起",M66="暂停",Q66="挂起",Q66="暂停",U66="挂起",U66="暂停",Y66="挂起",Y66="暂停"),"暂停","已完成") | G33: 46209 | H33: 46227 | I33: 40 | J33: =IF(I33="","待估算",IF(F33="已完成","已结束",IF(AND(ISNUMBER(G33),ISNUMBER(H33),G33<='项目驾驶舱'!$B$3,H33>='项目驾驶舱'!$B$3),"进行中","计划中"))) | K33: =IF(J33="待估算","补充投入工时",IF(AND(H33<'项目驾驶舱'!$B$3,F33<>"已完成"),"确认延期和后续安排","按计划跟踪"))
C34: T064 | D34: 卸船作业货权跟踪 | E34: 第一批次 | F34: =IF(OR(M67="挂起",M67="暂停",Q67="挂起",Q67="暂停",U67="挂起",U67="暂停",Y67="挂起",Y67="暂停"),"暂停","已完成") | G34: 46209 | H34: 46227 | I34: 40 | J34: =IF(I34="","待估算",IF(F34="已完成","已结束",IF(AND(ISNUMBER(G34),ISNUMBER(H34),G34<='项目驾驶舱'!$B$3,H34>='项目驾驶舱'!$B$3),"进行中","计划中"))) | K34: =IF(J34="待估算","补充投入工时",IF(AND(H34<'项目驾驶舱'!$B$3,F34<>"已完成"),"确认延期和后续安排","按计划跟踪"))
C35: T065 | D35: 装船作业货权跟踪 | E35: 第一批次 | F35: =IF(OR(M68="挂起",M68="暂停",Q68="挂起",Q68="暂停",U68="挂起",U68="暂停",Y68="挂起",Y68="暂停"),"暂停","已完成") | G35: 46209 | H35: 46227 | I35: 40 | J35: =IF(I35="","待估算",IF(F35="已完成","已结束",IF(AND(ISNUMBER(G35),ISNUMBER(H35),G35<='项目驾驶舱'!$B$3,H35>='项目驾驶舱'!$B$3),"进行中","计划中"))) | K35: =IF(J35="待估算","补充投入工时",IF(AND(H35<'项目驾驶舱'!$B$3,F35<>"已完成"),"确认延期和后续安排","按计划跟踪"))
C36: T066 | D36: 装船作业货权跟踪 | E36: 第一批次 | F36: =IF(OR(M69="挂起",M69="暂停",Q69="挂起",Q69="暂停",U69="挂起",U69="暂停",Y69="挂起",Y69="暂停"),"暂停","已完成") | G36: 46209 | H36: 46227 | I36: 40 | J36: =IF(I36="","待估算",IF(F36="已完成","已结束",IF(AND(ISNUMBER(G36),ISNUMBER(H36),G36<='项目驾驶舱'!$B$3,H36>='项目驾驶舱'!$B$3),"进行中","计划中"))) | K36: =IF(J36="待估算","补充投入工时",IF(AND(H36<'项目驾驶舱'!$B$3,F36<>"已完成"),"确认延期和后续安排","按计划跟踪"))
C37: T067 | D37: 装船作业货权跟踪 | E37: 第一批次 | F37: =IF(OR(M70="挂起",M70="暂停",Q70="挂起",Q70="暂停",U70="挂起",U70="暂停",Y70="挂起",Y70="暂停"),"暂停","已完成") | G37: 46209 | H37: 46227 | I37: 40 | J37: =IF(I37="","待估算",IF(F37="已完成","已结束",IF(AND(ISNUMBER(G37),ISNUMBER(H37),G37<='项目驾驶舱'!$B$3,H37>='项目驾驶舱'!$B$3),"进行中","计划中"))) | K37: =IF(J37="待估算","补充投入工时",IF(AND(H37<'项目驾驶舱'!$B$3,F37<>"已完成"),"确认延期和后续安排","按计划跟踪"))
C38: T068 | D38: 装船作业货权跟踪 | E38: 第一批次 | F38: =IF(OR(M71="挂起",M71="暂停",Q71="挂起",Q71="暂停",U71="挂起",U71="暂停",Y71="挂起",Y71="暂停"),"暂停","已完成") | G38: 46209 | H38: 46227 | I38: 40 | J38: =IF(I38="","待估算",IF(F38="已完成","已结束",IF(AND(ISNUMBER(G38),ISNUMBER(H38),G38<='项目驾驶舱'!$B$3,H38>='项目驾驶舱'!$B$3),"进行中","计划中"))) | K38: =IF(J38="待估算","补充投入工时",IF(AND(H38<'项目驾驶舱'!$B$3,F38<>"已完成"),"确认延期和后续安排","按计划跟踪"))
C39: T072 | D39: OCR识别 | E39: 第一批次 | F39: =IF(OR(M75="挂起",M75="暂停",Q75="挂起",Q75="暂停",U75="挂起",U75="暂停",Y75="挂起",Y75="暂停"),"暂停","已完成") | G39: 46209 | H39: 46225 | I39: 40 | J39: =IF(I39="","待估算",IF(F39="已完成","已结束",IF(AND(ISNUMBER(G39),ISNUMBER(H39),G39<='项目驾驶舱'!$B$3,H39>='项目驾驶舱'!$B$3),"进行中","计划中"))) | K39: =IF(J39="待估算","补充投入工时",IF(AND(H39<'项目驾驶舱'!$B$3,F39<>"已完成"),"确认延期和后续安排","按计划跟踪"))
A40: 刘凯 | B40: 后端 | C40: T096 | D40: 自动生成装船港杂费 | E40: 第一批次 | F40: =IF(OR(M99="挂起",M99="暂停",Q99="挂起",Q99="暂停",U99="挂起",U99="暂停",Y99="挂起",Y99="暂停"),"暂停","已完成") | G40: 46209 | H40: 46225 | I40: 40 | J40: =IF(I40="","待估算",IF(F40="已完成","已结束",IF(AND(ISNUMBER(G40),ISNUMBER(H40),G40<='项目驾驶舱'!$B$3,H40>='项目驾驶舱'!$B$3),"进行中","计划中"))) | K40: =IF(J40="待估算","补充投入工时",IF(AND(H40<'项目驾驶舱'!$B$3,F40<>"已完成"),"确认延期和后续安排","按计划跟踪"))
C41: T073 | D41: 采样作业信息录入新增 | E41: 第一批次 | F41: =IF(OR(M76="挂起",M76="暂停",Q76="挂起",Q76="暂停",U76="挂起",U76="暂停",Y76="挂起",Y76="暂停"),"暂停","已完成") | G41: 46227 | H41: 46227 | I41: 40 | J41: =IF(I41="","待估算",IF(F41="已完成","已结束",IF(AND(ISNUMBER(G41),ISNUMBER(H41),G41<='项目驾驶舱'!$B$3,H41>='项目驾驶舱'!$B$3),"进行中","计划中"))) | K41: =IF(J41="待估算","补充投入工时",IF(AND(H41<'项目驾驶舱'!$B$3,F41<>"已完成"),"确认延期和后续安排","按计划跟踪"))
C42: T074 | D42: 采样作业信息录入编辑 | E42: 第一批次 | F42: =IF(OR(M77="挂起",M77="暂停",Q77="挂起",Q77="暂停",U77="挂起",U77="暂停",Y77="挂起",Y77="暂停"),"暂停","已完成") | G42: 46227 | H42: 46227 | I42: 40 | J42: =IF(I42="","待估算",IF(F42="已完成","已结束",IF(AND(ISNUMBER(G42),ISNUMBER(H42),G42<='项目驾驶舱'!$B$3,H42>='项目驾驶舱'!$B$3),"进行中","计划中"))) | K42: =IF(J42="待估算","补充投入工时",IF(AND(H42<'项目驾驶舱'!$B$3,F42<>"已完成"),"确认延期和后续安排","按计划跟踪"))
C43: T075 | D43: 采样作业信息录入详情 | E43: 第一批次 | F43: =IF(OR(M78="挂起",M78="暂停",Q78="挂起",Q78="暂停",U78="挂起",U78="暂停",Y78="挂起",Y78="暂停"),"暂停","已完成") | G43: 46227 | H43: 46227 | I43: 40 | J43: =IF(I43="","待估算",IF(F43="已完成","已结束",IF(AND(ISNUMBER(G43),ISNUMBER(H43),G43<='项目驾驶舱'!$B$3,H43>='项目驾驶舱'!$B$3),"进行中","计划中"))) | K43: =IF(J43="待估算","补充投入工时",IF(AND(H43<'项目驾驶舱'!$B$3,F43<>"已完成"),"确认延期和后续安排","按计划跟踪"))
C44: T076 | D44: 采样作业信息录入删除 | E44: 第一批次 | F44: =IF(OR(M79="挂起",M79="暂停",Q79="挂起",Q79="暂停",U79="挂起",U79="暂停",Y79="挂起",Y79="暂停"),"暂停","已完成") | G44: 46227 | H44: 46227 | I44: 40 | J44: =IF(I44="","待估算",IF(F44="已完成","已结束",IF(AND(ISNUMBER(G44),ISNUMBER(H44),G44<='项目驾驶舱'!$B$3,H44>='项目驾驶舱'!$B$3),"进行中","计划中"))) | K44: =IF(J44="待估算","补充投入工时",IF(AND(H44<'项目驾驶舱'!$B$3,F44<>"已完成"),"确认延期和后续安排","按计划跟踪"))
C45: T077 | D45: 采样作业信息录入列表 | E45: 第一批次 | F45: =IF(OR(M80="挂起",M80="暂停",Q80="挂起",Q80="暂停",U80="挂起",U80="暂停",Y80="挂起",Y80="暂停"),"暂停","已完成") | G45: 46227 | H45: 46227 | I45: 40 | J45: =IF(I45="","待估算",IF(F45="已完成","已结束",IF(AND(ISNUMBER(G45),ISNUMBER(H45),G45<='项目驾驶舱'!$B$3,H45>='项目驾驶舱'!$B$3),"进行中","计划中"))) | K45: =IF(J45="待估算","补充投入工时",IF(AND(H45<'项目驾驶舱'!$B$3,F45<>"已完成"),"确认延期和后续安排","按计划跟踪"))
C46: T097 | D46: 自动生成租赁费 | E46: 第一批次 | F46: =IF(OR(M100="挂起",M100="暂停",Q100="挂起",Q100="暂停",U100="挂起",U100="暂停",Y100="挂起",Y100="暂停"),"暂停","已完成") | G46: 46227 | H46: 46227 | I46: 40 | J46: =IF(I46="","待估算",IF(F46="已完成","已结束",IF(AND(ISNUMBER(G46),ISNUMBER(H46),G46<='项目驾驶舱'!$B$3,H46>='项目驾驶舱'!$B$3),"进行中","计划中"))) | K46: =IF(J46="待估算","补充投入工时",IF(AND(H46<'项目驾驶舱'!$B$3,F46<>"已完成"),"确认延期和后续安排","按计划跟踪"))
C47: T098 | D47: 优化装卸费新增 | E47: 第一批次 | F47: =IF(OR(M101="挂起",M101="暂停",Q101="挂起",Q101="暂停",U101="挂起",U101="暂停",Y101="挂起",Y101="暂停"),"暂停","已完成") | G47: 46227 | H47: 46227 | I47: 40 | J47: =IF(I47="","待估算",IF(F47="已完成","已结束",IF(AND(ISNUMBER(G47),ISNUMBER(H47),G47<='项目驾驶舱'!$B$3,H47>='项目驾驶舱'!$B$3),"进行中","计划中"))) | K47: =IF(J47="待估算","补充投入工时",IF(AND(H47<'项目驾驶舱'!$B$3,F47<>"已完成"),"确认延期和后续安排","按计划跟踪"))
C48: T099 | D48: 优化装卸费编辑 | E48: 第一批次 | F48: =IF(OR(M102="挂起",M102="暂停",Q102="挂起",Q102="暂停",U102="挂起",U102="暂停",Y102="挂起",Y102="暂停"),"暂停","已完成") | G48: 46227 | H48: 46227 | I48: 40 | J48: =IF(I48="","待估算",IF(F48="已完成","已结束",IF(AND(ISNUMBER(G48),ISNUMBER(H48),G48<='项目驾驶舱'!$B$3,H48>='项目驾驶舱'!$B$3),"进行中","计划中"))) | K48: =IF(J48="待估算","补充投入工时",IF(AND(H48<'项目驾驶舱'!$B$3,F48<>"已完成"),"确认延期和后续安排","按计划跟踪"))
C49: T037 | D49: 创建卸车流程 | E49: 第一批次 | F49: =IF(OR(M40="挂起",M40="暂停",Q40="挂起",Q40="暂停",U40="挂起",U40="暂停",Y40="挂起",Y40="暂停"),"暂停","已完成") | G49: 46230 | H49: 46262 | I49: 40 | J49: =IF(I49="","待估算",IF(F49="已完成","已结束",IF(AND(ISNUMBER(G49),ISNUMBER(H49),G49<='项目驾驶舱'!$B$3,H49>='项目驾驶舱'!$B$3),"进行中","计划中"))) | K49: =IF(J49="待估算","补充投入工时",IF(AND(H49<'项目驾驶舱'!$B$3,F49<>"已完成"),"确认延期和后续安排","按计划跟踪"))
C50: T038 | D50: 查询卸车流程 | E50: 第一批次 | F50: =IF(OR(M41="挂起",M41="暂停",Q41="挂起",Q41="暂停",U41="挂起",U41="暂停",Y41="挂起",Y41="暂停"),"暂停","已完成") | G50: 46230 | H50: 46262 | I50: 40 | J50: =IF(I50="","待估算",IF(F50="已完成","已结束",IF(AND(ISNUMBER(G50),ISNUMBER(H50),G50<='项目驾驶舱'!$B$3,H50>='项目驾驶舱'!$B$3),"进行中","计划中"))) | K50: =IF(J50="待估算","补充投入工时",IF(AND(H50<'项目驾驶舱'!$B$3,F50<>"已完成"),"确认延期和后续安排","按计划跟踪"))
C51: T039 | D51: 修改卸车流程 | E51: 第一批次 | F51: =IF(OR(M42="挂起",M42="暂停",Q42="挂起",Q42="暂停",U42="挂起",U42="暂停",Y42="挂起",Y42="暂停"),"暂停","已完成") | G51: 46230 | H51: 46262 | I51: 40 | J51: =IF(I51="","待估算",IF(F51="已完成","已结束",IF(AND(ISNUMBER(G51),ISNUMBER(H51),G51<='项目驾驶舱'!$B$3,H51>='项目驾驶舱'!$B$3),"进行中","计划中"))) | K51: =IF(J51="待估算","补充投入工时",IF(AND(H51<'项目驾驶舱'!$B$3,F51<>"已完成"),"确认延期和后续安排","按计划跟踪"))
A52: 刘凯 | B52: 后端 | C52: T040 | D52: 创建装船流程 | E52: 第一批次 | F52: =IF(OR(M43="挂起",M43="暂停",Q43="挂起",Q43="暂停",U43="挂起",U43="暂停",Y43="挂起",Y43="暂停"),"暂停","已完成") | G52: 46230 | H52: 46262 | I52: 40 | J52: =IF(I52="","待估算",IF(F52="已完成","已结束",IF(AND(ISNUMBER(G52),ISNUMBER(H52),G52<='项目驾驶舱'!$B$3,H52>='项目驾驶舱'!$B$3),"进行中","计划中"))) | K52: =IF(J52="待估算","补充投入工时",IF(AND(H52<'项目驾驶舱'!$B$3,F52<>"已完成"),"确认延期和后续安排","按计划跟踪"))
C53: T041 | D53: 查询装船流程 | E53: 第一批次 | F53: =IF(OR(M44="挂起",M44="暂停",Q44="挂起",Q44="暂停",U44="挂起",U44="暂停",Y44="挂起",Y44="暂停"),"暂停","已完成") | G53: 46230 | H53: 46262 | I53: 40 | J53: =IF(I53="","待估算",IF(F53="已完成","已结束",IF(AND(ISNUMBER(G53),ISNUMBER(H53),G53<='项目驾驶舱'!$B$3,H53>='项目驾驶舱'!$B$3),"进行中","计划中"))) | K53: =IF(J53="待估算","补充投入工时",IF(AND(H53<'项目驾驶舱'!$B$3,F53<>"已完成"),"确认延期和后续安排","按计划跟踪"))
C54: T042 | D54: 修改装船流程 | E54: 第一批次 | F54: =IF(OR(M45="挂起",M45="暂停",Q45="挂起",Q45="暂停",U45="挂起",U45="暂停",Y45="挂起",Y45="暂停"),"暂停","已完成") | G54: 46230 | H54: 46262 | I54: 40 | J54: =IF(I54="","待估算",IF(F54="已完成","已结束",IF(AND(ISNUMBER(G54),ISNUMBER(H54),G54<='项目驾驶舱'!$B$3,H54>='项目驾驶舱'!$B$3),"进行中","计划中"))) | K54: =IF(J54="待估算","补充投入工时",IF(AND(H54<'项目驾驶舱'!$B$3,F54<>"已完成"),"确认延期和后续安排","按计划跟踪"))
C55: T043 | D55: 创建卸船流程 | E55: 第二批次 | F55: =IF(OR(M46="挂起",M46="暂停",Q46="挂起",Q46="暂停",U46="挂起",U46="暂停",Y46="挂起",Y46="暂停"),"暂停","已完成") | G55: 46230 | H55: 46262 | I55: 40 | J55: =IF(I55="","待估算",IF(F55="已完成","已结束",IF(AND(ISNUMBER(G55),ISNUMBER(H55),G55<='项目驾驶舱'!$B$3,H55>='项目驾驶舱'!$B$3),"进行中","计划中"))) | K55: =IF(J55="待估算","补充投入工时",IF(AND(H55<'项目驾驶舱'!$B$3,F55<>"已完成"),"确认延期和后续安排","按计划跟踪"))
C56: T044 | D56: 查询卸船流程 | E56: 第二批次 | F56: =IF(OR(M47="挂起",M47="暂停",Q47="挂起",Q47="暂停",U47="挂起",U47="暂停",Y47="挂起",Y47="暂停"),"暂停","已完成") | G56: 46230 | H56: 46262 | I56: 40 | J56: =IF(I56="","待估算",IF(F56="已完成","已结束",IF(AND(ISNUMBER(G56),ISNUMBER(H56),G56<='项目驾驶舱'!$B$3,H56>='项目驾驶舱'!$B$3),"进行中","计划中"))) | K56: =IF(J56="待估算","补充投入工时",IF(AND(H56<'项目驾驶舱'!$B$3,F56<>"已完成"),"确认延期和后续安排","按计划跟踪"))
C57: T045 | D57: 修改卸船流程 | E57: 第二批次 | F57: =IF(OR(M48="挂起",M48="暂停",Q48="挂起",Q48="暂停",U48="挂起",U48="暂停",Y48="挂起",Y48="暂停"),"暂停","已完成") | G57: 46230 | H57: 46262 | I57: 40 | J57: =IF(I57="","待估算",IF(F57="已完成","已结束",IF(AND(ISNUMBER(G57),ISNUMBER(H57),G57<='项目驾驶舱'!$B$3,H57>='项目驾驶舱'!$B$3),"进行中","计划中"))) | K57: =IF(J57="待估算","补充投入工时",IF(AND(H57<'项目驾驶舱'!$B$3,F57<>"已完成"),"确认延期和后续安排","按计划跟踪"))
C58: T059 | D58: 优化新增装车作业信息 | E58: 第一批次 | F58: =IF(OR(M62="挂起",M62="暂停",Q62="挂起",Q62="暂停",U62="挂起",U62="暂停",Y62="挂起",Y62="暂停"),"暂停","已完成") | G58: 46230 | H58: 46241 | I58: 40 | J58: =IF(I58="","待估算",IF(F58="已完成","已结束",IF(AND(ISNUMBER(G58),ISNUMBER(H58),G58<='项目驾驶舱'!$B$3,H58>='项目驾驶舱'!$B$3),"进行中","计划中"))) | K58: =IF(J58="待估算","补充投入工时",IF(AND(H58<'项目驾驶舱'!$B$3,F58<>"已完成"),"确认延期和后续安排","按计划跟踪"))
C59: T104 | D59: 吞吐量统计（曹妃甸） | E59: 第一批次 | F59: =IF(OR(M107="挂起",M107="暂停",Q107="挂起",Q107="暂停",U107="挂起",U107="暂停",Y107="挂起",Y107="暂停"),"暂停","已完成") | G59: 46230 | H59: 46262 | I59: 40 | J59: =IF(I59="","待估算",IF(F59="已完成","已结束",IF(AND(ISNUMBER(G59),ISNUMBER(H59),G59<='项目驾驶舱'!$B$3,H59>='项目驾驶舱'!$B$3),"进行中","计划中"))) | K59: =IF(J59="待估算","补充投入工时",IF(AND(H59<'项目驾驶舱'!$B$3,F59<>"已完成"),"确认延期和后续安排","按计划跟踪"))
C60: T105 | D60: 泊位占用率分析（曹妃甸） | E60: 第一批次 | F60: =IF(OR(M108="挂起",M108="暂停",Q108="挂起",Q108="暂停",U108="挂起",U108="暂停",Y108="挂起",Y108="暂停"),"暂停","已完成") | G60: 46230 | H60: 46262 | I60: 40 | J60: =IF(I60="","待估算",IF(F60="已完成","已结束",IF(AND(ISNUMBER(G60),ISNUMBER(H60),G60<='项目驾驶舱'!$B$3,H60>='项目驾驶舱'!$B$3),"进行中","计划中"))) | K60: =IF(J60="待估算","补充投入工时",IF(AND(H60<'项目驾驶舱'!$B$3,F60<>"已完成"),"确认延期和后续安排","按计划跟踪"))
C61: T106 | D61: 堆存库存统计（曹妃甸） | E61: 第一批次 | F61: =IF(OR(M109="挂起",M109="暂停",Q109="挂起",Q109="暂停",U109="挂起",U109="暂停",Y109="挂起",Y109="暂停"),"暂停","已完成") | G61: 46230 | H61: 46262 | I61: 40 | J61: =IF(I61="","待估算",IF(F61="已完成","已结束",IF(AND(ISNUMBER(G61),ISNUMBER(H61),G61<='项目驾驶舱'!$B$3,H61>='项目驾驶舱'!$B$3),"进行中","计划中"))) | K61: =IF(J61="待估算","补充投入工时",IF(AND(H61<'项目驾驶舱'!$B$3,F61<>"已完成"),"确认延期和后续安排","按计划跟踪"))
C62: T107 | D62: 分货主实时统计表（曹妃甸） | E62: 第一批次 | F62: =IF(OR(M110="挂起",M110="暂停",Q110="挂起",Q110="暂停",U110="挂起",U110="暂停",Y110="挂起",Y110="暂停"),"暂停","已完成") | G62: 46230 | H62: 46262 | I62: 40 | J62: =IF(I62="","待估算",IF(F62="已完成","已结束",IF(AND(ISNUMBER(G62),ISNUMBER(H62),G62<='项目驾驶舱'!$B$3,H62>='项目驾驶舱'!$B$3),"进行中","计划中"))) | K62: =IF(J62="待估算","补充投入工时",IF(AND(H62<'项目驾驶舱'!$B$3,F62<>"已完成"),"确认延期和后续安排","按计划跟踪"))
C63: T108 | D63: 综合装船效率分析（曹妃甸） | E63: 第一批次 | F63: =IF(OR(M111="挂起",M111="暂停",Q111="挂起",Q111="暂停",U111="挂起",U111="暂停",Y111="挂起",Y111="暂停"),"暂停","已完成") | G63: 46230 | H63: 46262 | I63: 40 | J63: =IF(I63="","待估算",IF(F63="已完成","已结束",IF(AND(ISNUMBER(G63),ISNUMBER(H63),G63<='项目驾驶舱'!$B$3,H63>='项目驾驶舱'!$B$3),"进行中","计划中"))) | K63: =IF(J63="待估算","补充投入工时",IF(AND(H63<'项目驾驶舱'!$B$3,F63<>"已完成"),"确认延期和后续安排","按计划跟踪"))
A64: 刘凯 | B64: 后端 | C64: T109 | D64: 综合卸车效率分析（曹妃甸） | E64: 第一批次 | F64: =IF(OR(M112="挂起",M112="暂停",Q112="挂起",Q112="暂停",U112="挂起",U112="暂停",Y112="挂起",Y112="暂停"),"暂停","已完成") | G64: 46230 | H64: 46262 | I64: 40 | J64: =IF(I64="","待估算",IF(F64="已完成","已结束",IF(AND(ISNUMBER(G64),ISNUMBER(H64),G64<='项目驾驶舱'!$B$3,H64>='项目驾驶舱'!$B$3),"进行中","计划中"))) | K64: =IF(J64="待估算","补充投入工时",IF(AND(H64<'项目驾驶舱'!$B$3,F64<>"已完成"),"确认延期和后续安排","按计划跟踪"))
C65: T110 | D65: 综合卸船效率分析（曹妃甸） | E65: 第二批次 | F65: =IF(OR(M113="挂起",M113="暂停",Q113="挂起",Q113="暂停",U113="挂起",U113="暂停",Y113="挂起",Y113="暂停"),"暂停","已完成") | G65: 46230 | H65: 46262 | I65: 40 | J65: =IF(I65="","待估算",IF(F65="已完成","已结束",IF(AND(ISNUMBER(G65),ISNUMBER(H65),G65<='项目驾驶舱'!$B$3,H65>='项目驾驶舱'!$B$3),"进行中","计划中"))) | K65: =IF(J65="待估算","补充投入工时",IF(AND(H65<'项目驾驶舱'!$B$3,F65<>"已完成"),"确认延期和后续安排","按计划跟踪"))
C66: T117 | D66: 经营任务情况分析报告 | E66: 第一批次 | F66: =IF(OR(M120="挂起",M120="暂停",Q120="挂起",Q120="暂停",U120="挂起",U120="暂停",Y120="挂起",Y120="暂停"),"暂停","已完成") | G66: 46230 | H66: 46262 | I66: 40 | J66: =IF(I66="","待估算",IF(F66="已完成","已结束",IF(AND(ISNUMBER(G66),ISNUMBER(H66),G66<='项目驾驶舱'!$B$3,H66>='项目驾驶舱'!$B$3),"进行中","计划中"))) | K66: =IF(J66="待估算","补充投入工时",IF(AND(H66<'项目驾驶舱'!$B$3,F66<>"已完成"),"确认延期和后续安排","按计划跟踪"))
C67: T118 | D67: 客户月报报告 | E67: 第一批次 | F67: =IF(OR(M121="挂起",M121="暂停",Q121="挂起",Q121="暂停",U121="挂起",U121="暂停",Y121="挂起",Y121="暂停"),"暂停","已完成") | G67: 46230 | H67: 46262 | I67: 40 | J67: =IF(I67="","待估算",IF(F67="已完成","已结束",IF(AND(ISNUMBER(G67),ISNUMBER(H67),G67<='项目驾驶舱'!$B$3,H67>='项目驾驶舱'!$B$3),"进行中","计划中"))) | K67: =IF(J67="待估算","补充投入工时",IF(AND(H67<'项目驾驶舱'!$B$3,F67<>"已完成"),"确认延期和后续安排","按计划跟踪"))
C68: T119 | D68: 月度客户情况报告 | E68: 第一批次 | F68: =IF(OR(M122="挂起",M122="暂停",Q122="挂起",Q122="暂停",U122="挂起",U122="暂停",Y122="挂起",Y122="暂停"),"暂停","已完成") | G68: 46230 | H68: 46262 | I68: 40 | J68: =IF(I68="","待估算",IF(F68="已完成","已结束",IF(AND(ISNUMBER(G68),ISNUMBER(H68),G68<='项目驾驶舱'!$B$3,H68>='项目驾驶舱'!$B$3),"进行中","计划中"))) | K68: =IF(J68="待估算","补充投入工时",IF(AND(H68<'项目驾驶舱'!$B$3,F68<>"已完成"),"确认延期和后续安排","按计划跟踪"))
C69: T120 | D69: 商务计划周报 | E69: 第一批次 | F69: =IF(OR(M123="挂起",M123="暂停",Q123="挂起",Q123="暂停",U123="挂起",U123="暂停",Y123="挂起",Y123="暂停"),"暂停","已完成") | G69: 46230 | H69: 46262 | I69: 40 | J69: =IF(I69="","待估算",IF(F69="已完成","已结束",IF(AND(ISNUMBER(G69),ISNUMBER(H69),G69<='项目驾驶舱'!$B$3,H69>='项目驾驶舱'!$B$3),"进行中","计划中"))) | K69: =IF(J69="待估算","补充投入工时",IF(AND(H69<'项目驾驶舱'!$B$3,F69<>"已完成"),"确认延期和后续安排","按计划跟踪"))
C70: T138 | D70: 查询卸车流程 | E70: 第二批次 | F70: =IF(OR(M141="挂起",M141="暂停",Q141="挂起",Q141="暂停",U141="挂起",U141="暂停",Y141="挂起",Y141="暂停"),"暂停","已完成") | G70: 46230 | H70: 46262 | I70: 40 | J70: =IF(I70="","待估算",IF(F70="已完成","已结束",IF(AND(ISNUMBER(G70),ISNUMBER(H70),G70<='项目驾驶舱'!$B$3,H70>='项目驾驶舱'!$B$3),"进行中","计划中"))) | K70: =IF(J70="待估算","补充投入工时",IF(AND(H70<'项目驾驶舱'!$B$3,F70<>"已完成"),"确认延期和后续安排","按计划跟踪"))
C71: T139 | D71: 查询装船流程 | E71: 第二批次 | F71: =IF(OR(M142="挂起",M142="暂停",Q142="挂起",Q142="暂停",U142="挂起",U142="暂停",Y142="挂起",Y142="暂停"),"暂停","已完成") | G71: 46230 | H71: 46262 | I71: 40 | J71: =IF(I71="","待估算",IF(F71="已完成","已结束",IF(AND(ISNUMBER(G71),ISNUMBER(H71),G71<='项目驾驶舱'!$B$3,H71>='项目驾驶舱'!$B$3),"进行中","计划中"))) | K71: =IF(J71="待估算","补充投入工时",IF(AND(H71<'项目驾驶舱'!$B$3,F71<>"已完成"),"确认延期和后续安排","按计划跟踪"))
C72: T140 | D72: 查询卸船流程 | E72: 第二批次 | F72: =IF(OR(M143="挂起",M143="暂停",Q143="挂起",Q143="暂停",U143="挂起",U143="暂停",Y143="挂起",Y143="暂停"),"暂停","已完成") | G72: 46230 | H72: 46262 | I72: 40 | J72: =IF(I72="","待估算",IF(F72="已完成","已结束",IF(AND(ISNUMBER(G72),ISNUMBER(H72),G72<='项目驾驶舱'!$B$3,H72>='项目驾驶舱'!$B$3),"进行中","计划中"))) | K72: =IF(J72="待估算","补充投入工时",IF(AND(H72<'项目驾驶舱'!$B$3,F72<>"已完成"),"确认延期和后续安排","按计划跟踪"))
C73: T143 | D73: 图片上传 | E73: 第一批次 | F73: =IF(OR(M146="挂起",M146="暂停",Q146="挂起",Q146="暂停",U146="挂起",U146="暂停",Y146="挂起",Y146="暂停"),"暂停","已完成") | G73: 46237 | H73: 46252 | I73: 40 | J73: =IF(I73="","待估算",IF(F73="已完成","已结束",IF(AND(ISNUMBER(G73),ISNUMBER(H73),G73<='项目驾驶舱'!$B$3,H73>='项目驾驶舱'!$B$3),"进行中","计划中"))) | K73: =IF(J73="待估算","补充投入工时",IF(AND(H73<'项目驾驶舱'!$B$3,F73<>"已完成"),"确认延期和后续安排","按计划跟踪"))
C74: T144 | D74: 图片上传 | E74: 第一批次 | F74: =IF(OR(M147="挂起",M147="暂停",Q147="挂起",Q147="暂停",U147="挂起",U147="暂停",Y147="挂起",Y147="暂停"),"暂停","已完成") | G74: 46237 | H74: 46252 | I74: 40 | J74: =IF(I74="","待估算",IF(F74="已完成","已结束",IF(AND(ISNUMBER(G74),ISNUMBER(H74),G74<='项目驾驶舱'!$B$3,H74>='项目驾驶舱'!$B$3),"进行中","计划中"))) | K74: =IF(J74="待估算","补充投入工时",IF(AND(H74<'项目驾驶舱'!$B$3,F74<>"已完成"),"确认延期和后续安排","按计划跟踪"))
C75: T145 | D75: 图片上传 | E75: 第二批次 | F75: =IF(OR(M148="挂起",M148="暂停",Q148="挂起",Q148="暂停",U148="挂起",U148="暂停",Y148="挂起",Y148="暂停"),"暂停","已完成") | G75: 46237 | H75: 46252 | I75: 40 | J75: =IF(I75="","待估算",IF(F75="已完成","已结束",IF(AND(ISNUMBER(G75),ISNUMBER(H75),G75<='项目驾驶舱'!$B$3,H75>='项目驾驶舱'!$B$3),"进行中","计划中"))) | K75: =IF(J75="待估算","补充投入工时",IF(AND(H75<'项目驾驶舱'!$B$3,F75<>"已完成"),"确认延期和后续安排","按计划跟踪"))
A76: 刘凯 | B76: 后端 | C76: T121 | D76: 船舶供应服务查询 | E76: 第二批次 | F76: =IF(OR(M124="挂起",M124="暂停",Q124="挂起",Q124="暂停",U124="挂起",U124="暂停",Y124="挂起",Y124="暂停"),"暂停","已完成") | G76: 46265 | H76: 46269 | I76: 40 | J76: =IF(I76="","待估算",IF(F76="已完成","已结束",IF(AND(ISNUMBER(G76),ISNUMBER(H76),G76<='项目驾驶舱'!$B$3,H76>='项目驾驶舱'!$B$3),"进行中","计划中"))) | K76: =IF(J76="待估算","补充投入工时",IF(AND(H76<'项目驾驶舱'!$B$3,F76<>"已完成"),"确认延期和后续安排","按计划跟踪"))
C77: T122 | D77: 船舶预到（内贸）查询 | E77: 第二批次 | F77: =IF(OR(M125="挂起",M125="暂停",Q125="挂起",Q125="暂停",U125="挂起",U125="暂停",Y125="挂起",Y125="暂停"),"暂停","已完成") | G77: 46265 | H77: 46269 | I77: 40 | J77: =IF(I77="","待估算",IF(F77="已完成","已结束",IF(AND(ISNUMBER(G77),ISNUMBER(H77),G77<='项目驾驶舱'!$B$3,H77>='项目驾驶舱'!$B$3),"进行中","计划中"))) | K77: =IF(J77="待估算","补充投入工时",IF(AND(H77<'项目驾驶舱'!$B$3,F77<>"已完成"),"确认延期和后续安排","按计划跟踪"))
C78: T123 | D78: 台账查询 | E78: 第二批次 | F78: =IF(OR(M126="挂起",M126="暂停",Q126="挂起",Q126="暂停",U126="挂起",U126="暂停",Y126="挂起",Y126="暂停"),"暂停","已完成") | G78: 46265 | H78: 46269 | I78: 40 | J78: =IF(I78="","待估算",IF(F78="已完成","已结束",IF(AND(ISNUMBER(G78),ISNUMBER(H78),G78<='项目驾驶舱'!$B$3,H78>='项目驾驶舱'!$B$3),"进行中","计划中"))) | K78: =IF(J78="待估算","补充投入工时",IF(AND(H78<'项目驾驶舱'!$B$3,F78<>"已完成"),"确认延期和后续安排","按计划跟踪"))
C79: T124 | D79: 停泊费（内贸）查询 | E79: 第二批次 | F79: =IF(OR(M127="挂起",M127="暂停",Q127="挂起",Q127="暂停",U127="挂起",U127="暂停",Y127="挂起",Y127="暂停"),"暂停","已完成") | G79: 46265 | H79: 46269 | I79: 40 | J79: =IF(I79="","待估算",IF(F79="已完成","已结束",IF(AND(ISNUMBER(G79),ISNUMBER(H79),G79<='项目驾驶舱'!$B$3,H79>='项目驾驶舱'!$B$3),"进行中","计划中"))) | K79: =IF(J79="待估算","补充投入工时",IF(AND(H79<'项目驾驶舱'!$B$3,F79<>"已完成"),"确认延期和后续安排","按计划跟踪"))
C80: T125 | D80: 船舶供应服务费（内贸）查询 | E80: 第二批次 | F80: =IF(OR(M128="挂起",M128="暂停",Q128="挂起",Q128="暂停",U128="挂起",U128="暂停",Y128="挂起",Y128="暂停"),"暂停","已完成") | G80: 46265 | H80: 46269 | I80: 40 | J80: =IF(I80="","待估算",IF(F80="已完成","已结束",IF(AND(ISNUMBER(G80),ISNUMBER(H80),G80<='项目驾驶舱'!$B$3,H80>='项目驾驶舱'!$B$3),"进行中","计划中"))) | K80: =IF(J80="待估算","补充投入工时",IF(AND(H80<'项目驾驶舱'!$B$3,F80<>"已完成"),"确认延期和后续安排","按计划跟踪"))
C81: T013 | D81: 新增结算条款 | E81: 第二批次 | F81: =IF(OR(M16="挂起",M16="暂停",Q16="挂起",Q16="暂停",U16="挂起",U16="暂停",Y16="挂起",Y16="暂停"),"暂停","未开始") | G81: 46272 | H81: 46304 | I81: 40 | J81: =IF(I81="","待估算",IF(F81="已完成","已结束",IF(AND(ISNUMBER(G81),ISNUMBER(H81),G81<='项目驾驶舱'!$B$3,H81>='项目驾驶舱'!$B$3),"进行中","计划中"))) | K81: =IF(J81="待估算","补充投入工时",IF(AND(H81<'项目驾驶舱'!$B$3,F81<>"已完成"),"确认延期和后续安排","按计划跟踪"))
C82: T014 | D82: 结算条款审批 | E82: 第二批次 | F82: =IF(OR(M17="挂起",M17="暂停",Q17="挂起",Q17="暂停",U17="挂起",U17="暂停",Y17="挂起",Y17="暂停"),"暂停","未开始") | G82: 46272 | H82: 46304 | I82: 40 | J82: =IF(I82="","待估算",IF(F82="已完成","已结束",IF(AND(ISNUMBER(G82),ISNUMBER(H82),G82<='项目驾驶舱'!$B$3,H82>='项目驾驶舱'!$B$3),"进行中","计划中"))) | K82: =IF(J82="待估算","补充投入工时",IF(AND(H82<'项目驾驶舱'!$B$3,F82<>"已完成"),"确认延期和后续安排","按计划跟踪"))
C83: T015 | D83: 修改结算条款 | E83: 第二批次 | F83: =IF(OR(M18="挂起",M18="暂停",Q18="挂起",Q18="暂停",U18="挂起",U18="暂停",Y18="挂起",Y18="暂停"),"暂停","未开始") | G83: 46272 | H83: 46304 | I83: 40 | J83: =IF(I83="","待估算",IF(F83="已完成","已结束",IF(AND(ISNUMBER(G83),ISNUMBER(H83),G83<='项目驾驶舱'!$B$3,H83>='项目驾驶舱'!$B$3),"进行中","计划中"))) | K83: =IF(J83="待估算","补充投入工时",IF(AND(H83<'项目驾驶舱'!$B$3,F83<>"已完成"),"确认延期和后续安排","按计划跟踪"))
C84: T016 | D84: 删除结算条款 | E84: 第二批次 | F84: =IF(OR(M19="挂起",M19="暂停",Q19="挂起",Q19="暂停",U19="挂起",U19="暂停",Y19="挂起",Y19="暂停"),"暂停","未开始") | G84: 46272 | H84: 46304 | I84: 40 | J84: =IF(I84="","待估算",IF(F84="已完成","已结束",IF(AND(ISNUMBER(G84),ISNUMBER(H84),G84<='项目驾驶舱'!$B$3,H84>='项目驾驶舱'!$B$3),"进行中","计划中"))) | K84: =IF(J84="待估算","补充投入工时",IF(AND(H84<'项目驾驶舱'!$B$3,F84<>"已完成"),"确认延期和后续安排","按计划跟踪"))
C85: T017 | D85: 查询展示结算条款 | E85: 第二批次 | F85: =IF(OR(M20="挂起",M20="暂停",Q20="挂起",Q20="暂停",U20="挂起",U20="暂停",Y20="挂起",Y20="暂停"),"暂停","未开始") | G85: 46272 | H85: 46304 | I85: 40 | J85: =IF(I85="","待估算",IF(F85="已完成","已结束",IF(AND(ISNUMBER(G85),ISNUMBER(H85),G85<='项目驾驶舱'!$B$3,H85>='项目驾驶舱'!$B$3),"进行中","计划中"))) | K85: =IF(J85="待估算","补充投入工时",IF(AND(H85<'项目驾驶舱'!$B$3,F85<>"已完成"),"确认延期和后续安排","按计划跟踪"))
C86: T018 | D86: 结算条款推送法务系统 | E86: 第二批次 | F86: =IF(OR(M21="挂起",M21="暂停",Q21="挂起",Q21="暂停",U21="挂起",U21="暂停",Y21="挂起",Y21="暂停"),"暂停","未开始") | G86: 46272 | H86: 46304 | I86: 40 | J86: =IF(I86="","待估算",IF(F86="已完成","已结束",IF(AND(ISNUMBER(G86),ISNUMBER(H86),G86<='项目驾驶舱'!$B$3,H86>='项目驾驶舱'!$B$3),"进行中","计划中"))) | K86: =IF(J86="待估算","补充投入工时",IF(AND(H86<'项目驾驶舱'!$B$3,F86<>"已完成"),"确认延期和后续安排","按计划跟踪"))
C87: T053 | D87: 接入港口侧视频监控 | E87: 第二批次 | F87: =IF(OR(M56="挂起",M56="暂停",Q56="挂起",Q56="暂停",U56="挂起",U56="暂停",Y56="挂起",Y56="暂停"),"暂停","未开始") | G87: 46272 | H87: 46304 | I87: 40 | J87: =IF(I87="","待估算",IF(F87="已完成","已结束",IF(AND(ISNUMBER(G87),ISNUMBER(H87),G87<='项目驾驶舱'!$B$3,H87>='项目驾驶舱'!$B$3),"进行中","计划中"))) | K87: =IF(J87="待估算","补充投入工时",IF(AND(H87<'项目驾驶舱'!$B$3,F87<>"已完成"),"确认延期和后续安排","按计划跟踪"))
A88: 刘凯 | B88: 后端 | C88: T054 | D88: 视频查看权限申请 | E88: 第二批次 | F88: =IF(OR(M57="挂起",M57="暂停",Q57="挂起",Q57="暂停",U57="挂起",U57="暂停",Y57="挂起",Y57="暂停"),"暂停","未开始") | G88: 46272 | H88: 46304 | I88: 40 | J88: =IF(I88="","待估算",IF(F88="已完成","已结束",IF(AND(ISNUMBER(G88),ISNUMBER(H88),G88<='项目驾驶舱'!$B$3,H88>='项目驾驶舱'!$B$3),"进行中","计划中"))) | K88: =IF(J88="待估算","补充投入工时",IF(AND(H88<'项目驾驶舱'!$B$3,F88<>"已完成"),"确认延期和后续安排","按计划跟踪"))
C89: T055 | D89: 视频查看权限审批 | E89: 第二批次 | F89: =IF(OR(M58="挂起",M58="暂停",Q58="挂起",Q58="暂停",U58="挂起",U58="暂停",Y58="挂起",Y58="暂停"),"暂停","未开始") | G89: 46272 | H89: 46304 | I89: 40 | J89: =IF(I89="","待估算",IF(F89="已完成","已结束",IF(AND(ISNUMBER(G89),ISNUMBER(H89),G89<='项目驾驶舱'!$B$3,H89>='项目驾驶舱'!$B$3),"进行中","计划中"))) | K89: =IF(J89="待估算","补充投入工时",IF(AND(H89<'项目驾驶舱'!$B$3,F89<>"已完成"),"确认延期和后续安排","按计划跟踪"))
C90: T056 | D90: 视频查看权限有效期控制 | E90: 第二批次 | F90: =IF(OR(M59="挂起",M59="暂停",Q59="挂起",Q59="暂停",U59="挂起",U59="暂停",Y59="挂起",Y59="暂停"),"暂停","未开始") | G90: 46272 | H90: 46304 | I90: 40 | J90: =IF(I90="","待估算",IF(F90="已完成","已结束",IF(AND(ISNUMBER(G90),ISNUMBER(H90),G90<='项目驾驶舱'!$B$3,H90>='项目驾驶舱'!$B$3),"进行中","计划中"))) | K90: =IF(J90="待估算","补充投入工时",IF(AND(H90<'项目驾驶舱'!$B$3,F90<>"已完成"),"确认延期和后续安排","按计划跟踪"))
C91: T057 | D91: 外网PC端视频监控查询 | E91: 第二批次 | F91: =IF(OR(M60="挂起",M60="暂停",Q60="挂起",Q60="暂停",U60="挂起",U60="暂停",Y60="挂起",Y60="暂停"),"暂停","未开始") | G91: 46272 | H91: 46304 | I91: 40 | J91: =IF(I91="","待估算",IF(F91="已完成","已结束",IF(AND(ISNUMBER(G91),ISNUMBER(H91),G91<='项目驾驶舱'!$B$3,H91>='项目驾驶舱'!$B$3),"进行中","计划中"))) | K91: =IF(J91="待估算","补充投入工时",IF(AND(H91<'项目驾驶舱'!$B$3,F91<>"已完成"),"确认延期和后续安排","按计划跟踪"))
C92: T141 | D92: 视频监控查询 | E92: 第二批次 | F92: =IF(OR(M144="挂起",M144="暂停",Q144="挂起",Q144="暂停",U144="挂起",U144="暂停",Y144="挂起",Y144="暂停"),"暂停","未开始") | G92: 46272 | H92: 46304 | I92: 40 | J92: =IF(I92="","待估算",IF(F92="已完成","已结束",IF(AND(ISNUMBER(G92),ISNUMBER(H92),G92<='项目驾驶舱'!$B$3,H92>='项目驾驶舱'!$B$3),"进行中","计划中"))) | K92: =IF(J92="待估算","补充投入工时",IF(AND(H92<'项目驾驶舱'!$B$3,F92<>"已完成"),"确认延期和后续安排","按计划跟踪"))
C93: T005 | D93: 船舶唯一性校验 | E93: 第二批次 | F93: =IF(OR(M8="挂起",M8="暂停",Q8="挂起",Q8="暂停",U8="挂起",U8="暂停",Y8="挂起",Y8="暂停"),"暂停","已完成") | G93: 46307 | H93: 46339 | I93: 40 | J93: =IF(I93="","待估算",IF(F93="已完成","已结束",IF(AND(ISNUMBER(G93),ISNUMBER(H93),G93<='项目驾驶舱'!$B$3,H93>='项目驾驶舱'!$B$3),"进行中","计划中"))) | K93: =IF(J93="待估算","补充投入工时",IF(AND(H93<'项目驾驶舱'!$B$3,F93<>"已完成"),"确认延期和后续安排","按计划跟踪"))
C94: T019 | D94: 对接卸船计划 | E94: 第二批次 | F94: =IF(OR(M22="挂起",M22="暂停",Q22="挂起",Q22="暂停",U22="挂起",U22="暂停",Y22="挂起",Y22="暂停"),"暂停","进行中") | G94: 46307 | H94: 46339 | I94: 40 | J94: =IF(I94="","待估算",IF(F94="已完成","已结束",IF(AND(ISNUMBER(G94),ISNUMBER(H94),G94<='项目驾驶舱'!$B$3,H94>='项目驾驶舱'!$B$3),"进行中","计划中"))) | K94: =IF(J94="待估算","补充投入工时",IF(AND(H94<'项目驾驶舱'!$B$3,F94<>"已完成"),"确认延期和后续安排","按计划跟踪"))
C95: T020 | D95: 查询卸车计划 | E95: 第二批次 | F95: =IF(OR(M23="挂起",M23="暂停",Q23="挂起",Q23="暂停",U23="挂起",U23="暂停",Y23="挂起",Y23="暂停"),"暂停","进行中") | G95: 46307 | H95: 46339 | I95: 40 | J95: =IF(I95="","待估算",IF(F95="已完成","已结束",IF(AND(ISNUMBER(G95),ISNUMBER(H95),G95<='项目驾驶舱'!$B$3,H95>='项目驾驶舱'!$B$3),"进行中","计划中"))) | K95: =IF(J95="待估算","补充投入工时",IF(AND(H95<'项目驾驶舱'!$B$3,F95<>"已完成"),"确认延期和后续安排","按计划跟踪"))
C96: T021 | D96: 外部客户确认 | E96: 第二批次 | F96: =IF(OR(M24="挂起",M24="暂停",Q24="挂起",Q24="暂停",U24="挂起",U24="暂停",Y24="挂起",Y24="暂停"),"暂停","进行中") | G96: 46307 | H96: 46339 | I96: 40 | J96: =IF(I96="","待估算",IF(F96="已完成","已结束",IF(AND(ISNUMBER(G96),ISNUMBER(H96),G96<='项目驾驶舱'!$B$3,H96>='项目驾驶舱'!$B$3),"进行中","计划中"))) | K96: =IF(J96="待估算","补充投入工时",IF(AND(H96<'项目驾驶舱'!$B$3,F96<>"已完成"),"确认延期和后续安排","按计划跟踪"))
C97: T022 | D97: 对接卸船作业信息 | E97: 第二批次 | F97: =IF(OR(M25="挂起",M25="暂停",Q25="挂起",Q25="暂停",U25="挂起",U25="暂停",Y25="挂起",Y25="暂停"),"暂停","未开始") | G97: 46307 | H97: 46339 | I97: 40 | J97: =IF(I97="","待估算",IF(F97="已完成","已结束",IF(AND(ISNUMBER(G97),ISNUMBER(H97),G97<='项目驾驶舱'!$B$3,H97>='项目驾驶舱'!$B$3),"进行中","计划中"))) | K97: =IF(J97="待估算","补充投入工时",IF(AND(H97<'项目驾驶舱'!$B$3,F97<>"已完成"),"确认延期和后续安排","按计划跟踪"))
C98: T023 | D98: 查询卸船作业信息 | E98: 第二批次 | F98: =IF(OR(M26="挂起",M26="暂停",Q26="挂起",Q26="暂停",U26="挂起",U26="暂停",Y26="挂起",Y26="暂停"),"暂停","未开始") | G98: 46307 | H98: 46339 | I98: 40 | J98: =IF(I98="","待估算",IF(F98="已完成","已结束",IF(AND(ISNUMBER(G98),ISNUMBER(H98),G98<='项目驾驶舱'!$B$3,H98>='项目驾驶舱'!$B$3),"进行中","计划中"))) | K98: =IF(J98="待估算","补充投入工时",IF(AND(H98<'项目驾驶舱'!$B$3,F98<>"已完成"),"确认延期和后续安排","按计划跟踪"))
C99: T024 | D99: 卸船查询列表 | E99: 第二批次 | F99: =IF(OR(M27="挂起",M27="暂停",Q27="挂起",Q27="暂停",U27="挂起",U27="暂停",Y27="挂起",Y27="暂停"),"暂停","未开始") | G99: 46307 | H99: 46339 | I99: 40 | J99: =IF(I99="","待估算",IF(F99="已完成","已结束",IF(AND(ISNUMBER(G99),ISNUMBER(H99),G99<='项目驾驶舱'!$B$3,H99>='项目驾驶舱'!$B$3),"进行中","计划中"))) | K99: =IF(J99="待估算","补充投入工时",IF(AND(H99<'项目驾驶舱'!$B$3,F99<>"已完成"),"确认延期和后续安排","按计划跟踪"))
A100: 刘凯 | B100: 后端 | C100: T025 | D100: 卸船查询详情 | E100: 第二批次 | F100: =IF(OR(M28="挂起",M28="暂停",Q28="挂起",Q28="暂停",U28="挂起",U28="暂停",Y28="挂起",Y28="暂停"),"暂停","未开始") | G100: 46307 | H100: 46339 | I100: 40 | J100: =IF(I100="","待估算",IF(F100="已完成","已结束",IF(AND(ISNUMBER(G100),ISNUMBER(H100),G100<='项目驾驶舱'!$B$3,H100>='项目驾驶舱'!$B$3),"进行中","计划中"))) | K100: =IF(J100="待估算","补充投入工时",IF(AND(H100<'项目驾驶舱'!$B$3,F100<>"已完成"),"确认延期和后续安排","按计划跟踪"))
C101: T026 | D101: 创建卸船作业委托信息 | E101: 第二批次 | F101: =IF(OR(M29="挂起",M29="暂停",Q29="挂起",Q29="暂停",U29="挂起",U29="暂停",Y29="挂起",Y29="暂停"),"暂停","进行中") | G101: 46307 | H101: 46339 | I101: 40 | J101: =IF(I101="","待估算",IF(F101="已完成","已结束",IF(AND(ISNUMBER(G101),ISNUMBER(H101),G101<='项目驾驶舱'!$B$3,H101>='项目驾驶舱'!$B$3),"进行中","计划中"))) | K101: =IF(J101="待估算","补充投入工时",IF(AND(H101<'项目驾驶舱'!$B$3,F101<>"已完成"),"确认延期和后续安排","按计划跟踪"))
C102: T027 | D102: 修改卸船作业委托信息 | E102: 第二批次 | F102: =IF(OR(M30="挂起",M30="暂停",Q30="挂起",Q30="暂停",U30="挂起",U30="暂停",Y30="挂起",Y30="暂停"),"暂停","进行中") | G102: 46307 | H102: 46339 | I102: 40 | J102: =IF(I102="","待估算",IF(F102="已完成","已结束",IF(AND(ISNUMBER(G102),ISNUMBER(H102),G102<='项目驾驶舱'!$B$3,H102>='项目驾驶舱'!$B$3),"进行中","计划中"))) | K102: =IF(J102="待估算","补充投入工时",IF(AND(H102<'项目驾驶舱'!$B$3,F102<>"已完成"),"确认延期和后续安排","按计划跟踪"))
C103: T028 | D103: 作废卸船作业委托信息 | E103: 第二批次 | F103: =IF(OR(M31="挂起",M31="暂停",Q31="挂起",Q31="暂停",U31="挂起",U31="暂停",Y31="挂起",Y31="暂停"),"暂停","进行中") | G103: 46307 | H103: 46339 | I103: 40 | J103: =IF(I103="","待估算",IF(F103="已完成","已结束",IF(AND(ISNUMBER(G103),ISNUMBER(H103),G103<='项目驾驶舱'!$B$3,H103>='项目驾驶舱'!$B$3),"进行中","计划中"))) | K103: =IF(J103="待估算","补充投入工时",IF(AND(H103<'项目驾驶舱'!$B$3,F103<>"已完成"),"确认延期和后续安排","按计划跟踪"))
C104: T029 | D104: 推送卸船作业委托信息 | E104: 第二批次 | F104: =IF(OR(M32="挂起",M32="暂停",Q32="挂起",Q32="暂停",U32="挂起",U32="暂停",Y32="挂起",Y32="暂停"),"暂停","进行中") | G104: 46307 | H104: 46339 | I104: 40 | J104: =IF(I104="","待估算",IF(F104="已完成","已结束",IF(AND(ISNUMBER(G104),ISNUMBER(H104),G104<='项目驾驶舱'!$B$3,H104>='项目驾驶舱'!$B$3),"进行中","计划中"))) | K104: =IF(J104="待估算","补充投入工时",IF(AND(H104<'项目驾驶舱'!$B$3,F104<>"已完成"),"确认延期和后续安排","按计划跟踪"))
...

Sheet PMO周报
A1: PMO周报
A2: 面向项目领导的周报底稿。指标自动计算，黄色区域由项目经理审核后填写。
A4: 报告日期 | B4: ='项目驾驶舱'!B3
A5: 项目状态 | B5: ='AI项目诊断'!E4
A6: 状态说明 | B6: ='AI项目诊断'!H4
A8: 一、本周总体判断
A9: 说明项目整体状态、与上周相比的变化以及最大失控点。
A12: 二、本周完成事项
A13: 列出已经完成且有证据的关键事项，不写日常过程。
A17: 三、未来两周重点
A18: 从“两周督办”筛选“是否纳入=是”，确认责任人和承诺日期。
A22: 四、主要风险与问题
A23: 优先说明高等级、已逾期、影响里程碑的风险与问题。
A27: 五、待决策与需协调事项
A28: 从“待决策事项”提取仍未决策且已接近需要日期的事项。
A32: 自动指标
A33: 指标 | B33: 本期值 | C33: 管理含义
A34: 任务完成率 | B34: =IFERROR(COUNTIF('项目总控台账'!$G$4:$G$148,"已完成")/COUNTIF('项目总控台账'!$A$4:$A$148,"<>"),0) | C34: 观察总体交付进展
A35: 逾期任务数 | B35: =COUNTIF('项目总控台账'!$AC$4:$AC$148,"*延期*") | C35: 检查关键路径和补救计划
A36: 未关闭高风险 | B36: =COUNTIFS('风险问题台账'!$D$4:$D$102,"高",'风险问题台账'!$K$4:$K$102,"<>已关闭") | C36: 确认应对措施和升级需求
A37: 逾期行动项 | B37: =COUNTIFS('会议行动项'!$J$4:$J$102,">0",'会议行动项'!$H$4:$H$102,"<>已完成") | C37: 检查承诺兑现情况
A38: 待决策事项 | B38: =COUNTIFS('待决策事项'!$C$5:$C$54,"<>",'待决策事项'!$I$5:$I$54,"<>已决策",'待决策事项'!$I$5:$I$54,"<>已关闭") | C38: 明确决策人和最迟日期
A39: 数据质量问题 | B39: =COUNTIF('数据质量检查'!$H$5:$H$149,"需整改") | C39: 提高AI诊断可信度

Sheet AI运行日志
A1: AI运行日志
A2: 记录每次AI分析的输入范围、发现、建议、人工确认和处理结果，便于追踪与复盘。
A4: 运行ID | B4: 运行时间 | C4: 分析类型 | D4: 数据日期 | E4: 分析范围 | F4: 主要发现 | G4: 风险等级 | H4: AI建议 | I4: 人工结论 | J4: 处理人 | K4: 处理状态 | L4: 完成时间
A5: =IF(B5="","","AI-"&TEXT(ROW()-4,"0000"))
A6: =IF(B6="","","AI-"&TEXT(ROW()-4,"0000"))
A7: =IF(B7="","","AI-"&TEXT(ROW()-4,"0000"))
A8: =IF(B8="","","AI-"&TEXT(ROW()-4,"0000"))
A9: =IF(B9="","","AI-"&TEXT(ROW()-4,"0000"))
A10: =IF(B10="","","AI-"&TEXT(ROW()-4,"0000"))
A11: =IF(B11="","","AI-"&TEXT(ROW()-4,"0000"))
A12: =IF(B12="","","AI-"&TEXT(ROW()-4,"0000"))
A13: =IF(B13="","","AI-"&TEXT(ROW()-4,"0000"))
A14: =IF(B14="","","AI-"&TEXT(ROW()-4,"0000"))
A15: =IF(B15="","","AI-"&TEXT(ROW()-4,"0000"))
A16: =IF(B16="","","AI-"&TEXT(ROW()-4,"0000"))
... A104: =IF(B104="","","AI-"&TEXT(ROW()-4,"0000"))
