Workbook

Sheet 使用说明
A1: 计划与进度管理-20260921-V1 使用说明
A2: 维护里程碑、总控任务、资源周计划和迭代承诺。
A4: 项目 | B4: 能源行业合同全生命周期管理系统
A5: 适用对象 | B5: 项目集经理、项目经理、各工作流负责人
A6: 更新频率 | B6: 每周滚动更新；里程碑和基线变化须同步评审。
A7: 版本日期 | B7: 46288
A8: 颜色约定 | B8: 浅蓝表头；黄色为人工输入区；白色/灰色通常为公式、说明或系统数据。
A10: 推荐使用流程
A11: 1 | B11: 先维护里程碑基线
A12: 2 | B12: 细化总控台账任务和责任人
A13: 3 | B13: 按人员核对每周40小时资源负荷
A14: 4 | B14: 按接口清单落实外部系统责任人、联调窗口和前置条件
A15: 5 | B15: 复核延期、挂起、暂停和阻塞项
A18: 工作表导航
A19: 顺序 | B19: 工作表 | C19: 用途
A20: 1 | B20: 里程碑计划 | C20: 维护阶段里程碑、计划与实际日期。
A21: 2 | B21: 项目总控台账 | C21: 原始维护页；按层级合并展示，不建议直接筛选或排序。
A22: 3 | B22: 资源计划 | C22: 按人员查看每周任务和工时负荷。
A23: 4 | B23: 周迭代计划 | C23: 管理当周承诺、执行结果和滚动安排。
A24: 5 | B24: _数据接口 | C24: 供AI PMO和跨文件联动使用的内部数据
A26: 维护与检查规则
A27: 1 | B27: 先维护唯一编号、责任人、计划日期和状态，再补充说明与证据。
A28: 2 | B28: 状态变化时同步更新实际日期、完成比例、阻塞原因或验证结果。
A29: 3 | B29: 涉及基线、预算、范围、合同或上线门禁的变化，须先履行评审或审批。
A30: 4 | B30: 不要覆盖公式、汇总区、图表数据区和“_数据接口”中的系统字段。
A31: 5 | B31: 每周检查空责任人、逾期未完成、状态与日期矛盾、缺少证据和公式错误。
A32: 6 | B32: 文件升级后，将被替换版本移入本模块_archive目录，不在正式目录保留多个现行版本。
A33: 系统集成联动 | B33: 总控台账T096-T135保留40个系统/阶段工作包；470项实施明细在系统集成管理V1维护
A34: 资源同步规则 | B34: 系统集成建议资源按人员和总控任务同步到资源计划；多人并行时共享个人当周40小时，具体任务工时在说明列展示
A35: 文件边界 | B35: 计划文件负责里程碑与总控；系统集成文件负责规格、实施、联调、测试和上线证据
A36: 总控筛选视图 | B36: 只读公式联动页；用于筛选、排序和快速定位任务，所有业务数据仍在项目总控台账维护。
A37: 迭代周生成 | B37: 在项目总控台账AF列"迭代周"填 ISO 周（如 2026-W40）人工指定迭代；留空不纳入。填写后运行 automation/scripts/generate_iteration_plan.py --apply 生成周迭代计划明细（任务ID联动，改总控自动跟随）。
A38: 总体状态回算 | B38: G列"总体状态"由公式按四专业状态（M/Q/U/Y列）自动回算：暂停/挂起→暂停，全部完成→已完成，有进行中→进行中，有待确认→待确认，其余→未开始，无责任人→未分配。人工只维护四专业状态列，勿改G列公式。
A39: 预测完成日期 | B39: AG列人工维护：每次迭代评审后刷新该任务的当前预测完成日期，留空表示尚未评估。
A40: 基线偏差天数 | B40: AH列公式自动计算＝预测完成日期－基线计划完成（J列），负数表示预计早于基线。

Sheet 里程碑计划
A1: 能源行业合同全生命周期管理系统｜里程碑计划
A3: 里程碑ID | B3: 阶段 | C3: 里程碑名称 | D3: 验收/完成标准 | E3: 负责人 | F3: 配合人 | G3: 计划开始日期 | H3: 计划结束日期 | I3: 实际开始日期 | J3: 实际结束日期 | K3: 状态 | L3: 偏差天数 | M3: 健康度 | N3: 交付物
A4: MS001 | B4: 可研与原业务梳理 | C4: 可研工作启动 | D4: 范围、负责人和调研计划确认 | E4: 项目经理 | F4: 项目集经理、产品经理 | G4: 46054 | H4: 46063 | I4: 46054 | J4: 46063 | K4: 已完成 | L4: =IF(J4<>"",J4-H4,MAX(0,DATE(2026,9,16)-H4)) -> 0 | M4: =IF(K4="已完成","绿",IF(H4<DATE(2026,9,16),"红",IF(H4<=DATE(2026,9,23),"黄","绿"))) -> 绿 | N4: 可研工作方案
A5: MS002 | C5: 可行性研究完成 | D5: 业务、技术、投资和实施可行性完成评审 | E5: 项目经理 | F5: 技术经理、产品经理 | G5: 46054 | H5: 46283 | I5: 46054 | J5: 46283 | K5: 已完成 | L5: =IF(J5<>"",J5-H5,MAX(0,DATE(2026,9,16)-H5)) -> 0 | M5: =IF(K5="已完成","绿",IF(H5<DATE(2026,9,16),"红",IF(H5<=DATE(2026,9,23),"黄","绿"))) -> 绿 | N5: 项目可行性研究报告
A6: MS003 | C6: 原业务梳理完成 | D6: 核心业务部门确认现状基线 | E6: 产品经理 | F6: 项目经理、业务代表 | G6: 46153 | H6: 46295 | I6: 46153 | K6: 进行中 | L6: =IF(J6<>"",J6-H6,MAX(0,DATE(2026,9,16)-H6)) -> 0 | M6: =IF(K6="已完成","绿",IF(H6<DATE(2026,9,16),"红",IF(H6<=DATE(2026,9,23),"黄","绿"))) -> 绿 | N6: 现状流程、问题及改进机会清单
A7: MS004 | B7: 项目规范梳理与技术架构搭建 | C7: 项目规范基线确认 | D7: 计划、需求、质量、变更和配置规范通过评审 | E7: 项目经理 | F7: 项目集经理、技术经理、产品经理、高级测试人员、中级测试人员、配置人员 | G7: 46204 | H7: 46265 | I7: 46204 | J7: 46265 | K7: 已完成 | L7: =IF(J7<>"",J7-H7,MAX(0,DATE(2026,9,16)-H7)) -> 0 | M7: =IF(K7="已完成","绿",IF(H7<DATE(2026,9,16),"红",IF(H7<=DATE(2026,9,23),"黄","绿"))) -> 绿 | N7: 项目管理与研发规范
A8: MS005 | C8: 技术架构基线确认 | D8: 应用、数据、集成、安全和部署架构通过评审 | E8: 技术经理 | F8: 高级开发人员、配置人员 | G8: 46204 | H8: 46295 | I8: 46204 | K8: 进行中 | L8: =IF(J8<>"",J8-H8,MAX(0,DATE(2026,9,16)-H8)) -> 0 | M8: =IF(K8="已完成","绿",IF(H8<DATE(2026,9,16),"红",IF(H8<=DATE(2026,9,23),"黄","绿"))) -> 绿 | N8: 总体技术架构和环境基础
A9: MS017 | C9: 外部产品POC验证完成 | D9: CA完成证书签发、身份认证、电子签名及验签验证；电子文档完成模板生成、在线预览、格式转换、水印和归档验证；BI报表完成核心经营指标、权限控制、钻取导出及性能验证；三类产品形成问题清单、适配结论和选型建议并通过评审 | E9: 技术经理 | F9: 项目经理、产品经理、高级开发人员、高级测试人员、中级测试人员、外部产品厂商 | G9: 46249 | H9: 46320 | I9: 46249 | K9: 进行中 | L9: =IF(J9<>"",J9-H9,MAX(0,DATE(2026,9,16)-H9)) -> 0 | M9: =IF(K9="已完成","绿",IF(H9<DATE(2026,9,16),"红",IF(H9<=DATE(2026,9,23),"黄","绿"))) -> 绿 | N9: CA、电子文档、BI报表POC报告、量化评分表、联合评审记录及产品选型建议
A10: MS006 | B10: 正式启动准备 | C10: 启动准备评审通过 | D10: 范围、组织、预算、计划和治理机制具备启动条件 | E10: 项目集经理 | F10: 项目经理、技术经理、产品经理 | G10: 46296 | H10: 46311 | K10: 未开始 | L10: =IF(J10<>"",J10-H10,MAX(0,DATE(2026,9,16)-H10)) -> 0 | M10: =IF(K10="已完成","绿",IF(H10<DATE(2026,9,16),"红",IF(H10<=DATE(2026,9,23),"黄","绿"))) -> 绿 | N10: 项目章程、整体管理计划、启动门禁清单及评审结论
A11: MS007 | B11: 正式实施与上线准备 | C11: 项目正式启动 | D11: 项目组织到位、职责明确、计划发布 | E11: 项目集经理 | F11: 项目经理、技术经理、产品经理 | G11: 46315 | H11: 46315 | K11: 未开始 | L11: =IF(J11<>"",J11-H11,MAX(0,DATE(2026,9,16)-H11)) -> 0 | M11: =IF(K11="已完成","绿",IF(H11<DATE(2026,9,16),"红",IF(H11<=DATE(2026,9,23),"黄","绿"))) -> 绿 | N11: 启动会纪要与行动项
A12: MS008 | C12: 需求基线确认 | D12: P0/P1/P2范围、验收标准和变更机制确认 | E12: 产品经理 | F12: 项目经理、业务代表、技术经理 | G12: 46316 | H12: 46356 | K12: 未开始 | L12: =IF(J12<>"",J12-H12,MAX(0,DATE(2026,9,16)-H12)) -> 0 | M12: =IF(K12="已完成","绿",IF(H12<DATE(2026,9,16),"红",IF(H12<=DATE(2026,9,23),"黄","绿"))) -> 绿 | N12: 需求规格说明书与跟踪矩阵
A13: MS009 | C13: 详细设计完成 | D13: 核心模块、数据、权限和安全设计通过评审；94条P0接口完成规格编制并获得合同系统、外部系统、业务和测试联合批准 | E13: 技术经理 | F13: 产品经理、高级开发人员、配置人员 | G13: 46341 | H13: 46387 | K13: 未开始 | L13: =IF(J13<>"",J13-H13,MAX(0,DATE(2026,9,16)-H13)) -> 0 | M13: =IF(K13="已完成","绿",IF(H13<DATE(2026,9,16),"红",IF(H13<=DATE(2026,9,23),"黄","绿"))) -> 绿 | N13: 详细设计、数据设计、94条P0接口批准版规格及评审记录
A14: MS010 | C14: 核心功能开发完成 | D14: P0功能完成且单元测试通过 | E14: 高级开发人员 | F14: 技术经理、中级开发人员、高级测试人员、中级测试人员 | G14: 46357 | H14: 46461 | K14: 未开始 | L14: =IF(J14<>"",J14-H14,MAX(0,DATE(2026,9,16)-H14)) -> 0 | M14: =IF(K14="已完成","绿",IF(H14<DATE(2026,9,16),"红",IF(H14<=DATE(2026,9,23),"黄","绿"))) -> 绿 | N14: 可测试版本
A15: MS011 | C15: 内部系统集成完成 | D15: 合同起草、审批、履约、收付款、变更、归档、权限和数据流端到端贯通 | E15: 技术经理 | F15: 高级开发人员、中级开发人员、高级测试人员、中级测试人员、配置人员 | G15: 46419 | H15: 46456 | K15: 未开始 | L15: =IF(J15<>"",J15-H15,MAX(0,DATE(2026,9,16)-H15)) -> 0 | M15: =IF(K15="已完成","绿",IF(H15<DATE(2026,9,16),"红",IF(H15<=DATE(2026,9,23),"黄","绿"))) -> 绿 | N15: 内部集成测试报告
A16: MS012 | C16: 外部系统集成完成 | D16: 接口范围分级经联合评审批准；P0 94条接口完成规格、责任、环境、联调、异常补偿和对账验证；P1/P2形成后续排期 | E16: 技术经理 | F16: 高级开发人员、中级开发人员、高级测试人员、中级测试人员、外部接口负责人 | G16: 46433 | H16: 46466 | K16: 未开始 | L16: =IF(J16<>"",J16-H16,MAX(0,DATE(2026,9,16)-H16)) -> 0 | M16: =IF(K16="已完成","绿",IF(H16<DATE(2026,9,16),"红",IF(H16<=DATE(2026,9,23),"黄","绿"))) -> 绿 | N16: 接口分级评审记录、范围基线、接口规格、联调与对账报告
A17: MS013 | C17: 系统测试完成 | D17: 阻断及严重缺陷关闭，内部与外部集成回归通过 | E17: 高级测试人员、中级测试人员 | F17: 技术经理、高级开发人员、中级开发人员、产品经理 | G17: 46447 | H17: 46492 | K17: 未开始 | L17: =IF(J17<>"",J17-H17,MAX(0,DATE(2026,9,16)-H17)) -> 0 | M17: =IF(K17="已完成","绿",IF(H17<DATE(2026,9,16),"红",IF(H17<=DATE(2026,9,23),"黄","绿"))) -> 绿 | N17: 系统测试报告
A18: MS014 | C18: UAT验收完成 | D18: P0场景验收通过，遗留事项获得批准 | E18: 产品经理 | F18: 业务代表、高级测试人员、中级测试人员、项目经理 | G18: 46493 | H18: 46517 | K18: 未开始 | L18: =IF(J18<>"",J18-H18,MAX(0,DATE(2026,9,16)-H18)) -> 0 | M18: =IF(K18="已完成","绿",IF(H18<DATE(2026,9,16),"红",IF(H18<=DATE(2026,9,23),"黄","绿"))) -> 绿 | N18: UAT报告与业务确认单
A19: MS015 | C19: 上线准入评审通过 | D19: 数据、接口、权限、回退、培训和运维准备就绪 | E19: 项目集经理 | F19: 项目经理、技术经理、产品经理、高级测试人员、中级测试人员、配置人员 | G19: 46518 | H19: 46531 | K19: 未开始 | L19: =IF(J19<>"",J19-H19,MAX(0,DATE(2026,9,16)-H19)) -> 0 | M19: =IF(K19="已完成","绿",IF(H19<DATE(2026,9,16),"红",IF(H19<=DATE(2026,9,23),"黄","绿"))) -> 绿 | N19: 上线检查表和批准记录
A20: MS016 | B20: 系统上线与试运行 | C20: 生产上线并进入试运行 | D20: 生产验证通过、监控启用、支持机制生效 | E20: 技术经理 | F20: 项目集经理、项目经理、配置人员、高级测试人员、中级测试人员 | G20: 46538 | H20: 46538 | K20: 未开始 | L20: =IF(J20<>"",J20-H20,MAX(0,DATE(2026,9,16)-H20)) -> 0 | M20: =IF(K20="已完成","绿",IF(H20<DATE(2026,9,16),"红",IF(H20<=DATE(2026,9,23),"黄","绿"))) -> 绿 | N20: 上线确认单和试运行计划

Sheet 项目总控台账
A1: 能源行业合同全生命周期管理系统｜项目总控台账
A2: 蓝色字段为计划分解项；黄色字段为执行维护项；进度与延期由公式自动计算。
A3: 任务ID | B3: 一级功能 | C3: 二级功能 | D3: 三级功能 | E3: 四级功能 | F3: 批次 | G3: 总体状态 | H3: 主责人 | I3: 计划开始 | J3: 计划完成 | K3: 计划上线 | L3: 业务负责人 | M3: 业务状态 | N3: 业务开始 | O3: 业务结束 | P3: 后端负责人 | Q3: 后端状态 | R3: 后端开始 | S3: 后端结束 | T3: 前端负责人 | U3: 前端状态 | V3: 前端开始 | W3: 前端结束 | X3: 测试负责人 | Y3: 测试状态 | Z3: 测试开始 | AA3: 测试结束 | AB3: 综合进度 | AC3: 延期状态 | AD3: 当前问题/阻塞 | AE3: 备注 | AF3: 迭代周 | AG3: 预测完成日期 | AH3: 基线偏差天数
A4: T001 | B4: 可研与原业务梳理 | C4: 可研工作启动 | D4: 可研启动 | E4: 明确可研目标、范围与边界 | F4: MS001 | G4: =IF(OR(M4="暂停",M4="挂起",Q4="暂停",Q4="挂起",U4="暂停",U4="挂起",Y4="暂停",Y4="挂起"),"暂停",IF(COUNTA(L4,P4,T4,X4)=0,"未分配",IF(IF(L4<>"",M4="已完成",0)+IF(P4<>"",Q4="已完成",0)+IF(T4<>"",U4="已完成",0)+IF(X4<>"",Y4="已完成",0)=COUNTA(L4,P4,T4,X4),"已完成",IF(IF(L4<>"",M4="进行中",0)+IF(P4<>"",Q4="进行中",0)+IF(T4<>"",U4="进行中",0)+IF(X4<>"",Y4="进行中",0)>0,"进行中",IF(IF(L4<>"",M4="待确认",0)+IF(P4<>"",Q4="待确认",0)+IF(T4<>"",U4="待确认",0)+IF(X4<>"",Y4="待确认",0)>0,"待确认","未开始"))))) -> 已完成 | H4: =IF(L4<>"",L4,IF(P4<>"",P4,IF(T4<>"",T4,X4))) -> 项目经理 | I4: =IF(COUNT(N4,R4,V4,Z4)=0,"",MIN(N4,R4,V4,Z4)) -> 46054 | J4: =IF(COUNT(O4,S4,W4,AA4)=0,"",MAX(O4,S4,W4,AA4)) -> 46056 | K4: 46063 | L4: 项目经理 | M4: 已完成 | N4: 46054 | O4: 46056 | AB4: =IFERROR((IF(L4<>"",IF(M4="已完成",1,IF(M4="进行中",0.5,0))*15%,0)+IF(P4<>"",IF(Q4="已完成",1,IF(Q4="进行中",0.5,0))*35%,0)+IF(T4<>"",IF(U4="已完成",1,IF(U4="进行中",0.5,0))*30%,0)+IF(X4<>"",IF(Y4="已完成",1,IF(Y4="进行中",0.5,0))*20%,0))/(IF(L4<>"",15%,0)+IF(P4<>"",35%,0)+IF(T4<>"",30%,0)+IF(X4<>"",20%,0)),0) -> 1 | AC4: =IF($A4="","",IF(G4="已完成","正常",IF(G4="暂停","暂停",IF(J4="","日期缺失",IF(J4<_数据接口!$B$7,"已延期",IF(J4<=_数据接口!$B$7+7,"临近到期","正常")))))) -> 正常 | AH4: =IF(OR($A4="",J4="",AG4=""),"",AG4-J4)
A5: T002 | E5: 建立相关方清单与访谈计划 | F5: MS001 | G5: =IF(OR(M5="暂停",M5="挂起",Q5="暂停",Q5="挂起",U5="暂停",U5="挂起",Y5="暂停",Y5="挂起"),"暂停",IF(COUNTA(L5,P5,T5,X5)=0,"未分配",IF(IF(L5<>"",M5="已完成",0)+IF(P5<>"",Q5="已完成",0)+IF(T5<>"",U5="已完成",0)+IF(X5<>"",Y5="已完成",0)=COUNTA(L5,P5,T5,X5),"已完成",IF(IF(L5<>"",M5="进行中",0)+IF(P5<>"",Q5="进行中",0)+IF(T5<>"",U5="进行中",0)+IF(X5<>"",Y5="进行中",0)>0,"进行中",IF(IF(L5<>"",M5="待确认",0)+IF(P5<>"",Q5="待确认",0)+IF(T5<>"",U5="待确认",0)+IF(X5<>"",Y5="待确认",0)>0,"待确认","未开始"))))) -> 已完成 | H5: =IF(L5<>"",L5,IF(P5<>"",P5,IF(T5<>"",T5,X5))) -> 产品经理 | I5: =IF(COUNT(N5,R5,V5,Z5)=0,"",MIN(N5,R5,V5,Z5)) -> 46057 | J5: =IF(COUNT(O5,S5,W5,AA5)=0,"",MAX(O5,S5,W5,AA5)) -> 46059 | K5: 46063 | L5: 产品经理 | M5: 已完成 | N5: 46057 | O5: 46059 | AB5: =IFERROR((IF(L5<>"",IF(M5="已完成",1,IF(M5="进行中",0.5,0))*15%,0)+IF(P5<>"",IF(Q5="已完成",1,IF(Q5="进行中",0.5,0))*35%,0)+IF(T5<>"",IF(U5="已完成",1,IF(U5="进行中",0.5,0))*30%,0)+IF(X5<>"",IF(Y5="已完成",1,IF(Y5="进行中",0.5,0))*20%,0))/(IF(L5<>"",15%,0)+IF(P5<>"",35%,0)+IF(T5<>"",30%,0)+IF(X5<>"",20%,0)),0) -> 1 | AC5: =IF($A5="","",IF(G5="已完成","正常",IF(G5="暂停","暂停",IF(J5="","日期缺失",IF(J5<_数据接口!$B$7,"已延期",IF(J5<=_数据接口!$B$7+7,"临近到期","正常")))))) -> 正常 | AH5: =IF(OR($A5="",J5="",AG5=""),"",AG5-J5)
A6: T003 | E6: 评审并发布可研工作方案 | F6: MS001 | G6: =IF(OR(M6="暂停",M6="挂起",Q6="暂停",Q6="挂起",U6="暂停",U6="挂起",Y6="暂停",Y6="挂起"),"暂停",IF(COUNTA(L6,P6,T6,X6)=0,"未分配",IF(IF(L6<>"",M6="已完成",0)+IF(P6<>"",Q6="已完成",0)+IF(T6<>"",U6="已完成",0)+IF(X6<>"",Y6="已完成",0)=COUNTA(L6,P6,T6,X6),"已完成",IF(IF(L6<>"",M6="进行中",0)+IF(P6<>"",Q6="进行中",0)+IF(T6<>"",U6="进行中",0)+IF(X6<>"",Y6="进行中",0)>0,"进行中",IF(IF(L6<>"",M6="待确认",0)+IF(P6<>"",Q6="待确认",0)+IF(T6<>"",U6="待确认",0)+IF(X6<>"",Y6="待确认",0)>0,"待确认","未开始"))))) -> 已完成 | H6: =IF(L6<>"",L6,IF(P6<>"",P6,IF(T6<>"",T6,X6))) -> 项目集经理 | I6: =IF(COUNT(N6,R6,V6,Z6)=0,"",MIN(N6,R6,V6,Z6)) -> 46060 | J6: =IF(COUNT(O6,S6,W6,AA6)=0,"",MAX(O6,S6,W6,AA6)) -> 46063 | K6: 46063 | L6: 项目集经理 | M6: 已完成 | N6: 46060 | O6: 46063 | AB6: =IFERROR((IF(L6<>"",IF(M6="已完成",1,IF(M6="进行中",0.5,0))*15%,0)+IF(P6<>"",IF(Q6="已完成",1,IF(Q6="进行中",0.5,0))*35%,0)+IF(T6<>"",IF(U6="已完成",1,IF(U6="进行中",0.5,0))*30%,0)+IF(X6<>"",IF(Y6="已完成",1,IF(Y6="进行中",0.5,0))*20%,0))/(IF(L6<>"",15%,0)+IF(P6<>"",35%,0)+IF(T6<>"",30%,0)+IF(X6<>"",20%,0)),0) -> 1 | AC6: =IF($A6="","",IF(G6="已完成","正常",IF(G6="暂停","暂停",IF(J6="","日期缺失",IF(J6<_数据接口!$B$7,"已延期",IF(J6<=_数据接口!$B$7+7,"临近到期","正常")))))) -> 正常 | AH6: =IF(OR($A6="",J6="",AG6=""),"",AG6-J6)
A7: T004 | C7: 可行性研究完成 | D7: 可行性研究 | E7: 完成业务可行性与需求价值分析 | F7: MS002 | G7: =IF(OR(M7="暂停",M7="挂起",Q7="暂停",Q7="挂起",U7="暂停",U7="挂起",Y7="暂停",Y7="挂起"),"暂停",IF(COUNTA(L7,P7,T7,X7)=0,"未分配",IF(IF(L7<>"",M7="已完成",0)+IF(P7<>"",Q7="已完成",0)+IF(T7<>"",U7="已完成",0)+IF(X7<>"",Y7="已完成",0)=COUNTA(L7,P7,T7,X7),"已完成",IF(IF(L7<>"",M7="进行中",0)+IF(P7<>"",Q7="进行中",0)+IF(T7<>"",U7="进行中",0)+IF(X7<>"",Y7="进行中",0)>0,"进行中",IF(IF(L7<>"",M7="待确认",0)+IF(P7<>"",Q7="待确认",0)+IF(T7<>"",U7="待确认",0)+IF(X7<>"",Y7="待确认",0)>0,"待确认","未开始"))))) -> 已完成 | H7: =IF(L7<>"",L7,IF(P7<>"",P7,IF(T7<>"",T7,X7))) -> 产品经理 | I7: =IF(COUNT(N7,R7,V7,Z7)=0,"",MIN(N7,R7,V7,Z7)) -> 46054 | J7: =IF(COUNT(O7,S7,W7,AA7)=0,"",MAX(O7,S7,W7,AA7)) -> 46099 | K7: 46283 | L7: 产品经理 | M7: 已完成 | N7: 46054 | O7: 46099 | AB7: =IFERROR((IF(L7<>"",IF(M7="已完成",1,IF(M7="进行中",0.5,0))*15%,0)+IF(P7<>"",IF(Q7="已完成",1,IF(Q7="进行中",0.5,0))*35%,0)+IF(T7<>"",IF(U7="已完成",1,IF(U7="进行中",0.5,0))*30%,0)+IF(X7<>"",IF(Y7="已完成",1,IF(Y7="进行中",0.5,0))*20%,0))/(IF(L7<>"",15%,0)+IF(P7<>"",35%,0)+IF(T7<>"",30%,0)+IF(X7<>"",20%,0)),0) -> 1 | AC7: =IF($A7="","",IF(G7="已完成","正常",IF(G7="暂停","暂停",IF(J7="","日期缺失",IF(J7<_数据接口!$B$7,"已延期",IF(J7<=_数据接口!$B$7+7,"临近到期","正常")))))) -> 正常 | AH7: =IF(OR($A7="",J7="",AG7=""),"",AG7-J7)
A8: T005 | E8: 完成技术路线与系统边界论证 | F8: MS002 | G8: =IF(OR(M8="暂停",M8="挂起",Q8="暂停",Q8="挂起",U8="暂停",U8="挂起",Y8="暂停",Y8="挂起"),"暂停",IF(COUNTA(L8,P8,T8,X8)=0,"未分配",IF(IF(L8<>"",M8="已完成",0)+IF(P8<>"",Q8="已完成",0)+IF(T8<>"",U8="已完成",0)+IF(X8<>"",Y8="已完成",0)=COUNTA(L8,P8,T8,X8),"已完成",IF(IF(L8<>"",M8="进行中",0)+IF(P8<>"",Q8="进行中",0)+IF(T8<>"",U8="进行中",0)+IF(X8<>"",Y8="进行中",0)>0,"进行中",IF(IF(L8<>"",M8="待确认",0)+IF(P8<>"",Q8="待确认",0)+IF(T8<>"",U8="待确认",0)+IF(X8<>"",Y8="待确认",0)>0,"待确认","未开始"))))) -> 已完成 | H8: =IF(L8<>"",L8,IF(P8<>"",P8,IF(T8<>"",T8,X8))) -> 技术经理 | I8: =IF(COUNT(N8,R8,V8,Z8)=0,"",MIN(N8,R8,V8,Z8)) -> 46100 | J8: =IF(COUNT(O8,S8,W8,AA8)=0,"",MAX(O8,S8,W8,AA8)) -> 46145 | K8: 46283 | M8: 已完成 | P8: 技术经理 | Q8: 已完成 | R8: 46100 | S8: 46145 | AB8: =IFERROR((IF(L8<>"",IF(M8="已完成",1,IF(M8="进行中",0.5,0))*15%,0)+IF(P8<>"",IF(Q8="已完成",1,IF(Q8="进行中",0.5,0))*35%,0)+IF(T8<>"",IF(U8="已完成",1,IF(U8="进行中",0.5,0))*30%,0)+IF(X8<>"",IF(Y8="已完成",1,IF(Y8="进行中",0.5,0))*20%,0))/(IF(L8<>"",15%,0)+IF(P8<>"",35%,0)+IF(T8<>"",30%,0)+IF(X8<>"",20%,0)),0) -> 1 | AC8: =IF($A8="","",IF(G8="已完成","正常",IF(G8="暂停","暂停",IF(J8="","日期缺失",IF(J8<_数据接口!$B$7,"已延期",IF(J8<=_数据接口!$B$7+7,"临近到期","正常")))))) -> 正常 | AH8: =IF(OR($A8="",J8="",AG8=""),"",AG8-J8)
A9: T006 | E9: 测算投资、成本与预期收益 | F9: MS002 | G9: =IF(OR(M9="暂停",M9="挂起",Q9="暂停",Q9="挂起",U9="暂停",U9="挂起",Y9="暂停",Y9="挂起"),"暂停",IF(COUNTA(L9,P9,T9,X9)=0,"未分配",IF(IF(L9<>"",M9="已完成",0)+IF(P9<>"",Q9="已完成",0)+IF(T9<>"",U9="已完成",0)+IF(X9<>"",Y9="已完成",0)=COUNTA(L9,P9,T9,X9),"已完成",IF(IF(L9<>"",M9="进行中",0)+IF(P9<>"",Q9="进行中",0)+IF(T9<>"",U9="进行中",0)+IF(X9<>"",Y9="进行中",0)>0,"进行中",IF(IF(L9<>"",M9="待确认",0)+IF(P9<>"",Q9="待确认",0)+IF(T9<>"",U9="待确认",0)+IF(X9<>"",Y9="待确认",0)>0,"待确认","未开始"))))) -> 已完成 | H9: =IF(L9<>"",L9,IF(P9<>"",P9,IF(T9<>"",T9,X9))) -> 项目经理 | I9: =IF(COUNT(N9,R9,V9,Z9)=0,"",MIN(N9,R9,V9,Z9)) -> 46146 | J9: =IF(COUNT(O9,S9,W9,AA9)=0,"",MAX(O9,S9,W9,AA9)) -> 46191 | K9: 46283 | L9: 项目经理 | M9: 已完成 | N9: 46146 | O9: 46191 | AB9: =IFERROR((IF(L9<>"",IF(M9="已完成",1,IF(M9="进行中",0.5,0))*15%,0)+IF(P9<>"",IF(Q9="已完成",1,IF(Q9="进行中",0.5,0))*35%,0)+IF(T9<>"",IF(U9="已完成",1,IF(U9="进行中",0.5,0))*30%,0)+IF(X9<>"",IF(Y9="已完成",1,IF(Y9="进行中",0.5,0))*20%,0))/(IF(L9<>"",15%,0)+IF(P9<>"",35%,0)+IF(T9<>"",30%,0)+IF(X9<>"",20%,0)),0) -> 1 | AC9: =IF($A9="","",IF(G9="已完成","正常",IF(G9="暂停","暂停",IF(J9="","日期缺失",IF(J9<_数据接口!$B$7,"已延期",IF(J9<=_数据接口!$B$7+7,"临近到期","正常")))))) -> 正常 | AH9: =IF(OR($A9="",J9="",AG9=""),"",AG9-J9)
A10: T007 | E10: 形成实施路径、资源与风险建议 | F10: MS002 | G10: =IF(OR(M10="暂停",M10="挂起",Q10="暂停",Q10="挂起",U10="暂停",U10="挂起",Y10="暂停",Y10="挂起"),"暂停",IF(COUNTA(L10,P10,T10,X10)=0,"未分配",IF(IF(L10<>"",M10="已完成",0)+IF(P10<>"",Q10="已完成",0)+IF(T10<>"",U10="已完成",0)+IF(X10<>"",Y10="已完成",0)=COUNTA(L10,P10,T10,X10),"已完成",IF(IF(L10<>"",M10="进行中",0)+IF(P10<>"",Q10="进行中",0)+IF(T10<>"",U10="进行中",0)+IF(X10<>"",Y10="进行中",0)>0,"进行中",IF(IF(L10<>"",M10="待确认",0)+IF(P10<>"",Q10="待确认",0)+IF(T10<>"",U10="待确认",0)+IF(X10<>"",Y10="待确认",0)>0,"待确认","未开始"))))) -> 已完成 | H10: =IF(L10<>"",L10,IF(P10<>"",P10,IF(T10<>"",T10,X10))) -> 项目经理 | I10: =IF(COUNT(N10,R10,V10,Z10)=0,"",MIN(N10,R10,V10,Z10)) -> 46192 | J10: =IF(COUNT(O10,S10,W10,AA10)=0,"",MAX(O10,S10,W10,AA10)) -> 46237 | K10: 46283 | L10: 项目经理 | M10: 已完成 | N10: 46192 | O10: 46237 | AB10: =IFERROR((IF(L10<>"",IF(M10="已完成",1,IF(M10="进行中",0.5,0))*15%,0)+IF(P10<>"",IF(Q10="已完成",1,IF(Q10="进行中",0.5,0))*35%,0)+IF(T10<>"",IF(U10="已完成",1,IF(U10="进行中",0.5,0))*30%,0)+IF(X10<>"",IF(Y10="已完成",1,IF(Y10="进行中",0.5,0))*20%,0))/(IF(L10<>"",15%,0)+IF(P10<>"",35%,0)+IF(T10<>"",30%,0)+IF(X10<>"",20%,0)),0) -> 1 | AC10: =IF($A10="","",IF(G10="已完成","正常",IF(G10="暂停","暂停",IF(J10="","日期缺失",IF(J10<_数据接口!$B$7,"已延期",IF(J10<=_数据接口!$B$7+7,"临近到期","正常")))))) -> 正常 | AH10: =IF(OR($A10="",J10="",AG10=""),"",AG10-J10)
A11: T008 | E11: 汇编可研报告并组织评审 | F11: MS002 | G11: =IF(OR(M11="暂停",M11="挂起",Q11="暂停",Q11="挂起",U11="暂停",U11="挂起",Y11="暂停",Y11="挂起"),"暂停",IF(COUNTA(L11,P11,T11,X11)=0,"未分配",IF(IF(L11<>"",M11="已完成",0)+IF(P11<>"",Q11="已完成",0)+IF(T11<>"",U11="已完成",0)+IF(X11<>"",Y11="已完成",0)=COUNTA(L11,P11,T11,X11),"已完成",IF(IF(L11<>"",M11="进行中",0)+IF(P11<>"",Q11="进行中",0)+IF(T11<>"",U11="进行中",0)+IF(X11<>"",Y11="进行中",0)>0,"进行中",IF(IF(L11<>"",M11="待确认",0)+IF(P11<>"",Q11="待确认",0)+IF(T11<>"",U11="待确认",0)+IF(X11<>"",Y11="待确认",0)>0,"待确认","未开始"))))) -> 已完成 | H11: =IF(L11<>"",L11,IF(P11<>"",P11,IF(T11<>"",T11,X11))) -> 项目经理 | I11: =IF(COUNT(N11,R11,V11,Z11)=0,"",MIN(N11,R11,V11,Z11)) -> 46238 | J11: =IF(COUNT(O11,S11,W11,AA11)=0,"",MAX(O11,S11,W11,AA11)) -> 46283 | K11: 46283 | L11: 项目经理 | M11: 已完成 | N11: 46238 | O11: 46283 | AB11: =IFERROR((IF(L11<>"",IF(M11="已完成",1,IF(M11="进行中",0.5,0))*15%,0)+IF(P11<>"",IF(Q11="已完成",1,IF(Q11="进行中",0.5,0))*35%,0)+IF(T11<>"",IF(U11="已完成",1,IF(U11="进行中",0.5,0))*30%,0)+IF(X11<>"",IF(Y11="已完成",1,IF(Y11="进行中",0.5,0))*20%,0))/(IF(L11<>"",15%,0)+IF(P11<>"",35%,0)+IF(T11<>"",30%,0)+IF(X11<>"",20%,0)),0) -> 1 | AC11: =IF($A11="","",IF(G11="已完成","正常",IF(G11="暂停","暂停",IF(J11="","日期缺失",IF(J11<_数据接口!$B$7,"已延期",IF(J11<=_数据接口!$B$7+7,"临近到期","正常")))))) -> 正常 | AF11: 2026-W40 | AH11: =IF(OR($A11="",J11="",AG11=""),"",AG11-J11)
A12: T009 | C12: 原业务梳理完成 | D12: 现状调研 | E12: 梳理合同业务组织与职责 | F12: MS003 | G12: =IF(OR(M12="暂停",M12="挂起",Q12="暂停",Q12="挂起",U12="暂停",U12="挂起",Y12="暂停",Y12="挂起"),"暂停",IF(COUNTA(L12,P12,T12,X12)=0,"未分配",IF(IF(L12<>"",M12="已完成",0)+IF(P12<>"",Q12="已完成",0)+IF(T12<>"",U12="已完成",0)+IF(X12<>"",Y12="已完成",0)=COUNTA(L12,P12,T12,X12),"已完成",IF(IF(L12<>"",M12="进行中",0)+IF(P12<>"",Q12="进行中",0)+IF(T12<>"",U12="进行中",0)+IF(X12<>"",Y12="进行中",0)>0,"进行中",IF(IF(L12<>"",M12="待确认",0)+IF(P12<>"",Q12="待确认",0)+IF(T12<>"",U12="待确认",0)+IF(X12<>"",Y12="待确认",0)>0,"待确认","未开始"))))) -> 已完成 | H12: =IF(L12<>"",L12,IF(P12<>"",P12,IF(T12<>"",T12,X12))) -> 产品经理 | I12: =IF(COUNT(N12,R12,V12,Z12)=0,"",MIN(N12,R12,V12,Z12)) -> 46064 | J12: =IF(COUNT(O12,S12,W12,AA12)=0,"",MAX(O12,S12,W12,AA12)) -> 46091 | K12: 46203 | L12: 产品经理 | M12: 已完成 | N12: 46064 | O12: 46091 | AB12: =IFERROR((IF(L12<>"",IF(M12="已完成",1,IF(M12="进行中",0.5,0))*15%,0)+IF(P12<>"",IF(Q12="已完成",1,IF(Q12="进行中",0.5,0))*35%,0)+IF(T12<>"",IF(U12="已完成",1,IF(U12="进行中",0.5,0))*30%,0)+IF(X12<>"",IF(Y12="已完成",1,IF(Y12="进行中",0.5,0))*20%,0))/(IF(L12<>"",15%,0)+IF(P12<>"",35%,0)+IF(T12<>"",30%,0)+IF(X12<>"",20%,0)),0) -> 1 | AC12: =IF($A12="","",IF(G12="已完成","正常",IF(G12="暂停","暂停",IF(J12="","日期缺失",IF(J12<_数据接口!$B$7,"已延期",IF(J12<=_数据接口!$B$7+7,"临近到期","正常")))))) -> 正常 | AH12: =IF(OR($A12="",J12="",AG12=""),"",AG12-J12)
A13: T010 | E13: 盘点合同全生命周期业务流程 | F13: MS003 | G13: =IF(OR(M13="暂停",M13="挂起",Q13="暂停",Q13="挂起",U13="暂停",U13="挂起",Y13="暂停",Y13="挂起"),"暂停",IF(COUNTA(L13,P13,T13,X13)=0,"未分配",IF(IF(L13<>"",M13="已完成",0)+IF(P13<>"",Q13="已完成",0)+IF(T13<>"",U13="已完成",0)+IF(X13<>"",Y13="已完成",0)=COUNTA(L13,P13,T13,X13),"已完成",IF(IF(L13<>"",M13="进行中",0)+IF(P13<>"",Q13="进行中",0)+IF(T13<>"",U13="进行中",0)+IF(X13<>"",Y13="进行中",0)>0,"进行中",IF(IF(L13<>"",M13="待确认",0)+IF(P13<>"",Q13="待确认",0)+IF(T13<>"",U13="待确认",0)+IF(X13<>"",Y13="待确认",0)>0,"待确认","未开始"))))) -> 已完成 | H13: =IF(L13<>"",L13,IF(P13<>"",P13,IF(T13<>"",T13,X13))) -> 产品经理 | I13: =IF(COUNT(N13,R13,V13,Z13)=0,"",MIN(N13,R13,V13,Z13)) -> 46092 | J13: =IF(COUNT(O13,S13,W13,AA13)=0,"",MAX(O13,S13,W13,AA13)) -> 46119 | K13: 46203 | L13: 产品经理 | M13: 已完成 | N13: 46092 | O13: 46119 | AB13: =IFERROR((IF(L13<>"",IF(M13="已完成",1,IF(M13="进行中",0.5,0))*15%,0)+IF(P13<>"",IF(Q13="已完成",1,IF(Q13="进行中",0.5,0))*35%,0)+IF(T13<>"",IF(U13="已完成",1,IF(U13="进行中",0.5,0))*30%,0)+IF(X13<>"",IF(Y13="已完成",1,IF(Y13="进行中",0.5,0))*20%,0))/(IF(L13<>"",15%,0)+IF(P13<>"",35%,0)+IF(T13<>"",30%,0)+IF(X13<>"",20%,0)),0) -> 1 | AC13: =IF($A13="","",IF(G13="已完成","正常",IF(G13="暂停","暂停",IF(J13="","日期缺失",IF(J13<_数据接口!$B$7,"已延期",IF(J13<=_数据接口!$B$7+7,"临近到期","正常")))))) -> 正常 | AH13: =IF(OR($A13="",J13="",AG13=""),"",AG13-J13)
A14: T011 | E14: 盘点既有系统、接口与数据 | F14: MS003 | G14: =IF(OR(M14="暂停",M14="挂起",Q14="暂停",Q14="挂起",U14="暂停",U14="挂起",Y14="暂停",Y14="挂起"),"暂停",IF(COUNTA(L14,P14,T14,X14)=0,"未分配",IF(IF(L14<>"",M14="已完成",0)+IF(P14<>"",Q14="已完成",0)+IF(T14<>"",U14="已完成",0)+IF(X14<>"",Y14="已完成",0)=COUNTA(L14,P14,T14,X14),"已完成",IF(IF(L14<>"",M14="进行中",0)+IF(P14<>"",Q14="进行中",0)+IF(T14<>"",U14="进行中",0)+IF(X14<>"",Y14="进行中",0)>0,"进行中",IF(IF(L14<>"",M14="待确认",0)+IF(P14<>"",Q14="待确认",0)+IF(T14<>"",U14="待确认",0)+IF(X14<>"",Y14="待确认",0)>0,"待确认","未开始"))))) -> 进行中 | H14: =IF(L14<>"",L14,IF(P14<>"",P14,IF(T14<>"",T14,X14))) -> 技术经理 | I14: =IF(COUNT(N14,R14,V14,Z14)=0,"",MIN(N14,R14,V14,Z14)) -> 46120 | J14: =IF(COUNT(O14,S14,W14,AA14)=0,"",MAX(O14,S14,W14,AA14)) -> 46147 | K14: 46203 | M14: 进行中 | P14: 技术经理 | Q14: 进行中 | R14: 46120 | S14: 46147 | AB14: =IFERROR((IF(L14<>"",IF(M14="已完成",1,IF(M14="进行中",0.5,0))*15%,0)+IF(P14<>"",IF(Q14="已完成",1,IF(Q14="进行中",0.5,0))*35%,0)+IF(T14<>"",IF(U14="已完成",1,IF(U14="进行中",0.5,0))*30%,0)+IF(X14<>"",IF(Y14="已完成",1,IF(Y14="进行中",0.5,0))*20%,0))/(IF(L14<>"",15%,0)+IF(P14<>"",35%,0)+IF(T14<>"",30%,0)+IF(X14<>"",20%,0)),0) -> 0.5 | AC14: =IF($A14="","",IF(G14="已完成","正常",IF(G14="暂停","暂停",IF(J14="","日期缺失",IF(J14<_数据接口!$B$7,"已延期",IF(J14<=_数据接口!$B$7+7,"临近到期","正常")))))) -> 已延期 | AF14: 2026-W40 | AH14: =IF(OR($A14="",J14="",AG14=""),"",AG14-J14)
A15: T012 | D15: 问题分析 | E15: 访谈业务部门并形成痛点清单 | F15: MS003 | G15: =IF(OR(M15="暂停",M15="挂起",Q15="暂停",Q15="挂起",U15="暂停",U15="挂起",Y15="暂停",Y15="挂起"),"暂停",IF(COUNTA(L15,P15,T15,X15)=0,"未分配",IF(IF(L15<>"",M15="已完成",0)+IF(P15<>"",Q15="已完成",0)+IF(T15<>"",U15="已完成",0)+IF(X15<>"",Y15="已完成",0)=COUNTA(L15,P15,T15,X15),"已完成",IF(IF(L15<>"",M15="进行中",0)+IF(P15<>"",Q15="进行中",0)+IF(T15<>"",U15="进行中",0)+IF(X15<>"",Y15="进行中",0)>0,"进行中",IF(IF(L15<>"",M15="待确认",0)+IF(P15<>"",Q15="待确认",0)+IF(T15<>"",U15="待确认",0)+IF(X15<>"",Y15="待确认",0)>0,"待确认","未开始"))))) -> 已完成 | H15: =IF(L15<>"",L15,IF(P15<>"",P15,IF(T15<>"",T15,X15))) -> 产品经理 | I15: =IF(COUNT(N15,R15,V15,Z15)=0,"",MIN(N15,R15,V15,Z15)) -> 46148 | J15: =IF(COUNT(O15,S15,W15,AA15)=0,"",MAX(O15,S15,W15,AA15)) -> 46175 | K15: 46203 | L15: 产品经理 | M15: 已完成 | N15: 46148 | O15: 46175 | AB15: =IFERROR((IF(L15<>"",IF(M15="已完成",1,IF(M15="进行中",0.5,0))*15%,0)+IF(P15<>"",IF(Q15="已完成",1,IF(Q15="进行中",0.5,0))*35%,0)+IF(T15<>"",IF(U15="已完成",1,IF(U15="进行中",0.5,0))*30%,0)+IF(X15<>"",IF(Y15="已完成",1,IF(Y15="进行中",0.5,0))*20%,0))/(IF(L15<>"",15%,0)+IF(P15<>"",35%,0)+IF(T15<>"",30%,0)+IF(X15<>"",20%,0)),0) -> 1 | AC15: =IF($A15="","",IF(G15="已完成","正常",IF(G15="暂停","暂停",IF(J15="","日期缺失",IF(J15<_数据接口!$B$7,"已延期",IF(J15<=_数据接口!$B$7+7,"临近到期","正常")))))) -> 正常 | AH15: =IF(OR($A15="",J15="",AG15=""),"",AG15-J15)
A16: T013 | D16: 现状基线 | E16: 确认现状流程、问题与改进机会基线 | F16: MS003 | G16: =IF(OR(M16="暂停",M16="挂起",Q16="暂停",Q16="挂起",U16="暂停",U16="挂起",Y16="暂停",Y16="挂起"),"暂停",IF(COUNTA(L16,P16,T16,X16)=0,"未分配",IF(IF(L16<>"",M16="已完成",0)+IF(P16<>"",Q16="已完成",0)+IF(T16<>"",U16="已完成",0)+IF(X16<>"",Y16="已完成",0)=COUNTA(L16,P16,T16,X16),"已完成",IF(IF(L16<>"",M16="进行中",0)+IF(P16<>"",Q16="进行中",0)+IF(T16<>"",U16="进行中",0)+IF(X16<>"",Y16="进行中",0)>0,"进行中",IF(IF(L16<>"",M16="待确认",0)+IF(P16<>"",Q16="待确认",0)+IF(T16<>"",U16="待确认",0)+IF(X16<>"",Y16="待确认",0)>0,"待确认","未开始"))))) -> 已完成 | H16: =IF(L16<>"",L16,IF(P16<>"",P16,IF(T16<>"",T16,X16))) -> 项目经理 | I16: =IF(COUNT(N16,R16,V16,Z16)=0,"",MIN(N16,R16,V16,Z16)) -> 46176 | J16: =IF(COUNT(O16,S16,W16,AA16)=0,"",MAX(O16,S16,W16,AA16)) -> 46203 | K16: 46203 | L16: 项目经理 | M16: 已完成 | N16: 46176 | O16: 46203 | AB16: =IFERROR((IF(L16<>"",IF(M16="已完成",1,IF(M16="进行中",0.5,0))*15%,0)+IF(P16<>"",IF(Q16="已完成",1,IF(Q16="进行中",0.5,0))*35%,0)+IF(T16<>"",IF(U16="已完成",1,IF(U16="进行中",0.5,0))*30%,0)+IF(X16<>"",IF(Y16="已完成",1,IF(Y16="进行中",0.5,0))*20%,0))/(IF(L16<>"",15%,0)+IF(P16<>"",35%,0)+IF(T16<>"",30%,0)+IF(X16<>"",20%,0)),0) -> 1 | AC16: =IF($A16="","",IF(G16="已完成","正常",IF(G16="暂停","暂停",IF(J16="","日期缺失",IF(J16<_数据接口!$B$7,"已延期",IF(J16<=_数据接口!$B$7+7,"临近到期","正常")))))) -> 正常 | AH16: =IF(OR($A16="",J16="",AG16=""),"",AG16-J16)
A17: T014 | B17: 项目规范梳理与技术架构搭建 | C17: 项目规范基线确认 | D17: 项目规范 | E17: 制定项目治理、会议与报告机制 | F17: MS004 | G17: =IF(OR(M17="暂停",M17="挂起",Q17="暂停",Q17="挂起",U17="暂停",U17="挂起",Y17="暂停",Y17="挂起"),"暂停",IF(COUNTA(L17,P17,T17,X17)=0,"未分配",IF(IF(L17<>"",M17="已完成",0)+IF(P17<>"",Q17="已完成",0)+IF(T17<>"",U17="已完成",0)+IF(X17<>"",Y17="已完成",0)=COUNTA(L17,P17,T17,X17),"已完成",IF(IF(L17<>"",M17="进行中",0)+IF(P17<>"",Q17="进行中",0)+IF(T17<>"",U17="进行中",0)+IF(X17<>"",Y17="进行中",0)>0,"进行中",IF(IF(L17<>"",M17="待确认",0)+IF(P17<>"",Q17="待确认",0)+IF(T17<>"",U17="待确认",0)+IF(X17<>"",Y17="待确认",0)>0,"待确认","未开始"))))) -> 待确认 | H17: =IF(L17<>"",L17,IF(P17<>"",P17,IF(T17<>"",T17,X17))) -> 项目经理 | I17: =IF(COUNT(N17,R17,V17,Z17)=0,"",MIN(N17,R17,V17,Z17)) -> 46204 | J17: =IF(COUNT(O17,S17,W17,AA17)=0,"",MAX(O17,S17,W17,AA17)) -> 46215 | K17: 46265 | L17: 项目经理 | M17: 待确认 | N17: 46204 | O17: 46215 | AB17: =IFERROR((IF(L17<>"",IF(M17="已完成",1,IF(M17="进行中",0.5,0))*15%,0)+IF(P17<>"",IF(Q17="已完成",1,IF(Q17="进行中",0.5,0))*35%,0)+IF(T17<>"",IF(U17="已完成",1,IF(U17="进行中",0.5,0))*30%,0)+IF(X17<>"",IF(Y17="已完成",1,IF(Y17="进行中",0.5,0))*20%,0))/(IF(L17<>"",15%,0)+IF(P17<>"",35%,0)+IF(T17<>"",30%,0)+IF(X17<>"",20%,0)),0) -> 0 | AC17: =IF($A17="","",IF(G17="已完成","正常",IF(G17="暂停","暂停",IF(J17="","日期缺失",IF(J17<_数据接口!$B$7,"已延期",IF(J17<=_数据接口!$B$7+7,"临近到期","正常")))))) -> 已延期 | AH17: =IF(OR($A17="",J17="",AG17=""),"",AG17-J17)
A18: T015 | D18: 需求规范 | E18: 制定需求分级、跟踪与变更规范 | F18: MS004 | G18: =IF(OR(M18="暂停",M18="挂起",Q18="暂停",Q18="挂起",U18="暂停",U18="挂起",Y18="暂停",Y18="挂起"),"暂停",IF(COUNTA(L18,P18,T18,X18)=0,"未分配",IF(IF(L18<>"",M18="已完成",0)+IF(P18<>"",Q18="已完成",0)+IF(T18<>"",U18="已完成",0)+IF(X18<>"",Y18="已完成",0)=COUNTA(L18,P18,T18,X18),"已完成",IF(IF(L18<>"",M18="进行中",0)+IF(P18<>"",Q18="进行中",0)+IF(T18<>"",U18="进行中",0)+IF(X18<>"",Y18="进行中",0)>0,"进行中",IF(IF(L18<>"",M18="待确认",0)+IF(P18<>"",Q18="待确认",0)+IF(T18<>"",U18="待确认",0)+IF(X18<>"",Y18="待确认",0)>0,"待确认","未开始"))))) -> 待确认 | H18: =IF(L18<>"",L18,IF(P18<>"",P18,IF(T18<>"",T18,X18))) -> 产品经理 | I18: =IF(COUNT(N18,R18,V18,Z18)=0,"",MIN(N18,R18,V18,Z18)) -> 46216 | J18: =IF(COUNT(O18,S18,W18,AA18)=0,"",MAX(O18,S18,W18,AA18)) -> 46227 | K18: 46265 | L18: 产品经理 | M18: 待确认 | N18: 46216 | O18: 46227 | AB18: =IFERROR((IF(L18<>"",IF(M18="已完成",1,IF(M18="进行中",0.5,0))*15%,0)+IF(P18<>"",IF(Q18="已完成",1,IF(Q18="进行中",0.5,0))*35%,0)+IF(T18<>"",IF(U18="已完成",1,IF(U18="进行中",0.5,0))*30%,0)+IF(X18<>"",IF(Y18="已完成",1,IF(Y18="进行中",0.5,0))*20%,0))/(IF(L18<>"",15%,0)+IF(P18<>"",35%,0)+IF(T18<>"",30%,0)+IF(X18<>"",20%,0)),0) -> 0 | AC18: =IF($A18="","",IF(G18="已完成","正常",IF(G18="暂停","暂停",IF(J18="","日期缺失",IF(J18<_数据接口!$B$7,"已延期",IF(J18<=_数据接口!$B$7+7,"临近到期","正常")))))) -> 已延期 | AH18: =IF(OR($A18="",J18="",AG18=""),"",AG18-J18)
A19: T016 | D19: 研发规范 | E19: 制定设计、编码与代码评审规范 | F19: MS004 | G19: =IF(OR(M19="暂停",M19="挂起",Q19="暂停",Q19="挂起",U19="暂停",U19="挂起",Y19="暂停",Y19="挂起"),"暂停",IF(COUNTA(L19,P19,T19,X19)=0,"未分配",IF(IF(L19<>"",M19="已完成",0)+IF(P19<>"",Q19="已完成",0)+IF(T19<>"",U19="已完成",0)+IF(X19<>"",Y19="已完成",0)=COUNTA(L19,P19,T19,X19),"已完成",IF(IF(L19<>"",M19="进行中",0)+IF(P19<>"",Q19="进行中",0)+IF(T19<>"",U19="进行中",0)+IF(X19<>"",Y19="进行中",0)>0,"进行中",IF(IF(L19<>"",M19="待确认",0)+IF(P19<>"",Q19="待确认",0)+IF(T19<>"",U19="待确认",0)+IF(X19<>"",Y19="待确认",0)>0,"待确认","未开始"))))) -> 待确认 | H19: =IF(L19<>"",L19,IF(P19<>"",P19,IF(T19<>"",T19,X19))) -> 技术经理 | I19: =IF(COUNT(N19,R19,V19,Z19)=0,"",MIN(N19,R19,V19,Z19)) -> 46228 | J19: =IF(COUNT(O19,S19,W19,AA19)=0,"",MAX(O19,S19,W19,AA19)) -> 46240 | K19: 46265 | P19: 技术经理 | Q19: 待确认 | R19: 46228 | S19: 46240 | AB19: =IFERROR((IF(L19<>"",IF(M19="已完成",1,IF(M19="进行中",0.5,0))*15%,0)+IF(P19<>"",IF(Q19="已完成",1,IF(Q19="进行中",0.5,0))*35%,0)+IF(T19<>"",IF(U19="已完成",1,IF(U19="进行中",0.5,0))*30%,0)+IF(X19<>"",IF(Y19="已完成",1,IF(Y19="进行中",0.5,0))*20%,0))/(IF(L19<>"",15%,0)+IF(P19<>"",35%,0)+IF(T19<>"",30%,0)+IF(X19<>"",20%,0)),0) -> 0 | AC19: =IF($A19="","",IF(G19="已完成","正常",IF(G19="暂停","暂停",IF(J19="","日期缺失",IF(J19<_数据接口!$B$7,"已延期",IF(J19<=_数据接口!$B$7+7,"临近到期","正常")))))) -> 已延期 | AH19: =IF(OR($A19="",J19="",AG19=""),"",AG19-J19)
A20: T017 | D20: 质量规范 | E20: 制定测试、缺陷与质量门禁规范 | F20: MS004 | G20: =IF(OR(M20="暂停",M20="挂起",Q20="暂停",Q20="挂起",U20="暂停",U20="挂起",Y20="暂停",Y20="挂起"),"暂停",IF(COUNTA(L20,P20,T20,X20)=0,"未分配",IF(IF(L20<>"",M20="已完成",0)+IF(P20<>"",Q20="已完成",0)+IF(T20<>"",U20="已完成",0)+IF(X20<>"",Y20="已完成",0)=COUNTA(L20,P20,T20,X20),"已完成",IF(IF(L20<>"",M20="进行中",0)+IF(P20<>"",Q20="进行中",0)+IF(T20<>"",U20="进行中",0)+IF(X20<>"",Y20="进行中",0)>0,"进行中",IF(IF(L20<>"",M20="待确认",0)+IF(P20<>"",Q20="待确认",0)+IF(T20<>"",U20="待确认",0)+IF(X20<>"",Y20="待确认",0)>0,"待确认","未开始"))))) -> 待确认 | H20: =IF(L20<>"",L20,IF(P20<>"",P20,IF(T20<>"",T20,X20))) -> 高级测试人员、中级测试人员 | I20: =IF(COUNT(N20,R20,V20,Z20)=0,"",MIN(N20,R20,V20,Z20)) -> 46241 | J20: =IF(COUNT(O20,S20,W20,AA20)=0,"",MAX(O20,S20,W20,AA20)) -> 46252 | K20: 46265 | X20: 高级测试人员、中级测试人员 | Y20: 待确认 | Z20: 46241 | AA20: 46252 | AB20: =IFERROR((IF(L20<>"",IF(M20="已完成",1,IF(M20="进行中",0.5,0))*15%,0)+IF(P20<>"",IF(Q20="已完成",1,IF(Q20="进行中",0.5,0))*35%,0)+IF(T20<>"",IF(U20="已完成",1,IF(U20="进行中",0.5,0))*30%,0)+IF(X20<>"",IF(Y20="已完成",1,IF(Y20="进行中",0.5,0))*20%,0))/(IF(L20<>"",15%,0)+IF(P20<>"",35%,0)+IF(T20<>"",30%,0)+IF(X20<>"",20%,0)),0) -> 0 | AC20: =IF($A20="","",IF(G20="已完成","正常",IF(G20="暂停","暂停",IF(J20="","日期缺失",IF(J20<_数据接口!$B$7,"已延期",IF(J20<=_数据接口!$B$7+7,"临近到期","正常")))))) -> 已延期 | AH20: =IF(OR($A20="",J20="",AG20=""),"",AG20-J20)
A21: T018 | D21: 配置规范 | E21: 制定配置、发布与文档归档规范 | F21: MS004 | G21: =IF(OR(M21="暂停",M21="挂起",Q21="暂停",Q21="挂起",U21="暂停",U21="挂起",Y21="暂停",Y21="挂起"),"暂停",IF(COUNTA(L21,P21,T21,X21)=0,"未分配",IF(IF(L21<>"",M21="已完成",0)+IF(P21<>"",Q21="已完成",0)+IF(T21<>"",U21="已完成",0)+IF(X21<>"",Y21="已完成",0)=COUNTA(L21,P21,T21,X21),"已完成",IF(IF(L21<>"",M21="进行中",0)+IF(P21<>"",Q21="进行中",0)+IF(T21<>"",U21="进行中",0)+IF(X21<>"",Y21="进行中",0)>0,"进行中",IF(IF(L21<>"",M21="待确认",0)+IF(P21<>"",Q21="待确认",0)+IF(T21<>"",U21="待确认",0)+IF(X21<>"",Y21="待确认",0)>0,"待确认","未开始"))))) -> 待确认 | H21: =IF(L21<>"",L21,IF(P21<>"",P21,IF(T21<>"",T21,X21))) -> 配置人员 | I21: =IF(COUNT(N21,R21,V21,Z21)=0,"",MIN(N21,R21,V21,Z21)) -> 46253 | J21: =IF(COUNT(O21,S21,W21,AA21)=0,"",MAX(O21,S21,W21,AA21)) -> 46265 | K21: 46265 | P21: 配置人员 | Q21: 待确认 | R21: 46253 | S21: 46265 | AB21: =IFERROR((IF(L21<>"",IF(M21="已完成",1,IF(M21="进行中",0.5,0))*15%,0)+IF(P21<>"",IF(Q21="已完成",1,IF(Q21="进行中",0.5,0))*35%,0)+IF(T21<>"",IF(U21="已完成",1,IF(U21="进行中",0.5,0))*30%,0)+IF(X21<>"",IF(Y21="已完成",1,IF(Y21="进行中",0.5,0))*20%,0))/(IF(L21<>"",15%,0)+IF(P21<>"",35%,0)+IF(T21<>"",30%,0)+IF(X21<>"",20%,0)),0) -> 0 | AC21: =IF($A21="","",IF(G21="已完成","正常",IF(G21="暂停","暂停",IF(J21="","日期缺失",IF(J21<_数据接口!$B$7,"已延期",IF(J21<=_数据接口!$B$7+7,"临近到期","正常")))))) -> 已延期 | AH21: =IF(OR($A21="",J21="",AG21=""),"",AG21-J21)
A22: T019 | C22: 技术架构基线确认 | D22: 应用架构 | E22: 完成系统分层、模块与服务边界设计 | F22: MS005 | G22: =IF(OR(M22="暂停",M22="挂起",Q22="暂停",Q22="挂起",U22="暂停",U22="挂起",Y22="暂停",Y22="挂起"),"暂停",IF(COUNTA(L22,P22,T22,X22)=0,"未分配",IF(IF(L22<>"",M22="已完成",0)+IF(P22<>"",Q22="已完成",0)+IF(T22<>"",U22="已完成",0)+IF(X22<>"",Y22="已完成",0)=COUNTA(L22,P22,T22,X22),"已完成",IF(IF(L22<>"",M22="进行中",0)+IF(P22<>"",Q22="进行中",0)+IF(T22<>"",U22="进行中",0)+IF(X22<>"",Y22="进行中",0)>0,"进行中",IF(IF(L22<>"",M22="待确认",0)+IF(P22<>"",Q22="待确认",0)+IF(T22<>"",U22="待确认",0)+IF(X22<>"",Y22="待确认",0)>0,"待确认","未开始"))))) -> 待确认 | H22: =IF(L22<>"",L22,IF(P22<>"",P22,IF(T22<>"",T22,X22))) -> 技术经理 | I22: =IF(COUNT(N22,R22,V22,Z22)=0,"",MIN(N22,R22,V22,Z22)) -> 46204 | J22: =IF(COUNT(O22,S22,W22,AA22)=0,"",MAX(O22,S22,W22,AA22)) -> 46218 | K22: 46295 | P22: 技术经理 | Q22: 待确认 | R22: 46204 | S22: 46218 | AB22: =IFERROR((IF(L22<>"",IF(M22="已完成",1,IF(M22="进行中",0.5,0))*15%,0)+IF(P22<>"",IF(Q22="已完成",1,IF(Q22="进行中",0.5,0))*35%,0)+IF(T22<>"",IF(U22="已完成",1,IF(U22="进行中",0.5,0))*30%,0)+IF(X22<>"",IF(Y22="已完成",1,IF(Y22="进行中",0.5,0))*20%,0))/(IF(L22<>"",15%,0)+IF(P22<>"",35%,0)+IF(T22<>"",30%,0)+IF(X22<>"",20%,0)),0) -> 0 | AC22: =IF($A22="","",IF(G22="已完成","正常",IF(G22="暂停","暂停",IF(J22="","日期缺失",IF(J22<_数据接口!$B$7,"已延期",IF(J22<=_数据接口!$B$7+7,"临近到期","正常")))))) -> 已延期 | AH22: =IF(OR($A22="",J22="",AG22=""),"",AG22-J22)
A23: T020 | D23: 数据架构 | E23: 完成主数据、交易数据与分析数据架构 | F23: MS005 | G23: =IF(OR(M23="暂停",M23="挂起",Q23="暂停",Q23="挂起",U23="暂停",U23="挂起",Y23="暂停",Y23="挂起"),"暂停",IF(COUNTA(L23,P23,T23,X23)=0,"未分配",IF(IF(L23<>"",M23="已完成",0)+IF(P23<>"",Q23="已完成",0)+IF(T23<>"",U23="已完成",0)+IF(X23<>"",Y23="已完成",0)=COUNTA(L23,P23,T23,X23),"已完成",IF(IF(L23<>"",M23="进行中",0)+IF(P23<>"",Q23="进行中",0)+IF(T23<>"",U23="进行中",0)+IF(X23<>"",Y23="进行中",0)>0,"进行中",IF(IF(L23<>"",M23="待确认",0)+IF(P23<>"",Q23="待确认",0)+IF(T23<>"",U23="待确认",0)+IF(X23<>"",Y23="待确认",0)>0,"待确认","未开始"))))) -> 待确认 | H23: =IF(L23<>"",L23,IF(P23<>"",P23,IF(T23<>"",T23,X23))) -> 技术经理 | I23: =IF(COUNT(N23,R23,V23,Z23)=0,"",MIN(N23,R23,V23,Z23)) -> 46219 | J23: =IF(COUNT(O23,S23,W23,AA23)=0,"",MAX(O23,S23,W23,AA23)) -> 46233 | K23: 46295 | P23: 技术经理 | Q23: 待确认 | R23: 46219 | S23: 46233 | AB23: =IFERROR((IF(L23<>"",IF(M23="已完成",1,IF(M23="进行中",0.5,0))*15%,0)+IF(P23<>"",IF(Q23="已完成",1,IF(Q23="进行中",0.5,0))*35%,0)+IF(T23<>"",IF(U23="已完成",1,IF(U23="进行中",0.5,0))*30%,0)+IF(X23<>"",IF(Y23="已完成",1,IF(Y23="进行中",0.5,0))*20%,0))/(IF(L23<>"",15%,0)+IF(P23<>"",35%,0)+IF(T23<>"",30%,0)+IF(X23<>"",20%,0)),0) -> 0 | AC23: =IF($A23="","",IF(G23="已完成","正常",IF(G23="暂停","暂停",IF(J23="","日期缺失",IF(J23<_数据接口!$B$7,"已延期",IF(J23<=_数据接口!$B$7+7,"临近到期","正常")))))) -> 已延期 | AH23: =IF(OR($A23="",J23="",AG23=""),"",AG23-J23)
A24: T021 | D24: 集成架构 | E24: 完成内部及外部接口总体架构 | F24: MS005 | G24: =IF(OR(M24="暂停",M24="挂起",Q24="暂停",Q24="挂起",U24="暂停",U24="挂起",Y24="暂停",Y24="挂起"),"暂停",IF(COUNTA(L24,P24,T24,X24)=0,"未分配",IF(IF(L24<>"",M24="已完成",0)+IF(P24<>"",Q24="已完成",0)+IF(T24<>"",U24="已完成",0)+IF(X24<>"",Y24="已完成",0)=COUNTA(L24,P24,T24,X24),"已完成",IF(IF(L24<>"",M24="进行中",0)+IF(P24<>"",Q24="进行中",0)+IF(T24<>"",U24="进行中",0)+IF(X24<>"",Y24="进行中",0)>0,"进行中",IF(IF(L24<>"",M24="待确认",0)+IF(P24<>"",Q24="待确认",0)+IF(T24<>"",U24="待确认",0)+IF(X24<>"",Y24="待确认",0)>0,"待确认","未开始"))))) -> 待确认 | H24: =IF(L24<>"",L24,IF(P24<>"",P24,IF(T24<>"",T24,X24))) -> 高级开发人员 | I24: =IF(COUNT(N24,R24,V24,Z24)=0,"",MIN(N24,R24,V24,Z24)) -> 46234 | J24: =IF(COUNT(O24,S24,W24,AA24)=0,"",MAX(O24,S24,W24,AA24)) -> 46249 | K24: 46295 | P24: 高级开发人员 | Q24: 待确认 | R24: 46234 | S24: 46249 | AB24: =IFERROR((IF(L24<>"",IF(M24="已完成",1,IF(M24="进行中",0.5,0))*15%,0)+IF(P24<>"",IF(Q24="已完成",1,IF(Q24="进行中",0.5,0))*35%,0)+IF(T24<>"",IF(U24="已完成",1,IF(U24="进行中",0.5,0))*30%,0)+IF(X24<>"",IF(Y24="已完成",1,IF(Y24="进行中",0.5,0))*20%,0))/(IF(L24<>"",15%,0)+IF(P24<>"",35%,0)+IF(T24<>"",30%,0)+IF(X24<>"",20%,0)),0) -> 0 | AC24: =IF($A24="","",IF(G24="已完成","正常",IF(G24="暂停","暂停",IF(J24="","日期缺失",IF(J24<_数据接口!$B$7,"已延期",IF(J24<=_数据接口!$B$7+7,"临近到期","正常")))))) -> 已延期 | AH24: =IF(OR($A24="",J24="",AG24=""),"",AG24-J24)
A25: T022 | D25: 安全架构 | E25: 完成身份、权限、审计与数据安全设计 | F25: MS005 | G25: =IF(OR(M25="暂停",M25="挂起",Q25="暂停",Q25="挂起",U25="暂停",U25="挂起",Y25="暂停",Y25="挂起"),"暂停",IF(COUNTA(L25,P25,T25,X25)=0,"未分配",IF(IF(L25<>"",M25="已完成",0)+IF(P25<>"",Q25="已完成",0)+IF(T25<>"",U25="已完成",0)+IF(X25<>"",Y25="已完成",0)=COUNTA(L25,P25,T25,X25),"已完成",IF(IF(L25<>"",M25="进行中",0)+IF(P25<>"",Q25="进行中",0)+IF(T25<>"",U25="进行中",0)+IF(X25<>"",Y25="进行中",0)>0,"进行中",IF(IF(L25<>"",M25="待确认",0)+IF(P25<>"",Q25="待确认",0)+IF(T25<>"",U25="待确认",0)+IF(X25<>"",Y25="待确认",0)>0,"待确认","未开始"))))) -> 待确认 | H25: =IF(L25<>"",L25,IF(P25<>"",P25,IF(T25<>"",T25,X25))) -> 技术经理 | I25: =IF(COUNT(N25,R25,V25,Z25)=0,"",MIN(N25,R25,V25,Z25)) -> 46250 | J25: =IF(COUNT(O25,S25,W25,AA25)=0,"",MAX(O25,S25,W25,AA25)) -> 46264 | K25: 46295 | P25: 技术经理 | Q25: 待确认 | R25: 46250 | S25: 46264 | AB25: =IFERROR((IF(L25<>"",IF(M25="已完成",1,IF(M25="进行中",0.5,0))*15%,0)+IF(P25<>"",IF(Q25="已完成",1,IF(Q25="进行中",0.5,0))*35%,0)+IF(T25<>"",IF(U25="已完成",1,IF(U25="进行中",0.5,0))*30%,0)+IF(X25<>"",IF(Y25="已完成",1,IF(Y25="进行中",0.5,0))*20%,0))/(IF(L25<>"",15%,0)+IF(P25<>"",35%,0)+IF(T25<>"",30%,0)+IF(X25<>"",20%,0)),0) -> 0 | AC25: =IF($A25="","",IF(G25="已完成","正常",IF(G25="暂停","暂停",IF(J25="","日期缺失",IF(J25<_数据接口!$B$7,"已延期",IF(J25<=_数据接口!$B$7+7,"临近到期","正常")))))) -> 已延期 | AH25: =IF(OR($A25="",J25="",AG25=""),"",AG25-J25)
A26: T023 | D26: 部署架构 | E26: 完成环境、网络、容灾和DevOps设计 | F26: MS005 | G26: =IF(OR(M26="暂停",M26="挂起",Q26="暂停",Q26="挂起",U26="暂停",U26="挂起",Y26="暂停",Y26="挂起"),"暂停",IF(COUNTA(L26,P26,T26,X26)=0,"未分配",IF(IF(L26<>"",M26="已完成",0)+IF(P26<>"",Q26="已完成",0)+IF(T26<>"",U26="已完成",0)+IF(X26<>"",Y26="已完成",0)=COUNTA(L26,P26,T26,X26),"已完成",IF(IF(L26<>"",M26="进行中",0)+IF(P26<>"",Q26="进行中",0)+IF(T26<>"",U26="进行中",0)+IF(X26<>"",Y26="进行中",0)>0,"进行中",IF(IF(L26<>"",M26="待确认",0)+IF(P26<>"",Q26="待确认",0)+IF(T26<>"",U26="待确认",0)+IF(X26<>"",Y26="待确认",0)>0,"待确认","未开始"))))) -> 待确认 | H26: =IF(L26<>"",L26,IF(P26<>"",P26,IF(T26<>"",T26,X26))) -> 配置人员 | I26: =IF(COUNT(N26,R26,V26,Z26)=0,"",MIN(N26,R26,V26,Z26)) -> 46265 | J26: =IF(COUNT(O26,S26,W26,AA26)=0,"",MAX(O26,S26,W26,AA26)) -> 46279 | K26: 46295 | P26: 配置人员 | Q26: 待确认 | R26: 46265 | S26: 46279 | AB26: =IFERROR((IF(L26<>"",IF(M26="已完成",1,IF(M26="进行中",0.5,0))*15%,0)+IF(P26<>"",IF(Q26="已完成",1,IF(Q26="进行中",0.5,0))*35%,0)+IF(T26<>"",IF(U26="已完成",1,IF(U26="进行中",0.5,0))*30%,0)+IF(X26<>"",IF(Y26="已完成",1,IF(Y26="进行中",0.5,0))*20%,0))/(IF(L26<>"",15%,0)+IF(P26<>"",35%,0)+IF(T26<>"",30%,0)+IF(X26<>"",20%,0)),0) -> 0 | AC26: =IF($A26="","",IF(G26="已完成","正常",IF(G26="暂停","暂停",IF(J26="","日期缺失",IF(J26<_数据接口!$B$7,"已延期",IF(J26<=_数据接口!$B$7+7,"临近到期","正常")))))) -> 已延期 | AH26: =IF(OR($A26="",J26="",AG26=""),"",AG26-J26)
A27: T024 | D27: 架构评审 | E27: 汇编总体技术架构并完成基线评审 | F27: MS005 | G27: =IF(OR(M27="暂停",M27="挂起",Q27="暂停",Q27="挂起",U27="暂停",U27="挂起",Y27="暂停",Y27="挂起"),"暂停",IF(COUNTA(L27,P27,T27,X27)=0,"未分配",IF(IF(L27<>"",M27="已完成",0)+IF(P27<>"",Q27="已完成",0)+IF(T27<>"",U27="已完成",0)+IF(X27<>"",Y27="已完成",0)=COUNTA(L27,P27,T27,X27),"已完成",IF(IF(L27<>"",M27="进行中",0)+IF(P27<>"",Q27="进行中",0)+IF(T27<>"",U27="进行中",0)+IF(X27<>"",Y27="进行中",0)>0,"进行中",IF(IF(L27<>"",M27="待确认",0)+IF(P27<>"",Q27="待确认",0)+IF(T27<>"",U27="待确认",0)+IF(X27<>"",Y27="待确认",0)>0,"待确认","未开始"))))) -> 进行中 | H27: =IF(L27<>"",L27,IF(P27<>"",P27,IF(T27<>"",T27,X27))) -> 技术经理 | I27: =IF(COUNT(N27,R27,V27,Z27)=0,"",MIN(N27,R27,V27,Z27)) -> 46280 | J27: =IF(COUNT(O27,S27,W27,AA27)=0,"",MAX(O27,S27,W27,AA27)) -> 46295 | K27: 46295 | P27: 技术经理 | Q27: 进行中 | R27: 46280 | S27: 46295 | AB27: =IFERROR((IF(L27<>"",IF(M27="已完成",1,IF(M27="进行中",0.5,0))*15%,0)+IF(P27<>"",IF(Q27="已完成",1,IF(Q27="进行中",0.5,0))*35%,0)+IF(T27<>"",IF(U27="已完成",1,IF(U27="进行中",0.5,0))*30%,0)+IF(X27<>"",IF(Y27="已完成",1,IF(Y27="进行中",0.5,0))*20%,0))/(IF(L27<>"",15%,0)+IF(P27<>"",35%,0)+IF(T27<>"",30%,0)+IF(X27<>"",20%,0)),0) -> 0.5 | AC27: =IF($A27="","",IF(G27="已完成","正常",IF(G27="暂停","暂停",IF(J27="","日期缺失",IF(J27<_数据接口!$B$7,"已延期",IF(J27<=_数据接口!$B$7+7,"临近到期","正常")))))) -> 正常 | AF27: 2026-W40 | AH27: =IF(OR($A27="",J27="",AG27=""),"",AG27-J27)
A28: T025 | C28: 外部产品POC验证完成 | D28: POC准备 | E28: 编制CA、电子文档、BI报表POC方案与评分标准 | F28: MS017 | G28: =IF(OR(M28="暂停",M28="挂起",Q28="暂停",Q28="挂起",U28="暂停",U28="挂起",Y28="暂停",Y28="挂起"),"暂停",IF(COUNTA(L28,P28,T28,X28)=0,"未分配",IF(IF(L28<>"",M28="已完成",0)+IF(P28<>"",Q28="已完成",0)+IF(T28<>"",U28="已完成",0)+IF(X28<>"",Y28="已完成",0)=COUNTA(L28,P28,T28,X28),"已完成",IF(IF(L28<>"",M28="进行中",0)+IF(P28<>"",Q28="进行中",0)+IF(T28<>"",U28="进行中",0)+IF(X28<>"",Y28="进行中",0)>0,"进行中",IF(IF(L28<>"",M28="待确认",0)+IF(P28<>"",Q28="待确认",0)+IF(T28<>"",U28="待确认",0)+IF(X28<>"",Y28="待确认",0)>0,"待确认","未开始"))))) -> 待确认 | H28: =IF(L28<>"",L28,IF(P28<>"",P28,IF(T28<>"",T28,X28))) -> 技术经理 | I28: =IF(COUNT(N28,R28,V28,Z28)=0,"",MIN(N28,R28,V28,Z28)) -> 46249 | J28: =IF(COUNT(O28,S28,W28,AA28)=0,"",MAX(O28,S28,W28,AA28)) -> 46253 | K28: 46290 | P28: 技术经理 | Q28: 待确认 | R28: 46249 | S28: 46253 | AB28: =IFERROR((IF(L28<>"",IF(M28="已完成",1,IF(M28="进行中",0.5,0))*15%,0)+IF(P28<>"",IF(Q28="已完成",1,IF(Q28="进行中",0.5,0))*35%,0)+IF(T28<>"",IF(U28="已完成",1,IF(U28="进行中",0.5,0))*30%,0)+IF(X28<>"",IF(Y28="已完成",1,IF(Y28="进行中",0.5,0))*20%,0))/(IF(L28<>"",15%,0)+IF(P28<>"",35%,0)+IF(T28<>"",30%,0)+IF(X28<>"",20%,0)),0) -> 0 | AC28: =IF($A28="","",IF(G28="已完成","正常",IF(G28="暂停","暂停",IF(J28="","日期缺失",IF(J28<_数据接口!$B$7,"已延期",IF(J28<=_数据接口!$B$7+7,"临近到期","正常")))))) -> 已延期 | AE28: 执行工具：项目启动与治理/POC评分表；评分标准完成后由联合评审组确认。 | AH28: =IF(OR($A28="",J28="",AG28=""),"",AG28-J28)
A29: T026 | D29: CA验证 | E29: 验证证书签发、身份认证和证书管理 | F29: MS017 | G29: =IF(OR(M29="暂停",M29="挂起",Q29="暂停",Q29="挂起",U29="暂停",U29="挂起",Y29="暂停",Y29="挂起"),"暂停",IF(COUNTA(L29,P29,T29,X29)=0,"未分配",IF(IF(L29<>"",M29="已完成",0)+IF(P29<>"",Q29="已完成",0)+IF(T29<>"",U29="已完成",0)+IF(X29<>"",Y29="已完成",0)=COUNTA(L29,P29,T29,X29),"已完成",IF(IF(L29<>"",M29="进行中",0)+IF(P29<>"",Q29="进行中",0)+IF(T29<>"",U29="进行中",0)+IF(X29<>"",Y29="进行中",0)>0,"进行中",IF(IF(L29<>"",M29="待确认",0)+IF(P29<>"",Q29="待确认",0)+IF(T29<>"",U29="待确认",0)+IF(X29<>"",Y29="待确认",0)>0,"待确认","未开始"))))) -> 待确认 | H29: =IF(L29<>"",L29,IF(P29<>"",P29,IF(T29<>"",T29,X29))) -> 高级开发人员 | I29: =IF(COUNT(N29,R29,V29,Z29)=0,"",MIN(N29,R29,V29,Z29)) -> 46254 | J29: =IF(COUNT(O29,S29,W29,AA29)=0,"",MAX(O29,S29,W29,AA29)) -> 46258 | K29: 46290 | P29: 高级开发人员 | Q29: 待确认 | R29: 46254 | S29: 46258 | AB29: =IFERROR((IF(L29<>"",IF(M29="已完成",1,IF(M29="进行中",0.5,0))*15%,0)+IF(P29<>"",IF(Q29="已完成",1,IF(Q29="进行中",0.5,0))*35%,0)+IF(T29<>"",IF(U29="已完成",1,IF(U29="进行中",0.5,0))*30%,0)+IF(X29<>"",IF(Y29="已完成",1,IF(Y29="进行中",0.5,0))*20%,0))/(IF(L29<>"",15%,0)+IF(P29<>"",35%,0)+IF(T29<>"",30%,0)+IF(X29<>"",20%,0)),0) -> 0 | AC29: =IF($A29="","",IF(G29="已完成","正常",IF(G29="暂停","暂停",IF(J29="","日期缺失",IF(J29<_数据接口!$B$7,"已延期",IF(J29<=_数据接口!$B$7+7,"临近到期","正常")))))) -> 已延期 | AH29: =IF(OR($A29="",J29="",AG29=""),"",AG29-J29)
A30: T027 | E30: 验证电子签名、验签、时间戳和审计追溯 | F30: MS017 | G30: =IF(OR(M30="暂停",M30="挂起",Q30="暂停",Q30="挂起",U30="暂停",U30="挂起",Y30="暂停",Y30="挂起"),"暂停",IF(COUNTA(L30,P30,T30,X30)=0,"未分配",IF(IF(L30<>"",M30="已完成",0)+IF(P30<>"",Q30="已完成",0)+IF(T30<>"",U30="已完成",0)+IF(X30<>"",Y30="已完成",0)=COUNTA(L30,P30,T30,X30),"已完成",IF(IF(L30<>"",M30="进行中",0)+IF(P30<>"",Q30="进行中",0)+IF(T30<>"",U30="进行中",0)+IF(X30<>"",Y30="进行中",0)>0,"进行中",IF(IF(L30<>"",M30="待确认",0)+IF(P30<>"",Q30="待确认",0)+IF(T30<>"",U30="待确认",0)+IF(X30<>"",Y30="待确认",0)>0,"待确认","未开始"))))) -> 待确认 | H30: =IF(L30<>"",L30,IF(P30<>"",P30,IF(T30<>"",T30,X30))) -> 高级测试人员、中级测试人员 | I30: =IF(COUNT(N30,R30,V30,Z30)=0,"",MIN(N30,R30,V30,Z30)) -> 46259 | J30: =IF(COUNT(O30,S30,W30,AA30)=0,"",MAX(O30,S30,W30,AA30)) -> 46263 | K30: 46290 | X30: 高级测试人员、中级测试人员 | Y30: 待确认 | Z30: 46259 | AA30: 46263 | AB30: =IFERROR((IF(L30<>"",IF(M30="已完成",1,IF(M30="进行中",0.5,0))*15%,0)+IF(P30<>"",IF(Q30="已完成",1,IF(Q30="进行中",0.5,0))*35%,0)+IF(T30<>"",IF(U30="已完成",1,IF(U30="进行中",0.5,0))*30%,0)+IF(X30<>"",IF(Y30="已完成",1,IF(Y30="进行中",0.5,0))*20%,0))/(IF(L30<>"",15%,0)+IF(P30<>"",35%,0)+IF(T30<>"",30%,0)+IF(X30<>"",20%,0)),0) -> 0 | AC30: =IF($A30="","",IF(G30="已完成","正常",IF(G30="暂停","暂停",IF(J30="","日期缺失",IF(J30<_数据接口!$B$7,"已延期",IF(J30<=_数据接口!$B$7+7,"临近到期","正常")))))) -> 已延期 | AH30: =IF(OR($A30="",J30="",AG30=""),"",AG30-J30)
A31: T028 | D31: 电子文档验证 | E31: 验证模板生成、在线预览和格式转换 | F31: MS017 | G31: =IF(OR(M31="暂停",M31="挂起",Q31="暂停",Q31="挂起",U31="暂停",U31="挂起",Y31="暂停",Y31="挂起"),"暂停",IF(COUNTA(L31,P31,T31,X31)=0,"未分配",IF(IF(L31<>"",M31="已完成",0)+IF(P31<>"",Q31="已完成",0)+IF(T31<>"",U31="已完成",0)+IF(X31<>"",Y31="已完成",0)=COUNTA(L31,P31,T31,X31),"已完成",IF(IF(L31<>"",M31="进行中",0)+IF(P31<>"",Q31="进行中",0)+IF(T31<>"",U31="进行中",0)+IF(X31<>"",Y31="进行中",0)>0,"进行中",IF(IF(L31<>"",M31="待确认",0)+IF(P31<>"",Q31="待确认",0)+IF(T31<>"",U31="待确认",0)+IF(X31<>"",Y31="待确认",0)>0,"待确认","未开始"))))) -> 待确认 | H31: =IF(L31<>"",L31,IF(P31<>"",P31,IF(T31<>"",T31,X31))) -> 中级开发人员 | I31: =IF(COUNT(N31,R31,V31,Z31)=0,"",MIN(N31,R31,V31,Z31)) -> 46264 | J31: =IF(COUNT(O31,S31,W31,AA31)=0,"",MAX(O31,S31,W31,AA31)) -> 46269 | K31: 46290 | T31: 中级开发人员 | U31: 待确认 | V31: 46264 | W31: 46269 | AB31: =IFERROR((IF(L31<>"",IF(M31="已完成",1,IF(M31="进行中",0.5,0))*15%,0)+IF(P31<>"",IF(Q31="已完成",1,IF(Q31="进行中",0.5,0))*35%,0)+IF(T31<>"",IF(U31="已完成",1,IF(U31="进行中",0.5,0))*30%,0)+IF(X31<>"",IF(Y31="已完成",1,IF(Y31="进行中",0.5,0))*20%,0))/(IF(L31<>"",15%,0)+IF(P31<>"",35%,0)+IF(T31<>"",30%,0)+IF(X31<>"",20%,0)),0) -> 0 | AC31: =IF($A31="","",IF(G31="已完成","正常",IF(G31="暂停","暂停",IF(J31="","日期缺失",IF(J31<_数据接口!$B$7,"已延期",IF(J31<=_数据接口!$B$7+7,"临近到期","正常")))))) -> 已延期 | AH31: =IF(OR($A31="",J31="",AG31=""),"",AG31-J31)
A32: T029 | E32: 验证水印、权限控制、归档和大文件性能 | F32: MS017 | G32: =IF(OR(M32="暂停",M32="挂起",Q32="暂停",Q32="挂起",U32="暂停",U32="挂起",Y32="暂停",Y32="挂起"),"暂停",IF(COUNTA(L32,P32,T32,X32)=0,"未分配",IF(IF(L32<>"",M32="已完成",0)+IF(P32<>"",Q32="已完成",0)+IF(T32<>"",U32="已完成",0)+IF(X32<>"",Y32="已完成",0)=COUNTA(L32,P32,T32,X32),"已完成",IF(IF(L32<>"",M32="进行中",0)+IF(P32<>"",Q32="进行中",0)+IF(T32<>"",U32="进行中",0)+IF(X32<>"",Y32="进行中",0)>0,"进行中",IF(IF(L32<>"",M32="待确认",0)+IF(P32<>"",Q32="待确认",0)+IF(T32<>"",U32="待确认",0)+IF(X32<>"",Y32="待确认",0)>0,"待确认","未开始"))))) -> 待确认 | H32: =IF(L32<>"",L32,IF(P32<>"",P32,IF(T32<>"",T32,X32))) -> 高级测试人员、中级测试人员 | I32: =IF(COUNT(N32,R32,V32,Z32)=0,"",MIN(N32,R32,V32,Z32)) -> 46270 | J32: =IF(COUNT(O32,S32,W32,AA32)=0,"",MAX(O32,S32,W32,AA32)) -> 46274 | K32: 46290 | X32: 高级测试人员、中级测试人员 | Y32: 待确认 | Z32: 46270 | AA32: 46274 | AB32: =IFERROR((IF(L32<>"",IF(M32="已完成",1,IF(M32="进行中",0.5,0))*15%,0)+IF(P32<>"",IF(Q32="已完成",1,IF(Q32="进行中",0.5,0))*35%,0)+IF(T32<>"",IF(U32="已完成",1,IF(U32="进行中",0.5,0))*30%,0)+IF(X32<>"",IF(Y32="已完成",1,IF(Y32="进行中",0.5,0))*20%,0))/(IF(L32<>"",15%,0)+IF(P32<>"",35%,0)+IF(T32<>"",30%,0)+IF(X32<>"",20%,0)),0) -> 0 | AC32: =IF($A32="","",IF(G32="已完成","正常",IF(G32="暂停","暂停",IF(J32="","日期缺失",IF(J32<_数据接口!$B$7,"已延期",IF(J32<=_数据接口!$B$7+7,"临近到期","正常")))))) -> 已延期 | AH32: =IF(OR($A32="",J32="",AG32=""),"",AG32-J32)
A33: T030 | D33: BI报表验证 | E33: 验证数据接入、指标模型和经营报表 | F33: MS017 | G33: =IF(OR(M33="暂停",M33="挂起",Q33="暂停",Q33="挂起",U33="暂停",U33="挂起",Y33="暂停",Y33="挂起"),"暂停",IF(COUNTA(L33,P33,T33,X33)=0,"未分配",IF(IF(L33<>"",M33="已完成",0)+IF(P33<>"",Q33="已完成",0)+IF(T33<>"",U33="已完成",0)+IF(X33<>"",Y33="已完成",0)=COUNTA(L33,P33,T33,X33),"已完成",IF(IF(L33<>"",M33="进行中",0)+IF(P33<>"",Q33="进行中",0)+IF(T33<>"",U33="进行中",0)+IF(X33<>"",Y33="进行中",0)>0,"进行中",IF(IF(L33<>"",M33="待确认",0)+IF(P33<>"",Q33="待确认",0)+IF(T33<>"",U33="待确认",0)+IF(X33<>"",Y33="待确认",0)>0,"待确认","未开始"))))) -> 待确认 | H33: =IF(L33<>"",L33,IF(P33<>"",P33,IF(T33<>"",T33,X33))) -> 高级开发人员 | I33: =IF(COUNT(N33,R33,V33,Z33)=0,"",MIN(N33,R33,V33,Z33)) -> 46275 | J33: =IF(COUNT(O33,S33,W33,AA33)=0,"",MAX(O33,S33,W33,AA33)) -> 46279 | K33: 46290 | P33: 高级开发人员 | Q33: 待确认 | R33: 46275 | S33: 46279 | AB33: =IFERROR((IF(L33<>"",IF(M33="已完成",1,IF(M33="进行中",0.5,0))*15%,0)+IF(P33<>"",IF(Q33="已完成",1,IF(Q33="进行中",0.5,0))*35%,0)+IF(T33<>"",IF(U33="已完成",1,IF(U33="进行中",0.5,0))*30%,0)+IF(X33<>"",IF(Y33="已完成",1,IF(Y33="进行中",0.5,0))*20%,0))/(IF(L33<>"",15%,0)+IF(P33<>"",35%,0)+IF(T33<>"",30%,0)+IF(X33<>"",20%,0)),0) -> 0 | AC33: =IF($A33="","",IF(G33="已完成","正常",IF(G33="暂停","暂停",IF(J33="","日期缺失",IF(J33<_数据接口!$B$7,"已延期",IF(J33<=_数据接口!$B$7+7,"临近到期","正常")))))) -> 已延期 | AH33: =IF(OR($A33="",J33="",AG33=""),"",AG33-J33)
A34: T031 | E34: 验证权限、钻取、导出和查询性能 | F34: MS017 | G34: =IF(OR(M34="暂停",M34="挂起",Q34="暂停",Q34="挂起",U34="暂停",U34="挂起",Y34="暂停",Y34="挂起"),"暂停",IF(COUNTA(L34,P34,T34,X34)=0,"未分配",IF(IF(L34<>"",M34="已完成",0)+IF(P34<>"",Q34="已完成",0)+IF(T34<>"",U34="已完成",0)+IF(X34<>"",Y34="已完成",0)=COUNTA(L34,P34,T34,X34),"已完成",IF(IF(L34<>"",M34="进行中",0)+IF(P34<>"",Q34="进行中",0)+IF(T34<>"",U34="进行中",0)+IF(X34<>"",Y34="进行中",0)>0,"进行中",IF(IF(L34<>"",M34="待确认",0)+IF(P34<>"",Q34="待确认",0)+IF(T34<>"",U34="待确认",0)+IF(X34<>"",Y34="待确认",0)>0,"待确认","未开始"))))) -> 进行中 | H34: =IF(L34<>"",L34,IF(P34<>"",P34,IF(T34<>"",T34,X34))) -> 高级测试人员、中级测试人员 | I34: =IF(COUNT(N34,R34,V34,Z34)=0,"",MIN(N34,R34,V34,Z34)) -> 46280 | J34: =IF(COUNT(O34,S34,W34,AA34)=0,"",MAX(O34,S34,W34,AA34)) -> 46284 | K34: 46290 | X34: 高级测试人员、中级测试人员 | Y34: 进行中 | Z34: 46280 | AA34: 46284 | AB34: =IFERROR((IF(L34<>"",IF(M34="已完成",1,IF(M34="进行中",0.5,0))*15%,0)+IF(P34<>"",IF(Q34="已完成",1,IF(Q34="进行中",0.5,0))*35%,0)+IF(T34<>"",IF(U34="已完成",1,IF(U34="进行中",0.5,0))*30%,0)+IF(X34<>"",IF(Y34="已完成",1,IF(Y34="进行中",0.5,0))*20%,0))/(IF(L34<>"",15%,0)+IF(P34<>"",35%,0)+IF(T34<>"",30%,0)+IF(X34<>"",20%,0)),0) -> 0.5 | AC34: =IF($A34="","",IF(G34="已完成","正常",IF(G34="暂停","暂停",IF(J34="","日期缺失",IF(J34<_数据接口!$B$7,"已延期",IF(J34<=_数据接口!$B$7+7,"临近到期","正常")))))) -> 临近到期 | AF34: 2026-W40 | AH34: =IF(OR($A34="",J34="",AG34=""),"",AG34-J34)
A35: T032 | D35: POC结论 | E35: 汇总问题清单、适配结论和产品选型建议 | F35: MS017 | G35: =IF(OR(M35="暂停",M35="挂起",Q35="暂停",Q35="挂起",U35="暂停",U35="挂起",Y35="暂停",Y35="挂起"),"暂停",IF(COUNTA(L35,P35,T35,X35)=0,"未分配",IF(IF(L35<>"",M35="已完成",0)+IF(P35<>"",Q35="已完成",0)+IF(T35<>"",U35="已完成",0)+IF(X35<>"",Y35="已完成",0)=COUNTA(L35,P35,T35,X35),"已完成",IF(IF(L35<>"",M35="进行中",0)+IF(P35<>"",Q35="进行中",0)+IF(T35<>"",U35="进行中",0)+IF(X35<>"",Y35="进行中",0)>0,"进行中",IF(IF(L35<>"",M35="待确认",0)+IF(P35<>"",Q35="待确认",0)+IF(T35<>"",U35="待确认",0)+IF(X35<>"",Y35="待确认",0)>0,"待确认","未开始"))))) -> 未开始 | H35: =IF(L35<>"",L35,IF(P35<>"",P35,IF(T35<>"",T35,X35))) -> 项目经理 | I35: =IF(COUNT(N35,R35,V35,Z35)=0,"",MIN(N35,R35,V35,Z35)) -> 46285 | J35: =IF(COUNT(O35,S35,W35,AA35)=0,"",MAX(O35,S35,W35,AA35)) -> 46290 | K35: 46290 | L35: 项目经理 | M35: 未开始 | N35: 46285 | O35: 46290 | AB35: =IFERROR((IF(L35<>"",IF(M35="已完成",1,IF(M35="进行中",0.5,0))*15%,0)+IF(P35<>"",IF(Q35="已完成",1,IF(Q35="进行中",0.5,0))*35%,0)+IF(T35<>"",IF(U35="已完成",1,IF(U35="进行中",0.5,0))*30%,0)+IF(X35<>"",IF(Y35="已完成",1,IF(Y35="进行中",0.5,0))*20%,0))/(IF(L35<>"",15%,0)+IF(P35<>"",35%,0)+IF(T35<>"",30%,0)+IF(X35<>"",20%,0)),0) -> 0 | AC35: =IF($A35="","",IF(G35="已完成","正常",IF(G35="暂停","暂停",IF(J35="","日期缺失",IF(J35<_数据接口!$B$7,"已延期",IF(J35<=_数据接口!$B$7+7,"临近到期","正常")))))) -> 正常 | AE35: 执行工具：项目启动与治理/供应商POC计划、POC评分表；输出选型建议。 | AH35: =IF(OR($A35="",J35="",AG35=""),"",AG35-J35)
A36: T033 | B36: 正式启动准备 | C36: 启动准备评审通过 | D36: 启动准备 | E36: 编制并审批项目章程 | F36: MS006 | G36: =IF(OR(M36="暂停",M36="挂起",Q36="暂停",Q36="挂起",U36="暂停",U36="挂起",Y36="暂停",Y36="挂起"),"暂停",IF(COUNTA(L36,P36,T36,X36)=0,"未分配",IF(IF(L36<>"",M36="已完成",0)+IF(P36<>"",Q36="已完成",0)+IF(T36<>"",U36="已完成",0)+IF(X36<>"",Y36="已完成",0)=COUNTA(L36,P36,T36,X36),"已完成",IF(IF(L36<>"",M36="进行中",0)+IF(P36<>"",Q36="进行中",0)+IF(T36<>"",U36="进行中",0)+IF(X36<>"",Y36="进行中",0)>0,"进行中",IF(IF(L36<>"",M36="待确认",0)+IF(P36<>"",Q36="待确认",0)+IF(T36<>"",U36="待确认",0)+IF(X36<>"",Y36="待确认",0)>0,"待确认","未开始"))))) -> 未开始 | H36: =IF(L36<>"",L36,IF(P36<>"",P36,IF(T36<>"",T36,X36))) -> 项目集经理 | I36: =IF(COUNT(N36,R36,V36,Z36)=0,"",MIN(N36,R36,V36,Z36)) -> 46296 | J36: =IF(COUNT(O36,S36,W36,AA36)=0,"",MAX(O36,S36,W36,AA36)) -> 46297 | K36: 46311 | L36: 项目集经理 | M36: 未开始 | N36: 46296 | O36: 46297 | AB36: =IFERROR((IF(L36<>"",IF(M36="已完成",1,IF(M36="进行中",0.5,0))*15%,0)+IF(P36<>"",IF(Q36="已完成",1,IF(Q36="进行中",0.5,0))*35%,0)+IF(T36<>"",IF(U36="已完成",1,IF(U36="进行中",0.5,0))*30%,0)+IF(X36<>"",IF(Y36="已完成",1,IF(Y36="进行中",0.5,0))*20%,0))/(IF(L36<>"",15%,0)+IF(P36<>"",35%,0)+IF(T36<>"",30%,0)+IF(X36<>"",20%,0)),0) -> 0 | AC36: =IF($A36="","",IF(G36="已完成","正常",IF(G36="暂停","暂停",IF(J36="","日期缺失",IF(J36<_数据接口!$B$7,"已延期",IF(J36<=_数据接口!$B$7+7,"临近到期","正常")))))) -> 正常 | AH36: =IF(OR($A36="",J36="",AG36=""),"",AG36-J36)
A37: T034 | E37: 编制范围、里程碑和主进度计划 | F37: MS006 | G37: =IF(OR(M37="暂停",M37="挂起",Q37="暂停",Q37="挂起",U37="暂停",U37="挂起",Y37="暂停",Y37="挂起"),"暂停",IF(COUNTA(L37,P37,T37,X37)=0,"未分配",IF(IF(L37<>"",M37="已完成",0)+IF(P37<>"",Q37="已完成",0)+IF(T37<>"",U37="已完成",0)+IF(X37<>"",Y37="已完成",0)=COUNTA(L37,P37,T37,X37),"已完成",IF(IF(L37<>"",M37="进行中",0)+IF(P37<>"",Q37="进行中",0)+IF(T37<>"",U37="进行中",0)+IF(X37<>"",Y37="进行中",0)>0,"进行中",IF(IF(L37<>"",M37="待确认",0)+IF(P37<>"",Q37="待确认",0)+IF(T37<>"",U37="待确认",0)+IF(X37<>"",Y37="待确认",0)>0,"待确认","未开始"))))) -> 未开始 | H37: =IF(L37<>"",L37,IF(P37<>"",P37,IF(T37<>"",T37,X37))) -> 项目经理 | I37: =IF(COUNT(N37,R37,V37,Z37)=0,"",MIN(N37,R37,V37,Z37)) -> 46298 | J37: =IF(COUNT(O37,S37,W37,AA37)=0,"",MAX(O37,S37,W37,AA37)) -> 46300 | K37: 46311 | L37: 项目经理 | M37: 未开始 | N37: 46298 | O37: 46300 | AB37: =IFERROR((IF(L37<>"",IF(M37="已完成",1,IF(M37="进行中",0.5,0))*15%,0)+IF(P37<>"",IF(Q37="已完成",1,IF(Q37="进行中",0.5,0))*35%,0)+IF(T37<>"",IF(U37="已完成",1,IF(U37="进行中",0.5,0))*30%,0)+IF(X37<>"",IF(Y37="已完成",1,IF(Y37="进行中",0.5,0))*20%,0))/(IF(L37<>"",15%,0)+IF(P37<>"",35%,0)+IF(T37<>"",30%,0)+IF(X37<>"",20%,0)),0) -> 0 | AC37: =IF($A37="","",IF(G37="已完成","正常",IF(G37="暂停","暂停",IF(J37="","日期缺失",IF(J37<_数据接口!$B$7,"已延期",IF(J37<=_数据接口!$B$7+7,"临近到期","正常")))))) -> 正常 | AH37: =IF(OR($A37="",J37="",AG37=""),"",AG37-J37)
A38: T035 | D38: 组织准备 | E38: 建立项目组织、RACI与沟通机制 | F38: MS006 | G38: =IF(OR(M38="暂停",M38="挂起",Q38="暂停",Q38="挂起",U38="暂停",U38="挂起",Y38="暂停",Y38="挂起"),"暂停",IF(COUNTA(L38,P38,T38,X38)=0,"未分配",IF(IF(L38<>"",M38="已完成",0)+IF(P38<>"",Q38="已完成",0)+IF(T38<>"",U38="已完成",0)+IF(X38<>"",Y38="已完成",0)=COUNTA(L38,P38,T38,X38),"已完成",IF(IF(L38<>"",M38="进行中",0)+IF(P38<>"",Q38="进行中",0)+IF(T38<>"",U38="进行中",0)+IF(X38<>"",Y38="进行中",0)>0,"进行中",IF(IF(L38<>"",M38="待确认",0)+IF(P38<>"",Q38="待确认",0)+IF(T38<>"",U38="待确认",0)+IF(X38<>"",Y38="待确认",0)>0,"待确认","未开始"))))) -> 未开始 | H38: =IF(L38<>"",L38,IF(P38<>"",P38,IF(T38<>"",T38,X38))) -> 项目经理 | I38: =IF(COUNT(N38,R38,V38,Z38)=0,"",MIN(N38,R38,V38,Z38)) -> 46301 | J38: =IF(COUNT(O38,S38,W38,AA38)=0,"",MAX(O38,S38,W38,AA38)) -> 46303 | K38: 46311 | L38: 项目经理 | M38: 未开始 | N38: 46301 | O38: 46303 | AB38: =IFERROR((IF(L38<>"",IF(M38="已完成",1,IF(M38="进行中",0.5,0))*15%,0)+IF(P38<>"",IF(Q38="已完成",1,IF(Q38="进行中",0.5,0))*35%,0)+IF(T38<>"",IF(U38="已完成",1,IF(U38="进行中",0.5,0))*30%,0)+IF(X38<>"",IF(Y38="已完成",1,IF(Y38="进行中",0.5,0))*20%,0))/(IF(L38<>"",15%,0)+IF(P38<>"",35%,0)+IF(T38<>"",30%,0)+IF(X38<>"",20%,0)),0) -> 0 | AC38: =IF($A38="","",IF(G38="已完成","正常",IF(G38="暂停","暂停",IF(J38="","日期缺失",IF(J38<_数据接口!$B$7,"已延期",IF(J38<=_数据接口!$B$7+7,"临近到期","正常")))))) -> 正常 | AE38: 执行工具：项目启动与治理/相关方管理；确认RACI与沟通责任人。 | AH38: =IF(OR($A38="",J38="",AG38=""),"",AG38-J38)
A39: T036 | D39: 资源准备 | E39: 确认30人团队投入与阶段资源计划 | F39: MS006 | G39: =IF(OR(M39="暂停",M39="挂起",Q39="暂停",Q39="挂起",U39="暂停",U39="挂起",Y39="暂停",Y39="挂起"),"暂停",IF(COUNTA(L39,P39,T39,X39)=0,"未分配",IF(IF(L39<>"",M39="已完成",0)+IF(P39<>"",Q39="已完成",0)+IF(T39<>"",U39="已完成",0)+IF(X39<>"",Y39="已完成",0)=COUNTA(L39,P39,T39,X39),"已完成",IF(IF(L39<>"",M39="进行中",0)+IF(P39<>"",Q39="进行中",0)+IF(T39<>"",U39="进行中",0)+IF(X39<>"",Y39="进行中",0)>0,"进行中",IF(IF(L39<>"",M39="待确认",0)+IF(P39<>"",Q39="待确认",0)+IF(T39<>"",U39="待确认",0)+IF(X39<>"",Y39="待确认",0)>0,"待确认","未开始"))))) -> 未开始 | H39: =IF(L39<>"",L39,IF(P39<>"",P39,IF(T39<>"",T39,X39))) -> 项目集经理 | I39: =IF(COUNT(N39,R39,V39,Z39)=0,"",MIN(N39,R39,V39,Z39)) -> 46304 | J39: =IF(COUNT(O39,S39,W39,AA39)=0,"",MAX(O39,S39,W39,AA39)) -> 46305 | K39: 46311 | L39: 项目集经理 | M39: 未开始 | N39: 46304 | O39: 46305 | AB39: =IFERROR((IF(L39<>"",IF(M39="已完成",1,IF(M39="进行中",0.5,0))*15%,0)+IF(P39<>"",IF(Q39="已完成",1,IF(Q39="进行中",0.5,0))*35%,0)+IF(T39<>"",IF(U39="已完成",1,IF(U39="进行中",0.5,0))*30%,0)+IF(X39<>"",IF(Y39="已完成",1,IF(Y39="进行中",0.5,0))*20%,0))/(IF(L39<>"",15%,0)+IF(P39<>"",35%,0)+IF(T39<>"",30%,0)+IF(X39<>"",20%,0)),0) -> 0 | AC39: =IF($A39="","",IF(G39="已完成","正常",IF(G39="暂停","暂停",IF(J39="","日期缺失",IF(J39<_数据接口!$B$7,"已延期",IF(J39<=_数据接口!$B$7+7,"临近到期","正常")))))) -> 正常 | AH39: =IF(OR($A39="",J39="",AG39=""),"",AG39-J39)
A40: T037 | D40: 治理准备 | E40: 建立风险、问题、变更和决策台账 | F40: MS006 | G40: =IF(OR(M40="暂停",M40="挂起",Q40="暂停",Q40="挂起",U40="暂停",U40="挂起",Y40="暂停",Y40="挂起"),"暂停",IF(COUNTA(L40,P40,T40,X40)=0,"未分配",IF(IF(L40<>"",M40="已完成",0)+IF(P40<>"",Q40="已完成",0)+IF(T40<>"",U40="已完成",0)+IF(X40<>"",Y40="已完成",0)=COUNTA(L40,P40,T40,X40),"已完成",IF(IF(L40<>"",M40="进行中",0)+IF(P40<>"",Q40="进行中",0)+IF(T40<>"",U40="进行中",0)+IF(X40<>"",Y40="进行中",0)>0,"进行中",IF(IF(L40<>"",M40="待确认",0)+IF(P40<>"",Q40="待确认",0)+IF(T40<>"",U40="待确认",0)+IF(X40<>"",Y40="待确认",0)>0,"待确认","未开始"))))) -> 未开始 | H40: =IF(L40<>"",L40,IF(P40<>"",P40,IF(T40<>"",T40,X40))) -> 项目经理 | I40: =IF(COUNT(N40,R40,V40,Z40)=0,"",MIN(N40,R40,V40,Z40)) -> 46306 | J40: =IF(COUNT(O40,S40,W40,AA40)=0,"",MAX(O40,S40,W40,AA40)) -> 46308 | K40: 46311 | L40: 项目经理 | M40: 未开始 | N40: 46306 | O40: 46308 | AB40: =IFERROR((IF(L40<>"",IF(M40="已完成",1,IF(M40="进行中",0.5,0))*15%,0)+IF(P40<>"",IF(Q40="已完成",1,IF(Q40="进行中",0.5,0))*35%,0)+IF(T40<>"",IF(U40="已完成",1,IF(U40="进行中",0.5,0))*30%,0)+IF(X40<>"",IF(Y40="已完成",1,IF(Y40="进行中",0.5,0))*20%,0))/(IF(L40<>"",15%,0)+IF(P40<>"",35%,0)+IF(T40<>"",30%,0)+IF(X40<>"",20%,0)),0) -> 0 | AC40: =IF($A40="","",IF(G40="已完成","正常",IF(G40="暂停","暂停",IF(J40="","日期缺失",IF(J40<_数据接口!$B$7,"已延期",IF(J40<=_数据接口!$B$7+7,"临近到期","正常")))))) -> 正常 | AH40: =IF(OR($A40="",J40="",AG40=""),"",AG40-J40)
A41: T038 | D41: 启动门禁 | E41: 完成启动条件检查与评审 | F41: MS006 | G41: =IF(OR(M41="暂停",M41="挂起",Q41="暂停",Q41="挂起",U41="暂停",U41="挂起",Y41="暂停",Y41="挂起"),"暂停",IF(COUNTA(L41,P41,T41,X41)=0,"未分配",IF(IF(L41<>"",M41="已完成",0)+IF(P41<>"",Q41="已完成",0)+IF(T41<>"",U41="已完成",0)+IF(X41<>"",Y41="已完成",0)=COUNTA(L41,P41,T41,X41),"已完成",IF(IF(L41<>"",M41="进行中",0)+IF(P41<>"",Q41="进行中",0)+IF(T41<>"",U41="进行中",0)+IF(X41<>"",Y41="进行中",0)>0,"进行中",IF(IF(L41<>"",M41="待确认",0)+IF(P41<>"",Q41="待确认",0)+IF(T41<>"",U41="待确认",0)+IF(X41<>"",Y41="待确认",0)>0,"待确认","未开始"))))) -> 未开始 | H41: =IF(L41<>"",L41,IF(P41<>"",P41,IF(T41<>"",T41,X41))) -> 项目集经理 | I41: =IF(COUNT(N41,R41,V41,Z41)=0,"",MIN(N41,R41,V41,Z41)) -> 46309 | J41: =IF(COUNT(O41,S41,W41,AA41)=0,"",MAX(O41,S41,W41,AA41)) -> 46311 | K41: 46311 | L41: 项目集经理 | M41: 未开始 | N41: 46309 | O41: 46311 | AB41: =IFERROR((IF(L41<>"",IF(M41="已完成",1,IF(M41="进行中",0.5,0))*15%,0)+IF(P41<>"",IF(Q41="已完成",1,IF(Q41="进行中",0.5,0))*35%,0)+IF(T41<>"",IF(U41="已完成",1,IF(U41="进行中",0.5,0))*30%,0)+IF(X41<>"",IF(Y41="已完成",1,IF(Y41="进行中",0.5,0))*20%,0))/(IF(L41<>"",15%,0)+IF(P41<>"",35%,0)+IF(T41<>"",30%,0)+IF(X41<>"",20%,0)),0) -> 0 | AC41: =IF($A41="","",IF(G41="已完成","正常",IF(G41="暂停","暂停",IF(J41="","日期缺失",IF(J41<_数据接口!$B$7,"已延期",IF(J41<=_数据接口!$B$7+7,"临近到期","正常")))))) -> 正常 | AE41: 执行工具：项目启动与治理/启动门禁清单；必过项未通过不得正式启动。 | AH41: =IF(OR($A41="",J41="",AG41=""),"",AG41-J41)
A42: T039 | B42: 正式实施与上线准备 | C42: 项目正式启动 | D42: 正式启动 | E42: 准备启动会材料与项目目标宣贯 | F42: MS007 | G42: =IF(OR(M42="暂停",M42="挂起",Q42="暂停",Q42="挂起",U42="暂停",U42="挂起",Y42="暂停",Y42="挂起"),"暂停",IF(COUNTA(L42,P42,T42,X42)=0,"未分配",IF(IF(L42<>"",M42="已完成",0)+IF(P42<>"",Q42="已完成",0)+IF(T42<>"",U42="已完成",0)+IF(X42<>"",Y42="已完成",0)=COUNTA(L42,P42,T42,X42),"已完成",IF(IF(L42<>"",M42="进行中",0)+IF(P42<>"",Q42="进行中",0)+IF(T42<>"",U42="进行中",0)+IF(X42<>"",Y42="进行中",0)>0,"进行中",IF(IF(L42<>"",M42="待确认",0)+IF(P42<>"",Q42="待确认",0)+IF(T42<>"",U42="待确认",0)+IF(X42<>"",Y42="待确认",0)>0,"待确认","未开始"))))) -> 未开始 | H42: =IF(L42<>"",L42,IF(P42<>"",P42,IF(T42<>"",T42,X42))) -> 项目经理 | I42: =IF(COUNT(N42,R42,V42,Z42)=0,"",MIN(N42,R42,V42,Z42)) -> 46315 | J42: =IF(COUNT(O42,S42,W42,AA42)=0,"",MAX(O42,S42,W42,AA42)) -> 46315 | K42: 46315 | L42: 项目经理 | M42: 未开始 | N42: 46315 | O42: 46315 | AB42: =IFERROR((IF(L42<>"",IF(M42="已完成",1,IF(M42="进行中",0.5,0))*15%,0)+IF(P42<>"",IF(Q42="已完成",1,IF(Q42="进行中",0.5,0))*35%,0)+IF(T42<>"",IF(U42="已完成",1,IF(U42="进行中",0.5,0))*30%,0)+IF(X42<>"",IF(Y42="已完成",1,IF(Y42="进行中",0.5,0))*20%,0))/(IF(L42<>"",15%,0)+IF(P42<>"",35%,0)+IF(T42<>"",30%,0)+IF(X42<>"",20%,0)),0) -> 0 | AC42: =IF($A42="","",IF(G42="已完成","正常",IF(G42="暂停","暂停",IF(J42="","日期缺失",IF(J42<_数据接口!$B$7,"已延期",IF(J42<=_数据接口!$B$7+7,"临近到期","正常")))))) -> 正常 | AH42: =IF(OR($A42="",J42="",AG42=""),"",AG42-J42)
A43: T040 | E43: 召开项目启动会并确认职责 | F43: MS007 | G43: =IF(OR(M43="暂停",M43="挂起",Q43="暂停",Q43="挂起",U43="暂停",U43="挂起",Y43="暂停",Y43="挂起"),"暂停",IF(COUNTA(L43,P43,T43,X43)=0,"未分配",IF(IF(L43<>"",M43="已完成",0)+IF(P43<>"",Q43="已完成",0)+IF(T43<>"",U43="已完成",0)+IF(X43<>"",Y43="已完成",0)=COUNTA(L43,P43,T43,X43),"已完成",IF(IF(L43<>"",M43="进行中",0)+IF(P43<>"",Q43="进行中",0)+IF(T43<>"",U43="进行中",0)+IF(X43<>"",Y43="进行中",0)>0,"进行中",IF(IF(L43<>"",M43="待确认",0)+IF(P43<>"",Q43="待确认",0)+IF(T43<>"",U43="待确认",0)+IF(X43<>"",Y43="待确认",0)>0,"待确认","未开始"))))) -> 未开始 | H43: =IF(L43<>"",L43,IF(P43<>"",P43,IF(T43<>"",T43,X43))) -> 项目集经理 | I43: =IF(COUNT(N43,R43,V43,Z43)=0,"",MIN(N43,R43,V43,Z43)) -> 46315 | J43: =IF(COUNT(O43,S43,W43,AA43)=0,"",MAX(O43,S43,W43,AA43)) -> 46315 | K43: 46315 | L43: 项目集经理 | M43: 未开始 | N43: 46315 | O43: 46315 | AB43: =IFERROR((IF(L43<>"",IF(M43="已完成",1,IF(M43="进行中",0.5,0))*15%,0)+IF(P43<>"",IF(Q43="已完成",1,IF(Q43="进行中",0.5,0))*35%,0)+IF(T43<>"",IF(U43="已完成",1,IF(U43="进行中",0.5,0))*30%,0)+IF(X43<>"",IF(Y43="已完成",1,IF(Y43="进行中",0.5,0))*20%,0))/(IF(L43<>"",15%,0)+IF(P43<>"",35%,0)+IF(T43<>"",30%,0)+IF(X43<>"",20%,0)),0) -> 0 | AC43: =IF($A43="","",IF(G43="已完成","正常",IF(G43="暂停","暂停",IF(J43="","日期缺失",IF(J43<_数据接口!$B$7,"已延期",IF(J43<=_数据接口!$B$7+7,"临近到期","正常")))))) -> 正常 | AH43: =IF(OR($A43="",J43="",AG43=""),"",AG43-J43)
A44: T041 | E44: 发布会议纪要、行动项和基准计划 | F44: MS007 | G44: =IF(OR(M44="暂停",M44="挂起",Q44="暂停",Q44="挂起",U44="暂停",U44="挂起",Y44="暂停",Y44="挂起"),"暂停",IF(COUNTA(L44,P44,T44,X44)=0,"未分配",IF(IF(L44<>"",M44="已完成",0)+IF(P44<>"",Q44="已完成",0)+IF(T44<>"",U44="已完成",0)+IF(X44<>"",Y44="已完成",0)=COUNTA(L44,P44,T44,X44),"已完成",IF(IF(L44<>"",M44="进行中",0)+IF(P44<>"",Q44="进行中",0)+IF(T44<>"",U44="进行中",0)+IF(X44<>"",Y44="进行中",0)>0,"进行中",IF(IF(L44<>"",M44="待确认",0)+IF(P44<>"",Q44="待确认",0)+IF(T44<>"",U44="待确认",0)+IF(X44<>"",Y44="待确认",0)>0,"待确认","未开始"))))) -> 未开始 | H44: =IF(L44<>"",L44,IF(P44<>"",P44,IF(T44<>"",T44,X44))) -> 项目经理 | I44: =IF(COUNT(N44,R44,V44,Z44)=0,"",MIN(N44,R44,V44,Z44)) -> 46315 | J44: =IF(COUNT(O44,S44,W44,AA44)=0,"",MAX(O44,S44,W44,AA44)) -> 46315 | K44: 46315 | L44: 项目经理 | M44: 未开始 | N44: 46315 | O44: 46315 | AB44: =IFERROR((IF(L44<>"",IF(M44="已完成",1,IF(M44="进行中",0.5,0))*15%,0)+IF(P44<>"",IF(Q44="已完成",1,IF(Q44="进行中",0.5,0))*35%,0)+IF(T44<>"",IF(U44="已完成",1,IF(U44="进行中",0.5,0))*30%,0)+IF(X44<>"",IF(Y44="已完成",1,IF(Y44="进行中",0.5,0))*20%,0))/(IF(L44<>"",15%,0)+IF(P44<>"",35%,0)+IF(T44<>"",30%,0)+IF(X44<>"",20%,0)),0) -> 0 | AC44: =IF($A44="","",IF(G44="已完成","正常",IF(G44="暂停","暂停",IF(J44="","日期缺失",IF(J44<_数据接口!$B$7,"已延期",IF(J44<=_数据接口!$B$7+7,"临近到期","正常")))))) -> 正常 | AH44: =IF(OR($A44="",J44="",AG44=""),"",AG44-J44)
A45: T042 | C45: 需求基线确认 | D45: 需求调研 | E45: 开展业务场景与用户需求工作坊 | F45: MS008 | G45: =IF(OR(M45="暂停",M45="挂起",Q45="暂停",Q45="挂起",U45="暂停",U45="挂起",Y45="暂停",Y45="挂起"),"暂停",IF(COUNTA(L45,P45,T45,X45)=0,"未分配",IF(IF(L45<>"",M45="已完成",0)+IF(P45<>"",Q45="已完成",0)+IF(T45<>"",U45="已完成",0)+IF(X45<>"",Y45="已完成",0)=COUNTA(L45,P45,T45,X45),"已完成",IF(IF(L45<>"",M45="进行中",0)+IF(P45<>"",Q45="进行中",0)+IF(T45<>"",U45="进行中",0)+IF(X45<>"",Y45="进行中",0)>0,"进行中",IF(IF(L45<>"",M45="待确认",0)+IF(P45<>"",Q45="待确认",0)+IF(T45<>"",U45="待确认",0)+IF(X45<>"",Y45="待确认",0)>0,"待确认","未开始"))))) -> 未开始 | H45: =IF(L45<>"",L45,IF(P45<>"",P45,IF(T45<>"",T45,X45))) -> 产品经理 | I45: =IF(COUNT(N45,R45,V45,Z45)=0,"",MIN(N45,R45,V45,Z45)) -> 46316 | J45: =IF(COUNT(O45,S45,W45,AA45)=0,"",MAX(O45,S45,W45,AA45)) -> 46321 | K45: 46356 | L45: 产品经理 | M45: 未开始 | N45: 46316 | O45: 46321 | AB45: =IFERROR((IF(L45<>"",IF(M45="已完成",1,IF(M45="进行中",0.5,0))*15%,0)+IF(P45<>"",IF(Q45="已完成",1,IF(Q45="进行中",0.5,0))*35%,0)+IF(T45<>"",IF(U45="已完成",1,IF(U45="进行中",0.5,0))*30%,0)+IF(X45<>"",IF(Y45="已完成",1,IF(Y45="进行中",0.5,0))*20%,0))/(IF(L45<>"",15%,0)+IF(P45<>"",35%,0)+IF(T45<>"",30%,0)+IF(X45<>"",20%,0)),0) -> 0 | AC45: =IF($A45="","",IF(G45="已完成","正常",IF(G45="暂停","暂停",IF(J45="","日期缺失",IF(J45<_数据接口!$B$7,"已延期",IF(J45<=_数据接口!$B$7+7,"临近到期","正常")))))) -> 正常 | AH45: =IF(OR($A45="",J45="",AG45=""),"",AG45-J45)
A46: T043 | D46: 范围管理 | E46: 形成需求清单并完成P0/P1/P2分级 | F46: MS008 | G46: =IF(OR(M46="暂停",M46="挂起",Q46="暂停",Q46="挂起",U46="暂停",U46="挂起",Y46="暂停",Y46="挂起"),"暂停",IF(COUNTA(L46,P46,T46,X46)=0,"未分配",IF(IF(L46<>"",M46="已完成",0)+IF(P46<>"",Q46="已完成",0)+IF(T46<>"",U46="已完成",0)+IF(X46<>"",Y46="已完成",0)=COUNTA(L46,P46,T46,X46),"已完成",IF(IF(L46<>"",M46="进行中",0)+IF(P46<>"",Q46="进行中",0)+IF(T46<>"",U46="进行中",0)+IF(X46<>"",Y46="进行中",0)>0,"进行中",IF(IF(L46<>"",M46="待确认",0)+IF(P46<>"",Q46="待确认",0)+IF(T46<>"",U46="待确认",0)+IF(X46<>"",Y46="待确认",0)>0,"待确认","未开始"))))) -> 未开始 | H46: =IF(L46<>"",L46,IF(P46<>"",P46,IF(T46<>"",T46,X46))) -> 产品经理 | I46: =IF(COUNT(N46,R46,V46,Z46)=0,"",MIN(N46,R46,V46,Z46)) -> 46322 | J46: =IF(COUNT(O46,S46,W46,AA46)=0,"",MAX(O46,S46,W46,AA46)) -> 46328 | K46: 46356 | L46: 产品经理 | M46: 未开始 | N46: 46322 | O46: 46328 | AB46: =IFERROR((IF(L46<>"",IF(M46="已完成",1,IF(M46="进行中",0.5,0))*15%,0)+IF(P46<>"",IF(Q46="已完成",1,IF(Q46="进行中",0.5,0))*35%,0)+IF(T46<>"",IF(U46="已完成",1,IF(U46="进行中",0.5,0))*30%,0)+IF(X46<>"",IF(Y46="已完成",1,IF(Y46="进行中",0.5,0))*20%,0))/(IF(L46<>"",15%,0)+IF(P46<>"",35%,0)+IF(T46<>"",30%,0)+IF(X46<>"",20%,0)),0) -> 0 | AC46: =IF($A46="","",IF(G46="已完成","正常",IF(G46="暂停","暂停",IF(J46="","日期缺失",IF(J46<_数据接口!$B$7,"已延期",IF(J46<=_数据接口!$B$7+7,"临近到期","正常")))))) -> 正常 | AH46: =IF(OR($A46="",J46="",AG46=""),"",AG46-J46)
A47: T044 | D47: 需求分析 | E47: 设计目标流程、用例和业务规则 | F47: MS008 | G47: =IF(OR(M47="暂停",M47="挂起",Q47="暂停",Q47="挂起",U47="暂停",U47="挂起",Y47="暂停",Y47="挂起"),"暂停",IF(COUNTA(L47,P47,T47,X47)=0,"未分配",IF(IF(L47<>"",M47="已完成",0)+IF(P47<>"",Q47="已完成",0)+IF(T47<>"",U47="已完成",0)+IF(X47<>"",Y47="已完成",0)=COUNTA(L47,P47,T47,X47),"已完成",IF(IF(L47<>"",M47="进行中",0)+IF(P47<>"",Q47="进行中",0)+IF(T47<>"",U47="进行中",0)+IF(X47<>"",Y47="进行中",0)>0,"进行中",IF(IF(L47<>"",M47="待确认",0)+IF(P47<>"",Q47="待确认",0)+IF(T47<>"",U47="待确认",0)+IF(X47<>"",Y47="待确认",0)>0,"待确认","未开始"))))) -> 未开始 | H47: =IF(L47<>"",L47,IF(P47<>"",P47,IF(T47<>"",T47,X47))) -> 产品经理 | I47: =IF(COUNT(N47,R47,V47,Z47)=0,"",MIN(N47,R47,V47,Z47)) -> 46329 | J47: =IF(COUNT(O47,S47,W47,AA47)=0,"",MAX(O47,S47,W47,AA47)) -> 46335 | K47: 46356 | L47: 产品经理 | M47: 未开始 | N47: 46329 | O47: 46335 | AB47: =IFERROR((IF(L47<>"",IF(M47="已完成",1,IF(M47="进行中",0.5,0))*15%,0)+IF(P47<>"",IF(Q47="已完成",1,IF(Q47="进行中",0.5,0))*35%,0)+IF(T47<>"",IF(U47="已完成",1,IF(U47="进行中",0.5,0))*30%,0)+IF(X47<>"",IF(Y47="已完成",1,IF(Y47="进行中",0.5,0))*20%,0))/(IF(L47<>"",15%,0)+IF(P47<>"",35%,0)+IF(T47<>"",30%,0)+IF(X47<>"",20%,0)),0) -> 0 | AC47: =IF($A47="","",IF(G47="已完成","正常",IF(G47="暂停","暂停",IF(J47="","日期缺失",IF(J47<_数据接口!$B$7,"已延期",IF(J47<=_数据接口!$B$7+7,"临近到期","正常")))))) -> 正常 | AH47: =IF(OR($A47="",J47="",AG47=""),"",AG47-J47)
A48: T045 | D48: 原型设计 | E48: 完成核心功能原型和交互确认 | F48: MS008 | G48: =IF(OR(M48="暂停",M48="挂起",Q48="暂停",Q48="挂起",U48="暂停",U48="挂起",Y48="暂停",Y48="挂起"),"暂停",IF(COUNTA(L48,P48,T48,X48)=0,"未分配",IF(IF(L48<>"",M48="已完成",0)+IF(P48<>"",Q48="已完成",0)+IF(T48<>"",U48="已完成",0)+IF(X48<>"",Y48="已完成",0)=COUNTA(L48,P48,T48,X48),"已完成",IF(IF(L48<>"",M48="进行中",0)+IF(P48<>"",Q48="进行中",0)+IF(T48<>"",U48="进行中",0)+IF(X48<>"",Y48="进行中",0)>0,"进行中",IF(IF(L48<>"",M48="待确认",0)+IF(P48<>"",Q48="待确认",0)+IF(T48<>"",U48="待确认",0)+IF(X48<>"",Y48="待确认",0)>0,"待确认","未开始"))))) -> 未开始 | H48: =IF(L48<>"",L48,IF(P48<>"",P48,IF(T48<>"",T48,X48))) -> 美工 | I48: =IF(COUNT(N48,R48,V48,Z48)=0,"",MIN(N48,R48,V48,Z48)) -> 46336 | J48: =IF(COUNT(O48,S48,W48,AA48)=0,"",MAX(O48,S48,W48,AA48)) -> 46342 | K48: 46356 | T48: 美工 | U48: 未开始 | V48: 46336 | W48: 46342 | AB48: =IFERROR((IF(L48<>"",IF(M48="已完成",1,IF(M48="进行中",0.5,0))*15%,0)+IF(P48<>"",IF(Q48="已完成",1,IF(Q48="进行中",0.5,0))*35%,0)+IF(T48<>"",IF(U48="已完成",1,IF(U48="进行中",0.5,0))*30%,0)+IF(X48<>"",IF(Y48="已完成",1,IF(Y48="进行中",0.5,0))*20%,0))/(IF(L48<>"",15%,0)+IF(P48<>"",35%,0)+IF(T48<>"",30%,0)+IF(X48<>"",20%,0)),0) -> 0 | AC48: =IF($A48="","",IF(G48="已完成","正常",IF(G48="暂停","暂停",IF(J48="","日期缺失",IF(J48<_数据接口!$B$7,"已延期",IF(J48<=_数据接口!$B$7+7,"临近到期","正常")))))) -> 正常 | AH48: =IF(OR($A48="",J48="",AG48=""),"",AG48-J48)
A49: T046 | D49: 非功能需求 | E49: 明确性能、安全、可用性和合规要求 | F49: MS008 | G49: =IF(OR(M49="暂停",M49="挂起",Q49="暂停",Q49="挂起",U49="暂停",U49="挂起",Y49="暂停",Y49="挂起"),"暂停",IF(COUNTA(L49,P49,T49,X49)=0,"未分配",IF(IF(L49<>"",M49="已完成",0)+IF(P49<>"",Q49="已完成",0)+IF(T49<>"",U49="已完成",0)+IF(X49<>"",Y49="已完成",0)=COUNTA(L49,P49,T49,X49),"已完成",IF(IF(L49<>"",M49="进行中",0)+IF(P49<>"",Q49="进行中",0)+IF(T49<>"",U49="进行中",0)+IF(X49<>"",Y49="进行中",0)>0,"进行中",IF(IF(L49<>"",M49="待确认",0)+IF(P49<>"",Q49="待确认",0)+IF(T49<>"",U49="待确认",0)+IF(X49<>"",Y49="待确认",0)>0,"待确认","未开始"))))) -> 未开始 | H49: =IF(L49<>"",L49,IF(P49<>"",P49,IF(T49<>"",T49,X49))) -> 技术经理 | I49: =IF(COUNT(N49,R49,V49,Z49)=0,"",MIN(N49,R49,V49,Z49)) -> 46343 | J49: =IF(COUNT(O49,S49,W49,AA49)=0,"",MAX(O49,S49,W49,AA49)) -> 46349 | K49: 46356 | P49: 技术经理 | Q49: 未开始 | R49: 46343 | S49: 46349 | AB49: =IFERROR((IF(L49<>"",IF(M49="已完成",1,IF(M49="进行中",0.5,0))*15%,0)+IF(P49<>"",IF(Q49="已完成",1,IF(Q49="进行中",0.5,0))*35%,0)+IF(T49<>"",IF(U49="已完成",1,IF(U49="进行中",0.5,0))*30%,0)+IF(X49<>"",IF(Y49="已完成",1,IF(Y49="进行中",0.5,0))*20%,0))/(IF(L49<>"",15%,0)+IF(P49<>"",35%,0)+IF(T49<>"",30%,0)+IF(X49<>"",20%,0)),0) -> 0 | AC49: =IF($A49="","",IF(G49="已完成","正常",IF(G49="暂停","暂停",IF(J49="","日期缺失",IF(J49<_数据接口!$B$7,"已延期",IF(J49<=_数据接口!$B$7+7,"临近到期","正常")))))) -> 正常 | AH49: =IF(OR($A49="",J49="",AG49=""),"",AG49-J49)
A50: T047 | D50: 需求基线 | E50: 建立需求跟踪矩阵并完成基线评审 | F50: MS008 | G50: =IF(OR(M50="暂停",M50="挂起",Q50="暂停",Q50="挂起",U50="暂停",U50="挂起",Y50="暂停",Y50="挂起"),"暂停",IF(COUNTA(L50,P50,T50,X50)=0,"未分配",IF(IF(L50<>"",M50="已完成",0)+IF(P50<>"",Q50="已完成",0)+IF(T50<>"",U50="已完成",0)+IF(X50<>"",Y50="已完成",0)=COUNTA(L50,P50,T50,X50),"已完成",IF(IF(L50<>"",M50="进行中",0)+IF(P50<>"",Q50="进行中",0)+IF(T50<>"",U50="进行中",0)+IF(X50<>"",Y50="进行中",0)>0,"进行中",IF(IF(L50<>"",M50="待确认",0)+IF(P50<>"",Q50="待确认",0)+IF(T50<>"",U50="待确认",0)+IF(X50<>"",Y50="待确认",0)>0,"待确认","未开始"))))) -> 未开始 | H50: =IF(L50<>"",L50,IF(P50<>"",P50,IF(T50<>"",T50,X50))) -> 项目经理 | I50: =IF(COUNT(N50,R50,V50,Z50)=0,"",MIN(N50,R50,V50,Z50)) -> 46350 | J50: =IF(COUNT(O50,S50,W50,AA50)=0,"",MAX(O50,S50,W50,AA50)) -> 46356 | K50: 46356 | L50: 项目经理 | M50: 未开始 | N50: 46350 | O50: 46356 | AB50: =IFERROR((IF(L50<>"",IF(M50="已完成",1,IF(M50="进行中",0.5,0))*15%,0)+IF(P50<>"",IF(Q50="已完成",1,IF(Q50="进行中",0.5,0))*35%,0)+IF(T50<>"",IF(U50="已完成",1,IF(U50="进行中",0.5,0))*30%,0)+IF(X50<>"",IF(Y50="已完成",1,IF(Y50="进行中",0.5,0))*20%,0))/(IF(L50<>"",15%,0)+IF(P50<>"",35%,0)+IF(T50<>"",30%,0)+IF(X50<>"",20%,0)),0) -> 0 | AC50: =IF($A50="","",IF(G50="已完成","正常",IF(G50="暂停","暂停",IF(J50="","日期缺失",IF(J50<_数据接口!$B$7,"已延期",IF(J50<=_数据接口!$B$7+7,"临近到期","正常")))))) -> 正常 | AH50: =IF(OR($A50="",J50="",AG50=""),"",AG50-J50)
A51: T048 | C51: 详细设计完成 | D51: 详细设计 | E51: 完成核心模块和服务详细设计 | F51: MS009 | G51: =IF(OR(M51="暂停",M51="挂起",Q51="暂停",Q51="挂起",U51="暂停",U51="挂起",Y51="暂停",Y51="挂起"),"暂停",IF(COUNTA(L51,P51,T51,X51)=0,"未分配",IF(IF(L51<>"",M51="已完成",0)+IF(P51<>"",Q51="已完成",0)+IF(T51<>"",U51="已完成",0)+IF(X51<>"",Y51="已完成",0)=COUNTA(L51,P51,T51,X51),"已完成",IF(IF(L51<>"",M51="进行中",0)+IF(P51<>"",Q51="进行中",0)+IF(T51<>"",U51="进行中",0)+IF(X51<>"",Y51="进行中",0)>0,"进行中",IF(IF(L51<>"",M51="待确认",0)+IF(P51<>"",Q51="待确认",0)+IF(T51<>"",U51="待确认",0)+IF(X51<>"",Y51="待确认",0)>0,"待确认","未开始"))))) -> 未开始 | H51: =IF(L51<>"",L51,IF(P51<>"",P51,IF(T51<>"",T51,X51))) -> 技术经理 | I51: =IF(COUNT(N51,R51,V51,Z51)=0,"",MIN(N51,R51,V51,Z51)) -> 46341 | J51: =IF(COUNT(O51,S51,W51,AA51)=0,"",MAX(O51,S51,W51,AA51)) -> 46347 | K51: 46387 | P51: 技术经理 | Q51: 未开始 | R51: 46341 | S51: 46347 | AB51: =IFERROR((IF(L51<>"",IF(M51="已完成",1,IF(M51="进行中",0.5,0))*15%,0)+IF(P51<>"",IF(Q51="已完成",1,IF(Q51="进行中",0.5,0))*35%,0)+IF(T51<>"",IF(U51="已完成",1,IF(U51="进行中",0.5,0))*30%,0)+IF(X51<>"",IF(Y51="已完成",1,IF(Y51="进行中",0.5,0))*20%,0))/(IF(L51<>"",15%,0)+IF(P51<>"",35%,0)+IF(T51<>"",30%,0)+IF(X51<>"",20%,0)),0) -> 0 | AC51: =IF($A51="","",IF(G51="已完成","正常",IF(G51="暂停","暂停",IF(J51="","日期缺失",IF(J51<_数据接口!$B$7,"已延期",IF(J51<=_数据接口!$B$7+7,"临近到期","正常")))))) -> 正常 | AH51: =IF(OR($A51="",J51="",AG51=""),"",AG51-J51)
A52: T049 | D52: 数据设计 | E52: 完成数据模型、字典和数据质量规则 | F52: MS009 | G52: =IF(OR(M52="暂停",M52="挂起",Q52="暂停",Q52="挂起",U52="暂停",U52="挂起",Y52="暂停",Y52="挂起"),"暂停",IF(COUNTA(L52,P52,T52,X52)=0,"未分配",IF(IF(L52<>"",M52="已完成",0)+IF(P52<>"",Q52="已完成",0)+IF(T52<>"",U52="已完成",0)+IF(X52<>"",Y52="已完成",0)=COUNTA(L52,P52,T52,X52),"已完成",IF(IF(L52<>"",M52="进行中",0)+IF(P52<>"",Q52="进行中",0)+IF(T52<>"",U52="进行中",0)+IF(X52<>"",Y52="进行中",0)>0,"进行中",IF(IF(L52<>"",M52="待确认",0)+IF(P52<>"",Q52="待确认",0)+IF(T52<>"",U52="待确认",0)+IF(X52<>"",Y52="待确认",0)>0,"待确认","未开始"))))) -> 未开始 | H52: =IF(L52<>"",L52,IF(P52<>"",P52,IF(T52<>"",T52,X52))) -> 高级开发人员 | I52: =IF(COUNT(N52,R52,V52,Z52)=0,"",MIN(N52,R52,V52,Z52)) -> 46348 | J52: =IF(COUNT(O52,S52,W52,AA52)=0,"",MAX(O52,S52,W52,AA52)) -> 46355 | K52: 46387 | P52: 高级开发人员 | Q52: 未开始 | R52: 46348 | S52: 46355 | AB52: =IFERROR((IF(L52<>"",IF(M52="已完成",1,IF(M52="进行中",0.5,0))*15%,0)+IF(P52<>"",IF(Q52="已完成",1,IF(Q52="进行中",0.5,0))*35%,0)+IF(T52<>"",IF(U52="已完成",1,IF(U52="进行中",0.5,0))*30%,0)+IF(X52<>"",IF(Y52="已完成",1,IF(Y52="进行中",0.5,0))*20%,0))/(IF(L52<>"",15%,0)+IF(P52<>"",35%,0)+IF(T52<>"",30%,0)+IF(X52<>"",20%,0)),0) -> 0 | AC52: =IF($A52="","",IF(G52="已完成","正常",IF(G52="暂停","暂停",IF(J52="","日期缺失",IF(J52<_数据接口!$B$7,"已延期",IF(J52<=_数据接口!$B$7+7,"临近到期","正常")))))) -> 正常 | AH52: =IF(OR($A52="",J52="",AG52=""),"",AG52-J52)
A53: T050 | D53: 接口设计 | E53: 完成内部与外部接口详细设计 | F53: MS009 | G53: =IF(OR(M53="暂停",M53="挂起",Q53="暂停",Q53="挂起",U53="暂停",U53="挂起",Y53="暂停",Y53="挂起"),"暂停",IF(COUNTA(L53,P53,T53,X53)=0,"未分配",IF(IF(L53<>"",M53="已完成",0)+IF(P53<>"",Q53="已完成",0)+IF(T53<>"",U53="已完成",0)+IF(X53<>"",Y53="已完成",0)=COUNTA(L53,P53,T53,X53),"已完成",IF(IF(L53<>"",M53="进行中",0)+IF(P53<>"",Q53="进行中",0)+IF(T53<>"",U53="进行中",0)+IF(X53<>"",Y53="进行中",0)>0,"进行中",IF(IF(L53<>"",M53="待确认",0)+IF(P53<>"",Q53="待确认",0)+IF(T53<>"",U53="待确认",0)+IF(X53<>"",Y53="待确认",0)>0,"待确认","未开始"))))) -> 未开始 | H53: =IF(L53<>"",L53,IF(P53<>"",P53,IF(T53<>"",T53,X53))) -> 高级开发人员 | I53: =IF(COUNT(N53,R53,V53,Z53)=0,"",MIN(N53,R53,V53,Z53)) -> 46356 | J53: =IF(COUNT(O53,S53,W53,AA53)=0,"",MAX(O53,S53,W53,AA53)) -> 46363 | K53: 46387 | P53: 高级开发人员 | Q53: 未开始 | R53: 46356 | S53: 46363 | AB53: =IFERROR((IF(L53<>"",IF(M53="已完成",1,IF(M53="进行中",0.5,0))*15%,0)+IF(P53<>"",IF(Q53="已完成",1,IF(Q53="进行中",0.5,0))*35%,0)+IF(T53<>"",IF(U53="已完成",1,IF(U53="进行中",0.5,0))*30%,0)+IF(X53<>"",IF(Y53="已完成",1,IF(Y53="进行中",0.5,0))*20%,0))/(IF(L53<>"",15%,0)+IF(P53<>"",35%,0)+IF(T53<>"",30%,0)+IF(X53<>"",20%,0)),0) -> 0 | AC53: =IF($A53="","",IF(G53="已完成","正常",IF(G53="暂停","暂停",IF(J53="","日期缺失",IF(J53<_数据接口!$B$7,"已延期",IF(J53<=_数据接口!$B$7+7,"临近到期","正常")))))) -> 正常 | AH53: =IF(OR($A53="",J53="",AG53=""),"",AG53-J53)
A54: T051 | D54: 安全设计 | E54: 完成角色权限、数据权限和审计设计 | F54: MS009 | G54: =IF(OR(M54="暂停",M54="挂起",Q54="暂停",Q54="挂起",U54="暂停",U54="挂起",Y54="暂停",Y54="挂起"),"暂停",IF(COUNTA(L54,P54,T54,X54)=0,"未分配",IF(IF(L54<>"",M54="已完成",0)+IF(P54<>"",Q54="已完成",0)+IF(T54<>"",U54="已完成",0)+IF(X54<>"",Y54="已完成",0)=COUNTA(L54,P54,T54,X54),"已完成",IF(IF(L54<>"",M54="进行中",0)+IF(P54<>"",Q54="进行中",0)+IF(T54<>"",U54="进行中",0)+IF(X54<>"",Y54="进行中",0)>0,"进行中",IF(IF(L54<>"",M54="待确认",0)+IF(P54<>"",Q54="待确认",0)+IF(T54<>"",U54="待确认",0)+IF(X54<>"",Y54="待确认",0)>0,"待确认","未开始"))))) -> 未开始 | H54: =IF(L54<>"",L54,IF(P54<>"",P54,IF(T54<>"",T54,X54))) -> 技术经理 | I54: =IF(COUNT(N54,R54,V54,Z54)=0,"",MIN(N54,R54,V54,Z54)) -> 46364 | J54: =IF(COUNT(O54,S54,W54,AA54)=0,"",MAX(O54,S54,W54,AA54)) -> 46371 | K54: 46387 | P54: 技术经理 | Q54: 未开始 | R54: 46364 | S54: 46371 | AB54: =IFERROR((IF(L54<>"",IF(M54="已完成",1,IF(M54="进行中",0.5,0))*15%,0)+IF(P54<>"",IF(Q54="已完成",1,IF(Q54="进行中",0.5,0))*35%,0)+IF(T54<>"",IF(U54="已完成",1,IF(U54="进行中",0.5,0))*30%,0)+IF(X54<>"",IF(Y54="已完成",1,IF(Y54="进行中",0.5,0))*20%,0))/(IF(L54<>"",15%,0)+IF(P54<>"",35%,0)+IF(T54<>"",30%,0)+IF(X54<>"",20%,0)),0) -> 0 | AC54: =IF($A54="","",IF(G54="已完成","正常",IF(G54="暂停","暂停",IF(J54="","日期缺失",IF(J54<_数据接口!$B$7,"已延期",IF(J54<=_数据接口!$B$7+7,"临近到期","正常")))))) -> 正常 | AH54: =IF(OR($A54="",J54="",AG54=""),"",AG54-J54)
A55: T052 | D55: 界面设计 | E55: 完成核心页面视觉与交互设计 | F55: MS009 | G55: =IF(OR(M55="暂停",M55="挂起",Q55="暂停",Q55="挂起",U55="暂停",U55="挂起",Y55="暂停",Y55="挂起"),"暂停",IF(COUNTA(L55,P55,T55,X55)=0,"未分配",IF(IF(L55<>"",M55="已完成",0)+IF(P55<>"",Q55="已完成",0)+IF(T55<>"",U55="已完成",0)+IF(X55<>"",Y55="已完成",0)=COUNTA(L55,P55,T55,X55),"已完成",IF(IF(L55<>"",M55="进行中",0)+IF(P55<>"",Q55="进行中",0)+IF(T55<>"",U55="进行中",0)+IF(X55<>"",Y55="进行中",0)>0,"进行中",IF(IF(L55<>"",M55="待确认",0)+IF(P55<>"",Q55="待确认",0)+IF(T55<>"",U55="待确认",0)+IF(X55<>"",Y55="待确认",0)>0,"待确认","未开始"))))) -> 未开始 | H55: =IF(L55<>"",L55,IF(P55<>"",P55,IF(T55<>"",T55,X55))) -> 美工 | I55: =IF(COUNT(N55,R55,V55,Z55)=0,"",MIN(N55,R55,V55,Z55)) -> 46372 | J55: =IF(COUNT(O55,S55,W55,AA55)=0,"",MAX(O55,S55,W55,AA55)) -> 46379 | K55: 46387 | T55: 美工 | U55: 未开始 | V55: 46372 | W55: 46379 | AB55: =IFERROR((IF(L55<>"",IF(M55="已完成",1,IF(M55="进行中",0.5,0))*15%,0)+IF(P55<>"",IF(Q55="已完成",1,IF(Q55="进行中",0.5,0))*35%,0)+IF(T55<>"",IF(U55="已完成",1,IF(U55="进行中",0.5,0))*30%,0)+IF(X55<>"",IF(Y55="已完成",1,IF(Y55="进行中",0.5,0))*20%,0))/(IF(L55<>"",15%,0)+IF(P55<>"",35%,0)+IF(T55<>"",30%,0)+IF(X55<>"",20%,0)),0) -> 0 | AC55: =IF($A55="","",IF(G55="已完成","正常",IF(G55="暂停","暂停",IF(J55="","日期缺失",IF(J55<_数据接口!$B$7,"已延期",IF(J55<=_数据接口!$B$7+7,"临近到期","正常")))))) -> 正常 | AH55: =IF(OR($A55="",J55="",AG55=""),"",AG55-J55)
A56: T053 | D56: 设计评审 | E56: 完成设计走查、问题关闭和版本基线 | F56: MS009 | G56: =IF(OR(M56="暂停",M56="挂起",Q56="暂停",Q56="挂起",U56="暂停",U56="挂起",Y56="暂停",Y56="挂起"),"暂停",IF(COUNTA(L56,P56,T56,X56)=0,"未分配",IF(IF(L56<>"",M56="已完成",0)+IF(P56<>"",Q56="已完成",0)+IF(T56<>"",U56="已完成",0)+IF(X56<>"",Y56="已完成",0)=COUNTA(L56,P56,T56,X56),"已完成",IF(IF(L56<>"",M56="进行中",0)+IF(P56<>"",Q56="进行中",0)+IF(T56<>"",U56="进行中",0)+IF(X56<>"",Y56="进行中",0)>0,"进行中",IF(IF(L56<>"",M56="待确认",0)+IF(P56<>"",Q56="待确认",0)+IF(T56<>"",U56="待确认",0)+IF(X56<>"",Y56="待确认",0)>0,"待确认","未开始"))))) -> 未开始 | H56: =IF(L56<>"",L56,IF(P56<>"",P56,IF(T56<>"",T56,X56))) -> 技术经理 | I56: =IF(COUNT(N56,R56,V56,Z56)=0,"",MIN(N56,R56,V56,Z56)) -> 46380 | J56: =IF(COUNT(O56,S56,W56,AA56)=0,"",MAX(O56,S56,W56,AA56)) -> 46387 | K56: 46387 | P56: 技术经理 | Q56: 未开始 | R56: 46380 | S56: 46387 | AB56: =IFERROR((IF(L56<>"",IF(M56="已完成",1,IF(M56="进行中",0.5,0))*15%,0)+IF(P56<>"",IF(Q56="已完成",1,IF(Q56="进行中",0.5,0))*35%,0)+IF(T56<>"",IF(U56="已完成",1,IF(U56="进行中",0.5,0))*30%,0)+IF(X56<>"",IF(Y56="已完成",1,IF(Y56="进行中",0.5,0))*20%,0))/(IF(L56<>"",15%,0)+IF(P56<>"",35%,0)+IF(T56<>"",30%,0)+IF(X56<>"",20%,0)),0) -> 0 | AC56: =IF($A56="","",IF(G56="已完成","正常",IF(G56="暂停","暂停",IF(J56="","日期缺失",IF(J56<_数据接口!$B$7,"已延期",IF(J56<=_数据接口!$B$7+7,"临近到期","正常")))))) -> 正常 | AH56: =IF(OR($A56="",J56="",AG56=""),"",AG56-J56)
A57: T054 | C57: 核心功能开发完成 | D57: 基础平台 | E57: 搭建项目工程、公共组件和持续集成 | F57: MS010 | G57: =IF(OR(M57="暂停",M57="挂起",Q57="暂停",Q57="挂起",U57="暂停",U57="挂起",Y57="暂停",Y57="挂起"),"暂停",IF(COUNTA(L57,P57,T57,X57)=0,"未分配",IF(IF(L57<>"",M57="已完成",0)+IF(P57<>"",Q57="已完成",0)+IF(T57<>"",U57="已完成",0)+IF(X57<>"",Y57="已完成",0)=COUNTA(L57,P57,T57,X57),"已完成",IF(IF(L57<>"",M57="进行中",0)+IF(P57<>"",Q57="进行中",0)+IF(T57<>"",U57="进行中",0)+IF(X57<>"",Y57="进行中",0)>0,"进行中",IF(IF(L57<>"",M57="待确认",0)+IF(P57<>"",Q57="待确认",0)+IF(T57<>"",U57="待确认",0)+IF(X57<>"",Y57="待确认",0)>0,"待确认","未开始"))))) -> 未开始 | H57: =IF(L57<>"",L57,IF(P57<>"",P57,IF(T57<>"",T57,X57))) -> 高级开发人员 | I57: =IF(COUNT(N57,R57,V57,Z57)=0,"",MIN(N57,R57,V57,Z57)) -> 46357 | J57: =IF(COUNT(O57,S57,W57,AA57)=0,"",MAX(O57,S57,W57,AA57)) -> 46367 | K57: 46461 | P57: 高级开发人员 | Q57: 未开始 | R57: 46357 | S57: 46367 | AB57: =IFERROR((IF(L57<>"",IF(M57="已完成",1,IF(M57="进行中",0.5,0))*15%,0)+IF(P57<>"",IF(Q57="已完成",1,IF(Q57="进行中",0.5,0))*35%,0)+IF(T57<>"",IF(U57="已完成",1,IF(U57="进行中",0.5,0))*30%,0)+IF(X57<>"",IF(Y57="已完成",1,IF(Y57="进行中",0.5,0))*20%,0))/(IF(L57<>"",15%,0)+IF(P57<>"",35%,0)+IF(T57<>"",30%,0)+IF(X57<>"",20%,0)),0) -> 0 | AC57: =IF($A57="","",IF(G57="已完成","正常",IF(G57="暂停","暂停",IF(J57="","日期缺失",IF(J57<_数据接口!$B$7,"已延期",IF(J57<=_数据接口!$B$7+7,"临近到期","正常")))))) -> 正常 | AH57: =IF(OR($A57="",J57="",AG57=""),"",AG57-J57)
A58: T055 | D58: 合同模板 | E58: 开发合同模板、范本和条款库管理 | F58: MS010 | G58: =IF(OR(M58="暂停",M58="挂起",Q58="暂停",Q58="挂起",U58="暂停",U58="挂起",Y58="暂停",Y58="挂起"),"暂停",IF(COUNTA(L58,P58,T58,X58)=0,"未分配",IF(IF(L58<>"",M58="已完成",0)+IF(P58<>"",Q58="已完成",0)+IF(T58<>"",U58="已完成",0)+IF(X58<>"",Y58="已完成",0)=COUNTA(L58,P58,T58,X58),"已完成",IF(IF(L58<>"",M58="进行中",0)+IF(P58<>"",Q58="进行中",0)+IF(T58<>"",U58="进行中",0)+IF(X58<>"",Y58="进行中",0)>0,"进行中",IF(IF(L58<>"",M58="待确认",0)+IF(P58<>"",Q58="待确认",0)+IF(T58<>"",U58="待确认",0)+IF(X58<>"",Y58="待确认",0)>0,"待确认","未开始"))))) -> 未开始 | H58: =IF(L58<>"",L58,IF(P58<>"",P58,IF(T58<>"",T58,X58))) -> 中级开发人员 | I58: =IF(COUNT(N58,R58,V58,Z58)=0,"",MIN(N58,R58,V58,Z58)) -> 46368 | J58: =IF(COUNT(O58,S58,W58,AA58)=0,"",MAX(O58,S58,W58,AA58)) -> 46379 | K58: 46461 | T58: 中级开发人员 | U58: 未开始 | V58: 46368 | W58: 46379 | AB58: =IFERROR((IF(L58<>"",IF(M58="已完成",1,IF(M58="进行中",0.5,0))*15%,0)+IF(P58<>"",IF(Q58="已完成",1,IF(Q58="进行中",0.5,0))*35%,0)+IF(T58<>"",IF(U58="已完成",1,IF(U58="进行中",0.5,0))*30%,0)+IF(X58<>"",IF(Y58="已完成",1,IF(Y58="进行中",0.5,0))*20%,0))/(IF(L58<>"",15%,0)+IF(P58<>"",35%,0)+IF(T58<>"",30%,0)+IF(X58<>"",20%,0)),0) -> 0 | AC58: =IF($A58="","",IF(G58="已完成","正常",IF(G58="暂停","暂停",IF(J58="","日期缺失",IF(J58<_数据接口!$B$7,"已延期",IF(J58<=_数据接口!$B$7+7,"临近到期","正常")))))) -> 正常 | AH58: =IF(OR($A58="",J58="",AG58=""),"",AG58-J58)
A59: T056 | D59: 合同起草 | E59: 开发合同拟稿、协同编辑和版本管理 | F59: MS010 | G59: =IF(OR(M59="暂停",M59="挂起",Q59="暂停",Q59="挂起",U59="暂停",U59="挂起",Y59="暂停",Y59="挂起"),"暂停",IF(COUNTA(L59,P59,T59,X59)=0,"未分配",IF(IF(L59<>"",M59="已完成",0)+IF(P59<>"",Q59="已完成",0)+IF(T59<>"",U59="已完成",0)+IF(X59<>"",Y59="已完成",0)=COUNTA(L59,P59,T59,X59),"已完成",IF(IF(L59<>"",M59="进行中",0)+IF(P59<>"",Q59="进行中",0)+IF(T59<>"",U59="进行中",0)+IF(X59<>"",Y59="进行中",0)>0,"进行中",IF(IF(L59<>"",M59="待确认",0)+IF(P59<>"",Q59="待确认",0)+IF(T59<>"",U59="待确认",0)+IF(X59<>"",Y59="待确认",0)>0,"待确认","未开始"))))) -> 未开始 | H59: =IF(L59<>"",L59,IF(P59<>"",P59,IF(T59<>"",T59,X59))) -> 中级开发人员 | I59: =IF(COUNT(N59,R59,V59,Z59)=0,"",MIN(N59,R59,V59,Z59)) -> 46380 | J59: =IF(COUNT(O59,S59,W59,AA59)=0,"",MAX(O59,S59,W59,AA59)) -> 46391 | K59: 46461 | T59: 中级开发人员 | U59: 未开始 | V59: 46380 | W59: 46391 | AB59: =IFERROR((IF(L59<>"",IF(M59="已完成",1,IF(M59="进行中",0.5,0))*15%,0)+IF(P59<>"",IF(Q59="已完成",1,IF(Q59="进行中",0.5,0))*35%,0)+IF(T59<>"",IF(U59="已完成",1,IF(U59="进行中",0.5,0))*30%,0)+IF(X59<>"",IF(Y59="已完成",1,IF(Y59="进行中",0.5,0))*20%,0))/(IF(L59<>"",15%,0)+IF(P59<>"",35%,0)+IF(T59<>"",30%,0)+IF(X59<>"",20%,0)),0) -> 0 | AC59: =IF($A59="","",IF(G59="已完成","正常",IF(G59="暂停","暂停",IF(J59="","日期缺失",IF(J59<_数据接口!$B$7,"已延期",IF(J59<=_数据接口!$B$7+7,"临近到期","正常")))))) -> 正常 | AH59: =IF(OR($A59="",J59="",AG59=""),"",AG59-J59)
A60: T057 | D60: 合同审批 | E60: 开发合同审查、审批和用印流程 | F60: MS010 | G60: =IF(OR(M60="暂停",M60="挂起",Q60="暂停",Q60="挂起",U60="暂停",U60="挂起",Y60="暂停",Y60="挂起"),"暂停",IF(COUNTA(L60,P60,T60,X60)=0,"未分配",IF(IF(L60<>"",M60="已完成",0)+IF(P60<>"",Q60="已完成",0)+IF(T60<>"",U60="已完成",0)+IF(X60<>"",Y60="已完成",0)=COUNTA(L60,P60,T60,X60),"已完成",IF(IF(L60<>"",M60="进行中",0)+IF(P60<>"",Q60="进行中",0)+IF(T60<>"",U60="进行中",0)+IF(X60<>"",Y60="进行中",0)>0,"进行中",IF(IF(L60<>"",M60="待确认",0)+IF(P60<>"",Q60="待确认",0)+IF(T60<>"",U60="待确认",0)+IF(X60<>"",Y60="待确认",0)>0,"待确认","未开始"))))) -> 未开始 | H60: =IF(L60<>"",L60,IF(P60<>"",P60,IF(T60<>"",T60,X60))) -> 高级开发人员 | I60: =IF(COUNT(N60,R60,V60,Z60)=0,"",MIN(N60,R60,V60,Z60)) -> 46392 | J60: =IF(COUNT(O60,S60,W60,AA60)=0,"",MAX(O60,S60,W60,AA60)) -> 46402 | K60: 46461 | P60: 高级开发人员 | Q60: 未开始 | R60: 46392 | S60: 46402 | AB60: =IFERROR((IF(L60<>"",IF(M60="已完成",1,IF(M60="进行中",0.5,0))*15%,0)+IF(P60<>"",IF(Q60="已完成",1,IF(Q60="进行中",0.5,0))*35%,0)+IF(T60<>"",IF(U60="已完成",1,IF(U60="进行中",0.5,0))*30%,0)+IF(X60<>"",IF(Y60="已完成",1,IF(Y60="进行中",0.5,0))*20%,0))/(IF(L60<>"",15%,0)+IF(P60<>"",35%,0)+IF(T60<>"",30%,0)+IF(X60<>"",20%,0)),0) -> 0 | AC60: =IF($A60="","",IF(G60="已完成","正常",IF(G60="暂停","暂停",IF(J60="","日期缺失",IF(J60<_数据接口!$B$7,"已延期",IF(J60<=_数据接口!$B$7+7,"临近到期","正常")))))) -> 正常 | AH60: =IF(OR($A60="",J60="",AG60=""),"",AG60-J60)
A61: T058 | D61: 合同签署 | E61: 开发签署状态、签章和合同生效管理 | F61: MS010 | G61: =IF(OR(M61="暂停",M61="挂起",Q61="暂停",Q61="挂起",U61="暂停",U61="挂起",Y61="暂停",Y61="挂起"),"暂停",IF(COUNTA(L61,P61,T61,X61)=0,"未分配",IF(IF(L61<>"",M61="已完成",0)+IF(P61<>"",Q61="已完成",0)+IF(T61<>"",U61="已完成",0)+IF(X61<>"",Y61="已完成",0)=COUNTA(L61,P61,T61,X61),"已完成",IF(IF(L61<>"",M61="进行中",0)+IF(P61<>"",Q61="进行中",0)+IF(T61<>"",U61="进行中",0)+IF(X61<>"",Y61="进行中",0)>0,"进行中",IF(IF(L61<>"",M61="待确认",0)+IF(P61<>"",Q61="待确认",0)+IF(T61<>"",U61="待确认",0)+IF(X61<>"",Y61="待确认",0)>0,"待确认","未开始"))))) -> 未开始 | H61: =IF(L61<>"",L61,IF(P61<>"",P61,IF(T61<>"",T61,X61))) -> 高级开发人员 | I61: =IF(COUNT(N61,R61,V61,Z61)=0,"",MIN(N61,R61,V61,Z61)) -> 46403 | J61: =IF(COUNT(O61,S61,W61,AA61)=0,"",MAX(O61,S61,W61,AA61)) -> 46414 | K61: 46461 | P61: 高级开发人员 | Q61: 未开始 | R61: 46403 | S61: 46414 | AB61: =IFERROR((IF(L61<>"",IF(M61="已完成",1,IF(M61="进行中",0.5,0))*15%,0)+IF(P61<>"",IF(Q61="已完成",1,IF(Q61="进行中",0.5,0))*35%,0)+IF(T61<>"",IF(U61="已完成",1,IF(U61="进行中",0.5,0))*30%,0)+IF(X61<>"",IF(Y61="已完成",1,IF(Y61="进行中",0.5,0))*20%,0))/(IF(L61<>"",15%,0)+IF(P61<>"",35%,0)+IF(T61<>"",30%,0)+IF(X61<>"",20%,0)),0) -> 0 | AC61: =IF($A61="","",IF(G61="已完成","正常",IF(G61="暂停","暂停",IF(J61="","日期缺失",IF(J61<_数据接口!$B$7,"已延期",IF(J61<=_数据接口!$B$7+7,"临近到期","正常")))))) -> 正常 | AH61: =IF(OR($A61="",J61="",AG61=""),"",AG61-J61)
A62: T059 | D62: 履约管理 | E62: 开发履约计划、交付、验收和预警 | F62: MS010 | G62: =IF(OR(M62="暂停",M62="挂起",Q62="暂停",Q62="挂起",U62="暂停",U62="挂起",Y62="暂停",Y62="挂起"),"暂停",IF(COUNTA(L62,P62,T62,X62)=0,"未分配",IF(IF(L62<>"",M62="已完成",0)+IF(P62<>"",Q62="已完成",0)+IF(T62<>"",U62="已完成",0)+IF(X62<>"",Y62="已完成",0)=COUNTA(L62,P62,T62,X62),"已完成",IF(IF(L62<>"",M62="进行中",0)+IF(P62<>"",Q62="进行中",0)+IF(T62<>"",U62="进行中",0)+IF(X62<>"",Y62="进行中",0)>0,"进行中",IF(IF(L62<>"",M62="待确认",0)+IF(P62<>"",Q62="待确认",0)+IF(T62<>"",U62="待确认",0)+IF(X62<>"",Y62="待确认",0)>0,"待确认","未开始"))))) -> 未开始 | H62: =IF(L62<>"",L62,IF(P62<>"",P62,IF(T62<>"",T62,X62))) -> 中级开发人员 | I62: =IF(COUNT(N62,R62,V62,Z62)=0,"",MIN(N62,R62,V62,Z62)) -> 46415 | J62: =IF(COUNT(O62,S62,W62,AA62)=0,"",MAX(O62,S62,W62,AA62)) -> 46426 | K62: 46461 | P62: 中级开发人员 | Q62: 未开始 | R62: 46415 | S62: 46426 | AB62: =IFERROR((IF(L62<>"",IF(M62="已完成",1,IF(M62="进行中",0.5,0))*15%,0)+IF(P62<>"",IF(Q62="已完成",1,IF(Q62="进行中",0.5,0))*35%,0)+IF(T62<>"",IF(U62="已完成",1,IF(U62="进行中",0.5,0))*30%,0)+IF(X62<>"",IF(Y62="已完成",1,IF(Y62="进行中",0.5,0))*20%,0))/(IF(L62<>"",15%,0)+IF(P62<>"",35%,0)+IF(T62<>"",30%,0)+IF(X62<>"",20%,0)),0) -> 0 | AC62: =IF($A62="","",IF(G62="已完成","正常",IF(G62="暂停","暂停",IF(J62="","日期缺失",IF(J62<_数据接口!$B$7,"已延期",IF(J62<=_数据接口!$B$7+7,"临近到期","正常")))))) -> 正常 | AH62: =IF(OR($A62="",J62="",AG62=""),"",AG62-J62)
A63: T060 | D63: 收付款管理 | E63: 开发应收应付、开票和付款计划 | F63: MS010 | G63: =IF(OR(M63="暂停",M63="挂起",Q63="暂停",Q63="挂起",U63="暂停",U63="挂起",Y63="暂停",Y63="挂起"),"暂停",IF(COUNTA(L63,P63,T63,X63)=0,"未分配",IF(IF(L63<>"",M63="已完成",0)+IF(P63<>"",Q63="已完成",0)+IF(T63<>"",U63="已完成",0)+IF(X63<>"",Y63="已完成",0)=COUNTA(L63,P63,T63,X63),"已完成",IF(IF(L63<>"",M63="进行中",0)+IF(P63<>"",Q63="进行中",0)+IF(T63<>"",U63="进行中",0)+IF(X63<>"",Y63="进行中",0)>0,"进行中",IF(IF(L63<>"",M63="待确认",0)+IF(P63<>"",Q63="待确认",0)+IF(T63<>"",U63="待确认",0)+IF(X63<>"",Y63="待确认",0)>0,"待确认","未开始"))))) -> 未开始 | H63: =IF(L63<>"",L63,IF(P63<>"",P63,IF(T63<>"",T63,X63))) -> 中级开发人员 | I63: =IF(COUNT(N63,R63,V63,Z63)=0,"",MIN(N63,R63,V63,Z63)) -> 46427 | J63: =IF(COUNT(O63,S63,W63,AA63)=0,"",MAX(O63,S63,W63,AA63)) -> 46437 | K63: 46461 | P63: 中级开发人员 | Q63: 未开始 | R63: 46427 | S63: 46437 | AB63: =IFERROR((IF(L63<>"",IF(M63="已完成",1,IF(M63="进行中",0.5,0))*15%,0)+IF(P63<>"",IF(Q63="已完成",1,IF(Q63="进行中",0.5,0))*35%,0)+IF(T63<>"",IF(U63="已完成",1,IF(U63="进行中",0.5,0))*30%,0)+IF(X63<>"",IF(Y63="已完成",1,IF(Y63="进行中",0.5,0))*20%,0))/(IF(L63<>"",15%,0)+IF(P63<>"",35%,0)+IF(T63<>"",30%,0)+IF(X63<>"",20%,0)),0) -> 0 | AC63: =IF($A63="","",IF(G63="已完成","正常",IF(G63="暂停","暂停",IF(J63="","日期缺失",IF(J63<_数据接口!$B$7,"已延期",IF(J63<=_数据接口!$B$7+7,"临近到期","正常")))))) -> 正常 | AH63: =IF(OR($A63="",J63="",AG63=""),"",AG63-J63)
A64: T061 | D64: 变更归档 | E64: 开发变更、解除、终止和电子归档 | F64: MS010 | G64: =IF(OR(M64="暂停",M64="挂起",Q64="暂停",Q64="挂起",U64="暂停",U64="挂起",Y64="暂停",Y64="挂起"),"暂停",IF(COUNTA(L64,P64,T64,X64)=0,"未分配",IF(IF(L64<>"",M64="已完成",0)+IF(P64<>"",Q64="已完成",0)+IF(T64<>"",U64="已完成",0)+IF(X64<>"",Y64="已完成",0)=COUNTA(L64,P64,T64,X64),"已完成",IF(IF(L64<>"",M64="进行中",0)+IF(P64<>"",Q64="进行中",0)+IF(T64<>"",U64="进行中",0)+IF(X64<>"",Y64="进行中",0)>0,"进行中",IF(IF(L64<>"",M64="待确认",0)+IF(P64<>"",Q64="待确认",0)+IF(T64<>"",U64="待确认",0)+IF(X64<>"",Y64="待确认",0)>0,"待确认","未开始"))))) -> 未开始 | H64: =IF(L64<>"",L64,IF(P64<>"",P64,IF(T64<>"",T64,X64))) -> 中级开发人员 | I64: =IF(COUNT(N64,R64,V64,Z64)=0,"",MIN(N64,R64,V64,Z64)) -> 46438 | J64: =IF(COUNT(O64,S64,W64,AA64)=0,"",MAX(O64,S64,W64,AA64)) -> 46449 | K64: 46461 | P64: 中级开发人员 | Q64: 未开始 | R64: 46438 | S64: 46449 | AB64: =IFERROR((IF(L64<>"",IF(M64="已完成",1,IF(M64="进行中",0.5,0))*15%,0)+IF(P64<>"",IF(Q64="已完成",1,IF(Q64="进行中",0.5,0))*35%,0)+IF(T64<>"",IF(U64="已完成",1,IF(U64="进行中",0.5,0))*30%,0)+IF(X64<>"",IF(Y64="已完成",1,IF(Y64="进行中",0.5,0))*20%,0))/(IF(L64<>"",15%,0)+IF(P64<>"",35%,0)+IF(T64<>"",30%,0)+IF(X64<>"",20%,0)),0) -> 0 | AC64: =IF($A64="","",IF(G64="已完成","正常",IF(G64="暂停","暂停",IF(J64="","日期缺失",IF(J64<_数据接口!$B$7,"已延期",IF(J64<=_数据接口!$B$7+7,"临近到期","正常")))))) -> 正常 | AH64: =IF(OR($A64="",J64="",AG64=""),"",AG64-J64)
A65: T062 | D65: 查询分析 | E65: 开发合同检索、台账和经营分析页面 | F65: MS010 | G65: =IF(OR(M65="暂停",M65="挂起",Q65="暂停",Q65="挂起",U65="暂停",U65="挂起",Y65="暂停",Y65="挂起"),"暂停",IF(COUNTA(L65,P65,T65,X65)=0,"未分配",IF(IF(L65<>"",M65="已完成",0)+IF(P65<>"",Q65="已完成",0)+IF(T65<>"",U65="已完成",0)+IF(X65<>"",Y65="已完成",0)=COUNTA(L65,P65,T65,X65),"已完成",IF(IF(L65<>"",M65="进行中",0)+IF(P65<>"",Q65="进行中",0)+IF(T65<>"",U65="进行中",0)+IF(X65<>"",Y65="进行中",0)>0,"进行中",IF(IF(L65<>"",M65="待确认",0)+IF(P65<>"",Q65="待确认",0)+IF(T65<>"",U65="待确认",0)+IF(X65<>"",Y65="待确认",0)>0,"待确认","未开始"))))) -> 未开始 | H65: =IF(L65<>"",L65,IF(P65<>"",P65,IF(T65<>"",T65,X65))) -> 中级开发人员 | I65: =IF(COUNT(N65,R65,V65,Z65)=0,"",MIN(N65,R65,V65,Z65)) -> 46450 | J65: =IF(COUNT(O65,S65,W65,AA65)=0,"",MAX(O65,S65,W65,AA65)) -> 46461 | K65: 46461 | T65: 中级开发人员 | U65: 未开始 | V65: 46450 | W65: 46461 | AB65: =IFERROR((IF(L65<>"",IF(M65="已完成",1,IF(M65="进行中",0.5,0))*15%,0)+IF(P65<>"",IF(Q65="已完成",1,IF(Q65="进行中",0.5,0))*35%,0)+IF(T65<>"",IF(U65="已完成",1,IF(U65="进行中",0.5,0))*30%,0)+IF(X65<>"",IF(Y65="已完成",1,IF(Y65="进行中",0.5,0))*20%,0))/(IF(L65<>"",15%,0)+IF(P65<>"",35%,0)+IF(T65<>"",30%,0)+IF(X65<>"",20%,0)),0) -> 0 | AC65: =IF($A65="","",IF(G65="已完成","正常",IF(G65="暂停","暂停",IF(J65="","日期缺失",IF(J65<_数据接口!$B$7,"已延期",IF(J65<=_数据接口!$B$7+7,"临近到期","正常")))))) -> 正常 | AH65: =IF(OR($A65="",J65="",AG65=""),"",AG65-J65)
A66: T063 | C66: 内部系统集成完成 | D66: 内部集成 | E66: 制定端到端集成场景和测试数据 | F66: MS011 | G66: =IF(OR(M66="暂停",M66="挂起",Q66="暂停",Q66="挂起",U66="暂停",U66="挂起",Y66="暂停",Y66="挂起"),"暂停",IF(COUNTA(L66,P66,T66,X66)=0,"未分配",IF(IF(L66<>"",M66="已完成",0)+IF(P66<>"",Q66="已完成",0)+IF(T66<>"",U66="已完成",0)+IF(X66<>"",Y66="已完成",0)=COUNTA(L66,P66,T66,X66),"已完成",IF(IF(L66<>"",M66="进行中",0)+IF(P66<>"",Q66="进行中",0)+IF(T66<>"",U66="进行中",0)+IF(X66<>"",Y66="进行中",0)>0,"进行中",IF(IF(L66<>"",M66="待确认",0)+IF(P66<>"",Q66="待确认",0)+IF(T66<>"",U66="待确认",0)+IF(X66<>"",Y66="待确认",0)>0,"待确认","未开始"))))) -> 未开始 | H66: =IF(L66<>"",L66,IF(P66<>"",P66,IF(T66<>"",T66,X66))) -> 技术经理 | I66: =IF(COUNT(N66,R66,V66,Z66)=0,"",MIN(N66,R66,V66,Z66)) -> 46419 | J66: =IF(COUNT(O66,S66,W66,AA66)=0,"",MAX(O66,S66,W66,AA66)) -> 46424 | K66: 46456 | P66: 技术经理 | Q66: 未开始 | R66: 46419 | S66: 46424 | AB66: =IFERROR((IF(L66<>"",IF(M66="已完成",1,IF(M66="进行中",0.5,0))*15%,0)+IF(P66<>"",IF(Q66="已完成",1,IF(Q66="进行中",0.5,0))*35%,0)+IF(T66<>"",IF(U66="已完成",1,IF(U66="进行中",0.5,0))*30%,0)+IF(X66<>"",IF(Y66="已完成",1,IF(Y66="进行中",0.5,0))*20%,0))/(IF(L66<>"",15%,0)+IF(P66<>"",35%,0)+IF(T66<>"",30%,0)+IF(X66<>"",20%,0)),0) -> 0 | AC66: =IF($A66="","",IF(G66="已完成","正常",IF(G66="暂停","暂停",IF(J66="","日期缺失",IF(J66<_数据接口!$B$7,"已延期",IF(J66<=_数据接口!$B$7+7,"临近到期","正常")))))) -> 正常 | AH66: =IF(OR($A66="",J66="",AG66=""),"",AG66-J66)
A67: T064 | E67: 贯通合同起草、审批、签署和生效流程 | F67: MS011 | G67: =IF(OR(M67="暂停",M67="挂起",Q67="暂停",Q67="挂起",U67="暂停",U67="挂起",Y67="暂停",Y67="挂起"),"暂停",IF(COUNTA(L67,P67,T67,X67)=0,"未分配",IF(IF(L67<>"",M67="已完成",0)+IF(P67<>"",Q67="已完成",0)+IF(T67<>"",U67="已完成",0)+IF(X67<>"",Y67="已完成",0)=COUNTA(L67,P67,T67,X67),"已完成",IF(IF(L67<>"",M67="进行中",0)+IF(P67<>"",Q67="进行中",0)+IF(T67<>"",U67="进行中",0)+IF(X67<>"",Y67="进行中",0)>0,"进行中",IF(IF(L67<>"",M67="待确认",0)+IF(P67<>"",Q67="待确认",0)+IF(T67<>"",U67="待确认",0)+IF(X67<>"",Y67="待确认",0)>0,"待确认","未开始"))))) -> 未开始 | H67: =IF(L67<>"",L67,IF(P67<>"",P67,IF(T67<>"",T67,X67))) -> 高级开发人员 | I67: =IF(COUNT(N67,R67,V67,Z67)=0,"",MIN(N67,R67,V67,Z67)) -> 46425 | J67: =IF(COUNT(O67,S67,W67,AA67)=0,"",MAX(O67,S67,W67,AA67)) -> 46430 | K67: 46456 | P67: 高级开发人员 | Q67: 未开始 | R67: 46425 | S67: 46430 | AB67: =IFERROR((IF(L67<>"",IF(M67="已完成",1,IF(M67="进行中",0.5,0))*15%,0)+IF(P67<>"",IF(Q67="已完成",1,IF(Q67="进行中",0.5,0))*35%,0)+IF(T67<>"",IF(U67="已完成",1,IF(U67="进行中",0.5,0))*30%,0)+IF(X67<>"",IF(Y67="已完成",1,IF(Y67="进行中",0.5,0))*20%,0))/(IF(L67<>"",15%,0)+IF(P67<>"",35%,0)+IF(T67<>"",30%,0)+IF(X67<>"",20%,0)),0) -> 0 | AC67: =IF($A67="","",IF(G67="已完成","正常",IF(G67="暂停","暂停",IF(J67="","日期缺失",IF(J67<_数据接口!$B$7,"已延期",IF(J67<=_数据接口!$B$7+7,"临近到期","正常")))))) -> 正常 | AH67: =IF(OR($A67="",J67="",AG67=""),"",AG67-J67)
A68: T065 | E68: 贯通履约、收付款、变更和归档流程 | F68: MS011 | G68: =IF(OR(M68="暂停",M68="挂起",Q68="暂停",Q68="挂起",U68="暂停",U68="挂起",Y68="暂停",Y68="挂起"),"暂停",IF(COUNTA(L68,P68,T68,X68)=0,"未分配",IF(IF(L68<>"",M68="已完成",0)+IF(P68<>"",Q68="已完成",0)+IF(T68<>"",U68="已完成",0)+IF(X68<>"",Y68="已完成",0)=COUNTA(L68,P68,T68,X68),"已完成",IF(IF(L68<>"",M68="进行中",0)+IF(P68<>"",Q68="进行中",0)+IF(T68<>"",U68="进行中",0)+IF(X68<>"",Y68="进行中",0)>0,"进行中",IF(IF(L68<>"",M68="待确认",0)+IF(P68<>"",Q68="待确认",0)+IF(T68<>"",U68="待确认",0)+IF(X68<>"",Y68="待确认",0)>0,"待确认","未开始"))))) -> 未开始 | H68: =IF(L68<>"",L68,IF(P68<>"",P68,IF(T68<>"",T68,X68))) -> 高级开发人员 | I68: =IF(COUNT(N68,R68,V68,Z68)=0,"",MIN(N68,R68,V68,Z68)) -> 46431 | J68: =IF(COUNT(O68,S68,W68,AA68)=0,"",MAX(O68,S68,W68,AA68)) -> 46437 | K68: 46456 | P68: 高级开发人员 | Q68: 未开始 | R68: 46431 | S68: 46437 | AB68: =IFERROR((IF(L68<>"",IF(M68="已完成",1,IF(M68="进行中",0.5,0))*15%,0)+IF(P68<>"",IF(Q68="已完成",1,IF(Q68="进行中",0.5,0))*35%,0)+IF(T68<>"",IF(U68="已完成",1,IF(U68="进行中",0.5,0))*30%,0)+IF(X68<>"",IF(Y68="已完成",1,IF(Y68="进行中",0.5,0))*20%,0))/(IF(L68<>"",15%,0)+IF(P68<>"",35%,0)+IF(T68<>"",30%,0)+IF(X68<>"",20%,0)),0) -> 0 | AC68: =IF($A68="","",IF(G68="已完成","正常",IF(G68="暂停","暂停",IF(J68="","日期缺失",IF(J68<_数据接口!$B$7,"已延期",IF(J68<=_数据接口!$B$7+7,"临近到期","正常")))))) -> 正常 | AH68: =IF(OR($A68="",J68="",AG68=""),"",AG68-J68)
A69: T066 | E69: 验证主数据、权限和审计数据流 | F69: MS011 | G69: =IF(OR(M69="暂停",M69="挂起",Q69="暂停",Q69="挂起",U69="暂停",U69="挂起",Y69="暂停",Y69="挂起"),"暂停",IF(COUNTA(L69,P69,T69,X69)=0,"未分配",IF(IF(L69<>"",M69="已完成",0)+IF(P69<>"",Q69="已完成",0)+IF(T69<>"",U69="已完成",0)+IF(X69<>"",Y69="已完成",0)=COUNTA(L69,P69,T69,X69),"已完成",IF(IF(L69<>"",M69="进行中",0)+IF(P69<>"",Q69="进行中",0)+IF(T69<>"",U69="进行中",0)+IF(X69<>"",Y69="进行中",0)>0,"进行中",IF(IF(L69<>"",M69="待确认",0)+IF(P69<>"",Q69="待确认",0)+IF(T69<>"",U69="待确认",0)+IF(X69<>"",Y69="待确认",0)>0,"待确认","未开始"))))) -> 未开始 | H69: =IF(L69<>"",L69,IF(P69<>"",P69,IF(T69<>"",T69,X69))) -> 高级测试人员、中级测试人员 | I69: =IF(COUNT(N69,R69,V69,Z69)=0,"",MIN(N69,R69,V69,Z69)) -> 46438 | J69: =IF(COUNT(O69,S69,W69,AA69)=0,"",MAX(O69,S69,W69,AA69)) -> 46443 | K69: 46456 | X69: 高级测试人员、中级测试人员 | Y69: 未开始 | Z69: 46438 | AA69: 46443 | AB69: =IFERROR((IF(L69<>"",IF(M69="已完成",1,IF(M69="进行中",0.5,0))*15%,0)+IF(P69<>"",IF(Q69="已完成",1,IF(Q69="进行中",0.5,0))*35%,0)+IF(T69<>"",IF(U69="已完成",1,IF(U69="进行中",0.5,0))*30%,0)+IF(X69<>"",IF(Y69="已完成",1,IF(Y69="进行中",0.5,0))*20%,0))/(IF(L69<>"",15%,0)+IF(P69<>"",35%,0)+IF(T69<>"",30%,0)+IF(X69<>"",20%,0)),0) -> 0 | AC69: =IF($A69="","",IF(G69="已完成","正常",IF(G69="暂停","暂停",IF(J69="","日期缺失",IF(J69<_数据接口!$B$7,"已延期",IF(J69<=_数据接口!$B$7+7,"临近到期","正常")))))) -> 正常 | AH69: =IF(OR($A69="",J69="",AG69=""),"",AG69-J69)
A70: T067 | D70: 异常处理 | E70: 验证异常补偿、重试和一致性处理 | F70: MS011 | G70: =IF(OR(M70="暂停",M70="挂起",Q70="暂停",Q70="挂起",U70="暂停",U70="挂起",Y70="暂停",Y70="挂起"),"暂停",IF(COUNTA(L70,P70,T70,X70)=0,"未分配",IF(IF(L70<>"",M70="已完成",0)+IF(P70<>"",Q70="已完成",0)+IF(T70<>"",U70="已完成",0)+IF(X70<>"",Y70="已完成",0)=COUNTA(L70,P70,T70,X70),"已完成",IF(IF(L70<>"",M70="进行中",0)+IF(P70<>"",Q70="进行中",0)+IF(T70<>"",U70="进行中",0)+IF(X70<>"",Y70="进行中",0)>0,"进行中",IF(IF(L70<>"",M70="待确认",0)+IF(P70<>"",Q70="待确认",0)+IF(T70<>"",U70="待确认",0)+IF(X70<>"",Y70="待确认",0)>0,"待确认","未开始"))))) -> 未开始 | H70: =IF(L70<>"",L70,IF(P70<>"",P70,IF(T70<>"",T70,X70))) -> 高级开发人员 | I70: =IF(COUNT(N70,R70,V70,Z70)=0,"",MIN(N70,R70,V70,Z70)) -> 46444 | J70: =IF(COUNT(O70,S70,W70,AA70)=0,"",MAX(O70,S70,W70,AA70)) -> 46449 | K70: 46456 | P70: 高级开发人员 | Q70: 未开始 | R70: 46444 | S70: 46449 | AB70: =IFERROR((IF(L70<>"",IF(M70="已完成",1,IF(M70="进行中",0.5,0))*15%,0)+IF(P70<>"",IF(Q70="已完成",1,IF(Q70="进行中",0.5,0))*35%,0)+IF(T70<>"",IF(U70="已完成",1,IF(U70="进行中",0.5,0))*30%,0)+IF(X70<>"",IF(Y70="已完成",1,IF(Y70="进行中",0.5,0))*20%,0))/(IF(L70<>"",15%,0)+IF(P70<>"",35%,0)+IF(T70<>"",30%,0)+IF(X70<>"",20%,0)),0) -> 0 | AC70: =IF($A70="","",IF(G70="已完成","正常",IF(G70="暂停","暂停",IF(J70="","日期缺失",IF(J70<_数据接口!$B$7,"已延期",IF(J70<=_数据接口!$B$7+7,"临近到期","正常")))))) -> 正常 | AH70: =IF(OR($A70="",J70="",AG70=""),"",AG70-J70)
A71: T068 | D71: 集成验收 | E71: 完成内部集成回归并出具报告 | F71: MS011 | G71: =IF(OR(M71="暂停",M71="挂起",Q71="暂停",Q71="挂起",U71="暂停",U71="挂起",Y71="暂停",Y71="挂起"),"暂停",IF(COUNTA(L71,P71,T71,X71)=0,"未分配",IF(IF(L71<>"",M71="已完成",0)+IF(P71<>"",Q71="已完成",0)+IF(T71<>"",U71="已完成",0)+IF(X71<>"",Y71="已完成",0)=COUNTA(L71,P71,T71,X71),"已完成",IF(IF(L71<>"",M71="进行中",0)+IF(P71<>"",Q71="进行中",0)+IF(T71<>"",U71="进行中",0)+IF(X71<>"",Y71="进行中",0)>0,"进行中",IF(IF(L71<>"",M71="待确认",0)+IF(P71<>"",Q71="待确认",0)+IF(T71<>"",U71="待确认",0)+IF(X71<>"",Y71="待确认",0)>0,"待确认","未开始"))))) -> 未开始 | H71: =IF(L71<>"",L71,IF(P71<>"",P71,IF(T71<>"",T71,X71))) -> 高级测试人员、中级测试人员 | I71: =IF(COUNT(N71,R71,V71,Z71)=0,"",MIN(N71,R71,V71,Z71)) -> 46450 | J71: =IF(COUNT(O71,S71,W71,AA71)=0,"",MAX(O71,S71,W71,AA71)) -> 46456 | K71: 46456 | X71: 高级测试人员、中级测试人员 | Y71: 未开始 | Z71: 46450 | AA71: 46456 | AB71: =IFERROR((IF(L71<>"",IF(M71="已完成",1,IF(M71="进行中",0.5,0))*15%,0)+IF(P71<>"",IF(Q71="已完成",1,IF(Q71="进行中",0.5,0))*35%,0)+IF(T71<>"",IF(U71="已完成",1,IF(U71="进行中",0.5,0))*30%,0)+IF(X71<>"",IF(Y71="已完成",1,IF(Y71="进行中",0.5,0))*20%,0))/(IF(L71<>"",15%,0)+IF(P71<>"",35%,0)+IF(T71<>"",30%,0)+IF(X71<>"",20%,0)),0) -> 0 | AC71: =IF($A71="","",IF(G71="已完成","正常",IF(G71="暂停","暂停",IF(J71="","日期缺失",IF(J71<_数据接口!$B$7,"已延期",IF(J71<=_数据接口!$B$7+7,"临近到期","正常")))))) -> 正常 | AH71: =IF(OR($A71="",J71="",AG71=""),"",AG71-J71)
A72: T069 | C72: 外部系统集成完成 | D72: 外部接口 | E72: 确认外部系统清单、接口规范和联调计划 | F72: MS012 | G72: =IF(OR(M72="暂停",M72="挂起",Q72="暂停",Q72="挂起",U72="暂停",U72="挂起",Y72="暂停",Y72="挂起"),"暂停",IF(COUNTA(L72,P72,T72,X72)=0,"未分配",IF(IF(L72<>"",M72="已完成",0)+IF(P72<>"",Q72="已完成",0)+IF(T72<>"",U72="已完成",0)+IF(X72<>"",Y72="已完成",0)=COUNTA(L72,P72,T72,X72),"已完成",IF(IF(L72<>"",M72="进行中",0)+IF(P72<>"",Q72="进行中",0)+IF(T72<>"",U72="进行中",0)+IF(X72<>"",Y72="进行中",0)>0,"进行中",IF(IF(L72<>"",M72="待确认",0)+IF(P72<>"",Q72="待确认",0)+IF(T72<>"",U72="待确认",0)+IF(X72<>"",Y72="待确认",0)>0,"待确认","未开始"))))) -> 未开始 | H72: =IF(L72<>"",L72,IF(P72<>"",P72,IF(T72<>"",T72,X72))) -> 技术经理 | I72: =IF(COUNT(N72,R72,V72,Z72)=0,"",MIN(N72,R72,V72,Z72)) -> 46433 | J72: =IF(COUNT(O72,S72,W72,AA72)=0,"",MAX(O72,S72,W72,AA72)) -> 46436 | K72: 46466 | P72: 技术经理 | Q72: 未开始 | R72: 46433 | S72: 46436 | AB72: =IFERROR((IF(L72<>"",IF(M72="已完成",1,IF(M72="进行中",0.5,0))*15%,0)+IF(P72<>"",IF(Q72="已完成",1,IF(Q72="进行中",0.5,0))*35%,0)+IF(T72<>"",IF(U72="已完成",1,IF(U72="进行中",0.5,0))*30%,0)+IF(X72<>"",IF(Y72="已完成",1,IF(Y72="进行中",0.5,0))*20%,0))/(IF(L72<>"",15%,0)+IF(P72<>"",35%,0)+IF(T72<>"",30%,0)+IF(X72<>"",20%,0)),0) -> 0 | AC72: =IF($A72="","",IF(G72="已完成","正常",IF(G72="暂停","暂停",IF(J72="","日期缺失",IF(J72<_数据接口!$B$7,"已延期",IF(J72<=_数据接口!$B$7+7,"临近到期","正常")))))) -> 正常 | AH72: =IF(OR($A72="",J72="",AG72=""),"",AG72-J72)
A73: T070 | D73: ERP集成 | E73: 完成ERP及主数据接口联调 | F73: MS012 | G73: =IF(OR(M73="暂停",M73="挂起",Q73="暂停",Q73="挂起",U73="暂停",U73="挂起",Y73="暂停",Y73="挂起"),"暂停",IF(COUNTA(L73,P73,T73,X73)=0,"未分配",IF(IF(L73<>"",M73="已完成",0)+IF(P73<>"",Q73="已完成",0)+IF(T73<>"",U73="已完成",0)+IF(X73<>"",Y73="已完成",0)=COUNTA(L73,P73,T73,X73),"已完成",IF(IF(L73<>"",M73="进行中",0)+IF(P73<>"",Q73="进行中",0)+IF(T73<>"",U73="进行中",0)+IF(X73<>"",Y73="进行中",0)>0,"进行中",IF(IF(L73<>"",M73="待确认",0)+IF(P73<>"",Q73="待确认",0)+IF(T73<>"",U73="待确认",0)+IF(X73<>"",Y73="待确认",0)>0,"待确认","未开始"))))) -> 未开始 | H73: =IF(L73<>"",L73,IF(P73<>"",P73,IF(T73<>"",T73,X73))) -> 高级开发人员 | I73: =IF(COUNT(N73,R73,V73,Z73)=0,"",MIN(N73,R73,V73,Z73)) -> 46437 | J73: =IF(COUNT(O73,S73,W73,AA73)=0,"",MAX(O73,S73,W73,AA73)) -> 46441 | K73: 46466 | P73: 高级开发人员 | Q73: 未开始 | R73: 46437 | S73: 46441 | AB73: =IFERROR((IF(L73<>"",IF(M73="已完成",1,IF(M73="进行中",0.5,0))*15%,0)+IF(P73<>"",IF(Q73="已完成",1,IF(Q73="进行中",0.5,0))*35%,0)+IF(T73<>"",IF(U73="已完成",1,IF(U73="进行中",0.5,0))*30%,0)+IF(X73<>"",IF(Y73="已完成",1,IF(Y73="进行中",0.5,0))*20%,0))/(IF(L73<>"",15%,0)+IF(P73<>"",35%,0)+IF(T73<>"",30%,0)+IF(X73<>"",20%,0)),0) -> 0 | AC73: =IF($A73="","",IF(G73="已完成","正常",IF(G73="暂停","暂停",IF(J73="","日期缺失",IF(J73<_数据接口!$B$7,"已延期",IF(J73<=_数据接口!$B$7+7,"临近到期","正常")))))) -> 正常 | AH73: =IF(OR($A73="",J73="",AG73=""),"",AG73-J73)
A74: T071 | D74: 财务集成 | E74: 完成财务、开票和收付款接口联调 | F74: MS012 | G74: =IF(OR(M74="暂停",M74="挂起",Q74="暂停",Q74="挂起",U74="暂停",U74="挂起",Y74="暂停",Y74="挂起"),"暂停",IF(COUNTA(L74,P74,T74,X74)=0,"未分配",IF(IF(L74<>"",M74="已完成",0)+IF(P74<>"",Q74="已完成",0)+IF(T74<>"",U74="已完成",0)+IF(X74<>"",Y74="已完成",0)=COUNTA(L74,P74,T74,X74),"已完成",IF(IF(L74<>"",M74="进行中",0)+IF(P74<>"",Q74="进行中",0)+IF(T74<>"",U74="进行中",0)+IF(X74<>"",Y74="进行中",0)>0,"进行中",IF(IF(L74<>"",M74="待确认",0)+IF(P74<>"",Q74="待确认",0)+IF(T74<>"",U74="待确认",0)+IF(X74<>"",Y74="待确认",0)>0,"待确认","未开始"))))) -> 未开始 | H74: =IF(L74<>"",L74,IF(P74<>"",P74,IF(T74<>"",T74,X74))) -> 高级开发人员 | I74: =IF(COUNT(N74,R74,V74,Z74)=0,"",MIN(N74,R74,V74,Z74)) -> 46442 | J74: =IF(COUNT(O74,S74,W74,AA74)=0,"",MAX(O74,S74,W74,AA74)) -> 46446 | K74: 46466 | P74: 高级开发人员 | Q74: 未开始 | R74: 46442 | S74: 46446 | AB74: =IFERROR((IF(L74<>"",IF(M74="已完成",1,IF(M74="进行中",0.5,0))*15%,0)+IF(P74<>"",IF(Q74="已完成",1,IF(Q74="进行中",0.5,0))*35%,0)+IF(T74<>"",IF(U74="已完成",1,IF(U74="进行中",0.5,0))*30%,0)+IF(X74<>"",IF(Y74="已完成",1,IF(Y74="进行中",0.5,0))*20%,0))/(IF(L74<>"",15%,0)+IF(P74<>"",35%,0)+IF(T74<>"",30%,0)+IF(X74<>"",20%,0)),0) -> 0 | AC74: =IF($A74="","",IF(G74="已完成","正常",IF(G74="暂停","暂停",IF(J74="","日期缺失",IF(J74<_数据接口!$B$7,"已延期",IF(J74<=_数据接口!$B$7+7,"临近到期","正常")))))) -> 正常 | AH74: =IF(OR($A74="",J74="",AG74=""),"",AG74-J74)
A75: T072 | D75: OA集成 | E75: 完成OA待办、审批和消息接口联调 | F75: MS012 | G75: =IF(OR(M75="暂停",M75="挂起",Q75="暂停",Q75="挂起",U75="暂停",U75="挂起",Y75="暂停",Y75="挂起"),"暂停",IF(COUNTA(L75,P75,T75,X75)=0,"未分配",IF(IF(L75<>"",M75="已完成",0)+IF(P75<>"",Q75="已完成",0)+IF(T75<>"",U75="已完成",0)+IF(X75<>"",Y75="已完成",0)=COUNTA(L75,P75,T75,X75),"已完成",IF(IF(L75<>"",M75="进行中",0)+IF(P75<>"",Q75="进行中",0)+IF(T75<>"",U75="进行中",0)+IF(X75<>"",Y75="进行中",0)>0,"进行中",IF(IF(L75<>"",M75="待确认",0)+IF(P75<>"",Q75="待确认",0)+IF(T75<>"",U75="待确认",0)+IF(X75<>"",Y75="待确认",0)>0,"待确认","未开始"))))) -> 未开始 | H75: =IF(L75<>"",L75,IF(P75<>"",P75,IF(T75<>"",T75,X75))) -> 中级开发人员 | I75: =IF(COUNT(N75,R75,V75,Z75)=0,"",MIN(N75,R75,V75,Z75)) -> 46447 | J75: =IF(COUNT(O75,S75,W75,AA75)=0,"",MAX(O75,S75,W75,AA75)) -> 46451 | K75: 46466 | P75: 中级开发人员 | Q75: 未开始 | R75: 46447 | S75: 46451 | AB75: =IFERROR((IF(L75<>"",IF(M75="已完成",1,IF(M75="进行中",0.5,0))*15%,0)+IF(P75<>"",IF(Q75="已完成",1,IF(Q75="进行中",0.5,0))*35%,0)+IF(T75<>"",IF(U75="已完成",1,IF(U75="进行中",0.5,0))*30%,0)+IF(X75<>"",IF(Y75="已完成",1,IF(Y75="进行中",0.5,0))*20%,0))/(IF(L75<>"",15%,0)+IF(P75<>"",35%,0)+IF(T75<>"",30%,0)+IF(X75<>"",20%,0)),0) -> 0 | AC75: =IF($A75="","",IF(G75="已完成","正常",IF(G75="暂停","暂停",IF(J75="","日期缺失",IF(J75<_数据接口!$B$7,"已延期",IF(J75<=_数据接口!$B$7+7,"临近到期","正常")))))) -> 正常 | AH75: =IF(OR($A75="",J75="",AG75=""),"",AG75-J75)
A76: T073 | D76: 签章集成 | E76: 完成电子签章、CA和时间戳接口联调 | F76: MS012 | G76: =IF(OR(M76="暂停",M76="挂起",Q76="暂停",Q76="挂起",U76="暂停",U76="挂起",Y76="暂停",Y76="挂起"),"暂停",IF(COUNTA(L76,P76,T76,X76)=0,"未分配",IF(IF(L76<>"",M76="已完成",0)+IF(P76<>"",Q76="已完成",0)+IF(T76<>"",U76="已完成",0)+IF(X76<>"",Y76="已完成",0)=COUNTA(L76,P76,T76,X76),"已完成",IF(IF(L76<>"",M76="进行中",0)+IF(P76<>"",Q76="进行中",0)+IF(T76<>"",U76="进行中",0)+IF(X76<>"",Y76="进行中",0)>0,"进行中",IF(IF(L76<>"",M76="待确认",0)+IF(P76<>"",Q76="待确认",0)+IF(T76<>"",U76="待确认",0)+IF(X76<>"",Y76="待确认",0)>0,"待确认","未开始"))))) -> 未开始 | H76: =IF(L76<>"",L76,IF(P76<>"",P76,IF(T76<>"",T76,X76))) -> 高级开发人员 | I76: =IF(COUNT(N76,R76,V76,Z76)=0,"",MIN(N76,R76,V76,Z76)) -> 46452 | J76: =IF(COUNT(O76,S76,W76,AA76)=0,"",MAX(O76,S76,W76,AA76)) -> 46456 | K76: 46466 | P76: 高级开发人员 | Q76: 未开始 | R76: 46452 | S76: 46456 | AB76: =IFERROR((IF(L76<>"",IF(M76="已完成",1,IF(M76="进行中",0.5,0))*15%,0)+IF(P76<>"",IF(Q76="已完成",1,IF(Q76="进行中",0.5,0))*35%,0)+IF(T76<>"",IF(U76="已完成",1,IF(U76="进行中",0.5,0))*30%,0)+IF(X76<>"",IF(Y76="已完成",1,IF(Y76="进行中",0.5,0))*20%,0))/(IF(L76<>"",15%,0)+IF(P76<>"",35%,0)+IF(T76<>"",30%,0)+IF(X76<>"",20%,0)),0) -> 0 | AC76: =IF($A76="","",IF(G76="已完成","正常",IF(G76="暂停","暂停",IF(J76="","日期缺失",IF(J76<_数据接口!$B$7,"已延期",IF(J76<=_数据接口!$B$7+7,"临近到期","正常")))))) -> 正常 | AH76: =IF(OR($A76="",J76="",AG76=""),"",AG76-J76)
A77: T074 | D77: 接口质量 | E77: 验证对账、幂等、补偿和监控机制 | F77: MS012 | G77: =IF(OR(M77="暂停",M77="挂起",Q77="暂停",Q77="挂起",U77="暂停",U77="挂起",Y77="暂停",Y77="挂起"),"暂停",IF(COUNTA(L77,P77,T77,X77)=0,"未分配",IF(IF(L77<>"",M77="已完成",0)+IF(P77<>"",Q77="已完成",0)+IF(T77<>"",U77="已完成",0)+IF(X77<>"",Y77="已完成",0)=COUNTA(L77,P77,T77,X77),"已完成",IF(IF(L77<>"",M77="进行中",0)+IF(P77<>"",Q77="进行中",0)+IF(T77<>"",U77="进行中",0)+IF(X77<>"",Y77="进行中",0)>0,"进行中",IF(IF(L77<>"",M77="待确认",0)+IF(P77<>"",Q77="待确认",0)+IF(T77<>"",U77="待确认",0)+IF(X77<>"",Y77="待确认",0)>0,"待确认","未开始"))))) -> 未开始 | H77: =IF(L77<>"",L77,IF(P77<>"",P77,IF(T77<>"",T77,X77))) -> 高级测试人员、中级测试人员 | I77: =IF(COUNT(N77,R77,V77,Z77)=0,"",MIN(N77,R77,V77,Z77)) -> 46457 | J77: =IF(COUNT(O77,S77,W77,AA77)=0,"",MAX(O77,S77,W77,AA77)) -> 46461 | K77: 46466 | X77: 高级测试人员、中级测试人员 | Y77: 未开始 | Z77: 46457 | AA77: 46461 | AB77: =IFERROR((IF(L77<>"",IF(M77="已完成",1,IF(M77="进行中",0.5,0))*15%,0)+IF(P77<>"",IF(Q77="已完成",1,IF(Q77="进行中",0.5,0))*35%,0)+IF(T77<>"",IF(U77="已完成",1,IF(U77="进行中",0.5,0))*30%,0)+IF(X77<>"",IF(Y77="已完成",1,IF(Y77="进行中",0.5,0))*20%,0))/(IF(L77<>"",15%,0)+IF(P77<>"",35%,0)+IF(T77<>"",30%,0)+IF(X77<>"",20%,0)),0) -> 0 | AC77: =IF($A77="","",IF(G77="已完成","正常",IF(G77="暂停","暂停",IF(J77="","日期缺失",IF(J77<_数据接口!$B$7,"已延期",IF(J77<=_数据接口!$B$7+7,"临近到期","正常")))))) -> 正常 | AH77: =IF(OR($A77="",J77="",AG77=""),"",AG77-J77)
A78: T075 | D78: 联调验收 | E78: 完成外部系统联合测试并出具报告 | F78: MS012 | G78: =IF(OR(M78="暂停",M78="挂起",Q78="暂停",Q78="挂起",U78="暂停",U78="挂起",Y78="暂停",Y78="挂起"),"暂停",IF(COUNTA(L78,P78,T78,X78)=0,"未分配",IF(IF(L78<>"",M78="已完成",0)+IF(P78<>"",Q78="已完成",0)+IF(T78<>"",U78="已完成",0)+IF(X78<>"",Y78="已完成",0)=COUNTA(L78,P78,T78,X78),"已完成",IF(IF(L78<>"",M78="进行中",0)+IF(P78<>"",Q78="进行中",0)+IF(T78<>"",U78="进行中",0)+IF(X78<>"",Y78="进行中",0)>0,"进行中",IF(IF(L78<>"",M78="待确认",0)+IF(P78<>"",Q78="待确认",0)+IF(T78<>"",U78="待确认",0)+IF(X78<>"",Y78="待确认",0)>0,"待确认","未开始"))))) -> 未开始 | H78: =IF(L78<>"",L78,IF(P78<>"",P78,IF(T78<>"",T78,X78))) -> 技术经理 | I78: =IF(COUNT(N78,R78,V78,Z78)=0,"",MIN(N78,R78,V78,Z78)) -> 46462 | J78: =IF(COUNT(O78,S78,W78,AA78)=0,"",MAX(O78,S78,W78,AA78)) -> 46466 | K78: 46466 | P78: 技术经理 | Q78: 未开始 | R78: 46462 | S78: 46466 | AB78: =IFERROR((IF(L78<>"",IF(M78="已完成",1,IF(M78="进行中",0.5,0))*15%,0)+IF(P78<>"",IF(Q78="已完成",1,IF(Q78="进行中",0.5,0))*35%,0)+IF(T78<>"",IF(U78="已完成",1,IF(U78="进行中",0.5,0))*30%,0)+IF(X78<>"",IF(Y78="已完成",1,IF(Y78="进行中",0.5,0))*20%,0))/(IF(L78<>"",15%,0)+IF(P78<>"",35%,0)+IF(T78<>"",30%,0)+IF(X78<>"",20%,0)),0) -> 0 | AC78: =IF($A78="","",IF(G78="已完成","正常",IF(G78="暂停","暂停",IF(J78="","日期缺失",IF(J78<_数据接口!$B$7,"已延期",IF(J78<=_数据接口!$B$7+7,"临近到期","正常")))))) -> 正常 | AH78: =IF(OR($A78="",J78="",AG78=""),"",AG78-J78)
A79: T076 | C79: 系统测试完成 | D79: 测试准备 | E79: 编制系统测试计划、用例和测试数据 | F79: MS013 | G79: =IF(OR(M79="暂停",M79="挂起",Q79="暂停",Q79="挂起",U79="暂停",U79="挂起",Y79="暂停",Y79="挂起"),"暂停",IF(COUNTA(L79,P79,T79,X79)=0,"未分配",IF(IF(L79<>"",M79="已完成",0)+IF(P79<>"",Q79="已完成",0)+IF(T79<>"",U79="已完成",0)+IF(X79<>"",Y79="已完成",0)=COUNTA(L79,P79,T79,X79),"已完成",IF(IF(L79<>"",M79="进行中",0)+IF(P79<>"",Q79="进行中",0)+IF(T79<>"",U79="进行中",0)+IF(X79<>"",Y79="进行中",0)>0,"进行中",IF(IF(L79<>"",M79="待确认",0)+IF(P79<>"",Q79="待确认",0)+IF(T79<>"",U79="待确认",0)+IF(X79<>"",Y79="待确认",0)>0,"待确认","未开始"))))) -> 未开始 | H79: =IF(L79<>"",L79,IF(P79<>"",P79,IF(T79<>"",T79,X79))) -> 高级测试人员、中级测试人员 | I79: =IF(COUNT(N79,R79,V79,Z79)=0,"",MIN(N79,R79,V79,Z79)) -> 46447 | J79: =IF(COUNT(O79,S79,W79,AA79)=0,"",MAX(O79,S79,W79,AA79)) -> 46453 | K79: 46492 | X79: 高级测试人员、中级测试人员 | Y79: 未开始 | Z79: 46447 | AA79: 46453 | AB79: =IFERROR((IF(L79<>"",IF(M79="已完成",1,IF(M79="进行中",0.5,0))*15%,0)+IF(P79<>"",IF(Q79="已完成",1,IF(Q79="进行中",0.5,0))*35%,0)+IF(T79<>"",IF(U79="已完成",1,IF(U79="进行中",0.5,0))*30%,0)+IF(X79<>"",IF(Y79="已完成",1,IF(Y79="进行中",0.5,0))*20%,0))/(IF(L79<>"",15%,0)+IF(P79<>"",35%,0)+IF(T79<>"",30%,0)+IF(X79<>"",20%,0)),0) -> 0 | AC79: =IF($A79="","",IF(G79="已完成","正常",IF(G79="暂停","暂停",IF(J79="","日期缺失",IF(J79<_数据接口!$B$7,"已延期",IF(J79<=_数据接口!$B$7+7,"临近到期","正常")))))) -> 正常 | AH79: =IF(OR($A79="",J79="",AG79=""),"",AG79-J79)
A80: T077 | D80: 功能测试 | E80: 完成P0/P1功能与业务规则测试 | F80: MS013 | G80: =IF(OR(M80="暂停",M80="挂起",Q80="暂停",Q80="挂起",U80="暂停",U80="挂起",Y80="暂停",Y80="挂起"),"暂停",IF(COUNTA(L80,P80,T80,X80)=0,"未分配",IF(IF(L80<>"",M80="已完成",0)+IF(P80<>"",Q80="已完成",0)+IF(T80<>"",U80="已完成",0)+IF(X80<>"",Y80="已完成",0)=COUNTA(L80,P80,T80,X80),"已完成",IF(IF(L80<>"",M80="进行中",0)+IF(P80<>"",Q80="进行中",0)+IF(T80<>"",U80="进行中",0)+IF(X80<>"",Y80="进行中",0)>0,"进行中",IF(IF(L80<>"",M80="待确认",0)+IF(P80<>"",Q80="待确认",0)+IF(T80<>"",U80="待确认",0)+IF(X80<>"",Y80="待确认",0)>0,"待确认","未开始"))))) -> 未开始 | H80: =IF(L80<>"",L80,IF(P80<>"",P80,IF(T80<>"",T80,X80))) -> 高级测试人员、中级测试人员 | I80: =IF(COUNT(N80,R80,V80,Z80)=0,"",MIN(N80,R80,V80,Z80)) -> 46454 | J80: =IF(COUNT(O80,S80,W80,AA80)=0,"",MAX(O80,S80,W80,AA80)) -> 46461 | K80: 46492 | X80: 高级测试人员、中级测试人员 | Y80: 未开始 | Z80: 46454 | AA80: 46461 | AB80: =IFERROR((IF(L80<>"",IF(M80="已完成",1,IF(M80="进行中",0.5,0))*15%,0)+IF(P80<>"",IF(Q80="已完成",1,IF(Q80="进行中",0.5,0))*35%,0)+IF(T80<>"",IF(U80="已完成",1,IF(U80="进行中",0.5,0))*30%,0)+IF(X80<>"",IF(Y80="已完成",1,IF(Y80="进行中",0.5,0))*20%,0))/(IF(L80<>"",15%,0)+IF(P80<>"",35%,0)+IF(T80<>"",30%,0)+IF(X80<>"",20%,0)),0) -> 0 | AC80: =IF($A80="","",IF(G80="已完成","正常",IF(G80="暂停","暂停",IF(J80="","日期缺失",IF(J80<_数据接口!$B$7,"已延期",IF(J80<=_数据接口!$B$7+7,"临近到期","正常")))))) -> 正常 | AH80: =IF(OR($A80="",J80="",AG80=""),"",AG80-J80)
A81: T078 | D81: 集成回归 | E81: 完成内部外部接口及端到端回归 | F81: MS013 | G81: =IF(OR(M81="暂停",M81="挂起",Q81="暂停",Q81="挂起",U81="暂停",U81="挂起",Y81="暂停",Y81="挂起"),"暂停",IF(COUNTA(L81,P81,T81,X81)=0,"未分配",IF(IF(L81<>"",M81="已完成",0)+IF(P81<>"",Q81="已完成",0)+IF(T81<>"",U81="已完成",0)+IF(X81<>"",Y81="已完成",0)=COUNTA(L81,P81,T81,X81),"已完成",IF(IF(L81<>"",M81="进行中",0)+IF(P81<>"",Q81="进行中",0)+IF(T81<>"",U81="进行中",0)+IF(X81<>"",Y81="进行中",0)>0,"进行中",IF(IF(L81<>"",M81="待确认",0)+IF(P81<>"",Q81="待确认",0)+IF(T81<>"",U81="待确认",0)+IF(X81<>"",Y81="待确认",0)>0,"待确认","未开始"))))) -> 未开始 | H81: =IF(L81<>"",L81,IF(P81<>"",P81,IF(T81<>"",T81,X81))) -> 高级测试人员、中级测试人员 | I81: =IF(COUNT(N81,R81,V81,Z81)=0,"",MIN(N81,R81,V81,Z81)) -> 46462 | J81: =IF(COUNT(O81,S81,W81,AA81)=0,"",MAX(O81,S81,W81,AA81)) -> 46469 | K81: 46492 | X81: 高级测试人员、中级测试人员 | Y81: 未开始 | Z81: 46462 | AA81: 46469 | AB81: =IFERROR((IF(L81<>"",IF(M81="已完成",1,IF(M81="进行中",0.5,0))*15%,0)+IF(P81<>"",IF(Q81="已完成",1,IF(Q81="进行中",0.5,0))*35%,0)+IF(T81<>"",IF(U81="已完成",1,IF(U81="进行中",0.5,0))*30%,0)+IF(X81<>"",IF(Y81="已完成",1,IF(Y81="进行中",0.5,0))*20%,0))/(IF(L81<>"",15%,0)+IF(P81<>"",35%,0)+IF(T81<>"",30%,0)+IF(X81<>"",20%,0)),0) -> 0 | AC81: =IF($A81="","",IF(G81="已完成","正常",IF(G81="暂停","暂停",IF(J81="","日期缺失",IF(J81<_数据接口!$B$7,"已延期",IF(J81<=_数据接口!$B$7+7,"临近到期","正常")))))) -> 正常 | AH81: =IF(OR($A81="",J81="",AG81=""),"",AG81-J81)
A82: T079 | D82: 专项测试 | E82: 完成性能、安全、兼容性和可靠性测试 | F82: MS013 | G82: =IF(OR(M82="暂停",M82="挂起",Q82="暂停",Q82="挂起",U82="暂停",U82="挂起",Y82="暂停",Y82="挂起"),"暂停",IF(COUNTA(L82,P82,T82,X82)=0,"未分配",IF(IF(L82<>"",M82="已完成",0)+IF(P82<>"",Q82="已完成",0)+IF(T82<>"",U82="已完成",0)+IF(X82<>"",Y82="已完成",0)=COUNTA(L82,P82,T82,X82),"已完成",IF(IF(L82<>"",M82="进行中",0)+IF(P82<>"",Q82="进行中",0)+IF(T82<>"",U82="进行中",0)+IF(X82<>"",Y82="进行中",0)>0,"进行中",IF(IF(L82<>"",M82="待确认",0)+IF(P82<>"",Q82="待确认",0)+IF(T82<>"",U82="待确认",0)+IF(X82<>"",Y82="待确认",0)>0,"待确认","未开始"))))) -> 未开始 | H82: =IF(L82<>"",L82,IF(P82<>"",P82,IF(T82<>"",T82,X82))) -> 高级测试人员、中级测试人员 | I82: =IF(COUNT(N82,R82,V82,Z82)=0,"",MIN(N82,R82,V82,Z82)) -> 46470 | J82: =IF(COUNT(O82,S82,W82,AA82)=0,"",MAX(O82,S82,W82,AA82)) -> 46476 | K82: 46492 | X82: 高级测试人员、中级测试人员 | Y82: 未开始 | Z82: 46470 | AA82: 46476 | AB82: =IFERROR((IF(L82<>"",IF(M82="已完成",1,IF(M82="进行中",0.5,0))*15%,0)+IF(P82<>"",IF(Q82="已完成",1,IF(Q82="进行中",0.5,0))*35%,0)+IF(T82<>"",IF(U82="已完成",1,IF(U82="进行中",0.5,0))*30%,0)+IF(X82<>"",IF(Y82="已完成",1,IF(Y82="进行中",0.5,0))*20%,0))/(IF(L82<>"",15%,0)+IF(P82<>"",35%,0)+IF(T82<>"",30%,0)+IF(X82<>"",20%,0)),0) -> 0 | AC82: =IF($A82="","",IF(G82="已完成","正常",IF(G82="暂停","暂停",IF(J82="","日期缺失",IF(J82<_数据接口!$B$7,"已延期",IF(J82<=_数据接口!$B$7+7,"临近到期","正常")))))) -> 正常 | AH82: =IF(OR($A82="",J82="",AG82=""),"",AG82-J82)
A83: T080 | D83: 缺陷治理 | E83: 完成阻断及严重缺陷修复和复测 | F83: MS013 | G83: =IF(OR(M83="暂停",M83="挂起",Q83="暂停",Q83="挂起",U83="暂停",U83="挂起",Y83="暂停",Y83="挂起"),"暂停",IF(COUNTA(L83,P83,T83,X83)=0,"未分配",IF(IF(L83<>"",M83="已完成",0)+IF(P83<>"",Q83="已完成",0)+IF(T83<>"",U83="已完成",0)+IF(X83<>"",Y83="已完成",0)=COUNTA(L83,P83,T83,X83),"已完成",IF(IF(L83<>"",M83="进行中",0)+IF(P83<>"",Q83="进行中",0)+IF(T83<>"",U83="进行中",0)+IF(X83<>"",Y83="进行中",0)>0,"进行中",IF(IF(L83<>"",M83="待确认",0)+IF(P83<>"",Q83="待确认",0)+IF(T83<>"",U83="待确认",0)+IF(X83<>"",Y83="待确认",0)>0,"待确认","未开始"))))) -> 未开始 | H83: =IF(L83<>"",L83,IF(P83<>"",P83,IF(T83<>"",T83,X83))) -> 高级开发人员 | I83: =IF(COUNT(N83,R83,V83,Z83)=0,"",MIN(N83,R83,V83,Z83)) -> 46477 | J83: =IF(COUNT(O83,S83,W83,AA83)=0,"",MAX(O83,S83,W83,AA83)) -> 46484 | K83: 46492 | P83: 高级开发人员 | Q83: 未开始 | R83: 46477 | S83: 46484 | AB83: =IFERROR((IF(L83<>"",IF(M83="已完成",1,IF(M83="进行中",0.5,0))*15%,0)+IF(P83<>"",IF(Q83="已完成",1,IF(Q83="进行中",0.5,0))*35%,0)+IF(T83<>"",IF(U83="已完成",1,IF(U83="进行中",0.5,0))*30%,0)+IF(X83<>"",IF(Y83="已完成",1,IF(Y83="进行中",0.5,0))*20%,0))/(IF(L83<>"",15%,0)+IF(P83<>"",35%,0)+IF(T83<>"",30%,0)+IF(X83<>"",20%,0)),0) -> 0 | AC83: =IF($A83="","",IF(G83="已完成","正常",IF(G83="暂停","暂停",IF(J83="","日期缺失",IF(J83<_数据接口!$B$7,"已延期",IF(J83<=_数据接口!$B$7+7,"临近到期","正常")))))) -> 正常 | AH83: =IF(OR($A83="",J83="",AG83=""),"",AG83-J83)
A84: T081 | D84: 测试结论 | E84: 汇总覆盖率、缺陷和质量结论并评审 | F84: MS013 | G84: =IF(OR(M84="暂停",M84="挂起",Q84="暂停",Q84="挂起",U84="暂停",U84="挂起",Y84="暂停",Y84="挂起"),"暂停",IF(COUNTA(L84,P84,T84,X84)=0,"未分配",IF(IF(L84<>"",M84="已完成",0)+IF(P84<>"",Q84="已完成",0)+IF(T84<>"",U84="已完成",0)+IF(X84<>"",Y84="已完成",0)=COUNTA(L84,P84,T84,X84),"已完成",IF(IF(L84<>"",M84="进行中",0)+IF(P84<>"",Q84="进行中",0)+IF(T84<>"",U84="进行中",0)+IF(X84<>"",Y84="进行中",0)>0,"进行中",IF(IF(L84<>"",M84="待确认",0)+IF(P84<>"",Q84="待确认",0)+IF(T84<>"",U84="待确认",0)+IF(X84<>"",Y84="待确认",0)>0,"待确认","未开始"))))) -> 未开始 | H84: =IF(L84<>"",L84,IF(P84<>"",P84,IF(T84<>"",T84,X84))) -> 高级测试人员、中级测试人员 | I84: =IF(COUNT(N84,R84,V84,Z84)=0,"",MIN(N84,R84,V84,Z84)) -> 46485 | J84: =IF(COUNT(O84,S84,W84,AA84)=0,"",MAX(O84,S84,W84,AA84)) -> 46492 | K84: 46492 | X84: 高级测试人员、中级测试人员 | Y84: 未开始 | Z84: 46485 | AA84: 46492 | AB84: =IFERROR((IF(L84<>"",IF(M84="已完成",1,IF(M84="进行中",0.5,0))*15%,0)+IF(P84<>"",IF(Q84="已完成",1,IF(Q84="进行中",0.5,0))*35%,0)+IF(T84<>"",IF(U84="已完成",1,IF(U84="进行中",0.5,0))*30%,0)+IF(X84<>"",IF(Y84="已完成",1,IF(Y84="进行中",0.5,0))*20%,0))/(IF(L84<>"",15%,0)+IF(P84<>"",35%,0)+IF(T84<>"",30%,0)+IF(X84<>"",20%,0)),0) -> 0 | AC84: =IF($A84="","",IF(G84="已完成","正常",IF(G84="暂停","暂停",IF(J84="","日期缺失",IF(J84<_数据接口!$B$7,"已延期",IF(J84<=_数据接口!$B$7+7,"临近到期","正常")))))) -> 正常 | AH84: =IF(OR($A84="",J84="",AG84=""),"",AG84-J84)
A85: T082 | C85: UAT验收完成 | D85: UAT准备 | E85: 确认UAT场景、用户、数据和验收安排 | F85: MS014 | G85: =IF(OR(M85="暂停",M85="挂起",Q85="暂停",Q85="挂起",U85="暂停",U85="挂起",Y85="暂停",Y85="挂起"),"暂停",IF(COUNTA(L85,P85,T85,X85)=0,"未分配",IF(IF(L85<>"",M85="已完成",0)+IF(P85<>"",Q85="已完成",0)+IF(T85<>"",U85="已完成",0)+IF(X85<>"",Y85="已完成",0)=COUNTA(L85,P85,T85,X85),"已完成",IF(IF(L85<>"",M85="进行中",0)+IF(P85<>"",Q85="进行中",0)+IF(T85<>"",U85="进行中",0)+IF(X85<>"",Y85="进行中",0)>0,"进行中",IF(IF(L85<>"",M85="待确认",0)+IF(P85<>"",Q85="待确认",0)+IF(T85<>"",U85="待确认",0)+IF(X85<>"",Y85="待确认",0)>0,"待确认","未开始"))))) -> 未开始 | H85: =IF(L85<>"",L85,IF(P85<>"",P85,IF(T85<>"",T85,X85))) -> 产品经理 | I85: =IF(COUNT(N85,R85,V85,Z85)=0,"",MIN(N85,R85,V85,Z85)) -> 46493 | J85: =IF(COUNT(O85,S85,W85,AA85)=0,"",MAX(O85,S85,W85,AA85)) -> 46498 | K85: 46517 | L85: 产品经理 | M85: 未开始 | N85: 46493 | O85: 46498 | AB85: =IFERROR((IF(L85<>"",IF(M85="已完成",1,IF(M85="进行中",0.5,0))*15%,0)+IF(P85<>"",IF(Q85="已完成",1,IF(Q85="进行中",0.5,0))*35%,0)+IF(T85<>"",IF(U85="已完成",1,IF(U85="进行中",0.5,0))*30%,0)+IF(X85<>"",IF(Y85="已完成",1,IF(Y85="进行中",0.5,0))*20%,0))/(IF(L85<>"",15%,0)+IF(P85<>"",35%,0)+IF(T85<>"",30%,0)+IF(X85<>"",20%,0)),0) -> 0 | AC85: =IF($A85="","",IF(G85="已完成","正常",IF(G85="暂停","暂停",IF(J85="","日期缺失",IF(J85<_数据接口!$B$7,"已延期",IF(J85<=_数据接口!$B$7+7,"临近到期","正常")))))) -> 正常 | AH85: =IF(OR($A85="",J85="",AG85=""),"",AG85-J85)
A86: T083 | D86: UAT执行 | E86: 组织业务用户执行P0场景验收 | F86: MS014 | G86: =IF(OR(M86="暂停",M86="挂起",Q86="暂停",Q86="挂起",U86="暂停",U86="挂起",Y86="暂停",Y86="挂起"),"暂停",IF(COUNTA(L86,P86,T86,X86)=0,"未分配",IF(IF(L86<>"",M86="已完成",0)+IF(P86<>"",Q86="已完成",0)+IF(T86<>"",U86="已完成",0)+IF(X86<>"",Y86="已完成",0)=COUNTA(L86,P86,T86,X86),"已完成",IF(IF(L86<>"",M86="进行中",0)+IF(P86<>"",Q86="进行中",0)+IF(T86<>"",U86="进行中",0)+IF(X86<>"",Y86="进行中",0)>0,"进行中",IF(IF(L86<>"",M86="待确认",0)+IF(P86<>"",Q86="待确认",0)+IF(T86<>"",U86="待确认",0)+IF(X86<>"",Y86="待确认",0)>0,"待确认","未开始"))))) -> 未开始 | H86: =IF(L86<>"",L86,IF(P86<>"",P86,IF(T86<>"",T86,X86))) -> 产品经理 | I86: =IF(COUNT(N86,R86,V86,Z86)=0,"",MIN(N86,R86,V86,Z86)) -> 46499 | J86: =IF(COUNT(O86,S86,W86,AA86)=0,"",MAX(O86,S86,W86,AA86)) -> 46504 | K86: 46517 | L86: 产品经理 | M86: 未开始 | N86: 46499 | O86: 46504 | AB86: =IFERROR((IF(L86<>"",IF(M86="已完成",1,IF(M86="进行中",0.5,0))*15%,0)+IF(P86<>"",IF(Q86="已完成",1,IF(Q86="进行中",0.5,0))*35%,0)+IF(T86<>"",IF(U86="已完成",1,IF(U86="进行中",0.5,0))*30%,0)+IF(X86<>"",IF(Y86="已完成",1,IF(Y86="进行中",0.5,0))*20%,0))/(IF(L86<>"",15%,0)+IF(P86<>"",35%,0)+IF(T86<>"",30%,0)+IF(X86<>"",20%,0)),0) -> 0 | AC86: =IF($A86="","",IF(G86="已完成","正常",IF(G86="暂停","暂停",IF(J86="","日期缺失",IF(J86<_数据接口!$B$7,"已延期",IF(J86<=_数据接口!$B$7+7,"临近到期","正常")))))) -> 正常 | AH86: =IF(OR($A86="",J86="",AG86=""),"",AG86-J86)
A87: T084 | D87: 问题闭环 | E87: 修复UAT问题并完成业务回归 | F87: MS014 | G87: =IF(OR(M87="暂停",M87="挂起",Q87="暂停",Q87="挂起",U87="暂停",U87="挂起",Y87="暂停",Y87="挂起"),"暂停",IF(COUNTA(L87,P87,T87,X87)=0,"未分配",IF(IF(L87<>"",M87="已完成",0)+IF(P87<>"",Q87="已完成",0)+IF(T87<>"",U87="已完成",0)+IF(X87<>"",Y87="已完成",0)=COUNTA(L87,P87,T87,X87),"已完成",IF(IF(L87<>"",M87="进行中",0)+IF(P87<>"",Q87="进行中",0)+IF(T87<>"",U87="进行中",0)+IF(X87<>"",Y87="进行中",0)>0,"进行中",IF(IF(L87<>"",M87="待确认",0)+IF(P87<>"",Q87="待确认",0)+IF(T87<>"",U87="待确认",0)+IF(X87<>"",Y87="待确认",0)>0,"待确认","未开始"))))) -> 未开始 | H87: =IF(L87<>"",L87,IF(P87<>"",P87,IF(T87<>"",T87,X87))) -> 高级开发人员 | I87: =IF(COUNT(N87,R87,V87,Z87)=0,"",MIN(N87,R87,V87,Z87)) -> 46505 | J87: =IF(COUNT(O87,S87,W87,AA87)=0,"",MAX(O87,S87,W87,AA87)) -> 46510 | K87: 46517 | P87: 高级开发人员 | Q87: 未开始 | R87: 46505 | S87: 46510 | AB87: =IFERROR((IF(L87<>"",IF(M87="已完成",1,IF(M87="进行中",0.5,0))*15%,0)+IF(P87<>"",IF(Q87="已完成",1,IF(Q87="进行中",0.5,0))*35%,0)+IF(T87<>"",IF(U87="已完成",1,IF(U87="进行中",0.5,0))*30%,0)+IF(X87<>"",IF(Y87="已完成",1,IF(Y87="进行中",0.5,0))*20%,0))/(IF(L87<>"",15%,0)+IF(P87<>"",35%,0)+IF(T87<>"",30%,0)+IF(X87<>"",20%,0)),0) -> 0 | AC87: =IF($A87="","",IF(G87="已完成","正常",IF(G87="暂停","暂停",IF(J87="","日期缺失",IF(J87<_数据接口!$B$7,"已延期",IF(J87<=_数据接口!$B$7+7,"临近到期","正常")))))) -> 正常 | AH87: =IF(OR($A87="",J87="",AG87=""),"",AG87-J87)
A88: T085 | D88: 业务验收 | E88: 形成UAT报告、遗留事项和确认单 | F88: MS014 | G88: =IF(OR(M88="暂停",M88="挂起",Q88="暂停",Q88="挂起",U88="暂停",U88="挂起",Y88="暂停",Y88="挂起"),"暂停",IF(COUNTA(L88,P88,T88,X88)=0,"未分配",IF(IF(L88<>"",M88="已完成",0)+IF(P88<>"",Q88="已完成",0)+IF(T88<>"",U88="已完成",0)+IF(X88<>"",Y88="已完成",0)=COUNTA(L88,P88,T88,X88),"已完成",IF(IF(L88<>"",M88="进行中",0)+IF(P88<>"",Q88="进行中",0)+IF(T88<>"",U88="进行中",0)+IF(X88<>"",Y88="进行中",0)>0,"进行中",IF(IF(L88<>"",M88="待确认",0)+IF(P88<>"",Q88="待确认",0)+IF(T88<>"",U88="待确认",0)+IF(X88<>"",Y88="待确认",0)>0,"待确认","未开始"))))) -> 未开始 | H88: =IF(L88<>"",L88,IF(P88<>"",P88,IF(T88<>"",T88,X88))) -> 项目经理 | I88: =IF(COUNT(N88,R88,V88,Z88)=0,"",MIN(N88,R88,V88,Z88)) -> 46511 | J88: =IF(COUNT(O88,S88,W88,AA88)=0,"",MAX(O88,S88,W88,AA88)) -> 46517 | K88: 46517 | L88: 项目经理 | M88: 未开始 | N88: 46511 | O88: 46517 | AB88: =IFERROR((IF(L88<>"",IF(M88="已完成",1,IF(M88="进行中",0.5,0))*15%,0)+IF(P88<>"",IF(Q88="已完成",1,IF(Q88="进行中",0.5,0))*35%,0)+IF(T88<>"",IF(U88="已完成",1,IF(U88="进行中",0.5,0))*30%,0)+IF(X88<>"",IF(Y88="已完成",1,IF(Y88="进行中",0.5,0))*20%,0))/(IF(L88<>"",15%,0)+IF(P88<>"",35%,0)+IF(T88<>"",30%,0)+IF(X88<>"",20%,0)),0) -> 0 | AC88: =IF($A88="","",IF(G88="已完成","正常",IF(G88="暂停","暂停",IF(J88="","日期缺失",IF(J88<_数据接口!$B$7,"已延期",IF(J88<=_数据接口!$B$7+7,"临近到期","正常")))))) -> 正常 | AH88: =IF(OR($A88="",J88="",AG88=""),"",AG88-J88)
A89: T086 | C89: 上线准入评审通过 | D89: 上线准备 | E89: 完成生产部署、发布和回退方案 | F89: MS015 | G89: =IF(OR(M89="暂停",M89="挂起",Q89="暂停",Q89="挂起",U89="暂停",U89="挂起",Y89="暂停",Y89="挂起"),"暂停",IF(COUNTA(L89,P89,T89,X89)=0,"未分配",IF(IF(L89<>"",M89="已完成",0)+IF(P89<>"",Q89="已完成",0)+IF(T89<>"",U89="已完成",0)+IF(X89<>"",Y89="已完成",0)=COUNTA(L89,P89,T89,X89),"已完成",IF(IF(L89<>"",M89="进行中",0)+IF(P89<>"",Q89="进行中",0)+IF(T89<>"",U89="进行中",0)+IF(X89<>"",Y89="进行中",0)>0,"进行中",IF(IF(L89<>"",M89="待确认",0)+IF(P89<>"",Q89="待确认",0)+IF(T89<>"",U89="待确认",0)+IF(X89<>"",Y89="待确认",0)>0,"待确认","未开始"))))) -> 未开始 | H89: =IF(L89<>"",L89,IF(P89<>"",P89,IF(T89<>"",T89,X89))) -> 配置人员 | I89: =IF(COUNT(N89,R89,V89,Z89)=0,"",MIN(N89,R89,V89,Z89)) -> 46518 | J89: =IF(COUNT(O89,S89,W89,AA89)=0,"",MAX(O89,S89,W89,AA89)) -> 46519 | K89: 46531 | P89: 配置人员 | Q89: 未开始 | R89: 46518 | S89: 46519 | AB89: =IFERROR((IF(L89<>"",IF(M89="已完成",1,IF(M89="进行中",0.5,0))*15%,0)+IF(P89<>"",IF(Q89="已完成",1,IF(Q89="进行中",0.5,0))*35%,0)+IF(T89<>"",IF(U89="已完成",1,IF(U89="进行中",0.5,0))*30%,0)+IF(X89<>"",IF(Y89="已完成",1,IF(Y89="进行中",0.5,0))*20%,0))/(IF(L89<>"",15%,0)+IF(P89<>"",35%,0)+IF(T89<>"",30%,0)+IF(X89<>"",20%,0)),0) -> 0 | AC89: =IF($A89="","",IF(G89="已完成","正常",IF(G89="暂停","暂停",IF(J89="","日期缺失",IF(J89<_数据接口!$B$7,"已延期",IF(J89<=_数据接口!$B$7+7,"临近到期","正常")))))) -> 正常 | AH89: =IF(OR($A89="",J89="",AG89=""),"",AG89-J89)
A90: T087 | D90: 数据准备 | E90: 完成数据迁移、清洗和对账演练 | F90: MS015 | G90: =IF(OR(M90="暂停",M90="挂起",Q90="暂停",Q90="挂起",U90="暂停",U90="挂起",Y90="暂停",Y90="挂起"),"暂停",IF(COUNTA(L90,P90,T90,X90)=0,"未分配",IF(IF(L90<>"",M90="已完成",0)+IF(P90<>"",Q90="已完成",0)+IF(T90<>"",U90="已完成",0)+IF(X90<>"",Y90="已完成",0)=COUNTA(L90,P90,T90,X90),"已完成",IF(IF(L90<>"",M90="进行中",0)+IF(P90<>"",Q90="进行中",0)+IF(T90<>"",U90="进行中",0)+IF(X90<>"",Y90="进行中",0)>0,"进行中",IF(IF(L90<>"",M90="待确认",0)+IF(P90<>"",Q90="待确认",0)+IF(T90<>"",U90="待确认",0)+IF(X90<>"",Y90="待确认",0)>0,"待确认","未开始"))))) -> 未开始 | H90: =IF(L90<>"",L90,IF(P90<>"",P90,IF(T90<>"",T90,X90))) -> 高级开发人员 | I90: =IF(COUNT(N90,R90,V90,Z90)=0,"",MIN(N90,R90,V90,Z90)) -> 46520 | J90: =IF(COUNT(O90,S90,W90,AA90)=0,"",MAX(O90,S90,W90,AA90)) -> 46521 | K90: 46531 | P90: 高级开发人员 | Q90: 未开始 | R90: 46520 | S90: 46521 | AB90: =IFERROR((IF(L90<>"",IF(M90="已完成",1,IF(M90="进行中",0.5,0))*15%,0)+IF(P90<>"",IF(Q90="已完成",1,IF(Q90="进行中",0.5,0))*35%,0)+IF(T90<>"",IF(U90="已完成",1,IF(U90="进行中",0.5,0))*30%,0)+IF(X90<>"",IF(Y90="已完成",1,IF(Y90="进行中",0.5,0))*20%,0))/(IF(L90<>"",15%,0)+IF(P90<>"",35%,0)+IF(T90<>"",30%,0)+IF(X90<>"",20%,0)),0) -> 0 | AC90: =IF($A90="","",IF(G90="已完成","正常",IF(G90="暂停","暂停",IF(J90="","日期缺失",IF(J90<_数据接口!$B$7,"已延期",IF(J90<=_数据接口!$B$7+7,"临近到期","正常")))))) -> 正常 | AH90: =IF(OR($A90="",J90="",AG90=""),"",AG90-J90)
A91: T088 | D91: 上线检查 | E91: 核查接口、权限、证书和配置参数 | F91: MS015 | G91: =IF(OR(M91="暂停",M91="挂起",Q91="暂停",Q91="挂起",U91="暂停",U91="挂起",Y91="暂停",Y91="挂起"),"暂停",IF(COUNTA(L91,P91,T91,X91)=0,"未分配",IF(IF(L91<>"",M91="已完成",0)+IF(P91<>"",Q91="已完成",0)+IF(T91<>"",U91="已完成",0)+IF(X91<>"",Y91="已完成",0)=COUNTA(L91,P91,T91,X91),"已完成",IF(IF(L91<>"",M91="进行中",0)+IF(P91<>"",Q91="进行中",0)+IF(T91<>"",U91="进行中",0)+IF(X91<>"",Y91="进行中",0)>0,"进行中",IF(IF(L91<>"",M91="待确认",0)+IF(P91<>"",Q91="待确认",0)+IF(T91<>"",U91="待确认",0)+IF(X91<>"",Y91="待确认",0)>0,"待确认","未开始"))))) -> 未开始 | H91: =IF(L91<>"",L91,IF(P91<>"",P91,IF(T91<>"",T91,X91))) -> 技术经理 | I91: =IF(COUNT(N91,R91,V91,Z91)=0,"",MIN(N91,R91,V91,Z91)) -> 46522 | J91: =IF(COUNT(O91,S91,W91,AA91)=0,"",MAX(O91,S91,W91,AA91)) -> 46524 | K91: 46531 | P91: 技术经理 | Q91: 未开始 | R91: 46522 | S91: 46524 | AB91: =IFERROR((IF(L91<>"",IF(M91="已完成",1,IF(M91="进行中",0.5,0))*15%,0)+IF(P91<>"",IF(Q91="已完成",1,IF(Q91="进行中",0.5,0))*35%,0)+IF(T91<>"",IF(U91="已完成",1,IF(U91="进行中",0.5,0))*30%,0)+IF(X91<>"",IF(Y91="已完成",1,IF(Y91="进行中",0.5,0))*20%,0))/(IF(L91<>"",15%,0)+IF(P91<>"",35%,0)+IF(T91<>"",30%,0)+IF(X91<>"",20%,0)),0) -> 0 | AC91: =IF($A91="","",IF(G91="已完成","正常",IF(G91="暂停","暂停",IF(J91="","日期缺失",IF(J91<_数据接口!$B$7,"已延期",IF(J91<=_数据接口!$B$7+7,"临近到期","正常")))))) -> 正常 | AH91: =IF(OR($A91="",J91="",AG91=""),"",AG91-J91)
A92: T089 | D92: 运维准备 | E92: 建立监控、告警、备份和支持机制 | F92: MS015 | G92: =IF(OR(M92="暂停",M92="挂起",Q92="暂停",Q92="挂起",U92="暂停",U92="挂起",Y92="暂停",Y92="挂起"),"暂停",IF(COUNTA(L92,P92,T92,X92)=0,"未分配",IF(IF(L92<>"",M92="已完成",0)+IF(P92<>"",Q92="已完成",0)+IF(T92<>"",U92="已完成",0)+IF(X92<>"",Y92="已完成",0)=COUNTA(L92,P92,T92,X92),"已完成",IF(IF(L92<>"",M92="进行中",0)+IF(P92<>"",Q92="进行中",0)+IF(T92<>"",U92="进行中",0)+IF(X92<>"",Y92="进行中",0)>0,"进行中",IF(IF(L92<>"",M92="待确认",0)+IF(P92<>"",Q92="待确认",0)+IF(T92<>"",U92="待确认",0)+IF(X92<>"",Y92="待确认",0)>0,"待确认","未开始"))))) -> 未开始 | H92: =IF(L92<>"",L92,IF(P92<>"",P92,IF(T92<>"",T92,X92))) -> 配置人员 | I92: =IF(COUNT(N92,R92,V92,Z92)=0,"",MIN(N92,R92,V92,Z92)) -> 46525 | J92: =IF(COUNT(O92,S92,W92,AA92)=0,"",MAX(O92,S92,W92,AA92)) -> 46526 | K92: 46531 | P92: 配置人员 | Q92: 未开始 | R92: 46525 | S92: 46526 | AB92: =IFERROR((IF(L92<>"",IF(M92="已完成",1,IF(M92="进行中",0.5,0))*15%,0)+IF(P92<>"",IF(Q92="已完成",1,IF(Q92="进行中",0.5,0))*35%,0)+IF(T92<>"",IF(U92="已完成",1,IF(U92="进行中",0.5,0))*30%,0)+IF(X92<>"",IF(Y92="已完成",1,IF(Y92="进行中",0.5,0))*20%,0))/(IF(L92<>"",15%,0)+IF(P92<>"",35%,0)+IF(T92<>"",30%,0)+IF(X92<>"",20%,0)),0) -> 0 | AC92: =IF($A92="","",IF(G92="已完成","正常",IF(G92="暂停","暂停",IF(J92="","日期缺失",IF(J92<_数据接口!$B$7,"已延期",IF(J92<=_数据接口!$B$7+7,"临近到期","正常")))))) -> 正常 | AH92: =IF(OR($A92="",J92="",AG92=""),"",AG92-J92)
A93: T090 | D93: 培训交接 | E93: 完成用户培训、手册和运维交接 | F93: MS015 | G93: =IF(OR(M93="暂停",M93="挂起",Q93="暂停",Q93="挂起",U93="暂停",U93="挂起",Y93="暂停",Y93="挂起"),"暂停",IF(COUNTA(L93,P93,T93,X93)=0,"未分配",IF(IF(L93<>"",M93="已完成",0)+IF(P93<>"",Q93="已完成",0)+IF(T93<>"",U93="已完成",0)+IF(X93<>"",Y93="已完成",0)=COUNTA(L93,P93,T93,X93),"已完成",IF(IF(L93<>"",M93="进行中",0)+IF(P93<>"",Q93="进行中",0)+IF(T93<>"",U93="进行中",0)+IF(X93<>"",Y93="进行中",0)>0,"进行中",IF(IF(L93<>"",M93="待确认",0)+IF(P93<>"",Q93="待确认",0)+IF(T93<>"",U93="待确认",0)+IF(X93<>"",Y93="待确认",0)>0,"待确认","未开始"))))) -> 未开始 | H93: =IF(L93<>"",L93,IF(P93<>"",P93,IF(T93<>"",T93,X93))) -> 产品经理 | I93: =IF(COUNT(N93,R93,V93,Z93)=0,"",MIN(N93,R93,V93,Z93)) -> 46527 | J93: =IF(COUNT(O93,S93,W93,AA93)=0,"",MAX(O93,S93,W93,AA93)) -> 46528 | K93: 46531 | L93: 产品经理 | M93: 未开始 | N93: 46527 | O93: 46528 | AB93: =IFERROR((IF(L93<>"",IF(M93="已完成",1,IF(M93="进行中",0.5,0))*15%,0)+IF(P93<>"",IF(Q93="已完成",1,IF(Q93="进行中",0.5,0))*35%,0)+IF(T93<>"",IF(U93="已完成",1,IF(U93="进行中",0.5,0))*30%,0)+IF(X93<>"",IF(Y93="已完成",1,IF(Y93="进行中",0.5,0))*20%,0))/(IF(L93<>"",15%,0)+IF(P93<>"",35%,0)+IF(T93<>"",30%,0)+IF(X93<>"",20%,0)),0) -> 0 | AC93: =IF($A93="","",IF(G93="已完成","正常",IF(G93="暂停","暂停",IF(J93="","日期缺失",IF(J93<_数据接口!$B$7,"已延期",IF(J93<=_数据接口!$B$7+7,"临近到期","正常")))))) -> 正常 | AH93: =IF(OR($A93="",J93="",AG93=""),"",AG93-J93)
A94: T091 | D94: 准入评审 | E94: 执行上线检查表并获得上线批准 | F94: MS015 | G94: =IF(OR(M94="暂停",M94="挂起",Q94="暂停",Q94="挂起",U94="暂停",U94="挂起",Y94="暂停",Y94="挂起"),"暂停",IF(COUNTA(L94,P94,T94,X94)=0,"未分配",IF(IF(L94<>"",M94="已完成",0)+IF(P94<>"",Q94="已完成",0)+IF(T94<>"",U94="已完成",0)+IF(X94<>"",Y94="已完成",0)=COUNTA(L94,P94,T94,X94),"已完成",IF(IF(L94<>"",M94="进行中",0)+IF(P94<>"",Q94="进行中",0)+IF(T94<>"",U94="进行中",0)+IF(X94<>"",Y94="进行中",0)>0,"进行中",IF(IF(L94<>"",M94="待确认",0)+IF(P94<>"",Q94="待确认",0)+IF(T94<>"",U94="待确认",0)+IF(X94<>"",Y94="待确认",0)>0,"待确认","未开始"))))) -> 未开始 | H94: =IF(L94<>"",L94,IF(P94<>"",P94,IF(T94<>"",T94,X94))) -> 项目集经理 | I94: =IF(COUNT(N94,R94,V94,Z94)=0,"",MIN(N94,R94,V94,Z94)) -> 46529 | J94: =IF(COUNT(O94,S94,W94,AA94)=0,"",MAX(O94,S94,W94,AA94)) -> 46531 | K94: 46531 | L94: 项目集经理 | M94: 未开始 | N94: 46529 | O94: 46531 | AB94: =IFERROR((IF(L94<>"",IF(M94="已完成",1,IF(M94="进行中",0.5,0))*15%,0)+IF(P94<>"",IF(Q94="已完成",1,IF(Q94="进行中",0.5,0))*35%,0)+IF(T94<>"",IF(U94="已完成",1,IF(U94="进行中",0.5,0))*30%,0)+IF(X94<>"",IF(Y94="已完成",1,IF(Y94="进行中",0.5,0))*20%,0))/(IF(L94<>"",15%,0)+IF(P94<>"",35%,0)+IF(T94<>"",30%,0)+IF(X94<>"",20%,0)),0) -> 0 | AC94: =IF($A94="","",IF(G94="已完成","正常",IF(G94="暂停","暂停",IF(J94="","日期缺失",IF(J94<_数据接口!$B$7,"已延期",IF(J94<=_数据接口!$B$7+7,"临近到期","正常")))))) -> 正常 | AH94: =IF(OR($A94="",J94="",AG94=""),"",AG94-J94)
A95: T092 | B95: 系统上线与试运行 | C95: 生产上线并进入试运行 | D95: 生产发布 | E95: 执行生产部署、数据切换和版本发布 | F95: MS016 | G95: =IF(OR(M95="暂停",M95="挂起",Q95="暂停",Q95="挂起",U95="暂停",U95="挂起",Y95="暂停",Y95="挂起"),"暂停",IF(COUNTA(L95,P95,T95,X95)=0,"未分配",IF(IF(L95<>"",M95="已完成",0)+IF(P95<>"",Q95="已完成",0)+IF(T95<>"",U95="已完成",0)+IF(X95<>"",Y95="已完成",0)=COUNTA(L95,P95,T95,X95),"已完成",IF(IF(L95<>"",M95="进行中",0)+IF(P95<>"",Q95="进行中",0)+IF(T95<>"",U95="进行中",0)+IF(X95<>"",Y95="进行中",0)>0,"进行中",IF(IF(L95<>"",M95="待确认",0)+IF(P95<>"",Q95="待确认",0)+IF(T95<>"",U95="待确认",0)+IF(X95<>"",Y95="待确认",0)>0,"待确认","未开始"))))) -> 未开始 | H95: =IF(L95<>"",L95,IF(P95<>"",P95,IF(T95<>"",T95,X95))) -> 配置人员 | I95: =IF(COUNT(N95,R95,V95,Z95)=0,"",MIN(N95,R95,V95,Z95)) -> 46538 | J95: =IF(COUNT(O95,S95,W95,AA95)=0,"",MAX(O95,S95,W95,AA95)) -> 46538 | K95: 46538 | P95: 配置人员 | Q95: 未开始 | R95: 46538 | S95: 46538 | AB95: =IFERROR((IF(L95<>"",IF(M95="已完成",1,IF(M95="进行中",0.5,0))*15%,0)+IF(P95<>"",IF(Q95="已完成",1,IF(Q95="进行中",0.5,0))*35%,0)+IF(T95<>"",IF(U95="已完成",1,IF(U95="进行中",0.5,0))*30%,0)+IF(X95<>"",IF(Y95="已完成",1,IF(Y95="进行中",0.5,0))*20%,0))/(IF(L95<>"",15%,0)+IF(P95<>"",35%,0)+IF(T95<>"",30%,0)+IF(X95<>"",20%,0)),0) -> 0 | AC95: =IF($A95="","",IF(G95="已完成","正常",IF(G95="暂停","暂停",IF(J95="","日期缺失",IF(J95<_数据接口!$B$7,"已延期",IF(J95<=_数据接口!$B$7+7,"临近到期","正常")))))) -> 正常 | AH95: =IF(OR($A95="",J95="",AG95=""),"",AG95-J95)
A96: T093 | D96: 上线验证 | E96: 执行生产冒烟和关键业务链路验证 | F96: MS016 | G96: =IF(OR(M96="暂停",M96="挂起",Q96="暂停",Q96="挂起",U96="暂停",U96="挂起",Y96="暂停",Y96="挂起"),"暂停",IF(COUNTA(L96,P96,T96,X96)=0,"未分配",IF(IF(L96<>"",M96="已完成",0)+IF(P96<>"",Q96="已完成",0)+IF(T96<>"",U96="已完成",0)+IF(X96<>"",Y96="已完成",0)=COUNTA(L96,P96,T96,X96),"已完成",IF(IF(L96<>"",M96="进行中",0)+IF(P96<>"",Q96="进行中",0)+IF(T96<>"",U96="进行中",0)+IF(X96<>"",Y96="进行中",0)>0,"进行中",IF(IF(L96<>"",M96="待确认",0)+IF(P96<>"",Q96="待确认",0)+IF(T96<>"",U96="待确认",0)+IF(X96<>"",Y96="待确认",0)>0,"待确认","未开始"))))) -> 未开始 | H96: =IF(L96<>"",L96,IF(P96<>"",P96,IF(T96<>"",T96,X96))) -> 高级测试人员、中级测试人员 | I96: =IF(COUNT(N96,R96,V96,Z96)=0,"",MIN(N96,R96,V96,Z96)) -> 46538 | J96: =IF(COUNT(O96,S96,W96,AA96)=0,"",MAX(O96,S96,W96,AA96)) -> 46538 | K96: 46538 | X96: 高级测试人员、中级测试人员 | Y96: 未开始 | Z96: 46538 | AA96: 46538 | AB96: =IFERROR((IF(L96<>"",IF(M96="已完成",1,IF(M96="进行中",0.5,0))*15%,0)+IF(P96<>"",IF(Q96="已完成",1,IF(Q96="进行中",0.5,0))*35%,0)+IF(T96<>"",IF(U96="已完成",1,IF(U96="进行中",0.5,0))*30%,0)+IF(X96<>"",IF(Y96="已完成",1,IF(Y96="进行中",0.5,0))*20%,0))/(IF(L96<>"",15%,0)+IF(P96<>"",35%,0)+IF(T96<>"",30%,0)+IF(X96<>"",20%,0)),0) -> 0 | AC96: =IF($A96="","",IF(G96="已完成","正常",IF(G96="暂停","暂停",IF(J96="","日期缺失",IF(J96<_数据接口!$B$7,"已延期",IF(J96<=_数据接口!$B$7+7,"临近到期","正常")))))) -> 正常 | AH96: =IF(OR($A96="",J96="",AG96=""),"",AG96-J96)
A97: T094 | D97: 试运行 | E97: 启动监控、问题响应和试运行支持 | F97: MS016 | G97: =IF(OR(M97="暂停",M97="挂起",Q97="暂停",Q97="挂起",U97="暂停",U97="挂起",Y97="暂停",Y97="挂起"),"暂停",IF(COUNTA(L97,P97,T97,X97)=0,"未分配",IF(IF(L97<>"",M97="已完成",0)+IF(P97<>"",Q97="已完成",0)+IF(T97<>"",U97="已完成",0)+IF(X97<>"",Y97="已完成",0)=COUNTA(L97,P97,T97,X97),"已完成",IF(IF(L97<>"",M97="进行中",0)+IF(P97<>"",Q97="进行中",0)+IF(T97<>"",U97="进行中",0)+IF(X97<>"",Y97="进行中",0)>0,"进行中",IF(IF(L97<>"",M97="待确认",0)+IF(P97<>"",Q97="待确认",0)+IF(T97<>"",U97="待确认",0)+IF(X97<>"",Y97="待确认",0)>0,"待确认","未开始"))))) -> 未开始 | H97: =IF(L97<>"",L97,IF(P97<>"",P97,IF(T97<>"",T97,X97))) -> 技术经理 | I97: =IF(COUNT(N97,R97,V97,Z97)=0,"",MIN(N97,R97,V97,Z97)) -> 46538 | J97: =IF(COUNT(O97,S97,W97,AA97)=0,"",MAX(O97,S97,W97,AA97)) -> 46538 | K97: 46538 | P97: 技术经理 | Q97: 未开始 | R97: 46538 | S97: 46538 | AB97: =IFERROR((IF(L97<>"",IF(M97="已完成",1,IF(M97="进行中",0.5,0))*15%,0)+IF(P97<>"",IF(Q97="已完成",1,IF(Q97="进行中",0.5,0))*35%,0)+IF(T97<>"",IF(U97="已完成",1,IF(U97="进行中",0.5,0))*30%,0)+IF(X97<>"",IF(Y97="已完成",1,IF(Y97="进行中",0.5,0))*20%,0))/(IF(L97<>"",15%,0)+IF(P97<>"",35%,0)+IF(T97<>"",30%,0)+IF(X97<>"",20%,0)),0) -> 0 | AC97: =IF($A97="","",IF(G97="已完成","正常",IF(G97="暂停","暂停",IF(J97="","日期缺失",IF(J97<_数据接口!$B$7,"已延期",IF(J97<=_数据接口!$B$7+7,"临近到期","正常")))))) -> 正常 | AH97: =IF(OR($A97="",J97="",AG97=""),"",AG97-J97)
A98: T095 | D98: 上线确认 | E98: 形成上线确认单和试运行跟踪计划 | F98: MS016 | G98: =IF(OR(M98="暂停",M98="挂起",Q98="暂停",Q98="挂起",U98="暂停",U98="挂起",Y98="暂停",Y98="挂起"),"暂停",IF(COUNTA(L98,P98,T98,X98)=0,"未分配",IF(IF(L98<>"",M98="已完成",0)+IF(P98<>"",Q98="已完成",0)+IF(T98<>"",U98="已完成",0)+IF(X98<>"",Y98="已完成",0)=COUNTA(L98,P98,T98,X98),"已完成",IF(IF(L98<>"",M98="进行中",0)+IF(P98<>"",Q98="进行中",0)+IF(T98<>"",U98="进行中",0)+IF(X98<>"",Y98="进行中",0)>0,"进行中",IF(IF(L98<>"",M98="待确认",0)+IF(P98<>"",Q98="待确认",0)+IF(T98<>"",U98="待确认",0)+IF(X98<>"",Y98="待确认",0)>0,"待确认","未开始"))))) -> 未开始 | H98: =IF(L98<>"",L98,IF(P98<>"",P98,IF(T98<>"",T98,X98))) -> 项目经理 | I98: =IF(COUNT(N98,R98,V98,Z98)=0,"",MIN(N98,R98,V98,Z98)) -> 46538 | J98: =IF(COUNT(O98,S98,W98,AA98)=0,"",MAX(O98,S98,W98,AA98)) -> 46538 | K98: 46538 | L98: 项目经理 | M98: 未开始 | N98: 46538 | O98: 46538 | AB98: =IFERROR((IF(L98<>"",IF(M98="已完成",1,IF(M98="进行中",0.5,0))*15%,0)+IF(P98<>"",IF(Q98="已完成",1,IF(Q98="进行中",0.5,0))*35%,0)+IF(T98<>"",IF(U98="已完成",1,IF(U98="进行中",0.5,0))*30%,0)+IF(X98<>"",IF(Y98="已完成",1,IF(Y98="进行中",0.5,0))*20%,0))/(IF(L98<>"",15%,0)+IF(P98<>"",35%,0)+IF(T98<>"",30%,0)+IF(X98<>"",20%,0)),0) -> 0 | AC98: =IF($A98="","",IF(G98="已完成","正常",IF(G98="暂停","暂停",IF(J98="","日期缺失",IF(J98<_数据接口!$B$7,"已延期",IF(J98<=_数据接口!$B$7+7,"临近到期","正常")))))) -> 正常 | AH98: =IF(OR($A98="",J98="",AG98=""),"",AG98-J98)
A99: T096 | B99: 大集中ERP | C99: 外部系统接口实施 | D99: 设计 | E99: 大集中ERPP0接口设计工作包：接口设计说明、字段映射、异常与安全方案通过评审 | F99: MS009 | G99: =IF(OR(M99="暂停",M99="挂起",Q99="暂停",Q99="挂起",U99="暂停",U99="挂起",Y99="暂停",Y99="挂起"),"暂停",IF(COUNTA(L99,P99,T99,X99)=0,"未分配",IF(IF(L99<>"",M99="已完成",0)+IF(P99<>"",Q99="已完成",0)+IF(T99<>"",U99="已完成",0)+IF(X99<>"",Y99="已完成",0)=COUNTA(L99,P99,T99,X99),"已完成",IF(IF(L99<>"",M99="进行中",0)+IF(P99<>"",Q99="进行中",0)+IF(T99<>"",U99="进行中",0)+IF(X99<>"",Y99="进行中",0)>0,"进行中",IF(IF(L99<>"",M99="待确认",0)+IF(P99<>"",Q99="待确认",0)+IF(T99<>"",U99="待确认",0)+IF(X99<>"",Y99="待确认",0)>0,"待确认","未开始"))))) -> 未开始 | H99: =IF($A99="","",IF(L99<>"",L99,IF(P99<>"",P99,IF(T99<>"",T99,X99)))) -> 产品经理 | I99: =IF($A99="","",IF(COUNT(N99,R99,V99,Z99)=0,"",MIN(N99,R99,V99,Z99))) -> 46341 | J99: =IF($A99="","",IF(COUNT(O99,S99,W99,AA99)=0,"",MAX(O99,S99,W99,AA99))) -> 46367 | K99: 46367 | L99: 产品经理 | M99: 未开始 | N99: 46341 | O99: 46367 | AB99: =IF($A99="","",0) -> 0 | AC99: =IF($A99="","",IF(G99="已完成","正常",IF(G99="暂停","暂停",IF(J99="","日期缺失",IF(J99<_数据接口!$B$7,"已延期",IF(J99<=_数据接口!$B$7+7,"临近到期","正常")))))) -> 正常 | AE99: 实施明细见“04_系统集成管理/系统集成管理-20260918-V1.xlsx”；大集中ERP共23条P0接口 | AH99: =IF(OR($A99="",J99="",AG99=""),"",AG99-J99)
A100: T097 | C100: 外部系统接口实施 | D100: 开发 | E100: 大集中ERPP0接口开发工作包：接口代码、自测记录及部署包完成 | F100: MS010 | G100: =IF(OR(M100="暂停",M100="挂起",Q100="暂停",Q100="挂起",U100="暂停",U100="挂起",Y100="暂停",Y100="挂起"),"暂停",IF(COUNTA(L100,P100,T100,X100)=0,"未分配",IF(IF(L100<>"",M100="已完成",0)+IF(P100<>"",Q100="已完成",0)+IF(T100<>"",U100="已完成",0)+IF(X100<>"",Y100="已完成",0)=COUNTA(L100,P100,T100,X100),"已完成",IF(IF(L100<>"",M100="进行中",0)+IF(P100<>"",Q100="进行中",0)+IF(T100<>"",U100="进行中",0)+IF(X100<>"",Y100="进行中",0)>0,"进行中",IF(IF(L100<>"",M100="待确认",0)+IF(P100<>"",Q100="待确认",0)+IF(T100<>"",U100="待确认",0)+IF(X100<>"",Y100="待确认",0)>0,"待确认","未开始"))))) -> 未开始 | H100: =IF($A100="","",IF(L100<>"",L100,IF(P100<>"",P100,IF(T100<>"",T100,X100)))) -> 产品经理 | I100: =IF($A100="","",IF(COUNT(N100,R100,V100,Z100)=0,"",MIN(N100,R100,V100,Z100))) -> 46368 | J100: =IF($A100="","",IF(COUNT(O100,S100,W100,AA100)=0,"",MAX(O100,S100,W100,AA100))) -> 46430 | K100: 46430 | L100: 产品经理 | M100: 未开始 | N100: 46368 | O100: 46430 | P100: 高级开发人员-01 | Q100: 未开始 | R100: 46368 | S100: 46430 | AB100: =IF($A100="","",0) -> 0 | AC100: =IF($A100="","",IF(G100="已完成","正常",IF(G100="暂停","暂停",IF(J100="","日期缺失",IF(J100<_数据接口!$B$7,"已延期",IF(J100<=_数据接口!$B$7+7,"临近到期","正常")))))) -> 正常 | AE100: 实施明细见“04_系统集成管理/系统集成管理-20260918-V1.xlsx”；大集中ERP共23条P0接口 | AH100: =IF(OR($A100="",J100="",AG100=""),"",AG100-J100)
...

Sheet 总控筛选视图
A1: 能源行业合同全生命周期管理系统｜总控筛选视图
A2: 只读筛选视图：数据与项目总控台账公式联动；筛选、排序可在本页执行，业务数据请回项目总控台账维护。
A3: 任务ID | B3: 一级功能 | C3: 二级功能 | D3: 三级功能 | E3: 四级功能 | F3: 批次 | G3: 总体状态 | H3: 主责人 | I3: 计划开始 | J3: 计划完成 | K3: 计划上线 | L3: 业务负责人 | M3: 业务状态 | N3: 业务开始 | O3: 业务结束 | P3: 后端负责人 | Q3: 后端状态 | R3: 后端开始 | S3: 后端结束 | T3: 前端负责人 | U3: 前端状态 | V3: 前端开始 | W3: 前端结束 | X3: 测试负责人 | Y3: 测试状态 | Z3: 测试开始 | AA3: 测试结束 | AB3: 综合进度 | AC3: 延期状态 | AD3: 当前问题/阻塞 | AE3: 备注 | AF3: 迭代周 | AG3: 预测完成日期 | AH3: 基线偏差天数
A4: =IF(项目总控台账!A4="","",项目总控台账!A4) -> T001 | B4: =项目总控台账!B4 -> 可研与原业务梳理 | C4: =项目总控台账!C4 -> 可研工作启动 | D4: =项目总控台账!D4 -> 可研启动 | E4: =IF(项目总控台账!E4="","",项目总控台账!E4) -> 明确可研目标、范围与边界 | F4: =IF(项目总控台账!F4="","",项目总控台账!F4) -> MS001 | G4: =IF(项目总控台账!G4="","",项目总控台账!G4) -> 已完成 | H4: =IF(项目总控台账!H4="","",项目总控台账!H4) -> 项目经理 | I4: =IF(项目总控台账!I4="","",项目总控台账!I4) -> 46054 | J4: =IF(项目总控台账!J4="","",项目总控台账!J4) -> 46056 | K4: =IF(项目总控台账!K4="","",项目总控台账!K4) -> 46063 | L4: =IF(项目总控台账!L4="","",项目总控台账!L4) -> 项目经理 | ... AH4: =IF(项目总控台账!AH4="","",项目总控台账!AH4)
A5: =IF(项目总控台账!A5="","",项目总控台账!A5) -> T002 | B5: =项目总控台账!B4 -> 可研与原业务梳理 | C5: =项目总控台账!C4 -> 可研工作启动 | D5: =项目总控台账!D4 -> 可研启动 | E5: =IF(项目总控台账!E5="","",项目总控台账!E5) -> 建立相关方清单与访谈计划 | F5: =IF(项目总控台账!F5="","",项目总控台账!F5) -> MS001 | G5: =IF(项目总控台账!G5="","",项目总控台账!G5) -> 已完成 | H5: =IF(项目总控台账!H5="","",项目总控台账!H5) -> 产品经理 | I5: =IF(项目总控台账!I5="","",项目总控台账!I5) -> 46057 | J5: =IF(项目总控台账!J5="","",项目总控台账!J5) -> 46059 | K5: =IF(项目总控台账!K5="","",项目总控台账!K5) -> 46063 | L5: =IF(项目总控台账!L5="","",项目总控台账!L5) -> 产品经理 | ... AH5: =IF(项目总控台账!AH5="","",项目总控台账!AH5)
A6: =IF(项目总控台账!A6="","",项目总控台账!A6) -> T003 | B6: =项目总控台账!B4 -> 可研与原业务梳理 | C6: =项目总控台账!C4 -> 可研工作启动 | D6: =项目总控台账!D4 -> 可研启动 | E6: =IF(项目总控台账!E6="","",项目总控台账!E6) -> 评审并发布可研工作方案 | F6: =IF(项目总控台账!F6="","",项目总控台账!F6) -> MS001 | G6: =IF(项目总控台账!G6="","",项目总控台账!G6) -> 已完成 | H6: =IF(项目总控台账!H6="","",项目总控台账!H6) -> 项目集经理 | I6: =IF(项目总控台账!I6="","",项目总控台账!I6) -> 46060 | J6: =IF(项目总控台账!J6="","",项目总控台账!J6) -> 46063 | K6: =IF(项目总控台账!K6="","",项目总控台账!K6) -> 46063 | L6: =IF(项目总控台账!L6="","",项目总控台账!L6) -> 项目集经理 | ... AH6: =IF(项目总控台账!AH6="","",项目总控台账!AH6)
A7: =IF(项目总控台账!A7="","",项目总控台账!A7) -> T004 | B7: =项目总控台账!B4 -> 可研与原业务梳理 | C7: =项目总控台账!C7 -> 可行性研究完成 | D7: =项目总控台账!D7 -> 可行性研究 | E7: =IF(项目总控台账!E7="","",项目总控台账!E7) -> 完成业务可行性与需求价值分析 | F7: =IF(项目总控台账!F7="","",项目总控台账!F7) -> MS002 | G7: =IF(项目总控台账!G7="","",项目总控台账!G7) -> 已完成 | H7: =IF(项目总控台账!H7="","",项目总控台账!H7) -> 产品经理 | I7: =IF(项目总控台账!I7="","",项目总控台账!I7) -> 46054 | J7: =IF(项目总控台账!J7="","",项目总控台账!J7) -> 46099 | K7: =IF(项目总控台账!K7="","",项目总控台账!K7) -> 46283 | L7: =IF(项目总控台账!L7="","",项目总控台账!L7) -> 产品经理 | ... AH7: =IF(项目总控台账!AH7="","",项目总控台账!AH7)
A8: =IF(项目总控台账!A8="","",项目总控台账!A8) -> T005 | B8: =项目总控台账!B4 -> 可研与原业务梳理 | C8: =项目总控台账!C7 -> 可行性研究完成 | D8: =项目总控台账!D7 -> 可行性研究 | E8: =IF(项目总控台账!E8="","",项目总控台账!E8) -> 完成技术路线与系统边界论证 | F8: =IF(项目总控台账!F8="","",项目总控台账!F8) -> MS002 | G8: =IF(项目总控台账!G8="","",项目总控台账!G8) -> 已完成 | H8: =IF(项目总控台账!H8="","",项目总控台账!H8) -> 技术经理 | I8: =IF(项目总控台账!I8="","",项目总控台账!I8) -> 46100 | J8: =IF(项目总控台账!J8="","",项目总控台账!J8) -> 46145 | K8: =IF(项目总控台账!K8="","",项目总控台账!K8) -> 46283 | L8: =IF(项目总控台账!L8="","",项目总控台账!L8) | ... AH8: =IF(项目总控台账!AH8="","",项目总控台账!AH8)
A9: =IF(项目总控台账!A9="","",项目总控台账!A9) -> T006 | B9: =项目总控台账!B4 -> 可研与原业务梳理 | C9: =项目总控台账!C7 -> 可行性研究完成 | D9: =项目总控台账!D7 -> 可行性研究 | E9: =IF(项目总控台账!E9="","",项目总控台账!E9) -> 测算投资、成本与预期收益 | F9: =IF(项目总控台账!F9="","",项目总控台账!F9) -> MS002 | G9: =IF(项目总控台账!G9="","",项目总控台账!G9) -> 已完成 | H9: =IF(项目总控台账!H9="","",项目总控台账!H9) -> 项目经理 | I9: =IF(项目总控台账!I9="","",项目总控台账!I9) -> 46146 | J9: =IF(项目总控台账!J9="","",项目总控台账!J9) -> 46191 | K9: =IF(项目总控台账!K9="","",项目总控台账!K9) -> 46283 | L9: =IF(项目总控台账!L9="","",项目总控台账!L9) -> 项目经理 | ... AH9: =IF(项目总控台账!AH9="","",项目总控台账!AH9)
A10: =IF(项目总控台账!A10="","",项目总控台账!A10) -> T007 | B10: =项目总控台账!B4 -> 可研与原业务梳理 | C10: =项目总控台账!C7 -> 可行性研究完成 | D10: =项目总控台账!D7 -> 可行性研究 | E10: =IF(项目总控台账!E10="","",项目总控台账!E10) -> 形成实施路径、资源与风险建议 | F10: =IF(项目总控台账!F10="","",项目总控台账!F10) -> MS002 | G10: =IF(项目总控台账!G10="","",项目总控台账!G10) -> 已完成 | H10: =IF(项目总控台账!H10="","",项目总控台账!H10) -> 项目经理 | I10: =IF(项目总控台账!I10="","",项目总控台账!I10) -> 46192 | J10: =IF(项目总控台账!J10="","",项目总控台账!J10) -> 46237 | K10: =IF(项目总控台账!K10="","",项目总控台账!K10) -> 46283 | L10: =IF(项目总控台账!L10="","",项目总控台账!L10) -> 项目经理 | ... AH10: =IF(项目总控台账!AH10="","",项目总控台账!AH10)
A11: =IF(项目总控台账!A11="","",项目总控台账!A11) -> T008 | B11: =项目总控台账!B4 -> 可研与原业务梳理 | C11: =项目总控台账!C7 -> 可行性研究完成 | D11: =项目总控台账!D7 -> 可行性研究 | E11: =IF(项目总控台账!E11="","",项目总控台账!E11) -> 汇编可研报告并组织评审 | F11: =IF(项目总控台账!F11="","",项目总控台账!F11) -> MS002 | G11: =IF(项目总控台账!G11="","",项目总控台账!G11) -> 已完成 | H11: =IF(项目总控台账!H11="","",项目总控台账!H11) -> 项目经理 | I11: =IF(项目总控台账!I11="","",项目总控台账!I11) -> 46238 | J11: =IF(项目总控台账!J11="","",项目总控台账!J11) -> 46283 | K11: =IF(项目总控台账!K11="","",项目总控台账!K11) -> 46283 | L11: =IF(项目总控台账!L11="","",项目总控台账!L11) -> 项目经理 | ... AH11: =IF(项目总控台账!AH11="","",项目总控台账!AH11)
A12: =IF(项目总控台账!A12="","",项目总控台账!A12) -> T009 | B12: =项目总控台账!B4 -> 可研与原业务梳理 | C12: =项目总控台账!C12 -> 原业务梳理完成 | D12: =项目总控台账!D12 -> 现状调研 | E12: =IF(项目总控台账!E12="","",项目总控台账!E12) -> 梳理合同业务组织与职责 | F12: =IF(项目总控台账!F12="","",项目总控台账!F12) -> MS003 | G12: =IF(项目总控台账!G12="","",项目总控台账!G12) -> 已完成 | H12: =IF(项目总控台账!H12="","",项目总控台账!H12) -> 产品经理 | I12: =IF(项目总控台账!I12="","",项目总控台账!I12) -> 46064 | J12: =IF(项目总控台账!J12="","",项目总控台账!J12) -> 46091 | K12: =IF(项目总控台账!K12="","",项目总控台账!K12) -> 46203 | L12: =IF(项目总控台账!L12="","",项目总控台账!L12) -> 产品经理 | ... AH12: =IF(项目总控台账!AH12="","",项目总控台账!AH12)
A13: =IF(项目总控台账!A13="","",项目总控台账!A13) -> T010 | B13: =项目总控台账!B4 -> 可研与原业务梳理 | C13: =项目总控台账!C12 -> 原业务梳理完成 | D13: =项目总控台账!D12 -> 现状调研 | E13: =IF(项目总控台账!E13="","",项目总控台账!E13) -> 盘点合同全生命周期业务流程 | F13: =IF(项目总控台账!F13="","",项目总控台账!F13) -> MS003 | G13: =IF(项目总控台账!G13="","",项目总控台账!G13) -> 已完成 | H13: =IF(项目总控台账!H13="","",项目总控台账!H13) -> 产品经理 | I13: =IF(项目总控台账!I13="","",项目总控台账!I13) -> 46092 | J13: =IF(项目总控台账!J13="","",项目总控台账!J13) -> 46119 | K13: =IF(项目总控台账!K13="","",项目总控台账!K13) -> 46203 | L13: =IF(项目总控台账!L13="","",项目总控台账!L13) -> 产品经理 | ... AH13: =IF(项目总控台账!AH13="","",项目总控台账!AH13)
A14: =IF(项目总控台账!A14="","",项目总控台账!A14) -> T011 | B14: =项目总控台账!B4 -> 可研与原业务梳理 | C14: =项目总控台账!C12 -> 原业务梳理完成 | D14: =项目总控台账!D12 -> 现状调研 | E14: =IF(项目总控台账!E14="","",项目总控台账!E14) -> 盘点既有系统、接口与数据 | F14: =IF(项目总控台账!F14="","",项目总控台账!F14) -> MS003 | G14: =IF(项目总控台账!G14="","",项目总控台账!G14) -> 进行中 | H14: =IF(项目总控台账!H14="","",项目总控台账!H14) -> 技术经理 | I14: =IF(项目总控台账!I14="","",项目总控台账!I14) -> 46120 | J14: =IF(项目总控台账!J14="","",项目总控台账!J14) -> 46147 | K14: =IF(项目总控台账!K14="","",项目总控台账!K14) -> 46203 | L14: =IF(项目总控台账!L14="","",项目总控台账!L14) | ... AH14: =IF(项目总控台账!AH14="","",项目总控台账!AH14)
A15: =IF(项目总控台账!A15="","",项目总控台账!A15) -> T012 | B15: =项目总控台账!B4 -> 可研与原业务梳理 | C15: =项目总控台账!C12 -> 原业务梳理完成 | D15: =项目总控台账!D15 -> 问题分析 | E15: =IF(项目总控台账!E15="","",项目总控台账!E15) -> 访谈业务部门并形成痛点清单 | F15: =IF(项目总控台账!F15="","",项目总控台账!F15) -> MS003 | G15: =IF(项目总控台账!G15="","",项目总控台账!G15) -> 已完成 | H15: =IF(项目总控台账!H15="","",项目总控台账!H15) -> 产品经理 | I15: =IF(项目总控台账!I15="","",项目总控台账!I15) -> 46148 | J15: =IF(项目总控台账!J15="","",项目总控台账!J15) -> 46175 | K15: =IF(项目总控台账!K15="","",项目总控台账!K15) -> 46203 | L15: =IF(项目总控台账!L15="","",项目总控台账!L15) -> 产品经理 | ... AH15: =IF(项目总控台账!AH15="","",项目总控台账!AH15)
A16: =IF(项目总控台账!A16="","",项目总控台账!A16) -> T013 | B16: =项目总控台账!B4 -> 可研与原业务梳理 | C16: =项目总控台账!C12 -> 原业务梳理完成 | D16: =项目总控台账!D16 -> 现状基线 | E16: =IF(项目总控台账!E16="","",项目总控台账!E16) -> 确认现状流程、问题与改进机会基线 | F16: =IF(项目总控台账!F16="","",项目总控台账!F16) -> MS003 | G16: =IF(项目总控台账!G16="","",项目总控台账!G16) -> 已完成 | H16: =IF(项目总控台账!H16="","",项目总控台账!H16) -> 项目经理 | I16: =IF(项目总控台账!I16="","",项目总控台账!I16) -> 46176 | J16: =IF(项目总控台账!J16="","",项目总控台账!J16) -> 46203 | K16: =IF(项目总控台账!K16="","",项目总控台账!K16) -> 46203 | L16: =IF(项目总控台账!L16="","",项目总控台账!L16) -> 项目经理 | ... AH16: =IF(项目总控台账!AH16="","",项目总控台账!AH16)
A17: =IF(项目总控台账!A17="","",项目总控台账!A17) -> T014 | B17: =项目总控台账!B17 -> 项目规范梳理与技术架构搭建 | C17: =项目总控台账!C17 -> 项目规范基线确认 | D17: =项目总控台账!D17 -> 项目规范 | E17: =IF(项目总控台账!E17="","",项目总控台账!E17) -> 制定项目治理、会议与报告机制 | F17: =IF(项目总控台账!F17="","",项目总控台账!F17) -> MS004 | G17: =IF(项目总控台账!G17="","",项目总控台账!G17) -> 待确认 | H17: =IF(项目总控台账!H17="","",项目总控台账!H17) -> 项目经理 | I17: =IF(项目总控台账!I17="","",项目总控台账!I17) -> 46204 | J17: =IF(项目总控台账!J17="","",项目总控台账!J17) -> 46215 | K17: =IF(项目总控台账!K17="","",项目总控台账!K17) -> 46265 | L17: =IF(项目总控台账!L17="","",项目总控台账!L17) -> 项目经理 | ... AH17: =IF(项目总控台账!AH17="","",项目总控台账!AH17)
A18: =IF(项目总控台账!A18="","",项目总控台账!A18) -> T015 | B18: =项目总控台账!B17 -> 项目规范梳理与技术架构搭建 | C18: =项目总控台账!C17 -> 项目规范基线确认 | D18: =项目总控台账!D18 -> 需求规范 | E18: =IF(项目总控台账!E18="","",项目总控台账!E18) -> 制定需求分级、跟踪与变更规范 | F18: =IF(项目总控台账!F18="","",项目总控台账!F18) -> MS004 | G18: =IF(项目总控台账!G18="","",项目总控台账!G18) -> 待确认 | H18: =IF(项目总控台账!H18="","",项目总控台账!H18) -> 产品经理 | I18: =IF(项目总控台账!I18="","",项目总控台账!I18) -> 46216 | J18: =IF(项目总控台账!J18="","",项目总控台账!J18) -> 46227 | K18: =IF(项目总控台账!K18="","",项目总控台账!K18) -> 46265 | L18: =IF(项目总控台账!L18="","",项目总控台账!L18) -> 产品经理 | ... AH18: =IF(项目总控台账!AH18="","",项目总控台账!AH18)
A19: =IF(项目总控台账!A19="","",项目总控台账!A19) -> T016 | B19: =项目总控台账!B17 -> 项目规范梳理与技术架构搭建 | C19: =项目总控台账!C17 -> 项目规范基线确认 | D19: =项目总控台账!D19 -> 研发规范 | E19: =IF(项目总控台账!E19="","",项目总控台账!E19) -> 制定设计、编码与代码评审规范 | F19: =IF(项目总控台账!F19="","",项目总控台账!F19) -> MS004 | G19: =IF(项目总控台账!G19="","",项目总控台账!G19) -> 待确认 | H19: =IF(项目总控台账!H19="","",项目总控台账!H19) -> 技术经理 | I19: =IF(项目总控台账!I19="","",项目总控台账!I19) -> 46228 | J19: =IF(项目总控台账!J19="","",项目总控台账!J19) -> 46240 | K19: =IF(项目总控台账!K19="","",项目总控台账!K19) -> 46265 | L19: =IF(项目总控台账!L19="","",项目总控台账!L19) | ... AH19: =IF(项目总控台账!AH19="","",项目总控台账!AH19)
A20: =IF(项目总控台账!A20="","",项目总控台账!A20) -> T017 | B20: =项目总控台账!B17 -> 项目规范梳理与技术架构搭建 | C20: =项目总控台账!C17 -> 项目规范基线确认 | D20: =项目总控台账!D20 -> 质量规范 | E20: =IF(项目总控台账!E20="","",项目总控台账!E20) -> 制定测试、缺陷与质量门禁规范 | F20: =IF(项目总控台账!F20="","",项目总控台账!F20) -> MS004 | G20: =IF(项目总控台账!G20="","",项目总控台账!G20) -> 待确认 | H20: =IF(项目总控台账!H20="","",项目总控台账!H20) -> 高级测试人员、中级测试人员 | I20: =IF(项目总控台账!I20="","",项目总控台账!I20) -> 46241 | J20: =IF(项目总控台账!J20="","",项目总控台账!J20) -> 46252 | K20: =IF(项目总控台账!K20="","",项目总控台账!K20) -> 46265 | L20: =IF(项目总控台账!L20="","",项目总控台账!L20) | ... AH20: =IF(项目总控台账!AH20="","",项目总控台账!AH20)
A21: =IF(项目总控台账!A21="","",项目总控台账!A21) -> T018 | B21: =项目总控台账!B17 -> 项目规范梳理与技术架构搭建 | C21: =项目总控台账!C17 -> 项目规范基线确认 | D21: =项目总控台账!D21 -> 配置规范 | E21: =IF(项目总控台账!E21="","",项目总控台账!E21) -> 制定配置、发布与文档归档规范 | F21: =IF(项目总控台账!F21="","",项目总控台账!F21) -> MS004 | G21: =IF(项目总控台账!G21="","",项目总控台账!G21) -> 待确认 | H21: =IF(项目总控台账!H21="","",项目总控台账!H21) -> 配置人员 | I21: =IF(项目总控台账!I21="","",项目总控台账!I21) -> 46253 | J21: =IF(项目总控台账!J21="","",项目总控台账!J21) -> 46265 | K21: =IF(项目总控台账!K21="","",项目总控台账!K21) -> 46265 | L21: =IF(项目总控台账!L21="","",项目总控台账!L21) | ... AH21: =IF(项目总控台账!AH21="","",项目总控台账!AH21)
A22: =IF(项目总控台账!A22="","",项目总控台账!A22) -> T019 | B22: =项目总控台账!B17 -> 项目规范梳理与技术架构搭建 | C22: =项目总控台账!C22 -> 技术架构基线确认 | D22: =项目总控台账!D22 -> 应用架构 | E22: =IF(项目总控台账!E22="","",项目总控台账!E22) -> 完成系统分层、模块与服务边界设计 | F22: =IF(项目总控台账!F22="","",项目总控台账!F22) -> MS005 | G22: =IF(项目总控台账!G22="","",项目总控台账!G22) -> 待确认 | H22: =IF(项目总控台账!H22="","",项目总控台账!H22) -> 技术经理 | I22: =IF(项目总控台账!I22="","",项目总控台账!I22) -> 46204 | J22: =IF(项目总控台账!J22="","",项目总控台账!J22) -> 46218 | K22: =IF(项目总控台账!K22="","",项目总控台账!K22) -> 46295 | L22: =IF(项目总控台账!L22="","",项目总控台账!L22) | ... AH22: =IF(项目总控台账!AH22="","",项目总控台账!AH22)
A23: =IF(项目总控台账!A23="","",项目总控台账!A23) -> T020 | B23: =项目总控台账!B17 -> 项目规范梳理与技术架构搭建 | C23: =项目总控台账!C22 -> 技术架构基线确认 | D23: =项目总控台账!D23 -> 数据架构 | E23: =IF(项目总控台账!E23="","",项目总控台账!E23) -> 完成主数据、交易数据与分析数据架构 | F23: =IF(项目总控台账!F23="","",项目总控台账!F23) -> MS005 | G23: =IF(项目总控台账!G23="","",项目总控台账!G23) -> 待确认 | H23: =IF(项目总控台账!H23="","",项目总控台账!H23) -> 技术经理 | I23: =IF(项目总控台账!I23="","",项目总控台账!I23) -> 46219 | J23: =IF(项目总控台账!J23="","",项目总控台账!J23) -> 46233 | K23: =IF(项目总控台账!K23="","",项目总控台账!K23) -> 46295 | L23: =IF(项目总控台账!L23="","",项目总控台账!L23) | ... AH23: =IF(项目总控台账!AH23="","",项目总控台账!AH23)
A24: =IF(项目总控台账!A24="","",项目总控台账!A24) -> T021 | B24: =项目总控台账!B17 -> 项目规范梳理与技术架构搭建 | C24: =项目总控台账!C22 -> 技术架构基线确认 | D24: =项目总控台账!D24 -> 集成架构 | E24: =IF(项目总控台账!E24="","",项目总控台账!E24) -> 完成内部及外部接口总体架构 | F24: =IF(项目总控台账!F24="","",项目总控台账!F24) -> MS005 | G24: =IF(项目总控台账!G24="","",项目总控台账!G24) -> 待确认 | H24: =IF(项目总控台账!H24="","",项目总控台账!H24) -> 高级开发人员 | I24: =IF(项目总控台账!I24="","",项目总控台账!I24) -> 46234 | J24: =IF(项目总控台账!J24="","",项目总控台账!J24) -> 46249 | K24: =IF(项目总控台账!K24="","",项目总控台账!K24) -> 46295 | L24: =IF(项目总控台账!L24="","",项目总控台账!L24) | ... AH24: =IF(项目总控台账!AH24="","",项目总控台账!AH24)
A25: =IF(项目总控台账!A25="","",项目总控台账!A25) -> T022 | B25: =项目总控台账!B17 -> 项目规范梳理与技术架构搭建 | C25: =项目总控台账!C22 -> 技术架构基线确认 | D25: =项目总控台账!D25 -> 安全架构 | E25: =IF(项目总控台账!E25="","",项目总控台账!E25) -> 完成身份、权限、审计与数据安全设计 | F25: =IF(项目总控台账!F25="","",项目总控台账!F25) -> MS005 | G25: =IF(项目总控台账!G25="","",项目总控台账!G25) -> 待确认 | H25: =IF(项目总控台账!H25="","",项目总控台账!H25) -> 技术经理 | I25: =IF(项目总控台账!I25="","",项目总控台账!I25) -> 46250 | J25: =IF(项目总控台账!J25="","",项目总控台账!J25) -> 46264 | K25: =IF(项目总控台账!K25="","",项目总控台账!K25) -> 46295 | L25: =IF(项目总控台账!L25="","",项目总控台账!L25) | ... AH25: =IF(项目总控台账!AH25="","",项目总控台账!AH25)
A26: =IF(项目总控台账!A26="","",项目总控台账!A26) -> T023 | B26: =项目总控台账!B17 -> 项目规范梳理与技术架构搭建 | C26: =项目总控台账!C22 -> 技术架构基线确认 | D26: =项目总控台账!D26 -> 部署架构 | E26: =IF(项目总控台账!E26="","",项目总控台账!E26) -> 完成环境、网络、容灾和DevOps设计 | F26: =IF(项目总控台账!F26="","",项目总控台账!F26) -> MS005 | G26: =IF(项目总控台账!G26="","",项目总控台账!G26) -> 待确认 | H26: =IF(项目总控台账!H26="","",项目总控台账!H26) -> 配置人员 | I26: =IF(项目总控台账!I26="","",项目总控台账!I26) -> 46265 | J26: =IF(项目总控台账!J26="","",项目总控台账!J26) -> 46279 | K26: =IF(项目总控台账!K26="","",项目总控台账!K26) -> 46295 | L26: =IF(项目总控台账!L26="","",项目总控台账!L26) | ... AH26: =IF(项目总控台账!AH26="","",项目总控台账!AH26)
A27: =IF(项目总控台账!A27="","",项目总控台账!A27) -> T024 | B27: =项目总控台账!B17 -> 项目规范梳理与技术架构搭建 | C27: =项目总控台账!C22 -> 技术架构基线确认 | D27: =项目总控台账!D27 -> 架构评审 | E27: =IF(项目总控台账!E27="","",项目总控台账!E27) -> 汇编总体技术架构并完成基线评审 | F27: =IF(项目总控台账!F27="","",项目总控台账!F27) -> MS005 | G27: =IF(项目总控台账!G27="","",项目总控台账!G27) -> 进行中 | H27: =IF(项目总控台账!H27="","",项目总控台账!H27) -> 技术经理 | I27: =IF(项目总控台账!I27="","",项目总控台账!I27) -> 46280 | J27: =IF(项目总控台账!J27="","",项目总控台账!J27) -> 46295 | K27: =IF(项目总控台账!K27="","",项目总控台账!K27) -> 46295 | L27: =IF(项目总控台账!L27="","",项目总控台账!L27) | ... AH27: =IF(项目总控台账!AH27="","",项目总控台账!AH27)
A28: =IF(项目总控台账!A28="","",项目总控台账!A28) -> T025 | B28: =项目总控台账!B17 -> 项目规范梳理与技术架构搭建 | C28: =项目总控台账!C28 -> 外部产品POC验证完成 | D28: =项目总控台账!D28 -> POC准备 | E28: =IF(项目总控台账!E28="","",项目总控台账!E28) -> 编制CA、电子文档、BI报表POC方案与评分标准 | F28: =IF(项目总控台账!F28="","",项目总控台账!F28) -> MS017 | G28: =IF(项目总控台账!G28="","",项目总控台账!G28) -> 待确认 | H28: =IF(项目总控台账!H28="","",项目总控台账!H28) -> 技术经理 | I28: =IF(项目总控台账!I28="","",项目总控台账!I28) -> 46249 | J28: =IF(项目总控台账!J28="","",项目总控台账!J28) -> 46253 | K28: =IF(项目总控台账!K28="","",项目总控台账!K28) -> 46290 | L28: =IF(项目总控台账!L28="","",项目总控台账!L28) | ... AH28: =IF(项目总控台账!AH28="","",项目总控台账!AH28)
A29: =IF(项目总控台账!A29="","",项目总控台账!A29) -> T026 | B29: =项目总控台账!B17 -> 项目规范梳理与技术架构搭建 | C29: =项目总控台账!C28 -> 外部产品POC验证完成 | D29: =项目总控台账!D29 -> CA验证 | E29: =IF(项目总控台账!E29="","",项目总控台账!E29) -> 验证证书签发、身份认证和证书管理 | F29: =IF(项目总控台账!F29="","",项目总控台账!F29) -> MS017 | G29: =IF(项目总控台账!G29="","",项目总控台账!G29) -> 待确认 | H29: =IF(项目总控台账!H29="","",项目总控台账!H29) -> 高级开发人员 | I29: =IF(项目总控台账!I29="","",项目总控台账!I29) -> 46254 | J29: =IF(项目总控台账!J29="","",项目总控台账!J29) -> 46258 | K29: =IF(项目总控台账!K29="","",项目总控台账!K29) -> 46290 | L29: =IF(项目总控台账!L29="","",项目总控台账!L29) | ... AH29: =IF(项目总控台账!AH29="","",项目总控台账!AH29)
A30: =IF(项目总控台账!A30="","",项目总控台账!A30) -> T027 | B30: =项目总控台账!B17 -> 项目规范梳理与技术架构搭建 | C30: =项目总控台账!C28 -> 外部产品POC验证完成 | D30: =项目总控台账!D29 -> CA验证 | E30: =IF(项目总控台账!E30="","",项目总控台账!E30) -> 验证电子签名、验签、时间戳和审计追溯 | F30: =IF(项目总控台账!F30="","",项目总控台账!F30) -> MS017 | G30: =IF(项目总控台账!G30="","",项目总控台账!G30) -> 待确认 | H30: =IF(项目总控台账!H30="","",项目总控台账!H30) -> 高级测试人员、中级测试人员 | I30: =IF(项目总控台账!I30="","",项目总控台账!I30) -> 46259 | J30: =IF(项目总控台账!J30="","",项目总控台账!J30) -> 46263 | K30: =IF(项目总控台账!K30="","",项目总控台账!K30) -> 46290 | L30: =IF(项目总控台账!L30="","",项目总控台账!L30) | ... AH30: =IF(项目总控台账!AH30="","",项目总控台账!AH30)
A31: =IF(项目总控台账!A31="","",项目总控台账!A31) -> T028 | B31: =项目总控台账!B17 -> 项目规范梳理与技术架构搭建 | C31: =项目总控台账!C28 -> 外部产品POC验证完成 | D31: =项目总控台账!D31 -> 电子文档验证 | E31: =IF(项目总控台账!E31="","",项目总控台账!E31) -> 验证模板生成、在线预览和格式转换 | F31: =IF(项目总控台账!F31="","",项目总控台账!F31) -> MS017 | G31: =IF(项目总控台账!G31="","",项目总控台账!G31) -> 待确认 | H31: =IF(项目总控台账!H31="","",项目总控台账!H31) -> 中级开发人员 | I31: =IF(项目总控台账!I31="","",项目总控台账!I31) -> 46264 | J31: =IF(项目总控台账!J31="","",项目总控台账!J31) -> 46269 | K31: =IF(项目总控台账!K31="","",项目总控台账!K31) -> 46290 | L31: =IF(项目总控台账!L31="","",项目总控台账!L31) | ... AH31: =IF(项目总控台账!AH31="","",项目总控台账!AH31)
A32: =IF(项目总控台账!A32="","",项目总控台账!A32) -> T029 | B32: =项目总控台账!B17 -> 项目规范梳理与技术架构搭建 | C32: =项目总控台账!C28 -> 外部产品POC验证完成 | D32: =项目总控台账!D31 -> 电子文档验证 | E32: =IF(项目总控台账!E32="","",项目总控台账!E32) -> 验证水印、权限控制、归档和大文件性能 | F32: =IF(项目总控台账!F32="","",项目总控台账!F32) -> MS017 | G32: =IF(项目总控台账!G32="","",项目总控台账!G32) -> 待确认 | H32: =IF(项目总控台账!H32="","",项目总控台账!H32) -> 高级测试人员、中级测试人员 | I32: =IF(项目总控台账!I32="","",项目总控台账!I32) -> 46270 | J32: =IF(项目总控台账!J32="","",项目总控台账!J32) -> 46274 | K32: =IF(项目总控台账!K32="","",项目总控台账!K32) -> 46290 | L32: =IF(项目总控台账!L32="","",项目总控台账!L32) | ... AH32: =IF(项目总控台账!AH32="","",项目总控台账!AH32)
A33: =IF(项目总控台账!A33="","",项目总控台账!A33) -> T030 | B33: =项目总控台账!B17 -> 项目规范梳理与技术架构搭建 | C33: =项目总控台账!C28 -> 外部产品POC验证完成 | D33: =项目总控台账!D33 -> BI报表验证 | E33: =IF(项目总控台账!E33="","",项目总控台账!E33) -> 验证数据接入、指标模型和经营报表 | F33: =IF(项目总控台账!F33="","",项目总控台账!F33) -> MS017 | G33: =IF(项目总控台账!G33="","",项目总控台账!G33) -> 待确认 | H33: =IF(项目总控台账!H33="","",项目总控台账!H33) -> 高级开发人员 | I33: =IF(项目总控台账!I33="","",项目总控台账!I33) -> 46275 | J33: =IF(项目总控台账!J33="","",项目总控台账!J33) -> 46279 | K33: =IF(项目总控台账!K33="","",项目总控台账!K33) -> 46290 | L33: =IF(项目总控台账!L33="","",项目总控台账!L33) | ... AH33: =IF(项目总控台账!AH33="","",项目总控台账!AH33)
A34: =IF(项目总控台账!A34="","",项目总控台账!A34) -> T031 | B34: =项目总控台账!B17 -> 项目规范梳理与技术架构搭建 | C34: =项目总控台账!C28 -> 外部产品POC验证完成 | D34: =项目总控台账!D33 -> BI报表验证 | E34: =IF(项目总控台账!E34="","",项目总控台账!E34) -> 验证权限、钻取、导出和查询性能 | F34: =IF(项目总控台账!F34="","",项目总控台账!F34) -> MS017 | G34: =IF(项目总控台账!G34="","",项目总控台账!G34) -> 进行中 | H34: =IF(项目总控台账!H34="","",项目总控台账!H34) -> 高级测试人员、中级测试人员 | I34: =IF(项目总控台账!I34="","",项目总控台账!I34) -> 46280 | J34: =IF(项目总控台账!J34="","",项目总控台账!J34) -> 46284 | K34: =IF(项目总控台账!K34="","",项目总控台账!K34) -> 46290 | L34: =IF(项目总控台账!L34="","",项目总控台账!L34) | ... AH34: =IF(项目总控台账!AH34="","",项目总控台账!AH34)
A35: =IF(项目总控台账!A35="","",项目总控台账!A35) -> T032 | B35: =项目总控台账!B17 -> 项目规范梳理与技术架构搭建 | C35: =项目总控台账!C28 -> 外部产品POC验证完成 | D35: =项目总控台账!D35 -> POC结论 | E35: =IF(项目总控台账!E35="","",项目总控台账!E35) -> 汇总问题清单、适配结论和产品选型建议 | F35: =IF(项目总控台账!F35="","",项目总控台账!F35) -> MS017 | G35: =IF(项目总控台账!G35="","",项目总控台账!G35) -> 未开始 | H35: =IF(项目总控台账!H35="","",项目总控台账!H35) -> 项目经理 | I35: =IF(项目总控台账!I35="","",项目总控台账!I35) -> 46285 | J35: =IF(项目总控台账!J35="","",项目总控台账!J35) -> 46290 | K35: =IF(项目总控台账!K35="","",项目总控台账!K35) -> 46290 | L35: =IF(项目总控台账!L35="","",项目总控台账!L35) -> 项目经理 | ... AH35: =IF(项目总控台账!AH35="","",项目总控台账!AH35)
A36: =IF(项目总控台账!A36="","",项目总控台账!A36) -> T033 | B36: =项目总控台账!B36 -> 正式启动准备 | C36: =项目总控台账!C36 -> 启动准备评审通过 | D36: =项目总控台账!D36 -> 启动准备 | E36: =IF(项目总控台账!E36="","",项目总控台账!E36) -> 编制并审批项目章程 | F36: =IF(项目总控台账!F36="","",项目总控台账!F36) -> MS006 | G36: =IF(项目总控台账!G36="","",项目总控台账!G36) -> 未开始 | H36: =IF(项目总控台账!H36="","",项目总控台账!H36) -> 项目集经理 | I36: =IF(项目总控台账!I36="","",项目总控台账!I36) -> 46296 | J36: =IF(项目总控台账!J36="","",项目总控台账!J36) -> 46297 | K36: =IF(项目总控台账!K36="","",项目总控台账!K36) -> 46311 | L36: =IF(项目总控台账!L36="","",项目总控台账!L36) -> 项目集经理 | ... AH36: =IF(项目总控台账!AH36="","",项目总控台账!AH36)
A37: =IF(项目总控台账!A37="","",项目总控台账!A37) -> T034 | B37: =项目总控台账!B36 -> 正式启动准备 | C37: =项目总控台账!C36 -> 启动准备评审通过 | D37: =项目总控台账!D36 -> 启动准备 | E37: =IF(项目总控台账!E37="","",项目总控台账!E37) -> 编制范围、里程碑和主进度计划 | F37: =IF(项目总控台账!F37="","",项目总控台账!F37) -> MS006 | G37: =IF(项目总控台账!G37="","",项目总控台账!G37) -> 未开始 | H37: =IF(项目总控台账!H37="","",项目总控台账!H37) -> 项目经理 | I37: =IF(项目总控台账!I37="","",项目总控台账!I37) -> 46298 | J37: =IF(项目总控台账!J37="","",项目总控台账!J37) -> 46300 | K37: =IF(项目总控台账!K37="","",项目总控台账!K37) -> 46311 | L37: =IF(项目总控台账!L37="","",项目总控台账!L37) -> 项目经理 | ... AH37: =IF(项目总控台账!AH37="","",项目总控台账!AH37)
A38: =IF(项目总控台账!A38="","",项目总控台账!A38) -> T035 | B38: =项目总控台账!B36 -> 正式启动准备 | C38: =项目总控台账!C36 -> 启动准备评审通过 | D38: =项目总控台账!D38 -> 组织准备 | E38: =IF(项目总控台账!E38="","",项目总控台账!E38) -> 建立项目组织、RACI与沟通机制 | F38: =IF(项目总控台账!F38="","",项目总控台账!F38) -> MS006 | G38: =IF(项目总控台账!G38="","",项目总控台账!G38) -> 未开始 | H38: =IF(项目总控台账!H38="","",项目总控台账!H38) -> 项目经理 | I38: =IF(项目总控台账!I38="","",项目总控台账!I38) -> 46301 | J38: =IF(项目总控台账!J38="","",项目总控台账!J38) -> 46303 | K38: =IF(项目总控台账!K38="","",项目总控台账!K38) -> 46311 | L38: =IF(项目总控台账!L38="","",项目总控台账!L38) -> 项目经理 | ... AH38: =IF(项目总控台账!AH38="","",项目总控台账!AH38)
A39: =IF(项目总控台账!A39="","",项目总控台账!A39) -> T036 | B39: =项目总控台账!B36 -> 正式启动准备 | C39: =项目总控台账!C36 -> 启动准备评审通过 | D39: =项目总控台账!D39 -> 资源准备 | E39: =IF(项目总控台账!E39="","",项目总控台账!E39) -> 确认30人团队投入与阶段资源计划 | F39: =IF(项目总控台账!F39="","",项目总控台账!F39) -> MS006 | G39: =IF(项目总控台账!G39="","",项目总控台账!G39) -> 未开始 | H39: =IF(项目总控台账!H39="","",项目总控台账!H39) -> 项目集经理 | I39: =IF(项目总控台账!I39="","",项目总控台账!I39) -> 46304 | J39: =IF(项目总控台账!J39="","",项目总控台账!J39) -> 46305 | K39: =IF(项目总控台账!K39="","",项目总控台账!K39) -> 46311 | L39: =IF(项目总控台账!L39="","",项目总控台账!L39) -> 项目集经理 | ... AH39: =IF(项目总控台账!AH39="","",项目总控台账!AH39)
A40: =IF(项目总控台账!A40="","",项目总控台账!A40) -> T037 | B40: =项目总控台账!B36 -> 正式启动准备 | C40: =项目总控台账!C36 -> 启动准备评审通过 | D40: =项目总控台账!D40 -> 治理准备 | E40: =IF(项目总控台账!E40="","",项目总控台账!E40) -> 建立风险、问题、变更和决策台账 | F40: =IF(项目总控台账!F40="","",项目总控台账!F40) -> MS006 | G40: =IF(项目总控台账!G40="","",项目总控台账!G40) -> 未开始 | H40: =IF(项目总控台账!H40="","",项目总控台账!H40) -> 项目经理 | I40: =IF(项目总控台账!I40="","",项目总控台账!I40) -> 46306 | J40: =IF(项目总控台账!J40="","",项目总控台账!J40) -> 46308 | K40: =IF(项目总控台账!K40="","",项目总控台账!K40) -> 46311 | L40: =IF(项目总控台账!L40="","",项目总控台账!L40) -> 项目经理 | ... AH40: =IF(项目总控台账!AH40="","",项目总控台账!AH40)
A41: =IF(项目总控台账!A41="","",项目总控台账!A41) -> T038 | B41: =项目总控台账!B36 -> 正式启动准备 | C41: =项目总控台账!C36 -> 启动准备评审通过 | D41: =项目总控台账!D41 -> 启动门禁 | E41: =IF(项目总控台账!E41="","",项目总控台账!E41) -> 完成启动条件检查与评审 | F41: =IF(项目总控台账!F41="","",项目总控台账!F41) -> MS006 | G41: =IF(项目总控台账!G41="","",项目总控台账!G41) -> 未开始 | H41: =IF(项目总控台账!H41="","",项目总控台账!H41) -> 项目集经理 | I41: =IF(项目总控台账!I41="","",项目总控台账!I41) -> 46309 | J41: =IF(项目总控台账!J41="","",项目总控台账!J41) -> 46311 | K41: =IF(项目总控台账!K41="","",项目总控台账!K41) -> 46311 | L41: =IF(项目总控台账!L41="","",项目总控台账!L41) -> 项目集经理 | ... AH41: =IF(项目总控台账!AH41="","",项目总控台账!AH41)
A42: =IF(项目总控台账!A42="","",项目总控台账!A42) -> T039 | B42: =项目总控台账!B42 -> 正式实施与上线准备 | C42: =项目总控台账!C42 -> 项目正式启动 | D42: =项目总控台账!D42 -> 正式启动 | E42: =IF(项目总控台账!E42="","",项目总控台账!E42) -> 准备启动会材料与项目目标宣贯 | F42: =IF(项目总控台账!F42="","",项目总控台账!F42) -> MS007 | G42: =IF(项目总控台账!G42="","",项目总控台账!G42) -> 未开始 | H42: =IF(项目总控台账!H42="","",项目总控台账!H42) -> 项目经理 | I42: =IF(项目总控台账!I42="","",项目总控台账!I42) -> 46315 | J42: =IF(项目总控台账!J42="","",项目总控台账!J42) -> 46315 | K42: =IF(项目总控台账!K42="","",项目总控台账!K42) -> 46315 | L42: =IF(项目总控台账!L42="","",项目总控台账!L42) -> 项目经理 | ... AH42: =IF(项目总控台账!AH42="","",项目总控台账!AH42)
A43: =IF(项目总控台账!A43="","",项目总控台账!A43) -> T040 | B43: =项目总控台账!B42 -> 正式实施与上线准备 | C43: =项目总控台账!C42 -> 项目正式启动 | D43: =项目总控台账!D42 -> 正式启动 | E43: =IF(项目总控台账!E43="","",项目总控台账!E43) -> 召开项目启动会并确认职责 | F43: =IF(项目总控台账!F43="","",项目总控台账!F43) -> MS007 | G43: =IF(项目总控台账!G43="","",项目总控台账!G43) -> 未开始 | H43: =IF(项目总控台账!H43="","",项目总控台账!H43) -> 项目集经理 | I43: =IF(项目总控台账!I43="","",项目总控台账!I43) -> 46315 | J43: =IF(项目总控台账!J43="","",项目总控台账!J43) -> 46315 | K43: =IF(项目总控台账!K43="","",项目总控台账!K43) -> 46315 | L43: =IF(项目总控台账!L43="","",项目总控台账!L43) -> 项目集经理 | ... AH43: =IF(项目总控台账!AH43="","",项目总控台账!AH43)
A44: =IF(项目总控台账!A44="","",项目总控台账!A44) -> T041 | B44: =项目总控台账!B42 -> 正式实施与上线准备 | C44: =项目总控台账!C42 -> 项目正式启动 | D44: =项目总控台账!D42 -> 正式启动 | E44: =IF(项目总控台账!E44="","",项目总控台账!E44) -> 发布会议纪要、行动项和基准计划 | F44: =IF(项目总控台账!F44="","",项目总控台账!F44) -> MS007 | G44: =IF(项目总控台账!G44="","",项目总控台账!G44) -> 未开始 | H44: =IF(项目总控台账!H44="","",项目总控台账!H44) -> 项目经理 | I44: =IF(项目总控台账!I44="","",项目总控台账!I44) -> 46315 | J44: =IF(项目总控台账!J44="","",项目总控台账!J44) -> 46315 | K44: =IF(项目总控台账!K44="","",项目总控台账!K44) -> 46315 | L44: =IF(项目总控台账!L44="","",项目总控台账!L44) -> 项目经理 | ... AH44: =IF(项目总控台账!AH44="","",项目总控台账!AH44)
A45: =IF(项目总控台账!A45="","",项目总控台账!A45) -> T042 | B45: =项目总控台账!B42 -> 正式实施与上线准备 | C45: =项目总控台账!C45 -> 需求基线确认 | D45: =项目总控台账!D45 -> 需求调研 | E45: =IF(项目总控台账!E45="","",项目总控台账!E45) -> 开展业务场景与用户需求工作坊 | F45: =IF(项目总控台账!F45="","",项目总控台账!F45) -> MS008 | G45: =IF(项目总控台账!G45="","",项目总控台账!G45) -> 未开始 | H45: =IF(项目总控台账!H45="","",项目总控台账!H45) -> 产品经理 | I45: =IF(项目总控台账!I45="","",项目总控台账!I45) -> 46316 | J45: =IF(项目总控台账!J45="","",项目总控台账!J45) -> 46321 | K45: =IF(项目总控台账!K45="","",项目总控台账!K45) -> 46356 | L45: =IF(项目总控台账!L45="","",项目总控台账!L45) -> 产品经理 | ... AH45: =IF(项目总控台账!AH45="","",项目总控台账!AH45)
A46: =IF(项目总控台账!A46="","",项目总控台账!A46) -> T043 | B46: =项目总控台账!B42 -> 正式实施与上线准备 | C46: =项目总控台账!C45 -> 需求基线确认 | D46: =项目总控台账!D46 -> 范围管理 | E46: =IF(项目总控台账!E46="","",项目总控台账!E46) -> 形成需求清单并完成P0/P1/P2分级 | F46: =IF(项目总控台账!F46="","",项目总控台账!F46) -> MS008 | G46: =IF(项目总控台账!G46="","",项目总控台账!G46) -> 未开始 | H46: =IF(项目总控台账!H46="","",项目总控台账!H46) -> 产品经理 | I46: =IF(项目总控台账!I46="","",项目总控台账!I46) -> 46322 | J46: =IF(项目总控台账!J46="","",项目总控台账!J46) -> 46328 | K46: =IF(项目总控台账!K46="","",项目总控台账!K46) -> 46356 | L46: =IF(项目总控台账!L46="","",项目总控台账!L46) -> 产品经理 | ... AH46: =IF(项目总控台账!AH46="","",项目总控台账!AH46)
A47: =IF(项目总控台账!A47="","",项目总控台账!A47) -> T044 | B47: =项目总控台账!B42 -> 正式实施与上线准备 | C47: =项目总控台账!C45 -> 需求基线确认 | D47: =项目总控台账!D47 -> 需求分析 | E47: =IF(项目总控台账!E47="","",项目总控台账!E47) -> 设计目标流程、用例和业务规则 | F47: =IF(项目总控台账!F47="","",项目总控台账!F47) -> MS008 | G47: =IF(项目总控台账!G47="","",项目总控台账!G47) -> 未开始 | H47: =IF(项目总控台账!H47="","",项目总控台账!H47) -> 产品经理 | I47: =IF(项目总控台账!I47="","",项目总控台账!I47) -> 46329 | J47: =IF(项目总控台账!J47="","",项目总控台账!J47) -> 46335 | K47: =IF(项目总控台账!K47="","",项目总控台账!K47) -> 46356 | L47: =IF(项目总控台账!L47="","",项目总控台账!L47) -> 产品经理 | ... AH47: =IF(项目总控台账!AH47="","",项目总控台账!AH47)
A48: =IF(项目总控台账!A48="","",项目总控台账!A48) -> T045 | B48: =项目总控台账!B42 -> 正式实施与上线准备 | C48: =项目总控台账!C45 -> 需求基线确认 | D48: =项目总控台账!D48 -> 原型设计 | E48: =IF(项目总控台账!E48="","",项目总控台账!E48) -> 完成核心功能原型和交互确认 | F48: =IF(项目总控台账!F48="","",项目总控台账!F48) -> MS008 | G48: =IF(项目总控台账!G48="","",项目总控台账!G48) -> 未开始 | H48: =IF(项目总控台账!H48="","",项目总控台账!H48) -> 美工 | I48: =IF(项目总控台账!I48="","",项目总控台账!I48) -> 46336 | J48: =IF(项目总控台账!J48="","",项目总控台账!J48) -> 46342 | K48: =IF(项目总控台账!K48="","",项目总控台账!K48) -> 46356 | L48: =IF(项目总控台账!L48="","",项目总控台账!L48) | ... AH48: =IF(项目总控台账!AH48="","",项目总控台账!AH48)
A49: =IF(项目总控台账!A49="","",项目总控台账!A49) -> T046 | B49: =项目总控台账!B42 -> 正式实施与上线准备 | C49: =项目总控台账!C45 -> 需求基线确认 | D49: =项目总控台账!D49 -> 非功能需求 | E49: =IF(项目总控台账!E49="","",项目总控台账!E49) -> 明确性能、安全、可用性和合规要求 | F49: =IF(项目总控台账!F49="","",项目总控台账!F49) -> MS008 | G49: =IF(项目总控台账!G49="","",项目总控台账!G49) -> 未开始 | H49: =IF(项目总控台账!H49="","",项目总控台账!H49) -> 技术经理 | I49: =IF(项目总控台账!I49="","",项目总控台账!I49) -> 46343 | J49: =IF(项目总控台账!J49="","",项目总控台账!J49) -> 46349 | K49: =IF(项目总控台账!K49="","",项目总控台账!K49) -> 46356 | L49: =IF(项目总控台账!L49="","",项目总控台账!L49) | ... AH49: =IF(项目总控台账!AH49="","",项目总控台账!AH49)
A50: =IF(项目总控台账!A50="","",项目总控台账!A50) -> T047 | B50: =项目总控台账!B42 -> 正式实施与上线准备 | C50: =项目总控台账!C45 -> 需求基线确认 | D50: =项目总控台账!D50 -> 需求基线 | E50: =IF(项目总控台账!E50="","",项目总控台账!E50) -> 建立需求跟踪矩阵并完成基线评审 | F50: =IF(项目总控台账!F50="","",项目总控台账!F50) -> MS008 | G50: =IF(项目总控台账!G50="","",项目总控台账!G50) -> 未开始 | H50: =IF(项目总控台账!H50="","",项目总控台账!H50) -> 项目经理 | I50: =IF(项目总控台账!I50="","",项目总控台账!I50) -> 46350 | J50: =IF(项目总控台账!J50="","",项目总控台账!J50) -> 46356 | K50: =IF(项目总控台账!K50="","",项目总控台账!K50) -> 46356 | L50: =IF(项目总控台账!L50="","",项目总控台账!L50) -> 项目经理 | ... AH50: =IF(项目总控台账!AH50="","",项目总控台账!AH50)
A51: =IF(项目总控台账!A51="","",项目总控台账!A51) -> T048 | B51: =项目总控台账!B42 -> 正式实施与上线准备 | C51: =项目总控台账!C51 -> 详细设计完成 | D51: =项目总控台账!D51 -> 详细设计 | E51: =IF(项目总控台账!E51="","",项目总控台账!E51) -> 完成核心模块和服务详细设计 | F51: =IF(项目总控台账!F51="","",项目总控台账!F51) -> MS009 | G51: =IF(项目总控台账!G51="","",项目总控台账!G51) -> 未开始 | H51: =IF(项目总控台账!H51="","",项目总控台账!H51) -> 技术经理 | I51: =IF(项目总控台账!I51="","",项目总控台账!I51) -> 46341 | J51: =IF(项目总控台账!J51="","",项目总控台账!J51) -> 46347 | K51: =IF(项目总控台账!K51="","",项目总控台账!K51) -> 46387 | L51: =IF(项目总控台账!L51="","",项目总控台账!L51) | ... AH51: =IF(项目总控台账!AH51="","",项目总控台账!AH51)
A52: =IF(项目总控台账!A52="","",项目总控台账!A52) -> T049 | B52: =项目总控台账!B42 -> 正式实施与上线准备 | C52: =项目总控台账!C51 -> 详细设计完成 | D52: =项目总控台账!D52 -> 数据设计 | E52: =IF(项目总控台账!E52="","",项目总控台账!E52) -> 完成数据模型、字典和数据质量规则 | F52: =IF(项目总控台账!F52="","",项目总控台账!F52) -> MS009 | G52: =IF(项目总控台账!G52="","",项目总控台账!G52) -> 未开始 | H52: =IF(项目总控台账!H52="","",项目总控台账!H52) -> 高级开发人员 | I52: =IF(项目总控台账!I52="","",项目总控台账!I52) -> 46348 | J52: =IF(项目总控台账!J52="","",项目总控台账!J52) -> 46355 | K52: =IF(项目总控台账!K52="","",项目总控台账!K52) -> 46387 | L52: =IF(项目总控台账!L52="","",项目总控台账!L52) | ... AH52: =IF(项目总控台账!AH52="","",项目总控台账!AH52)
A53: =IF(项目总控台账!A53="","",项目总控台账!A53) -> T050 | B53: =项目总控台账!B42 -> 正式实施与上线准备 | C53: =项目总控台账!C51 -> 详细设计完成 | D53: =项目总控台账!D53 -> 接口设计 | E53: =IF(项目总控台账!E53="","",项目总控台账!E53) -> 完成内部与外部接口详细设计 | F53: =IF(项目总控台账!F53="","",项目总控台账!F53) -> MS009 | G53: =IF(项目总控台账!G53="","",项目总控台账!G53) -> 未开始 | H53: =IF(项目总控台账!H53="","",项目总控台账!H53) -> 高级开发人员 | I53: =IF(项目总控台账!I53="","",项目总控台账!I53) -> 46356 | J53: =IF(项目总控台账!J53="","",项目总控台账!J53) -> 46363 | K53: =IF(项目总控台账!K53="","",项目总控台账!K53) -> 46387 | L53: =IF(项目总控台账!L53="","",项目总控台账!L53) | ... AH53: =IF(项目总控台账!AH53="","",项目总控台账!AH53)
A54: =IF(项目总控台账!A54="","",项目总控台账!A54) -> T051 | B54: =项目总控台账!B42 -> 正式实施与上线准备 | C54: =项目总控台账!C51 -> 详细设计完成 | D54: =项目总控台账!D54 -> 安全设计 | E54: =IF(项目总控台账!E54="","",项目总控台账!E54) -> 完成角色权限、数据权限和审计设计 | F54: =IF(项目总控台账!F54="","",项目总控台账!F54) -> MS009 | G54: =IF(项目总控台账!G54="","",项目总控台账!G54) -> 未开始 | H54: =IF(项目总控台账!H54="","",项目总控台账!H54) -> 技术经理 | I54: =IF(项目总控台账!I54="","",项目总控台账!I54) -> 46364 | J54: =IF(项目总控台账!J54="","",项目总控台账!J54) -> 46371 | K54: =IF(项目总控台账!K54="","",项目总控台账!K54) -> 46387 | L54: =IF(项目总控台账!L54="","",项目总控台账!L54) | ... AH54: =IF(项目总控台账!AH54="","",项目总控台账!AH54)
A55: =IF(项目总控台账!A55="","",项目总控台账!A55) -> T052 | B55: =项目总控台账!B42 -> 正式实施与上线准备 | C55: =项目总控台账!C51 -> 详细设计完成 | D55: =项目总控台账!D55 -> 界面设计 | E55: =IF(项目总控台账!E55="","",项目总控台账!E55) -> 完成核心页面视觉与交互设计 | F55: =IF(项目总控台账!F55="","",项目总控台账!F55) -> MS009 | G55: =IF(项目总控台账!G55="","",项目总控台账!G55) -> 未开始 | H55: =IF(项目总控台账!H55="","",项目总控台账!H55) -> 美工 | I55: =IF(项目总控台账!I55="","",项目总控台账!I55) -> 46372 | J55: =IF(项目总控台账!J55="","",项目总控台账!J55) -> 46379 | K55: =IF(项目总控台账!K55="","",项目总控台账!K55) -> 46387 | L55: =IF(项目总控台账!L55="","",项目总控台账!L55) | ... AH55: =IF(项目总控台账!AH55="","",项目总控台账!AH55)
A56: =IF(项目总控台账!A56="","",项目总控台账!A56) -> T053 | B56: =项目总控台账!B42 -> 正式实施与上线准备 | C56: =项目总控台账!C51 -> 详细设计完成 | D56: =项目总控台账!D56 -> 设计评审 | E56: =IF(项目总控台账!E56="","",项目总控台账!E56) -> 完成设计走查、问题关闭和版本基线 | F56: =IF(项目总控台账!F56="","",项目总控台账!F56) -> MS009 | G56: =IF(项目总控台账!G56="","",项目总控台账!G56) -> 未开始 | H56: =IF(项目总控台账!H56="","",项目总控台账!H56) -> 技术经理 | I56: =IF(项目总控台账!I56="","",项目总控台账!I56) -> 46380 | J56: =IF(项目总控台账!J56="","",项目总控台账!J56) -> 46387 | K56: =IF(项目总控台账!K56="","",项目总控台账!K56) -> 46387 | L56: =IF(项目总控台账!L56="","",项目总控台账!L56) | ... AH56: =IF(项目总控台账!AH56="","",项目总控台账!AH56)
A57: =IF(项目总控台账!A57="","",项目总控台账!A57) -> T054 | B57: =项目总控台账!B42 -> 正式实施与上线准备 | C57: =项目总控台账!C57 -> 核心功能开发完成 | D57: =项目总控台账!D57 -> 基础平台 | E57: =IF(项目总控台账!E57="","",项目总控台账!E57) -> 搭建项目工程、公共组件和持续集成 | F57: =IF(项目总控台账!F57="","",项目总控台账!F57) -> MS010 | G57: =IF(项目总控台账!G57="","",项目总控台账!G57) -> 未开始 | H57: =IF(项目总控台账!H57="","",项目总控台账!H57) -> 高级开发人员 | I57: =IF(项目总控台账!I57="","",项目总控台账!I57) -> 46357 | J57: =IF(项目总控台账!J57="","",项目总控台账!J57) -> 46367 | K57: =IF(项目总控台账!K57="","",项目总控台账!K57) -> 46461 | L57: =IF(项目总控台账!L57="","",项目总控台账!L57) | ... AH57: =IF(项目总控台账!AH57="","",项目总控台账!AH57)
A58: =IF(项目总控台账!A58="","",项目总控台账!A58) -> T055 | B58: =项目总控台账!B42 -> 正式实施与上线准备 | C58: =项目总控台账!C57 -> 核心功能开发完成 | D58: =项目总控台账!D58 -> 合同模板 | E58: =IF(项目总控台账!E58="","",项目总控台账!E58) -> 开发合同模板、范本和条款库管理 | F58: =IF(项目总控台账!F58="","",项目总控台账!F58) -> MS010 | G58: =IF(项目总控台账!G58="","",项目总控台账!G58) -> 未开始 | H58: =IF(项目总控台账!H58="","",项目总控台账!H58) -> 中级开发人员 | I58: =IF(项目总控台账!I58="","",项目总控台账!I58) -> 46368 | J58: =IF(项目总控台账!J58="","",项目总控台账!J58) -> 46379 | K58: =IF(项目总控台账!K58="","",项目总控台账!K58) -> 46461 | L58: =IF(项目总控台账!L58="","",项目总控台账!L58) | ... AH58: =IF(项目总控台账!AH58="","",项目总控台账!AH58)
A59: =IF(项目总控台账!A59="","",项目总控台账!A59) -> T056 | B59: =项目总控台账!B42 -> 正式实施与上线准备 | C59: =项目总控台账!C57 -> 核心功能开发完成 | D59: =项目总控台账!D59 -> 合同起草 | E59: =IF(项目总控台账!E59="","",项目总控台账!E59) -> 开发合同拟稿、协同编辑和版本管理 | F59: =IF(项目总控台账!F59="","",项目总控台账!F59) -> MS010 | G59: =IF(项目总控台账!G59="","",项目总控台账!G59) -> 未开始 | H59: =IF(项目总控台账!H59="","",项目总控台账!H59) -> 中级开发人员 | I59: =IF(项目总控台账!I59="","",项目总控台账!I59) -> 46380 | J59: =IF(项目总控台账!J59="","",项目总控台账!J59) -> 46391 | K59: =IF(项目总控台账!K59="","",项目总控台账!K59) -> 46461 | L59: =IF(项目总控台账!L59="","",项目总控台账!L59) | ... AH59: =IF(项目总控台账!AH59="","",项目总控台账!AH59)
A60: =IF(项目总控台账!A60="","",项目总控台账!A60) -> T057 | B60: =项目总控台账!B42 -> 正式实施与上线准备 | C60: =项目总控台账!C57 -> 核心功能开发完成 | D60: =项目总控台账!D60 -> 合同审批 | E60: =IF(项目总控台账!E60="","",项目总控台账!E60) -> 开发合同审查、审批和用印流程 | F60: =IF(项目总控台账!F60="","",项目总控台账!F60) -> MS010 | G60: =IF(项目总控台账!G60="","",项目总控台账!G60) -> 未开始 | H60: =IF(项目总控台账!H60="","",项目总控台账!H60) -> 高级开发人员 | I60: =IF(项目总控台账!I60="","",项目总控台账!I60) -> 46392 | J60: =IF(项目总控台账!J60="","",项目总控台账!J60) -> 46402 | K60: =IF(项目总控台账!K60="","",项目总控台账!K60) -> 46461 | L60: =IF(项目总控台账!L60="","",项目总控台账!L60) | ... AH60: =IF(项目总控台账!AH60="","",项目总控台账!AH60)
A61: =IF(项目总控台账!A61="","",项目总控台账!A61) -> T058 | B61: =项目总控台账!B42 -> 正式实施与上线准备 | C61: =项目总控台账!C57 -> 核心功能开发完成 | D61: =项目总控台账!D61 -> 合同签署 | E61: =IF(项目总控台账!E61="","",项目总控台账!E61) -> 开发签署状态、签章和合同生效管理 | F61: =IF(项目总控台账!F61="","",项目总控台账!F61) -> MS010 | G61: =IF(项目总控台账!G61="","",项目总控台账!G61) -> 未开始 | H61: =IF(项目总控台账!H61="","",项目总控台账!H61) -> 高级开发人员 | I61: =IF(项目总控台账!I61="","",项目总控台账!I61) -> 46403 | J61: =IF(项目总控台账!J61="","",项目总控台账!J61) -> 46414 | K61: =IF(项目总控台账!K61="","",项目总控台账!K61) -> 46461 | L61: =IF(项目总控台账!L61="","",项目总控台账!L61) | ... AH61: =IF(项目总控台账!AH61="","",项目总控台账!AH61)
A62: =IF(项目总控台账!A62="","",项目总控台账!A62) -> T059 | B62: =项目总控台账!B42 -> 正式实施与上线准备 | C62: =项目总控台账!C57 -> 核心功能开发完成 | D62: =项目总控台账!D62 -> 履约管理 | E62: =IF(项目总控台账!E62="","",项目总控台账!E62) -> 开发履约计划、交付、验收和预警 | F62: =IF(项目总控台账!F62="","",项目总控台账!F62) -> MS010 | G62: =IF(项目总控台账!G62="","",项目总控台账!G62) -> 未开始 | H62: =IF(项目总控台账!H62="","",项目总控台账!H62) -> 中级开发人员 | I62: =IF(项目总控台账!I62="","",项目总控台账!I62) -> 46415 | J62: =IF(项目总控台账!J62="","",项目总控台账!J62) -> 46426 | K62: =IF(项目总控台账!K62="","",项目总控台账!K62) -> 46461 | L62: =IF(项目总控台账!L62="","",项目总控台账!L62) | ... AH62: =IF(项目总控台账!AH62="","",项目总控台账!AH62)
A63: =IF(项目总控台账!A63="","",项目总控台账!A63) -> T060 | B63: =项目总控台账!B42 -> 正式实施与上线准备 | C63: =项目总控台账!C57 -> 核心功能开发完成 | D63: =项目总控台账!D63 -> 收付款管理 | E63: =IF(项目总控台账!E63="","",项目总控台账!E63) -> 开发应收应付、开票和付款计划 | F63: =IF(项目总控台账!F63="","",项目总控台账!F63) -> MS010 | G63: =IF(项目总控台账!G63="","",项目总控台账!G63) -> 未开始 | H63: =IF(项目总控台账!H63="","",项目总控台账!H63) -> 中级开发人员 | I63: =IF(项目总控台账!I63="","",项目总控台账!I63) -> 46427 | J63: =IF(项目总控台账!J63="","",项目总控台账!J63) -> 46437 | K63: =IF(项目总控台账!K63="","",项目总控台账!K63) -> 46461 | L63: =IF(项目总控台账!L63="","",项目总控台账!L63) | ... AH63: =IF(项目总控台账!AH63="","",项目总控台账!AH63)
A64: =IF(项目总控台账!A64="","",项目总控台账!A64) -> T061 | B64: =项目总控台账!B42 -> 正式实施与上线准备 | C64: =项目总控台账!C57 -> 核心功能开发完成 | D64: =项目总控台账!D64 -> 变更归档 | E64: =IF(项目总控台账!E64="","",项目总控台账!E64) -> 开发变更、解除、终止和电子归档 | F64: =IF(项目总控台账!F64="","",项目总控台账!F64) -> MS010 | G64: =IF(项目总控台账!G64="","",项目总控台账!G64) -> 未开始 | H64: =IF(项目总控台账!H64="","",项目总控台账!H64) -> 中级开发人员 | I64: =IF(项目总控台账!I64="","",项目总控台账!I64) -> 46438 | J64: =IF(项目总控台账!J64="","",项目总控台账!J64) -> 46449 | K64: =IF(项目总控台账!K64="","",项目总控台账!K64) -> 46461 | L64: =IF(项目总控台账!L64="","",项目总控台账!L64) | ... AH64: =IF(项目总控台账!AH64="","",项目总控台账!AH64)
A65: =IF(项目总控台账!A65="","",项目总控台账!A65) -> T062 | B65: =项目总控台账!B42 -> 正式实施与上线准备 | C65: =项目总控台账!C57 -> 核心功能开发完成 | D65: =项目总控台账!D65 -> 查询分析 | E65: =IF(项目总控台账!E65="","",项目总控台账!E65) -> 开发合同检索、台账和经营分析页面 | F65: =IF(项目总控台账!F65="","",项目总控台账!F65) -> MS010 | G65: =IF(项目总控台账!G65="","",项目总控台账!G65) -> 未开始 | H65: =IF(项目总控台账!H65="","",项目总控台账!H65) -> 中级开发人员 | I65: =IF(项目总控台账!I65="","",项目总控台账!I65) -> 46450 | J65: =IF(项目总控台账!J65="","",项目总控台账!J65) -> 46461 | K65: =IF(项目总控台账!K65="","",项目总控台账!K65) -> 46461 | L65: =IF(项目总控台账!L65="","",项目总控台账!L65) | ... AH65: =IF(项目总控台账!AH65="","",项目总控台账!AH65)
A66: =IF(项目总控台账!A66="","",项目总控台账!A66) -> T063 | B66: =项目总控台账!B42 -> 正式实施与上线准备 | C66: =项目总控台账!C66 -> 内部系统集成完成 | D66: =项目总控台账!D66 -> 内部集成 | E66: =IF(项目总控台账!E66="","",项目总控台账!E66) -> 制定端到端集成场景和测试数据 | F66: =IF(项目总控台账!F66="","",项目总控台账!F66) -> MS011 | G66: =IF(项目总控台账!G66="","",项目总控台账!G66) -> 未开始 | H66: =IF(项目总控台账!H66="","",项目总控台账!H66) -> 技术经理 | I66: =IF(项目总控台账!I66="","",项目总控台账!I66) -> 46419 | J66: =IF(项目总控台账!J66="","",项目总控台账!J66) -> 46424 | K66: =IF(项目总控台账!K66="","",项目总控台账!K66) -> 46456 | L66: =IF(项目总控台账!L66="","",项目总控台账!L66) | ... AH66: =IF(项目总控台账!AH66="","",项目总控台账!AH66)
A67: =IF(项目总控台账!A67="","",项目总控台账!A67) -> T064 | B67: =项目总控台账!B42 -> 正式实施与上线准备 | C67: =项目总控台账!C66 -> 内部系统集成完成 | D67: =项目总控台账!D66 -> 内部集成 | E67: =IF(项目总控台账!E67="","",项目总控台账!E67) -> 贯通合同起草、审批、签署和生效流程 | F67: =IF(项目总控台账!F67="","",项目总控台账!F67) -> MS011 | G67: =IF(项目总控台账!G67="","",项目总控台账!G67) -> 未开始 | H67: =IF(项目总控台账!H67="","",项目总控台账!H67) -> 高级开发人员 | I67: =IF(项目总控台账!I67="","",项目总控台账!I67) -> 46425 | J67: =IF(项目总控台账!J67="","",项目总控台账!J67) -> 46430 | K67: =IF(项目总控台账!K67="","",项目总控台账!K67) -> 46456 | L67: =IF(项目总控台账!L67="","",项目总控台账!L67) | ... AH67: =IF(项目总控台账!AH67="","",项目总控台账!AH67)
A68: =IF(项目总控台账!A68="","",项目总控台账!A68) -> T065 | B68: =项目总控台账!B42 -> 正式实施与上线准备 | C68: =项目总控台账!C66 -> 内部系统集成完成 | D68: =项目总控台账!D66 -> 内部集成 | E68: =IF(项目总控台账!E68="","",项目总控台账!E68) -> 贯通履约、收付款、变更和归档流程 | F68: =IF(项目总控台账!F68="","",项目总控台账!F68) -> MS011 | G68: =IF(项目总控台账!G68="","",项目总控台账!G68) -> 未开始 | H68: =IF(项目总控台账!H68="","",项目总控台账!H68) -> 高级开发人员 | I68: =IF(项目总控台账!I68="","",项目总控台账!I68) -> 46431 | J68: =IF(项目总控台账!J68="","",项目总控台账!J68) -> 46437 | K68: =IF(项目总控台账!K68="","",项目总控台账!K68) -> 46456 | L68: =IF(项目总控台账!L68="","",项目总控台账!L68) | ... AH68: =IF(项目总控台账!AH68="","",项目总控台账!AH68)
A69: =IF(项目总控台账!A69="","",项目总控台账!A69) -> T066 | B69: =项目总控台账!B42 -> 正式实施与上线准备 | C69: =项目总控台账!C66 -> 内部系统集成完成 | D69: =项目总控台账!D66 -> 内部集成 | E69: =IF(项目总控台账!E69="","",项目总控台账!E69) -> 验证主数据、权限和审计数据流 | F69: =IF(项目总控台账!F69="","",项目总控台账!F69) -> MS011 | G69: =IF(项目总控台账!G69="","",项目总控台账!G69) -> 未开始 | H69: =IF(项目总控台账!H69="","",项目总控台账!H69) -> 高级测试人员、中级测试人员 | I69: =IF(项目总控台账!I69="","",项目总控台账!I69) -> 46438 | J69: =IF(项目总控台账!J69="","",项目总控台账!J69) -> 46443 | K69: =IF(项目总控台账!K69="","",项目总控台账!K69) -> 46456 | L69: =IF(项目总控台账!L69="","",项目总控台账!L69) | ... AH69: =IF(项目总控台账!AH69="","",项目总控台账!AH69)
A70: =IF(项目总控台账!A70="","",项目总控台账!A70) -> T067 | B70: =项目总控台账!B42 -> 正式实施与上线准备 | C70: =项目总控台账!C66 -> 内部系统集成完成 | D70: =项目总控台账!D70 -> 异常处理 | E70: =IF(项目总控台账!E70="","",项目总控台账!E70) -> 验证异常补偿、重试和一致性处理 | F70: =IF(项目总控台账!F70="","",项目总控台账!F70) -> MS011 | G70: =IF(项目总控台账!G70="","",项目总控台账!G70) -> 未开始 | H70: =IF(项目总控台账!H70="","",项目总控台账!H70) -> 高级开发人员 | I70: =IF(项目总控台账!I70="","",项目总控台账!I70) -> 46444 | J70: =IF(项目总控台账!J70="","",项目总控台账!J70) -> 46449 | K70: =IF(项目总控台账!K70="","",项目总控台账!K70) -> 46456 | L70: =IF(项目总控台账!L70="","",项目总控台账!L70) | ... AH70: =IF(项目总控台账!AH70="","",项目总控台账!AH70)
A71: =IF(项目总控台账!A71="","",项目总控台账!A71) -> T068 | B71: =项目总控台账!B42 -> 正式实施与上线准备 | C71: =项目总控台账!C66 -> 内部系统集成完成 | D71: =项目总控台账!D71 -> 集成验收 | E71: =IF(项目总控台账!E71="","",项目总控台账!E71) -> 完成内部集成回归并出具报告 | F71: =IF(项目总控台账!F71="","",项目总控台账!F71) -> MS011 | G71: =IF(项目总控台账!G71="","",项目总控台账!G71) -> 未开始 | H71: =IF(项目总控台账!H71="","",项目总控台账!H71) -> 高级测试人员、中级测试人员 | I71: =IF(项目总控台账!I71="","",项目总控台账!I71) -> 46450 | J71: =IF(项目总控台账!J71="","",项目总控台账!J71) -> 46456 | K71: =IF(项目总控台账!K71="","",项目总控台账!K71) -> 46456 | L71: =IF(项目总控台账!L71="","",项目总控台账!L71) | ... AH71: =IF(项目总控台账!AH71="","",项目总控台账!AH71)
A72: =IF(项目总控台账!A72="","",项目总控台账!A72) -> T069 | B72: =项目总控台账!B42 -> 正式实施与上线准备 | C72: =项目总控台账!C72 -> 外部系统集成完成 | D72: =项目总控台账!D72 -> 外部接口 | E72: =IF(项目总控台账!E72="","",项目总控台账!E72) -> 确认外部系统清单、接口规范和联调计划 | F72: =IF(项目总控台账!F72="","",项目总控台账!F72) -> MS012 | G72: =IF(项目总控台账!G72="","",项目总控台账!G72) -> 未开始 | H72: =IF(项目总控台账!H72="","",项目总控台账!H72) -> 技术经理 | I72: =IF(项目总控台账!I72="","",项目总控台账!I72) -> 46433 | J72: =IF(项目总控台账!J72="","",项目总控台账!J72) -> 46436 | K72: =IF(项目总控台账!K72="","",项目总控台账!K72) -> 46466 | L72: =IF(项目总控台账!L72="","",项目总控台账!L72) | ... AH72: =IF(项目总控台账!AH72="","",项目总控台账!AH72)
A73: =IF(项目总控台账!A73="","",项目总控台账!A73) -> T070 | B73: =项目总控台账!B42 -> 正式实施与上线准备 | C73: =项目总控台账!C72 -> 外部系统集成完成 | D73: =项目总控台账!D73 -> ERP集成 | E73: =IF(项目总控台账!E73="","",项目总控台账!E73) -> 完成ERP及主数据接口联调 | F73: =IF(项目总控台账!F73="","",项目总控台账!F73) -> MS012 | G73: =IF(项目总控台账!G73="","",项目总控台账!G73) -> 未开始 | H73: =IF(项目总控台账!H73="","",项目总控台账!H73) -> 高级开发人员 | I73: =IF(项目总控台账!I73="","",项目总控台账!I73) -> 46437 | J73: =IF(项目总控台账!J73="","",项目总控台账!J73) -> 46441 | K73: =IF(项目总控台账!K73="","",项目总控台账!K73) -> 46466 | L73: =IF(项目总控台账!L73="","",项目总控台账!L73) | ... AH73: =IF(项目总控台账!AH73="","",项目总控台账!AH73)
A74: =IF(项目总控台账!A74="","",项目总控台账!A74) -> T071 | B74: =项目总控台账!B42 -> 正式实施与上线准备 | C74: =项目总控台账!C72 -> 外部系统集成完成 | D74: =项目总控台账!D74 -> 财务集成 | E74: =IF(项目总控台账!E74="","",项目总控台账!E74) -> 完成财务、开票和收付款接口联调 | F74: =IF(项目总控台账!F74="","",项目总控台账!F74) -> MS012 | G74: =IF(项目总控台账!G74="","",项目总控台账!G74) -> 未开始 | H74: =IF(项目总控台账!H74="","",项目总控台账!H74) -> 高级开发人员 | I74: =IF(项目总控台账!I74="","",项目总控台账!I74) -> 46442 | J74: =IF(项目总控台账!J74="","",项目总控台账!J74) -> 46446 | K74: =IF(项目总控台账!K74="","",项目总控台账!K74) -> 46466 | L74: =IF(项目总控台账!L74="","",项目总控台账!L74) | ... AH74: =IF(项目总控台账!AH74="","",项目总控台账!AH74)
A75: =IF(项目总控台账!A75="","",项目总控台账!A75) -> T072 | B75: =项目总控台账!B42 -> 正式实施与上线准备 | C75: =项目总控台账!C72 -> 外部系统集成完成 | D75: =项目总控台账!D75 -> OA集成 | E75: =IF(项目总控台账!E75="","",项目总控台账!E75) -> 完成OA待办、审批和消息接口联调 | F75: =IF(项目总控台账!F75="","",项目总控台账!F75) -> MS012 | G75: =IF(项目总控台账!G75="","",项目总控台账!G75) -> 未开始 | H75: =IF(项目总控台账!H75="","",项目总控台账!H75) -> 中级开发人员 | I75: =IF(项目总控台账!I75="","",项目总控台账!I75) -> 46447 | J75: =IF(项目总控台账!J75="","",项目总控台账!J75) -> 46451 | K75: =IF(项目总控台账!K75="","",项目总控台账!K75) -> 46466 | L75: =IF(项目总控台账!L75="","",项目总控台账!L75) | ... AH75: =IF(项目总控台账!AH75="","",项目总控台账!AH75)
A76: =IF(项目总控台账!A76="","",项目总控台账!A76) -> T073 | B76: =项目总控台账!B42 -> 正式实施与上线准备 | C76: =项目总控台账!C72 -> 外部系统集成完成 | D76: =项目总控台账!D76 -> 签章集成 | E76: =IF(项目总控台账!E76="","",项目总控台账!E76) -> 完成电子签章、CA和时间戳接口联调 | F76: =IF(项目总控台账!F76="","",项目总控台账!F76) -> MS012 | G76: =IF(项目总控台账!G76="","",项目总控台账!G76) -> 未开始 | H76: =IF(项目总控台账!H76="","",项目总控台账!H76) -> 高级开发人员 | I76: =IF(项目总控台账!I76="","",项目总控台账!I76) -> 46452 | J76: =IF(项目总控台账!J76="","",项目总控台账!J76) -> 46456 | K76: =IF(项目总控台账!K76="","",项目总控台账!K76) -> 46466 | L76: =IF(项目总控台账!L76="","",项目总控台账!L76) | ... AH76: =IF(项目总控台账!AH76="","",项目总控台账!AH76)
A77: =IF(项目总控台账!A77="","",项目总控台账!A77) -> T074 | B77: =项目总控台账!B42 -> 正式实施与上线准备 | C77: =项目总控台账!C72 -> 外部系统集成完成 | D77: =项目总控台账!D77 -> 接口质量 | E77: =IF(项目总控台账!E77="","",项目总控台账!E77) -> 验证对账、幂等、补偿和监控机制 | F77: =IF(项目总控台账!F77="","",项目总控台账!F77) -> MS012 | G77: =IF(项目总控台账!G77="","",项目总控台账!G77) -> 未开始 | H77: =IF(项目总控台账!H77="","",项目总控台账!H77) -> 高级测试人员、中级测试人员 | I77: =IF(项目总控台账!I77="","",项目总控台账!I77) -> 46457 | J77: =IF(项目总控台账!J77="","",项目总控台账!J77) -> 46461 | K77: =IF(项目总控台账!K77="","",项目总控台账!K77) -> 46466 | L77: =IF(项目总控台账!L77="","",项目总控台账!L77) | ... AH77: =IF(项目总控台账!AH77="","",项目总控台账!AH77)
A78: =IF(项目总控台账!A78="","",项目总控台账!A78) -> T075 | B78: =项目总控台账!B42 -> 正式实施与上线准备 | C78: =项目总控台账!C72 -> 外部系统集成完成 | D78: =项目总控台账!D78 -> 联调验收 | E78: =IF(项目总控台账!E78="","",项目总控台账!E78) -> 完成外部系统联合测试并出具报告 | F78: =IF(项目总控台账!F78="","",项目总控台账!F78) -> MS012 | G78: =IF(项目总控台账!G78="","",项目总控台账!G78) -> 未开始 | H78: =IF(项目总控台账!H78="","",项目总控台账!H78) -> 技术经理 | I78: =IF(项目总控台账!I78="","",项目总控台账!I78) -> 46462 | J78: =IF(项目总控台账!J78="","",项目总控台账!J78) -> 46466 | K78: =IF(项目总控台账!K78="","",项目总控台账!K78) -> 46466 | L78: =IF(项目总控台账!L78="","",项目总控台账!L78) | ... AH78: =IF(项目总控台账!AH78="","",项目总控台账!AH78)
A79: =IF(项目总控台账!A79="","",项目总控台账!A79) -> T076 | B79: =项目总控台账!B42 -> 正式实施与上线准备 | C79: =项目总控台账!C79 -> 系统测试完成 | D79: =项目总控台账!D79 -> 测试准备 | E79: =IF(项目总控台账!E79="","",项目总控台账!E79) -> 编制系统测试计划、用例和测试数据 | F79: =IF(项目总控台账!F79="","",项目总控台账!F79) -> MS013 | G79: =IF(项目总控台账!G79="","",项目总控台账!G79) -> 未开始 | H79: =IF(项目总控台账!H79="","",项目总控台账!H79) -> 高级测试人员、中级测试人员 | I79: =IF(项目总控台账!I79="","",项目总控台账!I79) -> 46447 | J79: =IF(项目总控台账!J79="","",项目总控台账!J79) -> 46453 | K79: =IF(项目总控台账!K79="","",项目总控台账!K79) -> 46492 | L79: =IF(项目总控台账!L79="","",项目总控台账!L79) | ... AH79: =IF(项目总控台账!AH79="","",项目总控台账!AH79)
A80: =IF(项目总控台账!A80="","",项目总控台账!A80) -> T077 | B80: =项目总控台账!B42 -> 正式实施与上线准备 | C80: =项目总控台账!C79 -> 系统测试完成 | D80: =项目总控台账!D80 -> 功能测试 | E80: =IF(项目总控台账!E80="","",项目总控台账!E80) -> 完成P0/P1功能与业务规则测试 | F80: =IF(项目总控台账!F80="","",项目总控台账!F80) -> MS013 | G80: =IF(项目总控台账!G80="","",项目总控台账!G80) -> 未开始 | H80: =IF(项目总控台账!H80="","",项目总控台账!H80) -> 高级测试人员、中级测试人员 | I80: =IF(项目总控台账!I80="","",项目总控台账!I80) -> 46454 | J80: =IF(项目总控台账!J80="","",项目总控台账!J80) -> 46461 | K80: =IF(项目总控台账!K80="","",项目总控台账!K80) -> 46492 | L80: =IF(项目总控台账!L80="","",项目总控台账!L80) | ... AH80: =IF(项目总控台账!AH80="","",项目总控台账!AH80)
A81: =IF(项目总控台账!A81="","",项目总控台账!A81) -> T078 | B81: =项目总控台账!B42 -> 正式实施与上线准备 | C81: =项目总控台账!C79 -> 系统测试完成 | D81: =项目总控台账!D81 -> 集成回归 | E81: =IF(项目总控台账!E81="","",项目总控台账!E81) -> 完成内部外部接口及端到端回归 | F81: =IF(项目总控台账!F81="","",项目总控台账!F81) -> MS013 | G81: =IF(项目总控台账!G81="","",项目总控台账!G81) -> 未开始 | H81: =IF(项目总控台账!H81="","",项目总控台账!H81) -> 高级测试人员、中级测试人员 | I81: =IF(项目总控台账!I81="","",项目总控台账!I81) -> 46462 | J81: =IF(项目总控台账!J81="","",项目总控台账!J81) -> 46469 | K81: =IF(项目总控台账!K81="","",项目总控台账!K81) -> 46492 | L81: =IF(项目总控台账!L81="","",项目总控台账!L81) | ... AH81: =IF(项目总控台账!AH81="","",项目总控台账!AH81)
A82: =IF(项目总控台账!A82="","",项目总控台账!A82) -> T079 | B82: =项目总控台账!B42 -> 正式实施与上线准备 | C82: =项目总控台账!C79 -> 系统测试完成 | D82: =项目总控台账!D82 -> 专项测试 | E82: =IF(项目总控台账!E82="","",项目总控台账!E82) -> 完成性能、安全、兼容性和可靠性测试 | F82: =IF(项目总控台账!F82="","",项目总控台账!F82) -> MS013 | G82: =IF(项目总控台账!G82="","",项目总控台账!G82) -> 未开始 | H82: =IF(项目总控台账!H82="","",项目总控台账!H82) -> 高级测试人员、中级测试人员 | I82: =IF(项目总控台账!I82="","",项目总控台账!I82) -> 46470 | J82: =IF(项目总控台账!J82="","",项目总控台账!J82) -> 46476 | K82: =IF(项目总控台账!K82="","",项目总控台账!K82) -> 46492 | L82: =IF(项目总控台账!L82="","",项目总控台账!L82) | ... AH82: =IF(项目总控台账!AH82="","",项目总控台账!AH82)
A83: =IF(项目总控台账!A83="","",项目总控台账!A83) -> T080 | B83: =项目总控台账!B42 -> 正式实施与上线准备 | C83: =项目总控台账!C79 -> 系统测试完成 | D83: =项目总控台账!D83 -> 缺陷治理 | E83: =IF(项目总控台账!E83="","",项目总控台账!E83) -> 完成阻断及严重缺陷修复和复测 | F83: =IF(项目总控台账!F83="","",项目总控台账!F83) -> MS013 | G83: =IF(项目总控台账!G83="","",项目总控台账!G83) -> 未开始 | H83: =IF(项目总控台账!H83="","",项目总控台账!H83) -> 高级开发人员 | I83: =IF(项目总控台账!I83="","",项目总控台账!I83) -> 46477 | J83: =IF(项目总控台账!J83="","",项目总控台账!J83) -> 46484 | K83: =IF(项目总控台账!K83="","",项目总控台账!K83) -> 46492 | L83: =IF(项目总控台账!L83="","",项目总控台账!L83) | ... AH83: =IF(项目总控台账!AH83="","",项目总控台账!AH83)
A84: =IF(项目总控台账!A84="","",项目总控台账!A84) -> T081 | B84: =项目总控台账!B42 -> 正式实施与上线准备 | C84: =项目总控台账!C79 -> 系统测试完成 | D84: =项目总控台账!D84 -> 测试结论 | E84: =IF(项目总控台账!E84="","",项目总控台账!E84) -> 汇总覆盖率、缺陷和质量结论并评审 | F84: =IF(项目总控台账!F84="","",项目总控台账!F84) -> MS013 | G84: =IF(项目总控台账!G84="","",项目总控台账!G84) -> 未开始 | H84: =IF(项目总控台账!H84="","",项目总控台账!H84) -> 高级测试人员、中级测试人员 | I84: =IF(项目总控台账!I84="","",项目总控台账!I84) -> 46485 | J84: =IF(项目总控台账!J84="","",项目总控台账!J84) -> 46492 | K84: =IF(项目总控台账!K84="","",项目总控台账!K84) -> 46492 | L84: =IF(项目总控台账!L84="","",项目总控台账!L84) | ... AH84: =IF(项目总控台账!AH84="","",项目总控台账!AH84)
A85: =IF(项目总控台账!A85="","",项目总控台账!A85) -> T082 | B85: =项目总控台账!B42 -> 正式实施与上线准备 | C85: =项目总控台账!C85 -> UAT验收完成 | D85: =项目总控台账!D85 -> UAT准备 | E85: =IF(项目总控台账!E85="","",项目总控台账!E85) -> 确认UAT场景、用户、数据和验收安排 | F85: =IF(项目总控台账!F85="","",项目总控台账!F85) -> MS014 | G85: =IF(项目总控台账!G85="","",项目总控台账!G85) -> 未开始 | H85: =IF(项目总控台账!H85="","",项目总控台账!H85) -> 产品经理 | I85: =IF(项目总控台账!I85="","",项目总控台账!I85) -> 46493 | J85: =IF(项目总控台账!J85="","",项目总控台账!J85) -> 46498 | K85: =IF(项目总控台账!K85="","",项目总控台账!K85) -> 46517 | L85: =IF(项目总控台账!L85="","",项目总控台账!L85) -> 产品经理 | ... AH85: =IF(项目总控台账!AH85="","",项目总控台账!AH85)
A86: =IF(项目总控台账!A86="","",项目总控台账!A86) -> T083 | B86: =项目总控台账!B42 -> 正式实施与上线准备 | C86: =项目总控台账!C85 -> UAT验收完成 | D86: =项目总控台账!D86 -> UAT执行 | E86: =IF(项目总控台账!E86="","",项目总控台账!E86) -> 组织业务用户执行P0场景验收 | F86: =IF(项目总控台账!F86="","",项目总控台账!F86) -> MS014 | G86: =IF(项目总控台账!G86="","",项目总控台账!G86) -> 未开始 | H86: =IF(项目总控台账!H86="","",项目总控台账!H86) -> 产品经理 | I86: =IF(项目总控台账!I86="","",项目总控台账!I86) -> 46499 | J86: =IF(项目总控台账!J86="","",项目总控台账!J86) -> 46504 | K86: =IF(项目总控台账!K86="","",项目总控台账!K86) -> 46517 | L86: =IF(项目总控台账!L86="","",项目总控台账!L86) -> 产品经理 | ... AH86: =IF(项目总控台账!AH86="","",项目总控台账!AH86)
A87: =IF(项目总控台账!A87="","",项目总控台账!A87) -> T084 | B87: =项目总控台账!B42 -> 正式实施与上线准备 | C87: =项目总控台账!C85 -> UAT验收完成 | D87: =项目总控台账!D87 -> 问题闭环 | E87: =IF(项目总控台账!E87="","",项目总控台账!E87) -> 修复UAT问题并完成业务回归 | F87: =IF(项目总控台账!F87="","",项目总控台账!F87) -> MS014 | G87: =IF(项目总控台账!G87="","",项目总控台账!G87) -> 未开始 | H87: =IF(项目总控台账!H87="","",项目总控台账!H87) -> 高级开发人员 | I87: =IF(项目总控台账!I87="","",项目总控台账!I87) -> 46505 | J87: =IF(项目总控台账!J87="","",项目总控台账!J87) -> 46510 | K87: =IF(项目总控台账!K87="","",项目总控台账!K87) -> 46517 | L87: =IF(项目总控台账!L87="","",项目总控台账!L87) | ... AH87: =IF(项目总控台账!AH87="","",项目总控台账!AH87)
A88: =IF(项目总控台账!A88="","",项目总控台账!A88) -> T085 | B88: =项目总控台账!B42 -> 正式实施与上线准备 | C88: =项目总控台账!C85 -> UAT验收完成 | D88: =项目总控台账!D88 -> 业务验收 | E88: =IF(项目总控台账!E88="","",项目总控台账!E88) -> 形成UAT报告、遗留事项和确认单 | F88: =IF(项目总控台账!F88="","",项目总控台账!F88) -> MS014 | G88: =IF(项目总控台账!G88="","",项目总控台账!G88) -> 未开始 | H88: =IF(项目总控台账!H88="","",项目总控台账!H88) -> 项目经理 | I88: =IF(项目总控台账!I88="","",项目总控台账!I88) -> 46511 | J88: =IF(项目总控台账!J88="","",项目总控台账!J88) -> 46517 | K88: =IF(项目总控台账!K88="","",项目总控台账!K88) -> 46517 | L88: =IF(项目总控台账!L88="","",项目总控台账!L88) -> 项目经理 | ... AH88: =IF(项目总控台账!AH88="","",项目总控台账!AH88)
A89: =IF(项目总控台账!A89="","",项目总控台账!A89) -> T086 | B89: =项目总控台账!B42 -> 正式实施与上线准备 | C89: =项目总控台账!C89 -> 上线准入评审通过 | D89: =项目总控台账!D89 -> 上线准备 | E89: =IF(项目总控台账!E89="","",项目总控台账!E89) -> 完成生产部署、发布和回退方案 | F89: =IF(项目总控台账!F89="","",项目总控台账!F89) -> MS015 | G89: =IF(项目总控台账!G89="","",项目总控台账!G89) -> 未开始 | H89: =IF(项目总控台账!H89="","",项目总控台账!H89) -> 配置人员 | I89: =IF(项目总控台账!I89="","",项目总控台账!I89) -> 46518 | J89: =IF(项目总控台账!J89="","",项目总控台账!J89) -> 46519 | K89: =IF(项目总控台账!K89="","",项目总控台账!K89) -> 46531 | L89: =IF(项目总控台账!L89="","",项目总控台账!L89) | ... AH89: =IF(项目总控台账!AH89="","",项目总控台账!AH89)
A90: =IF(项目总控台账!A90="","",项目总控台账!A90) -> T087 | B90: =项目总控台账!B42 -> 正式实施与上线准备 | C90: =项目总控台账!C89 -> 上线准入评审通过 | D90: =项目总控台账!D90 -> 数据准备 | E90: =IF(项目总控台账!E90="","",项目总控台账!E90) -> 完成数据迁移、清洗和对账演练 | F90: =IF(项目总控台账!F90="","",项目总控台账!F90) -> MS015 | G90: =IF(项目总控台账!G90="","",项目总控台账!G90) -> 未开始 | H90: =IF(项目总控台账!H90="","",项目总控台账!H90) -> 高级开发人员 | I90: =IF(项目总控台账!I90="","",项目总控台账!I90) -> 46520 | J90: =IF(项目总控台账!J90="","",项目总控台账!J90) -> 46521 | K90: =IF(项目总控台账!K90="","",项目总控台账!K90) -> 46531 | L90: =IF(项目总控台账!L90="","",项目总控台账!L90) | ... AH90: =IF(项目总控台账!AH90="","",项目总控台账!AH90)
A91: =IF(项目总控台账!A91="","",项目总控台账!A91) -> T088 | B91: =项目总控台账!B42 -> 正式实施与上线准备 | C91: =项目总控台账!C89 -> 上线准入评审通过 | D91: =项目总控台账!D91 -> 上线检查 | E91: =IF(项目总控台账!E91="","",项目总控台账!E91) -> 核查接口、权限、证书和配置参数 | F91: =IF(项目总控台账!F91="","",项目总控台账!F91) -> MS015 | G91: =IF(项目总控台账!G91="","",项目总控台账!G91) -> 未开始 | H91: =IF(项目总控台账!H91="","",项目总控台账!H91) -> 技术经理 | I91: =IF(项目总控台账!I91="","",项目总控台账!I91) -> 46522 | J91: =IF(项目总控台账!J91="","",项目总控台账!J91) -> 46524 | K91: =IF(项目总控台账!K91="","",项目总控台账!K91) -> 46531 | L91: =IF(项目总控台账!L91="","",项目总控台账!L91) | ... AH91: =IF(项目总控台账!AH91="","",项目总控台账!AH91)
A92: =IF(项目总控台账!A92="","",项目总控台账!A92) -> T089 | B92: =项目总控台账!B42 -> 正式实施与上线准备 | C92: =项目总控台账!C89 -> 上线准入评审通过 | D92: =项目总控台账!D92 -> 运维准备 | E92: =IF(项目总控台账!E92="","",项目总控台账!E92) -> 建立监控、告警、备份和支持机制 | F92: =IF(项目总控台账!F92="","",项目总控台账!F92) -> MS015 | G92: =IF(项目总控台账!G92="","",项目总控台账!G92) -> 未开始 | H92: =IF(项目总控台账!H92="","",项目总控台账!H92) -> 配置人员 | I92: =IF(项目总控台账!I92="","",项目总控台账!I92) -> 46525 | J92: =IF(项目总控台账!J92="","",项目总控台账!J92) -> 46526 | K92: =IF(项目总控台账!K92="","",项目总控台账!K92) -> 46531 | L92: =IF(项目总控台账!L92="","",项目总控台账!L92) | ... AH92: =IF(项目总控台账!AH92="","",项目总控台账!AH92)
A93: =IF(项目总控台账!A93="","",项目总控台账!A93) -> T090 | B93: =项目总控台账!B42 -> 正式实施与上线准备 | C93: =项目总控台账!C89 -> 上线准入评审通过 | D93: =项目总控台账!D93 -> 培训交接 | E93: =IF(项目总控台账!E93="","",项目总控台账!E93) -> 完成用户培训、手册和运维交接 | F93: =IF(项目总控台账!F93="","",项目总控台账!F93) -> MS015 | G93: =IF(项目总控台账!G93="","",项目总控台账!G93) -> 未开始 | H93: =IF(项目总控台账!H93="","",项目总控台账!H93) -> 产品经理 | I93: =IF(项目总控台账!I93="","",项目总控台账!I93) -> 46527 | J93: =IF(项目总控台账!J93="","",项目总控台账!J93) -> 46528 | K93: =IF(项目总控台账!K93="","",项目总控台账!K93) -> 46531 | L93: =IF(项目总控台账!L93="","",项目总控台账!L93) -> 产品经理 | ... AH93: =IF(项目总控台账!AH93="","",项目总控台账!AH93)
A94: =IF(项目总控台账!A94="","",项目总控台账!A94) -> T091 | B94: =项目总控台账!B42 -> 正式实施与上线准备 | C94: =项目总控台账!C89 -> 上线准入评审通过 | D94: =项目总控台账!D94 -> 准入评审 | E94: =IF(项目总控台账!E94="","",项目总控台账!E94) -> 执行上线检查表并获得上线批准 | F94: =IF(项目总控台账!F94="","",项目总控台账!F94) -> MS015 | G94: =IF(项目总控台账!G94="","",项目总控台账!G94) -> 未开始 | H94: =IF(项目总控台账!H94="","",项目总控台账!H94) -> 项目集经理 | I94: =IF(项目总控台账!I94="","",项目总控台账!I94) -> 46529 | J94: =IF(项目总控台账!J94="","",项目总控台账!J94) -> 46531 | K94: =IF(项目总控台账!K94="","",项目总控台账!K94) -> 46531 | L94: =IF(项目总控台账!L94="","",项目总控台账!L94) -> 项目集经理 | ... AH94: =IF(项目总控台账!AH94="","",项目总控台账!AH94)
A95: =IF(项目总控台账!A95="","",项目总控台账!A95) -> T092 | B95: =项目总控台账!B95 -> 系统上线与试运行 | C95: =项目总控台账!C95 -> 生产上线并进入试运行 | D95: =项目总控台账!D95 -> 生产发布 | E95: =IF(项目总控台账!E95="","",项目总控台账!E95) -> 执行生产部署、数据切换和版本发布 | F95: =IF(项目总控台账!F95="","",项目总控台账!F95) -> MS016 | G95: =IF(项目总控台账!G95="","",项目总控台账!G95) -> 未开始 | H95: =IF(项目总控台账!H95="","",项目总控台账!H95) -> 配置人员 | I95: =IF(项目总控台账!I95="","",项目总控台账!I95) -> 46538 | J95: =IF(项目总控台账!J95="","",项目总控台账!J95) -> 46538 | K95: =IF(项目总控台账!K95="","",项目总控台账!K95) -> 46538 | L95: =IF(项目总控台账!L95="","",项目总控台账!L95) | ... AH95: =IF(项目总控台账!AH95="","",项目总控台账!AH95)
A96: =IF(项目总控台账!A96="","",项目总控台账!A96) -> T093 | B96: =项目总控台账!B95 -> 系统上线与试运行 | C96: =项目总控台账!C95 -> 生产上线并进入试运行 | D96: =项目总控台账!D96 -> 上线验证 | E96: =IF(项目总控台账!E96="","",项目总控台账!E96) -> 执行生产冒烟和关键业务链路验证 | F96: =IF(项目总控台账!F96="","",项目总控台账!F96) -> MS016 | G96: =IF(项目总控台账!G96="","",项目总控台账!G96) -> 未开始 | H96: =IF(项目总控台账!H96="","",项目总控台账!H96) -> 高级测试人员、中级测试人员 | I96: =IF(项目总控台账!I96="","",项目总控台账!I96) -> 46538 | J96: =IF(项目总控台账!J96="","",项目总控台账!J96) -> 46538 | K96: =IF(项目总控台账!K96="","",项目总控台账!K96) -> 46538 | L96: =IF(项目总控台账!L96="","",项目总控台账!L96) | ... AH96: =IF(项目总控台账!AH96="","",项目总控台账!AH96)
A97: =IF(项目总控台账!A97="","",项目总控台账!A97) -> T094 | B97: =项目总控台账!B95 -> 系统上线与试运行 | C97: =项目总控台账!C95 -> 生产上线并进入试运行 | D97: =项目总控台账!D97 -> 试运行 | E97: =IF(项目总控台账!E97="","",项目总控台账!E97) -> 启动监控、问题响应和试运行支持 | F97: =IF(项目总控台账!F97="","",项目总控台账!F97) -> MS016 | G97: =IF(项目总控台账!G97="","",项目总控台账!G97) -> 未开始 | H97: =IF(项目总控台账!H97="","",项目总控台账!H97) -> 技术经理 | I97: =IF(项目总控台账!I97="","",项目总控台账!I97) -> 46538 | J97: =IF(项目总控台账!J97="","",项目总控台账!J97) -> 46538 | K97: =IF(项目总控台账!K97="","",项目总控台账!K97) -> 46538 | L97: =IF(项目总控台账!L97="","",项目总控台账!L97) | ... AH97: =IF(项目总控台账!AH97="","",项目总控台账!AH97)
A98: =IF(项目总控台账!A98="","",项目总控台账!A98) -> T095 | B98: =项目总控台账!B95 -> 系统上线与试运行 | C98: =项目总控台账!C95 -> 生产上线并进入试运行 | D98: =项目总控台账!D98 -> 上线确认 | E98: =IF(项目总控台账!E98="","",项目总控台账!E98) -> 形成上线确认单和试运行跟踪计划 | F98: =IF(项目总控台账!F98="","",项目总控台账!F98) -> MS016 | G98: =IF(项目总控台账!G98="","",项目总控台账!G98) -> 未开始 | H98: =IF(项目总控台账!H98="","",项目总控台账!H98) -> 项目经理 | I98: =IF(项目总控台账!I98="","",项目总控台账!I98) -> 46538 | J98: =IF(项目总控台账!J98="","",项目总控台账!J98) -> 46538 | K98: =IF(项目总控台账!K98="","",项目总控台账!K98) -> 46538 | L98: =IF(项目总控台账!L98="","",项目总控台账!L98) -> 项目经理 | ... AH98: =IF(项目总控台账!AH98="","",项目总控台账!AH98)
A99: =IF(项目总控台账!A99="","",项目总控台账!A99) -> T096 | B99: =项目总控台账!B99 -> 大集中ERP | C99: =项目总控台账!C99 -> 外部系统接口实施 | D99: =项目总控台账!D99 -> 设计 | E99: =IF(项目总控台账!E99="","",项目总控台账!E99) -> 大集中ERPP0接口设计工作包：接口设计说明、字段映射、异常与安全方案通过评审 | F99: =IF(项目总控台账!F99="","",项目总控台账!F99) -> MS009 | G99: =IF(项目总控台账!G99="","",项目总控台账!G99) -> 未开始 | H99: =IF(项目总控台账!H99="","",项目总控台账!H99) -> 产品经理 | I99: =IF(项目总控台账!I99="","",项目总控台账!I99) -> 46341 | J99: =IF(项目总控台账!J99="","",项目总控台账!J99) -> 46367 | K99: =IF(项目总控台账!K99="","",项目总控台账!K99) -> 46367 | L99: =IF(项目总控台账!L99="","",项目总控台账!L99) -> 产品经理 | ... AH99: =IF(项目总控台账!AH99="","",项目总控台账!AH99)
A100: =IF(项目总控台账!A100="","",项目总控台账!A100) -> T097 | B100: =项目总控台账!B99 -> 大集中ERP | C100: =项目总控台账!C100 -> 外部系统接口实施 | D100: =项目总控台账!D100 -> 开发 | E100: =IF(项目总控台账!E100="","",项目总控台账!E100) -> 大集中ERPP0接口开发工作包：接口代码、自测记录及部署包完成 | F100: =IF(项目总控台账!F100="","",项目总控台账!F100) -> MS010 | G100: =IF(项目总控台账!G100="","",项目总控台账!G100) -> 未开始 | H100: =IF(项目总控台账!H100="","",项目总控台账!H100) -> 产品经理 | I100: =IF(项目总控台账!I100="","",项目总控台账!I100) -> 46368 | J100: =IF(项目总控台账!J100="","",项目总控台账!J100) -> 46430 | K100: =IF(项目总控台账!K100="","",项目总控台账!K100) -> 46430 | L100: =IF(项目总控台账!L100="","",项目总控台账!L100) -> 产品经理 | ... AH100: =IF(项目总控台账!AH100="","",项目总控台账!AH100)
...

Sheet 资源计划
A1: 资源计划
A2: 资源周计划按每人每周40小时控制；接口任务依据系统集成管理的建议资源人同步，多个并行任务平均分配当周40小时；人员成本预算不在本文件调整。
A4: 人员 | B4: 角色 | C4: 任务数 | D4: 未完成任务 | E4: 最早开始 | F4: 最晚结束 | G4: 周可用工时 | H4: 计划投入工时 | I4: 负荷率 | J4: 负荷判断 | K4: 资源建议 | L4: 备注
A5: 项目集经理-01 | B5: 项目集经理 | C5: 7 | D5: 6 | E5: 46055 | F5: 46537 | G5: 40 | H5: 600 | I5: =IFERROR(H5/(G5*((MAX($C$39:$C$2168)-MIN($B$39:$B$2168)+1)/7)),0) -> 0.21126761 | J5: =IF(I5=0,"空闲",IF(I5<=0.6,"低负荷",IF(I5<=0.85,"正常",IF(I5<=1,"满负荷","超负荷")))) -> 低负荷 | K5: 可承接同角色新增任务 | L5: 角色占位资源，待实名替换
A6: 项目经理-01 | B6: 项目经理 | C6: 7 | D6: 5 | E6: 46048 | F6: 46523 | G6: 40 | H6: 640 | I6: =IFERROR(H6/(G6*((MAX($C$39:$C$2168)-MIN($B$39:$B$2168)+1)/7)),0) -> 0.22535211 | J6: =IF(I6=0,"空闲",IF(I6<=0.6,"低负荷",IF(I6<=0.85,"正常",IF(I6<=1,"满负荷","超负荷")))) -> 低负荷 | K6: 可承接同角色新增任务 | L6: 角色占位资源，待实名替换
A7: 项目经理-02 | B7: 项目经理 | C7: 7 | D7: 6 | E7: 46146 | F7: 46544 | G7: 40 | H7: 640 | I7: =IFERROR(H7/(G7*((MAX($C$39:$C$2168)-MIN($B$39:$B$2168)+1)/7)),0) -> 0.22535211 | J7: =IF(I7=0,"空闲",IF(I7<=0.6,"低负荷",IF(I7<=0.85,"正常",IF(I7<=1,"满负荷","超负荷")))) -> 低负荷 | K7: 可承接同角色新增任务 | L7: 角色占位资源，待实名替换
A8: 技术经理-01 | B8: 技术经理 | C8: 16 | D8: 15 | E8: 46097 | F8: 46544 | G8: 40 | H8: 920 | I8: =IFERROR(H8/(G8*((MAX($C$39:$C$2168)-MIN($B$39:$B$2168)+1)/7)),0) -> 0.32394366 | J8: =IF(I8=0,"空闲",IF(I8<=0.6,"低负荷",IF(I8<=0.85,"正常",IF(I8<=1,"满负荷","超负荷")))) -> 低负荷 | K8: 可承接同角色新增任务 | L8: 角色占位资源，待实名替换
A9: 技术经理-02 | B9: 技术经理 | C9: 16 | D9: 16 | E9: 46118 | F9: 46530 | G9: 40 | H9: 880 | I9: =IFERROR(H9/(G9*((MAX($C$39:$C$2168)-MIN($B$39:$B$2168)+1)/7)),0) -> 0.30985915 | J9: =IF(I9=0,"空闲",IF(I9<=0.6,"低负荷",IF(I9<=0.85,"正常",IF(I9<=1,"满负荷","超负荷")))) -> 低负荷 | K9: 可承接同角色新增任务 | L9: 角色占位资源，待实名替换
A10: 产品经理-01 | B10: 产品经理 | C10: 6 | D10: 4 | E10: 46055 | F10: 46509 | G10: 40 | H10: 680 | I10: =IFERROR(H10/(G10*((MAX($C$39:$C$2168)-MIN($B$39:$B$2168)+1)/7)),0) -> 0.23943662 | J10: =IF(I10=0,"空闲",IF(I10<=0.6,"低负荷",IF(I10<=0.85,"正常",IF(I10<=1,"满负荷","超负荷")))) -> 低负荷 | K10: 可承接同角色新增任务 | L10: 角色占位资源，待实名替换
A11: 产品经理-02 | B11: 产品经理 | C11: 6 | D11: 4 | E11: 46048 | F11: 46530 | G11: 40 | H11: 720 | I11: =IFERROR(H11/(G11*((MAX($C$39:$C$2168)-MIN($B$39:$B$2168)+1)/7)),0) -> 0.25352113 | J11: =IF(I11=0,"空闲",IF(I11<=0.6,"低负荷",IF(I11<=0.85,"正常",IF(I11<=1,"满负荷","超负荷")))) -> 低负荷 | K11: 可承接同角色新增任务 | L11: 角色占位资源，待实名替换
A12: 美工-01 | B12: 美工 | C12: 2 | D12: 2 | E12: 46335 | F12: 46383 | G12: 40 | H12: 160 | I12: =IFERROR(H12/(G12*((MAX($C$39:$C$2168)-MIN($B$39:$B$2168)+1)/7)),0) -> 0.056338028 | J12: =IF(I12=0,"空闲",IF(I12<=0.6,"低负荷",IF(I12<=0.85,"正常",IF(I12<=1,"满负荷","超负荷")))) -> 低负荷 | K12: 可承接同角色新增任务 | L12: 角色占位资源，待实名替换
A13: 高级开发人员-01 | B13: 高级开发人员 | C13: 17 | D13: 17 | E13: 46230 | F13: 46516 | G13: 40 | H13: 840 | I13: =IFERROR(H13/(G13*((MAX($C$39:$C$2168)-MIN($B$39:$B$2168)+1)/7)),0) -> 0.29577465 | J13: =IF(I13=0,"空闲",IF(I13<=0.6,"低负荷",IF(I13<=0.85,"正常",IF(I13<=1,"满负荷","超负荷")))) -> 低负荷 | K13: 可承接同角色新增任务 | L13: 角色占位资源，待实名替换
A14: 高级开发人员-02 | B14: 高级开发人员 | C14: 17 | D14: 17 | E14: 46251 | F14: 46523 | G14: 40 | H14: 760 | I14: =IFERROR(H14/(G14*((MAX($C$39:$C$2168)-MIN($B$39:$B$2168)+1)/7)),0) -> 0.26760563 | J14: =IF(I14=0,"空闲",IF(I14<=0.6,"低负荷",IF(I14<=0.85,"正常",IF(I14<=1,"满负荷","超负荷")))) -> 低负荷 | K14: 可承接同角色新增任务 | L14: 角色占位资源，待实名替换
A15: 高级开发人员-03 | B15: 高级开发人员 | C15: 16 | D15: 16 | E15: 46272 | F15: 46488 | G15: 40 | H15: 760 | I15: =IFERROR(H15/(G15*((MAX($C$39:$C$2168)-MIN($B$39:$B$2168)+1)/7)),0) -> 0.26760563 | J15: =IF(I15=0,"空闲",IF(I15<=0.6,"低负荷",IF(I15<=0.85,"正常",IF(I15<=1,"满负荷","超负荷")))) -> 低负荷 | K15: 可承接同角色新增任务 | L15: 角色占位资源，待实名替换
A16: 中级开发人员-01 | B16: 中级开发人员 | C16: 6 | D16: 6 | E16: 46258 | F16: 46453 | G16: 40 | H16: 600 | I16: =IFERROR(H16/(G16*((MAX($C$39:$C$2168)-MIN($B$39:$B$2168)+1)/7)),0) -> 0.21126761 | J16: =IF(I16=0,"空闲",IF(I16<=0.6,"低负荷",IF(I16<=0.85,"正常",IF(I16<=1,"满负荷","超负荷")))) -> 低负荷 | K16: 可承接同角色新增任务 | L16: 角色占位资源，待实名替换
... A34: 配置人员-01 | B34: 配置人员 | C34: 13 | D34: 13 | E34: 46251 | F34: 46544 | G34: 40 | H34: 360 | I34: =IFERROR(H34/(G34*((MAX($C$39:$C$2168)-MIN($B$39:$B$2168)+1)/7)),0) -> 0.12676056 | J34: =IF(I34=0,"空闲",IF(I34<=0.6,"低负荷",IF(I34<=0.85,"正常",IF(I34<=1,"满负荷","超负荷")))) -> 低负荷 | K34: 可承接同角色新增任务 | L34: 角色占位资源，待实名替换
A36: 资源周计划
A37: 任务与日期来自新的总控台账；有任务周按每人40小时安排，无任务周保留为可用容量。 | L37: 人员名称为角色占位，可替换为实名
A38: 人员 | B38: 周开始 | C38: 周结束 | D38: 是否有任务 | E38: 任务数 | F38: 周计划工时 | G38: 负荷率 | H38: 负荷判断 | I38: 任务清单 | L38: 说明
A39: 项目集经理-01 | B39: 46048 | C39: 46054 | D39: 无 | E39: 0 | F39: 0 | G39: =IFERROR(F39/INDEX($G$5:$G$34,MATCH(LOOKUP(2,1/($A$39:A39<>""),$A$39:A39),$A$5:$A$34,0)),0) -> 0 | H39: =IF(G39=0,"空闲",IF(G39<=0.6,"低负荷",IF(G39<=0.85,"正常",IF(G39<=1,"满负荷","超负荷")))) -> 空闲 | I39: 无 | L39: 本周可承接任务
B40: 46055 | C40: 46061 | D40: 有 | E40: 1 | F40: 40 | G40: =IFERROR(F40/INDEX($G$5:$G$34,MATCH(LOOKUP(2,1/($A$39:A40<>""),$A$39:A40),$A$5:$A$34,0)),0) -> 1 | H40: =IF(G40=0,"空闲",IF(G40<=0.6,"低负荷",IF(G40<=0.85,"正常",IF(G40<=1,"满负荷","超负荷")))) -> 满负荷 | I40: T003 评审并发布可研工作方案 | L40: 本周40小时按1项任务平均，每项40.0小时
B41: 46062 | C41: 46068 | D41: 有 | E41: 1 | F41: 40 | G41: =IFERROR(F41/INDEX($G$5:$G$34,MATCH(LOOKUP(2,1/($A$39:A41<>""),$A$39:A41),$A$5:$A$34,0)),0) -> 1 | H41: =IF(G41=0,"空闲",IF(G41<=0.6,"低负荷",IF(G41<=0.85,"正常",IF(G41<=1,"满负荷","超负荷")))) -> 满负荷 | I41: T003 评审并发布可研工作方案 | L41: 本周40小时按1项任务平均，每项40.0小时
B42: 46069 | C42: 46075 | D42: 无 | E42: 0 | F42: 0 | G42: =IFERROR(F42/INDEX($G$5:$G$34,MATCH(LOOKUP(2,1/($A$39:A42<>""),$A$39:A42),$A$5:$A$34,0)),0) -> 0 | H42: =IF(G42=0,"空闲",IF(G42<=0.6,"低负荷",IF(G42<=0.85,"正常",IF(G42<=1,"满负荷","超负荷")))) -> 空闲 | I42: 无 | L42: 本周可承接任务
B43: 46076 | C43: 46082 | D43: 无 | E43: 0 | F43: 0 | G43: =IFERROR(F43/INDEX($G$5:$G$34,MATCH(LOOKUP(2,1/($A$39:A43<>""),$A$39:A43),$A$5:$A$34,0)),0) -> 0 | H43: =IF(G43=0,"空闲",IF(G43<=0.6,"低负荷",IF(G43<=0.85,"正常",IF(G43<=1,"满负荷","超负荷")))) -> 空闲 | I43: 无 | L43: 本周可承接任务
B44: 46083 | C44: 46089 | D44: 无 | E44: 0 | F44: 0 | G44: =IFERROR(F44/INDEX($G$5:$G$34,MATCH(LOOKUP(2,1/($A$39:A44<>""),$A$39:A44),$A$5:$A$34,0)),0) -> 0 | H44: =IF(G44=0,"空闲",IF(G44<=0.6,"低负荷",IF(G44<=0.85,"正常",IF(G44<=1,"满负荷","超负荷")))) -> 空闲 | I44: 无 | L44: 本周可承接任务
B45: 46090 | C45: 46096 | D45: 无 | E45: 0 | F45: 0 | G45: =IFERROR(F45/INDEX($G$5:$G$34,MATCH(LOOKUP(2,1/($A$39:A45<>""),$A$39:A45),$A$5:$A$34,0)),0) -> 0 | H45: =IF(G45=0,"空闲",IF(G45<=0.6,"低负荷",IF(G45<=0.85,"正常",IF(G45<=1,"满负荷","超负荷")))) -> 空闲 | I45: 无 | L45: 本周可承接任务
B46: 46097 | C46: 46103 | D46: 无 | E46: 0 | F46: 0 | G46: =IFERROR(F46/INDEX($G$5:$G$34,MATCH(LOOKUP(2,1/($A$39:A46<>""),$A$39:A46),$A$5:$A$34,0)),0) -> 0 | H46: =IF(G46=0,"空闲",IF(G46<=0.6,"低负荷",IF(G46<=0.85,"正常",IF(G46<=1,"满负荷","超负荷")))) -> 空闲 | I46: 无 | L46: 本周可承接任务
