Workbook

Sheet 使用说明
A1: 沟通会议与报告-20260918-V3 使用说明
A2: 管理沟通计划、会议、行动项、决策、报告、升级和相关方沟通记录。
A4: 项目 | B4: 能源行业合同全生命周期管理系统
A5: 适用对象 | B5: 项目经理、PMO、会议主持人、行动项责任人
A6: 更新频率 | B6: 会议后1个工作日内更新；周报按周发布，升级事项即时维护。
A7: 版本日期 | B7: 2026-09-17
A8: 颜色约定 | B8: 浅蓝表头；黄色为人工输入区；白色/灰色通常为公式、说明或系统数据。
A10: 推荐使用流程
A11: 1 | B11: 按沟通计划组织会议和报告
A12: 2 | B12: 记录会议纪要及决策
A13: 3 | B13: 将行动项分配到责任人和期限
A14: 4 | B14: 跟踪升级事项和相关方反馈
A15: 5 | B15: 通过沟通总览检查逾期和待决策项
A18: 工作表导航
A19: 顺序 | B19: 工作表 | C19: 用途
A20: 1 | B20: 沟通总览 | C20: 查看沟通、行动、决策和升级状态。
A21: 2 | B21: 沟通管理计划 | C21: 定义对象、内容、频率和渠道。
A22: 3 | B22: 会议计划 | C22: 安排例会、专题会和决策会。
A23: 4 | B23: 会议纪要 | C23: 记录议题、结论和后续事项。
A24: 5 | B24: 行动项台账 | C24: 跟踪责任人、期限和验证结果。
A25: 6 | B25: 决策日志 | C25: 记录关键决策及依据。
A26: 7 | B26: 报告台账 | C26: 管理周报、月报和专题报告。
A27: 8 | B27: 相关方沟通记录 | C27: 保留关键沟通历史。
A28: 9 | B28: 升级事项 | C28: 跟踪需要上级协调的问题。
A29: 10 | B29: _数据接口 | C29: 供Python脚本和AI PMO读取，人工一般不直接修改。
A31: 维护与检查规则
A32: 1 | B32: 先维护唯一编号、责任人、计划日期和状态，再补充说明与证据。
A33: 2 | B33: 状态变化时同步更新实际日期、完成比例、阻塞原因或验证结果。
A34: 3 | B34: 涉及基线、预算、范围、合同或上线门禁的变化，须先履行评审或审批。
A35: 4 | B35: 不要覆盖公式、汇总区、图表数据区和“_数据接口”中的系统字段。
A36: 5 | B36: 每周检查空责任人、逾期未完成、状态与日期矛盾、缺少证据和公式错误。
A37: 6 | B37: 文件升级后，将被替换版本移入本模块_archive目录，不在正式目录保留多个现行版本。

Sheet 沟通总览
A1: 沟通会议与报告总览
A2: 数据日期：2026-09-17。会议、决策、行动项和报告必须形成可追踪闭环。
A4: 沟通机制 | B4: 本周应开会议 | C4: 待办行动项 | D4: 逾期行动项 | E4: 待决策事项 | F4: 待升级事项
A5: =COUNTA(沟通管理计划!A5:A24) -> 8 | B5: =COUNTIF(会议计划!K5:K34,"未开始")+COUNTIF(会议计划!K5:K34,"已排期") -> 9 | C5: =COUNTIF(行动项台账!J5:J104,"未开始")+COUNTIF(行动项台账!J5:J104,"进行中")+COUNTIF(行动项台账!J5:J104,"阻塞") -> 0 | D5: =COUNTIF(行动项台账!L5:L104,"*逾期*") -> 0 | E5: =COUNTIF(决策日志!J5:J54,"待决策")+COUNTIF(决策日志!J5:J54,"评估中") -> 4 | F5: =COUNTIF(升级事项!I5:I54,"待升级")+COUNTIF(升级事项!I5:I54,"处理中") -> 0
A8: 近期沟通节点
A9: 节点 | B9: 频率/日期 | C9: 主持人 | D9: 核心参会人 | E9: 必须输出 | F9: 当前状态
A10: POC专项会 | B10: 每日站会/每周评审 | C10: 技术经理 | D10: 产品、技术、CA/电子文档/BI厂商 | E10: 问题清单、测试证据、选型结论 | F10: 进行中
A11: 科研成果收尾会 | B11: 2026-09-18 | C11: 项目集经理 | D11: 项目组、业务和技术负责人 | E11: 科研交付物、验收结论、遗留项 | F11: 已排期
A12: POC决策会 | B12: 2026-09-30 | C12: 项目集经理 | D12: 项目赞助人、业务、技术、采购 | E12: CA/电子文档/BI选型决策 | F12: 已排期
A13: 项目启动准备会 | B13: 2026-10-16 | C13: 项目集经理 | D13: 治理委员会、核心团队 | E13: 范围、预算、组织、基线批准 | F13: 已排期
A14: 项目启动会 | B14: 2026-10-20 | C14: 项目赞助人 | D14: 全体项目成员及关键相关方 | E14: 目标、范围、里程碑、角色和规则 | F14: 已排期
A15: 需求基线评审 | B15: 2026-11-30 | C15: 产品经理 | D15: 业务负责人、项目经理、技术经理 | E15: 需求基线、验收标准、待决策项 | F15: 未开始
A16: UAT每日协调会 | B16: 2027-04-16至2027-05-10 | C16: 项目经理 | D16: 业务关键用户、产品、测试、开发 | E16: 执行进展、缺陷、阻塞和验收证据 | F16: 未开始
A17: 上线准备会 | B17: 2027-05-11至2027-05-31 | C17: 项目集经理 | D17: 业务、技术、测试、配置、运维 | E17: 门禁、回退、数据、监控、支持结论 | F17: 未开始

Sheet 沟通管理计划
A1: 沟通管理计划
A2: 按相关方的权力、关注点和决策责任设计沟通，不用同一份报告覆盖所有人。
A4: 编号 | B4: 相关方/群体 | C4: 信息需求 | D4: 沟通目标 | E4: 方式/渠道 | F4: 频率 | G4: 主责人 | H4: 发送人 | I4: 输出/证据 | J4: 升级路径 | K4: 保密级别 | L4: 有效性验证 | M4: 状态
A5: CP-001 | B5: 项目赞助人/治理委员会 | C5: 业务价值、整体状态、重大风险、决策和资源 | D5: 及时获得重大决策和支持 | E5: 治理会/管理月报 | F5: 每月及重大事项触发 | G5: 项目集经理 | H5: 项目经理 | I5: 月报、决策记录、升级单 | J5: 赞助人→治理委员会 | K5: 内部 | L5: 决策在要求日期前完成 | M5: 有效
A6: CP-002 | B6: 业务负责人及关键用户 | C6: 范围、需求、原型、业务规则、验收和上线准备 | D6: 确保需求可用、可验收 | E6: 专题会/评审/UAT沟通群 | F6: 每周，UAT期间每日 | G6: 产品经理 | H6: 产品经理 | I6: 需求结论、原型确认、UAT证据 | J6: 业务负责人→赞助人 | K6: 内部 | L6: 减少重复返工和未决需求 | M6: 有效
A7: CP-003 | B7: 项目管理团队 | C7: 进度、资源、风险、问题、决策、变更 | D7: 保证项目基线与执行一致 | E7: PMO例会/周报 | F7: 每周 | G7: 项目集经理 | H7: 项目经理 | I7: 周报、控制项清单、行动项 | J7: 项目经理→项目集经理 | K7: 内部 | L7: 逾期行动和未决事项持续下降 | M7: 有效
A8: CP-004 | B8: 产品、设计、开发、测试团队 | C8: 迭代目标、任务、依赖、缺陷和验收标准 | D8: 保证交付协同和问题快速闭环 | E8: 项目例会/迭代计划/每日站会 | F8: 每周/每日 | G8: 项目经理 | H8: 各职能负责人 | I8: 迭代计划、障碍清单、评审结论 | J8: 职能负责人→项目经理 | K8: 内部 | L8: 迭代目标和承诺完成度 | M8: 有效
A9: CP-005 | B9: 技术架构及集成相关方 | C9: 架构决策、数据、接口、安全、性能、环境和发布 | D9: 控制跨系统依赖和技术风险 | E9: 架构/集成专题会、ADR | F9: 双周及重大变更时 | G9: 技术经理 | H9: 技术经理 | I9: 架构评审、接口结论、技术决策 | J9: 技术经理→项目集经理 | K9: 内部/敏感 | L9: 重大技术决策有证据可追溯 | M9: 有效
A10: CP-006 | B10: CA/电子文档/BI厂商 | C10: POC范围、测试数据、选型标准、交付物和时限 | D10: 完成POC证据和选型决策 | E10: POC日站会/周评审/书面澄清 | F10: POC期间每日/每周 | G10: 技术经理 | H10: 对接负责人 | I10: POC问题清单、测试证据、评分和结论 | J10: 技术经理→项目集经理→采购/治理委员会 | K10: 商密 | L10: 三类产品按时形成可审计结论 | M10: 进行中
A11: CP-007 | B11: 采购、财务、合同管理 | C11: 预算、采购、付款、变更和供应商履约 | D11: 确保商务与交付节奏一致 | E11: 成本专题会/采购评审/月报 | F11: 每月及采购节点前 | G11: 项目经理 | H11: 商务/采购负责人 | I11: 预算执行、采购状态、付款决策 | J11: 项目经理→赞助人 | K11: 商密 | L11: 不因商务审批延误关键节点 | M11: 有效
A12: CP-008 | B12: 运维、安全、档案及审计 | C12: 环境、账号、监控、备份、回退、审计证据和交接 | D12: 确保上线及运维可承接 | E12: 专题评审/上线准备会/交接会 | F12: 设计阶段月度，上线前每日 | G12: 项目经理 | H12: 配置/技术经理 | I12: 上线检查表、交接清单、演练证据 | J12: 职能负责人→项目集经理 | K12: 敏感 | L12: 上线门禁无未处置关键项 | M12: 有效

Sheet 会议计划
A1: 会议计划
A2: 会议应服务于决策、协同或验收，没有议题和必须输出的会议不建议召开。
A4: 会议ID | B4: 会议名称 | C4: 会议类型 | D4: 阶段 | E4: 频率 | F4: 计划日期/周期 | G4: 主持人 | H4: 必须参会人 | I4: 主要议题 | J4: 必须输出 | K4: 状态 | L4: 纪要ID
A5: MTG-001 | B5: 项目治理委员会 | C5: 治理 | D5: 全周期 | E5: 每月/触发 | F5: 每月最后一周 | G5: 项目赞助人 | H5: 治理委员会、项目集经理 | I5: 整体状态、重大风险、预算、重大决策 | J5: 决策和授权记录 | K5: 未开始 | L5: 3
A6: MTG-002 | B6: PMO周例会 | C6: 管理 | D6: 全周期 | E6: 每周 | F6: 每周一 | G6: 项目集经理 | H6: 项目经理、各职能负责人 | I6: 里程碑、资源、风险、问题、决策和变更 | J6: 周报、行动项、升级项 | K6: 已排期 | L6: 3
A7: MTG-003 | B7: 项目周例会 | C7: 执行 | D7: 全周期 | E7: 每周 | F7: 每周二 | G7: 项目经理 | H7: 产品、设计、技术、开发、测试、配置 | I7: 本周进展、下周计划、阻塞和依赖 | J7: 更新计划和行动项 | K7: 已排期 | L7: 3
A8: MTG-004 | B8: 需求专题会 | C8: 业务 | D8: 需求/设计 | E8: 每周2次 | F8: 周二、周四 | G8: 产品经理 | H8: 业务负责人、产品、技术、测试 | I8: 流程、规则、范围、原型、验收标准 | J8: 需求结论、待决策项 | K8: 未开始 | L8: 3
A9: MTG-005 | B9: 架构与集成评审 | C9: 技术 | D9: 设计/开发 | E9: 双周/触发 | F9: 双周周三 | G9: 技术经理 | H9: 架构、开发、测试、运维、外部系统对接人 | I9: 架构、数据、接口、安全、性能、发布 | J9: 评审结论、ADR、整改项 | K9: 未开始 | L9: 3
A10: MTG-006 | B10: POC日站会 | C10: POC | D10: 启动前 | E10: 每工作日 | F10: 2026-09-17至2026-09-30 | G10: 技术经理 | H10: 产品、技术、厂商对接人 | I10: 当日测试、问题、证据和阻塞 | J10: POC每日状态和问题清单 | K10: 进行中 | L10: 3
A11: MTG-007 | B11: 迭代计划/评审会 | C11: 迭代 | D11: 开发/测试 | E11: 每2周 | F11: 迭代首尾日 | G11: 项目经理 | H11: 产品、技术、开发、测试 | I11: 迭代目标、承诺、演示、验收和改进 | J11: 迭代计划、评审结论 | K11: 未开始 | L11: 3
A12: MTG-008 | B12: 缺陷分级会 | C12: 质量 | D12: 测试/UAT | E12: 每日 | F12: 系统测试和UAT期间 | G12: 测试负责人 | H12: 产品、开发、测试、项目经理 | I12: 缺陷优先级、修复计划、阻塞和回归 | J12: 缺陷分级和修复承诺 | K12: 未开始 | L12: 3
A13: MTG-009 | B13: UAT每日协调会 | C13: 验收 | D13: UAT | E13: 每日 | F13: 2027-04-16至2027-05-10 | G13: 项目经理 | H13: 关键用户、产品、测试、开发 | I13: 用例执行、缺陷、遗留风险和验收证据 | J13: UAT日报、缺陷和决策 | K13: 未开始 | L13: 3
A14: MTG-010 | B14: 上线准备会 | C14: 上线 | D14: 上线准备 | E14: 每日 | F14: 2027-05-11至2027-05-31 | G14: 项目集经理 | H14: 业务、技术、测试、配置、运维、安全 | I14: 门禁、数据、接口、权限、监控、回退和支持 | J14: 上线准备结论、升级项 | K14: 未开始 | L14: 3

Sheet 会议纪要
A1: 会议纪要
A2: 每次会议一行记录主要结论；详细附件保存在统一文档库，用链接关联。
A4: 纪要ID | B4: 会议ID | C4: 实际日期 | D4: 会议主题 | E4: 主持人 | F4: 记录人 | G4: 参会人 | H4: 议题 | I4: 主要结论 | J4: 决策ID | K4: 行动项ID | L4: 待确认事项 | M4: 附件/链接 | N4: 发布时间 | O4: 确认状态

Sheet 行动项台账
A1: 行动项台账
A2: 红色表示逾期、阻塞或需升级。完成必须有完成日期和证据。
A4: 行动项ID | B4: 来源类型 | C4: 来源ID | D4: 行动事项 | E4: 责任人 | F4: 协同人 | G4: 提出日期 | H4: 截止日期 | I4: 优先级 | J4: 状态 | K4: 完成日期 | L4: 时效判断 | M4: 完成证据 | N4: 升级事项ID
L5: =IF(A5="","",IF(J5="已完成",IF(K5="","待补证据",IF(K5<=H5,"按时完成","逾期完成")),IF(H5="","待定日期",IF(H5<_数据接口!$B$6,"逾期",IF(J5="阻塞","阻塞","进行中")))))
L6: =IF(A6="","",IF(J6="已完成",IF(K6="","待补证据",IF(K6<=H6,"按时完成","逾期完成")),IF(H6="","待定日期",IF(H6<_数据接口!$B$6,"逾期",IF(J6="阻塞","阻塞","进行中")))))
L7: =IF(A7="","",IF(J7="已完成",IF(K7="","待补证据",IF(K7<=H7,"按时完成","逾期完成")),IF(H7="","待定日期",IF(H7<_数据接口!$B$6,"逾期",IF(J7="阻塞","阻塞","进行中")))))
L8: =IF(A8="","",IF(J8="已完成",IF(K8="","待补证据",IF(K8<=H8,"按时完成","逾期完成")),IF(H8="","待定日期",IF(H8<_数据接口!$B$6,"逾期",IF(J8="阻塞","阻塞","进行中")))))
L9: =IF(A9="","",IF(J9="已完成",IF(K9="","待补证据",IF(K9<=H9,"按时完成","逾期完成")),IF(H9="","待定日期",IF(H9<_数据接口!$B$6,"逾期",IF(J9="阻塞","阻塞","进行中")))))
L10: =IF(A10="","",IF(J10="已完成",IF(K10="","待补证据",IF(K10<=H10,"按时完成","逾期完成")),IF(H10="","待定日期",IF(H10<_数据接口!$B$6,"逾期",IF(J10="阻塞","阻塞","进行中")))))
L11: =IF(A11="","",IF(J11="已完成",IF(K11="","待补证据",IF(K11<=H11,"按时完成","逾期完成")),IF(H11="","待定日期",IF(H11<_数据接口!$B$6,"逾期",IF(J11="阻塞","阻塞","进行中")))))
L12: =IF(A12="","",IF(J12="已完成",IF(K12="","待补证据",IF(K12<=H12,"按时完成","逾期完成")),IF(H12="","待定日期",IF(H12<_数据接口!$B$6,"逾期",IF(J12="阻塞","阻塞","进行中")))))
L13: =IF(A13="","",IF(J13="已完成",IF(K13="","待补证据",IF(K13<=H13,"按时完成","逾期完成")),IF(H13="","待定日期",IF(H13<_数据接口!$B$6,"逾期",IF(J13="阻塞","阻塞","进行中")))))
L14: =IF(A14="","",IF(J14="已完成",IF(K14="","待补证据",IF(K14<=H14,"按时完成","逾期完成")),IF(H14="","待定日期",IF(H14<_数据接口!$B$6,"逾期",IF(J14="阻塞","阻塞","进行中")))))
L15: =IF(A15="","",IF(J15="已完成",IF(K15="","待补证据",IF(K15<=H15,"按时完成","逾期完成")),IF(H15="","待定日期",IF(H15<_数据接口!$B$6,"逾期",IF(J15="阻塞","阻塞","进行中")))))
L16: =IF(A16="","",IF(J16="已完成",IF(K16="","待补证据",IF(K16<=H16,"按时完成","逾期完成")),IF(H16="","待定日期",IF(H16<_数据接口!$B$6,"逾期",IF(J16="阻塞","阻塞","进行中")))))
... L104: =IF(A104="","",IF(J104="已完成",IF(K104="","待补证据",IF(K104<=H104,"按时完成","逾期完成")),IF(H104="","待定日期",IF(H104<_数据接口!$B$6,"逾期",IF(J104="阻塞","阻塞","进行中")))))

Sheet 决策日志
A1: 决策日志
A2: 保留事实、选项、影响、建议、决策人和证据，避免口头决策不可追溯。
A4: 决策ID | B4: 决策主题 | C4: 类别 | D4: 提出日期 | E4: 决策截止日期 | F4: 背景/事实 | G4: 备选方案 | H4: 影响 | I4: 建议方案 | J4: 状态 | K4: 决策人 | L4: 决策日期 | M4: 决策结果 | N4: 证据/关联ID
A5: DEC-001 | B5: CA产品POC选型 | C5: 技术/采购 | D5: 46282 | E5: 46295 | F5: 需验证认证、签章、验签、时间戳和集成成本 | G5: 各候选厂商方案 | H5: 影响电子签署、合规、进度和采购 | I5: 依据POC证据及综合评分选型 | J5: 待决策 | K5: 项目治理委员会 | N5: POC评分表
A6: DEC-002 | B6: 电子文档产品POC选型 | C6: 技术/采购 | D6: 46282 | E6: 46295 | F6: 需验证模板、预览、转换、水印、大文件和归档 | G6: 各候选厂商方案 | H6: 影响文档生成、签署、归档和性能 | I6: 依据POC证据及综合评分选型 | J6: 待决策 | K6: 项目治理委员会 | N6: POC评分表
A7: DEC-003 | B7: BI报表产品POC选型 | C7: 技术/采购 | D7: 46282 | E7: 46295 | F7: 需验证数据接入、指标口径、权限、钻取、导出和性能 | G7: 各候选厂商方案 | H7: 影响经营分析、数据权限和交付成本 | I7: 依据POC证据及综合评分选型 | J7: 待决策 | K7: 项目治理委员会 | N7: POC评分表
A8: DEC-004 | B8: 项目基线与预算批准 | C8: 治理/成本 | D8: 46282 | E8: 46311 | F8: 项目2026-10-20启动，2027-05-31上线，计划投入30人 | G8: 基线方案及预算方案 | H8: 影响启动、资源到位、采购和交付范围 | I8: 按批准的里程碑、资源和成本基线启动 | J8: 待决策 | K8: 项目赞助人/治理委员会 | N8: 项目整体管理计划/成本与合同

Sheet 报告台账
A1: 报告台账
A2: 发布前确认数据日期、状态判断、证据、需决策项和版本。
A4: 报告ID | B4: 报告名称 | C4: 报告类型 | D4: 报告周期 | E4: 数据截止日 | F4: 编制人 | G4: 审核人 | H4: 发送对象 | I4: 核心内容 | J4: 状态判断 | K4: 需决策/支持 | L4: 发布日期 | M4: 版本/链接 | N4: 反馈及行动
A5: RPT-001 | B5: 项目周报 | C5: 定期 | D5: 每周 | F5: 项目经理 | G5: 项目集经理 | H5: 项目组、业务和相关负责人 | I5: 里程碑、进度、资源、风险、问题、决策和下周计划
A6: RPT-002 | B6: 管理月报 | C6: 定期 | D6: 每月 | F6: 项目集经理 | G6: 项目赞助人 | H6: 治理委员会 | I6: 价值、整体状态、里程碑、成本、质量、重大风险和决策
A7: RPT-003 | B7: 风险与问题专项报告 | C7: 专项 | D7: 双周/触发 | F7: 项目经理 | G7: 项目集经理 | H7: 治理委员会、风险责任人 | I7: 高风险、重大问题、趋势、应对和所需支持
A8: RPT-004 | B8: 质量与测试报告 | C8: 专项 | D8: 每迭代/测试期每周 | F8: 测试负责人 | G8: 项目经理 | H8: 项目组、业务负责人 | I8: 覆盖、执行、缺陷、回归、数据和门禁
A9: RPT-005 | B9: 成本、采购与供应商报告 | C9: 专项 | D9: 每月/采购节点前 | F9: 项目经理 | G9: 项目集经理 | H9: 赞助人、采购、财务 | I9: 预算执行、承诺、实际、预测、采购和供应商交付
A10: RPT-006 | B10: UAT日报/总结 | C10: 验收 | D10: 每日/完成时 | F10: 产品经理 | G10: 项目经理 | H10: 业务负责人、项目组 | I10: 场景执行、缺陷、遗留风险、证据和验收结论
A11: RPT-007 | B11: 上线准备报告 | C11: 上线 | D11: 每日/门禁前 | F11: 项目经理 | G11: 项目集经理 | H11: 治理委员会、业务、技术、运维 | I11: 数据、接口、权限、缺陷、回退、监控、培训和支持

Sheet 相关方沟通记录
A1: 相关方沟通记录
A2: 用于记录访谈、一对一、书面澄清等非正式会议沟通。
A4: 沟通ID | B4: 日期 | C4: 相关方 | D4: 单位/角色 | E4: 沟通方式 | F4: 沟通人 | G4: 主题 | H4: 诉求/关切 | I4: 沟通结论 | J4: 承诺/后续行动 | K4: 行动项ID | L4: 情绪/支持度变化 | M4: 备注

Sheet 升级事项
A1: 升级事项
A2: 当事项超出项目经理授权、超过时限或可能影响基线时使用。
A4: 升级ID | B4: 来源类型 | C4: 来源ID | D4: 事项 | E4: 影响 | F4: 已采取措施 | G4: 所需决策/支持 | H4: 决策截止日期 | I4: 状态 | J4: 升级人 | K4: 接收人/机构 | L4: 处理结论 | M4: 关闭日期 | N4: 关闭证据

Sheet _数据接口
A1: 字段 | B1: 值
A2: Project_ID | B2: ECM-2026
A3: 项目名称 | B3: 能源行业合同全生命周期管理系统
A4: 模块编码 | B4: 08
A5: 版本日期 | B5: 46283
A6: 数据日期 | B6: 46283
A7: 沟通机制数 | B7: 8
A8: 标准会议类型数 | B8: 10
A9: 待决策数 | B9: 4
A10: 本周报告类型数 | B10: 7
A11: 当前高优先级升级事项 | B11: 0
A12: 使用说明Sheet | B12: 已包含
A13: 使用说明版本 | B13: 20260918-V3
A14: 默认报告节奏 | B14: 周报+月报+专项
A15: 行动项逾期判断基准 | B15: 数据日期
A16: 中央数据库 | B16: ../90_项目数据中心/ai_pmo.db
A17: 上游模块 | B17: 01_启动与治理/02_计划与进度/06_风险问题与变更/07_质量测试与验收
A18: 下游模块 | B18: 11_AI-PMO中心
